Workbook
Name Estratégias: [1]Estratégias!$A$2:$A$5
Name Estratégias: [1]Estratégias!$A$2:$A$5
Name Estratégias: [1]Estratégias!$A$2:$A$5
Name Estratégias: [1]Estratégias!$A$2:$A$5
Name Estratégias: 'Estratégias (legenda)'!$A$2:$A$5
Name EstrategiasOport: [1]Estratégias!$D$2:$D$5
Name EstrategiasOport: [1]Estratégias!$D$2:$D$5
Name EstrategiasOport: [1]Estratégias!$D$2:$D$5
Name EstrategiasOport: [1]Estratégias!$D$2:$D$5
Name EstrategiasOport: 'Estratégias (legenda)'!$D$2:$D$5

Sheet Riscos-CANTU
E1: Matriz de Avaliação e Gestão de Riscos
E4: CANTU
B6: Item | C6: Riscos | E6: Avaliação de Impacto | W6: Avaliação do Controle (Probabilidade) | AS6: Significância | AU6: Estratégia
B7: Item | E7: Financeiro | F7: Pontos | G7: Inf. Média | H7: Legal | I7: Pontos | J7: Inf. Média | K7: Imagem | L7: Pontos | M7: Inf. Média | N7: Direcionamento Estratégico | O7: Pontos | P7: Inf. Média | Q7: Operação | R7: Pontos | S7: Inf. Média | W7: Características | AA7: Pontos | AC7: Tipo | AF7: Pontos | AH7: Histórico de Ocorrência | AN7: Pontos
U8: Impacto | W8: Controle-chave efetivo | X8: Controle Compensatório efetivo | Y8: Controle compensatório Não Efetivo | Z8: Controle Inexistente | AC8: Automatizado | AD8: Manual | AE8: Nenhum | AH8: Anual | AI8: Trimestral | AJ8: Mensal | AK8: Semanal | AL8: Diário | AM8: Mais de uma vez ao dia | AP8: Probabilidade | AQ8: Média | AX8: Desprezível | AY8: Administrável | AZ8: Indesejável | BA8: Intolerável
B10: 1. | C10: Comercial - Vacância | E10: Alto | F10: =IF(E10="N.A.",0)+IF(E10="Baixo",1)+IF(E10="Moderado",2)+IF(E10="Significativo",4)+IF(E10="Alto",6) -> 6 | G10: =IF(F10>0,1,0) -> 1 | H10: Baixo | I10: =IF(H10="N.A.",0)+IF(H10="Baixo",1)+IF(H10="Moderado",2)+IF(H10="Significativo",4)+IF(H10="Alto",6) -> 1 | J10: =IF(I10>0,1,0) -> 1 | K10: Baixo | L10: =IF(K10="N.A.",0)+IF(K10="Baixo",1)+IF(K10="Moderado",2)+IF(K10="Significativo",4)+IF(K10="Alto",6) -> 1 | M10: =IF(L10>0,1,0) -> 1 | N10: Significativo | O10: =IF(N10="N.A.",0)+IF(N10="Baixo",1)+IF(N10="Moderado",2)+IF(N10="Significativo",4)+IF(N10="Alto",6) -> 4 | P10: =IF(O10>0,1,0) -> 1 | Q10: Moderado | R10: =IF(Q10="N.A.",0)+IF(Q10="Baixo",1)+IF(Q10="Moderado",2)+IF(Q10="Significativo",4)+IF(Q10="Alto",6) -> 2 | S10: =IF(R10>0,1,0) -> 1 | T10: =SUM(G10,J10,M10,P10,S10) -> 5 | U10: =IFERROR(SUM(F10,I10,L10,O10,R10)/T10,0) -> 2.8 | Y10: X | AA10: =IF(W10="X",-1)+IF(X10="X",2)+IF(Y10="X",4)+IF(Z10="X",9) -> 4 | AD10: X | AF10: =IF(AC10="X",1)+IF(AD10="X",2)+IF(AE10="X",5) -> 2 | AJ10: X | AN10: =IF(AH10="X",1)+IF(AI10="X",2)+IF(AJ10="X",3)+IF(AK10="X",4)+IF(AL10="X",5)+IF(AM10="X",6) -> 3 | AP10: =AA10+AF10+AN10 -> 9 | AQ10: =(AP10+U10)/2 -> 5.9 | AR10: =IF(AS10="",0,10) -> 10 | AS10: =IF(AX10=TRUE,"Desprezível",IF(AY10=TRUE,"Administrável",IF(AZ10=TRUE,"Indesejável",IF(BA10=TRUE,"Intolerável","")))) -> Administrável | AU10: Mitigar | AW10: N.A. | AX10: =AND(U10>0,U10<=2,AP10>0,AP10<=7) -> FALSE | AY10: =OR(AND(U10>0,U10<=2,AP10>0,AP10>7,AP10<=13),AND(U10>0,U10>2,U10<=3,AP10>0,AP10<=10)) -> TRUE | AZ10: =OR(AND(U10>0,U10<=2,AP10>0,AP10>12,AP10<=17),AND(U10>0,U10>2,U10<=3,AP10>0,AP10>10,AP10<=13),AND(U10>0,U10>3,U10<=5,AP10>0,AP10<=10),AND(U10>0,U10>4,U10<=6,AP10>0,AP10<=7)) -> FALSE | BA10: =OR(AND(U10>0,U10>2,U10<=3,AP10>0,AP10>14,AP10<=20),AND(U10>0,U10>3,U10<=5,AP10>0,AP10>10),AND(U10>0,U10>5,U10<=6,AP10>0,AP10>7,AP10<=20)) -> FALSE | BC10: N.A.
I11: =IF(H11="N.A.",0)+IF(H11="Baixo",1)+IF(H11="Moderado",2)+IF(H11="Significativo",4)+IF(H11="Alto",6) -> 0 | J11: =IF(I11>0,1,0) -> 0 | L11: =IF(K11="N.A.",0)+IF(K11="Baixo",1)+IF(K11="Moderado",2)+IF(K11="Significativo",4)+IF(K11="Alto",6) -> 0 | R11: =IF(Q11="N.A.",0)+IF(Q11="Baixo",1)+IF(Q11="Moderado",2)+IF(Q11="Significativo",4)+IF(Q11="Alto",6) -> 0 | S11: =IF(R11>0,1,0) -> 0 | T11: =SUM(G11,J11,M11,P11,S11) -> 0 | U11: =IFERROR(SUM(F11,I11,L11,O11,R11)/T11,0) -> 0 | AF11: =IF(AC11="X",1)+IF(AD11="X",2)+IF(AE11="X",5) -> 0 | AW11: Baixo | AZ11: =OR(AND(U11>0,U11<=2,AP11>0,AP11>12,AP11<=17),AND(U11>0,U11>2,U11<=3,AP11>0,AP11>10,AP11<=13),AND(U11>0,U11>3,U11<=5,AP11>0,AP11<=10),AND(U11>0,U11>4,U11<=6,AP11>0,AP11<=7)) -> FALSE | BA11: =OR(AND(U11>0,U11>2,U11<=3,AP11>0,AP11>14,AP11<=20),AND(U11>0,U11>3,U11<=5,AP11>0,AP11>10),AND(U11>0,U11>5,U11<=6,AP11>0,AP11>7,AP11<=20)) -> FALSE | BC11: Baixo
B12: 2. | C12: Eventos de Sinistros em Imóveis | E12: Significativo | F12: =IF(E12="N.A.",0)+IF(E12="Baixo",1)+IF(E12="Moderado",2)+IF(E12="Significativo",4)+IF(E12="Alto",6) -> 4 | G12: =IF(F12>0,1,0) -> 1 | H12: Moderado | I12: =IF(H12="N.A.",0)+IF(H12="Baixo",1)+IF(H12="Moderado",2)+IF(H12="Significativo",4)+IF(H12="Alto",6) -> 2 | J12: =IF(I12>0,1,0) -> 1 | K12: Baixo | L12: =IF(K12="N.A.",0)+IF(K12="Baixo",1)+IF(K12="Moderado",2)+IF(K12="Significativo",4)+IF(K12="Alto",6) -> 1 | M12: =IF(L12>0,1,0) -> 1 | N12: Significativo | O12: =IF(N12="N.A.",0)+IF(N12="Baixo",1)+IF(N12="Moderado",2)+IF(N12="Significativo",4)+IF(N12="Alto",6) -> 4 | P12: =IF(O12>0,1,0) -> 1 | Q12: Significativo | R12: =IF(Q12="N.A.",0)+IF(Q12="Baixo",1)+IF(Q12="Moderado",2)+IF(Q12="Significativo",4)+IF(Q12="Alto",6) -> 4 | S12: =IF(R12>0,1,0) -> 1 | T12: =SUM(G12,J12,M12,P12,S12) -> 5 | U12: =IFERROR(SUM(F12,I12,L12,O12,R12)/T12,0) -> 3 | X12: X | AA12: =IF(W12="X",0)+IF(X12="X",2)+IF(Y12="X",4)+IF(Z12="X",9) -> 2 | AD12: X | AF12: =IF(AC12="X",1)+IF(AD12="X",2)+IF(AE12="X",5) -> 2 | AJ12: X | AN12: =IF(AH12="X",1)+IF(AI12="X",2)+IF(AJ12="X",3)+IF(AK12="X",4)+IF(AL12="X",5)+IF(AM12="X",6) -> 3 | AP12: =AA12+AF12+AN12 -> 7 | AQ12: =(AP12+U12)/2 -> 5 | AR12: =IF(AS12="",0,10) -> 10 | AS12: =IF(AX12=TRUE,"Desprezível",IF(AY12=TRUE,"Administrável",IF(AZ12=TRUE,"Indesejável",IF(BA12=TRUE,"Intolerável","")))) -> Administrável | AU12: Transferir | AW12: Alto | AX12: =AND(U12>0,U12<=2,AP12>0,AP12<=7) -> FALSE | AY12: =OR(AND(U12>0,U12<=2,AP12>0,AP12>7,AP12<=13),AND(U12>0,U12>2,U12<=3,AP12>0,AP12<=10)) -> TRUE | AZ12: =OR(AND(U12>0,U12<=2,AP12>0,AP12>12,AP12<=17),AND(U12>0,U12>2,U12<=3,AP12>0,AP12>10,AP12<=13),AND(U12>0,U12>3,U12<=5,AP12>0,AP12<=10),AND(U12>0,U12>4,U12<=6,AP12>0,AP12<=7)) -> FALSE | BA12: =OR(AND(U12>0,U12>2,U12<=3,AP12>0,AP12>14,AP12<=20),AND(U12>0,U12>3,U12<=5,AP12>0,AP12>10),AND(U12>0,U12>5,U12<=6,AP12>0,AP12>7,AP12<=20)) -> FALSE | BC12: Alto
F13: =IF(E13="N.A.",0)+IF(E13="Baixo",1)+IF(E13="Moderado",2)+IF(E13="Significativo",4)+IF(E13="Alto",6) -> 0 | G13: =IF(F13>0,1,0) -> 0 | I13: =IF(H13="N.A.",0)+IF(H13="Baixo",1)+IF(H13="Moderado",2)+IF(H13="Significativo",4)+IF(H13="Alto",6) -> 0 | J13: =IF(I13>0,1,0) -> 0 | L13: =IF(K13="N.A.",0)+IF(K13="Baixo",1)+IF(K13="Moderado",2)+IF(K13="Significativo",4)+IF(K13="Alto",6) -> 0 | M13: =IF(L13>0,1,0) -> 0 | O13: =IF(N13="N.A.",0)+IF(N13="Baixo",1)+IF(N13="Moderado",2)+IF(N13="Significativo",4)+IF(N13="Alto",6) -> 0 | P13: =IF(O13>0,1,0) -> 0 | R13: =IF(Q13="N.A.",0)+IF(Q13="Baixo",1)+IF(Q13="Moderado",2)+IF(Q13="Significativo",4)+IF(Q13="Alto",6) -> 0 | S13: =IF(R13>0,1,0) -> 0 | T13: =SUM(G13,J13,M13,P13,S13) -> 0 | U13: =IFERROR(SUM(F13,I13,L13,O13,R13)/T13,0) -> 0 | AA13: =IF(W13="X",0)+IF(X13="X",2)+IF(Y13="X",4)+IF(Z13="X",9) -> 0 | AF13: =IF(AC13="X",1)+IF(AD13="X",2)+IF(AE13="X",5) -> 0 | AZ13: =OR(AND(U13>0,U13<=2,AP13>0,AP13>12,AP13<=17),AND(U13>0,U13>2,U13<=3,AP13>0,AP13>10,AP13<=13),AND(U13>0,U13>3,U13<=5,AP13>0,AP13<=10),AND(U13>0,U13>4,U13<=6,AP13>0,AP13<=7)) -> FALSE | BA13: =OR(AND(U13>0,U13>2,U13<=3,AP13>0,AP13>14,AP13<=20),AND(U13>0,U13>3,U13<=5,AP13>0,AP13>10),AND(U13>0,U13>5,U13<=6,AP13>0,AP13>7,AP13<=20)) -> FALSE
B14: 3. | C14: Novos Negócios - Aquisição de Imóveis | E14: Alto | F14: =IF(E14="N.A.",0)+IF(E14="Baixo",1)+IF(E14="Moderado",2)+IF(E14="Significativo",4)+IF(E14="Alto",6) -> 6 | G14: =IF(F14>0,1,0) -> 1 | H14: Baixo | I14: =IF(H14="N.A.",0)+IF(H14="Baixo",1)+IF(H14="Moderado",2)+IF(H14="Significativo",4)+IF(H14="Alto",6) -> 1 | J14: =IF(I14>0,1,0) -> 1 | K14: Baixo | L14: =IF(K14="N.A.",0)+IF(K14="Baixo",1)+IF(K14="Moderado",2)+IF(K14="Significativo",4)+IF(K14="Alto",6) -> 1 | M14: =IF(L14>0,1,0) -> 1 | N14: Significativo | O14: =IF(N14="N.A.",0)+IF(N14="Baixo",1)+IF(N14="Moderado",2)+IF(N14="Significativo",4)+IF(N14="Alto",6) -> 4 | P14: =IF(O14>0,1,0) -> 1 | Q14: Moderado | R14: =IF(Q14="N.A.",0)+IF(Q14="Baixo",1)+IF(Q14="Moderado",2)+IF(Q14="Significativo",4)+IF(Q14="Alto",6) -> 2 | S14: =IF(R14>0,1,0) -> 1 | T14: =SUM(G14,J14,M14,P14,S14) -> 5 | U14: =IFERROR(SUM(F14,I14,L14,O14,R14)/T14,0) -> 2.8 | X14: X | AA14: =IF(W14="X",0)+IF(X14="X",2)+IF(Y14="X",4)+IF(Z14="X",9) -> 2 | AD14: X | AF14: =IF(AC14="X",1)+IF(AD14="X",2)+IF(AE14="X",5) -> 2 | AJ14: X | AN14: =IF(AH14="X",1)+IF(AI14="X",2)+IF(AJ14="X",3)+IF(AK14="X",4)+IF(AL14="X",5)+IF(AM14="X",6) -> 3 | AP14: =AA14+AF14+AN14 -> 7 | AQ14: =(AP14+U14)/2 -> 4.9 | AR14: =IF(AS14="",0,10) -> 10 | AS14: =IF(AX14=TRUE,"Desprezível",IF(AY14=TRUE,"Administrável",IF(AZ14=TRUE,"Indesejável",IF(BA14=TRUE,"Intolerável","")))) -> Administrável | AU14: Mitigar | AX14: =AND(U14>0,U14<=2,AP14>0,AP14<=7) -> FALSE | AY14: =OR(AND(U14>0,U14<=2,AP14>0,AP14>7,AP14<=13),AND(U14>0,U14>2,U14<=3,AP14>0,AP14<=10)) -> TRUE | AZ14: =OR(AND(U14>0,U14<=2,AP14>0,AP14>12,AP14<=17),AND(U14>0,U14>2,U14<=3,AP14>0,AP14>10,AP14<=13),AND(U14>0,U14>3,U14<=5,AP14>0,AP14<=10),AND(U14>0,U14>4,U14<=6,AP14>0,AP14<=7)) -> FALSE | BA14: =OR(AND(U14>0,U14>2,U14<=3,AP14>0,AP14>14,AP14<=20),AND(U14>0,U14>3,U14<=5,AP14>0,AP14>10),AND(U14>0,U14>5,U14<=6,AP14>0,AP14>7,AP14<=20)) -> FALSE
F15: =IF(E15="N.A.",0)+IF(E15="Baixo",1)+IF(E15="Moderado",2)+IF(E15="Significativo",4)+IF(E15="Alto",6) -> 0 | G15: =IF(F15>0,1,0) -> 0 | I15: =IF(H15="N.A.",0)+IF(H15="Baixo",1)+IF(H15="Moderado",2)+IF(H15="Significativo",4)+IF(H15="Alto",6) -> 0 | J15: =IF(I15>0,1,0) -> 0 | L15: =IF(K15="N.A.",0)+IF(K15="Baixo",1)+IF(K15="Moderado",2)+IF(K15="Significativo",4)+IF(K15="Alto",6) -> 0 | M15: =IF(L15>0,1,0) -> 0 | O15: =IF(N15="N.A.",0)+IF(N15="Baixo",1)+IF(N15="Moderado",2)+IF(N15="Significativo",4)+IF(N15="Alto",6) -> 0 | P15: =IF(O15>0,1,0) -> 0 | R15: =IF(Q15="N.A.",0)+IF(Q15="Baixo",1)+IF(Q15="Moderado",2)+IF(Q15="Significativo",4)+IF(Q15="Alto",6) -> 0 | S15: =IF(R15>0,1,0) -> 0 | T15: =SUM(G15,J15,M15,P15,S15) -> 0 | U15: =IFERROR(SUM(F15,I15,L15,O15,R15)/T15,0) -> 0 | AA15: =IF(W15="X",0)+IF(X15="X",2)+IF(Y15="X",4)+IF(Z15="X",9) -> 0 | AF15: =IF(AC15="X",1)+IF(AD15="X",2)+IF(AE15="X",5) -> 0 | AZ15: =OR(AND(U15>0,U15<=2,AP15>0,AP15>12,AP15<=17),AND(U15>0,U15>2,U15<=3,AP15>0,AP15>10,AP15<=13),AND(U15>0,U15>3,U15<=5,AP15>0,AP15<=10),AND(U15>0,U15>4,U15<=6,AP15>0,AP15<=7)) -> FALSE | BA15: =OR(AND(U15>0,U15>2,U15<=3,AP15>0,AP15>14,AP15<=20),AND(U15>0,U15>3,U15<=5,AP15>0,AP15>10),AND(U15>0,U15>5,U15<=6,AP15>0,AP15>7,AP15<=20)) -> FALSE
B16: 4. | C16: Novos Negócios - Definição do Produto | E16: Alto | F16: =IF(E16="N.A.",0)+IF(E16="Baixo",1)+IF(E16="Moderado",2)+IF(E16="Significativo",4)+IF(E16="Alto",6) -> 6 | G16: =IF(F16>0,1,0) -> 1 | H16: Baixo | I16: =IF(H16="N.A.",0)+IF(H16="Baixo",1)+IF(H16="Moderado",2)+IF(H16="Significativo",4)+IF(H16="Alto",6) -> 1 | J16: =IF(I16>0,1,0) -> 1 | K16: Baixo | L16: =IF(K16="N.A.",0)+IF(K16="Baixo",1)+IF(K16="Moderado",2)+IF(K16="Significativo",4)+IF(K16="Alto",6) -> 1 | M16: =IF(L16>0,1,0) -> 1 | N16: Significativo | O16: =IF(N16="N.A.",0)+IF(N16="Baixo",1)+IF(N16="Moderado",2)+IF(N16="Significativo",4)+IF(N16="Alto",6) -> 4 | P16: =IF(O16>0,1,0) -> 1 | Q16: Baixo | R16: =IF(Q16="N.A.",0)+IF(Q16="Baixo",1)+IF(Q16="Moderado",2)+IF(Q16="Significativo",4)+IF(Q16="Alto",6) -> 1 | S16: =IF(R16>0,1,0) -> 1 | T16: =SUM(G16,J16,M16,P16,S16) -> 5 | U16: =IFERROR(SUM(F16,I16,L16,O16,R16)/T16,0) -> 2.6 | X16: X | AA16: =IF(W16="X",0)+IF(X16="X",2)+IF(Y16="X",4)+IF(Z16="X",9) -> 2 | AD16: X | AF16: =IF(AC16="X",1)+IF(AD16="X",2)+IF(AE16="X",5) -> 2 | AJ16: X | AN16: =IF(AH16="X",1)+IF(AI16="X",2)+IF(AJ16="X",3)+IF(AK16="X",4)+IF(AL16="X",5)+IF(AM16="X",6) -> 3 | AP16: =AA16+AF16+AN16 -> 7 | AQ16: =(AP16+U16)/2 -> 4.8 | AR16: =IF(AS16="",0,10) -> 10 | AS16: =IF(AX16=TRUE,"Desprezível",IF(AY16=TRUE,"Administrável",IF(AZ16=TRUE,"Indesejável",IF(BA16=TRUE,"Intolerável","")))) -> Administrável | AU16: Mitigar | AW16: X | AX16: =AND(U16>0,U16<=2,AP16>0,AP16<=7) -> FALSE | AY16: =OR(AND(U16>0,U16<=2,AP16>0,AP16>7,AP16<=13),AND(U16>0,U16>2,U16<=3,AP16>0,AP16<=10)) -> TRUE | AZ16: =OR(AND(U16>0,U16<=2,AP16>0,AP16>12,AP16<=17),AND(U16>0,U16>2,U16<=3,AP16>0,AP16>10,AP16<=13),AND(U16>0,U16>3,U16<=5,AP16>0,AP16<=10),AND(U16>0,U16>4,U16<=6,AP16>0,AP16<=7)) -> FALSE | BA16: =OR(AND(U16>0,U16>2,U16<=3,AP16>0,AP16>14,AP16<=20),AND(U16>0,U16>3,U16<=5,AP16>0,AP16>10),AND(U16>0,U16>5,U16<=6,AP16>0,AP16>7,AP16<=20)) -> FALSE | BC16: X
F17: =IF(E17="N.A.",0)+IF(E17="Baixo",1)+IF(E17="Moderado",2)+IF(E17="Significativo",4)+IF(E17="Alto",6) -> 0 | G17: =IF(F17>0,1,0) -> 0 | I17: =IF(H17="N.A.",0)+IF(H17="Baixo",1)+IF(H17="Moderado",2)+IF(H17="Significativo",4)+IF(H17="Alto",6) -> 0 | J17: =IF(I17>0,1,0) -> 0 | L17: =IF(K17="N.A.",0)+IF(K17="Baixo",1)+IF(K17="Moderado",2)+IF(K17="Significativo",4)+IF(K17="Alto",6) -> 0 | M17: =IF(L17>0,1,0) -> 0 | O17: =IF(N17="N.A.",0)+IF(N17="Baixo",1)+IF(N17="Moderado",2)+IF(N17="Significativo",4)+IF(N17="Alto",6) -> 0 | P17: =IF(O17>0,1,0) -> 0 | R17: =IF(Q17="N.A.",0)+IF(Q17="Baixo",1)+IF(Q17="Moderado",2)+IF(Q17="Significativo",4)+IF(Q17="Alto",6) -> 0 | T17: =SUM(G17,J17,M17,P17,S17) -> 0 | U17: =IFERROR(SUM(F17,I17,L17,O17,R17)/T17,0) -> 0 | AA17: =IF(W17="X",0)+IF(X17="X",2)+IF(Y17="X",4)+IF(Z17="X",9) -> 0 | AF17: =IF(AC17="X",1)+IF(AD17="X",2)+IF(AE17="X",5) -> 0 | AZ17: =OR(AND(U17>0,U17<=2,AP17>0,AP17>12,AP17<=17),AND(U17>0,U17>2,U17<=3,AP17>0,AP17>10,AP17<=13),AND(U17>0,U17>3,U17<=5,AP17>0,AP17<=10),AND(U17>0,U17>4,U17<=6,AP17>0,AP17<=7)) -> FALSE | BA17: =OR(AND(U17>0,U17>2,U17<=3,AP17>0,AP17>14,AP17<=20),AND(U17>0,U17>3,U17<=5,AP17>0,AP17>10),AND(U17>0,U17>5,U17<=6,AP17>0,AP17>7,AP17<=20)) -> FALSE
B18: 5. | C18: Assistência Técnica - Conservação dos Imóveis | E18: Significativo | F18: =IF(E18="N.A.",0)+IF(E18="Baixo",1)+IF(E18="Moderado",2)+IF(E18="Significativo",4)+IF(E18="Alto",6) -> 4 | G18: =IF(F18>0,1,0) -> 1 | H18: Baixo | I18: =IF(H18="N.A.",0)+IF(H18="Baixo",1)+IF(H18="Moderado",2)+IF(H18="Significativo",4)+IF(H18="Alto",6) -> 1 | J18: =IF(I18>0,1,0) -> 1 | K18: Baixo | L18: =IF(K18="N.A.",0)+IF(K18="Baixo",1)+IF(K18="Moderado",2)+IF(K18="Significativo",4)+IF(K18="Alto",6) -> 1 | M18: =IF(L18>0,1,0) -> 1 | N18: Baixo | O18: =IF(N18="N.A.",0)+IF(N18="Baixo",1)+IF(N18="Moderado",2)+IF(N18="Significativo",4)+IF(N18="Alto",6) -> 1 | P18: =IF(O18>0,1,0) -> 1 | Q18: Significativo | R18: =IF(Q18="N.A.",0)+IF(Q18="Baixo",1)+IF(Q18="Moderado",2)+IF(Q18="Significativo",4)+IF(Q18="Alto",6) -> 4 | S18: =IF(R18>0,1,0) -> 1 | T18: =SUM(G18,J18,M18,P18,S18) -> 5 | U18: =IFERROR(SUM(F18,I18,L18,O18,R18)/T18,0) -> 2.2 | Y18: X | AA18: =IF(W18="X",0)+IF(X18="X",2)+IF(Y18="X",4)+IF(Z18="X",9) -> 4 | AD18: X | AF18: =IF(AC18="X",1)+IF(AD18="X",2)+IF(AE18="X",5) -> 2 | AJ18: X | AN18: =IF(AH18="X",1)+IF(AI18="X",2)+IF(AJ18="X",3)+IF(AK18="X",4)+IF(AL18="X",5)+IF(AM18="X",6) -> 3 | AP18: =AA18+AF18+AN18 -> 9 | AQ18: =(AP18+U18)/2 -> 5.6 | AR18: =IF(AS18="",0,10) -> 10 | AS18: =IF(AX18=TRUE,"Desprezível",IF(AY18=TRUE,"Administrável",IF(AZ18=TRUE,"Indesejável",IF(BA18=TRUE,"Intolerável","")))) -> Administrável | AU18: Prevenir | AX18: =AND(U18>0,U18<=2,AP18>0,AP18<=7) -> FALSE | AY18: =OR(AND(U18>0,U18<=2,AP18>0,AP18>7,AP18<=13),AND(U18>0,U18>2,U18<=3,AP18>0,AP18<=10)) -> TRUE | AZ18: =OR(AND(U18>0,U18<=2,AP18>0,AP18>12,AP18<=17),AND(U18>0,U18>2,U18<=3,AP18>0,AP18>10,AP18<=13),AND(U18>0,U18>3,U18<=5,AP18>0,AP18<=10),AND(U18>0,U18>4,U18<=6,AP18>0,AP18<=7)) -> FALSE | BA18: =OR(AND(U18>0,U18>2,U18<=3,AP18>0,AP18>14,AP18<=20),AND(U18>0,U18>3,U18<=5,AP18>0,AP18>10),AND(U18>0,U18>5,U18<=6,AP18>0,AP18>7,AP18<=20)) -> FALSE
F19: =IF(E19="N.A.",0)+IF(E19="Baixo",1)+IF(E19="Moderado",2)+IF(E19="Significativo",4)+IF(E19="Alto",6) -> 0 | G19: =IF(F19>0,1,0) -> 0 | I19: =IF(H19="N.A.",0)+IF(H19="Baixo",1)+IF(H19="Moderado",2)+IF(H19="Significativo",4)+IF(H19="Alto",6) -> 0 | J19: =IF(I19>0,1,0) -> 0 | L19: =IF(K19="N.A.",0)+IF(K19="Baixo",1)+IF(K19="Moderado",2)+IF(K19="Significativo",4)+IF(K19="Alto",6) -> 0 | M19: =IF(L19>0,1,0) -> 0 | O19: =IF(N19="N.A.",0)+IF(N19="Baixo",1)+IF(N19="Moderado",2)+IF(N19="Significativo",4)+IF(N19="Alto",6) -> 0 | P19: =IF(O19>0,1,0) -> 0 | R19: =IF(Q19="N.A.",0)+IF(Q19="Baixo",1)+IF(Q19="Moderado",2)+IF(Q19="Significativo",4)+IF(Q19="Alto",6) -> 0 | T19: =SUM(G19,J19,M19,P19,S19) -> 0 | U19: =IFERROR(SUM(F19,I19,L19,O19,R19)/T19,0) -> 0 | AA19: =IF(W19="X",0)+IF(X19="X",2)+IF(Y19="X",4)+IF(Z19="X",9) -> 0 | AF19: =IF(AC19="X",1)+IF(AD19="X",2)+IF(AE19="X",5) -> 0 | AZ19: =OR(AND(U19>0,U19<=2,AP19>0,AP19>12,AP19<=17),AND(U19>0,U19>2,U19<=3,AP19>0,AP19>10,AP19<=13),AND(U19>0,U19>3,U19<=5,AP19>0,AP19<=10),AND(U19>0,U19>4,U19<=6,AP19>0,AP19<=7)) -> FALSE | BA19: =OR(AND(U19>0,U19>2,U19<=3,AP19>0,AP19>14,AP19<=20),AND(U19>0,U19>3,U19<=5,AP19>0,AP19>10),AND(U19>0,U19>5,U19<=6,AP19>0,AP19>7,AP19<=20)) -> FALSE
B20: 6. | C20: Administrativo - Inadimplência | E20: Significativo | F20: =IF(E20="N.A.",0)+IF(E20="Baixo",1)+IF(E20="Moderado",2)+IF(E20="Significativo",4)+IF(E20="Alto",6) -> 4 | G20: =IF(F20>0,1,0) -> 1 | H20: Baixo | I20: =IF(H20="N.A.",0)+IF(H20="Baixo",1)+IF(H20="Moderado",2)+IF(H20="Significativo",4)+IF(H20="Alto",6) -> 1 | J20: =IF(I20>0,1,0) -> 1 | K20: Baixo | L20: =IF(K20="N.A.",0)+IF(K20="Baixo",1)+IF(K20="Moderado",2)+IF(K20="Significativo",4)+IF(K20="Alto",6) -> 1 | M20: =IF(L20>0,1,0) -> 1 | N20: Significativo | O20: =IF(N20="N.A.",0)+IF(N20="Baixo",1)+IF(N20="Moderado",2)+IF(N20="Significativo",4)+IF(N20="Alto",6) -> 4 | P20: =IF(O20>0,1,0) -> 1 | Q20: Baixo | R20: =IF(Q20="N.A.",0)+IF(Q20="Baixo",1)+IF(Q20="Moderado",2)+IF(Q20="Significativo",4)+IF(Q20="Alto",6) -> 1 | S20: =IF(R20>0,1,0) -> 1 | T20: =SUM(G20,J20,M20,P20,S20) -> 5 | U20: =IFERROR(SUM(F20,I20,L20,O20,R20)/T20,0) -> 2.2 | Y20: X | AA20: =IF(W20="X",0)+IF(X20="X",2)+IF(Y20="X",4)+IF(Z20="X",9) -> 4 | AC20: X | AF20: =IF(AC20="X",1)+IF(AD20="X",2)+IF(AE20="X",5) -> 1 | AJ20: X | AN20: =IF(AH20="X",1)+IF(AI20="X",2)+IF(AJ20="X",3)+IF(AK20="X",4)+IF(AL20="X",5)+IF(AM20="X",6) -> 3 | AP20: =AA20+AF20+AN20 -> 8 | AQ20: =(AP20+U20)/2 -> 5.1 | AR20: =IF(AS20="",0,10) -> 10 | AS20: =IF(AX20=TRUE,"Desprezível",IF(AY20=TRUE,"Administrável",IF(AZ20=TRUE,"Indesejável",IF(BA20=TRUE,"Intolerável","")))) -> Administrável | AU20: Mitigar | AX20: =AND(U20>0,U20<=2,AP20>0,AP20<=7) -> FALSE | AY20: =OR(AND(U20>0,U20<=2,AP20>0,AP20>7,AP20<=13),AND(U20>0,U20>2,U20<=3,AP20>0,AP20<=10)) -> TRUE | AZ20: =OR(AND(U20>0,U20<=2,AP20>0,AP20>12,AP20<=17),AND(U20>0,U20>2,U20<=3,AP20>0,AP20>10,AP20<=13),AND(U20>0,U20>3,U20<=5,AP20>0,AP20<=10),AND(U20>0,U20>4,U20<=6,AP20>0,AP20<=7)) -> FALSE | BA20: =OR(AND(U20>0,U20>2,U20<=3,AP20>0,AP20>14,AP20<=20),AND(U20>0,U20>3,U20<=5,AP20>0,AP20>10),AND(U20>0,U20>5,U20<=6,AP20>0,AP20>7,AP20<=20)) -> FALSE
F21: =IF(E21="N.A.",0)+IF(E21="Baixo",1)+IF(E21="Moderado",2)+IF(E21="Significativo",4)+IF(E21="Alto",6) -> 0 | G21: =IF(F21>0,1,0) -> 0 | I21: =IF(H21="N.A.",0)+IF(H21="Baixo",1)+IF(H21="Moderado",2)+IF(H21="Significativo",4)+IF(H21="Alto",6) -> 0 | J21: =IF(I21>0,1,0) -> 0 | L21: =IF(K21="N.A.",0)+IF(K21="Baixo",1)+IF(K21="Moderado",2)+IF(K21="Significativo",4)+IF(K21="Alto",6) -> 0 | M21: =IF(L21>0,1,0) -> 0 | O21: =IF(N21="N.A.",0)+IF(N21="Baixo",1)+IF(N21="Moderado",2)+IF(N21="Significativo",4)+IF(N21="Alto",6) -> 0 | P21: =IF(O21>0,1,0) -> 0 | R21: =IF(Q21="N.A.",0)+IF(Q21="Baixo",1)+IF(Q21="Moderado",2)+IF(Q21="Significativo",4)+IF(Q21="Alto",6) -> 0 | T21: =SUM(G21,J21,M21,P21,S21) -> 0 | U21: =IFERROR(SUM(F21,I21,L21,O21,R21)/T21,0) -> 0 | AA21: =IF(W21="X",0)+IF(X21="X",2)+IF(Y21="X",4)+IF(Z21="X",9) -> 0 | AF21: =IF(AC21="X",1)+IF(AD21="X",2)+IF(AE21="X",5) -> 0 | AZ21: =OR(AND(U21>0,U21<=2,AP21>0,AP21>12,AP21<=17),AND(U21>0,U21>2,U21<=3,AP21>0,AP21>10,AP21<=13),AND(U21>0,U21>3,U21<=5,AP21>0,AP21<=10),AND(U21>0,U21>4,U21<=6,AP21>0,AP21<=7)) -> FALSE | BA21: =OR(AND(U21>0,U21>2,U21<=3,AP21>0,AP21>14,AP21<=20),AND(U21>0,U21>3,U21<=5,AP21>0,AP21>10),AND(U21>0,U21>5,U21<=6,AP21>0,AP21>7,AP21<=20)) -> FALSE
B22: 7. | C22: Redução de faturamento em decorrência de Pandemias "Covid-19" | E22: Alto | F22: =IF(E22="N.A.",0)+IF(E22="Baixo",1)+IF(E22="Moderado",2)+IF(E22="Significativo",4)+IF(E22="Alto",6) -> 6 | G22: =IF(F22>0,1,0) -> 1 | H22: Baixo | I22: =IF(H22="N.A.",0)+IF(H22="Baixo",1)+IF(H22="Moderado",2)+IF(H22="Significativo",4)+IF(H22="Alto",6) -> 1 | J22: =IF(I22>0,1,0) -> 1 | K22: Baixo | L22: =IF(K22="N.A.",0)+IF(K22="Baixo",1)+IF(K22="Moderado",2)+IF(K22="Significativo",4)+IF(K22="Alto",6) -> 1 | M22: =IF(L22>0,1,0) -> 1 | N22: Significativo | O22: =IF(N22="N.A.",0)+IF(N22="Baixo",1)+IF(N22="Moderado",2)+IF(N22="Significativo",4)+IF(N22="Alto",6) -> 4 | P22: =IF(O22>0,1,0) -> 1 | Q22: Baixo | R22: =IF(Q22="N.A.",0)+IF(Q22="Baixo",1)+IF(Q22="Moderado",2)+IF(Q22="Significativo",4)+IF(Q22="Alto",6) -> 1 | S22: =IF(R22>0,1,0) -> 1 | T22: =SUM(G22,J22,M22,P22,S22) -> 5 | U22: =IFERROR(SUM(F22,I22,L22,O22,R22)/T22,0) -> 2.6 | Y22: X | AA22: =IF(W22="X",0)+IF(X22="X",2)+IF(Y22="X",4)+IF(Z22="X",9) -> 4 | AD22: X | AF22: =IF(AC22="X",1)+IF(AD22="X",2)+IF(AE22="X",5) -> 2 | AJ22: X | AN22: =IF(AH22="X",1)+IF(AI22="X",2)+IF(AJ22="X",3)+IF(AK22="X",4)+IF(AL22="X",5)+IF(AM22="X",6) -> 3 | AP22: =AA22+AF22+AN22 -> 9 | AQ22: =(AP22+U22)/2 -> 5.8 | AR22: =IF(AS22="",0,10) -> 10 | AS22: =IF(AX22=TRUE,"Desprezível",IF(AY22=TRUE,"Administrável",IF(AZ22=TRUE,"Indesejável",IF(BA22=TRUE,"Intolerável","")))) -> Administrável | AU22: Mitigar | AX22: =AND(U22>0,U22<=2,AP22>0,AP22<=7) -> FALSE | AY22: =OR(AND(U22>0,U22<=2,AP22>0,AP22>7,AP22<=13),AND(U22>0,U22>2,U22<=3,AP22>0,AP22<=10)) -> TRUE | AZ22: =OR(AND(U22>0,U22<=2,AP22>0,AP22>12,AP22<=17),AND(U22>0,U22>2,U22<=3,AP22>0,AP22>10,AP22<=13),AND(U22>0,U22>3,U22<=5,AP22>0,AP22<=10),AND(U22>0,U22>4,U22<=6,AP22>0,AP22<=7)) -> FALSE | BA22: =OR(AND(U22>0,U22>2,U22<=3,AP22>0,AP22>14,AP22<=20),AND(U22>0,U22>3,U22<=5,AP22>0,AP22>10),AND(U22>0,U22>5,U22<=6,AP22>0,AP22>7,AP22<=20)) -> FALSE
F23: =IF(E23="N.A.",0)+IF(E23="Baixo",1)+IF(E23="Moderado",2)+IF(E23="Significativo",4)+IF(E23="Alto",6) -> 0 | G23: =IF(F23>0,1,0) -> 0 | I23: =IF(H23="N.A.",0)+IF(H23="Baixo",1)+IF(H23="Moderado",2)+IF(H23="Significativo",4)+IF(H23="Alto",6) -> 0 | J23: =IF(I23>0,1,0) -> 0 | L23: =IF(K23="N.A.",0)+IF(K23="Baixo",1)+IF(K23="Moderado",2)+IF(K23="Significativo",4)+IF(K23="Alto",6) -> 0 | M23: =IF(L23>0,1,0) -> 0 | O23: =IF(N23="N.A.",0)+IF(N23="Baixo",1)+IF(N23="Moderado",2)+IF(N23="Significativo",4)+IF(N23="Alto",6) -> 0 | P23: =IF(O23>0,1,0) -> 0 | R23: =IF(Q23="N.A.",0)+IF(Q23="Baixo",1)+IF(Q23="Moderado",2)+IF(Q23="Significativo",4)+IF(Q23="Alto",6) -> 0 | T23: =SUM(G23,J23,M23,P23,S23) -> 0 | U23: =IFERROR(SUM(F23,I23,L23,O23,R23)/T23,0) -> 0 | AA23: =IF(W23="X",0)+IF(X23="X",2)+IF(Y23="X",4)+IF(Z23="X",9) -> 0 | AF23: =IF(AC23="X",1)+IF(AD23="X",2)+IF(AE23="X",5) -> 0 | AZ23: =OR(AND(U23>0,U23<=2,AP23>0,AP23>12,AP23<=17),AND(U23>0,U23>2,U23<=3,AP23>0,AP23>10,AP23<=13),AND(U23>0,U23>3,U23<=5,AP23>0,AP23<=10),AND(U23>0,U23>4,U23<=6,AP23>0,AP23<=7)) -> FALSE | BA23: =OR(AND(U23>0,U23>2,U23<=3,AP23>0,AP23>14,AP23<=20),AND(U23>0,U23>3,U23<=5,AP23>0,AP23>10),AND(U23>0,U23>5,U23<=6,AP23>0,AP23>7,AP23<=20)) -> FALSE
B24: 8. | F24: =IF(E24="N.A.",0)+IF(E24="Baixo",1)+IF(E24="Moderado",2)+IF(E24="Significativo",4)+IF(E24="Alto",6) -> 0 | G24: =IF(F24>0,1,0) -> 0 | I24: =IF(H24="N.A.",0)+IF(H24="Baixo",1)+IF(H24="Moderado",2)+IF(H24="Significativo",4)+IF(H24="Alto",6) -> 0 | J24: =IF(I24>0,1,0) -> 0 | L24: =IF(K24="N.A.",0)+IF(K24="Baixo",1)+IF(K24="Moderado",2)+IF(K24="Significativo",4)+IF(K24="Alto",6) -> 0 | M24: =IF(L24>0,1,0) -> 0 | O24: =IF(N24="N.A.",0)+IF(N24="Baixo",1)+IF(N24="Moderado",2)+IF(N24="Significativo",4)+IF(N24="Alto",6) -> 0 | P24: =IF(O24>0,1,0) -> 0 | R24: =IF(Q24="N.A.",0)+IF(Q24="Baixo",1)+IF(Q24="Moderado",2)+IF(Q24="Significativo",4)+IF(Q24="Alto",6) -> 0 | S24: =IF(R24>0,1,0) -> 0 | T24: =SUM(G24,J24,M24,P24,S24) -> 0 | U24: =IFERROR(SUM(F24,I24,L24,O24,R24)/T24,0) -> 0 | AA24: =IF(W24="X",0)+IF(X24="X",2)+IF(Y24="X",4)+IF(Z24="X",9) -> 0 | AF24: =IF(AC24="X",1)+IF(AD24="X",2)+IF(AE24="X",5) -> 0 | AN24: =IF(AH24="X",1)+IF(AI24="X",2)+IF(AJ24="X",3)+IF(AK24="X",4)+IF(AL24="X",5)+IF(AM24="X",6) -> 0 | AP24: =AA24+AF24+AN24 -> 0 | AQ24: =(AP24+U24)/2 -> 0 | AR24: =IF(AS24="",0,10) -> 0 | AS24: =IF(AX24=TRUE,"Desprezível",IF(AY24=TRUE,"Administrável",IF(AZ24=TRUE,"Indesejável",IF(BA24=TRUE,"Intolerável","")))) | AX24: =AND(U24>0,U24<=2,AP24>0,AP24<=7) -> FALSE | AY24: =OR(AND(U24>0,U24<=2,AP24>0,AP24>7,AP24<=13),AND(U24>0,U24>2,U24<=3,AP24>0,AP24<=10)) -> FALSE | AZ24: =OR(AND(U24>0,U24<=2,AP24>0,AP24>12,AP24<=17),AND(U24>0,U24>2,U24<=3,AP24>0,AP24>10,AP24<=13),AND(U24>0,U24>3,U24<=5,AP24>0,AP24<=10),AND(U24>0,U24>4,U24<=6,AP24>0,AP24<=7)) -> FALSE | BA24: =OR(AND(U24>0,U24>2,U24<=3,AP24>0,AP24>14,AP24<=20),AND(U24>0,U24>3,U24<=5,AP24>0,AP24>10),AND(U24>0,U24>5,U24<=6,AP24>0,AP24>7,AP24<=20)) -> FALSE
F25: =IF(E25="N.A.",0)+IF(E25="Baixo",1)+IF(E25="Moderado",2)+IF(E25="Significativo",4)+IF(E25="Alto",6) -> 0 | G25: =IF(F25>0,1,0) -> 0 | I25: =IF(H25="N.A.",0)+IF(H25="Baixo",1)+IF(H25="Moderado",2)+IF(H25="Significativo",4)+IF(H25="Alto",6) -> 0 | J25: =IF(I25>0,1,0) -> 0 | L25: =IF(K25="N.A.",0)+IF(K25="Baixo",1)+IF(K25="Moderado",2)+IF(K25="Significativo",4)+IF(K25="Alto",6) -> 0 | M25: =IF(L25>0,1,0) -> 0 | O25: =IF(N25="N.A.",0)+IF(N25="Baixo",1)+IF(N25="Moderado",2)+IF(N25="Significativo",4)+IF(N25="Alto",6) -> 0 | P25: =IF(O25>0,1,0) -> 0 | R25: =IF(Q25="N.A.",0)+IF(Q25="Baixo",1)+IF(Q25="Moderado",2)+IF(Q25="Significativo",4)+IF(Q25="Alto",6) -> 0 | T25: =SUM(G25,J25,M25,P25,S25) -> 0 | U25: =IFERROR(SUM(F25,I25,L25,O25,R25)/T25,0) -> 0 | AA25: =IF(W25="X",0)+IF(X25="X",2)+IF(Y25="X",4)+IF(Z25="X",9) -> 0 | AF25: =IF(AC25="X",1)+IF(AD25="X",2)+IF(AE25="X",5) -> 0 | AZ25: =OR(AND(U25>0,U25<=2,AP25>0,AP25>12,AP25<=17),AND(U25>0,U25>2,U25<=3,AP25>0,AP25>10,AP25<=13),AND(U25>0,U25>3,U25<=5,AP25>0,AP25<=10),AND(U25>0,U25>4,U25<=6,AP25>0,AP25<=7)) -> FALSE | BA25: =OR(AND(U25>0,U25>2,U25<=3,AP25>0,AP25>14,AP25<=20),AND(U25>0,U25>3,U25<=5,AP25>0,AP25>10),AND(U25>0,U25>5,U25<=6,AP25>0,AP25>7,AP25<=20)) -> FALSE
B26: 9. | F26: =IF(E26="N.A.",0)+IF(E26="Baixo",1)+IF(E26="Moderado",2)+IF(E26="Significativo",4)+IF(E26="Alto",6) -> 0 | G26: =IF(F26>0,1,0) -> 0 | I26: =IF(H26="N.A.",0)+IF(H26="Baixo",1)+IF(H26="Moderado",2)+IF(H26="Significativo",4)+IF(H26="Alto",6) -> 0 | J26: =IF(I26>0,1,0) -> 0 | L26: =IF(K26="N.A.",0)+IF(K26="Baixo",1)+IF(K26="Moderado",2)+IF(K26="Significativo",4)+IF(K26="Alto",6) -> 0 | M26: =IF(L26>0,1,0) -> 0 | O26: =IF(N26="N.A.",0)+IF(N26="Baixo",1)+IF(N26="Moderado",2)+IF(N26="Significativo",4)+IF(N26="Alto",6) -> 0 | P26: =IF(O26>0,1,0) -> 0 | R26: =IF(Q26="N.A.",0)+IF(Q26="Baixo",1)+IF(Q26="Moderado",2)+IF(Q26="Significativo",4)+IF(Q26="Alto",6) -> 0 | S26: =IF(R26>0,1,0) -> 0 | T26: =SUM(G26,J26,M26,P26,S26) -> 0 | U26: =IFERROR(SUM(F26,I26,L26,O26,R26)/T26,0) -> 0 | AA26: =IF(W26="X",0)+IF(X26="X",2)+IF(Y26="X",4)+IF(Z26="X",9) -> 0 | AF26: =IF(AC26="X",1)+IF(AD26="X",2)+IF(AE26="X",5) -> 0 | AN26: =IF(AH26="X",1)+IF(AI26="X",2)+IF(AJ26="X",3)+IF(AK26="X",4)+IF(AL26="X",5)+IF(AM26="X",6) -> 0 | AP26: =AA26+AF26+AN26 -> 0 | AQ26: =(AP26+U26)/2 -> 0 | AR26: =IF(AS26="",0,10) -> 0 | AS26: =IF(AX26=TRUE,"Desprezível",IF(AY26=TRUE,"Administrável",IF(AZ26=TRUE,"Indesejável",IF(BA26=TRUE,"Intolerável","")))) | AX26: =AND(U26>0,U26<=2,AP26>0,AP26<=7) -> FALSE | AY26: =OR(AND(U26>0,U26<=2,AP26>0,AP26>7,AP26<=13),AND(U26>0,U26>2,U26<=3,AP26>0,AP26<=10)) -> FALSE | AZ26: =OR(AND(U26>0,U26<=2,AP26>0,AP26>12,AP26<=17),AND(U26>0,U26>2,U26<=3,AP26>0,AP26>10,AP26<=13),AND(U26>0,U26>3,U26<=5,AP26>0,AP26<=10),AND(U26>0,U26>4,U26<=6,AP26>0,AP26<=7)) -> FALSE | BA26: =OR(AND(U26>0,U26>2,U26<=3,AP26>0,AP26>14,AP26<=20),AND(U26>0,U26>3,U26<=5,AP26>0,AP26>10),AND(U26>0,U26>5,U26<=6,AP26>0,AP26>7,AP26<=20)) -> FALSE
F27: =IF(E27="N.A.",0)+IF(E27="Baixo",1)+IF(E27="Moderado",2)+IF(E27="Significativo",4)+IF(E27="Alto",6) -> 0 | G27: =IF(F27>0,1,0) -> 0 | I27: =IF(H27="N.A.",0)+IF(H27="Baixo",1)+IF(H27="Moderado",2)+IF(H27="Significativo",4)+IF(H27="Alto",6) -> 0 | J27: =IF(I27>0,1,0) -> 0 | L27: =IF(K27="N.A.",0)+IF(K27="Baixo",1)+IF(K27="Moderado",2)+IF(K27="Significativo",4)+IF(K27="Alto",6) -> 0 | M27: =IF(L27>0,1,0) -> 0 | O27: =IF(N27="N.A.",0)+IF(N27="Baixo",1)+IF(N27="Moderado",2)+IF(N27="Significativo",4)+IF(N27="Alto",6) -> 0 | P27: =IF(O27>0,1,0) -> 0 | R27: =IF(Q27="N.A.",0)+IF(Q27="Baixo",1)+IF(Q27="Moderado",2)+IF(Q27="Significativo",4)+IF(Q27="Alto",6) -> 0 | T27: =SUM(G27,J27,M27,P27,S27) -> 0 | U27: =IFERROR(SUM(F27,I27,L27,O27,R27)/T27,0) -> 0 | AA27: =IF(W27="X",0)+IF(X27="X",2)+IF(Y27="X",4)+IF(Z27="X",9) -> 0 | AF27: =IF(AC27="X",1)+IF(AD27="X",2)+IF(AE27="X",5) -> 0 | AZ27: =OR(AND(U27>0,U27<=2,AP27>0,AP27>12,AP27<=17),AND(U27>0,U27>2,U27<=3,AP27>0,AP27>10,AP27<=13),AND(U27>0,U27>3,U27<=5,AP27>0,AP27<=10),AND(U27>0,U27>4,U27<=6,AP27>0,AP27<=7)) -> FALSE | BA27: =OR(AND(U27>0,U27>2,U27<=3,AP27>0,AP27>14,AP27<=20),AND(U27>0,U27>3,U27<=5,AP27>0,AP27>10),AND(U27>0,U27>5,U27<=6,AP27>0,AP27>7,AP27<=20)) -> FALSE
B28: 10. | F28: =IF(E28="N.A.",0)+IF(E28="Baixo",1)+IF(E28="Moderado",2)+IF(E28="Significativo",4)+IF(E28="Alto",6) -> 0 | G28: =IF(F28>0,1,0) -> 0 | I28: =IF(H28="N.A.",0)+IF(H28="Baixo",1)+IF(H28="Moderado",2)+IF(H28="Significativo",4)+IF(H28="Alto",6) -> 0 | J28: =IF(I28>0,1,0) -> 0 | L28: =IF(K28="N.A.",0)+IF(K28="Baixo",1)+IF(K28="Moderado",2)+IF(K28="Significativo",4)+IF(K28="Alto",6) -> 0 | M28: =IF(L28>0,1,0) -> 0 | O28: =IF(N28="N.A.",0)+IF(N28="Baixo",1)+IF(N28="Moderado",2)+IF(N28="Significativo",4)+IF(N28="Alto",6) -> 0 | P28: =IF(O28>0,1,0) -> 0 | R28: =IF(Q28="N.A.",0)+IF(Q28="Baixo",1)+IF(Q28="Moderado",2)+IF(Q28="Significativo",4)+IF(Q28="Alto",6) -> 0 | S28: =IF(R28>0,1,0) -> 0 | T28: =SUM(G28,J28,M28,P28,S28) -> 0 | U28: =IFERROR(SUM(F28,I28,L28,O28,R28)/T28,0) -> 0 | AA28: =IF(W28="X",0)+IF(X28="X",2)+IF(Y28="X",4)+IF(Z28="X",9) -> 0 | AF28: =IF(AC28="X",1)+IF(AD28="X",2)+IF(AE28="X",5) -> 0 | AN28: =IF(AH28="X",1)+IF(AI28="X",2)+IF(AJ28="X",3)+IF(AK28="X",4)+IF(AL28="X",5)+IF(AM28="X",6) -> 0 | AP28: =AA28+AF28+AN28 -> 0 | AQ28: =(AP28+U28)/2 -> 0 | AR28: =IF(AS28="",0,10) -> 0 | AS28: =IF(AX28=TRUE,"Desprezível",IF(AY28=TRUE,"Administrável",IF(AZ28=TRUE,"Indesejável",IF(BA28=TRUE,"Intolerável","")))) | AX28: =AND(U28>0,U28<=2,AP28>0,AP28<=7) -> FALSE | AY28: =OR(AND(U28>0,U28<=2,AP28>0,AP28>7,AP28<=13),AND(U28>0,U28>2,U28<=3,AP28>0,AP28<=10)) -> FALSE | AZ28: =OR(AND(U28>0,U28<=2,AP28>0,AP28>12,AP28<=17),AND(U28>0,U28>2,U28<=3,AP28>0,AP28>10,AP28<=13),AND(U28>0,U28>3,U28<=5,AP28>0,AP28<=10),AND(U28>0,U28>4,U28<=6,AP28>0,AP28<=7)) -> FALSE | BA28: =OR(AND(U28>0,U28>2,U28<=3,AP28>0,AP28>14,AP28<=20),AND(U28>0,U28>3,U28<=5,AP28>0,AP28>10),AND(U28>0,U28>5,U28<=6,AP28>0,AP28>7,AP28<=20)) -> FALSE
F29: =IF(E29="N.A.",0)+IF(E29="Baixo",1)+IF(E29="Moderado",2)+IF(E29="Significativo",4)+IF(E29="Alto",6) -> 0 | G29: =IF(F29>0,1,0) -> 0 | I29: =IF(H29="N.A.",0)+IF(H29="Baixo",1)+IF(H29="Moderado",2)+IF(H29="Significativo",4)+IF(H29="Alto",6) -> 0 | J29: =IF(I29>0,1,0) -> 0 | L29: =IF(K29="N.A.",0)+IF(K29="Baixo",1)+IF(K29="Moderado",2)+IF(K29="Significativo",4)+IF(K29="Alto",6) -> 0 | M29: =IF(L29>0,1,0) -> 0 | O29: =IF(N29="N.A.",0)+IF(N29="Baixo",1)+IF(N29="Moderado",2)+IF(N29="Significativo",4)+IF(N29="Alto",6) -> 0 | P29: =IF(O29>0,1,0) -> 0 | R29: =IF(Q29="N.A.",0)+IF(Q29="Baixo",1)+IF(Q29="Moderado",2)+IF(Q29="Significativo",4)+IF(Q29="Alto",6) -> 0 | T29: =SUM(G29,J29,M29,P29,S29) -> 0 | U29: =IFERROR(SUM(F29,I29,L29,O29,R29)/T29,0) -> 0 | AA29: =IF(W29="X",0)+IF(X29="X",2)+IF(Y29="X",4)+IF(Z29="X",9) -> 0 | AF29: =IF(AC29="X",1)+IF(AD29="X",2)+IF(AE29="X",5) -> 0 | AZ29: =OR(AND(U29>0,U29<=2,AP29>0,AP29>12,AP29<=17),AND(U29>0,U29>2,U29<=3,AP29>0,AP29>10,AP29<=13),AND(U29>0,U29>3,U29<=5,AP29>0,AP29<=10),AND(U29>0,U29>4,U29<=6,AP29>0,AP29<=7)) -> FALSE | BA29: =OR(AND(U29>0,U29>2,U29<=3,AP29>0,AP29>14,AP29<=20),AND(U29>0,U29>3,U29<=5,AP29>0,AP29>10),AND(U29>0,U29>5,U29<=6,AP29>0,AP29>7,AP29<=20)) -> FALSE
B30: 11. | F30: =IF(E30="N.A.",0)+IF(E30="Baixo",1)+IF(E30="Moderado",2)+IF(E30="Significativo",4)+IF(E30="Alto",6) -> 0 | G30: =IF(F30>0,1,0) -> 0 | I30: =IF(H30="N.A.",0)+IF(H30="Baixo",1)+IF(H30="Moderado",2)+IF(H30="Significativo",4)+IF(H30="Alto",6) -> 0 | J30: =IF(I30>0,1,0) -> 0 | L30: =IF(K30="N.A.",0)+IF(K30="Baixo",1)+IF(K30="Moderado",2)+IF(K30="Significativo",4)+IF(K30="Alto",6) -> 0 | M30: =IF(L30>0,1,0) -> 0 | O30: =IF(N30="N.A.",0)+IF(N30="Baixo",1)+IF(N30="Moderado",2)+IF(N30="Significativo",4)+IF(N30="Alto",6) -> 0 | P30: =IF(O30>0,1,0) -> 0 | R30: =IF(Q30="N.A.",0)+IF(Q30="Baixo",1)+IF(Q30="Moderado",2)+IF(Q30="Significativo",4)+IF(Q30="Alto",6) -> 0 | S30: =IF(R30>0,1,0) -> 0 | T30: =SUM(G30,J30,M30,P30,S30) -> 0 | U30: =IFERROR(SUM(F30,I30,L30,O30,R30)/T30,0) -> 0 | AA30: =IF(W30="X",0)+IF(X30="X",2)+IF(Y30="X",4)+IF(Z30="X",9) -> 0 | AF30: =IF(AC30="X",1)+IF(AD30="X",2)+IF(AE30="X",5) -> 0 | AN30: =IF(AH30="X",1)+IF(AI30="X",2)+IF(AJ30="X",3)+IF(AK30="X",4)+IF(AL30="X",5)+IF(AM30="X",6) -> 0 | AP30: =AA30+AF30+AN30 -> 0 | AQ30: =(AP30+U30)/2 -> 0 | AR30: =IF(AS30="",0,10) -> 0 | AS30: =IF(AX30=TRUE,"Desprezível",IF(AY30=TRUE,"Administrável",IF(AZ30=TRUE,"Indesejável",IF(BA30=TRUE,"Intolerável","")))) | AX30: =AND(U30>0,U30<=2,AP30>0,AP30<=7) -> FALSE | AY30: =OR(AND(U30>0,U30<=2,AP30>0,AP30>7,AP30<=13),AND(U30>0,U30>2,U30<=3,AP30>0,AP30<=10)) -> FALSE | AZ30: =OR(AND(U30>0,U30<=2,AP30>0,AP30>12,AP30<=17),AND(U30>0,U30>2,U30<=3,AP30>0,AP30>10,AP30<=13),AND(U30>0,U30>3,U30<=5,AP30>0,AP30<=10),AND(U30>0,U30>4,U30<=6,AP30>0,AP30<=7)) -> FALSE | BA30: =OR(AND(U30>0,U30>2,U30<=3,AP30>0,AP30>14,AP30<=20),AND(U30>0,U30>3,U30<=5,AP30>0,AP30>10),AND(U30>0,U30>5,U30<=6,AP30>0,AP30>7,AP30<=20)) -> FALSE
F31: =IF(E31="N.A.",0)+IF(E31="Baixo",1)+IF(E31="Moderado",2)+IF(E31="Significativo",4)+IF(E31="Alto",6) -> 0 | G31: =IF(F31>0,1,0) -> 0 | I31: =IF(H31="N.A.",0)+IF(H31="Baixo",1)+IF(H31="Moderado",2)+IF(H31="Significativo",4)+IF(H31="Alto",6) -> 0 | J31: =IF(I31>0,1,0) -> 0 | L31: =IF(K31="N.A.",0)+IF(K31="Baixo",1)+IF(K31="Moderado",2)+IF(K31="Significativo",4)+IF(K31="Alto",6) -> 0 | M31: =IF(L31>0,1,0) -> 0 | O31: =IF(N31="N.A.",0)+IF(N31="Baixo",1)+IF(N31="Moderado",2)+IF(N31="Significativo",4)+IF(N31="Alto",6) -> 0 | P31: =IF(O31>0,1,0) -> 0 | R31: =IF(Q31="N.A.",0)+IF(Q31="Baixo",1)+IF(Q31="Moderado",2)+IF(Q31="Significativo",4)+IF(Q31="Alto",6) -> 0 | T31: =SUM(G31,J31,M31,P31,S31) -> 0 | U31: =IFERROR(SUM(F31,I31,L31,O31,R31)/T31,0) -> 0 | AA31: =IF(W31="X",0)+IF(X31="X",2)+IF(Y31="X",4)+IF(Z31="X",9) -> 0 | AF31: =IF(AC31="X",1)+IF(AD31="X",2)+IF(AE31="X",5) -> 0 | AZ31: =OR(AND(U31>0,U31<=2,AP31>0,AP31>12,AP31<=17),AND(U31>0,U31>2,U31<=3,AP31>0,AP31>10,AP31<=13),AND(U31>0,U31>3,U31<=5,AP31>0,AP31<=10),AND(U31>0,U31>4,U31<=6,AP31>0,AP31<=7)) -> FALSE | BA31: =OR(AND(U31>0,U31>2,U31<=3,AP31>0,AP31>14,AP31<=20),AND(U31>0,U31>3,U31<=5,AP31>0,AP31>10),AND(U31>0,U31>5,U31<=6,AP31>0,AP31>7,AP31<=20)) -> FALSE
B32: 12. | F32: =IF(E32="N.A.",0)+IF(E32="Baixo",1)+IF(E32="Moderado",2)+IF(E32="Significativo",4)+IF(E32="Alto",6) -> 0 | G32: =IF(F32>0,1,0) -> 0 | I32: =IF(H32="N.A.",0)+IF(H32="Baixo",1)+IF(H32="Moderado",2)+IF(H32="Significativo",4)+IF(H32="Alto",6) -> 0 | J32: =IF(I32>0,1,0) -> 0 | L32: =IF(K32="N.A.",0)+IF(K32="Baixo",1)+IF(K32="Moderado",2)+IF(K32="Significativo",4)+IF(K32="Alto",6) -> 0 | M32: =IF(L32>0,1,0) -> 0 | O32: =IF(N32="N.A.",0)+IF(N32="Baixo",1)+IF(N32="Moderado",2)+IF(N32="Significativo",4)+IF(N32="Alto",6) -> 0 | P32: =IF(O32>0,1,0) -> 0 | R32: =IF(Q32="N.A.",0)+IF(Q32="Baixo",1)+IF(Q32="Moderado",2)+IF(Q32="Significativo",4)+IF(Q32="Alto",6) -> 0 | S32: =IF(R32>0,1,0) -> 0 | T32: =SUM(G32,J32,M32,P32,S32) -> 0 | U32: =IFERROR(SUM(F32,I32,L32,O32,R32)/T32,0) -> 0 | AA32: =IF(W32="X",0)+IF(X32="X",2)+IF(Y32="X",4)+IF(Z32="X",9) -> 0 | AF32: =IF(AC32="X",1)+IF(AD32="X",2)+IF(AE32="X",5) -> 0 | AN32: =IF(AH32="X",1)+IF(AI32="X",2)+IF(AJ32="X",3)+IF(AK32="X",4)+IF(AL32="X",5)+IF(AM32="X",6) -> 0 | AP32: =AA32+AF32+AN32 -> 0 | AQ32: =(AP32+U32)/2 -> 0 | AR32: =IF(AS32="",0,10) -> 0 | AS32: =IF(AX32=TRUE,"Desprezível",IF(AY32=TRUE,"Administrável",IF(AZ32=TRUE,"Indesejável",IF(BA32=TRUE,"Intolerável","")))) | AX32: =AND(U32>0,U32<=2,AP32>0,AP32<=7) -> FALSE | AY32: =OR(AND(U32>0,U32<=2,AP32>0,AP32>7,AP32<=13),AND(U32>0,U32>2,U32<=3,AP32>0,AP32<=10)) -> FALSE | AZ32: =OR(AND(U32>0,U32<=2,AP32>0,AP32>12,AP32<=17),AND(U32>0,U32>2,U32<=3,AP32>0,AP32>10,AP32<=13),AND(U32>0,U32>3,U32<=5,AP32>0,AP32<=10),AND(U32>0,U32>4,U32<=6,AP32>0,AP32<=7)) -> FALSE | BA32: =OR(AND(U32>0,U32>2,U32<=3,AP32>0,AP32>14,AP32<=20),AND(U32>0,U32>3,U32<=5,AP32>0,AP32>10),AND(U32>0,U32>5,U32<=6,AP32>0,AP32>7,AP32<=20)) -> FALSE
F33: =IF(E33="N.A.",0)+IF(E33="Baixo",1)+IF(E33="Moderado",2)+IF(E33="Significativo",4)+IF(E33="Alto",6) -> 0 | G33: =IF(F33>0,1,0) -> 0 | I33: =IF(H33="N.A.",0)+IF(H33="Baixo",1)+IF(H33="Moderado",2)+IF(H33="Significativo",4)+IF(H33="Alto",6) -> 0 | J33: =IF(I33>0,1,0) -> 0 | L33: =IF(K33="N.A.",0)+IF(K33="Baixo",1)+IF(K33="Moderado",2)+IF(K33="Significativo",4)+IF(K33="Alto",6) -> 0 | M33: =IF(L33>0,1,0) -> 0 | O33: =IF(N33="N.A.",0)+IF(N33="Baixo",1)+IF(N33="Moderado",2)+IF(N33="Significativo",4)+IF(N33="Alto",6) -> 0 | P33: =IF(O33>0,1,0) -> 0 | R33: =IF(Q33="N.A.",0)+IF(Q33="Baixo",1)+IF(Q33="Moderado",2)+IF(Q33="Significativo",4)+IF(Q33="Alto",6) -> 0 | T33: =SUM(G33,J33,M33,P33,S33) -> 0 | U33: =IFERROR(SUM(F33,I33,L33,O33,R33)/T33,0) -> 0 | AA33: =IF(W33="X",0)+IF(X33="X",2)+IF(Y33="X",4)+IF(Z33="X",9) -> 0 | AF33: =IF(AC33="X",1)+IF(AD33="X",2)+IF(AE33="X",5) -> 0 | AZ33: =OR(AND(U33>0,U33<=2,AP33>0,AP33>12,AP33<=17),AND(U33>0,U33>2,U33<=3,AP33>0,AP33>10,AP33<=13),AND(U33>0,U33>3,U33<=5,AP33>0,AP33<=10),AND(U33>0,U33>4,U33<=6,AP33>0,AP33<=7)) -> FALSE | BA33: =OR(AND(U33>0,U33>2,U33<=3,AP33>0,AP33>14,AP33<=20),AND(U33>0,U33>3,U33<=5,AP33>0,AP33>10),AND(U33>0,U33>5,U33<=6,AP33>0,AP33>7,AP33<=20)) -> FALSE
B34: 13. | F34: =IF(E34="N.A.",0)+IF(E34="Baixo",1)+IF(E34="Moderado",2)+IF(E34="Significativo",4)+IF(E34="Alto",6) -> 0 | G34: =IF(F34>0,1,0) -> 0 | I34: =IF(H34="N.A.",0)+IF(H34="Baixo",1)+IF(H34="Moderado",2)+IF(H34="Significativo",4)+IF(H34="Alto",6) -> 0 | J34: =IF(I34>0,1,0) -> 0 | L34: =IF(K34="N.A.",0)+IF(K34="Baixo",1)+IF(K34="Moderado",2)+IF(K34="Significativo",4)+IF(K34="Alto",6) -> 0 | M34: =IF(L34>0,1,0) -> 0 | O34: =IF(N34="N.A.",0)+IF(N34="Baixo",1)+IF(N34="Moderado",2)+IF(N34="Significativo",4)+IF(N34="Alto",6) -> 0 | P34: =IF(O34>0,1,0) -> 0 | R34: =IF(Q34="N.A.",0)+IF(Q34="Baixo",1)+IF(Q34="Moderado",2)+IF(Q34="Significativo",4)+IF(Q34="Alto",6) -> 0 | S34: =IF(R34>0,1,0) -> 0 | T34: =SUM(G34,J34,M34,P34,S34) -> 0 | U34: =IFERROR(SUM(F34,I34,L34,O34,R34)/T34,0) -> 0 | AA34: =IF(W34="X",0)+IF(X34="X",2)+IF(Y34="X",4)+IF(Z34="X",9) -> 0 | AF34: =IF(AC34="X",1)+IF(AD34="X",2)+IF(AE34="X",5) -> 0 | AN34: =IF(AH34="X",1)+IF(AI34="X",2)+IF(AJ34="X",3)+IF(AK34="X",4)+IF(AL34="X",5)+IF(AM34="X",6) -> 0 | AP34: =AA34+AF34+AN34 -> 0 | AQ34: =(AP34+U34)/2 -> 0 | AR34: =IF(AS34="",0,10) -> 0 | AS34: =IF(AX34=TRUE,"Desprezível",IF(AY34=TRUE,"Administrável",IF(AZ34=TRUE,"Indesejável",IF(BA34=TRUE,"Intolerável","")))) | AX34: =AND(U34>0,U34<=2,AP34>0,AP34<=7) -> FALSE | AY34: =OR(AND(U34>0,U34<=2,AP34>0,AP34>7,AP34<=13),AND(U34>0,U34>2,U34<=3,AP34>0,AP34<=10)) -> FALSE | AZ34: =OR(AND(U34>0,U34<=2,AP34>0,AP34>12,AP34<=17),AND(U34>0,U34>2,U34<=3,AP34>0,AP34>10,AP34<=13),AND(U34>0,U34>3,U34<=5,AP34>0,AP34<=10),AND(U34>0,U34>4,U34<=6,AP34>0,AP34<=7)) -> FALSE | BA34: =OR(AND(U34>0,U34>2,U34<=3,AP34>0,AP34>14,AP34<=20),AND(U34>0,U34>3,U34<=5,AP34>0,AP34>10),AND(U34>0,U34>5,U34<=6,AP34>0,AP34>7,AP34<=20)) -> FALSE
F35: =IF(E35="N.A.",0)+IF(E35="Baixo",1)+IF(E35="Moderado",2)+IF(E35="Significativo",4)+IF(E35="Alto",6) -> 0 | G35: =IF(F35>0,1,0) -> 0 | I35: =IF(H35="N.A.",0)+IF(H35="Baixo",1)+IF(H35="Moderado",2)+IF(H35="Significativo",4)+IF(H35="Alto",6) -> 0 | J35: =IF(I35>0,1,0) -> 0 | L35: =IF(K35="N.A.",0)+IF(K35="Baixo",1)+IF(K35="Moderado",2)+IF(K35="Significativo",4)+IF(K35="Alto",6) -> 0 | M35: =IF(L35>0,1,0) -> 0 | O35: =IF(N35="N.A.",0)+IF(N35="Baixo",1)+IF(N35="Moderado",2)+IF(N35="Significativo",4)+IF(N35="Alto",6) -> 0 | P35: =IF(O35>0,1,0) -> 0 | R35: =IF(Q35="N.A.",0)+IF(Q35="Baixo",1)+IF(Q35="Moderado",2)+IF(Q35="Significativo",4)+IF(Q35="Alto",6) -> 0 | T35: =SUM(G35,J35,M35,P35,S35) -> 0 | U35: =IFERROR(SUM(F35,I35,L35,O35,R35)/T35,0) -> 0 | AA35: =IF(W35="X",0)+IF(X35="X",2)+IF(Y35="X",4)+IF(Z35="X",9) -> 0 | AF35: =IF(AC35="X",1)+IF(AD35="X",2)+IF(AE35="X",5) -> 0 | AZ35: =OR(AND(U35>0,U35<=2,AP35>0,AP35>12,AP35<=17),AND(U35>0,U35>2,U35<=3,AP35>0,AP35>10,AP35<=13),AND(U35>0,U35>3,U35<=5,AP35>0,AP35<=10),AND(U35>0,U35>4,U35<=6,AP35>0,AP35<=7)) -> FALSE | BA35: =OR(AND(U35>0,U35>2,U35<=3,AP35>0,AP35>14,AP35<=20),AND(U35>0,U35>3,U35<=5,AP35>0,AP35>10),AND(U35>0,U35>5,U35<=6,AP35>0,AP35>7,AP35<=20)) -> FALSE
B36: 14. | F36: =IF(E36="N.A.",0)+IF(E36="Baixo",1)+IF(E36="Moderado",2)+IF(E36="Significativo",4)+IF(E36="Alto",6) -> 0 | G36: =IF(F36>0,1,0) -> 0 | I36: =IF(H36="N.A.",0)+IF(H36="Baixo",1)+IF(H36="Moderado",2)+IF(H36="Significativo",4)+IF(H36="Alto",6) -> 0 | J36: =IF(I36>0,1,0) -> 0 | L36: =IF(K36="N.A.",0)+IF(K36="Baixo",1)+IF(K36="Moderado",2)+IF(K36="Significativo",4)+IF(K36="Alto",6) -> 0 | M36: =IF(L36>0,1,0) -> 0 | O36: =IF(N36="N.A.",0)+IF(N36="Baixo",1)+IF(N36="Moderado",2)+IF(N36="Significativo",4)+IF(N36="Alto",6) -> 0 | P36: =IF(O36>0,1,0) -> 0 | R36: =IF(Q36="N.A.",0)+IF(Q36="Baixo",1)+IF(Q36="Moderado",2)+IF(Q36="Significativo",4)+IF(Q36="Alto",6) -> 0 | S36: =IF(R36>0,1,0) -> 0 | T36: =SUM(G36,J36,M36,P36,S36) -> 0 | U36: =IFERROR(SUM(F36,I36,L36,O36,R36)/T36,0) -> 0 | AA36: =IF(W36="X",0)+IF(X36="X",2)+IF(Y36="X",4)+IF(Z36="X",9) -> 0 | AF36: =IF(AC36="X",1)+IF(AD36="X",2)+IF(AE36="X",5) -> 0 | AN36: =IF(AH36="X",1)+IF(AI36="X",2)+IF(AJ36="X",3)+IF(AK36="X",4)+IF(AL36="X",5)+IF(AM36="X",6) -> 0 | AP36: =AA36+AF36+AN36 -> 0 | AQ36: =(AP36+U36)/2 -> 0 | AR36: =IF(AS36="",0,10) -> 0 | AS36: =IF(AX36=TRUE,"Desprezível",IF(AY36=TRUE,"Administrável",IF(AZ36=TRUE,"Indesejável",IF(BA36=TRUE,"Intolerável","")))) | AX36: =AND(U36>0,U36<=2,AP36>0,AP36<=7) -> FALSE | AY36: =OR(AND(U36>0,U36<=2,AP36>0,AP36>7,AP36<=13),AND(U36>0,U36>2,U36<=3,AP36>0,AP36<=10)) -> FALSE | AZ36: =OR(AND(U36>0,U36<=2,AP36>0,AP36>12,AP36<=17),AND(U36>0,U36>2,U36<=3,AP36>0,AP36>10,AP36<=13),AND(U36>0,U36>3,U36<=5,AP36>0,AP36<=10),AND(U36>0,U36>4,U36<=6,AP36>0,AP36<=7)) -> FALSE | BA36: =OR(AND(U36>0,U36>2,U36<=3,AP36>0,AP36>14,AP36<=20),AND(U36>0,U36>3,U36<=5,AP36>0,AP36>10),AND(U36>0,U36>5,U36<=6,AP36>0,AP36>7,AP36<=20)) -> FALSE
F37: =IF(E37="N.A.",0)+IF(E37="Baixo",1)+IF(E37="Moderado",2)+IF(E37="Significativo",4)+IF(E37="Alto",6) -> 0 | G37: =IF(F37>0,1,0) -> 0 | I37: =IF(H37="N.A.",0)+IF(H37="Baixo",1)+IF(H37="Moderado",2)+IF(H37="Significativo",4)+IF(H37="Alto",6) -> 0 | J37: =IF(I37>0,1,0) -> 0 | L37: =IF(K37="N.A.",0)+IF(K37="Baixo",1)+IF(K37="Moderado",2)+IF(K37="Significativo",4)+IF(K37="Alto",6) -> 0 | M37: =IF(L37>0,1,0) -> 0 | O37: =IF(N37="N.A.",0)+IF(N37="Baixo",1)+IF(N37="Moderado",2)+IF(N37="Significativo",4)+IF(N37="Alto",6) -> 0 | P37: =IF(O37>0,1,0) -> 0 | R37: =IF(Q37="N.A.",0)+IF(Q37="Baixo",1)+IF(Q37="Moderado",2)+IF(Q37="Significativo",4)+IF(Q37="Alto",6) -> 0 | T37: =SUM(G37,J37,M37,P37,S37) -> 0 | U37: =IFERROR(SUM(F37,I37,L37,O37,R37)/T37,0) -> 0 | AA37: =IF(W37="X",0)+IF(X37="X",2)+IF(Y37="X",4)+IF(Z37="X",9) -> 0 | AF37: =IF(AC37="X",1)+IF(AD37="X",2)+IF(AE37="X",5) -> 0 | AZ37: =OR(AND(U37>0,U37<=2,AP37>0,AP37>12,AP37<=17),AND(U37>0,U37>2,U37<=3,AP37>0,AP37>10,AP37<=13),AND(U37>0,U37>3,U37<=5,AP37>0,AP37<=10),AND(U37>0,U37>4,U37<=6,AP37>0,AP37<=7)) -> FALSE | BA37: =OR(AND(U37>0,U37>2,U37<=3,AP37>0,AP37>14,AP37<=20),AND(U37>0,U37>3,U37<=5,AP37>0,AP37>10),AND(U37>0,U37>5,U37<=6,AP37>0,AP37>7,AP37<=20)) -> FALSE
B38: 15. | F38: =IF(E38="N.A.",0)+IF(E38="Baixo",1)+IF(E38="Moderado",2)+IF(E38="Significativo",4)+IF(E38="Alto",6) -> 0 | G38: =IF(F38>0,1,0) -> 0 | I38: =IF(H38="N.A.",0)+IF(H38="Baixo",1)+IF(H38="Moderado",2)+IF(H38="Significativo",4)+IF(H38="Alto",6) -> 0 | J38: =IF(I38>0,1,0) -> 0 | L38: =IF(K38="N.A.",0)+IF(K38="Baixo",1)+IF(K38="Moderado",2)+IF(K38="Significativo",4)+IF(K38="Alto",6) -> 0 | M38: =IF(L38>0,1,0) -> 0 | O38: =IF(N38="N.A.",0)+IF(N38="Baixo",1)+IF(N38="Moderado",2)+IF(N38="Significativo",4)+IF(N38="Alto",6) -> 0 | P38: =IF(O38>0,1,0) -> 0 | R38: =IF(Q38="N.A.",0)+IF(Q38="Baixo",1)+IF(Q38="Moderado",2)+IF(Q38="Significativo",4)+IF(Q38="Alto",6) -> 0 | S38: =IF(R38>0,1,0) -> 0 | T38: =SUM(G38,J38,M38,P38,S38) -> 0 | U38: =IFERROR(SUM(F38,I38,L38,O38,R38)/T38,0) -> 0 | AA38: =IF(W38="X",0)+IF(X38="X",2)+IF(Y38="X",4)+IF(Z38="X",9) -> 0 | AF38: =IF(AC38="X",1)+IF(AD38="X",2)+IF(AE38="X",5) -> 0 | AN38: =IF(AH38="X",1)+IF(AI38="X",2)+IF(AJ38="X",3)+IF(AK38="X",4)+IF(AL38="X",5)+IF(AM38="X",6) -> 0 | AP38: =AA38+AF38+AN38 -> 0 | AQ38: =(AP38+U38)/2 -> 0 | AR38: =IF(AS38="",0,10) -> 0 | AS38: =IF(AX38=TRUE,"Desprezível",IF(AY38=TRUE,"Administrável",IF(AZ38=TRUE,"Indesejável",IF(BA38=TRUE,"Intolerável","")))) | AX38: =AND(U38>0,U38<=2,AP38>0,AP38<=7) -> FALSE | AY38: =OR(AND(U38>0,U38<=2,AP38>0,AP38>7,AP38<=13),AND(U38>0,U38>2,U38<=3,AP38>0,AP38<=10)) -> FALSE | AZ38: =OR(AND(U38>0,U38<=2,AP38>0,AP38>12,AP38<=17),AND(U38>0,U38>2,U38<=3,AP38>0,AP38>10,AP38<=13),AND(U38>0,U38>3,U38<=5,AP38>0,AP38<=10),AND(U38>0,U38>4,U38<=6,AP38>0,AP38<=7)) -> FALSE | BA38: =OR(AND(U38>0,U38>2,U38<=3,AP38>0,AP38>14,AP38<=20),AND(U38>0,U38>3,U38<=5,AP38>0,AP38>10),AND(U38>0,U38>5,U38<=6,AP38>0,AP38>7,AP38<=20)) -> FALSE
F39: =IF(E39="N.A.",0)+IF(E39="Baixo",1)+IF(E39="Moderado",2)+IF(E39="Significativo",4)+IF(E39="Alto",6) -> 0 | G39: =IF(F39>0,1,0) -> 0 | I39: =IF(H39="N.A.",0)+IF(H39="Baixo",1)+IF(H39="Moderado",2)+IF(H39="Significativo",4)+IF(H39="Alto",6) -> 0 | J39: =IF(I39>0,1,0) -> 0 | L39: =IF(K39="N.A.",0)+IF(K39="Baixo",1)+IF(K39="Moderado",2)+IF(K39="Significativo",4)+IF(K39="Alto",6) -> 0 | M39: =IF(L39>0,1,0) -> 0 | O39: =IF(N39="N.A.",0)+IF(N39="Baixo",1)+IF(N39="Moderado",2)+IF(N39="Significativo",4)+IF(N39="Alto",6) -> 0 | P39: =IF(O39>0,1,0) -> 0 | R39: =IF(Q39="N.A.",0)+IF(Q39="Baixo",1)+IF(Q39="Moderado",2)+IF(Q39="Significativo",4)+IF(Q39="Alto",6) -> 0 | T39: =SUM(G39,J39,M39,P39,S39) -> 0 | U39: =IFERROR(SUM(F39,I39,L39,O39,R39)/T39,0) -> 0 | AA39: =IF(W39="X",0)+IF(X39="X",2)+IF(Y39="X",4)+IF(Z39="X",9) -> 0 | AF39: =IF(AC39="X",1)+IF(AD39="X",2)+IF(AE39="X",5) -> 0 | AZ39: =OR(AND(U39>0,U39<=2,AP39>0,AP39>12,AP39<=17),AND(U39>0,U39>2,U39<=3,AP39>0,AP39>10,AP39<=13),AND(U39>0,U39>3,U39<=5,AP39>0,AP39<=10),AND(U39>0,U39>4,U39<=6,AP39>0,AP39<=7)) -> FALSE | BA39: =OR(AND(U39>0,U39>2,U39<=3,AP39>0,AP39>14,AP39<=20),AND(U39>0,U39>3,U39<=5,AP39>0,AP39>10),AND(U39>0,U39>5,U39<=6,AP39>0,AP39>7,AP39<=20)) -> FALSE
B40: 16. | F40: =IF(E40="N.A.",0)+IF(E40="Baixo",1)+IF(E40="Moderado",2)+IF(E40="Significativo",4)+IF(E40="Alto",6) -> 0 | G40: =IF(F40>0,1,0) -> 0 | I40: =IF(H40="N.A.",0)+IF(H40="Baixo",1)+IF(H40="Moderado",2)+IF(H40="Significativo",4)+IF(H40="Alto",6) -> 0 | J40: =IF(I40>0,1,0) -> 0 | L40: =IF(K40="N.A.",0)+IF(K40="Baixo",1)+IF(K40="Moderado",2)+IF(K40="Significativo",4)+IF(K40="Alto",6) -> 0 | M40: =IF(L40>0,1,0) -> 0 | O40: =IF(N40="N.A.",0)+IF(N40="Baixo",1)+IF(N40="Moderado",2)+IF(N40="Significativo",4)+IF(N40="Alto",6) -> 0 | P40: =IF(O40>0,1,0) -> 0 | R40: =IF(Q40="N.A.",0)+IF(Q40="Baixo",1)+IF(Q40="Moderado",2)+IF(Q40="Significativo",4)+IF(Q40="Alto",6) -> 0 | S40: =IF(R40>0,1,0) -> 0 | T40: =SUM(G40,J40,M40,P40,S40) -> 0 | U40: =IFERROR(SUM(F40,I40,L40,O40,R40)/T40,0) -> 0 | AA40: =IF(W40="X",0)+IF(X40="X",2)+IF(Y40="X",4)+IF(Z40="X",9) -> 0 | AF40: =IF(AC40="X",1)+IF(AD40="X",2)+IF(AE40="X",5) -> 0 | AN40: =IF(AH40="X",1)+IF(AI40="X",2)+IF(AJ40="X",3)+IF(AK40="X",4)+IF(AL40="X",5)+IF(AM40="X",6) -> 0 | AP40: =AA40+AF40+AN40 -> 0 | AQ40: =(AP40+U40)/2 -> 0 | AR40: =IF(AS40="",0,10) -> 0 | AS40: =IF(AX40=TRUE,"Desprezível",IF(AY40=TRUE,"Administrável",IF(AZ40=TRUE,"Indesejável",IF(BA40=TRUE,"Intolerável","")))) | AX40: =AND(U40>0,U40<=2,AP40>0,AP40<=7) -> FALSE | AY40: =OR(AND(U40>0,U40<=2,AP40>0,AP40>7,AP40<=13),AND(U40>0,U40>2,U40<=3,AP40>0,AP40<=10)) -> FALSE | AZ40: =OR(AND(U40>0,U40<=2,AP40>0,AP40>12,AP40<=17),AND(U40>0,U40>2,U40<=3,AP40>0,AP40>10,AP40<=13),AND(U40>0,U40>3,U40<=5,AP40>0,AP40<=10),AND(U40>0,U40>4,U40<=6,AP40>0,AP40<=7)) -> FALSE | BA40: =OR(AND(U40>0,U40>2,U40<=3,AP40>0,AP40>14,AP40<=20),AND(U40>0,U40>3,U40<=5,AP40>0,AP40>10),AND(U40>0,U40>5,U40<=6,AP40>0,AP40>7,AP40<=20)) -> FALSE
F41: =IF(E41="N.A.",0)+IF(E41="Baixo",1)+IF(E41="Moderado",2)+IF(E41="Significativo",4)+IF(E41="Alto",6) -> 0 | G41: =IF(F41>0,1,0) -> 0 | I41: =IF(H41="N.A.",0)+IF(H41="Baixo",1)+IF(H41="Moderado",2)+IF(H41="Significativo",4)+IF(H41="Alto",6) -> 0 | J41: =IF(I41>0,1,0) -> 0 | L41: =IF(K41="N.A.",0)+IF(K41="Baixo",1)+IF(K41="Moderado",2)+IF(K41="Significativo",4)+IF(K41="Alto",6) -> 0 | M41: =IF(L41>0,1,0) -> 0 | O41: =IF(N41="N.A.",0)+IF(N41="Baixo",1)+IF(N41="Moderado",2)+IF(N41="Significativo",4)+IF(N41="Alto",6) -> 0 | P41: =IF(O41>0,1,0) -> 0 | R41: =IF(Q41="N.A.",0)+IF(Q41="Baixo",1)+IF(Q41="Moderado",2)+IF(Q41="Significativo",4)+IF(Q41="Alto",6) -> 0 | T41: =SUM(G41,J41,M41,P41,S41) -> 0 | U41: =IFERROR(SUM(F41,I41,L41,O41,R41)/T41,0) -> 0 | AA41: =IF(W41="X",0)+IF(X41="X",2)+IF(Y41="X",4)+IF(Z41="X",9) -> 0 | AF41: =IF(AC41="X",1)+IF(AD41="X",2)+IF(AE41="X",5) -> 0 | AZ41: =OR(AND(U41>0,U41<=2,AP41>0,AP41>12,AP41<=17),AND(U41>0,U41>2,U41<=3,AP41>0,AP41>10,AP41<=13),AND(U41>0,U41>3,U41<=5,AP41>0,AP41<=10),AND(U41>0,U41>4,U41<=6,AP41>0,AP41<=7)) -> FALSE | BA41: =OR(AND(U41>0,U41>2,U41<=3,AP41>0,AP41>14,AP41<=20),AND(U41>0,U41>3,U41<=5,AP41>0,AP41>10),AND(U41>0,U41>5,U41<=6,AP41>0,AP41>7,AP41<=20)) -> FALSE
B42: 17. | F42: =IF(E42="N.A.",0)+IF(E42="Baixo",1)+IF(E42="Moderado",2)+IF(E42="Significativo",4)+IF(E42="Alto",6) -> 0 | G42: =IF(F42>0,1,0) -> 0 | I42: =IF(H42="N.A.",0)+IF(H42="Baixo",1)+IF(H42="Moderado",2)+IF(H42="Significativo",4)+IF(H42="Alto",6) -> 0 | J42: =IF(I42>0,1,0) -> 0 | L42: =IF(K42="N.A.",0)+IF(K42="Baixo",1)+IF(K42="Moderado",2)+IF(K42="Significativo",4)+IF(K42="Alto",6) -> 0 | M42: =IF(L42>0,1,0) -> 0 | O42: =IF(N42="N.A.",0)+IF(N42="Baixo",1)+IF(N42="Moderado",2)+IF(N42="Significativo",4)+IF(N42="Alto",6) -> 0 | P42: =IF(O42>0,1,0) -> 0 | R42: =IF(Q42="N.A.",0)+IF(Q42="Baixo",1)+IF(Q42="Moderado",2)+IF(Q42="Significativo",4)+IF(Q42="Alto",6) -> 0 | S42: =IF(R42>0,1,0) -> 0 | T42: =SUM(G42,J42,M42,P42,S42) -> 0 | U42: =IFERROR(SUM(F42,I42,L42,O42,R42)/T42,0) -> 0 | AA42: =IF(W42="X",0)+IF(X42="X",2)+IF(Y42="X",4)+IF(Z42="X",9) -> 0 | AF42: =IF(AC42="X",1)+IF(AD42="X",2)+IF(AE42="X",5) -> 0 | AN42: =IF(AH42="X",1)+IF(AI42="X",2)+IF(AJ42="X",3)+IF(AK42="X",4)+IF(AL42="X",5)+IF(AM42="X",6) -> 0 | AP42: =AA42+AF42+AN42 -> 0 | AQ42: =(AP42+U42)/2 -> 0 | AR42: =IF(AS42="",0,10) -> 0 | AS42: =IF(AX42=TRUE,"Desprezível",IF(AY42=TRUE,"Administrável",IF(AZ42=TRUE,"Indesejável",IF(BA42=TRUE,"Intolerável","")))) | AX42: =AND(U42>0,U42<=2,AP42>0,AP42<=7) -> FALSE | AY42: =OR(AND(U42>0,U42<=2,AP42>0,AP42>7,AP42<=13),AND(U42>0,U42>2,U42<=3,AP42>0,AP42<=10)) -> FALSE | AZ42: =OR(AND(U42>0,U42<=2,AP42>0,AP42>12,AP42<=17),AND(U42>0,U42>2,U42<=3,AP42>0,AP42>10,AP42<=13),AND(U42>0,U42>3,U42<=5,AP42>0,AP42<=10),AND(U42>0,U42>4,U42<=6,AP42>0,AP42<=7)) -> FALSE | BA42: =OR(AND(U42>0,U42>2,U42<=3,AP42>0,AP42>14,AP42<=20),AND(U42>0,U42>3,U42<=5,AP42>0,AP42>10),AND(U42>0,U42>5,U42<=6,AP42>0,AP42>7,AP42<=20)) -> FALSE
F43: =IF(E43="N.A.",0)+IF(E43="Baixo",1)+IF(E43="Moderado",2)+IF(E43="Significativo",4)+IF(E43="Alto",6) -> 0 | G43: =IF(F43>0,1,0) -> 0 | I43: =IF(H43="N.A.",0)+IF(H43="Baixo",1)+IF(H43="Moderado",2)+IF(H43="Significativo",4)+IF(H43="Alto",6) -> 0 | J43: =IF(I43>0,1,0) -> 0 | L43: =IF(K43="N.A.",0)+IF(K43="Baixo",1)+IF(K43="Moderado",2)+IF(K43="Significativo",4)+IF(K43="Alto",6) -> 0 | M43: =IF(L43>0,1,0) -> 0 | O43: =IF(N43="N.A.",0)+IF(N43="Baixo",1)+IF(N43="Moderado",2)+IF(N43="Significativo",4)+IF(N43="Alto",6) -> 0 | P43: =IF(O43>0,1,0) -> 0 | R43: =IF(Q43="N.A.",0)+IF(Q43="Baixo",1)+IF(Q43="Moderado",2)+IF(Q43="Significativo",4)+IF(Q43="Alto",6) -> 0 | T43: =SUM(G43,J43,M43,P43,S43) -> 0 | U43: =IFERROR(SUM(F43,I43,L43,O43,R43)/T43,0) -> 0 | AA43: =IF(W43="X",0)+IF(X43="X",2)+IF(Y43="X",4)+IF(Z43="X",9) -> 0 | AF43: =IF(AC43="X",1)+IF(AD43="X",2)+IF(AE43="X",5) -> 0 | AZ43: =OR(AND(U43>0,U43<=2,AP43>0,AP43>12,AP43<=17),AND(U43>0,U43>2,U43<=3,AP43>0,AP43>10,AP43<=13),AND(U43>0,U43>3,U43<=5,AP43>0,AP43<=10),AND(U43>0,U43>4,U43<=6,AP43>0,AP43<=7)) -> FALSE | BA43: =OR(AND(U43>0,U43>2,U43<=3,AP43>0,AP43>14,AP43<=20),AND(U43>0,U43>3,U43<=5,AP43>0,AP43>10),AND(U43>0,U43>5,U43<=6,AP43>0,AP43>7,AP43<=20)) -> FALSE
B44: 18. | F44: =IF(E44="N.A.",0)+IF(E44="Baixo",1)+IF(E44="Moderado",2)+IF(E44="Significativo",4)+IF(E44="Alto",6) -> 0 | G44: =IF(F44>0,1,0) -> 0 | I44: =IF(H44="N.A.",0)+IF(H44="Baixo",1)+IF(H44="Moderado",2)+IF(H44="Significativo",4)+IF(H44="Alto",6) -> 0 | J44: =IF(I44>0,1,0) -> 0 | L44: =IF(K44="N.A.",0)+IF(K44="Baixo",1)+IF(K44="Moderado",2)+IF(K44="Significativo",4)+IF(K44="Alto",6) -> 0 | M44: =IF(L44>0,1,0) -> 0 | O44: =IF(N44="N.A.",0)+IF(N44="Baixo",1)+IF(N44="Moderado",2)+IF(N44="Significativo",4)+IF(N44="Alto",6) -> 0 | P44: =IF(O44>0,1,0) -> 0 | R44: =IF(Q44="N.A.",0)+IF(Q44="Baixo",1)+IF(Q44="Moderado",2)+IF(Q44="Significativo",4)+IF(Q44="Alto",6) -> 0 | S44: =IF(R44>0,1,0) -> 0 | T44: =SUM(G44,J44,M44,P44,S44) -> 0 | U44: =IFERROR(SUM(F44,I44,L44,O44,R44)/T44,0) -> 0 | AA44: =IF(W44="X",0)+IF(X44="X",2)+IF(Y44="X",4)+IF(Z44="X",9) -> 0 | AF44: =IF(AC44="X",1)+IF(AD44="X",2)+IF(AE44="X",5) -> 0 | AN44: =IF(AH44="X",1)+IF(AI44="X",2)+IF(AJ44="X",3)+IF(AK44="X",4)+IF(AL44="X",5)+IF(AM44="X",6) -> 0 | AP44: =AA44+AF44+AN44 -> 0 | AQ44: =(AP44+U44)/2 -> 0 | AR44: =IF(AS44="",0,10) -> 0 | AS44: =IF(AX44=TRUE,"Desprezível",IF(AY44=TRUE,"Administrável",IF(AZ44=TRUE,"Indesejável",IF(BA44=TRUE,"Intolerável","")))) | AX44: =AND(U44>0,U44<=2,AP44>0,AP44<=7) -> FALSE | AY44: =OR(AND(U44>0,U44<=2,AP44>0,AP44>7,AP44<=13),AND(U44>0,U44>2,U44<=3,AP44>0,AP44<=10)) -> FALSE | AZ44: =OR(AND(U44>0,U44<=2,AP44>0,AP44>12,AP44<=17),AND(U44>0,U44>2,U44<=3,AP44>0,AP44>10,AP44<=13),AND(U44>0,U44>3,U44<=5,AP44>0,AP44<=10),AND(U44>0,U44>4,U44<=6,AP44>0,AP44<=7)) -> FALSE | BA44: =OR(AND(U44>0,U44>2,U44<=3,AP44>0,AP44>14,AP44<=20),AND(U44>0,U44>3,U44<=5,AP44>0,AP44>10),AND(U44>0,U44>5,U44<=6,AP44>0,AP44>7,AP44<=20)) -> FALSE
F45: =IF(E45="N.A.",0)+IF(E45="Baixo",1)+IF(E45="Moderado",2)+IF(E45="Significativo",4)+IF(E45="Alto",6) -> 0 | G45: =IF(F45>0,1,0) -> 0 | I45: =IF(H45="N.A.",0)+IF(H45="Baixo",1)+IF(H45="Moderado",2)+IF(H45="Significativo",4)+IF(H45="Alto",6) -> 0 | J45: =IF(I45>0,1,0) -> 0 | L45: =IF(K45="N.A.",0)+IF(K45="Baixo",1)+IF(K45="Moderado",2)+IF(K45="Significativo",4)+IF(K45="Alto",6) -> 0 | M45: =IF(L45>0,1,0) -> 0 | O45: =IF(N45="N.A.",0)+IF(N45="Baixo",1)+IF(N45="Moderado",2)+IF(N45="Significativo",4)+IF(N45="Alto",6) -> 0 | P45: =IF(O45>0,1,0) -> 0 | R45: =IF(Q45="N.A.",0)+IF(Q45="Baixo",1)+IF(Q45="Moderado",2)+IF(Q45="Significativo",4)+IF(Q45="Alto",6) -> 0 | T45: =SUM(G45,J45,M45,P45,S45) -> 0 | U45: =IFERROR(SUM(F45,I45,L45,O45,R45)/T45,0) -> 0 | AA45: =IF(W45="X",0)+IF(X45="X",2)+IF(Y45="X",4)+IF(Z45="X",9) -> 0 | AF45: =IF(AC45="X",1)+IF(AD45="X",2)+IF(AE45="X",5) -> 0 | AZ45: =OR(AND(U45>0,U45<=2,AP45>0,AP45>12,AP45<=17),AND(U45>0,U45>2,U45<=3,AP45>0,AP45>10,AP45<=13),AND(U45>0,U45>3,U45<=5,AP45>0,AP45<=10),AND(U45>0,U45>4,U45<=6,AP45>0,AP45<=7)) -> FALSE | BA45: =OR(AND(U45>0,U45>2,U45<=3,AP45>0,AP45>14,AP45<=20),AND(U45>0,U45>3,U45<=5,AP45>0,AP45>10),AND(U45>0,U45>5,U45<=6,AP45>0,AP45>7,AP45<=20)) -> FALSE
B46: 19. | F46: =IF(E46="N.A.",0)+IF(E46="Baixo",1)+IF(E46="Moderado",2)+IF(E46="Significativo",4)+IF(E46="Alto",6) -> 0 | G46: =IF(F46>0,1,0) -> 0 | I46: =IF(H46="N.A.",0)+IF(H46="Baixo",1)+IF(H46="Moderado",2)+IF(H46="Significativo",4)+IF(H46="Alto",6) -> 0 | J46: =IF(I46>0,1,0) -> 0 | L46: =IF(K46="N.A.",0)+IF(K46="Baixo",1)+IF(K46="Moderado",2)+IF(K46="Significativo",4)+IF(K46="Alto",6) -> 0 | M46: =IF(L46>0,1,0) -> 0 | O46: =IF(N46="N.A.",0)+IF(N46="Baixo",1)+IF(N46="Moderado",2)+IF(N46="Significativo",4)+IF(N46="Alto",6) -> 0 | P46: =IF(O46>0,1,0) -> 0 | R46: =IF(Q46="N.A.",0)+IF(Q46="Baixo",1)+IF(Q46="Moderado",2)+IF(Q46="Significativo",4)+IF(Q46="Alto",6) -> 0 | S46: =IF(R46>0,1,0) -> 0 | T46: =SUM(G46,J46,M46,P46,S46) -> 0 | U46: =IFERROR(SUM(F46,I46,L46,O46,R46)/T46,0) -> 0 | AA46: =IF(W46="X",0)+IF(X46="X",2)+IF(Y46="X",4)+IF(Z46="X",9) -> 0 | AF46: =IF(AC46="X",1)+IF(AD46="X",2)+IF(AE46="X",5) -> 0 | AN46: =IF(AH46="X",1)+IF(AI46="X",2)+IF(AJ46="X",3)+IF(AK46="X",4)+IF(AL46="X",5)+IF(AM46="X",6) -> 0 | AP46: =AA46+AF46+AN46 -> 0 | AQ46: =(AP46+U46)/2 -> 0 | AR46: =IF(AS46="",0,10) -> 0 | AS46: =IF(AX46=TRUE,"Desprezível",IF(AY46=TRUE,"Administrável",IF(AZ46=TRUE,"Indesejável",IF(BA46=TRUE,"Intolerável","")))) | AX46: =AND(U46>0,U46<=2,AP46>0,AP46<=7) -> FALSE | AY46: =OR(AND(U46>0,U46<=2,AP46>0,AP46>7,AP46<=13),AND(U46>0,U46>2,U46<=3,AP46>0,AP46<=10)) -> FALSE | AZ46: =OR(AND(U46>0,U46<=2,AP46>0,AP46>12,AP46<=17),AND(U46>0,U46>2,U46<=3,AP46>0,AP46>10,AP46<=13),AND(U46>0,U46>3,U46<=5,AP46>0,AP46<=10),AND(U46>0,U46>4,U46<=6,AP46>0,AP46<=7)) -> FALSE | BA46: =OR(AND(U46>0,U46>2,U46<=3,AP46>0,AP46>14,AP46<=20),AND(U46>0,U46>3,U46<=5,AP46>0,AP46>10),AND(U46>0,U46>5,U46<=6,AP46>0,AP46>7,AP46<=20)) -> FALSE
F47: =IF(E47="N.A.",0)+IF(E47="Baixo",1)+IF(E47="Moderado",2)+IF(E47="Significativo",4)+IF(E47="Alto",6) -> 0 | G47: =IF(F47>0,1,0) -> 0 | I47: =IF(H47="N.A.",0)+IF(H47="Baixo",1)+IF(H47="Moderado",2)+IF(H47="Significativo",4)+IF(H47="Alto",6) -> 0 | J47: =IF(I47>0,1,0) -> 0 | L47: =IF(K47="N.A.",0)+IF(K47="Baixo",1)+IF(K47="Moderado",2)+IF(K47="Significativo",4)+IF(K47="Alto",6) -> 0 | M47: =IF(L47>0,1,0) -> 0 | O47: =IF(N47="N.A.",0)+IF(N47="Baixo",1)+IF(N47="Moderado",2)+IF(N47="Significativo",4)+IF(N47="Alto",6) -> 0 | P47: =IF(O47>0,1,0) -> 0 | R47: =IF(Q47="N.A.",0)+IF(Q47="Baixo",1)+IF(Q47="Moderado",2)+IF(Q47="Significativo",4)+IF(Q47="Alto",6) -> 0 | T47: =SUM(G47,J47,M47,P47,S47) -> 0 | U47: =IFERROR(SUM(F47,I47,L47,O47,R47)/T47,0) -> 0 | AA47: =IF(W47="X",0)+IF(X47="X",2)+IF(Y47="X",4)+IF(Z47="X",9) -> 0 | AF47: =IF(AC47="X",1)+IF(AD47="X",2)+IF(AE47="X",5) -> 0 | AZ47: =OR(AND(U47>0,U47<=2,AP47>0,AP47>12,AP47<=17),AND(U47>0,U47>2,U47<=3,AP47>0,AP47>10,AP47<=13),AND(U47>0,U47>3,U47<=5,AP47>0,AP47<=10),AND(U47>0,U47>4,U47<=6,AP47>0,AP47<=7)) -> FALSE | BA47: =OR(AND(U47>0,U47>2,U47<=3,AP47>0,AP47>14,AP47<=20),AND(U47>0,U47>3,U47<=5,AP47>0,AP47>10),AND(U47>0,U47>5,U47<=6,AP47>0,AP47>7,AP47<=20)) -> FALSE
B48: 20. | F48: =IF(E48="N.A.",0)+IF(E48="Baixo",1)+IF(E48="Moderado",2)+IF(E48="Significativo",4)+IF(E48="Alto",6) -> 0 | G48: =IF(F48>0,1,0) -> 0 | I48: =IF(H48="N.A.",0)+IF(H48="Baixo",1)+IF(H48="Moderado",2)+IF(H48="Significativo",4)+IF(H48="Alto",6) -> 0 | J48: =IF(I48>0,1,0) -> 0 | L48: =IF(K48="N.A.",0)+IF(K48="Baixo",1)+IF(K48="Moderado",2)+IF(K48="Significativo",4)+IF(K48="Alto",6) -> 0 | M48: =IF(L48>0,1,0) -> 0 | O48: =IF(N48="N.A.",0)+IF(N48="Baixo",1)+IF(N48="Moderado",2)+IF(N48="Significativo",4)+IF(N48="Alto",6) -> 0 | P48: =IF(O48>0,1,0) -> 0 | R48: =IF(Q48="N.A.",0)+IF(Q48="Baixo",1)+IF(Q48="Moderado",2)+IF(Q48="Significativo",4)+IF(Q48="Alto",6) -> 0 | S48: =IF(R48>0,1,0) -> 0 | T48: =SUM(G48,J48,M48,P48,S48) -> 0 | U48: =IFERROR(SUM(F48,I48,L48,O48,R48)/T48,0) -> 0 | AA48: =IF(W48="X",0)+IF(X48="X",2)+IF(Y48="X",4)+IF(Z48="X",9) -> 0 | AF48: =IF(AC48="X",1)+IF(AD48="X",2)+IF(AE48="X",5) -> 0 | AN48: =IF(AH48="X",1)+IF(AI48="X",2)+IF(AJ48="X",3)+IF(AK48="X",4)+IF(AL48="X",5)+IF(AM48="X",6) -> 0 | AP48: =AA48+AF48+AN48 -> 0 | AQ48: =(AP48+U48)/2 -> 0 | AR48: =IF(AS48="",0,10) -> 0 | AS48: =IF(AX48=TRUE,"Desprezível",IF(AY48=TRUE,"Administrável",IF(AZ48=TRUE,"Indesejável",IF(BA48=TRUE,"Intolerável","")))) | AX48: =AND(U48>0,U48<=2,AP48>0,AP48<=7) -> FALSE | AY48: =OR(AND(U48>0,U48<=2,AP48>0,AP48>7,AP48<=13),AND(U48>0,U48>2,U48<=3,AP48>0,AP48<=10)) -> FALSE | AZ48: =OR(AND(U48>0,U48<=2,AP48>0,AP48>12,AP48<=17),AND(U48>0,U48>2,U48<=3,AP48>0,AP48>10,AP48<=13),AND(U48>0,U48>3,U48<=5,AP48>0,AP48<=10),AND(U48>0,U48>4,U48<=6,AP48>0,AP48<=7)) -> FALSE | BA48: =OR(AND(U48>0,U48>2,U48<=3,AP48>0,AP48>14,AP48<=20),AND(U48>0,U48>3,U48<=5,AP48>0,AP48>10),AND(U48>0,U48>5,U48<=6,AP48>0,AP48>7,AP48<=20)) -> FALSE
F49: =IF(E49="N.A.",0)+IF(E49="Baixo",1)+IF(E49="Moderado",2)+IF(E49="Significativo",4)+IF(E49="Alto",6) -> 0 | G49: =IF(F49>0,1,0) -> 0 | I49: =IF(H49="N.A.",0)+IF(H49="Baixo",1)+IF(H49="Moderado",2)+IF(H49="Significativo",4)+IF(H49="Alto",6) -> 0 | J49: =IF(I49>0,1,0) -> 0 | L49: =IF(K49="N.A.",0)+IF(K49="Baixo",1)+IF(K49="Moderado",2)+IF(K49="Significativo",4)+IF(K49="Alto",6) -> 0 | M49: =IF(L49>0,1,0) -> 0 | O49: =IF(N49="N.A.",0)+IF(N49="Baixo",1)+IF(N49="Moderado",2)+IF(N49="Significativo",4)+IF(N49="Alto",6) -> 0 | P49: =IF(O49>0,1,0) -> 0 | R49: =IF(Q49="N.A.",0)+IF(Q49="Baixo",1)+IF(Q49="Moderado",2)+IF(Q49="Significativo",4)+IF(Q49="Alto",6) -> 0 | T49: =SUM(G49,J49,M49,P49,S49) -> 0 | U49: =IFERROR(SUM(F49,I49,L49,O49,R49)/T49,0) -> 0 | AF49: =IF(AC49="X",1)+IF(AD49="X",2)+IF(AE49="X",5) -> 0 | AZ49: =OR(AND(U49>0,U49<=2,AP49>0,AP49>12,AP49<=17),AND(U49>0,U49>2,U49<=3,AP49>0,AP49>10,AP49<=13),AND(U49>0,U49>3,U49<=5,AP49>0,AP49<=10),AND(U49>0,U49>4,U49<=6,AP49>0,AP49<=7)) -> FALSE | BA49: =OR(AND(U49>0,U49>2,U49<=3,AP49>0,AP49>14,AP49<=20),AND(U49>0,U49>3,U49<=5,AP49>0,AP49>10),AND(U49>0,U49>5,U49<=6,AP49>0,AP49>7,AP49<=20)) -> FALSE

Sheet Ações-Riscos-CANTU
B2: Ações para tratar riscos
C6: Identificação de Riscos | E6: Significância
B7: Item | G7: BOM/RO/GR | I7: Responsável | K7: Ações / Monitoramento
B10: ='[1]Riscos-CANTU'!B10 -> 1. | C10: ='[1]Riscos-CANTU'!C10 -> Comercial - Vacância | E10: ='[1]Riscos-CANTU'!AS10 -> Administrável | K10: a) gestão comercial: vacância em R$ de 5,7%; em ABL de 9,96%, base set.2020;
I11: Ana Cristina | K11: b) negociações pontuais com locatários visando evitar a desocupação;
K12: c) imóvel de Fortaleza representa 15% do custo mensal (R$ 27k)
B14: ='[1]Riscos-CANTU'!B12 -> 2. | C14: ='[1]Riscos-CANTU'!C12 -> Eventos de Sinistros em Imóveis | E14: ='[1]Riscos-CANTU'!AS12 -> Administrável | K14: a) seguro dos imóveis:
I15: Ana Cristina | K15: b) segurança ou monitoramento nos imóveis desocupados;
B18: ='[1]Riscos-CANTU'!B14 -> 3. | C18: ='[1]Riscos-CANTU'!C14 -> Novos Negócios - Aquisição de Imóveis | E18: ='[1]Riscos-CANTU'!AS14 -> Administrável | K18: a) procedimento de análise de viabilidade;
I19: Nelson | K19: b) apresentação e aprovação do Conselho;
B22: ='[1]Riscos-CANTU'!B16 -> 4. | C22: ='[1]Riscos-CANTU'!C16 -> Novos Negócios - Definição do Produto | E22: ='[1]Riscos-CANTU'!AS16 -> Administrável | K22: a) pesquisa de mercado;
I23: Nelson | K23: b) busca de negócios com locação "casada";
K24: c) viabilidade apresentada e aprovada pelo Conselho;
B26: ='[1]Riscos-CANTU'!B18 -> 5. | C26: ='[1]Riscos-CANTU'!C18 -> Assistência Técnica - Conservação dos Imóveis | E26: ='[1]Riscos-CANTU'!AS18 -> Administrável | K26: a) manutenção corretiva;
I27: Ana Cristina | K27: b) manutenção e controle preventivo (futura equip. de manutenção da Piemonte);
B30: ='[1]Riscos-CANTU'!B20 -> 6. | C30: ='[1]Riscos-CANTU'!C20 -> Administrativo - Inadimplência | E30: ='[1]Riscos-CANTU'!AS20 -> Administrável | K30: a) acompanhamento por evento;
I31: Ana Cristina | K31: b) procedimentos jurídicos;
B34: ='[1]Riscos-CANTU'!B22 -> 7. | C34: ='[1]Riscos-CANTU'!C22 -> Redução de faturamento em decorrência de Pandemias "Covid-19" | E34: ='[1]Riscos-CANTU'!AS22 -> Administrável | K34: a) acompanhamento por evento;
I35: Ana Cristina | K35: b) buscar negociações;
B38: ='[1]Riscos-CANTU'!B24 -> 8. | C38: ='[1]Riscos-CANTU'!C24 -> 0 | E38: ='[1]Riscos-CANTU'!AS24
B42: ='[1]Riscos-CANTU'!B26 -> 9. | C42: ='[1]Riscos-CANTU'!C26 -> 0 | E42: ='[1]Riscos-CANTU'!AS26
B46: ='[1]Riscos-CANTU'!B28 -> 10. | C46: ='[1]Riscos-CANTU'!C28 -> 0 | E46: ='[1]Riscos-CANTU'!AS28
B50: ='[1]Riscos-CANTU'!B30 -> 11. | C50: ='[1]Riscos-CANTU'!C30 -> 0 | E50: ='[1]Riscos-CANTU'!AS30
B54: ='[1]Riscos-CANTU'!B32 -> 12. | C54: ='[1]Riscos-CANTU'!C32 -> 0 | E54: ='[1]Riscos-CANTU'!AS32
B58: ='[1]Riscos-CANTU'!B34 -> 13. | C58: ='[1]Riscos-CANTU'!C34 -> 0 | E58: ='[1]Riscos-CANTU'!AS34
B62: ='[1]Riscos-CANTU'!B36 -> 14. | C62: ='[1]Riscos-CANTU'!C36 -> 0 | E62: ='[1]Riscos-CANTU'!AS36
B66: ='[1]Riscos-CANTU'!B38 -> 15. | C66: ='[1]Riscos-CANTU'!C38 -> 0 | E66: ='[1]Riscos-CANTU'!AS38
B70: ='[1]Riscos-CANTU'!B40 -> 16. | C70: ='[1]Riscos-CANTU'!C40 -> 0 | E70: ='[1]Riscos-CANTU'!AS40
B74: ='[1]Riscos-CANTU'!B42 -> 17. | C74: ='[1]Riscos-CANTU'!C42 -> 0 | E74: ='[1]Riscos-CANTU'!AS42
B78: ='[1]Riscos-CANTU'!B44 -> 18. | C78: ='[1]Riscos-CANTU'!C44 -> 0 | E78: ='[1]Riscos-CANTU'!AS44
B82: ='[1]Riscos-CANTU'!B46 -> 19. | C82: ='[1]Riscos-CANTU'!C46 -> 0 | E82: ='[1]Riscos-CANTU'!AS46
B86: ='[1]Riscos-CANTU'!B48 -> 20. | C86: ='[1]Riscos-CANTU'!C48 -> 0 | E86: ='[1]Riscos-CANTU'!AS48
B90: ='[1]Riscos-CANTU'!#REF! -> #REF! | C90: ='[1]Riscos-CANTU'!#REF! -> #REF! | E90: ='[1]Riscos-CANTU'!#REF! -> #REF!

Sheet Oportunidades-CANTU
E1: Matriz de Avaliação e Gestão de Oportunidades
E4: GESTÃO DE PROPRIEDADES
B6: Item | C6: Oportunidade | E6: Avaliação de Impacto | W6: Condição para Implantação / Execução | AT6: Valor Agregado | AV6: Estratégia | AY6: Valor Agregado
E7: Financeiro | F7: Pontos | G7: Inf. Média | H7: Legal | I7: Pontos | J7: Inf. Média | K7: Imagem | L7: Pontos | M7: Inf. Média | N7: Direcionamento Estratégico | O7: Pontos | P7: Inf. Média | Q7: Operação | R7: Pontos | S7: Inf. Média | W7: Prazo | AB7: Pontos | AD7: Complexidade | AI7: Pontos | AK7: Payback (ROI) | AP7: Pontos
U8: Impacto | W8: Muito Curto | X8: Curto | Y8: Médio | Z8: Longo | AA8: Muito Longo | AD8: Nenhuma | AE8: Baixa | AF8: Média | AG8: Alta | AH8: Muito Alta | AK8: Imediato | AL8: Curto Prazo | AM8: Médio Prazo | AN8: Longo Prazo | AO8: Muito Longo | AQ8: Probabilidade | AR8: Média | AY8: Baixo | AZ8: Médio | BA8: Alto | BB8: Muito Alto
B10: 1. | C10: Expansão/aumento de faturamento na captação de Novos Negocios | E10: Alto | F10: =IF(E10="N.A.",0)+IF(E10="Baixo",1)+IF(E10="Moderado",2)+IF(E10="Significativo",4)+IF(E10="Alto",6) -> 6 | G10: =IF(F10>0,1,0) -> 1 | H10: Moderado | I10: =IF(H10="N.A.",0)+IF(H10="Baixo",1)+IF(H10="Moderado",2)+IF(H10="Significativo",4)+IF(H10="Alto",6) -> 2 | J10: =IF(I10>0,1,0) -> 1 | K10: Moderado | L10: =IF(K10="N.A.",0)+IF(K10="Baixo",1)+IF(K10="Moderado",2)+IF(K10="Significativo",4)+IF(K10="Alto",6) -> 2 | M10: =IF(L10>0,1,0) -> 1 | N10: Alto | O10: =IF(N10="N.A.",0)+IF(N10="Baixo",1)+IF(N10="Moderado",2)+IF(N10="Significativo",4)+IF(N10="Alto",6) -> 6 | P10: =IF(O10>0,1,0) -> 1 | Q10: Significativo | R10: =IF(Q10="N.A.",0)+IF(Q10="Baixo",1)+IF(Q10="Moderado",2)+IF(Q10="Significativo",4)+IF(Q10="Alto",6) -> 4 | S10: =IF(R10>0,1,0) -> 1 | T10: =SUM(G10,J10,M10,P10,S10) -> 5 | U10: =IFERROR(SUM(F10,I10,L10,O10,R10)/T10,0) -> 4 | AA10: x | AB10: =IF(W10="X",5)+IF(X10="X",4)+IF(Y10="X",3)+IF(Z10="X",2)+IF(AA10="X",1) -> 1 | AE10: x | AI10: =IF(AD10="X",5)+IF(AE10="X",4)+IF(AF10="X",3)+IF(AG10="X",2)+IF(AH10="X",1) -> 4 | AO10: x | AP10: =IF(AK10="X",5)+IF(AL10="X",4)+IF(AM10="X",3)+IF(AN10="X",2)+IF(AO10="X",1) -> 1 | AQ10: =AB10+AI10+AP10 -> 6 | AR10: =(AQ10+U10)/2 -> 5 | AS10: =IF(AT10="",0,10) -> 10 | AT10: =IF(AY10=TRUE,"Baixo",IF(AZ10=TRUE,"Médio",IF(BA10=TRUE,"Alto",IF(BB10=TRUE,"Muito Alto","")))) -> Alto | AV10: Melhorar | AX10: N.A. | AY10: =AND(U10>0,U10<=2,AQ10>0,AQ10<=7) -> FALSE | AZ10: =OR(AND(U10>0,U10<=2,AQ10>0,AQ10>7,AQ10<=13),AND(U10>0,U10>2,U10<=3,AQ10>0,AQ10<=10)) -> FALSE | BA10: =OR(AND(U10>0,U10<=2,AQ10>0,AQ10>12,AQ10<=17),AND(U10>0,U10>2,U10<=3,AQ10>0,AQ10>10,AQ10<=13),AND(U10>0,U10>3,U10<=5,AQ10>0,AQ10<=10),AND(U10>0,U10>5,U10<=6,AQ10>0,AQ10<=7)) -> TRUE | BB10: =OR(AND(U10>0,U10>2,U10<=3,AQ10>0,AQ10>14,AQ10<=20),AND(U10>0,U10>3,U10<=5,AQ10>0,AQ10>10),AND(U10>0,U10>5,U10<=6,AQ10>0,AQ10>7,AQ10<=20)) -> FALSE | BD10: N.A.
I11: =IF(H11="N.A.",0)+IF(H11="Baixo",1)+IF(H11="Moderado",2)+IF(H11="Significativo",4)+IF(H11="Alto",6) -> 0 | J11: =IF(I11>0,1,0) -> 0 | L11: =IF(K11="N.A.",0)+IF(K11="Baixo",1)+IF(K11="Moderado",2)+IF(K11="Significativo",4)+IF(K11="Alto",6) -> 0 | R11: =IF(Q11="N.A.",0)+IF(Q11="Baixo",1)+IF(Q11="Moderado",2)+IF(Q11="Significativo",4)+IF(Q11="Alto",6) -> 0 | S11: =IF(R11>0,1,0) -> 0 | T11: =SUM(G11,J11,M11,P11,S11) -> 0 | U11: =IFERROR(SUM(F11,I11,L11,O11,R11)/T11,0) -> 0 | AQ11: =AB11+AI11+AP11 -> 0 | AT11: =IF(AY11=TRUE,"Baixo",IF(AZ11=TRUE,"Médio",IF(BA11=TRUE,"Alto",IF(BB11=TRUE,"Muito Alto","")))) | AX11: Baixo | BA11: =OR(AND(U11>0,U11<=2,AQ11>0,AQ11>12,AQ11<=17),AND(U11>0,U11>2,U11<=3,AQ11>0,AQ11>10,AQ11<=13),AND(U11>0,U11>3,U11<=5,AQ11>0,AQ11<=10),AND(U11>0,U11>5,U11<=6,AQ11>0,AQ11<=7)) -> FALSE | BB11: =OR(AND(U11>0,U11>2,U11<=3,AQ11>0,AQ11>14,AQ11<=20),AND(U11>0,U11>3,U11<=5,AQ11>0,AQ11>10),AND(U11>0,U11>5,U11<=6,AQ11>0,AQ11>7,AQ11<=20)) -> FALSE | BD11: Baixo
B12: 2. | F12: =IF(E12="N.A.",0)+IF(E12="Baixo",1)+IF(E12="Moderado",2)+IF(E12="Significativo",4)+IF(E12="Alto",6) -> 0 | G12: =IF(F12>0,1,0) -> 0 | I12: =IF(H12="N.A.",0)+IF(H12="Baixo",1)+IF(H12="Moderado",2)+IF(H12="Significativo",4)+IF(H12="Alto",6) -> 0 | J12: =IF(I12>0,1,0) -> 0 | L12: =IF(K12="N.A.",0)+IF(K12="Baixo",1)+IF(K12="Moderado",2)+IF(K12="Significativo",4)+IF(K12="Alto",6) -> 0 | M12: =IF(L12>0,1,0) -> 0 | O12: =IF(N12="N.A.",0)+IF(N12="Baixo",1)+IF(N12="Moderado",2)+IF(N12="Significativo",4)+IF(N12="Alto",6) -> 0 | P12: =IF(O12>0,1,0) -> 0 | R12: =IF(Q12="N.A.",0)+IF(Q12="Baixo",1)+IF(Q12="Moderado",2)+IF(Q12="Significativo",4)+IF(Q12="Alto",6) -> 0 | S12: =IF(R12>0,1,0) -> 0 | T12: =SUM(G12,J12,M12,P12,S12) -> 0 | U12: =IFERROR(SUM(F12,I12,L12,O12,R12)/T12,0) -> 0 | AB12: =IF(W12="X",5)+IF(X12="X",4)+IF(Y12="X",3)+IF(Z12="X",2)+IF(AA12="X",1) -> 0 | AI12: =IF(AD12="X",5)+IF(AE12="X",4)+IF(AF12="X",3)+IF(AG12="X",2)+IF(AH12="X",1) -> 0 | AP12: =IF(AK12="X",5)+IF(AL12="X",4)+IF(AM12="X",3)+IF(AN12="X",2)+IF(AO12="X",1) -> 0 | AQ12: =AB12+AI12+AP12 -> 0 | AR12: =(AQ12+U12)/2 -> 0 | AS12: =IF(AT12="",0,10) -> 0 | AT12: =IF(AY12=TRUE,"Baixo",IF(AZ12=TRUE,"Médio",IF(BA12=TRUE,"Alto",IF(BB12=TRUE,"Muito Alto","")))) | AX12: Moderado | AY12: =AND(U12>0,U12<=2,AQ12>0,AQ12<=7) -> FALSE | AZ12: =OR(AND(U12>0,U12<=2,AQ12>0,AQ12>7,AQ12<=13),AND(U12>0,U12>2,U12<=3,AQ12>0,AQ12<=10)) -> FALSE | BA12: =OR(AND(U12>0,U12<=2,AQ12>0,AQ12>12,AQ12<=17),AND(U12>0,U12>2,U12<=3,AQ12>0,AQ12>10,AQ12<=13),AND(U12>0,U12>3,U12<=5,AQ12>0,AQ12<=10),AND(U12>0,U12>5,U12<=6,AQ12>0,AQ12<=7)) -> FALSE | BB12: =OR(AND(U12>0,U12>2,U12<=3,AQ12>0,AQ12>14,AQ12<=20),AND(U12>0,U12>3,U12<=5,AQ12>0,AQ12>10),AND(U12>0,U12>5,U12<=6,AQ12>0,AQ12>7,AQ12<=20)) -> FALSE | BD12: Moderado
T13: =SUM(G13,J13,M13,P13,S13) -> 0 | U13: =IFERROR(SUM(F13,I13,L13,O13,R13)/T13,0) -> 0 | AQ13: =AB13+AI13+AP13 -> 0 | AT13: =IF(AY13=TRUE,"Baixo",IF(AZ13=TRUE,"Médio",IF(BA13=TRUE,"Alto",IF(BB13=TRUE,"Muito Alto","")))) | AX13: Significativo | BA13: =OR(AND(U13>0,U13<=2,AQ13>0,AQ13>12,AQ13<=17),AND(U13>0,U13>2,U13<=3,AQ13>0,AQ13>10,AQ13<=13),AND(U13>0,U13>3,U13<=5,AQ13>0,AQ13<=10),AND(U13>0,U13>5,U13<=6,AQ13>0,AQ13<=7)) -> FALSE | BB13: =OR(AND(U13>0,U13>2,U13<=3,AQ13>0,AQ13>14,AQ13<=20),AND(U13>0,U13>3,U13<=5,AQ13>0,AQ13>10),AND(U13>0,U13>5,U13<=6,AQ13>0,AQ13>7,AQ13<=20)) -> FALSE | BD13: Significativo
B14: 3. | F14: =IF(E14="N.A.",0)+IF(E14="Baixo",1)+IF(E14="Moderado",2)+IF(E14="Significativo",4)+IF(E14="Alto",6) -> 0 | G14: =IF(F14>0,1,0) -> 0 | I14: =IF(H14="N.A.",0)+IF(H14="Baixo",1)+IF(H14="Moderado",2)+IF(H14="Significativo",4)+IF(H14="Alto",6) -> 0 | J14: =IF(I14>0,1,0) -> 0 | L14: =IF(K14="N.A.",0)+IF(K14="Baixo",1)+IF(K14="Moderado",2)+IF(K14="Significativo",4)+IF(K14="Alto",6) -> 0 | M14: =IF(L14>0,1,0) -> 0 | O14: =IF(N14="N.A.",0)+IF(N14="Baixo",1)+IF(N14="Moderado",2)+IF(N14="Significativo",4)+IF(N14="Alto",6) -> 0 | P14: =IF(O14>0,1,0) -> 0 | R14: =IF(Q14="N.A.",0)+IF(Q14="Baixo",1)+IF(Q14="Moderado",2)+IF(Q14="Significativo",4)+IF(Q14="Alto",6) -> 0 | S14: =IF(R14>0,1,0) -> 0 | T14: =SUM(G14,J14,M14,P14,S14) -> 0 | U14: =IFERROR(SUM(F14,I14,L14,O14,R14)/T14,0) -> 0 | AB14: =IF(W14="X",5)+IF(X14="X",4)+IF(Y14="X",3)+IF(Z14="X",2)+IF(AA14="X",1) -> 0 | AI14: =IF(AD14="X",5)+IF(AE14="X",4)+IF(AF14="X",3)+IF(AG14="X",2)+IF(AH14="X",1) -> 0 | AP14: =IF(AK14="X",5)+IF(AL14="X",4)+IF(AM14="X",3)+IF(AN14="X",2)+IF(AO14="X",1) -> 0 | AQ14: =AB14+AI14+AP14 -> 0 | AR14: =(AQ14+U14)/2 -> 0 | AS14: =IF(AT14="",0,10) -> 0 | AT14: =IF(AY14=TRUE,"Baixo",IF(AZ14=TRUE,"Médio",IF(BA14=TRUE,"Alto",IF(BB14=TRUE,"Muito Alto","")))) | AX14: Alto | AY14: =AND(U14>0,U14<=2,AQ14>0,AQ14<=7) -> FALSE | AZ14: =OR(AND(U14>0,U14<=2,AQ14>0,AQ14>7,AQ14<=13),AND(U14>0,U14>2,U14<=3,AQ14>0,AQ14<=10)) -> FALSE | BA14: =OR(AND(U14>0,U14<=2,AQ14>0,AQ14>12,AQ14<=17),AND(U14>0,U14>2,U14<=3,AQ14>0,AQ14>10,AQ14<=13),AND(U14>0,U14>3,U14<=5,AQ14>0,AQ14<=10),AND(U14>0,U14>5,U14<=6,AQ14>0,AQ14<=7)) -> FALSE | BB14: =OR(AND(U14>0,U14>2,U14<=3,AQ14>0,AQ14>14,AQ14<=20),AND(U14>0,U14>3,U14<=5,AQ14>0,AQ14>10),AND(U14>0,U14>5,U14<=6,AQ14>0,AQ14>7,AQ14<=20)) -> FALSE | BD14: Alto
T15: =SUM(G15,J15,M15,P15,S15) -> 0 | U15: =IFERROR(SUM(F15,I15,L15,O15,R15)/T15,0) -> 0 | AQ15: =AB15+AI15+AP15 -> 0 | AT15: =IF(AY15=TRUE,"Baixo",IF(AZ15=TRUE,"Médio",IF(BA15=TRUE,"Alto",IF(BB15=TRUE,"Muito Alto","")))) | BA15: =OR(AND(U15>0,U15<=2,AQ15>0,AQ15>12,AQ15<=17),AND(U15>0,U15>2,U15<=3,AQ15>0,AQ15>10,AQ15<=13),AND(U15>0,U15>3,U15<=5,AQ15>0,AQ15<=10),AND(U15>0,U15>5,U15<=6,AQ15>0,AQ15<=7)) -> FALSE | BB15: =OR(AND(U15>0,U15>2,U15<=3,AQ15>0,AQ15>14,AQ15<=20),AND(U15>0,U15>3,U15<=5,AQ15>0,AQ15>10),AND(U15>0,U15>5,U15<=6,AQ15>0,AQ15>7,AQ15<=20)) -> FALSE
B16: 4. | F16: =IF(E16="N.A.",0)+IF(E16="Baixo",1)+IF(E16="Moderado",2)+IF(E16="Significativo",4)+IF(E16="Alto",6) -> 0 | G16: =IF(F16>0,1,0) -> 0 | I16: =IF(H16="N.A.",0)+IF(H16="Baixo",1)+IF(H16="Moderado",2)+IF(H16="Significativo",4)+IF(H16="Alto",6) -> 0 | J16: =IF(I16>0,1,0) -> 0 | L16: =IF(K16="N.A.",0)+IF(K16="Baixo",1)+IF(K16="Moderado",2)+IF(K16="Significativo",4)+IF(K16="Alto",6) -> 0 | M16: =IF(L16>0,1,0) -> 0 | O16: =IF(N16="N.A.",0)+IF(N16="Baixo",1)+IF(N16="Moderado",2)+IF(N16="Significativo",4)+IF(N16="Alto",6) -> 0 | P16: =IF(O16>0,1,0) -> 0 | R16: =IF(Q16="N.A.",0)+IF(Q16="Baixo",1)+IF(Q16="Moderado",2)+IF(Q16="Significativo",4)+IF(Q16="Alto",6) -> 0 | S16: =IF(R16>0,1,0) -> 0 | T16: =SUM(G16,J16,M16,P16,S16) -> 0 | U16: =IFERROR(SUM(F16,I16,L16,O16,R16)/T16,0) -> 0 | AB16: =IF(W16="X",5)+IF(X16="X",4)+IF(Y16="X",3)+IF(Z16="X",2)+IF(AA16="X",1) -> 0 | AI16: =IF(AD16="X",5)+IF(AE16="X",4)+IF(AF16="X",3)+IF(AG16="X",2)+IF(AH16="X",1) -> 0 | AP16: =IF(AK16="X",5)+IF(AL16="X",4)+IF(AM16="X",3)+IF(AN16="X",2)+IF(AO16="X",1) -> 0 | AQ16: =AB16+AI16+AP16 -> 0 | AR16: =(AQ16+U16)/2 -> 0 | AS16: =IF(AT16="",0,10) -> 0 | AT16: =IF(AY16=TRUE,"Baixo",IF(AZ16=TRUE,"Médio",IF(BA16=TRUE,"Alto",IF(BB16=TRUE,"Muito Alto","")))) | AY16: =AND(U16>0,U16<=2,AQ16>0,AQ16<=7) -> FALSE | AZ16: =OR(AND(U16>0,U16<=2,AQ16>0,AQ16>7,AQ16<=13),AND(U16>0,U16>2,U16<=3,AQ16>0,AQ16<=10)) -> FALSE | BA16: =OR(AND(U16>0,U16<=2,AQ16>0,AQ16>12,AQ16<=17),AND(U16>0,U16>2,U16<=3,AQ16>0,AQ16>10,AQ16<=13),AND(U16>0,U16>3,U16<=5,AQ16>0,AQ16<=10),AND(U16>0,U16>5,U16<=6,AQ16>0,AQ16<=7)) -> FALSE | BB16: =OR(AND(U16>0,U16>2,U16<=3,AQ16>0,AQ16>14,AQ16<=20),AND(U16>0,U16>3,U16<=5,AQ16>0,AQ16>10),AND(U16>0,U16>5,U16<=6,AQ16>0,AQ16>7,AQ16<=20)) -> FALSE
T17: =SUM(G17,J17,M17,P17,S17) -> 0 | U17: =IFERROR(SUM(F17,I17,L17,O17,R17)/T17,0) -> 0 | AQ17: =AB17+AI17+AP17 -> 0 | AT17: =IF(AY17=TRUE,"Baixo",IF(AZ17=TRUE,"Médio",IF(BA17=TRUE,"Alto",IF(BB17=TRUE,"Muito Alto","")))) | BA17: =OR(AND(U17>0,U17<=2,AQ17>0,AQ17>12,AQ17<=17),AND(U17>0,U17>2,U17<=3,AQ17>0,AQ17>10,AQ17<=13),AND(U17>0,U17>3,U17<=5,AQ17>0,AQ17<=10),AND(U17>0,U17>5,U17<=6,AQ17>0,AQ17<=7)) -> FALSE | BB17: =OR(AND(U17>0,U17>2,U17<=3,AQ17>0,AQ17>14,AQ17<=20),AND(U17>0,U17>3,U17<=5,AQ17>0,AQ17>10),AND(U17>0,U17>5,U17<=6,AQ17>0,AQ17>7,AQ17<=20)) -> FALSE
B18: 5. | F18: =IF(E18="N.A.",0)+IF(E18="Baixo",1)+IF(E18="Moderado",2)+IF(E18="Significativo",4)+IF(E18="Alto",6) -> 0 | G18: =IF(F18>0,1,0) -> 0 | I18: =IF(H18="N.A.",0)+IF(H18="Baixo",1)+IF(H18="Moderado",2)+IF(H18="Significativo",4)+IF(H18="Alto",6) -> 0 | J18: =IF(I18>0,1,0) -> 0 | L18: =IF(K18="N.A.",0)+IF(K18="Baixo",1)+IF(K18="Moderado",2)+IF(K18="Significativo",4)+IF(K18="Alto",6) -> 0 | M18: =IF(L18>0,1,0) -> 0 | O18: =IF(N18="N.A.",0)+IF(N18="Baixo",1)+IF(N18="Moderado",2)+IF(N18="Significativo",4)+IF(N18="Alto",6) -> 0 | P18: =IF(O18>0,1,0) -> 0 | R18: =IF(Q18="N.A.",0)+IF(Q18="Baixo",1)+IF(Q18="Moderado",2)+IF(Q18="Significativo",4)+IF(Q18="Alto",6) -> 0 | S18: =IF(R18>0,1,0) -> 0 | T18: =SUM(G18,J18,M18,P18,S18) -> 0 | U18: =IFERROR(SUM(F18,I18,L18,O18,R18)/T18,0) -> 0 | AB18: =IF(W18="X",5)+IF(X18="X",4)+IF(Y18="X",3)+IF(Z18="X",2)+IF(AA18="X",1) -> 0 | AI18: =IF(AD18="X",5)+IF(AE18="X",4)+IF(AF18="X",3)+IF(AG18="X",2)+IF(AH18="X",1) -> 0 | AP18: =IF(AK18="X",5)+IF(AL18="X",4)+IF(AM18="X",3)+IF(AN18="X",2)+IF(AO18="X",1) -> 0 | AQ18: =AB18+AI18+AP18 -> 0 | AR18: =(AQ18+U18)/2 -> 0 | AS18: =IF(AT18="",0,10) -> 0 | AT18: =IF(AY18=TRUE,"Baixo",IF(AZ18=TRUE,"Médio",IF(BA18=TRUE,"Alto",IF(BB18=TRUE,"Muito Alto","")))) | AX18: X | AY18: =AND(U18>0,U18<=2,AQ18>0,AQ18<=7) -> FALSE | AZ18: =OR(AND(U18>0,U18<=2,AQ18>0,AQ18>7,AQ18<=13),AND(U18>0,U18>2,U18<=3,AQ18>0,AQ18<=10)) -> FALSE | BA18: =OR(AND(U18>0,U18<=2,AQ18>0,AQ18>12,AQ18<=17),AND(U18>0,U18>2,U18<=3,AQ18>0,AQ18>10,AQ18<=13),AND(U18>0,U18>3,U18<=5,AQ18>0,AQ18<=10),AND(U18>0,U18>5,U18<=6,AQ18>0,AQ18<=7)) -> FALSE | BB18: =OR(AND(U18>0,U18>2,U18<=3,AQ18>0,AQ18>14,AQ18<=20),AND(U18>0,U18>3,U18<=5,AQ18>0,AQ18>10),AND(U18>0,U18>5,U18<=6,AQ18>0,AQ18>7,AQ18<=20)) -> FALSE | BD18: X
BA19: =OR(AND(U19>0,U19<=2,AQ19>0,AQ19>12,AQ19<=17),AND(U19>0,U19>2,U19<=3,AQ19>0,AQ19>10,AQ19<=13),AND(U19>0,U19>3,U19<=5,AQ19>0,AQ19<=10),AND(U19>0,U19>5,U19<=6,AQ19>0,AQ19<=7)) -> FALSE | BB19: =OR(AND(U19>0,U19>2,U19<=3,AQ19>0,AQ19>14,AQ19<=20),AND(U19>0,U19>3,U19<=5,AQ19>0,AQ19>10),AND(U19>0,U19>5,U19<=6,AQ19>0,AQ19>7,AQ19<=20)) -> FALSE
B20: 6. | F20: =IF(E20="N.A.",0)+IF(E20="Baixo",1)+IF(E20="Moderado",2)+IF(E20="Significativo",4)+IF(E20="Alto",6) -> 0 | G20: =IF(F20>0,1,0) -> 0 | I20: =IF(H20="N.A.",0)+IF(H20="Baixo",1)+IF(H20="Moderado",2)+IF(H20="Significativo",4)+IF(H20="Alto",6) -> 0 | J20: =IF(I20>0,1,0) -> 0 | L20: =IF(K20="N.A.",0)+IF(K20="Baixo",1)+IF(K20="Moderado",2)+IF(K20="Significativo",4)+IF(K20="Alto",6) -> 0 | M20: =IF(L20>0,1,0) -> 0 | O20: =IF(N20="N.A.",0)+IF(N20="Baixo",1)+IF(N20="Moderado",2)+IF(N20="Significativo",4)+IF(N20="Alto",6) -> 0 | P20: =IF(O20>0,1,0) -> 0 | R20: =IF(Q20="N.A.",0)+IF(Q20="Baixo",1)+IF(Q20="Moderado",2)+IF(Q20="Significativo",4)+IF(Q20="Alto",6) -> 0 | S20: =IF(R20>0,1,0) -> 0 | T20: =SUM(G20,J20,M20,P20,S20) -> 0 | U20: =IFERROR(SUM(F20,I20,L20,O20,R20)/T20,0) -> 0 | AB20: =IF(W20="X",5)+IF(X20="X",4)+IF(Y20="X",3)+IF(Z20="X",2)+IF(AA20="X",1) -> 0 | AI20: =IF(AD20="X",5)+IF(AE20="X",4)+IF(AF20="X",3)+IF(AG20="X",2)+IF(AH20="X",1) -> 0 | AP20: =IF(AK20="X",5)+IF(AL20="X",4)+IF(AM20="X",3)+IF(AN20="X",2)+IF(AO20="X",1) -> 0 | AQ20: =AB20+AI20+AP20 -> 0 | AR20: =(AQ20+U20)/2 -> 0 | AS20: =IF(AT20="",0,10) -> 0 | AT20: =IF(AY20=TRUE,"Baixo",IF(AZ20=TRUE,"Médio",IF(BA20=TRUE,"Alto",IF(BB20=TRUE,"Muito Alto","")))) | AY20: =AND(U20>0,U20<=2,AQ20>0,AQ20<=7) -> FALSE | AZ20: =OR(AND(U20>0,U20<=2,AQ20>0,AQ20>7,AQ20<=13),AND(U20>0,U20>2,U20<=3,AQ20>0,AQ20<=10)) -> FALSE | BA20: =OR(AND(U20>0,U20<=2,AQ20>0,AQ20>12,AQ20<=17),AND(U20>0,U20>2,U20<=3,AQ20>0,AQ20>10,AQ20<=13),AND(U20>0,U20>3,U20<=5,AQ20>0,AQ20<=10),AND(U20>0,U20>5,U20<=6,AQ20>0,AQ20<=7)) -> FALSE | BB20: =OR(AND(U20>0,U20>2,U20<=3,AQ20>0,AQ20>14,AQ20<=20),AND(U20>0,U20>3,U20<=5,AQ20>0,AQ20>10),AND(U20>0,U20>5,U20<=6,AQ20>0,AQ20>7,AQ20<=20)) -> FALSE
BA21: =OR(AND(U21>0,U21<=2,AQ21>0,AQ21>12,AQ21<=17),AND(U21>0,U21>2,U21<=3,AQ21>0,AQ21>10,AQ21<=13),AND(U21>0,U21>3,U21<=5,AQ21>0,AQ21<=10),AND(U21>0,U21>5,U21<=6,AQ21>0,AQ21<=7)) -> FALSE | BB21: =OR(AND(U21>0,U21>2,U21<=3,AQ21>0,AQ21>14,AQ21<=20),AND(U21>0,U21>3,U21<=5,AQ21>0,AQ21>10),AND(U21>0,U21>5,U21<=6,AQ21>0,AQ21>7,AQ21<=20)) -> FALSE
B22: 7. | F22: =IF(E22="N.A.",0)+IF(E22="Baixo",1)+IF(E22="Moderado",2)+IF(E22="Significativo",4)+IF(E22="Alto",6) -> 0 | G22: =IF(F22>0,1,0) -> 0 | I22: =IF(H22="N.A.",0)+IF(H22="Baixo",1)+IF(H22="Moderado",2)+IF(H22="Significativo",4)+IF(H22="Alto",6) -> 0 | J22: =IF(I22>0,1,0) -> 0 | L22: =IF(K22="N.A.",0)+IF(K22="Baixo",1)+IF(K22="Moderado",2)+IF(K22="Significativo",4)+IF(K22="Alto",6) -> 0 | M22: =IF(L22>0,1,0) -> 0 | O22: =IF(N22="N.A.",0)+IF(N22="Baixo",1)+IF(N22="Moderado",2)+IF(N22="Significativo",4)+IF(N22="Alto",6) -> 0 | P22: =IF(O22>0,1,0) -> 0 | R22: =IF(Q22="N.A.",0)+IF(Q22="Baixo",1)+IF(Q22="Moderado",2)+IF(Q22="Significativo",4)+IF(Q22="Alto",6) -> 0 | S22: =IF(R22>0,1,0) -> 0 | T22: =SUM(G22,J22,M22,P22,S22) -> 0 | U22: =IFERROR(SUM(F22,I22,L22,O22,R22)/T22,0) -> 0 | AB22: =IF(W22="X",5)+IF(X22="X",4)+IF(Y22="X",3)+IF(Z22="X",2)+IF(AA22="X",1) -> 0 | AI22: =IF(AD22="X",5)+IF(AE22="X",4)+IF(AF22="X",3)+IF(AG22="X",2)+IF(AH22="X",1) -> 0 | AP22: =IF(AK22="X",5)+IF(AL22="X",4)+IF(AM22="X",3)+IF(AN22="X",2)+IF(AO22="X",1) -> 0 | AQ22: =AB22+AI22+AP22 -> 0 | AR22: =(AQ22+U22)/2 -> 0 | AS22: =IF(AT22="",0,10) -> 0 | AT22: =IF(AY22=TRUE,"Baixo",IF(AZ22=TRUE,"Médio",IF(BA22=TRUE,"Alto",IF(BB22=TRUE,"Muito Alto","")))) | AY22: =AND(U22>0,U22<=2,AQ22>0,AQ22<=7) -> FALSE | AZ22: =OR(AND(U22>0,U22<=2,AQ22>0,AQ22>7,AQ22<=13),AND(U22>0,U22>2,U22<=3,AQ22>0,AQ22<=10)) -> FALSE | BA22: =OR(AND(U22>0,U22<=2,AQ22>0,AQ22>12,AQ22<=17),AND(U22>0,U22>2,U22<=3,AQ22>0,AQ22>10,AQ22<=13),AND(U22>0,U22>3,U22<=5,AQ22>0,AQ22<=10),AND(U22>0,U22>5,U22<=6,AQ22>0,AQ22<=7)) -> FALSE | BB22: =OR(AND(U22>0,U22>2,U22<=3,AQ22>0,AQ22>14,AQ22<=20),AND(U22>0,U22>3,U22<=5,AQ22>0,AQ22>10),AND(U22>0,U22>5,U22<=6,AQ22>0,AQ22>7,AQ22<=20)) -> FALSE
BA23: =OR(AND(U23>0,U23<=2,AQ23>0,AQ23>12,AQ23<=17),AND(U23>0,U23>2,U23<=3,AQ23>0,AQ23>10,AQ23<=13),AND(U23>0,U23>3,U23<=5,AQ23>0,AQ23<=10),AND(U23>0,U23>5,U23<=6,AQ23>0,AQ23<=7)) -> FALSE | BB23: =OR(AND(U23>0,U23>2,U23<=3,AQ23>0,AQ23>14,AQ23<=20),AND(U23>0,U23>3,U23<=5,AQ23>0,AQ23>10),AND(U23>0,U23>5,U23<=6,AQ23>0,AQ23>7,AQ23<=20)) -> FALSE
B24: 8. | F24: =IF(E24="N.A.",0)+IF(E24="Baixo",1)+IF(E24="Moderado",2)+IF(E24="Significativo",4)+IF(E24="Alto",6) -> 0 | G24: =IF(F24>0,1,0) -> 0 | I24: =IF(H24="N.A.",0)+IF(H24="Baixo",1)+IF(H24="Moderado",2)+IF(H24="Significativo",4)+IF(H24="Alto",6) -> 0 | J24: =IF(I24>0,1,0) -> 0 | L24: =IF(K24="N.A.",0)+IF(K24="Baixo",1)+IF(K24="Moderado",2)+IF(K24="Significativo",4)+IF(K24="Alto",6) -> 0 | M24: =IF(L24>0,1,0) -> 0 | O24: =IF(N24="N.A.",0)+IF(N24="Baixo",1)+IF(N24="Moderado",2)+IF(N24="Significativo",4)+IF(N24="Alto",6) -> 0 | P24: =IF(O24>0,1,0) -> 0 | R24: =IF(Q24="N.A.",0)+IF(Q24="Baixo",1)+IF(Q24="Moderado",2)+IF(Q24="Significativo",4)+IF(Q24="Alto",6) -> 0 | S24: =IF(R24>0,1,0) -> 0 | T24: =SUM(G24,J24,M24,P24,S24) -> 0 | U24: =IFERROR(SUM(F24,I24,L24,O24,R24)/T24,0) -> 0 | AB24: =IF(W24="X",5)+IF(X24="X",4)+IF(Y24="X",3)+IF(Z24="X",2)+IF(AA24="X",1) -> 0 | AI24: =IF(AD24="X",5)+IF(AE24="X",4)+IF(AF24="X",3)+IF(AG24="X",2)+IF(AH24="X",1) -> 0 | AP24: =IF(AK24="X",5)+IF(AL24="X",4)+IF(AM24="X",3)+IF(AN24="X",2)+IF(AO24="X",1) -> 0 | AQ24: =AB24+AI24+AP24 -> 0 | AR24: =(AQ24+U24)/2 -> 0 | AS24: =IF(AT24="",0,10) -> 0 | AT24: =IF(AY24=TRUE,"Baixo",IF(AZ24=TRUE,"Médio",IF(BA24=TRUE,"Alto",IF(BB24=TRUE,"Muito Alto","")))) | AY24: =AND(U24>0,U24<=2,AQ24>0,AQ24<=7) -> FALSE | AZ24: =OR(AND(U24>0,U24<=2,AQ24>0,AQ24>7,AQ24<=13),AND(U24>0,U24>2,U24<=3,AQ24>0,AQ24<=10)) -> FALSE | BA24: =OR(AND(U24>0,U24<=2,AQ24>0,AQ24>12,AQ24<=17),AND(U24>0,U24>2,U24<=3,AQ24>0,AQ24>10,AQ24<=13),AND(U24>0,U24>3,U24<=5,AQ24>0,AQ24<=10),AND(U24>0,U24>5,U24<=6,AQ24>0,AQ24<=7)) -> FALSE | BB24: =OR(AND(U24>0,U24>2,U24<=3,AQ24>0,AQ24>14,AQ24<=20),AND(U24>0,U24>3,U24<=5,AQ24>0,AQ24>10),AND(U24>0,U24>5,U24<=6,AQ24>0,AQ24>7,AQ24<=20)) -> FALSE
BA25: =OR(AND(U25>0,U25<=2,AQ25>0,AQ25>12,AQ25<=17),AND(U25>0,U25>2,U25<=3,AQ25>0,AQ25>10,AQ25<=13),AND(U25>0,U25>3,U25<=5,AQ25>0,AQ25<=10),AND(U25>0,U25>5,U25<=6,AQ25>0,AQ25<=7)) -> FALSE | BB25: =OR(AND(U25>0,U25>2,U25<=3,AQ25>0,AQ25>14,AQ25<=20),AND(U25>0,U25>3,U25<=5,AQ25>0,AQ25>10),AND(U25>0,U25>5,U25<=6,AQ25>0,AQ25>7,AQ25<=20)) -> FALSE
B26: 9. | F26: =IF(E26="N.A.",0)+IF(E26="Baixo",1)+IF(E26="Moderado",2)+IF(E26="Significativo",4)+IF(E26="Alto",6) -> 0 | G26: =IF(F26>0,1,0) -> 0 | I26: =IF(H26="N.A.",0)+IF(H26="Baixo",1)+IF(H26="Moderado",2)+IF(H26="Significativo",4)+IF(H26="Alto",6) -> 0 | J26: =IF(I26>0,1,0) -> 0 | L26: =IF(K26="N.A.",0)+IF(K26="Baixo",1)+IF(K26="Moderado",2)+IF(K26="Significativo",4)+IF(K26="Alto",6) -> 0 | M26: =IF(L26>0,1,0) -> 0 | O26: =IF(N26="N.A.",0)+IF(N26="Baixo",1)+IF(N26="Moderado",2)+IF(N26="Significativo",4)+IF(N26="Alto",6) -> 0 | P26: =IF(O26>0,1,0) -> 0 | R26: =IF(Q26="N.A.",0)+IF(Q26="Baixo",1)+IF(Q26="Moderado",2)+IF(Q26="Significativo",4)+IF(Q26="Alto",6) -> 0 | S26: =IF(R26>0,1,0) -> 0 | T26: =SUM(G26,J26,M26,P26,S26) -> 0 | U26: =IFERROR(SUM(F26,I26,L26,O26,R26)/T26,0) -> 0 | AB26: =IF(W26="X",5)+IF(X26="X",4)+IF(Y26="X",3)+IF(Z26="X",2)+IF(AA26="X",1) -> 0 | AI26: =IF(AD26="X",5)+IF(AE26="X",4)+IF(AF26="X",3)+IF(AG26="X",2)+IF(AH26="X",1) -> 0 | AP26: =IF(AK26="X",5)+IF(AL26="X",4)+IF(AM26="X",3)+IF(AN26="X",2)+IF(AO26="X",1) -> 0 | AQ26: =AB26+AI26+AP26 -> 0 | AR26: =(AQ26+U26)/2 -> 0 | AS26: =IF(AT26="",0,10) -> 0 | AT26: =IF(AY26=TRUE,"Baixo",IF(AZ26=TRUE,"Médio",IF(BA26=TRUE,"Alto",IF(BB26=TRUE,"Muito Alto","")))) | AY26: =AND(U26>0,U26<=2,AQ26>0,AQ26<=7) -> FALSE | AZ26: =OR(AND(U26>0,U26<=2,AQ26>0,AQ26>7,AQ26<=13),AND(U26>0,U26>2,U26<=3,AQ26>0,AQ26<=10)) -> FALSE | BA26: =OR(AND(U26>0,U26<=2,AQ26>0,AQ26>12,AQ26<=17),AND(U26>0,U26>2,U26<=3,AQ26>0,AQ26>10,AQ26<=13),AND(U26>0,U26>3,U26<=5,AQ26>0,AQ26<=10),AND(U26>0,U26>5,U26<=6,AQ26>0,AQ26<=7)) -> FALSE | BB26: =OR(AND(U26>0,U26>2,U26<=3,AQ26>0,AQ26>14,AQ26<=20),AND(U26>0,U26>3,U26<=5,AQ26>0,AQ26>10),AND(U26>0,U26>5,U26<=6,AQ26>0,AQ26>7,AQ26<=20)) -> FALSE
BA27: =OR(AND(U27>0,U27<=2,AQ27>0,AQ27>12,AQ27<=17),AND(U27>0,U27>2,U27<=3,AQ27>0,AQ27>10,AQ27<=13),AND(U27>0,U27>3,U27<=5,AQ27>0,AQ27<=10),AND(U27>0,U27>5,U27<=6,AQ27>0,AQ27<=7)) -> FALSE | BB27: =OR(AND(U27>0,U27>2,U27<=3,AQ27>0,AQ27>14,AQ27<=20),AND(U27>0,U27>3,U27<=5,AQ27>0,AQ27>10),AND(U27>0,U27>5,U27<=6,AQ27>0,AQ27>7,AQ27<=20)) -> FALSE
B28: 10. | F28: =IF(E28="N.A.",0)+IF(E28="Baixo",1)+IF(E28="Moderado",2)+IF(E28="Significativo",4)+IF(E28="Alto",6) -> 0 | G28: =IF(F28>0,1,0) -> 0 | I28: =IF(H28="N.A.",0)+IF(H28="Baixo",1)+IF(H28="Moderado",2)+IF(H28="Significativo",4)+IF(H28="Alto",6) -> 0 | J28: =IF(I28>0,1,0) -> 0 | L28: =IF(K28="N.A.",0)+IF(K28="Baixo",1)+IF(K28="Moderado",2)+IF(K28="Significativo",4)+IF(K28="Alto",6) -> 0 | M28: =IF(L28>0,1,0) -> 0 | O28: =IF(N28="N.A.",0)+IF(N28="Baixo",1)+IF(N28="Moderado",2)+IF(N28="Significativo",4)+IF(N28="Alto",6) -> 0 | P28: =IF(O28>0,1,0) -> 0 | R28: =IF(Q28="N.A.",0)+IF(Q28="Baixo",1)+IF(Q28="Moderado",2)+IF(Q28="Significativo",4)+IF(Q28="Alto",6) -> 0 | S28: =IF(R28>0,1,0) -> 0 | T28: =SUM(G28,J28,M28,P28,S28) -> 0 | U28: =IFERROR(SUM(F28,I28,L28,O28,R28)/T28,0) -> 0 | AB28: =IF(W28="X",5)+IF(X28="X",4)+IF(Y28="X",3)+IF(Z28="X",2)+IF(AA28="X",1) -> 0 | AI28: =IF(AD28="X",5)+IF(AE28="X",4)+IF(AF28="X",3)+IF(AG28="X",2)+IF(AH28="X",1) -> 0 | AP28: =IF(AK28="X",5)+IF(AL28="X",4)+IF(AM28="X",3)+IF(AN28="X",2)+IF(AO28="X",1) -> 0 | AQ28: =AB28+AI28+AP28 -> 0 | AR28: =(AQ28+U28)/2 -> 0 | AS28: =IF(AT28="",0,10) -> 0 | AT28: =IF(AY28=TRUE,"Baixo",IF(AZ28=TRUE,"Médio",IF(BA28=TRUE,"Alto",IF(BB28=TRUE,"Muito Alto","")))) | AY28: =AND(U28>0,U28<=2,AQ28>0,AQ28<=7) -> FALSE | AZ28: =OR(AND(U28>0,U28<=2,AQ28>0,AQ28>7,AQ28<=13),AND(U28>0,U28>2,U28<=3,AQ28>0,AQ28<=10)) -> FALSE | BA28: =OR(AND(U28>0,U28<=2,AQ28>0,AQ28>12,AQ28<=17),AND(U28>0,U28>2,U28<=3,AQ28>0,AQ28>10,AQ28<=13),AND(U28>0,U28>3,U28<=5,AQ28>0,AQ28<=10),AND(U28>0,U28>5,U28<=6,AQ28>0,AQ28<=7)) -> FALSE | BB28: =OR(AND(U28>0,U28>2,U28<=3,AQ28>0,AQ28>14,AQ28<=20),AND(U28>0,U28>3,U28<=5,AQ28>0,AQ28>10),AND(U28>0,U28>5,U28<=6,AQ28>0,AQ28>7,AQ28<=20)) -> FALSE
BA29: =OR(AND(U29>0,U29<=2,AQ29>0,AQ29>12,AQ29<=17),AND(U29>0,U29>2,U29<=3,AQ29>0,AQ29>10,AQ29<=13),AND(U29>0,U29>3,U29<=5,AQ29>0,AQ29<=10),AND(U29>0,U29>5,U29<=6,AQ29>0,AQ29<=7)) -> FALSE | BB29: =OR(AND(U29>0,U29>2,U29<=3,AQ29>0,AQ29>14,AQ29<=20),AND(U29>0,U29>3,U29<=5,AQ29>0,AQ29>10),AND(U29>0,U29>5,U29<=6,AQ29>0,AQ29>7,AQ29<=20)) -> FALSE
B30: 11. | F30: =IF(E30="N.A.",0)+IF(E30="Baixo",1)+IF(E30="Moderado",2)+IF(E30="Significativo",4)+IF(E30="Alto",6) -> 0 | G30: =IF(F30>0,1,0) -> 0 | I30: =IF(H30="N.A.",0)+IF(H30="Baixo",1)+IF(H30="Moderado",2)+IF(H30="Significativo",4)+IF(H30="Alto",6) -> 0 | J30: =IF(I30>0,1,0) -> 0 | L30: =IF(K30="N.A.",0)+IF(K30="Baixo",1)+IF(K30="Moderado",2)+IF(K30="Significativo",4)+IF(K30="Alto",6) -> 0 | M30: =IF(L30>0,1,0) -> 0 | O30: =IF(N30="N.A.",0)+IF(N30="Baixo",1)+IF(N30="Moderado",2)+IF(N30="Significativo",4)+IF(N30="Alto",6) -> 0 | P30: =IF(O30>0,1,0) -> 0 | R30: =IF(Q30="N.A.",0)+IF(Q30="Baixo",1)+IF(Q30="Moderado",2)+IF(Q30="Significativo",4)+IF(Q30="Alto",6) -> 0 | S30: =IF(R30>0,1,0) -> 0 | T30: =SUM(G30,J30,M30,P30,S30) -> 0 | U30: =IFERROR(SUM(F30,I30,L30,O30,R30)/T30,0) -> 0 | AB30: =IF(W30="X",5)+IF(X30="X",4)+IF(Y30="X",3)+IF(Z30="X",2)+IF(AA30="X",1) -> 0 | AI30: =IF(AD30="X",5)+IF(AE30="X",4)+IF(AF30="X",3)+IF(AG30="X",2)+IF(AH30="X",1) -> 0 | AP30: =IF(AK30="X",5)+IF(AL30="X",4)+IF(AM30="X",3)+IF(AN30="X",2)+IF(AO30="X",1) -> 0 | AQ30: =AB30+AI30+AP30 -> 0 | AR30: =(AQ30+U30)/2 -> 0 | AS30: =IF(AT30="",0,10) -> 0 | AT30: =IF(AY30=TRUE,"Baixo",IF(AZ30=TRUE,"Médio",IF(BA30=TRUE,"Alto",IF(BB30=TRUE,"Muito Alto","")))) | AY30: =AND(U30>0,U30<=2,AQ30>0,AQ30<=7) -> FALSE | AZ30: =OR(AND(U30>0,U30<=2,AQ30>0,AQ30>7,AQ30<=13),AND(U30>0,U30>2,U30<=3,AQ30>0,AQ30<=10)) -> FALSE | BA30: =OR(AND(U30>0,U30<=2,AQ30>0,AQ30>12,AQ30<=17),AND(U30>0,U30>2,U30<=3,AQ30>0,AQ30>10,AQ30<=13),AND(U30>0,U30>3,U30<=5,AQ30>0,AQ30<=10),AND(U30>0,U30>5,U30<=6,AQ30>0,AQ30<=7)) -> FALSE | BB30: =OR(AND(U30>0,U30>2,U30<=3,AQ30>0,AQ30>14,AQ30<=20),AND(U30>0,U30>3,U30<=5,AQ30>0,AQ30>10),AND(U30>0,U30>5,U30<=6,AQ30>0,AQ30>7,AQ30<=20)) -> FALSE
BA31: =OR(AND(U31>0,U31<=2,AQ31>0,AQ31>12,AQ31<=17),AND(U31>0,U31>2,U31<=3,AQ31>0,AQ31>10,AQ31<=13),AND(U31>0,U31>3,U31<=5,AQ31>0,AQ31<=10),AND(U31>0,U31>5,U31<=6,AQ31>0,AQ31<=7)) -> FALSE | BB31: =OR(AND(U31>0,U31>2,U31<=3,AQ31>0,AQ31>14,AQ31<=20),AND(U31>0,U31>3,U31<=5,AQ31>0,AQ31>10),AND(U31>0,U31>5,U31<=6,AQ31>0,AQ31>7,AQ31<=20)) -> FALSE
B32: 12. | F32: =IF(E32="N.A.",0)+IF(E32="Baixo",1)+IF(E32="Moderado",2)+IF(E32="Significativo",4)+IF(E32="Alto",6) -> 0 | G32: =IF(F32>0,1,0) -> 0 | I32: =IF(H32="N.A.",0)+IF(H32="Baixo",1)+IF(H32="Moderado",2)+IF(H32="Significativo",4)+IF(H32="Alto",6) -> 0 | J32: =IF(I32>0,1,0) -> 0 | L32: =IF(K32="N.A.",0)+IF(K32="Baixo",1)+IF(K32="Moderado",2)+IF(K32="Significativo",4)+IF(K32="Alto",6) -> 0 | M32: =IF(L32>0,1,0) -> 0 | O32: =IF(N32="N.A.",0)+IF(N32="Baixo",1)+IF(N32="Moderado",2)+IF(N32="Significativo",4)+IF(N32="Alto",6) -> 0 | P32: =IF(O32>0,1,0) -> 0 | R32: =IF(Q32="N.A.",0)+IF(Q32="Baixo",1)+IF(Q32="Moderado",2)+IF(Q32="Significativo",4)+IF(Q32="Alto",6) -> 0 | S32: =IF(R32>0,1,0) -> 0 | T32: =SUM(G32,J32,M32,P32,S32) -> 0 | U32: =IFERROR(SUM(F32,I32,L32,O32,R32)/T32,0) -> 0 | AB32: =IF(W32="X",5)+IF(X32="X",4)+IF(Y32="X",3)+IF(Z32="X",2)+IF(AA32="X",1) -> 0 | AI32: =IF(AD32="X",5)+IF(AE32="X",4)+IF(AF32="X",3)+IF(AG32="X",2)+IF(AH32="X",1) -> 0 | AP32: =IF(AK32="X",5)+IF(AL32="X",4)+IF(AM32="X",3)+IF(AN32="X",2)+IF(AO32="X",1) -> 0 | AQ32: =AB32+AI32+AP32 -> 0 | AR32: =(AQ32+U32)/2 -> 0 | AS32: =IF(AT32="",0,10) -> 0 | AT32: =IF(AY32=TRUE,"Baixo",IF(AZ32=TRUE,"Médio",IF(BA32=TRUE,"Alto",IF(BB32=TRUE,"Muito Alto","")))) | AY32: =AND(U32>0,U32<=2,AQ32>0,AQ32<=7) -> FALSE | AZ32: =OR(AND(U32>0,U32<=2,AQ32>0,AQ32>7,AQ32<=13),AND(U32>0,U32>2,U32<=3,AQ32>0,AQ32<=10)) -> FALSE | BA32: =OR(AND(U32>0,U32<=2,AQ32>0,AQ32>12,AQ32<=17),AND(U32>0,U32>2,U32<=3,AQ32>0,AQ32>10,AQ32<=13),AND(U32>0,U32>3,U32<=5,AQ32>0,AQ32<=10),AND(U32>0,U32>5,U32<=6,AQ32>0,AQ32<=7)) -> FALSE | BB32: =OR(AND(U32>0,U32>2,U32<=3,AQ32>0,AQ32>14,AQ32<=20),AND(U32>0,U32>3,U32<=5,AQ32>0,AQ32>10),AND(U32>0,U32>5,U32<=6,AQ32>0,AQ32>7,AQ32<=20)) -> FALSE
BA33: =OR(AND(U33>0,U33<=2,AQ33>0,AQ33>12,AQ33<=17),AND(U33>0,U33>2,U33<=3,AQ33>0,AQ33>10,AQ33<=13),AND(U33>0,U33>3,U33<=5,AQ33>0,AQ33<=10),AND(U33>0,U33>5,U33<=6,AQ33>0,AQ33<=7)) -> FALSE | BB33: =OR(AND(U33>0,U33>2,U33<=3,AQ33>0,AQ33>14,AQ33<=20),AND(U33>0,U33>3,U33<=5,AQ33>0,AQ33>10),AND(U33>0,U33>5,U33<=6,AQ33>0,AQ33>7,AQ33<=20)) -> FALSE
B34: 13. | F34: =IF(E34="N.A.",0)+IF(E34="Baixo",1)+IF(E34="Moderado",2)+IF(E34="Significativo",4)+IF(E34="Alto",6) -> 0 | G34: =IF(F34>0,1,0) -> 0 | I34: =IF(H34="N.A.",0)+IF(H34="Baixo",1)+IF(H34="Moderado",2)+IF(H34="Significativo",4)+IF(H34="Alto",6) -> 0 | J34: =IF(I34>0,1,0) -> 0 | L34: =IF(K34="N.A.",0)+IF(K34="Baixo",1)+IF(K34="Moderado",2)+IF(K34="Significativo",4)+IF(K34="Alto",6) -> 0 | M34: =IF(L34>0,1,0) -> 0 | O34: =IF(N34="N.A.",0)+IF(N34="Baixo",1)+IF(N34="Moderado",2)+IF(N34="Significativo",4)+IF(N34="Alto",6) -> 0 | P34: =IF(O34>0,1,0) -> 0 | R34: =IF(Q34="N.A.",0)+IF(Q34="Baixo",1)+IF(Q34="Moderado",2)+IF(Q34="Significativo",4)+IF(Q34="Alto",6) -> 0 | S34: =IF(R34>0,1,0) -> 0 | T34: =SUM(G34,J34,M34,P34,S34) -> 0 | U34: =IFERROR(SUM(F34,I34,L34,O34,R34)/T34,0) -> 0 | AB34: =IF(W34="X",5)+IF(X34="X",4)+IF(Y34="X",3)+IF(Z34="X",2)+IF(AA34="X",1) -> 0 | AI34: =IF(AD34="X",5)+IF(AE34="X",4)+IF(AF34="X",3)+IF(AG34="X",2)+IF(AH34="X",1) -> 0 | AP34: =IF(AK34="X",5)+IF(AL34="X",4)+IF(AM34="X",3)+IF(AN34="X",2)+IF(AO34="X",1) -> 0 | AQ34: =AB34+AI34+AP34 -> 0 | AR34: =(AQ34+U34)/2 -> 0 | AS34: =IF(AT34="",0,10) -> 0 | AT34: =IF(AY34=TRUE,"Baixo",IF(AZ34=TRUE,"Médio",IF(BA34=TRUE,"Alto",IF(BB34=TRUE,"Muito Alto","")))) | AY34: =AND(U34>0,U34<=2,AQ34>0,AQ34<=7) -> FALSE | AZ34: =OR(AND(U34>0,U34<=2,AQ34>0,AQ34>7,AQ34<=13),AND(U34>0,U34>2,U34<=3,AQ34>0,AQ34<=10)) -> FALSE | BA34: =OR(AND(U34>0,U34<=2,AQ34>0,AQ34>12,AQ34<=17),AND(U34>0,U34>2,U34<=3,AQ34>0,AQ34>10,AQ34<=13),AND(U34>0,U34>3,U34<=5,AQ34>0,AQ34<=10),AND(U34>0,U34>5,U34<=6,AQ34>0,AQ34<=7)) -> FALSE | BB34: =OR(AND(U34>0,U34>2,U34<=3,AQ34>0,AQ34>14,AQ34<=20),AND(U34>0,U34>3,U34<=5,AQ34>0,AQ34>10),AND(U34>0,U34>5,U34<=6,AQ34>0,AQ34>7,AQ34<=20)) -> FALSE
BA35: =OR(AND(U35>0,U35<=2,AQ35>0,AQ35>12,AQ35<=17),AND(U35>0,U35>2,U35<=3,AQ35>0,AQ35>10,AQ35<=13),AND(U35>0,U35>3,U35<=5,AQ35>0,AQ35<=10),AND(U35>0,U35>5,U35<=6,AQ35>0,AQ35<=7)) -> FALSE | BB35: =OR(AND(U35>0,U35>2,U35<=3,AQ35>0,AQ35>14,AQ35<=20),AND(U35>0,U35>3,U35<=5,AQ35>0,AQ35>10),AND(U35>0,U35>5,U35<=6,AQ35>0,AQ35>7,AQ35<=20)) -> FALSE
B36: 14. | F36: =IF(E36="N.A.",0)+IF(E36="Baixo",1)+IF(E36="Moderado",2)+IF(E36="Significativo",4)+IF(E36="Alto",6) -> 0 | G36: =IF(F36>0,1,0) -> 0 | I36: =IF(H36="N.A.",0)+IF(H36="Baixo",1)+IF(H36="Moderado",2)+IF(H36="Significativo",4)+IF(H36="Alto",6) -> 0 | J36: =IF(I36>0,1,0) -> 0 | L36: =IF(K36="N.A.",0)+IF(K36="Baixo",1)+IF(K36="Moderado",2)+IF(K36="Significativo",4)+IF(K36="Alto",6) -> 0 | M36: =IF(L36>0,1,0) -> 0 | O36: =IF(N36="N.A.",0)+IF(N36="Baixo",1)+IF(N36="Moderado",2)+IF(N36="Significativo",4)+IF(N36="Alto",6) -> 0 | P36: =IF(O36>0,1,0) -> 0 | R36: =IF(Q36="N.A.",0)+IF(Q36="Baixo",1)+IF(Q36="Moderado",2)+IF(Q36="Significativo",4)+IF(Q36="Alto",6) -> 0 | S36: =IF(R36>0,1,0) -> 0 | T36: =SUM(G36,J36,M36,P36,S36) -> 0 | U36: =IFERROR(SUM(F36,I36,L36,O36,R36)/T36,0) -> 0 | AB36: =IF(W36="X",5)+IF(X36="X",4)+IF(Y36="X",3)+IF(Z36="X",2)+IF(AA36="X",1) -> 0 | AI36: =IF(AD36="X",5)+IF(AE36="X",4)+IF(AF36="X",3)+IF(AG36="X",2)+IF(AH36="X",1) -> 0 | AP36: =IF(AK36="X",5)+IF(AL36="X",4)+IF(AM36="X",3)+IF(AN36="X",2)+IF(AO36="X",1) -> 0 | AQ36: =AB36+AI36+AP36 -> 0 | AR36: =(AQ36+U36)/2 -> 0 | AS36: =IF(AT36="",0,10) -> 0 | AT36: =IF(AY36=TRUE,"Baixo",IF(AZ36=TRUE,"Médio",IF(BA36=TRUE,"Alto",IF(BB36=TRUE,"Muito Alto","")))) | AY36: =AND(U36>0,U36<=2,AQ36>0,AQ36<=7) -> FALSE | AZ36: =OR(AND(U36>0,U36<=2,AQ36>0,AQ36>7,AQ36<=13),AND(U36>0,U36>2,U36<=3,AQ36>0,AQ36<=10)) -> FALSE | BA36: =OR(AND(U36>0,U36<=2,AQ36>0,AQ36>12,AQ36<=17),AND(U36>0,U36>2,U36<=3,AQ36>0,AQ36>10,AQ36<=13),AND(U36>0,U36>3,U36<=5,AQ36>0,AQ36<=10),AND(U36>0,U36>5,U36<=6,AQ36>0,AQ36<=7)) -> FALSE | BB36: =OR(AND(U36>0,U36>2,U36<=3,AQ36>0,AQ36>14,AQ36<=20),AND(U36>0,U36>3,U36<=5,AQ36>0,AQ36>10),AND(U36>0,U36>5,U36<=6,AQ36>0,AQ36>7,AQ36<=20)) -> FALSE
BA37: =OR(AND(U37>0,U37<=2,AQ37>0,AQ37>12,AQ37<=17),AND(U37>0,U37>2,U37<=3,AQ37>0,AQ37>10,AQ37<=13),AND(U37>0,U37>3,U37<=5,AQ37>0,AQ37<=10),AND(U37>0,U37>5,U37<=6,AQ37>0,AQ37<=7)) -> FALSE | BB37: =OR(AND(U37>0,U37>2,U37<=3,AQ37>0,AQ37>14,AQ37<=20),AND(U37>0,U37>3,U37<=5,AQ37>0,AQ37>10),AND(U37>0,U37>5,U37<=6,AQ37>0,AQ37>7,AQ37<=20)) -> FALSE
B38: 15. | F38: =IF(E38="N.A.",0)+IF(E38="Baixo",1)+IF(E38="Moderado",2)+IF(E38="Significativo",4)+IF(E38="Alto",6) -> 0 | G38: =IF(F38>0,1,0) -> 0 | I38: =IF(H38="N.A.",0)+IF(H38="Baixo",1)+IF(H38="Moderado",2)+IF(H38="Significativo",4)+IF(H38="Alto",6) -> 0 | J38: =IF(I38>0,1,0) -> 0 | L38: =IF(K38="N.A.",0)+IF(K38="Baixo",1)+IF(K38="Moderado",2)+IF(K38="Significativo",4)+IF(K38="Alto",6) -> 0 | M38: =IF(L38>0,1,0) -> 0 | O38: =IF(N38="N.A.",0)+IF(N38="Baixo",1)+IF(N38="Moderado",2)+IF(N38="Significativo",4)+IF(N38="Alto",6) -> 0 | P38: =IF(O38>0,1,0) -> 0 | R38: =IF(Q38="N.A.",0)+IF(Q38="Baixo",1)+IF(Q38="Moderado",2)+IF(Q38="Significativo",4)+IF(Q38="Alto",6) -> 0 | S38: =IF(R38>0,1,0) -> 0 | T38: =SUM(G38,J38,M38,P38,S38) -> 0 | U38: =IFERROR(SUM(F38,I38,L38,O38,R38)/T38,0) -> 0 | AB38: =IF(W38="X",5)+IF(X38="X",4)+IF(Y38="X",3)+IF(Z38="X",2)+IF(AA38="X",1) -> 0 | AI38: =IF(AD38="X",5)+IF(AE38="X",4)+IF(AF38="X",3)+IF(AG38="X",2)+IF(AH38="X",1) -> 0 | AP38: =IF(AK38="X",5)+IF(AL38="X",4)+IF(AM38="X",3)+IF(AN38="X",2)+IF(AO38="X",1) -> 0 | AQ38: =AB38+AI38+AP38 -> 0 | AR38: =(AQ38+U38)/2 -> 0 | AS38: =IF(AT38="",0,10) -> 0 | AT38: =IF(AY38=TRUE,"Baixo",IF(AZ38=TRUE,"Médio",IF(BA38=TRUE,"Alto",IF(BB38=TRUE,"Muito Alto","")))) | AY38: =AND(U38>0,U38<=2,AQ38>0,AQ38<=7) -> FALSE | AZ38: =OR(AND(U38>0,U38<=2,AQ38>0,AQ38>7,AQ38<=13),AND(U38>0,U38>2,U38<=3,AQ38>0,AQ38<=10)) -> FALSE | BA38: =OR(AND(U38>0,U38<=2,AQ38>0,AQ38>12,AQ38<=17),AND(U38>0,U38>2,U38<=3,AQ38>0,AQ38>10,AQ38<=13),AND(U38>0,U38>3,U38<=5,AQ38>0,AQ38<=10),AND(U38>0,U38>5,U38<=6,AQ38>0,AQ38<=7)) -> FALSE | BB38: =OR(AND(U38>0,U38>2,U38<=3,AQ38>0,AQ38>14,AQ38<=20),AND(U38>0,U38>3,U38<=5,AQ38>0,AQ38>10),AND(U38>0,U38>5,U38<=6,AQ38>0,AQ38>7,AQ38<=20)) -> FALSE
BA39: =OR(AND(U39>0,U39<=2,AQ39>0,AQ39>12,AQ39<=17),AND(U39>0,U39>2,U39<=3,AQ39>0,AQ39>10,AQ39<=13),AND(U39>0,U39>3,U39<=5,AQ39>0,AQ39<=10),AND(U39>0,U39>5,U39<=6,AQ39>0,AQ39<=7)) -> FALSE | BB39: =OR(AND(U39>0,U39>2,U39<=3,AQ39>0,AQ39>14,AQ39<=20),AND(U39>0,U39>3,U39<=5,AQ39>0,AQ39>10),AND(U39>0,U39>5,U39<=6,AQ39>0,AQ39>7,AQ39<=20)) -> FALSE

Sheet Ações - Oportunidades-CANTU
B2: Ações para tratar oportunidades
C6: Identificação das Oportunidades | F6: BOM/RO/GR | H6: Responsável | J6: Ações / Monitoramento
B7: Item
B10: 1. | C10: ='[1] Aval.Oportunidades-CANTU'!C10 -> Expansão/aumento de faturamento na captação de Novos Negocios | F10: GR 178 / 179 | H10: Ana Cristina | J10: Ações de monitoramento evidenciadas conforme GR 178/179 no SIGO
B14: 2. | C14: ='[1] Aval.Oportunidades-CANTU'!C12 -> 0
B18: 3.
B22: 4.
B26: 5.
B30: 6.
B34: 7.
B38: 8.
B42: 9.
B46: 10.

Sheet SWOT
A1: EXTERNOS | C1: INTERNOS
A2: AMEAÇAS | B2: OPORTUNIDADES | C2: FORÇAS | D2: FRAQUEZAS
A3: Indefinições de projetos e soluções | B3: Aumento de número de obras terceiro para portfolio | C3: Solidez e credibilidade do grupo | D3: Obra com controle no sistema de gestão do cliente - SIENGE
A4: Reorçamento de obra pra definição taxa F2 | B4: Aumento de receita que proporciona uma diluição do custo fixo da construtora | C4: Equipe engenharia estruturada demonstrou confiança ao cliente | D4: Desorganização estrutura AG7 (monitorar atrasos NFs, etc)
C5: Contrato por adm, sem performance! Fugimos da disputa por preço, valorização do conhecimento
C6: Duas obras mesmo cliente
C7: Duas obras emblemáticas

Sheet Riscos-PIEMONTE
E1: Matriz de Avaliação e Gestão de Riscos - 2022
E4: PLATEA 19
B6: Item | C6: Riscos | E6: Avaliação de Impacto | W6: Avaliação do Controle (Probabilidade) | AS6: Significância | AU6: Estratégia
B7: Item | E7: Financeiro | F7: Pontos | G7: Inf. Média | H7: Legal | I7: Pontos | J7: Inf. Média | K7: Imagem | L7: Pontos | M7: Inf. Média | N7: Direcionamento Estratégico | O7: Pontos | P7: Inf. Média | Q7: Operação | R7: Pontos | S7: Inf. Média | W7: Características | AA7: Pontos | AC7: Tipo | AF7: Pontos | AH7: Histórico de Ocorrência | AN7: Pontos
U8: Impacto | W8: Controle-chave efetivo | X8: Controle Compensatório efetivo | Y8: Controle compensatório Não Efetivo | Z8: Controle Inexistente | AC8: Automatizado | AD8: Manual | AE8: Nenhum | AH8: Anual | AI8: Trimestral | AJ8: Mensal | AK8: Semanal | AL8: Diário | AM8: Mais de uma vez ao dia | AP8: Probabilidade | AQ8: Média | AX8: Desprezível | AY8: Administrável | AZ8: Indesejável | BA8: Intolerável
B10: 1. | C10: =SWOT!A3 -> Indefinições de projetos e soluções | E10: Baixo | F10: =IF(E10="N.A.",0)+IF(E10="Baixo",1)+IF(E10="Moderado",2)+IF(E10="Significativo",4)+IF(E10="Alto",6) -> 1 | G10: =IF(F10>0,1,0) -> 1 | H10: Baixo | I10: =IF(H10="N.A.",0)+IF(H10="Baixo",1)+IF(H10="Moderado",2)+IF(H10="Significativo",4)+IF(H10="Alto",6) -> 1 | J10: =IF(I10>0,1,0) -> 1 | K10: Significativo | L10: =IF(K10="N.A.",0)+IF(K10="Baixo",1)+IF(K10="Moderado",2)+IF(K10="Significativo",4)+IF(K10="Alto",6) -> 4 | M10: =IF(L10>0,1,0) -> 1 | N10: Significativo | O10: =IF(N10="N.A.",0)+IF(N10="Baixo",1)+IF(N10="Moderado",2)+IF(N10="Significativo",4)+IF(N10="Alto",6) -> 4 | P10: =IF(O10>0,1,0) -> 1 | Q10: Significativo | R10: =IF(Q10="N.A.",0)+IF(Q10="Baixo",1)+IF(Q10="Moderado",2)+IF(Q10="Significativo",4)+IF(Q10="Alto",6) -> 4 | S10: =IF(R10>0,1,0) -> 1 | T10: =SUM(G10,J10,M10,P10,S10) -> 5 | U10: =IFERROR(SUM(F10,I10,L10,O10,R10)/T10,0) -> 2.8 | W10: X | AA10: =IF(W10="X",-1)+IF(X10="X",2)+IF(Y10="X",4)+IF(Z10="X",9) -> -1 | AD10: X | AF10: =IF(AC10="X",1)+IF(AD10="X",2)+IF(AE10="X",5) -> 2 | AK10: X | AN10: =IF(AH10="X",1)+IF(AI10="X",2)+IF(AJ10="X",3)+IF(AK10="X",4)+IF(AL10="X",5)+IF(AM10="X",6) -> 4 | AP10: =AA10+AF10+AN10 -> 5 | AQ10: =(AP10+U10)/2 -> 3.9 | AR10: =IF(AS10="",0,10) -> 10 | AS10: =IF(AX10=TRUE,"Desprezível",IF(AY10=TRUE,"Administrável",IF(AZ10=TRUE,"Indesejável",IF(BA10=TRUE,"Intolerável","")))) -> Administrável | AU10: Mitigar | AW10: N.A. | AX10: =AND(U10>0,U10<=2,AP10>0,AP10<=7) -> FALSE | AY10: =OR(AND(U10>0,U10<=2,AP10>0,AP10>7,AP10<=13),AND(U10>0,U10>2,U10<=3,AP10>0,AP10<=10)) -> TRUE | AZ10: =OR(AND(U10>0,U10<=2,AP10>0,AP10>12,AP10<=17),AND(U10>0,U10>2,U10<=3,AP10>0,AP10>10,AP10<=13),AND(U10>0,U10>3,U10<=5,AP10>0,AP10<=10),AND(U10>0,U10>4,U10<=6,AP10>0,AP10<=7)) -> FALSE | BA10: =OR(AND(U10>0,U10>2,U10<=3,AP10>0,AP10>14,AP10<=20),AND(U10>0,U10>3,U10<=5,AP10>0,AP10>10),AND(U10>0,U10>5,U10<=6,AP10>0,AP10>7,AP10<=20)) -> FALSE | BC10: N.A.
I11: =IF(H11="N.A.",0)+IF(H11="Baixo",1)+IF(H11="Moderado",2)+IF(H11="Significativo",4)+IF(H11="Alto",6) -> 0 | J11: =IF(I11>0,1,0) -> 0 | L11: =IF(K11="N.A.",0)+IF(K11="Baixo",1)+IF(K11="Moderado",2)+IF(K11="Significativo",4)+IF(K11="Alto",6) -> 0 | R11: =IF(Q11="N.A.",0)+IF(Q11="Baixo",1)+IF(Q11="Moderado",2)+IF(Q11="Significativo",4)+IF(Q11="Alto",6) -> 0 | S11: =IF(R11>0,1,0) -> 0 | T11: =SUM(G11,J11,M11,P11,S11) -> 0 | U11: =IFERROR(SUM(F11,I11,L11,O11,R11)/T11,0) -> 0 | AF11: =IF(AC11="X",1)+IF(AD11="X",2)+IF(AE11="X",5) -> 0 | AW11: Baixo | AZ11: =OR(AND(U11>0,U11<=2,AP11>0,AP11>12,AP11<=17),AND(U11>0,U11>2,U11<=3,AP11>0,AP11>10,AP11<=13),AND(U11>0,U11>3,U11<=5,AP11>0,AP11<=10),AND(U11>0,U11>4,U11<=6,AP11>0,AP11<=7)) -> FALSE | BA11: =OR(AND(U11>0,U11>2,U11<=3,AP11>0,AP11>14,AP11<=20),AND(U11>0,U11>3,U11<=5,AP11>0,AP11>10),AND(U11>0,U11>5,U11<=6,AP11>0,AP11>7,AP11<=20)) -> FALSE | BC11: Baixo
B12: 2. | C12: =SWOT!D3 -> Obra com controle no sistema de gestão do cliente - SIENGE | E12: Baixo | F12: =IF(E12="N.A.",0)+IF(E12="Baixo",1)+IF(E12="Moderado",2)+IF(E12="Significativo",4)+IF(E12="Alto",6) -> 1 | G12: =IF(F12>0,1,0) -> 1 | H12: Baixo | I12: =IF(H12="N.A.",0)+IF(H12="Baixo",1)+IF(H12="Moderado",2)+IF(H12="Significativo",4)+IF(H12="Alto",6) -> 1 | J12: =IF(I12>0,1,0) -> 1 | K12: Baixo | L12: =IF(K12="N.A.",0)+IF(K12="Baixo",1)+IF(K12="Moderado",2)+IF(K12="Significativo",4)+IF(K12="Alto",6) -> 1 | M12: =IF(L12>0,1,0) -> 1 | N12: Moderado | O12: =IF(N12="N.A.",0)+IF(N12="Baixo",1)+IF(N12="Moderado",2)+IF(N12="Significativo",4)+IF(N12="Alto",6) -> 2 | P12: =IF(O12>0,1,0) -> 1 | Q12: Alto | R12: =IF(Q12="N.A.",0)+IF(Q12="Baixo",1)+IF(Q12="Moderado",2)+IF(Q12="Significativo",4)+IF(Q12="Alto",6) -> 6 | S12: =IF(R12>0,1,0) -> 1 | T12: =SUM(G12,J12,M12,P12,S12) -> 5 | U12: =IFERROR(SUM(F12,I12,L12,O12,R12)/T12,0) -> 2.2 | X12: X | AA12: =IF(W12="X",-1)+IF(X12="X",2)+IF(Y12="X",4)+IF(Z12="X",9) -> 2 | AD12: X | AF12: =IF(AC12="X",1)+IF(AD12="X",2)+IF(AE12="X",5) -> 2 | AL12: X | AN12: =IF(AH12="X",1)+IF(AI12="X",2)+IF(AJ12="X",3)+IF(AK12="X",4)+IF(AL12="X",5)+IF(AM12="X",6) -> 5 | AP12: =AA12+AF12+AN12 -> 9 | AQ12: =(AP12+U12)/2 -> 5.6 | AR12: =IF(AS12="",0,10) -> 10 | AS12: =IF(AX12=TRUE,"Desprezível",IF(AY12=TRUE,"Administrável",IF(AZ12=TRUE,"Indesejável",IF(BA12=TRUE,"Intolerável","")))) -> Administrável | AU12: Aceitar | AW12: Moderado | AX12: =AND(U12>0,U12<=2,AP12>0,AP12<=7) -> FALSE | AY12: =OR(AND(U12>0,U12<=2,AP12>0,AP12>7,AP12<=13),AND(U12>0,U12>2,U12<=3,AP12>0,AP12<=10)) -> TRUE | AZ12: =OR(AND(U12>0,U12<=2,AP12>0,AP12>12,AP12<=17),AND(U12>0,U12>2,U12<=3,AP12>0,AP12>10,AP12<=13),AND(U12>0,U12>3,U12<=5,AP12>0,AP12<=10),AND(U12>0,U12>4,U12<=6,AP12>0,AP12<=7)) -> FALSE | BA12: =OR(AND(U12>0,U12>2,U12<=3,AP12>0,AP12>14,AP12<=20),AND(U12>0,U12>3,U12<=5,AP12>0,AP12>10),AND(U12>0,U12>5,U12<=6,AP12>0,AP12>7,AP12<=20)) -> FALSE | BC12: Moderado
F13: =IF(E13="N.A.",0)+IF(E13="Baixo",1)+IF(E13="Moderado",2)+IF(E13="Significativo",4)+IF(E13="Alto",6) -> 0 | G13: =IF(F13>0,1,0) -> 0 | I13: =IF(H13="N.A.",0)+IF(H13="Baixo",1)+IF(H13="Moderado",2)+IF(H13="Significativo",4)+IF(H13="Alto",6) -> 0 | J13: =IF(I13>0,1,0) -> 0 | L13: =IF(K13="N.A.",0)+IF(K13="Baixo",1)+IF(K13="Moderado",2)+IF(K13="Significativo",4)+IF(K13="Alto",6) -> 0 | R13: =IF(Q13="N.A.",0)+IF(Q13="Baixo",1)+IF(Q13="Moderado",2)+IF(Q13="Significativo",4)+IF(Q13="Alto",6) -> 0 | S13: =IF(R13>0,1,0) -> 0 | T13: =SUM(G13,J13,M13,P13,S13) -> 0 | U13: =IFERROR(SUM(F13,I13,L13,O13,R13)/T13,0) -> 0 | AF13: =IF(AC13="X",1)+IF(AD13="X",2)+IF(AE13="X",5) -> 0 | AW13: Significativo | AZ13: =OR(AND(U13>0,U13<=2,AP13>0,AP13>12,AP13<=17),AND(U13>0,U13>2,U13<=3,AP13>0,AP13>10,AP13<=13),AND(U13>0,U13>3,U13<=5,AP13>0,AP13<=10),AND(U13>0,U13>4,U13<=6,AP13>0,AP13<=7)) -> FALSE | BA13: =OR(AND(U13>0,U13>2,U13<=3,AP13>0,AP13>14,AP13<=20),AND(U13>0,U13>3,U13<=5,AP13>0,AP13>10),AND(U13>0,U13>5,U13<=6,AP13>0,AP13>7,AP13<=20)) -> FALSE | BC13: Significativo
B14: 3. | C14: =SWOT!D4 -> Desorganização estrutura AG7 (monitorar atrasos NFs, etc) | E14: Baixo | F14: =IF(E14="N.A.",0)+IF(E14="Baixo",1)+IF(E14="Moderado",2)+IF(E14="Significativo",4)+IF(E14="Alto",6) -> 1 | G14: =IF(F14>0,1,0) -> 1 | H14: Baixo | I14: =IF(H14="N.A.",0)+IF(H14="Baixo",1)+IF(H14="Moderado",2)+IF(H14="Significativo",4)+IF(H14="Alto",6) -> 1 | J14: =IF(I14>0,1,0) -> 1 | K14: Moderado | L14: =IF(K14="N.A.",0)+IF(K14="Baixo",1)+IF(K14="Moderado",2)+IF(K14="Significativo",4)+IF(K14="Alto",6) -> 2 | M14: =IF(L14>0,1,0) -> 1 | N14: Baixo | O14: =IF(N14="N.A.",0)+IF(N14="Baixo",1)+IF(N14="Moderado",2)+IF(N14="Significativo",4)+IF(N14="Alto",6) -> 1 | P14: =IF(O14>0,1,0) -> 1 | Q14: Baixo | R14: =IF(Q14="N.A.",0)+IF(Q14="Baixo",1)+IF(Q14="Moderado",2)+IF(Q14="Significativo",4)+IF(Q14="Alto",6) -> 1 | S14: =IF(R14>0,1,0) -> 1 | T14: =SUM(G14,J14,M14,P14,S14) -> 5 | U14: =IFERROR(SUM(F14,I14,L14,O14,R14)/T14,0) -> 1.2 | X14: x | AA14: =IF(W14="X",0)+IF(X14="X",2)+IF(Y14="X",4)+IF(Z14="X",9) -> 2 | AD14: X | AF14: =IF(AC14="X",1)+IF(AD14="X",2)+IF(AE14="X",5) -> 2 | AL14: X | AN14: =IF(AH14="X",1)+IF(AI14="X",2)+IF(AJ14="X",3)+IF(AK14="X",4)+IF(AL14="X",5)+IF(AM14="X",6) -> 5 | AP14: =AA14+AF14+AN14 -> 9 | AQ14: =(AP14+U14)/2 -> 5.1 | AR14: =IF(AS14="",0,10) -> 10 | AS14: =IF(AX14=TRUE,"Desprezível",IF(AY14=TRUE,"Administrável",IF(AZ14=TRUE,"Indesejável",IF(BA14=TRUE,"Intolerável","")))) -> Administrável | AU14: Mitigar | AW14: Alto | AX14: =AND(U14>0,U14<=2,AP14>0,AP14<=7) -> FALSE | AY14: =OR(AND(U14>0,U14<=2,AP14>0,AP14>7,AP14<=13),AND(U14>0,U14>2,U14<=3,AP14>0,AP14<=10)) -> TRUE | AZ14: =OR(AND(U14>0,U14<=2,AP14>0,AP14>12,AP14<=17),AND(U14>0,U14>2,U14<=3,AP14>0,AP14>10,AP14<=13),AND(U14>0,U14>3,U14<=5,AP14>0,AP14<=10),AND(U14>0,U14>4,U14<=6,AP14>0,AP14<=7)) -> FALSE | BA14: =OR(AND(U14>0,U14>2,U14<=3,AP14>0,AP14>14,AP14<=20),AND(U14>0,U14>3,U14<=5,AP14>0,AP14>10),AND(U14>0,U14>5,U14<=6,AP14>0,AP14>7,AP14<=20)) -> FALSE | BC14: Alto
I15: =IF(H15="N.A.",0)+IF(H15="Baixo",1)+IF(H15="Moderado",2)+IF(H15="Significativo",4)+IF(H15="Alto",6) -> 0 | J15: =IF(I15>0,1,0) -> 0 | R15: =IF(Q15="N.A.",0)+IF(Q15="Baixo",1)+IF(Q15="Moderado",2)+IF(Q15="Significativo",4)+IF(Q15="Alto",6) -> 0 | S15: =IF(R15>0,1,0) -> 0 | T15: =SUM(G15,J15,M15,P15,S15) -> 0 | U15: =IFERROR(SUM(F15,I15,L15,O15,R15)/T15,0) -> 0 | AA15: =IF(W15="X",0)+IF(X15="X",2)+IF(Y15="X",4)+IF(Z15="X",9) -> 0 | AF15: =IF(AC15="X",1)+IF(AD15="X",2)+IF(AE15="X",5) -> 0 | AZ15: =OR(AND(U15>0,U15<=2,AP15>0,AP15>12,AP15<=17),AND(U15>0,U15>2,U15<=3,AP15>0,AP15>10,AP15<=13),AND(U15>0,U15>3,U15<=5,AP15>0,AP15<=10),AND(U15>0,U15>4,U15<=6,AP15>0,AP15<=7)) -> FALSE | BA15: =OR(AND(U15>0,U15>2,U15<=3,AP15>0,AP15>14,AP15<=20),AND(U15>0,U15>3,U15<=5,AP15>0,AP15>10),AND(U15>0,U15>5,U15<=6,AP15>0,AP15>7,AP15<=20)) -> FALSE
B16: 4. | F16: =IF(E16="N.A.",0)+IF(E16="Baixo",1)+IF(E16="Moderado",2)+IF(E16="Significativo",4)+IF(E16="Alto",6) -> 0 | G16: =IF(F16>0,1,0) -> 0 | I16: =IF(H16="N.A.",0)+IF(H16="Baixo",1)+IF(H16="Moderado",2)+IF(H16="Significativo",4)+IF(H16="Alto",6) -> 0 | J16: =IF(I16>0,1,0) -> 0 | L16: =IF(K16="N.A.",0)+IF(K16="Baixo",1)+IF(K16="Moderado",2)+IF(K16="Significativo",4)+IF(K16="Alto",6) -> 0 | M16: =IF(L16>0,1,0) -> 0 | O16: =IF(N16="N.A.",0)+IF(N16="Baixo",1)+IF(N16="Moderado",2)+IF(N16="Significativo",4)+IF(N16="Alto",6) -> 0 | P16: =IF(O16>0,1,0) -> 0 | R16: =IF(Q16="N.A.",0)+IF(Q16="Baixo",1)+IF(Q16="Moderado",2)+IF(Q16="Significativo",4)+IF(Q16="Alto",6) -> 0 | S16: =IF(R16>0,1,0) -> 0 | T16: =SUM(G16,J16,M16,P16,S16) -> 0 | U16: =IFERROR(SUM(F16,I16,L16,O16,R16)/T16,0) -> 0 | X16: X | AA16: =IF(W16="X",0)+IF(X16="X",2)+IF(Y16="X",4)+IF(Z16="X",9) -> 2 | AC16: X | AF16: =IF(AC16="X",1)+IF(AD16="X",2)+IF(AE16="X",5) -> 1 | AJ16: X | AN16: =IF(AH16="X",1)+IF(AI16="X",2)+IF(AJ16="X",3)+IF(AK16="X",4)+IF(AL16="X",5)+IF(AM16="X",6) -> 3 | AP16: =AA16+AF16+AN16 -> 6 | AQ16: =(AP16+U16)/2 -> 3 | AR16: =IF(AS16="",0,10) -> 0 | AS16: =IF(AX16=TRUE,"Desprezível",IF(AY16=TRUE,"Administrável",IF(AZ16=TRUE,"Indesejável",IF(BA16=TRUE,"Intolerável","")))) | AX16: =AND(U16>0,U16<=2,AP16>0,AP16<=7) -> FALSE | AY16: =OR(AND(U16>0,U16<=2,AP16>0,AP16>7,AP16<=13),AND(U16>0,U16>2,U16<=3,AP16>0,AP16<=10)) -> FALSE | AZ16: =OR(AND(U16>0,U16<=2,AP16>0,AP16>12,AP16<=17),AND(U16>0,U16>2,U16<=3,AP16>0,AP16>10,AP16<=13),AND(U16>0,U16>3,U16<=5,AP16>0,AP16<=10),AND(U16>0,U16>4,U16<=6,AP16>0,AP16<=7)) -> FALSE | BA16: =OR(AND(U16>0,U16>2,U16<=3,AP16>0,AP16>14,AP16<=20),AND(U16>0,U16>3,U16<=5,AP16>0,AP16>10),AND(U16>0,U16>5,U16<=6,AP16>0,AP16>7,AP16<=20)) -> FALSE
F17: =IF(E17="N.A.",0)+IF(E17="Baixo",1)+IF(E17="Moderado",2)+IF(E17="Significativo",4)+IF(E17="Alto",6) -> 0 | G17: =IF(F17>0,1,0) -> 0 | I17: =IF(H17="N.A.",0)+IF(H17="Baixo",1)+IF(H17="Moderado",2)+IF(H17="Significativo",4)+IF(H17="Alto",6) -> 0 | J17: =IF(I17>0,1,0) -> 0 | L17: =IF(K17="N.A.",0)+IF(K17="Baixo",1)+IF(K17="Moderado",2)+IF(K17="Significativo",4)+IF(K17="Alto",6) -> 0 | M17: =IF(L17>0,1,0) -> 0 | O17: =IF(N17="N.A.",0)+IF(N17="Baixo",1)+IF(N17="Moderado",2)+IF(N17="Significativo",4)+IF(N17="Alto",6) -> 0 | P17: =IF(O17>0,1,0) -> 0 | R17: =IF(Q17="N.A.",0)+IF(Q17="Baixo",1)+IF(Q17="Moderado",2)+IF(Q17="Significativo",4)+IF(Q17="Alto",6) -> 0 | S17: =IF(R17>0,1,0) -> 0 | T17: =SUM(G17,J17,M17,P17,S17) -> 0 | U17: =IFERROR(SUM(F17,I17,L17,O17,R17)/T17,0) -> 0 | AA17: =IF(W17="X",0)+IF(X17="X",2)+IF(Y17="X",4)+IF(Z17="X",9) -> 0 | AF17: =IF(AC17="X",1)+IF(AD17="X",2)+IF(AE17="X",5) -> 0 | AZ17: =OR(AND(U17>0,U17<=2,AP17>0,AP17>12,AP17<=17),AND(U17>0,U17>2,U17<=3,AP17>0,AP17>10,AP17<=13),AND(U17>0,U17>3,U17<=5,AP17>0,AP17<=10),AND(U17>0,U17>4,U17<=6,AP17>0,AP17<=7)) -> FALSE | BA17: =OR(AND(U17>0,U17>2,U17<=3,AP17>0,AP17>14,AP17<=20),AND(U17>0,U17>3,U17<=5,AP17>0,AP17>10),AND(U17>0,U17>5,U17<=6,AP17>0,AP17>7,AP17<=20)) -> FALSE
B18: 5. | F18: =IF(E18="N.A.",0)+IF(E18="Baixo",1)+IF(E18="Moderado",2)+IF(E18="Significativo",4)+IF(E18="Alto",6) -> 0 | G18: =IF(F18>0,1,0) -> 0 | I18: =IF(H18="N.A.",0)+IF(H18="Baixo",1)+IF(H18="Moderado",2)+IF(H18="Significativo",4)+IF(H18="Alto",6) -> 0 | J18: =IF(I18>0,1,0) -> 0 | L18: =IF(K18="N.A.",0)+IF(K18="Baixo",1)+IF(K18="Moderado",2)+IF(K18="Significativo",4)+IF(K18="Alto",6) -> 0 | M18: =IF(L18>0,1,0) -> 0 | O18: =IF(N18="N.A.",0)+IF(N18="Baixo",1)+IF(N18="Moderado",2)+IF(N18="Significativo",4)+IF(N18="Alto",6) -> 0 | P18: =IF(O18>0,1,0) -> 0 | R18: =IF(Q18="N.A.",0)+IF(Q18="Baixo",1)+IF(Q18="Moderado",2)+IF(Q18="Significativo",4)+IF(Q18="Alto",6) -> 0 | S18: =IF(R18>0,1,0) -> 0 | T18: =SUM(G18,J18,M18,P18,S18) -> 0 | U18: =IFERROR(SUM(F18,I18,L18,O18,R18)/T18,0) -> 0 | X18: X | AA18: =IF(W18="X",0)+IF(X18="X",2)+IF(Y18="X",4)+IF(Z18="X",9) -> 2 | AD18: X | AF18: =IF(AC18="X",1)+IF(AD18="X",2)+IF(AE18="X",5) -> 2 | AH18: X | AN18: =IF(AH18="X",1)+IF(AI18="X",2)+IF(AJ18="X",3)+IF(AK18="X",4)+IF(AL18="X",5)+IF(AM18="X",6) -> 1 | AP18: =AA18+AF18+AN18 -> 5 | AQ18: =(AP18+U18)/2 -> 2.5 | AR18: =IF(AS18="",0,10) -> 0 | AS18: =IF(AX18=TRUE,"Desprezível",IF(AY18=TRUE,"Administrável",IF(AZ18=TRUE,"Indesejável",IF(BA18=TRUE,"Intolerável","")))) | AW18: X | AX18: =AND(U18>0,U18<=2,AP18>0,AP18<=7) -> FALSE | AY18: =OR(AND(U18>0,U18<=2,AP18>0,AP18>7,AP18<=13),AND(U18>0,U18>2,U18<=3,AP18>0,AP18<=10)) -> FALSE | AZ18: =OR(AND(U18>0,U18<=2,AP18>0,AP18>12,AP18<=17),AND(U18>0,U18>2,U18<=3,AP18>0,AP18>10,AP18<=13),AND(U18>0,U18>3,U18<=5,AP18>0,AP18<=10),AND(U18>0,U18>4,U18<=6,AP18>0,AP18<=7)) -> FALSE | BA18: =OR(AND(U18>0,U18>2,U18<=3,AP18>0,AP18>14,AP18<=20),AND(U18>0,U18>3,U18<=5,AP18>0,AP18>10),AND(U18>0,U18>5,U18<=6,AP18>0,AP18>7,AP18<=20)) -> FALSE | BC18: X
F19: =IF(E19="N.A.",0)+IF(E19="Baixo",1)+IF(E19="Moderado",2)+IF(E19="Significativo",4)+IF(E19="Alto",6) -> 0 | G19: =IF(F19>0,1,0) -> 0 | I19: =IF(H19="N.A.",0)+IF(H19="Baixo",1)+IF(H19="Moderado",2)+IF(H19="Significativo",4)+IF(H19="Alto",6) -> 0 | J19: =IF(I19>0,1,0) -> 0 | L19: =IF(K19="N.A.",0)+IF(K19="Baixo",1)+IF(K19="Moderado",2)+IF(K19="Significativo",4)+IF(K19="Alto",6) -> 0 | R19: =IF(Q19="N.A.",0)+IF(Q19="Baixo",1)+IF(Q19="Moderado",2)+IF(Q19="Significativo",4)+IF(Q19="Alto",6) -> 0 | T19: =SUM(G19,J19,M19,P19,S19) -> 0 | U19: =IFERROR(SUM(F19,I19,L19,O19,R19)/T19,0) -> 0 | AA19: =IF(W19="X",0)+IF(X19="X",2)+IF(Y19="X",4)+IF(Z19="X",9) -> 0 | AF19: =IF(AC19="X",1)+IF(AD19="X",2)+IF(AE19="X",5) -> 0 | AZ19: =OR(AND(U19>0,U19<=2,AP19>0,AP19>12,AP19<=17),AND(U19>0,U19>2,U19<=3,AP19>0,AP19>10,AP19<=13),AND(U19>0,U19>3,U19<=5,AP19>0,AP19<=10),AND(U19>0,U19>4,U19<=6,AP19>0,AP19<=7)) -> FALSE | BA19: =OR(AND(U19>0,U19>2,U19<=3,AP19>0,AP19>14,AP19<=20),AND(U19>0,U19>3,U19<=5,AP19>0,AP19>10),AND(U19>0,U19>5,U19<=6,AP19>0,AP19>7,AP19<=20)) -> FALSE
B20: 6. | F20: 4 | G20: 1 | I20: 2 | J20: 1 | L20: 3 | M20: 1 | O20: =IF(N20="N.A.",0)+IF(N20="Baixo",1)+IF(N20="Moderado",2)+IF(N20="Significativo",4)+IF(N20="Alto",6) -> 0 | P20: =IF(O20>0,1,0) -> 0 | R20: =IF(Q20="N.A.",0)+IF(Q20="Baixo",1)+IF(Q20="Moderado",2)+IF(Q20="Significativo",4)+IF(Q20="Alto",6) -> 0 | S20: =IF(R20>0,1,0) -> 0 | T20: =SUM(G20,J20,M20,P20,S20) -> 3 | U20: =IFERROR(SUM(F20,I20,L20,O20,R20)/T20,0) -> 3 | AA20: =IF(W20="X",0)+IF(X20="X",2)+IF(Y20="X",4)+IF(Z20="X",9) -> 0 | AF20: =IF(AC20="X",1)+IF(AD20="X",2)+IF(AE20="X",5) -> 0 | AN20: =IF(AH20="X",1)+IF(AI20="X",2)+IF(AJ20="X",3)+IF(AK20="X",4)+IF(AL20="X",5)+IF(AM20="X",6) -> 0 | AP20: =AA20+AF20+AN20 -> 0 | AQ20: =(AP20+U20)/2 -> 1.5 | AR20: =IF(AS20="",0,10) -> 0 | AS20: =IF(AX20=TRUE,"Desprezível",IF(AY20=TRUE,"Administrável",IF(AZ20=TRUE,"Indesejável",IF(BA20=TRUE,"Intolerável","")))) | AX20: =AND(U20>0,U20<=2,AP20>0,AP20<=7) -> FALSE | AY20: =OR(AND(U20>0,U20<=2,AP20>0,AP20>7,AP20<=13),AND(U20>0,U20>2,U20<=3,AP20>0,AP20<=10)) -> FALSE | AZ20: =OR(AND(U20>0,U20<=2,AP20>0,AP20>12,AP20<=17),AND(U20>0,U20>2,U20<=3,AP20>0,AP20>10,AP20<=13),AND(U20>0,U20>3,U20<=5,AP20>0,AP20<=10),AND(U20>0,U20>4,U20<=6,AP20>0,AP20<=7)) -> FALSE | BA20: =OR(AND(U20>0,U20>2,U20<=3,AP20>0,AP20>14,AP20<=20),AND(U20>0,U20>3,U20<=5,AP20>0,AP20>10),AND(U20>0,U20>5,U20<=6,AP20>0,AP20>7,AP20<=20)) -> FALSE
F21: =IF(E21="N.A.",0)+IF(E21="Baixo",1)+IF(E21="Moderado",2)+IF(E21="Significativo",4)+IF(E21="Alto",6) -> 0 | G21: =IF(F21>0,1,0) -> 0 | I21: =IF(H21="N.A.",0)+IF(H21="Baixo",1)+IF(H21="Moderado",2)+IF(H21="Significativo",4)+IF(H21="Alto",6) -> 0 | J21: =IF(I21>0,1,0) -> 0 | L21: =IF(K21="N.A.",0)+IF(K21="Baixo",1)+IF(K21="Moderado",2)+IF(K21="Significativo",4)+IF(K21="Alto",6) -> 0 | M21: =IF(L21>0,1,0) -> 0 | O21: =IF(N21="N.A.",0)+IF(N21="Baixo",1)+IF(N21="Moderado",2)+IF(N21="Significativo",4)+IF(N21="Alto",6) -> 0 | P21: =IF(O21>0,1,0) -> 0 | R21: =IF(Q21="N.A.",0)+IF(Q21="Baixo",1)+IF(Q21="Moderado",2)+IF(Q21="Significativo",4)+IF(Q21="Alto",6) -> 0 | T21: =SUM(G21,J21,M21,P21,S21) -> 0 | U21: =IFERROR(SUM(F21,I21,L21,O21,R21)/T21,0) -> 0 | AA21: =IF(W21="X",0)+IF(X21="X",2)+IF(Y21="X",4)+IF(Z21="X",9) -> 0 | AF21: =IF(AC21="X",1)+IF(AD21="X",2)+IF(AE21="X",5) -> 0 | AZ21: =OR(AND(U21>0,U21<=2,AP21>0,AP21>12,AP21<=17),AND(U21>0,U21>2,U21<=3,AP21>0,AP21>10,AP21<=13),AND(U21>0,U21>3,U21<=5,AP21>0,AP21<=10),AND(U21>0,U21>4,U21<=6,AP21>0,AP21<=7)) -> FALSE | BA21: =OR(AND(U21>0,U21>2,U21<=3,AP21>0,AP21>14,AP21<=20),AND(U21>0,U21>3,U21<=5,AP21>0,AP21>10),AND(U21>0,U21>5,U21<=6,AP21>0,AP21>7,AP21<=20)) -> FALSE
B22: 7. | F22: 2 | G22: 1 | I22: 1 | J22: 1 | L22: 6 | M22: 1 | O22: 1 | P22: 1 | R22: 1 | S22: 1 | T22: 5 | U22: 2.2 | AA22: 0 | AF22: 2 | AN22: =IF(AH22="X",1)+IF(AI22="X",2)+IF(AJ22="X",3)+IF(AK22="X",4)+IF(AL22="X",5)+IF(AM22="X",6) -> 0 | AP22: =AA22+AF22+AN22 -> 2 | AQ22: =(AP22+U22)/2 -> 2.1 | AR22: =IF(AS22="",0,10) -> 10 | AS22: =IF(AX22=TRUE,"Desprezível",IF(AY22=TRUE,"Administrável",IF(AZ22=TRUE,"Indesejável",IF(BA22=TRUE,"Intolerável","")))) -> Administrável | AX22: =AND(U22>0,U22<=2,AP22>0,AP22<=7) -> FALSE | AY22: =OR(AND(U22>0,U22<=2,AP22>0,AP22>7,AP22<=13),AND(U22>0,U22>2,U22<=3,AP22>0,AP22<=10)) -> TRUE | AZ22: =OR(AND(U22>0,U22<=2,AP22>0,AP22>12,AP22<=17),AND(U22>0,U22>2,U22<=3,AP22>0,AP22>10,AP22<=13),AND(U22>0,U22>3,U22<=5,AP22>0,AP22<=10),AND(U22>0,U22>4,U22<=6,AP22>0,AP22<=7)) -> FALSE | BA22: =OR(AND(U22>0,U22>2,U22<=3,AP22>0,AP22>14,AP22<=20),AND(U22>0,U22>3,U22<=5,AP22>0,AP22>10),AND(U22>0,U22>5,U22<=6,AP22>0,AP22>7,AP22<=20)) -> FALSE
I23: =IF(H23="N.A.",0)+IF(H23="Baixo",1)+IF(H23="Moderado",2)+IF(H23="Significativo",4)+IF(H23="Alto",6) -> 0 | J23: =IF(I23>0,1,0) -> 0 | L23: =IF(K23="N.A.",0)+IF(K23="Baixo",1)+IF(K23="Moderado",2)+IF(K23="Significativo",4)+IF(K23="Alto",6) -> 0 | R23: =IF(Q23="N.A.",0)+IF(Q23="Baixo",1)+IF(Q23="Moderado",2)+IF(Q23="Significativo",4)+IF(Q23="Alto",6) -> 0 | T23: =SUM(G23,J23,M23,P23,S23) -> 0 | U23: =IFERROR(SUM(F23,I23,L23,O23,R23)/T23,0) -> 0 | AA23: =IF(W23="X",0)+IF(X23="X",2)+IF(Y23="X",4)+IF(Z23="X",9) -> 0 | AF23: =IF(AC23="X",1)+IF(AD23="X",2)+IF(AE23="X",5) -> 0 | AZ23: =OR(AND(U23>0,U23<=2,AP23>0,AP23>12,AP23<=17),AND(U23>0,U23>2,U23<=3,AP23>0,AP23>10,AP23<=13),AND(U23>0,U23>3,U23<=5,AP23>0,AP23<=10),AND(U23>0,U23>4,U23<=6,AP23>0,AP23<=7)) -> FALSE | BA23: =OR(AND(U23>0,U23>2,U23<=3,AP23>0,AP23>14,AP23<=20),AND(U23>0,U23>3,U23<=5,AP23>0,AP23>10),AND(U23>0,U23>5,U23<=6,AP23>0,AP23>7,AP23<=20)) -> FALSE
B24: 8. | F24: =IF(E24="N.A.",0)+IF(E24="Baixo",1)+IF(E24="Moderado",2)+IF(E24="Significativo",4)+IF(E24="Alto",6) -> 0 | G24: =IF(F24>0,1,0) -> 0 | I24: =IF(H24="N.A.",0)+IF(H24="Baixo",1)+IF(H24="Moderado",2)+IF(H24="Significativo",4)+IF(H24="Alto",6) -> 0 | J24: =IF(I24>0,1,0) -> 0 | L24: =IF(K24="N.A.",0)+IF(K24="Baixo",1)+IF(K24="Moderado",2)+IF(K24="Significativo",4)+IF(K24="Alto",6) -> 0 | M24: =IF(L24>0,1,0) -> 0 | O24: =IF(N24="N.A.",0)+IF(N24="Baixo",1)+IF(N24="Moderado",2)+IF(N24="Significativo",4)+IF(N24="Alto",6) -> 0 | P24: =IF(O24>0,1,0) -> 0 | R24: =IF(Q24="N.A.",0)+IF(Q24="Baixo",1)+IF(Q24="Moderado",2)+IF(Q24="Significativo",4)+IF(Q24="Alto",6) -> 0 | S24: =IF(R24>0,1,0) -> 0 | T24: =SUM(G24,J24,M24,P24,S24) -> 0 | U24: =IFERROR(SUM(F24,I24,L24,O24,R24)/T24,0) -> 0 | AA24: =IF(W24="X",0)+IF(X24="X",2)+IF(Y24="X",4)+IF(Z24="X",9) -> 0 | AF24: =IF(AC24="X",1)+IF(AD24="X",2)+IF(AE24="X",5) -> 0 | AN24: =IF(AH24="X",1)+IF(AI24="X",2)+IF(AJ24="X",3)+IF(AK24="X",4)+IF(AL24="X",5)+IF(AM24="X",6) -> 0 | AP24: =AA24+AF24+AN24 -> 0 | AQ24: =(AP24+U24)/2 -> 0 | AR24: =IF(AS24="",0,10) -> 0 | AS24: =IF(AX24=TRUE,"Desprezível",IF(AY24=TRUE,"Administrável",IF(AZ24=TRUE,"Indesejável",IF(BA24=TRUE,"Intolerável","")))) | AX24: =AND(U24>0,U24<=2,AP24>0,AP24<=7) -> FALSE | AY24: =OR(AND(U24>0,U24<=2,AP24>0,AP24>7,AP24<=13),AND(U24>0,U24>2,U24<=3,AP24>0,AP24<=10)) -> FALSE | AZ24: =OR(AND(U24>0,U24<=2,AP24>0,AP24>12,AP24<=17),AND(U24>0,U24>2,U24<=3,AP24>0,AP24>10,AP24<=13),AND(U24>0,U24>3,U24<=5,AP24>0,AP24<=10),AND(U24>0,U24>4,U24<=6,AP24>0,AP24<=7)) -> FALSE | BA24: =OR(AND(U24>0,U24>2,U24<=3,AP24>0,AP24>14,AP24<=20),AND(U24>0,U24>3,U24<=5,AP24>0,AP24>10),AND(U24>0,U24>5,U24<=6,AP24>0,AP24>7,AP24<=20)) -> FALSE
I25: =IF(H25="N.A.",0)+IF(H25="Baixo",1)+IF(H25="Moderado",2)+IF(H25="Significativo",4)+IF(H25="Alto",6) -> 0 | J25: =IF(I25>0,1,0) -> 0 | L25: =IF(K25="N.A.",0)+IF(K25="Baixo",1)+IF(K25="Moderado",2)+IF(K25="Significativo",4)+IF(K25="Alto",6) -> 0 | R25: =IF(Q25="N.A.",0)+IF(Q25="Baixo",1)+IF(Q25="Moderado",2)+IF(Q25="Significativo",4)+IF(Q25="Alto",6) -> 0 | T25: =SUM(G25,J25,M25,P25,S25) -> 0 | U25: =IFERROR(SUM(F25,I25,L25,O25,R25)/T25,0) -> 0 | AA25: =IF(W25="X",0)+IF(X25="X",2)+IF(Y25="X",4)+IF(Z25="X",9) -> 0 | AF25: =IF(AC25="X",1)+IF(AD25="X",2)+IF(AE25="X",5) -> 0 | AZ25: =OR(AND(U25>0,U25<=2,AP25>0,AP25>12,AP25<=17),AND(U25>0,U25>2,U25<=3,AP25>0,AP25>10,AP25<=13),AND(U25>0,U25>3,U25<=5,AP25>0,AP25<=10),AND(U25>0,U25>4,U25<=6,AP25>0,AP25<=7)) -> FALSE | BA25: =OR(AND(U25>0,U25>2,U25<=3,AP25>0,AP25>14,AP25<=20),AND(U25>0,U25>3,U25<=5,AP25>0,AP25>10),AND(U25>0,U25>5,U25<=6,AP25>0,AP25>7,AP25<=20)) -> FALSE
B26: 9. | F26: =IF(E26="N.A.",0)+IF(E26="Baixo",1)+IF(E26="Moderado",2)+IF(E26="Significativo",4)+IF(E26="Alto",6) -> 0 | G26: =IF(F26>0,1,0) -> 0 | I26: =IF(H26="N.A.",0)+IF(H26="Baixo",1)+IF(H26="Moderado",2)+IF(H26="Significativo",4)+IF(H26="Alto",6) -> 0 | J26: =IF(I26>0,1,0) -> 0 | L26: =IF(K26="N.A.",0)+IF(K26="Baixo",1)+IF(K26="Moderado",2)+IF(K26="Significativo",4)+IF(K26="Alto",6) -> 0 | M26: =IF(L26>0,1,0) -> 0 | O26: =IF(N26="N.A.",0)+IF(N26="Baixo",1)+IF(N26="Moderado",2)+IF(N26="Significativo",4)+IF(N26="Alto",6) -> 0 | P26: =IF(O26>0,1,0) -> 0 | R26: =IF(Q26="N.A.",0)+IF(Q26="Baixo",1)+IF(Q26="Moderado",2)+IF(Q26="Significativo",4)+IF(Q26="Alto",6) -> 0 | S26: =IF(R26>0,1,0) -> 0 | T26: =SUM(G26,J26,M26,P26,S26) -> 0 | U26: =IFERROR(SUM(F26,I26,L26,O26,R26)/T26,0) -> 0 | AA26: =IF(W26="X",0)+IF(X26="X",2)+IF(Y26="X",4)+IF(Z26="X",9) -> 0 | AF26: =IF(AC26="X",1)+IF(AD26="X",2)+IF(AE26="X",5) -> 0 | AN26: =IF(AH26="X",1)+IF(AI26="X",2)+IF(AJ26="X",3)+IF(AK26="X",4)+IF(AL26="X",5)+IF(AM26="X",6) -> 0 | AP26: =AA26+AF26+AN26 -> 0 | AQ26: =(AP26+U26)/2 -> 0 | AR26: =IF(AS26="",0,10) -> 0 | AS26: =IF(AX26=TRUE,"Desprezível",IF(AY26=TRUE,"Administrável",IF(AZ26=TRUE,"Indesejável",IF(BA26=TRUE,"Intolerável","")))) | AX26: =AND(U26>0,U26<=2,AP26>0,AP26<=7) -> FALSE | AY26: =OR(AND(U26>0,U26<=2,AP26>0,AP26>7,AP26<=13),AND(U26>0,U26>2,U26<=3,AP26>0,AP26<=10)) -> FALSE | AZ26: =OR(AND(U26>0,U26<=2,AP26>0,AP26>12,AP26<=17),AND(U26>0,U26>2,U26<=3,AP26>0,AP26>10,AP26<=13),AND(U26>0,U26>3,U26<=5,AP26>0,AP26<=10),AND(U26>0,U26>4,U26<=6,AP26>0,AP26<=7)) -> FALSE | BA26: =OR(AND(U26>0,U26>2,U26<=3,AP26>0,AP26>14,AP26<=20),AND(U26>0,U26>3,U26<=5,AP26>0,AP26>10),AND(U26>0,U26>5,U26<=6,AP26>0,AP26>7,AP26<=20)) -> FALSE
F27: =IF(E27="N.A.",0)+IF(E27="Baixo",1)+IF(E27="Moderado",2)+IF(E27="Significativo",4)+IF(E27="Alto",6) -> 0 | G27: =IF(F27>0,1,0) -> 0 | I27: =IF(H27="N.A.",0)+IF(H27="Baixo",1)+IF(H27="Moderado",2)+IF(H27="Significativo",4)+IF(H27="Alto",6) -> 0 | J27: =IF(I27>0,1,0) -> 0 | L27: =IF(K27="N.A.",0)+IF(K27="Baixo",1)+IF(K27="Moderado",2)+IF(K27="Significativo",4)+IF(K27="Alto",6) -> 0 | R27: =IF(Q27="N.A.",0)+IF(Q27="Baixo",1)+IF(Q27="Moderado",2)+IF(Q27="Significativo",4)+IF(Q27="Alto",6) -> 0 | T27: =SUM(G27,J27,M27,P27,S27) -> 0 | U27: =IFERROR(SUM(F27,I27,L27,O27,R27)/T27,0) -> 0 | AA27: =IF(W27="X",0)+IF(X27="X",2)+IF(Y27="X",4)+IF(Z27="X",9) -> 0 | AF27: =IF(AC27="X",1)+IF(AD27="X",2)+IF(AE27="X",5) -> 0 | AZ27: =OR(AND(U27>0,U27<=2,AP27>0,AP27>12,AP27<=17),AND(U27>0,U27>2,U27<=3,AP27>0,AP27>10,AP27<=13),AND(U27>0,U27>3,U27<=5,AP27>0,AP27<=10),AND(U27>0,U27>4,U27<=6,AP27>0,AP27<=7)) -> FALSE | BA27: =OR(AND(U27>0,U27>2,U27<=3,AP27>0,AP27>14,AP27<=20),AND(U27>0,U27>3,U27<=5,AP27>0,AP27>10),AND(U27>0,U27>5,U27<=6,AP27>0,AP27>7,AP27<=20)) -> FALSE
B28: 10. | F28: =IF(E28="N.A.",0)+IF(E28="Baixo",1)+IF(E28="Moderado",2)+IF(E28="Significativo",4)+IF(E28="Alto",6) -> 0 | G28: =IF(F28>0,1,0) -> 0 | I28: =IF(H28="N.A.",0)+IF(H28="Baixo",1)+IF(H28="Moderado",2)+IF(H28="Significativo",4)+IF(H28="Alto",6) -> 0 | J28: =IF(I28>0,1,0) -> 0 | L28: =IF(K28="N.A.",0)+IF(K28="Baixo",1)+IF(K28="Moderado",2)+IF(K28="Significativo",4)+IF(K28="Alto",6) -> 0 | M28: =IF(L28>0,1,0) -> 0 | O28: =IF(N28="N.A.",0)+IF(N28="Baixo",1)+IF(N28="Moderado",2)+IF(N28="Significativo",4)+IF(N28="Alto",6) -> 0 | P28: =IF(O28>0,1,0) -> 0 | R28: =IF(Q28="N.A.",0)+IF(Q28="Baixo",1)+IF(Q28="Moderado",2)+IF(Q28="Significativo",4)+IF(Q28="Alto",6) -> 0 | S28: =IF(R28>0,1,0) -> 0 | T28: =SUM(G28,J28,M28,P28,S28) -> 0 | U28: =IFERROR(SUM(F28,I28,L28,O28,R28)/T28,0) -> 0 | AA28: =IF(W28="X",0)+IF(X28="X",2)+IF(Y28="X",4)+IF(Z28="X",9) -> 0 | AF28: =IF(AC28="X",1)+IF(AD28="X",2)+IF(AE28="X",5) -> 0 | AN28: =IF(AH28="X",1)+IF(AI28="X",2)+IF(AJ28="X",3)+IF(AK28="X",4)+IF(AL28="X",5)+IF(AM28="X",6) -> 0 | AP28: =AA28+AF28+AN28 -> 0 | AQ28: =(AP28+U28)/2 -> 0 | AR28: =IF(AS28="",0,10) -> 0 | AS28: =IF(AX28=TRUE,"Desprezível",IF(AY28=TRUE,"Administrável",IF(AZ28=TRUE,"Indesejável",IF(BA28=TRUE,"Intolerável","")))) | AX28: =AND(U28>0,U28<=2,AP28>0,AP28<=7) -> FALSE | AY28: =OR(AND(U28>0,U28<=2,AP28>0,AP28>7,AP28<=13),AND(U28>0,U28>2,U28<=3,AP28>0,AP28<=10)) -> FALSE | AZ28: =OR(AND(U28>0,U28<=2,AP28>0,AP28>12,AP28<=17),AND(U28>0,U28>2,U28<=3,AP28>0,AP28>10,AP28<=13),AND(U28>0,U28>3,U28<=5,AP28>0,AP28<=10),AND(U28>0,U28>4,U28<=6,AP28>0,AP28<=7)) -> FALSE | BA28: =OR(AND(U28>0,U28>2,U28<=3,AP28>0,AP28>14,AP28<=20),AND(U28>0,U28>3,U28<=5,AP28>0,AP28>10),AND(U28>0,U28>5,U28<=6,AP28>0,AP28>7,AP28<=20)) -> FALSE
F29: =IF(E29="N.A.",0)+IF(E29="Baixo",1)+IF(E29="Moderado",2)+IF(E29="Significativo",4)+IF(E29="Alto",6) -> 0 | G29: =IF(F29>0,1,0) -> 0 | I29: =IF(H29="N.A.",0)+IF(H29="Baixo",1)+IF(H29="Moderado",2)+IF(H29="Significativo",4)+IF(H29="Alto",6) -> 0 | J29: =IF(I29>0,1,0) -> 0 | L29: =IF(K29="N.A.",0)+IF(K29="Baixo",1)+IF(K29="Moderado",2)+IF(K29="Significativo",4)+IF(K29="Alto",6) -> 0 | M29: =IF(L29>0,1,0) -> 0 | O29: =IF(N29="N.A.",0)+IF(N29="Baixo",1)+IF(N29="Moderado",2)+IF(N29="Significativo",4)+IF(N29="Alto",6) -> 0 | P29: =IF(O29>0,1,0) -> 0 | R29: =IF(Q29="N.A.",0)+IF(Q29="Baixo",1)+IF(Q29="Moderado",2)+IF(Q29="Significativo",4)+IF(Q29="Alto",6) -> 0 | T29: =SUM(G29,J29,M29,P29,S29) -> 0 | U29: =IFERROR(SUM(F29,I29,L29,O29,R29)/T29,0) -> 0 | AA29: =IF(W29="X",0)+IF(X29="X",2)+IF(Y29="X",4)+IF(Z29="X",9) -> 0 | AF29: =IF(AC29="X",1)+IF(AD29="X",2)+IF(AE29="X",5) -> 0 | AZ29: =OR(AND(U29>0,U29<=2,AP29>0,AP29>12,AP29<=17),AND(U29>0,U29>2,U29<=3,AP29>0,AP29>10,AP29<=13),AND(U29>0,U29>3,U29<=5,AP29>0,AP29<=10),AND(U29>0,U29>4,U29<=6,AP29>0,AP29<=7)) -> FALSE | BA29: =OR(AND(U29>0,U29>2,U29<=3,AP29>0,AP29>14,AP29<=20),AND(U29>0,U29>3,U29<=5,AP29>0,AP29>10),AND(U29>0,U29>5,U29<=6,AP29>0,AP29>7,AP29<=20)) -> FALSE
B30: 11. | F30: =IF(E30="N.A.",0)+IF(E30="Baixo",1)+IF(E30="Moderado",2)+IF(E30="Significativo",4)+IF(E30="Alto",6) -> 0 | G30: =IF(F30>0,1,0) -> 0 | I30: =IF(H30="N.A.",0)+IF(H30="Baixo",1)+IF(H30="Moderado",2)+IF(H30="Significativo",4)+IF(H30="Alto",6) -> 0 | J30: =IF(I30>0,1,0) -> 0 | L30: =IF(K30="N.A.",0)+IF(K30="Baixo",1)+IF(K30="Moderado",2)+IF(K30="Significativo",4)+IF(K30="Alto",6) -> 0 | M30: =IF(L30>0,1,0) -> 0 | O30: =IF(N30="N.A.",0)+IF(N30="Baixo",1)+IF(N30="Moderado",2)+IF(N30="Significativo",4)+IF(N30="Alto",6) -> 0 | P30: =IF(O30>0,1,0) -> 0 | R30: =IF(Q30="N.A.",0)+IF(Q30="Baixo",1)+IF(Q30="Moderado",2)+IF(Q30="Significativo",4)+IF(Q30="Alto",6) -> 0 | S30: =IF(R30>0,1,0) -> 0 | T30: =SUM(G30,J30,M30,P30,S30) -> 0 | U30: =IFERROR(SUM(F30,I30,L30,O30,R30)/T30,0) -> 0 | AA30: =IF(W30="X",0)+IF(X30="X",2)+IF(Y30="X",4)+IF(Z30="X",9) -> 0 | AF30: =IF(AC30="X",1)+IF(AD30="X",2)+IF(AE30="X",5) -> 0 | AN30: =IF(AH30="X",1)+IF(AI30="X",2)+IF(AJ30="X",3)+IF(AK30="X",4)+IF(AL30="X",5)+IF(AM30="X",6) -> 0 | AP30: =AA30+AF30+AN30 -> 0 | AQ30: =(AP30+U30)/2 -> 0 | AR30: =IF(AS30="",0,10) -> 0 | AS30: =IF(AX30=TRUE,"Desprezível",IF(AY30=TRUE,"Administrável",IF(AZ30=TRUE,"Indesejável",IF(BA30=TRUE,"Intolerável","")))) | AX30: =AND(U30>0,U30<=2,AP30>0,AP30<=7) -> FALSE | AY30: =OR(AND(U30>0,U30<=2,AP30>0,AP30>7,AP30<=13),AND(U30>0,U30>2,U30<=3,AP30>0,AP30<=10)) -> FALSE | AZ30: =OR(AND(U30>0,U30<=2,AP30>0,AP30>12,AP30<=17),AND(U30>0,U30>2,U30<=3,AP30>0,AP30>10,AP30<=13),AND(U30>0,U30>3,U30<=5,AP30>0,AP30<=10),AND(U30>0,U30>4,U30<=6,AP30>0,AP30<=7)) -> FALSE | BA30: =OR(AND(U30>0,U30>2,U30<=3,AP30>0,AP30>14,AP30<=20),AND(U30>0,U30>3,U30<=5,AP30>0,AP30>10),AND(U30>0,U30>5,U30<=6,AP30>0,AP30>7,AP30<=20)) -> FALSE
F31: =IF(E31="N.A.",0)+IF(E31="Baixo",1)+IF(E31="Moderado",2)+IF(E31="Significativo",4)+IF(E31="Alto",6) -> 0 | G31: =IF(F31>0,1,0) -> 0 | I31: =IF(H31="N.A.",0)+IF(H31="Baixo",1)+IF(H31="Moderado",2)+IF(H31="Significativo",4)+IF(H31="Alto",6) -> 0 | J31: =IF(I31>0,1,0) -> 0 | L31: =IF(K31="N.A.",0)+IF(K31="Baixo",1)+IF(K31="Moderado",2)+IF(K31="Significativo",4)+IF(K31="Alto",6) -> 0 | M31: =IF(L31>0,1,0) -> 0 | O31: =IF(N31="N.A.",0)+IF(N31="Baixo",1)+IF(N31="Moderado",2)+IF(N31="Significativo",4)+IF(N31="Alto",6) -> 0 | P31: =IF(O31>0,1,0) -> 0 | R31: =IF(Q31="N.A.",0)+IF(Q31="Baixo",1)+IF(Q31="Moderado",2)+IF(Q31="Significativo",4)+IF(Q31="Alto",6) -> 0 | T31: =SUM(G31,J31,M31,P31,S31) -> 0 | U31: =IFERROR(SUM(F31,I31,L31,O31,R31)/T31,0) -> 0 | AA31: =IF(W31="X",0)+IF(X31="X",2)+IF(Y31="X",4)+IF(Z31="X",9) -> 0 | AF31: =IF(AC31="X",1)+IF(AD31="X",2)+IF(AE31="X",5) -> 0 | AZ31: =OR(AND(U31>0,U31<=2,AP31>0,AP31>12,AP31<=17),AND(U31>0,U31>2,U31<=3,AP31>0,AP31>10,AP31<=13),AND(U31>0,U31>3,U31<=5,AP31>0,AP31<=10),AND(U31>0,U31>4,U31<=6,AP31>0,AP31<=7)) -> FALSE | BA31: =OR(AND(U31>0,U31>2,U31<=3,AP31>0,AP31>14,AP31<=20),AND(U31>0,U31>3,U31<=5,AP31>0,AP31>10),AND(U31>0,U31>5,U31<=6,AP31>0,AP31>7,AP31<=20)) -> FALSE
B32: 12. | F32: =IF(E32="N.A.",0)+IF(E32="Baixo",1)+IF(E32="Moderado",2)+IF(E32="Significativo",4)+IF(E32="Alto",6) -> 0 | G32: =IF(F32>0,1,0) -> 0 | I32: =IF(H32="N.A.",0)+IF(H32="Baixo",1)+IF(H32="Moderado",2)+IF(H32="Significativo",4)+IF(H32="Alto",6) -> 0 | J32: =IF(I32>0,1,0) -> 0 | L32: =IF(K32="N.A.",0)+IF(K32="Baixo",1)+IF(K32="Moderado",2)+IF(K32="Significativo",4)+IF(K32="Alto",6) -> 0 | M32: =IF(L32>0,1,0) -> 0 | O32: =IF(N32="N.A.",0)+IF(N32="Baixo",1)+IF(N32="Moderado",2)+IF(N32="Significativo",4)+IF(N32="Alto",6) -> 0 | P32: =IF(O32>0,1,0) -> 0 | R32: =IF(Q32="N.A.",0)+IF(Q32="Baixo",1)+IF(Q32="Moderado",2)+IF(Q32="Significativo",4)+IF(Q32="Alto",6) -> 0 | S32: =IF(R32>0,1,0) -> 0 | T32: =SUM(G32,J32,M32,P32,S32) -> 0 | U32: =IFERROR(SUM(F32,I32,L32,O32,R32)/T32,0) -> 0 | AA32: =IF(W32="X",0)+IF(X32="X",2)+IF(Y32="X",4)+IF(Z32="X",9) -> 0 | AF32: =IF(AC32="X",1)+IF(AD32="X",2)+IF(AE32="X",5) -> 0 | AN32: =IF(AH32="X",1)+IF(AI32="X",2)+IF(AJ32="X",3)+IF(AK32="X",4)+IF(AL32="X",5)+IF(AM32="X",6) -> 0 | AP32: =AA32+AF32+AN32 -> 0 | AQ32: =(AP32+U32)/2 -> 0 | AR32: =IF(AS32="",0,10) -> 0 | AS32: =IF(AX32=TRUE,"Desprezível",IF(AY32=TRUE,"Administrável",IF(AZ32=TRUE,"Indesejável",IF(BA32=TRUE,"Intolerável","")))) | AX32: =AND(U32>0,U32<=2,AP32>0,AP32<=7) -> FALSE | AY32: =OR(AND(U32>0,U32<=2,AP32>0,AP32>7,AP32<=13),AND(U32>0,U32>2,U32<=3,AP32>0,AP32<=10)) -> FALSE | AZ32: =OR(AND(U32>0,U32<=2,AP32>0,AP32>12,AP32<=17),AND(U32>0,U32>2,U32<=3,AP32>0,AP32>10,AP32<=13),AND(U32>0,U32>3,U32<=5,AP32>0,AP32<=10),AND(U32>0,U32>4,U32<=6,AP32>0,AP32<=7)) -> FALSE | BA32: =OR(AND(U32>0,U32>2,U32<=3,AP32>0,AP32>14,AP32<=20),AND(U32>0,U32>3,U32<=5,AP32>0,AP32>10),AND(U32>0,U32>5,U32<=6,AP32>0,AP32>7,AP32<=20)) -> FALSE
AZ33: =OR(AND(U33>0,U33<=2,AP33>0,AP33>12,AP33<=17),AND(U33>0,U33>2,U33<=3,AP33>0,AP33>10,AP33<=13),AND(U33>0,U33>3,U33<=5,AP33>0,AP33<=10),AND(U33>0,U33>4,U33<=6,AP33>0,AP33<=7)) -> FALSE | BA33: =OR(AND(U33>0,U33>2,U33<=3,AP33>0,AP33>14,AP33<=20),AND(U33>0,U33>3,U33<=5,AP33>0,AP33>10),AND(U33>0,U33>5,U33<=6,AP33>0,AP33>7,AP33<=20)) -> FALSE
B34: 13. | AN34: =IF(AH34="X",1)+IF(AI34="X",2)+IF(AJ34="X",3)+IF(AK34="X",4)+IF(AL34="X",5)+IF(AM34="X",6) -> 0 | AP34: =AA34+AF34+AN34 -> 0 | AQ34: =(AP34+U34)/2 -> 0 | AR34: =IF(AS34="",0,10) -> 0 | AS34: =IF(AX34=TRUE,"Desprezível",IF(AY34=TRUE,"Administrável",IF(AZ34=TRUE,"Indesejável",IF(BA34=TRUE,"Intolerável","")))) | AX34: =AND(U34>0,U34<=2,AP34>0,AP34<=7) -> FALSE | AY34: =OR(AND(U34>0,U34<=2,AP34>0,AP34>7,AP34<=13),AND(U34>0,U34>2,U34<=3,AP34>0,AP34<=10)) -> FALSE | AZ34: =OR(AND(U34>0,U34<=2,AP34>0,AP34>12,AP34<=17),AND(U34>0,U34>2,U34<=3,AP34>0,AP34>10,AP34<=13),AND(U34>0,U34>3,U34<=5,AP34>0,AP34<=10),AND(U34>0,U34>4,U34<=6,AP34>0,AP34<=7)) -> FALSE | BA34: =OR(AND(U34>0,U34>2,U34<=3,AP34>0,AP34>14,AP34<=20),AND(U34>0,U34>3,U34<=5,AP34>0,AP34>10),AND(U34>0,U34>5,U34<=6,AP34>0,AP34>7,AP34<=20)) -> FALSE
AZ35: =OR(AND(U35>0,U35<=2,AP35>0,AP35>12,AP35<=17),AND(U35>0,U35>2,U35<=3,AP35>0,AP35>10,AP35<=13),AND(U35>0,U35>3,U35<=5,AP35>0,AP35<=10),AND(U35>0,U35>4,U35<=6,AP35>0,AP35<=7)) -> FALSE | BA35: =OR(AND(U35>0,U35>2,U35<=3,AP35>0,AP35>14,AP35<=20),AND(U35>0,U35>3,U35<=5,AP35>0,AP35>10),AND(U35>0,U35>5,U35<=6,AP35>0,AP35>7,AP35<=20)) -> FALSE
B36: 14. | AN36: =IF(AH36="X",1)+IF(AI36="X",2)+IF(AJ36="X",3)+IF(AK36="X",4)+IF(AL36="X",5)+IF(AM36="X",6) -> 0 | AP36: =AA36+AF36+AN36 -> 0 | AQ36: =(AP36+U36)/2 -> 0 | AR36: =IF(AS36="",0,10) -> 0 | AS36: =IF(AX36=TRUE,"Desprezível",IF(AY36=TRUE,"Administrável",IF(AZ36=TRUE,"Indesejável",IF(BA36=TRUE,"Intolerável","")))) | AX36: =AND(U36>0,U36<=2,AP36>0,AP36<=7) -> FALSE | AY36: =OR(AND(U36>0,U36<=2,AP36>0,AP36>7,AP36<=13),AND(U36>0,U36>2,U36<=3,AP36>0,AP36<=10)) -> FALSE | AZ36: =OR(AND(U36>0,U36<=2,AP36>0,AP36>12,AP36<=17),AND(U36>0,U36>2,U36<=3,AP36>0,AP36>10,AP36<=13),AND(U36>0,U36>3,U36<=5,AP36>0,AP36<=10),AND(U36>0,U36>4,U36<=6,AP36>0,AP36<=7)) -> FALSE | BA36: =OR(AND(U36>0,U36>2,U36<=3,AP36>0,AP36>14,AP36<=20),AND(U36>0,U36>3,U36<=5,AP36>0,AP36>10),AND(U36>0,U36>5,U36<=6,AP36>0,AP36>7,AP36<=20)) -> FALSE
AZ37: =OR(AND(U37>0,U37<=2,AP37>0,AP37>12,AP37<=17),AND(U37>0,U37>2,U37<=3,AP37>0,AP37>10,AP37<=13),AND(U37>0,U37>3,U37<=5,AP37>0,AP37<=10),AND(U37>0,U37>4,U37<=6,AP37>0,AP37<=7)) -> FALSE | BA37: =OR(AND(U37>0,U37>2,U37<=3,AP37>0,AP37>14,AP37<=20),AND(U37>0,U37>3,U37<=5,AP37>0,AP37>10),AND(U37>0,U37>5,U37<=6,AP37>0,AP37>7,AP37<=20)) -> FALSE
B38: 15. | AN38: =IF(AH38="X",1)+IF(AI38="X",2)+IF(AJ38="X",3)+IF(AK38="X",4)+IF(AL38="X",5)+IF(AM38="X",6) -> 0 | AP38: =AA38+AF38+AN38 -> 0 | AQ38: =(AP38+U38)/2 -> 0 | AR38: =IF(AS38="",0,10) -> 0 | AS38: =IF(AX38=TRUE,"Desprezível",IF(AY38=TRUE,"Administrável",IF(AZ38=TRUE,"Indesejável",IF(BA38=TRUE,"Intolerável","")))) | AX38: =AND(U38>0,U38<=2,AP38>0,AP38<=7) -> FALSE | AY38: =OR(AND(U38>0,U38<=2,AP38>0,AP38>7,AP38<=13),AND(U38>0,U38>2,U38<=3,AP38>0,AP38<=10)) -> FALSE | AZ38: =OR(AND(U38>0,U38<=2,AP38>0,AP38>12,AP38<=17),AND(U38>0,U38>2,U38<=3,AP38>0,AP38>10,AP38<=13),AND(U38>0,U38>3,U38<=5,AP38>0,AP38<=10),AND(U38>0,U38>4,U38<=6,AP38>0,AP38<=7)) -> FALSE | BA38: =OR(AND(U38>0,U38>2,U38<=3,AP38>0,AP38>14,AP38<=20),AND(U38>0,U38>3,U38<=5,AP38>0,AP38>10),AND(U38>0,U38>5,U38<=6,AP38>0,AP38>7,AP38<=20)) -> FALSE
AZ39: =OR(AND(U39>0,U39<=2,AP39>0,AP39>12,AP39<=17),AND(U39>0,U39>2,U39<=3,AP39>0,AP39>10,AP39<=13),AND(U39>0,U39>3,U39<=5,AP39>0,AP39<=10),AND(U39>0,U39>4,U39<=6,AP39>0,AP39<=7)) -> FALSE | BA39: =OR(AND(U39>0,U39>2,U39<=3,AP39>0,AP39>14,AP39<=20),AND(U39>0,U39>3,U39<=5,AP39>0,AP39>10),AND(U39>0,U39>5,U39<=6,AP39>0,AP39>7,AP39<=20)) -> FALSE
B40: 16. | AN40: =IF(AH40="X",1)+IF(AI40="X",2)+IF(AJ40="X",3)+IF(AK40="X",4)+IF(AL40="X",5)+IF(AM40="X",6) -> 0 | AP40: =AA40+AF40+AN40 -> 0 | AQ40: =(AP40+U40)/2 -> 0 | AR40: =IF(AS40="",0,10) -> 0 | AS40: =IF(AX40=TRUE,"Desprezível",IF(AY40=TRUE,"Administrável",IF(AZ40=TRUE,"Indesejável",IF(BA40=TRUE,"Intolerável","")))) | AX40: =AND(U40>0,U40<=2,AP40>0,AP40<=7) -> FALSE | AY40: =OR(AND(U40>0,U40<=2,AP40>0,AP40>7,AP40<=13),AND(U40>0,U40>2,U40<=3,AP40>0,AP40<=10)) -> FALSE | AZ40: =OR(AND(U40>0,U40<=2,AP40>0,AP40>12,AP40<=17),AND(U40>0,U40>2,U40<=3,AP40>0,AP40>10,AP40<=13),AND(U40>0,U40>3,U40<=5,AP40>0,AP40<=10),AND(U40>0,U40>4,U40<=6,AP40>0,AP40<=7)) -> FALSE | BA40: =OR(AND(U40>0,U40>2,U40<=3,AP40>0,AP40>14,AP40<=20),AND(U40>0,U40>3,U40<=5,AP40>0,AP40>10),AND(U40>0,U40>5,U40<=6,AP40>0,AP40>7,AP40<=20)) -> FALSE
AZ41: =OR(AND(U41>0,U41<=2,AP41>0,AP41>12,AP41<=17),AND(U41>0,U41>2,U41<=3,AP41>0,AP41>10,AP41<=13),AND(U41>0,U41>3,U41<=5,AP41>0,AP41<=10),AND(U41>0,U41>4,U41<=6,AP41>0,AP41<=7)) -> FALSE | BA41: =OR(AND(U41>0,U41>2,U41<=3,AP41>0,AP41>14,AP41<=20),AND(U41>0,U41>3,U41<=5,AP41>0,AP41>10),AND(U41>0,U41>5,U41<=6,AP41>0,AP41>7,AP41<=20)) -> FALSE
B42: 17. | AN42: =IF(AH42="X",1)+IF(AI42="X",2)+IF(AJ42="X",3)+IF(AK42="X",4)+IF(AL42="X",5)+IF(AM42="X",6) -> 0 | AP42: =AA42+AF42+AN42 -> 0 | AQ42: =(AP42+U42)/2 -> 0 | AR42: =IF(AS42="",0,10) -> 0 | AS42: =IF(AX42=TRUE,"Desprezível",IF(AY42=TRUE,"Administrável",IF(AZ42=TRUE,"Indesejável",IF(BA42=TRUE,"Intolerável","")))) | AX42: =AND(U42>0,U42<=2,AP42>0,AP42<=7) -> FALSE | AY42: =OR(AND(U42>0,U42<=2,AP42>0,AP42>7,AP42<=13),AND(U42>0,U42>2,U42<=3,AP42>0,AP42<=10)) -> FALSE | AZ42: =OR(AND(U42>0,U42<=2,AP42>0,AP42>12,AP42<=17),AND(U42>0,U42>2,U42<=3,AP42>0,AP42>10,AP42<=13),AND(U42>0,U42>3,U42<=5,AP42>0,AP42<=10),AND(U42>0,U42>4,U42<=6,AP42>0,AP42<=7)) -> FALSE | BA42: =OR(AND(U42>0,U42>2,U42<=3,AP42>0,AP42>14,AP42<=20),AND(U42>0,U42>3,U42<=5,AP42>0,AP42>10),AND(U42>0,U42>5,U42<=6,AP42>0,AP42>7,AP42<=20)) -> FALSE
AZ43: =OR(AND(U43>0,U43<=2,AP43>0,AP43>12,AP43<=17),AND(U43>0,U43>2,U43<=3,AP43>0,AP43>10,AP43<=13),AND(U43>0,U43>3,U43<=5,AP43>0,AP43<=10),AND(U43>0,U43>4,U43<=6,AP43>0,AP43<=7)) -> FALSE | BA43: =OR(AND(U43>0,U43>2,U43<=3,AP43>0,AP43>14,AP43<=20),AND(U43>0,U43>3,U43<=5,AP43>0,AP43>10),AND(U43>0,U43>5,U43<=6,AP43>0,AP43>7,AP43<=20)) -> FALSE
B44: 18.
AZ45: =OR(AND(U45>0,U45<=2,AP45>0,AP45>12,AP45<=17),AND(U45>0,U45>2,U45<=3,AP45>0,AP45>10,AP45<=13),AND(U45>0,U45>3,U45<=5,AP45>0,AP45<=10),AND(U45>0,U45>4,U45<=6,AP45>0,AP45<=7)) -> FALSE | BA45: =OR(AND(U45>0,U45>2,U45<=3,AP45>0,AP45>14,AP45<=20),AND(U45>0,U45>3,U45<=5,AP45>0,AP45>10),AND(U45>0,U45>5,U45<=6,AP45>0,AP45>7,AP45<=20)) -> FALSE
B46: 19. | AN46: =IF(AH46="X",1)+IF(AI46="X",2)+IF(AJ46="X",3)+IF(AK46="X",4)+IF(AL46="X",5)+IF(AM46="X",6) -> 0 | AP46: =AA46+AF46+AN46 -> 0 | AQ46: =(AP46+U46)/2 -> 0 | AR46: =IF(AS46="",0,10) -> 0 | AS46: =IF(AX46=TRUE,"Desprezível",IF(AY46=TRUE,"Administrável",IF(AZ46=TRUE,"Indesejável",IF(BA46=TRUE,"Intolerável","")))) | AX46: =AND(U46>0,U46<=2,AP46>0,AP46<=7) -> FALSE | AY46: =OR(AND(U46>0,U46<=2,AP46>0,AP46>7,AP46<=13),AND(U46>0,U46>2,U46<=3,AP46>0,AP46<=10)) -> FALSE | AZ46: =OR(AND(U46>0,U46<=2,AP46>0,AP46>12,AP46<=17),AND(U46>0,U46>2,U46<=3,AP46>0,AP46>10,AP46<=13),AND(U46>0,U46>3,U46<=5,AP46>0,AP46<=10),AND(U46>0,U46>4,U46<=6,AP46>0,AP46<=7)) -> FALSE | BA46: =OR(AND(U46>0,U46>2,U46<=3,AP46>0,AP46>14,AP46<=20),AND(U46>0,U46>3,U46<=5,AP46>0,AP46>10),AND(U46>0,U46>5,U46<=6,AP46>0,AP46>7,AP46<=20)) -> FALSE
AZ47: =OR(AND(U47>0,U47<=2,AP47>0,AP47>12,AP47<=17),AND(U47>0,U47>2,U47<=3,AP47>0,AP47>10,AP47<=13),AND(U47>0,U47>3,U47<=5,AP47>0,AP47<=10),AND(U47>0,U47>4,U47<=6,AP47>0,AP47<=7)) -> FALSE | BA47: =OR(AND(U47>0,U47>2,U47<=3,AP47>0,AP47>14,AP47<=20),AND(U47>0,U47>3,U47<=5,AP47>0,AP47>10),AND(U47>0,U47>5,U47<=6,AP47>0,AP47>7,AP47<=20)) -> FALSE
B48: 20. | AN48: =IF(AH48="X",1)+IF(AI48="X",2)+IF(AJ48="X",3)+IF(AK48="X",4)+IF(AL48="X",5)+IF(AM48="X",6) -> 0 | AP48: =AA48+AF48+AN48 -> 0 | AQ48: =(AP48+U48)/2 -> 0 | AR48: =IF(AS48="",0,10) -> 0 | AS48: =IF(AX48=TRUE,"Desprezível",IF(AY48=TRUE,"Administrável",IF(AZ48=TRUE,"Indesejável",IF(BA48=TRUE,"Intolerável","")))) | AX48: =AND(U48>0,U48<=2,AP48>0,AP48<=7) -> FALSE | AY48: =OR(AND(U48>0,U48<=2,AP48>0,AP48>7,AP48<=13),AND(U48>0,U48>2,U48<=3,AP48>0,AP48<=10)) -> FALSE | AZ48: =OR(AND(U48>0,U48<=2,AP48>0,AP48>12,AP48<=17),AND(U48>0,U48>2,U48<=3,AP48>0,AP48>10,AP48<=13),AND(U48>0,U48>3,U48<=5,AP48>0,AP48<=10),AND(U48>0,U48>4,U48<=6,AP48>0,AP48<=7)) -> FALSE | BA48: =OR(AND(U48>0,U48>2,U48<=3,AP48>0,AP48>14,AP48<=20),AND(U48>0,U48>3,U48<=5,AP48>0,AP48>10),AND(U48>0,U48>5,U48<=6,AP48>0,AP48>7,AP48<=20)) -> FALSE
AZ49: =OR(AND(U49>0,U49<=2,AP49>0,AP49>12,AP49<=17),AND(U49>0,U49>2,U49<=3,AP49>0,AP49>10,AP49<=13),AND(U49>0,U49>3,U49<=5,AP49>0,AP49<=10),AND(U49>0,U49>4,U49<=6,AP49>0,AP49<=7)) -> FALSE | BA49: =OR(AND(U49>0,U49>2,U49<=3,AP49>0,AP49>14,AP49<=20),AND(U49>0,U49>3,U49<=5,AP49>0,AP49>10),AND(U49>0,U49>5,U49<=6,AP49>0,AP49>7,AP49<=20)) -> FALSE
B50: 21. | AN50: =IF(AH50="X",1)+IF(AI50="X",2)+IF(AJ50="X",3)+IF(AK50="X",4)+IF(AL50="X",5)+IF(AM50="X",6) -> 0 | AP50: =AA50+AF50+AN50 -> 0 | AQ50: =(AP50+U50)/2 -> 0 | AR50: =IF(AS50="",0,10) -> 0 | AS50: =IF(AX50=TRUE,"Desprezível",IF(AY50=TRUE,"Administrável",IF(AZ50=TRUE,"Indesejável",IF(BA50=TRUE,"Intolerável","")))) | AX50: =AND(U50>0,U50<=2,AP50>0,AP50<=7) -> FALSE | AY50: =OR(AND(U50>0,U50<=2,AP50>0,AP50>7,AP50<=13),AND(U50>0,U50>2,U50<=3,AP50>0,AP50<=10)) -> FALSE | AZ50: =OR(AND(U50>0,U50<=2,AP50>0,AP50>12,AP50<=17),AND(U50>0,U50>2,U50<=3,AP50>0,AP50>10,AP50<=13),AND(U50>0,U50>3,U50<=5,AP50>0,AP50<=10),AND(U50>0,U50>4,U50<=6,AP50>0,AP50<=7)) -> FALSE | BA50: =OR(AND(U50>0,U50>2,U50<=3,AP50>0,AP50>14,AP50<=20),AND(U50>0,U50>3,U50<=5,AP50>0,AP50>10),AND(U50>0,U50>5,U50<=6,AP50>0,AP50>7,AP50<=20)) -> FALSE
AZ51: =OR(AND(U51>0,U51<=2,AP51>0,AP51>12,AP51<=17),AND(U51>0,U51>2,U51<=3,AP51>0,AP51>10,AP51<=13),AND(U51>0,U51>3,U51<=5,AP51>0,AP51<=10),AND(U51>0,U51>4,U51<=6,AP51>0,AP51<=7)) -> FALSE | BA51: =OR(AND(U51>0,U51>2,U51<=3,AP51>0,AP51>14,AP51<=20),AND(U51>0,U51>3,U51<=5,AP51>0,AP51>10),AND(U51>0,U51>5,U51<=6,AP51>0,AP51>7,AP51<=20)) -> FALSE
B52: 22. | AN52: =IF(AH52="X",1)+IF(AI52="X",2)+IF(AJ52="X",3)+IF(AK52="X",4)+IF(AL52="X",5)+IF(AM52="X",6) -> 0 | AP52: =AA52+AF52+AN52 -> 0 | AQ52: =(AP52+U52)/2 -> 0 | AR52: =IF(AS52="",0,10) -> 0 | AS52: =IF(AX52=TRUE,"Desprezível",IF(AY52=TRUE,"Administrável",IF(AZ52=TRUE,"Indesejável",IF(BA52=TRUE,"Intolerável",""))))

Sheet Viabilidade NOVA
A1: 46082 | B1: OBRA: | C1: GRAND LODGE
B3: BASE DE DADOS
O4: LEGENDA:
E5: CONFERÊNCIAS | G5: CUSTO EQUIPE ADM PIEMONTE | H5: CUSTO CARGO | I5: POSSUI NESTE ORÇ | L5: valores orç | P5: preencher
B6: Modalidade de Contratação | C6: PMG | G6: COORDENADOR DE OBRAS | H6: =18100*15/12/2 -> 11312.5 | I6: 27 | K6: =H6/0.8 -> 14140.625 | L6: =[2]PRELIMINAR!$I$180 -> 14132.39 | M6: =K6<L6 -> FALSE | N6: =L6-K6 -> -8.235 | P6: preencher
B7: R$ Raso de Obra | C7: 46239534 | G7: ENGENHEIRO RESIDENTE | H7: =13100*15/12 -> 16375 | I7: 30 | K7: =H7/0.8 -> 20468.75 | L7: =[2]PRELIMINAR!$I$181 -> 20618.42 | M7: =K7<L7 -> TRUE | N7: =L7-K7 -> 149.67
B8: INCCs Raso de Obra | C8: =C7/C9 -> 38000.151 | G8: ESTAGIÁRIO | H8: =2100*2 -> 4200 | I8: 27 | K8: =H8/0.8 -> 5250 | L8: =[2]PRELIMINAR!$I$182 -> 5279.04 | M8: =K8<L8 -> TRUE | N8: =L8-K8 -> 29.04
B9: INCC Base | C9: 1216.825 | G9: MESTRE DE OBRAS | H9: =9200*1.94 -> 17848 | I9: 27 | K9: =H9/0.8 -> 22310 | L9: =[2]PRELIMINAR!$I$183 -> 22221.88 | M9: =K9<L9 -> FALSE | N9: =L9-K9 -> -88.12
B10: Prazo Obra | C10: 27 | G10: CONTRAMESTRE DE OBRAS | H10: 0 | K10: =H10/0.8 -> 0
B11: Data início Obra | C11: 46153 | E11: =C11=E34 -> TRUE | G11: ANALISTA DE ENGENHARIA | H11: =8000*15/12 -> 10000 | I11: 30 | K11: =H11/0.8 -> 12500 | L11: =[2]PRELIMINAR!$I$185 -> 11328.8 | M11: =K11<L11 -> FALSE | N11: =L11-K11 -> -1171.2
B12: Taxa Adm | C12: =9.5%*C7 -> 4392755.7 | E12: =C12=C36 -> FALSE | G12: ENCARREGADO | H12: 0 | K12: =H12/0.8 -> 0
B13: Reajuste Taxa Adm | C13: Sim | G13: ALMOXARIFE | H13: =4400*1.94 -> 8536 | I13: 27 | K13: =H13/0.8 -> 10670 | L13: =[2]PRELIMINAR!$I$187 -> 10633.68 | M13: =K13<L13 -> FALSE | N13: =L13-K13 -> -36.32
B14: Tem permuta | C14: Sim | G14: AUXILIAR DE ALMOXARIFE | H14: 0 | K14: =H14/0.8 -> 0
B15: R$ Permuta | C15: 2144183.4 | D15: =C15/C12 -> 0.48811807 | G15: ENGENHEIRO DE SEGURANÇA | H15: =14000*15/12/10 -> 1750 | I15: 27 | K15: =H15/0.8 -> 2187.5 | L15: =[2]PRELIMINAR!$I$189 -> 8425.13 | M15: =K15<L15 -> TRUE | N15: =L15-K15 -> 6237.63
B16: Taxa Assistência % | C16: 0.005 | G16: TÉCNICO SEGURANCA | H16: 0 | K16: =H16/0.8 -> 0
B17: Taxa Assistência R$ | C17: =C16*C7 -> 231197.67 | E17: =C17=C39 -> TRUE | G17: TÉCNICO EM EDIFICAÇÕES | H17: 0 | K17: =H17/0.8 -> 0
B18: Reajuste Taxa Assistência | C18: Sim | G18: FINALIZAÇÃO OBRA | H18: 31000 | I18: 1 | K18: =H18/0.8 -> 38750 | L18: =[2]PRELIMINAR!$I$203 -> 39303.51 | M18: =K18<L18 -> TRUE | N18: =L18-K18 -> 553.51
B19: R$ Equipe | C19: 2653384.8 | E19: =C19>-C42 -> TRUE
B20: Impostos (PIS + COFINS + ISS) | C20: 0.098071252
B21: Comissão Obra | C21: =3%*C12 -> 131782.67
B22: Necessário deslocamento | C22: Não
B23: Valor Descolamento | C23: 0
B24: IRPJ + CSLL | C24: 0.1088
B26: Despesa Adm Engenharia 2026 | C26: 0.15
B27: Despesa Adm Engenharia 2027 | C27: 0.15
B28: Despesa Adm Engenharia 2028 a ... | C28: 0.15
B31: VIABILIDADE
E32: MESES DE OBRA | AF32: MESES PÓS OBRA
E33: 1 | F33: 2 | G33: 3 | H33: 4 | I33: 5 | J33: 6 | K33: 7 | L33: 8 | M33: 9 | N33: 10 | O33: 11 | P33: 12 | Q33: 13 | R33: 14 | S33: 15 | T33: 16 | U33: 17 | V33: 18 | W33: 19 | X33: 20 | Y33: 21 | Z33: 22 | AA33: 23 | AB33: 24 | AC33: 25 | AD33: 26 | AE33: 27 | AF33: 28 | AG33: 29 | AH33: 30
E34: =C11 -> 46153 | F34: =E34+31 -> 46184 | G34: =F34+31 -> 46215 | H34: =G34+31 -> 46246 | I34: =H34+31 -> 46277 | J34: =I34+31 -> 46308 | K34: =J34+31 -> 46339 | L34: =K34+31 -> 46370 | M34: =L34+31 -> 46401 | ... AH34: =AG34+31 -> 47052
B35: DADOS | C35: VALORES TOTAIS | D35: VALORES %
A36: RECEITA | B36: Receita Taxa de Adm | C36: =SUM(E36:AH36) -> 2248572.2 | D36: =C36/C7 -> 0.048628783 | E36: =($C$12-$C$15)*E56 -> 27846.431 | F36: =($C$12-$C$15)*F56 -> 64727.693 | G36: =($C$12-$C$15)*G56 -> 49277.731 | H36: =($C$12-$C$15)*H56 -> 47467.473 | I36: =($C$12-$C$15)*I56 -> 51314.083 | J36: =($C$12-$C$15)*J56 -> 46796.656 | K36: =($C$12-$C$15)*K56 -> 24094.891 | L36: =($C$12-$C$15)*L56 -> 44306.632 | ... AH36: =($C$12-$C$15)*AH56 -> 0
A37: RECEITA | B37: Permuta Taxa de Adm | C37: =SUM(E37:AH37) -> 2144183.4 | D37: =C15/C7 -> 0.046371217 | E37: =$C$15/$C$10 -> 79414.201 | F37: =$C$15/$C$10 -> 79414.201 | G37: =$C$15/$C$10 -> 79414.201 | H37: =$C$15/$C$10 -> 79414.201 | I37: =$C$15/$C$10 -> 79414.201 | J37: =$C$15/$C$10 -> 79414.201 | K37: =$C$15/$C$10 -> 79414.201 | L37: =$C$15/$C$10 -> 79414.201 | ... AE37: =$C$15/$C$10 -> 79414.201
A38: RECEITA | B38: Receita MO Adm Piemonte | C38: =SUM(E38:AH38) -> 2653384.8 | D38: =C19/C7 -> 0.057383467 | E38: =$C$19/$C$10 -> 98273.509 | F38: =$C$19/$C$10 -> 98273.509 | G38: =$C$19/$C$10 -> 98273.509 | H38: =$C$19/$C$10 -> 98273.509 | I38: =$C$19/$C$10 -> 98273.509 | J38: =$C$19/$C$10 -> 98273.509 | K38: =$C$19/$C$10 -> 98273.509 | L38: =$C$19/$C$10 -> 98273.509 | ... AE38: =$C$19/$C$10 -> 98273.509
A39: RECEITA | B39: Receita Assistência | C39: =SUM(E39:AH39) -> 231197.67 | D39: =C16 -> 0.005 | AH39: =C16*C7 -> 231197.67
A40: DESPESA | B40: Impostos (PIS + COFINS + ISS) | C40: =SUM(E40:AH40) -> -713697.66 | D40: =-C20 -> -0.098071252 | E40: =$D$40*(E36+E37+E38+E39) -> -20156.991 | F40: =$D$40*(F36+F37+F38+F39) -> -23773.982 | G40: =$D$40*(G36+G37+G38+G39) -> -22258.785 | H40: =$D$40*(H36+H37+H38+H39) -> -22081.251 | I40: =$D$40*(I36+I37+I38+I39) -> -22458.493 | J40: =$D$40*(J36+J37+J38+J39) -> -22015.463 | K40: =$D$40*(K36+K37+K38+K39) -> -19789.072 | L40: =$D$40*(L36+L37+L38+L39) -> -21771.263 | ... AH40: =$D$40*(AH36+AH37+AH38+AH39) -> -22673.845
A41: DESPESA | B41: Despesa Assistência | C41: =SUM(E41:AH41) -> -693593 | D41: -0.015 | AH41: =D41*C7 -> -693593
A42: CUSTO | B42: Custos Equipe | C42: =SUM(E42:AH42) -> -2132488.2 | D42: =C42/C7 -> -0.046118289 | E42: =-((SUMPRODUCT($H$6:$H$18,$I$6:$I$18)/$C$10)+($C$21/$C$10)) -> -78981.043 | F42: =-((SUMPRODUCT($H$6:$H$18,$I$6:$I$18)/$C$10)+($C$21/$C$10)) -> -78981.043 | G42: =-((SUMPRODUCT($H$6:$H$18,$I$6:$I$18)/$C$10)+($C$21/$C$10)) -> -78981.043 | H42: =-((SUMPRODUCT($H$6:$H$18,$I$6:$I$18)/$C$10)+($C$21/$C$10)) -> -78981.043 | I42: =-((SUMPRODUCT($H$6:$H$18,$I$6:$I$18)/$C$10)+($C$21/$C$10)) -> -78981.043 | J42: =-((SUMPRODUCT($H$6:$H$18,$I$6:$I$18)/$C$10)+($C$21/$C$10)) -> -78981.043 | K42: =-((SUMPRODUCT($H$6:$H$18,$I$6:$I$18)/$C$10)+($C$21/$C$10)) -> -78981.043 | L42: =-((SUMPRODUCT($H$6:$H$18,$I$6:$I$18)/$C$10)+($C$21/$C$10)) -> -78981.043 | ... AE42: =-((SUMPRODUCT($H$6:$H$18,$I$6:$I$18)/$C$10)+($C$21/$C$10)) -> -78981.043
A43: CUSTO | B43: Custos Deslocamento | C43: =SUM(E43:AH43) -> 0 | D43: =C43/C7 -> 0 | E43: =-$C$23/$C$10 -> 0 | F43: =-$C$23/$C$10 -> 0 | G43: =-$C$23/$C$10 -> 0 | H43: =-$C$23/$C$10 -> 0 | I43: =-$C$23/$C$10 -> 0 | J43: =-$C$23/$C$10 -> 0 | K43: =-$C$23/$C$10 -> 0 | L43: =-$C$23/$C$10 -> 0 | ... AH43: =-$C$23/$C$10 -> 0
B45: MARGEM BRUTA R$ | C45: =SUM(C36:C43) -> 3737559.3 | D45: - | E45: =SUM(E36:E43) -> 106396.11 | F45: =SUM(F36:F43) -> 139660.38 | G45: =SUM(G36:G43) -> 125725.61 | H45: =SUM(H36:H43) -> 124092.89 | I45: =SUM(I36:I43) -> 127562.26 | J45: =SUM(J36:J43) -> 123487.86 | K45: =SUM(K36:K43) -> 103012.49 | L45: =SUM(L36:L43) -> 121242.04 | ... AH45: =SUM(AH36:AH43) -> -485069.18
B46: MARGEM BRUTA % | C46: - | D46: =C45/(C36+C37+C38+C39+C40) -> 0.56943388 | E46: =E45/(E36+E37+E38+E39+E40) -> 0.57394402 | F46: =F45/(F36+F37+F38+F39+F40) -> 0.6387645 | G46: =G45/(G36+G37+G38+G39+G40) -> 0.61417452 | H46: =H45/(H36+H37+H38+H39+H40) -> 0.61107247 | I46: =I45/(I36+I37+I38+I39+I40) -> 0.6176054 | J46: =J45/(J36+J37+J38+J39+J40) -> 0.60991025 | K46: =K45/(K36+K37+K38+K39+K40) -> 0.56602279 | L46: =L45/(L36+L37+L38+L39+L40) -> 0.60553477 | ... AH46: =AH45/(AH36+AH37+AH38+AH39+AH40) -> -2.3262051
A48: DESPESA | B48: Despesas Adm Pie | C48: =SUM(E48:AH48) -> -947350.94 | D48: variável / ano | E48: =-$C$26*(E36+E37+E38+E40) -> -27806.573 | F48: =-$C$26*(F36+F37+F38+F40) -> -32796.213 | G48: =-$C$26*(G36+G37+G38+G40) -> -30705.998 | H48: =-$C$26*(H36+H37+H38+H40) -> -30461.09 | I48: =-$C$26*(I36+I37+I38+I40) -> -30981.495 | J48: =-$C$26*(J36+J37+J38+J40) -> -30370.336 | K48: =-$C$26*(K36+K37+K38+K40) -> -27299.029 | L48: =-$C$26*(L36+L37+L38+L40) -> -30033.462 | M48: =-$C$27*(M36+M37+M38+M40) -> -29006.907 | N48: =-$C$27*(N36+N37+N38+N40) -> -29151.448 | O48: =-$C$27*(O36+O37+O38+O40) -> -34389.763 | P48: =-$C$27*(P36+P37+P38+P40) -> -35743.001 | Q48: =-$C$27*(Q36+Q37+Q38+Q40) -> -38488.644 | R48: =-$C$27*(R36+R37+R38+R40) -> -39168.865 | S48: =-$C$27*(S36+S37+S38+S40) -> -37865.87 | T48: =-$C$27*(T36+T37+T38+T40) -> -38328.162 | ... X48: =-$C$27*(X36+X37+X38+X40) -> -39684.369 | Y48: =-$C$28*(Y36+Y37+Y38+Y40) -> -41996.999 | Z48: =-$C$28*(Z36+Z37+Z38+Z40) -> -39751.684 | AA48: =-$C$28*(AA36+AA37+AA38+AA40) -> -39753.576 | AB48: =-$C$28*(AB36+AB37+AB38+AB40) -> -38863.011 | AC48: =-$C$28*(AC36+AC37+AC38+AC40) -> -33153.292 | AD48: =-$C$28*(AD36+AD37+AD38+AD40) -> -31260.676 | AE48: =-$C$28*(AE36+AE37+AE38+AE40) -> -30879.871
B50: RESULTADO | C50: =SUM(E50:AH50) -> 2790208.3 | D50: - | E50: =SUM(E36:E43,E48) -> 78589.535 | F50: =SUM(F36:F43,F48) -> 106864.17 | G50: =SUM(G36:G43,G48) -> 95019.615 | H50: =SUM(H36:H43,H48) -> 93631.799 | I50: =SUM(I36:I43,I48) -> 96580.762 | J50: =SUM(J36:J43,J48) -> 93117.525 | K50: =SUM(K36:K43,K48) -> 75713.456 | L50: =SUM(L36:L43,L48) -> 91208.574 | ... AH50: =SUM(AH36:AH43,AH48) -> -485069.18
B51: IRPJ + CSLL | C51: =SUM(E51:AH51) -> -791774.39 | D51: =C24 -> 0.1088 | E51: =-$C$24*(E36+E37+E38+E39) -> -22362.115 | F51: =-$C$24*(F36+F37+F38+F39) -> -26374.796 | G51: =-$C$24*(G36+G37+G38+G39) -> -24693.84 | H51: =-$C$24*(H36+H37+H38+H39) -> -24496.884 | I51: =-$C$24*(I36+I37+I38+I39) -> -24915.395 | J51: =-$C$24*(J36+J37+J38+J39) -> -24423.899 | K51: =-$C$24*(K36+K37+K38+K39) -> -21953.947 | L51: =-$C$24*(L36+L37+L38+L39) -> -24152.984 | ... AH51: =-$C$24*(AH36+AH37+AH38+AH39) -> -25154.306
B52: Resultado Final | C52: =SUM(E52:AH52) -> 1998433.9 | D52: - | E52: =SUM(E50:E51) -> 56227.421 | F52: =SUM(F50:F51) -> 80489.369 | G52: =SUM(G50:G51) -> 70325.775 | H52: =SUM(H50:H51) -> 69134.915 | I52: =SUM(I50:I51) -> 71665.367 | J52: =SUM(J50:J51) -> 68693.626 | K52: =SUM(K50:K51) -> 53759.509 | L52: =SUM(L50:L51) -> 67055.59 | ... AH52: =SUM(AH50:AH51) -> -510223.49
B53: Margem Líquida | C53: - | D53: =C52/(C36+C37+C38+C39+C40) -> 0.30447036 | E53: =E52/(E36+E37+E38+E39+E40) -> 0.30331365 | F53: =F52/(F36+F37+F38+F39+F40) -> 0.36813413 | G53: =G52/(G36+G37+G38+G39+G40) -> 0.34354415 | H53: =H52/(H36+H37+H38+H39+H40) -> 0.3404421 | I53: =I52/(I36+I37+I38+I39+I40) -> 0.34697503 | J53: =J52/(J36+J37+J38+J39+J40) -> 0.33927988 | K53: =K52/(K36+K37+K38+K39+K40) -> 0.29539242 | L53: =L52/(L36+L37+L38+L39+L40) -> 0.3349044 | ... AH53: =AH52/(AH36+AH37+AH38+AH39+AH40) -> -2.4468355
B54: RECEITA LÍQUIDA | C54: =SUM(E54:AH54) -> 6563640.4 | D54: - | E54: =E36+E37+E38+E39+E40 -> 185377.15 | F54: =F36+F37+F38+F39+F40 -> 218641.42 | G54: =G36+G37+G38+G39+G40 -> 204706.66 | H54: =H36+H37+H38+H39+H40 -> 203073.93 | I54: =I36+I37+I38+I39+I40 -> 206543.3 | J54: =J36+J37+J38+J39+J40 -> 202468.9 | K54: =K36+K37+K38+K39+K40 -> 181993.53 | L54: =L36+L37+L38+L39+L40 -> 200223.08 | ... AH54: =AH36+AH37+AH38+AH39+AH40 -> 208523.82
B56: CURVA FÍSICA OBRA | C56: - | D56: =SUM(E56:AH56) -> 1 | E56: 0.01238405 | F56: 0.02878613 | G56: 0.02191512 | H56: 0.02111005 | I56: 0.02282074 | J56: 0.02081172 | K56: 0.01071564 | L56: 0.01970434 | M56: 0.01632982 | N56: 0.01680496 | O56: 0.03402449 | P56: 0.03847289 | Q56: 0.04749844 | R56: 0.04973448 | S56: 0.04545124 | T56: 0.0469709 | U56: 0.05916078 | V56: 0.06179089 | W56: 0.06738296 | X56: 0.05142906 | Y56: 0.0590312 | Z56: 0.05165034 | AA56: 0.05165656 | AB56: 0.04872907 | AC56: 0.02995993 | AD56: 0.02373847 | AE56: 0.02248668 | AF56: 0.01503072 | AG56: 0.00441833
B58: RECEITAS - IMPOSTOS | C58: =SUM(E58:AH58) -> 5771866.1 | E58: =E54+E51 -> 163015.04 | F58: =F54+F51 -> 192266.63 | G58: =G54+G51 -> 180012.82 | H58: =H54+H51 -> 178577.05 | I58: =I54+I51 -> 181627.91 | J58: =J54+J51 -> 178045 | K58: =K54+K51 -> 160039.58 | L58: =L54+L51 -> 176070.1 | ... AH58: =AH54+AH51 -> 183369.52
B61: ANÁLISES
C63: %
A64: 1 | B64: Risco Estouro / Banda Estouro | C64: 0.04
A65: 2 | B65: Ganho Economia / Banda Economia | C65: 0.4
B67: CUSTO CAPITAL / MÊS (10% ANO) SEM INCC | C67: =POWER(1 + 10%, 1/12) - 1 -> 0.0079741404
B68: INCC ANO | C68: 0.062
B70: VPL | C70: =NPV(C67,E52:AH52) -> 1822056
B71: RECEITA | C71: =NPV(C67,E54:AH54) -> 5828250.6
B72: VPL/RECEITA | C72: =C70/C71 -> 0.31262485

Sheet Viabilidade NOVA_34%
A1: 46082 | B1: OBRA: | C1: GRAND LODGE
B3: BASE DE DADOS
O4: LEGENDA:
E5: CONFERÊNCIAS | G5: CUSTO EQUIPE ADM PIEMONTE | H5: CUSTO CARGO | I5: POSSUI NESTE ORÇ | L5: valores orç | P5: preencher
B6: Modalidade de Contratação | C6: PMG | G6: COORDENADOR DE OBRAS | H6: =18100*15/12/2 -> 11312.5 | I6: 27 | K6: =H6/0.8 -> 14140.625 | L6: =[2]PRELIMINAR!$I$180 -> 14132.39 | M6: =K6<L6 -> FALSE | N6: =L6-K6 -> -8.235 | P6: preencher
B7: R$ Raso de Obra | C7: 46239534 | G7: ENGENHEIRO RESIDENTE | H7: =13100*15/12 -> 16375 | I7: 30 | K7: =H7/0.8 -> 20468.75 | L7: =[2]PRELIMINAR!$I$181 -> 20618.42 | M7: =K7<L7 -> TRUE | N7: =L7-K7 -> 149.67
B8: INCCs Raso de Obra | C8: =C7/C9 -> 38000.151 | G8: ESTAGIÁRIO | H8: =2100*2 -> 4200 | I8: 27 | K8: =H8/0.8 -> 5250 | L8: =[2]PRELIMINAR!$I$182 -> 5279.04 | M8: =K8<L8 -> TRUE | N8: =L8-K8 -> 29.04
B9: INCC Base | C9: 1216.825 | G9: MESTRE DE OBRAS | H9: =9200*1.94 -> 17848 | I9: 27 | K9: =H9/0.8 -> 22310 | L9: =[2]PRELIMINAR!$I$183 -> 22221.88 | M9: =K9<L9 -> FALSE | N9: =L9-K9 -> -88.12
B10: Prazo Obra | C10: 27 | G10: CONTRAMESTRE DE OBRAS | H10: 0 | K10: =H10/0.8 -> 0
B11: Data início Obra | C11: 46153 | E11: =C11=E34 -> TRUE | G11: ANALISTA DE ENGENHARIA | H11: =8000*15/12 -> 10000 | I11: 30 | K11: =H11/0.8 -> 12500 | L11: =[2]PRELIMINAR!$I$185 -> 11328.8 | M11: =K11<L11 -> FALSE | N11: =L11-K11 -> -1171.2
B12: Taxa Adm | C12: =9.5%*C7 -> 4392755.7 | E12: =C12=C36 -> FALSE | G12: ENCARREGADO | H12: 0 | K12: =H12/0.8 -> 0
B13: Reajuste Taxa Adm | C13: Sim | G13: ALMOXARIFE | H13: =4400*1.94 -> 8536 | I13: 27 | K13: =H13/0.8 -> 10670 | L13: =[2]PRELIMINAR!$I$187 -> 10633.68 | M13: =K13<L13 -> FALSE | N13: =L13-K13 -> -36.32
B14: Tem permuta | C14: Sim | G14: AUXILIAR DE ALMOXARIFE | H14: 0 | K14: =H14/0.8 -> 0
B15: R$ Permuta | C15: 2144183.4 | D15: =C15/C12 -> 0.48811807 | G15: ENGENHEIRO DE SEGURANÇA | H15: =14000*15/12/10 -> 1750 | I15: 27 | K15: =H15/0.8 -> 2187.5 | L15: =[2]PRELIMINAR!$I$189 -> 8425.13 | M15: =K15<L15 -> TRUE | N15: =L15-K15 -> 6237.63
B16: Taxa Assistência % | C16: 0.005 | G16: TÉCNICO SEGURANCA | H16: 0 | K16: =H16/0.8 -> 0
B17: Taxa Assistência R$ | C17: =C16*C7 -> 231197.67 | E17: =C17=C39 -> TRUE | G17: TÉCNICO EM EDIFICAÇÕES | H17: 0 | K17: =H17/0.8 -> 0
B18: Reajuste Taxa Assistência | C18: Sim | G18: FINALIZAÇÃO OBRA | H18: 31000 | I18: 1 | K18: =H18/0.8 -> 38750 | L18: =[2]PRELIMINAR!$I$203 -> 39303.51 | M18: =K18<L18 -> TRUE | N18: =L18-K18 -> 553.51
B19: R$ Equipe | C19: 2653384.8 | E19: =C19>-C42 -> TRUE
B20: Impostos (PIS + COFINS + ISS) | C20: 0.098071252
B21: Comissão Obra | C21: =3%*C12 -> 131782.67
B22: Necessário deslocamento | C22: Não
B23: Valor Descolamento | C23: 0
B24: IRPJ + CSLL | C24: 0.1088
B26: Despesa Adm Engenharia 2026 | C26: ='[3]DRE Geral'!$U$23 -> 0.34650531
B27: Despesa Adm Engenharia 2027 | C27: =C26 -> 0.34650531
B28: Despesa Adm Engenharia 2028 a ... | C28: =C27 -> 0.34650531
B31: VIABILIDADE
E32: MESES DE OBRA | AF32: MESES PÓS OBRA
E33: 1 | F33: 2 | G33: 3 | H33: 4 | I33: 5 | J33: 6 | K33: 7 | L33: 8 | M33: 9 | N33: 10 | O33: 11 | P33: 12 | Q33: 13 | R33: 14 | S33: 15 | T33: 16 | U33: 17 | V33: 18 | W33: 19 | X33: 20 | Y33: 21 | Z33: 22 | AA33: 23 | AB33: 24 | AC33: 25 | AD33: 26 | AE33: 27 | AF33: 28 | AG33: 29 | AH33: 30
E34: =C11 -> 46153 | F34: =E34+31 -> 46184 | G34: =F34+31 -> 46215 | H34: =G34+31 -> 46246 | I34: =H34+31 -> 46277 | J34: =I34+31 -> 46308 | K34: =J34+31 -> 46339 | L34: =K34+31 -> 46370 | M34: =L34+31 -> 46401 | ... AH34: =AG34+31 -> 47052
B35: DADOS | C35: VALORES TOTAIS | D35: VALORES %
A36: RECEITA | B36: Receita Taxa de Adm | C36: =SUM(E36:AH36) -> 2248572.2 | D36: =C36/C7 -> 0.048628783 | E36: =($C$12-$C$15)*E56 -> 27846.431 | F36: =($C$12-$C$15)*F56 -> 64727.693 | G36: =($C$12-$C$15)*G56 -> 49277.731 | H36: =($C$12-$C$15)*H56 -> 47467.473 | I36: =($C$12-$C$15)*I56 -> 51314.083 | J36: =($C$12-$C$15)*J56 -> 46796.656 | K36: =($C$12-$C$15)*K56 -> 24094.891 | L36: =($C$12-$C$15)*L56 -> 44306.632 | ... AH36: =($C$12-$C$15)*AH56 -> 0
A37: RECEITA | B37: Permuta Taxa de Adm | C37: =SUM(E37:AH37) -> 2144183.4 | D37: =C15/C7 -> 0.046371217 | E37: =$C$15/$C$10 -> 79414.201 | F37: =$C$15/$C$10 -> 79414.201 | G37: =$C$15/$C$10 -> 79414.201 | H37: =$C$15/$C$10 -> 79414.201 | I37: =$C$15/$C$10 -> 79414.201 | J37: =$C$15/$C$10 -> 79414.201 | K37: =$C$15/$C$10 -> 79414.201 | L37: =$C$15/$C$10 -> 79414.201 | ... AE37: =$C$15/$C$10 -> 79414.201
A38: RECEITA | B38: Receita MO Adm Piemonte | C38: =SUM(E38:AH38) -> 2653384.8 | D38: =C19/C7 -> 0.057383467 | E38: =$C$19/$C$10 -> 98273.509 | F38: =$C$19/$C$10 -> 98273.509 | G38: =$C$19/$C$10 -> 98273.509 | H38: =$C$19/$C$10 -> 98273.509 | I38: =$C$19/$C$10 -> 98273.509 | J38: =$C$19/$C$10 -> 98273.509 | K38: =$C$19/$C$10 -> 98273.509 | L38: =$C$19/$C$10 -> 98273.509 | ... AE38: =$C$19/$C$10 -> 98273.509
A39: RECEITA | B39: Receita Assistência | C39: =SUM(E39:AH39) -> 231197.67 | D39: =C16 -> 0.005 | AH39: =C16*C7 -> 231197.67
A40: DESPESA | B40: Impostos (PIS + COFINS + ISS) | C40: =SUM(E40:AH40) -> -713697.66 | D40: =-C20 -> -0.098071252 | E40: =$D$40*(E36+E37+E38+E39) -> -20156.991 | F40: =$D$40*(F36+F37+F38+F39) -> -23773.982 | G40: =$D$40*(G36+G37+G38+G39) -> -22258.785 | H40: =$D$40*(H36+H37+H38+H39) -> -22081.251 | I40: =$D$40*(I36+I37+I38+I39) -> -22458.493 | J40: =$D$40*(J36+J37+J38+J39) -> -22015.463 | K40: =$D$40*(K36+K37+K38+K39) -> -19789.072 | L40: =$D$40*(L36+L37+L38+L39) -> -21771.263 | ... AH40: =$D$40*(AH36+AH37+AH38+AH39) -> -22673.845
A41: DESPESA | B41: Despesa Assistência | C41: =SUM(E41:AH41) -> -693593 | D41: -0.015 | AH41: =D41*C7 -> -693593
A42: CUSTO | B42: Custos Equipe | C42: =SUM(E42:AH42) -> -2132488.2 | D42: =C42/C7 -> -0.046118289 | E42: =-((SUMPRODUCT($H$6:$H$18,$I$6:$I$18)/$C$10)+($C$21/$C$10)) -> -78981.043 | F42: =-((SUMPRODUCT($H$6:$H$18,$I$6:$I$18)/$C$10)+($C$21/$C$10)) -> -78981.043 | G42: =-((SUMPRODUCT($H$6:$H$18,$I$6:$I$18)/$C$10)+($C$21/$C$10)) -> -78981.043 | H42: =-((SUMPRODUCT($H$6:$H$18,$I$6:$I$18)/$C$10)+($C$21/$C$10)) -> -78981.043 | I42: =-((SUMPRODUCT($H$6:$H$18,$I$6:$I$18)/$C$10)+($C$21/$C$10)) -> -78981.043 | J42: =-((SUMPRODUCT($H$6:$H$18,$I$6:$I$18)/$C$10)+($C$21/$C$10)) -> -78981.043 | K42: =-((SUMPRODUCT($H$6:$H$18,$I$6:$I$18)/$C$10)+($C$21/$C$10)) -> -78981.043 | L42: =-((SUMPRODUCT($H$6:$H$18,$I$6:$I$18)/$C$10)+($C$21/$C$10)) -> -78981.043 | ... AE42: =-((SUMPRODUCT($H$6:$H$18,$I$6:$I$18)/$C$10)+($C$21/$C$10)) -> -78981.043
A43: CUSTO | B43: Custos Deslocamento | C43: =SUM(E43:AH43) -> 0 | D43: =C43/C7 -> 0 | E43: =-$C$23/$C$10 -> 0 | F43: =-$C$23/$C$10 -> 0 | G43: =-$C$23/$C$10 -> 0 | H43: =-$C$23/$C$10 -> 0 | I43: =-$C$23/$C$10 -> 0 | J43: =-$C$23/$C$10 -> 0 | K43: =-$C$23/$C$10 -> 0 | L43: =-$C$23/$C$10 -> 0 | ... AH43: =-$C$23/$C$10 -> 0
B45: MARGEM BRUTA R$ | C45: =SUM(C36:C43) -> 3737559.3 | D45: - | E45: =SUM(E36:E43) -> 106396.11 | F45: =SUM(F36:F43) -> 139660.38 | G45: =SUM(G36:G43) -> 125725.61 | H45: =SUM(H36:H43) -> 124092.89 | I45: =SUM(I36:I43) -> 127562.26 | J45: =SUM(J36:J43) -> 123487.86 | K45: =SUM(K36:K43) -> 103012.49 | L45: =SUM(L36:L43) -> 121242.04 | ... AH45: =SUM(AH36:AH43) -> -485069.18
B46: MARGEM BRUTA % | C46: - | D46: =C45/(C36+C37+C38+C39+C40) -> 0.56943388 | E46: =E45/(E36+E37+E38+E39+E40) -> 0.57394402 | F46: =F45/(F36+F37+F38+F39+F40) -> 0.6387645 | G46: =G45/(G36+G37+G38+G39+G40) -> 0.61417452 | H46: =H45/(H36+H37+H38+H39+H40) -> 0.61107247 | I46: =I45/(I36+I37+I38+I39+I40) -> 0.6176054 | J46: =J45/(J36+J37+J38+J39+J40) -> 0.60991025 | K46: =K45/(K36+K37+K38+K39+K40) -> 0.56602279 | L46: =L45/(L36+L37+L38+L39+L40) -> 0.60553477 | ... AH46: =AH45/(AH36+AH37+AH38+AH39+AH40) -> -2.3262051
A48: DESPESA | B48: Despesas Adm Pie | C48: =SUM(E48:AH48) -> -1506959.6 | D48: variável / ano | E48: =-$C$26*(E36+E37) -> -37166.378 | F48: =-$C$26*(F36+F37) -> -49945.931 | G48: =-$C$26*(G36+G37) -> -44592.437 | H48: =-$C$26*(H36+H37) -> -43965.173 | I48: =-$C$26*(I36+I37) -> -45298.044 | J48: =-$C$26*(J36+J37) -> -43732.732 | K48: =-$C$26*(K36+K37) -> -35866.45 | L48: =-$C$26*(L36+L37) -> -42869.925 | M48: =-$C$27*(M36+M37) -> -40240.694 | N48: =-$C$27*(N36+N37) -> -40610.896 | O48: =-$C$27*(O36+O37) -> -54027.359 | P48: =-$C$27*(P36+P37) -> -57493.295 | Q48: =-$C$27*(Q36+Q37) -> -64525.482 | R48: =-$C$27*(R36+R37) -> -66267.675 | S48: =-$C$27*(S36+S37) -> -62930.422 | T48: =-$C$27*(T36+T37) -> -64114.453 | ... X48: =-$C$27*(X36+X37) -> -67587.994 | Y48: =-$C$28*(Y36+Y37) -> -73511.142 | Z48: =-$C$28*(Z36+Z37) -> -67760.402 | AA48: =-$C$28*(AA36+AA37) -> -67765.249 | AB48: =-$C$28*(AB36+AB37) -> -65484.318 | AC48: =-$C$28*(AC36+AC37) -> -50860.488 | AD48: =-$C$28*(AD36+AD37) -> -46013.086 | AE48: =-$C$28*(AE36+AE37) -> -45037.764
B50: RESULTADO | C50: =SUM(E50:AH50) -> 2230599.7 | D50: - | E50: =SUM(E36:E43,E48) -> 69229.73 | F50: =SUM(F36:F43,F48) -> 89714.447 | G50: =SUM(G36:G43,G48) -> 81133.176 | H50: =SUM(H36:H43,H48) -> 80127.716 | I50: =SUM(I36:I43,I48) -> 82264.213 | J50: =SUM(J36:J43,J48) -> 79755.129 | K50: =SUM(K36:K43,K48) -> 67146.036 | L50: =SUM(L36:L43,L48) -> 78372.111 | ... AH50: =SUM(AH36:AH43,AH48) -> -485069.18
B51: IRPJ + CSLL | C51: =SUM(E51:AH51) -> -791774.39 | D51: =C24 -> 0.1088 | E51: =-$C$24*(E36+E37+E38+E39) -> -22362.115 | F51: =-$C$24*(F36+F37+F38+F39) -> -26374.796 | G51: =-$C$24*(G36+G37+G38+G39) -> -24693.84 | H51: =-$C$24*(H36+H37+H38+H39) -> -24496.884 | I51: =-$C$24*(I36+I37+I38+I39) -> -24915.395 | J51: =-$C$24*(J36+J37+J38+J39) -> -24423.899 | K51: =-$C$24*(K36+K37+K38+K39) -> -21953.947 | L51: =-$C$24*(L36+L37+L38+L39) -> -24152.984 | ... AH51: =-$C$24*(AH36+AH37+AH38+AH39) -> -25154.306
B52: Resultado Final | C52: =SUM(E52:AH52) -> 1438825.3 | D52: - | E52: =SUM(E50:E51) -> 46867.615 | F52: =SUM(F50:F51) -> 63339.651 | G52: =SUM(G50:G51) -> 56439.336 | H52: =SUM(H50:H51) -> 55630.832 | I52: =SUM(I50:I51) -> 57348.818 | J52: =SUM(J50:J51) -> 55331.23 | K52: =SUM(K50:K51) -> 45192.089 | L52: =SUM(L50:L51) -> 54219.127 | ... AH52: =SUM(AH50:AH51) -> -510223.49
B53: Margem Líquida | C53: - | D53: =C52/(C36+C37+C38+C39+C40) -> 0.21921148 | E53: =E52/(E36+E37+E38+E39+E40) -> 0.25282304 | F53: =F52/(F36+F37+F38+F39+F40) -> 0.28969648 | G53: =G52/(G36+G37+G38+G39+G40) -> 0.27570836 | H53: =H52/(H36+H37+H38+H39+H40) -> 0.27394374 | I53: =I52/(I36+I37+I38+I39+I40) -> 0.27766003 | J53: =J52/(J36+J37+J38+J39+J40) -> 0.27328261 | K53: =K52/(K36+K37+K38+K39+K40) -> 0.24831701 | L53: =L52/(L36+L37+L38+L39+L40) -> 0.27079359 | ... AH53: =AH52/(AH36+AH37+AH38+AH39+AH40) -> -2.4468355
B54: RECEITA LÍQUIDA | C54: =SUM(E54:AH54) -> 6563640.4 | D54: - | E54: =E36+E37+E38+E39+E40 -> 185377.15 | F54: =F36+F37+F38+F39+F40 -> 218641.42 | G54: =G36+G37+G38+G39+G40 -> 204706.66 | H54: =H36+H37+H38+H39+H40 -> 203073.93 | I54: =I36+I37+I38+I39+I40 -> 206543.3 | J54: =J36+J37+J38+J39+J40 -> 202468.9 | K54: =K36+K37+K38+K39+K40 -> 181993.53 | L54: =L36+L37+L38+L39+L40 -> 200223.08 | ... AH54: =AH36+AH37+AH38+AH39+AH40 -> 208523.82
B56: CURVA FÍSICA OBRA | C56: - | D56: =SUM(E56:AH56) -> 1 | E56: 0.01238405 | F56: 0.02878613 | G56: 0.02191512 | H56: 0.02111005 | I56: 0.02282074 | J56: 0.02081172 | K56: 0.01071564 | L56: 0.01970434 | M56: 0.01632982 | N56: 0.01680496 | O56: 0.03402449 | P56: 0.03847289 | Q56: 0.04749844 | R56: 0.04973448 | S56: 0.04545124 | T56: 0.0469709 | U56: 0.05916078 | V56: 0.06179089 | W56: 0.06738296 | X56: 0.05142906 | Y56: 0.0590312 | Z56: 0.05165034 | AA56: 0.05165656 | AB56: 0.04872907 | AC56: 0.02995993 | AD56: 0.02373847 | AE56: 0.02248668 | AF56: 0.01503072 | AG56: 0.00441833
B58: RECEITAS - IMPOSTOS | C58: =SUM(E58:AH58) -> 5771866.1 | E58: =E54+E51 -> 163015.04 | F58: =F54+F51 -> 192266.63 | G58: =G54+G51 -> 180012.82 | H58: =H54+H51 -> 178577.05 | I58: =I54+I51 -> 181627.91 | J58: =J54+J51 -> 178045 | K58: =K54+K51 -> 160039.58 | L58: =L54+L51 -> 176070.1 | ... AH58: =AH54+AH51 -> 183369.52
B61: ANÁLISES
C63: %
A64: 1 | B64: Risco Estouro / Banda Estouro | C64: 0.04
A65: 2 | B65: Ganho Economia / Banda Economia | C65: 0.4
B67: CUSTO CAPITAL / MÊS (10% ANO) SEM INCC | C67: =POWER(1 + 10%, 1/12) - 1 -> 0.0079741404
B68: INCC ANO | C68: 0.062
B70: VPL | C70: =NPV(C67,E52:AH52) -> 1327274.4
B71: RECEITA | C71: =NPV(C67,E54:AH54) -> 5828250.6
B72: VPL/RECEITA | C72: =C70/C71 -> 0.22773118

Sheet Viabilidade NOVA_23%
A1: 46082 | B1: OBRA: | C1: GRAND LODGE
B3: BASE DE DADOS
O4: LEGENDA:
E5: CONFERÊNCIAS | G5: CUSTO EQUIPE ADM PIEMONTE | H5: CUSTO CARGO | I5: POSSUI NESTE ORÇ | L5: valores orç | P5: preencher
B6: Modalidade de Contratação | C6: PMG | G6: COORDENADOR DE OBRAS | H6: =18100*15/12/2 -> 11312.5 | I6: 27 | K6: =H6/0.8 -> 14140.625 | L6: =[2]PRELIMINAR!$I$180 -> 14132.39 | M6: =K6<L6 -> FALSE | N6: =L6-K6 -> -8.235 | P6: preencher
B7: R$ Raso de Obra | C7: 46239534 | G7: ENGENHEIRO RESIDENTE | H7: =13100*15/12 -> 16375 | I7: 30 | K7: =H7/0.8 -> 20468.75 | L7: =[2]PRELIMINAR!$I$181 -> 20618.42 | M7: =K7<L7 -> TRUE | N7: =L7-K7 -> 149.67
B8: INCCs Raso de Obra | C8: =C7/C9 -> 38000.151 | G8: ESTAGIÁRIO | H8: =2100*2 -> 4200 | I8: 27 | K8: =H8/0.8 -> 5250 | L8: =[2]PRELIMINAR!$I$182 -> 5279.04 | M8: =K8<L8 -> TRUE | N8: =L8-K8 -> 29.04
B9: INCC Base | C9: 1216.825 | G9: MESTRE DE OBRAS | H9: =9200*1.94 -> 17848 | I9: 27 | K9: =H9/0.8 -> 22310 | L9: =[2]PRELIMINAR!$I$183 -> 22221.88 | M9: =K9<L9 -> FALSE | N9: =L9-K9 -> -88.12
B10: Prazo Obra | C10: 27 | G10: CONTRAMESTRE DE OBRAS | H10: 0 | K10: =H10/0.8 -> 0
B11: Data início Obra | C11: 46153 | E11: =C11=E34 -> TRUE | G11: ANALISTA DE ENGENHARIA | H11: =8000*15/12 -> 10000 | I11: 30 | K11: =H11/0.8 -> 12500 | L11: =[2]PRELIMINAR!$I$185 -> 11328.8 | M11: =K11<L11 -> FALSE | N11: =L11-K11 -> -1171.2
B12: Taxa Adm | C12: =9.5%*C7 -> 4392755.7 | E12: =C12=C36 -> FALSE | G12: ENCARREGADO | H12: 0 | K12: =H12/0.8 -> 0
B13: Reajuste Taxa Adm | C13: Sim | G13: ALMOXARIFE | H13: =4400*1.94 -> 8536 | I13: 27 | K13: =H13/0.8 -> 10670 | L13: =[2]PRELIMINAR!$I$187 -> 10633.68 | M13: =K13<L13 -> FALSE | N13: =L13-K13 -> -36.32
B14: Tem permuta | C14: Sim | G14: AUXILIAR DE ALMOXARIFE | H14: 0 | K14: =H14/0.8 -> 0
B15: R$ Permuta | C15: 2144183.4 | D15: =C15/C12 -> 0.48811807 | G15: ENGENHEIRO DE SEGURANÇA | H15: =14000*15/12/10 -> 1750 | I15: 27 | K15: =H15/0.8 -> 2187.5 | L15: =[2]PRELIMINAR!$I$189 -> 8425.13 | M15: =K15<L15 -> TRUE | N15: =L15-K15 -> 6237.63
B16: Taxa Assistência % | C16: 0.005 | G16: TÉCNICO SEGURANCA | H16: 0 | K16: =H16/0.8 -> 0
B17: Taxa Assistência R$ | C17: =C16*C7 -> 231197.67 | E17: =C17=C39 -> TRUE | G17: TÉCNICO EM EDIFICAÇÕES | H17: 0 | K17: =H17/0.8 -> 0
B18: Reajuste Taxa Assistência | C18: Sim | G18: FINALIZAÇÃO OBRA | H18: 31000 | I18: 1 | K18: =H18/0.8 -> 38750 | L18: =[2]PRELIMINAR!$I$203 -> 39303.51 | M18: =K18<L18 -> TRUE | N18: =L18-K18 -> 553.51
B19: R$ Equipe | C19: 2653384.8 | E19: =C19>-C42 -> TRUE
B20: Impostos (PIS + COFINS + ISS) | C20: 0.098071252
B21: Comissão Obra | C21: =3%*C12 -> 131782.67
B22: Necessário deslocamento | C22: Não
B23: Valor Descolamento | C23: 0
B24: IRPJ + CSLL | C24: 0.1088
B26: Despesa Adm Engenharia 2026 | C26: ='[3]DRE Geral'!$W$23 -> 0.23819262
B27: Despesa Adm Engenharia 2027 | C27: =C26 -> 0.23819262
B28: Despesa Adm Engenharia 2028 a ... | C28: =C27 -> 0.23819262
B31: VIABILIDADE
E32: MESES DE OBRA | AF32: MESES PÓS OBRA
E33: 1 | F33: 2 | G33: 3 | H33: 4 | I33: 5 | J33: 6 | K33: 7 | L33: 8 | M33: 9 | N33: 10 | O33: 11 | P33: 12 | Q33: 13 | R33: 14 | S33: 15 | T33: 16 | U33: 17 | V33: 18 | W33: 19 | X33: 20 | Y33: 21 | Z33: 22 | AA33: 23 | AB33: 24 | AC33: 25 | AD33: 26 | AE33: 27 | AF33: 28 | AG33: 29 | AH33: 30
E34: =C11 -> 46153 | F34: =E34+31 -> 46184 | G34: =F34+31 -> 46215 | H34: =G34+31 -> 46246 | I34: =H34+31 -> 46277 | J34: =I34+31 -> 46308 | K34: =J34+31 -> 46339 | L34: =K34+31 -> 46370 | M34: =L34+31 -> 46401 | ... AH34: =AG34+31 -> 47052
B35: DADOS | C35: VALORES TOTAIS | D35: VALORES %
A36: RECEITA | B36: Receita Taxa de Adm | C36: =SUM(E36:AH36) -> 2248572.2 | D36: =C36/C7 -> 0.048628783 | E36: =($C$12-$C$15)*E56 -> 27846.431 | F36: =($C$12-$C$15)*F56 -> 64727.693 | G36: =($C$12-$C$15)*G56 -> 49277.731 | H36: =($C$12-$C$15)*H56 -> 47467.473 | I36: =($C$12-$C$15)*I56 -> 51314.083 | J36: =($C$12-$C$15)*J56 -> 46796.656 | K36: =($C$12-$C$15)*K56 -> 24094.891 | L36: =($C$12-$C$15)*L56 -> 44306.632 | ... AH36: =($C$12-$C$15)*AH56 -> 0
A37: RECEITA | B37: Permuta Taxa de Adm | C37: =SUM(E37:AH37) -> 2144183.4 | D37: =C15/C7 -> 0.046371217 | E37: =$C$15/$C$10 -> 79414.201 | F37: =$C$15/$C$10 -> 79414.201 | G37: =$C$15/$C$10 -> 79414.201 | H37: =$C$15/$C$10 -> 79414.201 | I37: =$C$15/$C$10 -> 79414.201 | J37: =$C$15/$C$10 -> 79414.201 | K37: =$C$15/$C$10 -> 79414.201 | L37: =$C$15/$C$10 -> 79414.201 | ... AE37: =$C$15/$C$10 -> 79414.201
A38: RECEITA | B38: Receita MO Adm Piemonte | C38: =SUM(E38:AH38) -> 2653384.8 | D38: =C19/C7 -> 0.057383467 | E38: =$C$19/$C$10 -> 98273.509 | F38: =$C$19/$C$10 -> 98273.509 | G38: =$C$19/$C$10 -> 98273.509 | H38: =$C$19/$C$10 -> 98273.509 | I38: =$C$19/$C$10 -> 98273.509 | J38: =$C$19/$C$10 -> 98273.509 | K38: =$C$19/$C$10 -> 98273.509 | L38: =$C$19/$C$10 -> 98273.509 | ... AE38: =$C$19/$C$10 -> 98273.509
A39: RECEITA | B39: Receita Assistência | C39: =SUM(E39:AH39) -> 231197.67 | D39: =C16 -> 0.005 | AH39: =C16*C7 -> 231197.67
A40: DESPESA | B40: Impostos (PIS + COFINS + ISS) | C40: =SUM(E40:AH40) -> -713697.66 | D40: =-C20 -> -0.098071252 | E40: =$D$40*(E36+E37+E38+E39) -> -20156.991 | F40: =$D$40*(F36+F37+F38+F39) -> -23773.982 | G40: =$D$40*(G36+G37+G38+G39) -> -22258.785 | H40: =$D$40*(H36+H37+H38+H39) -> -22081.251 | I40: =$D$40*(I36+I37+I38+I39) -> -22458.493 | J40: =$D$40*(J36+J37+J38+J39) -> -22015.463 | K40: =$D$40*(K36+K37+K38+K39) -> -19789.072 | L40: =$D$40*(L36+L37+L38+L39) -> -21771.263 | ... AH40: =$D$40*(AH36+AH37+AH38+AH39) -> -22673.845
A41: DESPESA | B41: Despesa Assistência | C41: =SUM(E41:AH41) -> -693593 | D41: -0.015 | AH41: =D41*C7 -> -693593
A42: CUSTO | B42: Custos Equipe | C42: =SUM(E42:AH42) -> -2132488.2 | D42: =C42/C7 -> -0.046118289 | E42: =-((SUMPRODUCT($H$6:$H$18,$I$6:$I$18)/$C$10)+($C$21/$C$10)) -> -78981.043 | F42: =-((SUMPRODUCT($H$6:$H$18,$I$6:$I$18)/$C$10)+($C$21/$C$10)) -> -78981.043 | G42: =-((SUMPRODUCT($H$6:$H$18,$I$6:$I$18)/$C$10)+($C$21/$C$10)) -> -78981.043 | H42: =-((SUMPRODUCT($H$6:$H$18,$I$6:$I$18)/$C$10)+($C$21/$C$10)) -> -78981.043 | I42: =-((SUMPRODUCT($H$6:$H$18,$I$6:$I$18)/$C$10)+($C$21/$C$10)) -> -78981.043 | J42: =-((SUMPRODUCT($H$6:$H$18,$I$6:$I$18)/$C$10)+($C$21/$C$10)) -> -78981.043 | K42: =-((SUMPRODUCT($H$6:$H$18,$I$6:$I$18)/$C$10)+($C$21/$C$10)) -> -78981.043 | L42: =-((SUMPRODUCT($H$6:$H$18,$I$6:$I$18)/$C$10)+($C$21/$C$10)) -> -78981.043 | ... AE42: =-((SUMPRODUCT($H$6:$H$18,$I$6:$I$18)/$C$10)+($C$21/$C$10)) -> -78981.043
A43: CUSTO | B43: Custos Deslocamento | C43: =SUM(E43:AH43) -> 0 | D43: =C43/C7 -> 0 | E43: =-$C$23/$C$10 -> 0 | F43: =-$C$23/$C$10 -> 0 | G43: =-$C$23/$C$10 -> 0 | H43: =-$C$23/$C$10 -> 0 | I43: =-$C$23/$C$10 -> 0 | J43: =-$C$23/$C$10 -> 0 | K43: =-$C$23/$C$10 -> 0 | L43: =-$C$23/$C$10 -> 0 | ... AH43: =-$C$23/$C$10 -> 0
B45: MARGEM BRUTA R$ | C45: =SUM(C36:C43) -> 3737559.3 | D45: - | E45: =SUM(E36:E43) -> 106396.11 | F45: =SUM(F36:F43) -> 139660.38 | G45: =SUM(G36:G43) -> 125725.61 | H45: =SUM(H36:H43) -> 124092.89 | I45: =SUM(I36:I43) -> 127562.26 | J45: =SUM(J36:J43) -> 123487.86 | K45: =SUM(K36:K43) -> 103012.49 | L45: =SUM(L36:L43) -> 121242.04 | ... AH45: =SUM(AH36:AH43) -> -485069.18
B46: MARGEM BRUTA % | C46: - | D46: =C45/(C36+C37+C38+C39+C40) -> 0.56943388 | E46: =E45/(E36+E37+E38+E39+E40) -> 0.57394402 | F46: =F45/(F36+F37+F38+F39+F40) -> 0.6387645 | G46: =G45/(G36+G37+G38+G39+G40) -> 0.61417452 | H46: =H45/(H36+H37+H38+H39+H40) -> 0.61107247 | I46: =I45/(I36+I37+I38+I39+I40) -> 0.6176054 | J46: =J45/(J36+J37+J38+J39+J40) -> 0.60991025 | K46: =K45/(K36+K37+K38+K39+K40) -> 0.56602279 | L46: =L45/(L36+L37+L38+L39+L40) -> 0.60553477 | ... AH46: =AH45/(AH36+AH37+AH38+AH39+AH40) -> -2.3262051
A48: DESPESA | B48: Despesas Adm Pie | C48: =SUM(E48:AH48) -> -1667921.9 | D48: variável / ano | E48: =-$C$26*(E36+E37+E38) -> -48956.715 | F48: =-$C$26*(F36+F37+F38) -> -57741.56 | G48: =-$C$26*(G36+G37+G38) -> -54061.493 | H48: =-$C$26*(H36+H37+H38) -> -53630.303 | I48: =-$C$26*(I36+I37+I38) -> -54546.537 | J48: =-$C$26*(J36+J37+J38) -> -53470.519 | K48: =-$C$26*(K36+K37+K38) -> -48063.126 | L48: =-$C$26*(L36+L37+L38) -> -52877.414 | M48: =-$C$27*(M36+M37+M38) -> -51070.043 | N48: =-$C$27*(N36+N37+N38) -> -51324.525 | O48: =-$C$27*(O36+O37+O38) -> -60547.19 | P48: =-$C$27*(P36+P37+P38) -> -62929.723 | Q48: =-$C$27*(Q36+Q37+Q38) -> -67763.748 | R48: =-$C$27*(R36+R37+R38) -> -68961.356 | S48: =-$C$27*(S36+S37+S38) -> -66667.281 | T48: =-$C$27*(T36+T37+T38) -> -67481.201 | ... X48: =-$C$27*(X36+X37+X38) -> -69868.961 | Y48: =-$C$28*(Y36+Y37+Y38) -> -73940.617 | Z48: =-$C$28*(Z36+Z37+Z38) -> -69987.478 | AA48: =-$C$28*(AA36+AA37+AA38) -> -69990.809 | AB48: =-$C$28*(AB36+AB37+AB38) -> -68422.865 | AC48: =-$C$28*(AC36+AC37+AC38) -> -58370.239 | AD48: =-$C$28*(AD36+AD37+AD38) -> -55038.067 | AE48: =-$C$28*(AE36+AE37+AE38) -> -54367.616
B50: RESULTADO | C50: =SUM(E50:AH50) -> 2069637.4 | D50: - | E50: =SUM(E36:E43,E48) -> 57439.393 | F50: =SUM(F36:F43,F48) -> 81918.819 | G50: =SUM(G36:G43,G48) -> 71664.12 | H50: =SUM(H36:H43,H48) -> 70462.587 | I50: =SUM(I36:I43,I48) -> 73015.721 | J50: =SUM(J36:J43,J48) -> 70017.342 | K50: =SUM(K36:K43,K48) -> 54949.36 | L50: =SUM(L36:L43,L48) -> 68364.623 | ... AH50: =SUM(AH36:AH43,AH48) -> -485069.18
B51: IRPJ + CSLL | C51: =SUM(E51:AH51) -> -791774.39 | D51: =C24 -> 0.1088 | E51: =-$C$24*(E36+E37+E38+E39) -> -22362.115 | F51: =-$C$24*(F36+F37+F38+F39) -> -26374.796 | G51: =-$C$24*(G36+G37+G38+G39) -> -24693.84 | H51: =-$C$24*(H36+H37+H38+H39) -> -24496.884 | I51: =-$C$24*(I36+I37+I38+I39) -> -24915.395 | J51: =-$C$24*(J36+J37+J38+J39) -> -24423.899 | K51: =-$C$24*(K36+K37+K38+K39) -> -21953.947 | L51: =-$C$24*(L36+L37+L38+L39) -> -24152.984 | ... AH51: =-$C$24*(AH36+AH37+AH38+AH39) -> -25154.306
B52: Resultado Final | C52: =SUM(E52:AH52) -> 1277863 | D52: - | E52: =SUM(E50:E51) -> 35077.278 | F52: =SUM(F50:F51) -> 55544.023 | G52: =SUM(G50:G51) -> 46970.28 | H52: =SUM(H50:H51) -> 45965.703 | I52: =SUM(I50:I51) -> 48100.326 | J52: =SUM(J50:J51) -> 45593.442 | K52: =SUM(K50:K51) -> 32995.413 | L52: =SUM(L50:L51) -> 44211.638 | ... AH52: =SUM(AH50:AH51) -> -510223.49
B53: Margem Líquida | C53: - | D53: =C52/(C36+C37+C38+C39+C40) -> 0.19468815 | E53: =E52/(E36+E37+E38+E39+E40) -> 0.18922115 | F53: =F52/(F36+F37+F38+F39+F40) -> 0.25404163 | G53: =G52/(G36+G37+G38+G39+G40) -> 0.22945165 | H53: =H52/(H36+H37+H38+H39+H40) -> 0.2263496 | I53: =I52/(I36+I37+I38+I39+I40) -> 0.23288253 | J53: =J52/(J36+J37+J38+J39+J40) -> 0.22518738 | K53: =K52/(K36+K37+K38+K39+K40) -> 0.18129992 | L53: =L52/(L36+L37+L38+L39+L40) -> 0.2208119 | ... AH53: =AH52/(AH36+AH37+AH38+AH39+AH40) -> -2.4468355
B54: RECEITA LÍQUIDA | C54: =SUM(E54:AH54) -> 6563640.4 | D54: - | E54: =E36+E37+E38+E39+E40 -> 185377.15 | F54: =F36+F37+F38+F39+F40 -> 218641.42 | G54: =G36+G37+G38+G39+G40 -> 204706.66 | H54: =H36+H37+H38+H39+H40 -> 203073.93 | I54: =I36+I37+I38+I39+I40 -> 206543.3 | J54: =J36+J37+J38+J39+J40 -> 202468.9 | K54: =K36+K37+K38+K39+K40 -> 181993.53 | L54: =L36+L37+L38+L39+L40 -> 200223.08 | ... AH54: =AH36+AH37+AH38+AH39+AH40 -> 208523.82
B56: CURVA FÍSICA OBRA | C56: - | D56: =SUM(E56:AH56) -> 1 | E56: 0.01238405 | F56: 0.02878613 | G56: 0.02191512 | H56: 0.02111005 | I56: 0.02282074 | J56: 0.02081172 | K56: 0.01071564 | L56: 0.01970434 | M56: 0.01632982 | N56: 0.01680496 | O56: 0.03402449 | P56: 0.03847289 | Q56: 0.04749844 | R56: 0.04973448 | S56: 0.04545124 | T56: 0.0469709 | U56: 0.05916078 | V56: 0.06179089 | W56: 0.06738296 | X56: 0.05142906 | Y56: 0.0590312 | Z56: 0.05165034 | AA56: 0.05165656 | AB56: 0.04872907 | AC56: 0.02995993 | AD56: 0.02373847 | AE56: 0.02248668 | AF56: 0.01503072 | AG56: 0.00441833
B58: RECEITAS - IMPOSTOS | C58: =SUM(E58:AH58) -> 5771866.1 | E58: =E54+E51 -> 163015.04 | F58: =F54+F51 -> 192266.63 | G58: =G54+G51 -> 180012.82 | H58: =H54+H51 -> 178577.05 | I58: =I54+I51 -> 181627.91 | J58: =J54+J51 -> 178045 | K58: =K54+K51 -> 160039.58 | L58: =L54+L51 -> 176070.1 | ... AH58: =AH54+AH51 -> 183369.52
B61: ANÁLISES
C63: %
A64: 1 | B64: Risco Estouro / Banda Estouro | C64: 0.04
A65: 2 | B65: Ganho Economia / Banda Economia | C65: 0.4
B67: CUSTO CAPITAL / MÊS (10% ANO) SEM INCC | C67: =POWER(1 + 10%, 1/12) - 1 -> 0.0079741404
B68: INCC ANO | C68: 0.062
B70: VPL | C70: =NPV(C67,E52:AH52) -> 1179439.7
B71: RECEITA | C71: =NPV(C67,E54:AH54) -> 5828250.6
B72: VPL/RECEITA | C72: =C70/C71 -> 0.20236599

Sheet Ações-Riscos-PIEMONTE
B2: Ações para tratar riscos
C6: Identificação de Riscos | E6: Significância
B7: Item | G7: BOM/RO/GR | I7: Responsável | K7: Ações / Monitoramento
B10: ='Riscos-PIEMONTE'!B10 -> 1. | C10: ='Riscos-PIEMONTE'!C10 -> Indefinições de projetos e soluções | E10: ='Riscos-PIEMONTE'!AS10 -> Administrável
B14: ='Riscos-PIEMONTE'!B12 -> 2. | C14: ='Riscos-PIEMONTE'!C12 -> Obra com controle no sistema de gestão do cliente - SIENGE | E14: ='Riscos-PIEMONTE'!AS12 -> Administrável
B19: ='Riscos-PIEMONTE'!B14 -> 3. | C19: ='Riscos-PIEMONTE'!C14 -> Desorganização estrutura AG7 (monitorar atrasos NFs, etc) | E19: ='Riscos-PIEMONTE'!AS14 -> Administrável
B23: ='Riscos-PIEMONTE'!B16 -> 4. | C23: ='Riscos-PIEMONTE'!C16 -> 0 | E23: ='Riscos-PIEMONTE'!AS16
B27: ='Riscos-PIEMONTE'!B18 -> 5. | C27: ='Riscos-PIEMONTE'!C18 -> 0 | E27: ='Riscos-PIEMONTE'!AS18
B31: ='Riscos-PIEMONTE'!B20 -> 6. | C31: ='Riscos-PIEMONTE'!C20 -> 0 | E31: ='Riscos-PIEMONTE'!AS20
B35: ='Riscos-PIEMONTE'!B22 -> 7. | C35: ='Riscos-PIEMONTE'!C22 -> 0 | E35: ='Riscos-PIEMONTE'!AS22 -> Administrável
B39: ='Riscos-PIEMONTE'!B24 -> 8. | C39: ='Riscos-PIEMONTE'!C24 -> 0 | E39: ='Riscos-PIEMONTE'!AS24
B43: ='Riscos-PIEMONTE'!B26 -> 9. | C43: ='Riscos-PIEMONTE'!C26 -> 0 | E43: ='Riscos-PIEMONTE'!AS26
B47: ='Riscos-PIEMONTE'!B28 -> 10. | C47: ='Riscos-PIEMONTE'!C28 -> 0 | E47: ='Riscos-PIEMONTE'!AS28
B52: ='Riscos-PIEMONTE'!B30 -> 11. | C52: ='Riscos-PIEMONTE'!C30 -> 0 | E52: ='Riscos-PIEMONTE'!AS30
B56: ='Riscos-PIEMONTE'!B32 -> 12. | C56: ='Riscos-PIEMONTE'!C32 -> 0 | E56: ='Riscos-PIEMONTE'!AS32
B60: ='Riscos-PIEMONTE'!B34 -> 13. | C60: ='Riscos-PIEMONTE'!C34 -> 0 | E60: ='Riscos-PIEMONTE'!AS34
B66: ='Riscos-PIEMONTE'!B36 -> 14. | C66: ='Riscos-PIEMONTE'!C36 -> 0 | E66: ='Riscos-PIEMONTE'!AS36
B70: ='Riscos-PIEMONTE'!B38 -> 15. | C70: ='Riscos-PIEMONTE'!C38 -> 0 | E70: ='Riscos-PIEMONTE'!AS38
B76: ='Riscos-PIEMONTE'!B40 -> 16. | C76: ='Riscos-PIEMONTE'!C40 -> 0 | E76: ='Riscos-PIEMONTE'!AS40
B80: ='Riscos-PIEMONTE'!B42 -> 17. | C80: ='Riscos-PIEMONTE'!C42 -> 0 | E80: ='Riscos-PIEMONTE'!AS42
B85: ='Riscos-PIEMONTE'!B46 -> 19. | C85: ='Riscos-PIEMONTE'!C46 -> 0 | E85: ='Riscos-PIEMONTE'!AS46
B89: ='Riscos-PIEMONTE'!B48 -> 20. | C89: ='Riscos-PIEMONTE'!C48 -> 0 | E89: ='Riscos-PIEMONTE'!AS48
B93: ='Riscos-PIEMONTE'!B50 -> 21. | C93: ='Riscos-PIEMONTE'!C50 -> 0 | E93: ='Riscos-PIEMONTE'!AS50
B98: 22. | C98: ='Riscos-PIEMONTE'!C52 -> 0 | E98: ='Riscos-PIEMONTE'!AS52

Sheet Probabilidade (legenda)
B4: AVALIAÇÃO DA PROBABILIDADE | D4: NOTAS
B5: Características do controle | C5: Controle-chave efetivo: existe um plano preventivo monitorando o processo minimizando o impacto caso incorra no risco. Após sua implantação não houve ocorrência do risco. | D5: 0
C6: Controle compensatório efetivo: existe um plano de contingência para recuperação, caso o processo incorra no Risco | D6: 2
C7: Controle compensatório não efetivo: o plano de contingência apresenta histórico de Falhas | D7: 4
C8: Controle Inexistente | D8: 9 | F8: PROBABILIDADE
B10: Tipo do controle | C10: Automatizado: existem sistemas mecanizados / informatizados associados | D10: 1 | F10: Remota | G10: Baixíssima possibilidade de o evento ocorrer | H10: < = 7
C11: Manual: não existem sistemas mecanizados / informatizados associados | D11: 3
C12: Nenhum | D12: 5 | F12: Improvável | G12: O evento ocorre raramente. | H12: > 7 e < 10
B14: Histórico de ocorrência do risco | C14: Anual ou mais | D14: 1 | F14: Possível | G14: O evento já ocorreu algumas vezes e pode voltar a ocorrer. | H14: > = 10 e < 13
C15: Trimestral | D15: 2
C16: Mensal | D16: 3 | F16: Provável | G16: O evento já ocorreu repetidas vezes e provavelmente voltará a ocorrer muitas vezes | H16: > = 20
C17: Semanal | D17: 4
C18: Diário | D18: 5
C19: Mais de uma vez ao dia | D19: 6

Sheet Condiç Exequibilidade (legenda)
B4: CONDIÇÕES PARA IMPLANTAÇÃO / EXECUÇÃO | E4: NOTAS
B5: Prazo para execução | C5: Muito curto | D5: 1 mês | E5: 5
C6: Curto | D6: 3 meses | E6: 4
C7: Médio | D7: 6 meses | E7: 3
C8: Longo | D8: 1 ano | E8: 2
C9: Muito longo | D9: Acima de 1 ano | E9: 1
B11: Complexidade | C11: Nenhuma | D11: Não requer mudanças na infraestrutura e nos processos | E11: 5
C12: Baixa | D12: Requer mudanças pouco significativas na infraestrutura e nos processos | E12: 4
C13: Média | D13: Requer mudanças significativas nos processos e pouco significativas na infraestrutura | E13: 3
C14: Alta | D14: Requer mudanças significativas na infraestrutura e pouco significativas nos processos | E14: 2
C15: Muito alta | D15: Requer mudanças significativas na estrutura e nos processos | E15: 1
B17: Payback (Retorno sobre o investimento) | C17: Imediato | D17: 0 a 3 meses | E17: 5
C18: Curto prazo | D18: 3 a 6 meses | E18: 4
C19: Médio prazo | D19: 6 meses a 1 ano | E19: 3
C20: Longo prazo | D20: 1 ano a 2 anos | E20: 2
C21: Muito longo | D21: Acima de 2 anos | E21: 1

Sheet Impacto (legenda)
B3: CLASSIFICAÇÃO DO IMPACTO
D4: 1 Baixo | E4: 2 Moderado | F4: 3 Significativo | G4: 4 Alto
B5: Financeiro (Anual) | C5: Risco | D5: Até R$ 100.000 | E5: De R$ 100.000 a R$ 300.000 | F5: De R$ 300.000 a R$ 500.000 | G5: Acima de R$ 500.000
C6: Oportunidade | D6: Até R$ 200.000 | E6: De R$ 200.000 a R$ 600.000 | F6: De R$ 600.000 a R$ 1.000.000 | G6: Acima de R$ 1.000.000
B7: Legal | C7: Risco | D7: Possibilidade de Autuação | E7: Pequena Possibilidade de Condenação | F7: Provável condenação | G7: Possibilidade de Responsabilização aos Representantes Legais
C8: Oportunidade | D8: Regulamentação com alta complexidade (difícil adapatação / alto custo e com pouco domínio pela empresa) | E8: Regulamentação com complexidade alta porém dominada pela empresa | F8: Regulamentação com complexidade moderada porém dominada pela empresa | G8: Regulamentação com baixa complexidade (fácil adapatação / aplicação / baixo custo, baixo risco de multas
B9: Imagem | C9: Risco | D9: Processo Simples de Reversão (Retração) | E9: Processo Complexo de Reversão | F9: Prejuízos Significativos com Stakeholders | G9: Degradação da Credibilidade com Ameaça da Perenidade
C10: Oportunidade | D10: Nenhuma agregação de valor para imagem / possibilidade de perda de credibilidade | E10: Pouca agregação de valor para imagem | F10: Agregação significativa com pouca elevação no posicionamento no mercado | G10: Alta agregação de valor a imagem da empresa / valorização da marca / elevação posicionamento no mercado
B11: Direcionamento Estratégico | C11: Risco | D11: Implica em redirecionar a gestão, mas sem impacto nas estratégias | E11: Pode afetar o Market Share, mas sem perda de Posição no Mercado | F11: Compromete a lucratividade do negócio | G11: Compromete sériamente a sustentabilidade / continuidade do negócio
C12: Oportunidade | D12: Não está alinhada ao direcionamento estratégico, mas agrega valor ao negócio | E12: Parcialmente alinhada ao direcionamento estratégico | F12: Alinhada ao direcionamento estratégico | G12: Fortemente alinhada e contemplada no direcionamento estratégico
B13: Operação | C13: Risco | D13: Afeta as condições operacionais da empresa sem comprometer a qualidade e entrega | E13: Afeta as condições operacionais da empresa podendo gerar não conformidades | F13: Afeta as condições operacionais da empresa podendo compremeter a satisfação dos clientes / saúde / segurança / meio ambiente | G13: Afeta fortemente as condições operacionais da empresa podendo gerar perda de clientes ou paralização da operação da empresa
C14: Oportunidade | D14: Pode compremeter a operação / sáude / segurança ocupacional / meio ambiente | E14: Não compremete a operação / sáude / segurança ocupacional / meio ambiente | F14: Melhora a operação sáude ocupacional / segurança / meio ambiente | G14: Contribui fortemente para com a melhoria da operação sáude / segurança ocupacional / meio ambiente

Sheet Estratégias (legenda)
A1: Estratégias para Riscos | D1: Estratégias para Oportunidades
A2: Prevenir | B2: Buscar alternativas/soluções visando evitar que o risco ocorra ou prevenir suas consequências. | D2: Explorar | E2: Buscar alternativas/soluções visando a implementação da oportunidade através da adoção de novas práticas ou utilização de novas tecnologias.
A3: Transferir | B3: Transferir o risco para terceiros, contratando seguros, terceirizando a atividade, etc. | D3: Melhorar | E3: Estudar metodologias buscando viabilizar o aperfeiçoamento dos processos e da infraestrutura para expandir a oportunidade.
A4: Mitigar | B4: Investir para que o risco ou seu impacto seja reduzido. | D4: Compartilhar | E4: Construir parcerias para viabilizar a implementação da oportunidade.
A5: Aceitar | B5: manter o risco no nível atual, assumindo que as perdas são toleráveis. | D5: Aceitar | E5: Manter a oportunidade no nível atual, assumindo que sua implementação não é viável no momento.

Sheet Oportunidades-PIEMONTE
E1: Matriz de Avaliação e Gestão de Oportunidades - 2022
E4: NOME DO PROJETO OU PROCESSO
B6: Item | C6: Oportunidade | E6: Avaliação de Impacto | W6: Condição para Implantação / Execução | AT6: Valor Agregado | AV6: Estratégia | AY6: Valor Agregado
E7: Financeiro | F7: Pontos | G7: Inf. Média | H7: Legal | I7: Pontos | J7: Inf. Média | K7: Imagem | L7: Pontos | M7: Inf. Média | N7: Direcionamento Estratégico | O7: Pontos | P7: Inf. Média | Q7: Operação | R7: Pontos | S7: Inf. Média | W7: Prazo | AB7: Pontos | AD7: Complexidade | AI7: Pontos | AK7: Payback (ROI) | AP7: Pontos
U8: Impacto | W8: Muito Curto | X8: Curto | Y8: Médio | Z8: Longo | AA8: Muito Longo | AD8: Nenhuma | AE8: Baixa | AF8: Média | AG8: Alta | AH8: Muito Alta | AK8: Imediato | AL8: Curto Prazo | AM8: Médio Prazo | AN8: Longo Prazo | AO8: Muito Longo | AQ8: Probabilidade | AR8: Média | AY8: Baixo | AZ8: Médio | BA8: Alto | BB8: Muito Alto
B10: 1. | C10: Crescimento do mercado trazendo oportunidades para o nicho de prestação de serviços no agronegócio | E10: Alto | F10: =IF(E10="N.A.",0)+IF(E10="Baixo",1)+IF(E10="Moderado",2)+IF(E10="Significativo",4)+IF(E10="Alto",6) -> 6 | G10: =IF(F10>0,1,0) -> 1 | H10: Moderado | I10: =IF(H10="N.A.",0)+IF(H10="Baixo",1)+IF(H10="Moderado",2)+IF(H10="Significativo",4)+IF(H10="Alto",6) -> 2 | J10: =IF(I10>0,1,0) -> 1 | K10: Alto | L10: =IF(K10="N.A.",0)+IF(K10="Baixo",1)+IF(K10="Moderado",2)+IF(K10="Significativo",4)+IF(K10="Alto",6) -> 6 | M10: =IF(L10>0,1,0) -> 1 | N10: Significativo | O10: =IF(N10="N.A.",0)+IF(N10="Baixo",1)+IF(N10="Moderado",2)+IF(N10="Significativo",4)+IF(N10="Alto",6) -> 4 | P10: =IF(O10>0,1,0) -> 1 | Q10: Significativo | R10: =IF(Q10="N.A.",0)+IF(Q10="Baixo",1)+IF(Q10="Moderado",2)+IF(Q10="Significativo",4)+IF(Q10="Alto",6) -> 4 | S10: =IF(R10>0,1,0) -> 1 | T10: =SUM(G10,J10,M10,P10,S10) -> 5 | U10: =IFERROR(SUM(F10,I10,L10,O10,R10)/T10,0) -> 4.4 | Z10: x | AB10: =IF(W10="X",5)+IF(X10="X",4)+IF(Y10="X",3)+IF(Z10="X",2)+IF(AA10="X",1) -> 2 | AF10: x | AI10: =IF(AD10="X",5)+IF(AE10="X",4)+IF(AF10="X",3)+IF(AG10="X",2)+IF(AH10="X",1) -> 3 | AM10: x | AP10: =IF(AK10="X",5)+IF(AL10="X",4)+IF(AM10="X",3)+IF(AN10="X",2)+IF(AO10="X",1) -> 3 | AQ10: =AB10+AI10+AP10 -> 8 | AR10: =(AQ10+U10)/2 -> 6.2 | AS10: =IF(AT10="",0,10) -> 10 | AT10: =IF(AY10=TRUE,"Baixo",IF(AZ10=TRUE,"Médio",IF(BA10=TRUE,"Alto",IF(BB10=TRUE,"Muito Alto","")))) -> Alto | AV10: Explorar | AX10: N.A. | AY10: =AND(U10>0,U10<=2,AQ10>0,AQ10<=7) -> FALSE | AZ10: =OR(AND(U10>0,U10<=2,AQ10>0,AQ10>7,AQ10<=13),AND(U10>0,U10>2,U10<=3,AQ10>0,AQ10<=10)) -> FALSE | BA10: =OR(AND(U10>0,U10<=2,AQ10>0,AQ10>12,AQ10<=17),AND(U10>0,U10>2,U10<=3,AQ10>0,AQ10>10,AQ10<=13),AND(U10>0,U10>3,U10<=5,AQ10>0,AQ10<=10),AND(U10>0,U10>5,U10<=6,AQ10>0,AQ10<=7)) -> TRUE | BB10: =OR(AND(U10>0,U10>2,U10<=3,AQ10>0,AQ10>14,AQ10<=20),AND(U10>0,U10>3,U10<=5,AQ10>0,AQ10>10),AND(U10>0,U10>5,U10<=6,AQ10>0,AQ10>7,AQ10<=20)) -> FALSE | BD10: N.A.
I11: =IF(H11="N.A.",0)+IF(H11="Baixo",1)+IF(H11="Moderado",2)+IF(H11="Significativo",4)+IF(H11="Alto",6) -> 0 | J11: =IF(I11>0,1,0) -> 0 | L11: =IF(K11="N.A.",0)+IF(K11="Baixo",1)+IF(K11="Moderado",2)+IF(K11="Significativo",4)+IF(K11="Alto",6) -> 0 | R11: =IF(Q11="N.A.",0)+IF(Q11="Baixo",1)+IF(Q11="Moderado",2)+IF(Q11="Significativo",4)+IF(Q11="Alto",6) -> 0 | S11: =IF(R11>0,1,0) -> 0 | T11: =SUM(G11,J11,M11,P11,S11) -> 0 | U11: =IFERROR(SUM(F11,I11,L11,O11,R11)/T11,0) -> 0 | AQ11: =AB11+AI11+AP11 -> 0 | AT11: =IF(AY11=TRUE,"Baixo",IF(AZ11=TRUE,"Médio",IF(BA11=TRUE,"Alto",IF(BB11=TRUE,"Muito Alto","")))) | AX11: Baixo | BA11: =OR(AND(U11>0,U11<=2,AQ11>0,AQ11>12,AQ11<=17),AND(U11>0,U11>2,U11<=3,AQ11>0,AQ11>10,AQ11<=13),AND(U11>0,U11>3,U11<=5,AQ11>0,AQ11<=10),AND(U11>0,U11>5,U11<=6,AQ11>0,AQ11<=7)) -> FALSE | BB11: =OR(AND(U11>0,U11>2,U11<=3,AQ11>0,AQ11>14,AQ11<=20),AND(U11>0,U11>3,U11<=5,AQ11>0,AQ11>10),AND(U11>0,U11>5,U11<=6,AQ11>0,AQ11>7,AQ11<=20)) -> FALSE | BD11: Baixo
B12: 2. | C12: Boa aceitação do mercado para aquisição de personalização de unidades | E12: Alto | F12: =IF(E12="N.A.",0)+IF(E12="Baixo",1)+IF(E12="Moderado",2)+IF(E12="Significativo",4)+IF(E12="Alto",6) -> 6 | G12: =IF(F12>0,1,0) -> 1 | H12: Alto | I12: =IF(H12="N.A.",0)+IF(H12="Baixo",1)+IF(H12="Moderado",2)+IF(H12="Significativo",4)+IF(H12="Alto",6) -> 6 | J12: =IF(I12>0,1,0) -> 1 | K12: Alto | L12: =IF(K12="N.A.",0)+IF(K12="Baixo",1)+IF(K12="Moderado",2)+IF(K12="Significativo",4)+IF(K12="Alto",6) -> 6 | M12: =IF(L12>0,1,0) -> 1 | N12: Significativo | O12: =IF(N12="N.A.",0)+IF(N12="Baixo",1)+IF(N12="Moderado",2)+IF(N12="Significativo",4)+IF(N12="Alto",6) -> 4 | P12: =IF(O12>0,1,0) -> 1 | Q12: Moderado | R12: =IF(Q12="N.A.",0)+IF(Q12="Baixo",1)+IF(Q12="Moderado",2)+IF(Q12="Significativo",4)+IF(Q12="Alto",6) -> 2 | S12: =IF(R12>0,1,0) -> 1 | T12: =SUM(G12,J12,M12,P12,S12) -> 5 | U12: =IFERROR(SUM(F12,I12,L12,O12,R12)/T12,0) -> 4.8 | X12: x | AB12: =IF(W12="X",5)+IF(X12="X",4)+IF(Y12="X",3)+IF(Z12="X",2)+IF(AA12="X",1) -> 4 | AG12: x | AI12: =IF(AD12="X",5)+IF(AE12="X",4)+IF(AF12="X",3)+IF(AG12="X",2)+IF(AH12="X",1) -> 2 | AK12: x | AP12: =IF(AK12="X",5)+IF(AL12="X",4)+IF(AM12="X",3)+IF(AN12="X",2)+IF(AO12="X",1) -> 5 | AQ12: =AB12+AI12+AP12 -> 11 | AR12: =(AQ12+U12)/2 -> 7.9 | AS12: =IF(AT12="",0,10) -> 10 | AT12: =IF(AY12=TRUE,"Baixo",IF(AZ12=TRUE,"Médio",IF(BA12=TRUE,"Alto",IF(BB12=TRUE,"Muito Alto","")))) -> Muito Alto | AV12: Melhorar | AX12: Moderado | AY12: =AND(U12>0,U12<=2,AQ12>0,AQ12<=7) -> FALSE | AZ12: =OR(AND(U12>0,U12<=2,AQ12>0,AQ12>7,AQ12<=13),AND(U12>0,U12>2,U12<=3,AQ12>0,AQ12<=10)) -> FALSE | BA12: =OR(AND(U12>0,U12<=2,AQ12>0,AQ12>12,AQ12<=17),AND(U12>0,U12>2,U12<=3,AQ12>0,AQ12>10,AQ12<=13),AND(U12>0,U12>3,U12<=5,AQ12>0,AQ12<=10),AND(U12>0,U12>5,U12<=6,AQ12>0,AQ12<=7)) -> FALSE | BB12: =OR(AND(U12>0,U12>2,U12<=3,AQ12>0,AQ12>14,AQ12<=20),AND(U12>0,U12>3,U12<=5,AQ12>0,AQ12>10),AND(U12>0,U12>5,U12<=6,AQ12>0,AQ12>7,AQ12<=20)) -> TRUE | BD12: Moderado
T13: =SUM(G13,J13,M13,P13,S13) -> 0 | U13: =IFERROR(SUM(F13,I13,L13,O13,R13)/T13,0) -> 0 | AQ13: =AB13+AI13+AP13 -> 0 | AT13: =IF(AY13=TRUE,"Baixo",IF(AZ13=TRUE,"Médio",IF(BA13=TRUE,"Alto",IF(BB13=TRUE,"Muito Alto","")))) | AX13: Significativo | BA13: =OR(AND(U13>0,U13<=2,AQ13>0,AQ13>12,AQ13<=17),AND(U13>0,U13>2,U13<=3,AQ13>0,AQ13>10,AQ13<=13),AND(U13>0,U13>3,U13<=5,AQ13>0,AQ13<=10),AND(U13>0,U13>5,U13<=6,AQ13>0,AQ13<=7)) -> FALSE | BB13: =OR(AND(U13>0,U13>2,U13<=3,AQ13>0,AQ13>14,AQ13<=20),AND(U13>0,U13>3,U13<=5,AQ13>0,AQ13>10),AND(U13>0,U13>5,U13<=6,AQ13>0,AQ13>7,AQ13<=20)) -> FALSE | BD13: Significativo
B14: 3. | C14: Redução do custo fixo através da centralização do DGCA | E14: Baixo | F14: =IF(E14="N.A.",0)+IF(E14="Baixo",1)+IF(E14="Moderado",2)+IF(E14="Significativo",4)+IF(E14="Alto",6) -> 1 | G14: =IF(F14>0,1,0) -> 1 | H14: Alto | I14: =IF(H14="N.A.",0)+IF(H14="Baixo",1)+IF(H14="Moderado",2)+IF(H14="Significativo",4)+IF(H14="Alto",6) -> 6 | J14: =IF(I14>0,1,0) -> 1 | K14: Moderado | L14: =IF(K14="N.A.",0)+IF(K14="Baixo",1)+IF(K14="Moderado",2)+IF(K14="Significativo",4)+IF(K14="Alto",6) -> 2 | M14: =IF(L14>0,1,0) -> 1 | N14: Significativo | O14: =IF(N14="N.A.",0)+IF(N14="Baixo",1)+IF(N14="Moderado",2)+IF(N14="Significativo",4)+IF(N14="Alto",6) -> 4 | P14: =IF(O14>0,1,0) -> 1 | Q14: Baixo | R14: =IF(Q14="N.A.",0)+IF(Q14="Baixo",1)+IF(Q14="Moderado",2)+IF(Q14="Significativo",4)+IF(Q14="Alto",6) -> 1 | S14: =IF(R14>0,1,0) -> 1 | T14: =SUM(G14,J14,M14,P14,S14) -> 5 | U14: =IFERROR(SUM(F14,I14,L14,O14,R14)/T14,0) -> 2.8 | X14: x | AB14: =IF(W14="X",5)+IF(X14="X",4)+IF(Y14="X",3)+IF(Z14="X",2)+IF(AA14="X",1) -> 4 | AF14: x | AI14: =IF(AD14="X",5)+IF(AE14="X",4)+IF(AF14="X",3)+IF(AG14="X",2)+IF(AH14="X",1) -> 3 | AL14: x | AP14: =IF(AK14="X",5)+IF(AL14="X",4)+IF(AM14="X",3)+IF(AN14="X",2)+IF(AO14="X",1) -> 4 | AQ14: =AB14+AI14+AP14 -> 11 | AR14: =(AQ14+U14)/2 -> 6.9 | AS14: =IF(AT14="",0,10) -> 10 | AT14: =IF(AY14=TRUE,"Baixo",IF(AZ14=TRUE,"Médio",IF(BA14=TRUE,"Alto",IF(BB14=TRUE,"Muito Alto","")))) -> Alto | AV14: Explorar | AX14: Alto | AY14: =AND(U14>0,U14<=2,AQ14>0,AQ14<=7) -> FALSE | AZ14: =OR(AND(U14>0,U14<=2,AQ14>0,AQ14>7,AQ14<=13),AND(U14>0,U14>2,U14<=3,AQ14>0,AQ14<=10)) -> FALSE | BA14: =OR(AND(U14>0,U14<=2,AQ14>0,AQ14>12,AQ14<=17),AND(U14>0,U14>2,U14<=3,AQ14>0,AQ14>10,AQ14<=13),AND(U14>0,U14>3,U14<=5,AQ14>0,AQ14<=10),AND(U14>0,U14>5,U14<=6,AQ14>0,AQ14<=7)) -> TRUE | BB14: =OR(AND(U14>0,U14>2,U14<=3,AQ14>0,AQ14>14,AQ14<=20),AND(U14>0,U14>3,U14<=5,AQ14>0,AQ14>10),AND(U14>0,U14>5,U14<=6,AQ14>0,AQ14>7,AQ14<=20)) -> FALSE | BD14: Alto
I15: =IF(H15="N.A.",0)+IF(H15="Baixo",1)+IF(H15="Moderado",2)+IF(H15="Significativo",4)+IF(H15="Alto",6) -> 0 | J15: =IF(I15>0,1,0) -> 0 | L15: =IF(K15="N.A.",0)+IF(K15="Baixo",1)+IF(K15="Moderado",2)+IF(K15="Significativo",4)+IF(K15="Alto",6) -> 0 | T15: =SUM(G15,J15,M15,P15,S15) -> 0 | U15: =IFERROR(SUM(F15,I15,L15,O15,R15)/T15,0) -> 0 | AQ15: =AB15+AI15+AP15 -> 0 | AT15: =IF(AY15=TRUE,"Baixo",IF(AZ15=TRUE,"Médio",IF(BA15=TRUE,"Alto",IF(BB15=TRUE,"Muito Alto","")))) | BA15: =OR(AND(U15>0,U15<=2,AQ15>0,AQ15>12,AQ15<=17),AND(U15>0,U15>2,U15<=3,AQ15>0,AQ15>10,AQ15<=13),AND(U15>0,U15>3,U15<=5,AQ15>0,AQ15<=10),AND(U15>0,U15>5,U15<=6,AQ15>0,AQ15<=7)) -> FALSE | BB15: =OR(AND(U15>0,U15>2,U15<=3,AQ15>0,AQ15>14,AQ15<=20),AND(U15>0,U15>3,U15<=5,AQ15>0,AQ15>10),AND(U15>0,U15>5,U15<=6,AQ15>0,AQ15>7,AQ15<=20)) -> FALSE
