Workbook

Sheet INCC - DI
A1: 34547 | B1: 100 | E1: 34547 | H1: 34547
A2: 34578 | B2: 100.381 | E2: 34578 | F2: =B1 -> 100 | H2: 34578
A3: 34608 | B3: 101.71 | E3: 34608 | F3: =B2 -> 100.381 | H3: 34608 | I3: =B1 -> 100
A4: 34639 | B4: 104.11 | E4: 34639 | F4: =B3 -> 101.71 | H4: 34639 | I4: =B2 -> 100.381
A5: 34669 | B5: 105.487 | E5: 34669 | F5: =B4 -> 104.11 | H5: 34669 | I5: =B3 -> 101.71
A6: 34700 | B6: 109.176 | E6: 34700 | F6: =B5 -> 105.487 | H6: 34700 | I6: =B4 -> 104.11
A7: 34731 | B7: 111.453 | E7: 34731 | F7: =B6 -> 109.176 | H7: 34731 | I7: =B5 -> 105.487
A8: 34759 | B8: 115.129 | E8: 34759 | F8: =B7 -> 111.453 | H8: 34759 | I8: =B6 -> 109.176
A9: 34790 | B9: 117.774 | E9: 34790 | F9: =B8 -> 115.129 | H9: 34790 | I9: =B7 -> 111.453
A10: 34820 | B10: 128.098 | E10: 34820 | F10: =B9 -> 117.774 | H10: 34820 | I10: =B8 -> 115.129
A11: 34851 | B11: 132.09 | E11: 34851 | F11: =B10 -> 128.098 | H11: 34851 | I11: =B9 -> 117.774
A12: 34881 | B12: 133.524 | E12: 34881 | F12: =B11 -> 132.09 | H12: 34881 | I12: =B10 -> 128.098
A13: 34912 | B13: 134.353 | E13: 34912 | F13: =B12 -> 133.524 | H13: 34912 | I13: =B11 -> 132.09
A14: 34943 | B14: 135.318 | E14: 34943 | F14: =B13 -> 134.353 | H14: 34943 | I14: =B12 -> 133.524
... A382: 46143 | B382: 1270.695 | E382: 46143 | F382: =B381 -> 1259.652 | H382: 46143 | I382: =B380 -> 1247.181
A383: 46174 | B383: =B382 -> 1270.695 | E383: 46174 | F383: =B382 -> 1270.695 | H383: 46174 | I383: =B381 -> 1259.652
A384: 46204 | B384: =B383 -> 1270.695 | E384: 46204 | F384: =B383 -> 1270.695 | H384: 46204 | I384: =B382 -> 1270.695
A385: 46235 | B385: =B384 -> 1270.695 | E385: 46235 | F385: =B384 -> 1270.695 | H385: 46235 | I385: =B383 -> 1270.695
A386: 46266 | B386: =B385 -> 1270.695 | E386: 46266 | F386: =B385 -> 1270.695 | H386: 46266 | I386: =B384 -> 1270.695
A387: 46296 | B387: =B386 -> 1270.695 | E387: 46296 | F387: =B386 -> 1270.695 | H387: 46296 | I387: =B385 -> 1270.695
A388: 46327 | B388: =B387 -> 1270.695 | E388: 46327 | F388: =B387 -> 1270.695 | H388: 46327 | I388: =B386 -> 1270.695
A389: 46357 | B389: =B388 -> 1270.695 | E389: 46357 | F389: =B388 -> 1270.695 | H389: 46357 | I389: =B387 -> 1270.695
A390: 46388 | B390: =B389 -> 1270.695 | E390: 46388 | F390: =B389 -> 1270.695 | H390: 46388 | I390: =B388 -> 1270.695
A391: 46419 | B391: =B390 -> 1270.695 | E391: 46419 | F391: =B390 -> 1270.695 | H391: 46419 | I391: =B389 -> 1270.695
A392: 46447 | B392: =B391 -> 1270.695 | E392: 46447 | F392: =B391 -> 1270.695 | H392: 46447 | I392: =B390 -> 1270.695
A393: 46478 | B393: =B392 -> 1270.695 | E393: 46478 | F393: =B392 -> 1270.695 | H393: 46478 | I393: =B391 -> 1270.695
A394: 46508 | B394: =B393 -> 1270.695 | E394: 46508 | F394: =B393 -> 1270.695 | H394: 46508 | I394: =B392 -> 1270.695
... A1611: 83551 | B1611: =B1610 -> 1270.695 | E1611: 83551 | F1611: =B1610 -> 1270.695 | H1611: 83551 | I1611: =B1609 -> 1270.695

Sheet INCC - M
A1: 34547 | B1: 100 | E1: 34547 | F1: =B1 -> 100
A2: 34578 | B2: 100.312 | E2: 34578 | F2: =B1 -> 100
A3: 34608 | B3: 101.195 | E3: 34608 | F3: =B2 -> 100.312
A4: 34639 | B4: 102.628 | E4: 34639 | F4: =B3 -> 101.195
A5: 34669 | B5: 105.136 | E5: 34669 | F5: =B4 -> 102.628
A6: 34700 | B6: 106.581 | E6: 34700 | F6: =B5 -> 105.136
A7: 34731 | B7: 110.354 | E7: 34731 | F7: =B6 -> 106.581
A8: 34759 | B8: 113.014 | E8: 34759 | F8: =B7 -> 110.354
A9: 34790 | B9: 116.114 | E9: 34790 | F9: =B8 -> 113.014
A10: 34820 | B10: 118.936 | E10: 34820 | F10: =B9 -> 116.114
A11: 34851 | B11: 130.089 | E11: 34851 | F11: =B10 -> 118.936
A12: 34881 | B12: 133.608 | E12: 34881 | F12: =B11 -> 130.089
A13: 34912 | B13: 134.856 | E13: 34912 | F13: =B12 -> 133.608
... A382: 46143 | B382: 1264.353 | E382: 46143 | F382: =B381 -> 1254.655
A383: 46174 | B383: =B382 -> 1264.353 | E383: 46174 | F383: =B382 -> 1264.353
A384: 46204 | B384: =B383 -> 1264.353 | E384: 46204 | F384: =B383 -> 1264.353
A385: 46235 | B385: =B384 -> 1264.353 | E385: 46235 | F385: =B384 -> 1264.353
A386: 46266 | B386: =B385 -> 1264.353 | E386: 46266 | F386: =B385 -> 1264.353
A387: 46296 | B387: =B386 -> 1264.353 | E387: 46296 | F387: =B386 -> 1264.353
A388: 46327 | B388: =B387 -> 1264.353 | E388: 46327 | F388: =B387 -> 1264.353
A389: 46357 | B389: =B388 -> 1264.353 | E389: 46357 | F389: =B388 -> 1264.353
A390: 46388 | B390: =B389 -> 1264.353 | E390: 46388 | F390: =B389 -> 1264.353
A391: 46419 | B391: =B390 -> 1264.353 | E391: 46419 | F391: =B390 -> 1264.353
A392: 46447 | B392: =B391 -> 1264.353 | E392: 46447 | F392: =B391 -> 1264.353
A393: 46478 | B393: =B392 -> 1264.353 | E393: 46478 | F393: =B392 -> 1264.353
A394: 46508 | B394: =B393 -> 1264.353 | E394: 46508 | F394: =B393 -> 1264.353
... A1611: 83551 | B1611: =B1610 -> 1264.353 | E1611: 83551 | F1611: =B1610 -> 1264.353

Sheet Croma R02
A1: Croma
A2: Data Base | B2: INCC Base | C2: Valor Orçado | D2: Valor da Taxa (Reaj) | G2: Valor Previsto Total | I2: Valor Cobrado
A3: 44562 | B3: =VLOOKUP(A3,'INCC - M'!$A:$F,2,FALSE) -> 967.003 | C3: 7716524.6 | D3: =SUM(D5:D48) -> 9048524.4 | G3: =SUM(G5:G48) -> 9047537.7 | I3: =SUM(I5:I48) -> 9048524.4 | J3: =D3-I3 -> 0
A4: Mês | B4: INCC M | C4: Medição | D4: Valor Reajustado | F4: Medição Prevista | G4: Valor Previsto | I4: Valor Cobrado
A5: 44805 | B5: =VLOOKUP(A5,'INCC - M'!$E:$F,2,FALSE) -> 1045.469 | C5: 0.0088722564 | D5: =(C5*$C$3)*B5/$B$3 -> 74018.311 | F5: 0.0088722564 | G5: =F5*($C$3/$B$3*B5) -> 74018.311 | I5: 65261.141
A6: 44835 | B6: =VLOOKUP(A6,'INCC - M'!$E:$F,2,FALSE) -> 1046.507 | C6: 0.010507913 | D6: =(C6*$C$3)*B6/$B$3 -> 87751.091 | F6: 0.010507913 | G6: =F6*($C$3/$B$3*B6) -> 87751.091 | I6: 76993.481
A7: 44866 | B7: =VLOOKUP(A7,'INCC - M'!$E:$F,2,FALSE) -> 1046.956 | C7: 0.012182026 | D7: =(C7*$C$3)*B7/$B$3 -> 101775.18 | F7: 0.012182026 | G7: =F7*($C$3/$B$3*B7) -> 101775.18 | I7: 89459.092
A8: 44896 | B8: =VLOOKUP(A8,'INCC - M'!$E:$F,2,FALSE) -> 1048.429 | C8: 0.0073798258 | D8: =(C8*$C$3)*B8/$B$3 -> 61741.768 | F8: 0.0073798258 | G8: =F8*($C$3/$B$3*B8) -> 61741.768 | I8: 147746.59
A9: 44927 | B9: =VLOOKUP(A9,'INCC - M'!$E:$F,2,FALSE) -> 1051.249 | C9: 0.0085197165 | D9: =(C9*$C$3)*B9/$B$3 -> 71470.145 | F9: 0.0085197165 | G9: =F9*($C$3/$B$3*B9) -> 71470.145 | I9: 129512.84
A10: 44958 | B10: =VLOOKUP(A10,'INCC - M'!$E:$F,2,FALSE) -> 1054.561 | C10: 0.0080329958 | D10: =(C10*$C$3)*B10/$B$3 -> 67599.451 | F10: 0.0080329958 | G10: =F10*($C$3/$B$3*B10) -> 67599.451 | I10: 148727.02
A11: 44986 | B11: =VLOOKUP(A11,'INCC - M'!$E:$F,2,FALSE) -> 1056.775 | C11: 0.012312466 | D11: =(C11*$C$3)*B11/$B$3 -> 103829.67 | F11: 0.012312466 | G11: =F11*($C$3/$B$3*B11) -> 103829.67 | I11: 161939.65
A12: 45017 | B12: =VLOOKUP(A12,'INCC - M'!$E:$F,2,FALSE) -> 1058.65 | C12: 0.015471498 | D12: =(C12*$C$3)*B12/$B$3 -> 130700.93 | F12: 0.015471498 | G12: =F12*($C$3/$B$3*B12) -> 130700.93 | I12: 227086.8
A13: 45047 | B13: =VLOOKUP(A13,'INCC - M'!$E:$F,2,FALSE) -> 1061.071 | C13: 0.010770974 | D13: =(C13*$C$3)*B13/$B$3 -> 91199.688 | F13: 0.010770974 | G13: =F13*($C$3/$B$3*B13) -> 91199.688 | I13: 260326.74
A14: 45078 | B14: =VLOOKUP(A14,'INCC - M'!$E:$F,2,FALSE) -> 1065.289 | C14: 0.0099065106 | D14: =(C14*$C$3)*B14/$B$3 -> 84213.57 | F14: 0.0099065106 | G14: =F14*($C$3/$B$3*B14) -> 84213.57 | I14: 300590.25
A15: 45108 | B15: =VLOOKUP(A15,'INCC - M'!$E:$F,2,FALSE) -> 1074.292 | C15: 0.0084854621 | D15: =(C15*$C$3)*B15/$B$3 -> 72743.094 | F15: 0.0084854621 | G15: =F15*($C$3/$B$3*B15) -> 72743.094 | I15: 318921.73
A16: 45139 | B16: =VLOOKUP(A16,'INCC - M'!$E:$F,2,FALSE) -> 1074.895 | C16: 0.021512494 | D16: =(C16*$C$3)*B16/$B$3 -> 184523.09 | F16: 0.021512494 | G16: =F16*($C$3/$B$3*B16) -> 184523.09 | I16: 351008.9
... A48: 46113 | B48: =VLOOKUP(A48,'INCC - M'!$E:$F,2,FALSE) -> 1241.721 | C48: 0.00956152 | D48: =(C48*$C$3)*B48/$B$3 -> 94742.511 | F48: 0 | G48: =F48*($C$3/$B$3*B48) -> 0 | I48: 94742.511

Sheet Unna R02
A1: Unna | F1: saldo | G1: =G3-D3 -> 1200662.3 | H1: =G3-I3 -> 1200662.3
A2: Data Base | B2: INCC Base | C2: Valor Orçado c/ Aditivos | D2: Valor da Taxa (Reaj) | G2: Valor Previsto Total | I2: Valor Cobrado
A3: 44805 | B3: =VLOOKUP(A3,'INCC - M'!$E:$F,2,FALSE) -> 1045.469 | C3: 9017791.7 | D3: =SUM(D5:D42) -> 8671856.3 | G3: =SUM(G5:G42) -> 9872518.6 | I3: =SUM(I5:I42) -> 8671856.3 | J3: =D3-I3 -> 0
A4: Mês | B4: INCC M (n-1) | C4: Medição | D4: Valor Reajustado | F4: Medição Prevista | G4: Valor Previsto | I4: Valor Cobrado
A5: 45047 | B5: =VLOOKUP(A5,'INCC - M'!$E:$F,2,FALSE) -> 1061.071 | C5: 0.0089087769 | D5: =(C5*$C$3)*B5/$B$3 -> 81536.406 | F5: 0.0089087769 | G5: =F5*($C$3/$B$3*B5) -> 81536.406 | I5: 120763.23
A6: 45078 | B6: =VLOOKUP(A6,'INCC - M'!$E:$F,2,FALSE) -> 1065.289 | C6: 0.0093150901 | D6: =(C6*$C$3)*B6/$B$3 -> 85594.043 | F6: 0.0093150901 | G6: =F6*($C$3/$B$3*B6) -> 85594.043 | I6: 96629.992
A7: 45108 | B7: =VLOOKUP(A7,'INCC - M'!$E:$F,2,FALSE) -> 1074.292 | C7: 0.0091427032 | D7: =(C7*$C$3)*B7/$B$3 -> 84720.011 | F7: 0.0091427032 | G7: =F7*($C$3/$B$3*B7) -> 84720.011 | I7: 80899.093
A8: 45139 | B8: =VLOOKUP(A8,'INCC - M'!$E:$F,2,FALSE) -> 1074.895 | C8: 0.012304597 | D8: =(C8*$C$3)*B8/$B$3 -> 114083.4 | F8: 0.012304597 | G8: =F8*($C$3/$B$3*B8) -> 114083.4 | I8: 80944.501
A9: 45170 | B9: =VLOOKUP(A9,'INCC - M'!$E:$F,2,FALSE) -> 1077.497 | C9: 0.012658837 | D9: =(C9*$C$3)*B9/$B$3 -> 117651.89 | F9: 0.012658837 | G9: =F9*($C$3/$B$3*B9) -> 117651.89 | I9: 81140.444
A10: 45200 | B10: =VLOOKUP(A10,'INCC - M'!$E:$F,2,FALSE) -> 1080.071 | C10: 0.014858479 | D10: =(C10*$C$3)*B10/$B$3 -> 138425.38 | F10: 0.014858479 | G10: =F10*($C$3/$B$3*B10) -> 138425.38 | I10: 81334.278
A11: 45231 | B11: =VLOOKUP(A11,'INCC - M'!$E:$F,2,FALSE) -> 1082.251 | C11: 0.011469743 | D11: =(C11*$C$3)*B11/$B$3 -> 107070.72 | F11: 0.011469743 | G11: =F11*($C$3/$B$3*B11) -> 107070.72 | I11: 79646.204
A12: 45261 | B12: =VLOOKUP(A12,'INCC - M'!$E:$F,2,FALSE) -> 1083.335 | C12: 0.011616776 | D12: =(C12*$C$3)*B12/$B$3 -> 108551.9 | F12: 0.011616776 | G12: =F12*($C$3/$B$3*B12) -> 108551.9 | I12: 186336.3
A13: 45292 | B13: =VLOOKUP(A13,'INCC - M'!$E:$F,2,FALSE) -> 1086.15 | C13: 0.026287543 | D13: =(C13*$C$3)*B13/$B$3 -> 246279.82 | F13: 0.026287543 | G13: =F13*($C$3/$B$3*B13) -> 246279.82 | I13: 240728.89
A14: 45323 | B14: =VLOOKUP(A14,'INCC - M'!$E:$F,2,FALSE) -> 1088.663 | C14: 0.024278094 | D14: =(C14*$C$3)*B14/$B$3 -> 227980.18 | F14: 0.024278094 | G14: =F14*($C$3/$B$3*B14) -> 227980.18 | I14: 220790.53
A15: 45352 | B15: =VLOOKUP(A15,'INCC - M'!$E:$F,2,FALSE) -> 1090.871 | C15: 0.022869584 | D15: =(C15*$C$3)*B15/$B$3 -> 215189.31 | F15: 0.022869584 | G15: =F15*($C$3/$B$3*B15) -> 215189.31 | I15: 196033.97
A16: 45383 | B16: =VLOOKUP(A16,'INCC - M'!$E:$F,2,FALSE) -> 1093.503 | C16: 0.035019256 | D16: =(C16*$C$3)*B16/$B$3 -> 330305.59 | F16: 0.035019256 | G16: =F16*($C$3/$B$3*B16) -> 330305.59 | I16: 208671.66
... A35: 45962 | B35: =VLOOKUP(A35,'INCC - M'!$E:$F,2,FALSE) -> 1219.407 | C35: 0.024597903 | D35: =(C35*$C$3)*B35/$B$3 -> 258723.46 | F35: 0.02013286 | G35: =F35*($C$3/$B$3*B35) -> 211759.64 | I35: 258723.46
A36: 45992 | B36: =VLOOKUP(A36,'INCC - M'!$E:$F,2,FALSE) -> 1222.865 | D36: =(C36*$C$3)*B36/$B$3 -> 0 | F36: 0.0086789408 | G36: =F36*($C$3/$B$3*B36) -> 91544.926 | H36: =(F36*$G$1/(SUM($F$36:$F$48))) -> 340040.97
A37: 46023 | B37: =VLOOKUP(A37,'INCC - M'!$E:$F,2,FALSE) -> 1225.398 | D37: =(C37*$C$3)*B37/$B$3 -> 0 | F37: 0.0052835025 | G37: =F37*($C$3/$B$3*B37) -> 55845.492 | H37: =(F37*$G$1/(SUM($F$36:$F$48))) -> 207007.67
A38: 46054 | B38: =VLOOKUP(A38,'INCC - M'!$E:$F,2,FALSE) -> 1233.096 | D38: =(C38*$C$3)*B38/$B$3 -> 0 | F38: 0.002565261 | G38: =F38*($C$3/$B$3*B38) -> 27284.594 | H38: =(F38*$G$1/(SUM($F$36:$F$48))) -> 100506.95
A39: 46082 | B39: =VLOOKUP(A39,'INCC - M'!$E:$F,2,FALSE) -> 1237.312 | D39: =(C39*$C$3)*B39/$B$3 -> 0 | F39: 0.0028217872 | G39: =F39*($C$3/$B$3*B39) -> 30115.669 | H39: =(F39*$G$1/(SUM($F$36:$F$48))) -> 110557.64
A40: 46113 | B40: =VLOOKUP(A40,'INCC - M'!$E:$F,2,FALSE) -> 1241.721 | D40: =(C40*$C$3)*B40/$B$3 -> 0 | F40: 0.0028217872 | G40: =F40*($C$3/$B$3*B40) -> 30222.982 | H40: =(F40*$G$1/(SUM($F$36:$F$48))) -> 110557.64
A41: 46143 | B41: =VLOOKUP(A41,'INCC - M'!$E:$F,2,FALSE) -> 1254.655 | D41: =(C41*$C$3)*B41/$B$3 -> 0 | F41: 0.0026935241 | G41: =F41*($C$3/$B$3*B41) -> 29149.709 | H41: =(F41*$G$1/(SUM($F$36:$F$48))) -> 105532.3
A42: =EDATE(A41,1) -> 46174 | B42: =VLOOKUP(A42,'INCC - M'!$E:$F,2,FALSE) -> 1264.353 | D42: =(C42*$C$3)*B42/$B$3 -> 0 | F42: 0.0027762277 | G42: =F42*($C$3/$B$3*B42) -> 30276.974 | H42: =(F42*$G$1/(SUM($F$36:$F$48))) -> 108772.62
A43: =EDATE(A42,1) -> 46204 | B43: =VLOOKUP(A43,'INCC - M'!$E:$F,2,FALSE) -> 1264.353 | D43: =(C43*$C$3)*B43/$B$3 -> 0 | F43: 0.0024261163 | G43: =F43*($C$3/$B$3*B43) -> 26458.73 | H43: =(F43*$G$1/(SUM($F$36:$F$48))) -> 95055.255
A44: =EDATE(A43,1) -> 46235 | B44: =VLOOKUP(A44,'INCC - M'!$E:$F,2,FALSE) -> 1264.353 | D44: =(C44*$C$3)*B44/$B$3 -> 0 | F44: 0.00011552444 | G44: =F44*($C$3/$B$3*B44) -> 1259.886 | H44: =(F44*$G$1/(SUM($F$36:$F$48))) -> 4526.2484
A45: =EDATE(A44,1) -> 46266 | B45: =VLOOKUP(A45,'INCC - M'!$E:$F,2,FALSE) -> 1264.353 | D45: =(C45*$C$3)*B45/$B$3 -> 0 | F45: 0.0001210256 | G45: =F45*($C$3/$B$3*B45) -> 1319.8805 | H45: =(F45*$G$1/(SUM($F$36:$F$48))) -> 4741.784
A46: =EDATE(A45,1) -> 46296 | B46: =VLOOKUP(A46,'INCC - M'!$E:$F,2,FALSE) -> 1264.353 | D46: =(C46*$C$3)*B46/$B$3 -> 0 | F46: 0.0001210256 | G46: =F46*($C$3/$B$3*B46) -> 1319.8805 | H46: =(F46*$G$1/(SUM($F$36:$F$48))) -> 4741.784
A47: =EDATE(A46,1) -> 46327 | B47: =VLOOKUP(A47,'INCC - M'!$E:$F,2,FALSE) -> 1264.353 | D47: =(C47*$C$3)*B47/$B$3 -> 0 | F47: 0.00011552444 | G47: =F47*($C$3/$B$3*B47) -> 1259.886 | H47: =(F47*$G$1/(SUM($F$36:$F$48))) -> 4526.2484
A48: =EDATE(A47,1) -> 46357 | B48: =VLOOKUP(A48,'INCC - M'!$E:$F,2,FALSE) -> 1264.353 | D48: =(C48*$C$3)*B48/$B$3 -> 0 | F48: 0.00010452211 | G48: =F48*($C$3/$B$3*B48) -> 1139.8968 | H48: =(F48*$G$1/(SUM($F$36:$F$48))) -> 4095.1771

Sheet Unna R02 - Reorç
A1: Unna | F1: saldo | G1: =G3-D3 -> 300692.98 | H1: =G3-I3 -> 300692.98
A2: Data Base | B2: INCC Base | C2: Valor Orçado c/ Aditivos | D2: Valor da Taxa (Reaj) | G2: Valor Previsto Total | I2: Valor Cobrado
A3: 44805 | B3: =VLOOKUP(A3,'INCC - M'!$E:$F,2,FALSE) -> 1045.469 | C3: =9300085.301432+K22 -> 9311845.1 | D3: =SUM(D5:D48) -> 9976432.8 | G3: =SUM(G5:G48) -> 10277126 | I3: =SUM(I5:I48) -> 9976432.8 | J3: =D3-I3 -> 0 | K3: Aditivos Incorporação | L3: Data | M3: Descrição
A4: Mês | B4: INCC M (n-1) | C4: Medição | D4: Valor Reajustado | F4: Medição Prevista | G4: Valor Previsto | I4: Valor Cobrado | K4: 3231.9 | L4: 46107 | M4: O aditivo de MO para aplicação de cimento queimado foi necessário devido a modificação de especificação de produto.
A5: 45047 | B5: =VLOOKUP(A5,'INCC - M'!$E:$F,2,FALSE) -> 1061.071 | C5: 0.0089087769 | D5: =(C5*$C$3)*B5/$B$3 -> 84195.157 | F5: 0.0089087769 | G5: =F5*($C$3/$B$3*B5) -> 84195.157 | I5: 120763.23 | K5: 2859.07 | L5: 46104 | M5: O aditivo é referente aos ajustes e solicitações de itens de bancada de interiores não apresentados em projeto.
A6: 45078 | B6: =VLOOKUP(A6,'INCC - M'!$E:$F,2,FALSE) -> 1065.289 | C6: 0.0093150901 | D6: =(C6*$C$3)*B6/$B$3 -> 88385.106 | F6: 0.0093150901 | G6: =F6*($C$3/$B$3*B6) -> 88385.106 | I6: 96629.992 | K6: 5668.85 | L6: 46156 | M6: Aditivo e-mail 14/05
A7: 45108 | B7: =VLOOKUP(A7,'INCC - M'!$E:$F,2,FALSE) -> 1074.292 | C7: 0.0091427032 | D7: =(C7*$C$3)*B7/$B$3 -> 87482.573 | F7: 0.0091427032 | G7: =F7*($C$3/$B$3*B7) -> 87482.573 | I7: 80899.093
A8: 45139 | B8: =VLOOKUP(A8,'INCC - M'!$E:$F,2,FALSE) -> 1074.895 | C8: 0.012304597 | D8: =(C8*$C$3)*B8/$B$3 -> 117803.45 | F8: 0.012304597 | G8: =F8*($C$3/$B$3*B8) -> 117803.45 | I8: 80944.501
A9: 45170 | B9: =VLOOKUP(A9,'INCC - M'!$E:$F,2,FALSE) -> 1077.497 | C9: 0.012658837 | D9: =(C9*$C$3)*B9/$B$3 -> 121488.3 | F9: 0.012658837 | G9: =F9*($C$3/$B$3*B9) -> 121488.3 | I9: 81140.444
A10: 45200 | B10: =VLOOKUP(A10,'INCC - M'!$E:$F,2,FALSE) -> 1080.071 | C10: 0.014858479 | D10: =(C10*$C$3)*B10/$B$3 -> 142939.17 | F10: 0.014858479 | G10: =F10*($C$3/$B$3*B10) -> 142939.17 | I10: 81334.278
A11: 45231 | B11: =VLOOKUP(A11,'INCC - M'!$E:$F,2,FALSE) -> 1082.251 | C11: 0.011469743 | D11: =(C11*$C$3)*B11/$B$3 -> 110562.1 | F11: 0.011469743 | G11: =F11*($C$3/$B$3*B11) -> 110562.1 | I11: 79646.204
A12: 45261 | B12: =VLOOKUP(A12,'INCC - M'!$E:$F,2,FALSE) -> 1083.335 | C12: 0.011616776 | D12: =(C12*$C$3)*B12/$B$3 -> 112091.58 | F12: 0.011616776 | G12: =F12*($C$3/$B$3*B12) -> 112091.58 | I12: 186336.3
A13: 45292 | B13: =VLOOKUP(A13,'INCC - M'!$E:$F,2,FALSE) -> 1086.15 | C13: 0.026287543 | D13: =(C13*$C$3)*B13/$B$3 -> 254310.55 | F13: 0.026287543 | G13: =F13*($C$3/$B$3*B13) -> 254310.55 | I13: 240728.89
A14: 45323 | B14: =VLOOKUP(A14,'INCC - M'!$E:$F,2,FALSE) -> 1088.663 | C14: 0.024278094 | D14: =(C14*$C$3)*B14/$B$3 -> 235414.19 | F14: 0.024278094 | G14: =F14*($C$3/$B$3*B14) -> 235414.19 | I14: 220790.53
A15: 45352 | B15: =VLOOKUP(A15,'INCC - M'!$E:$F,2,FALSE) -> 1090.871 | C15: 0.022869584 | D15: =(C15*$C$3)*B15/$B$3 -> 222206.24 | F15: 0.022869584 | G15: =F15*($C$3/$B$3*B15) -> 222206.24 | I15: 196033.97
A16: 45383 | B16: =VLOOKUP(A16,'INCC - M'!$E:$F,2,FALSE) -> 1093.503 | C16: 0.035019256 | D16: =(C16*$C$3)*B16/$B$3 -> 341076.24 | F16: 0.035019256 | G16: =F16*($C$3/$B$3*B16) -> 341076.24 | I16: 208671.66
A17: 45413 | B17: =VLOOKUP(A17,'INCC - M'!$E:$F,2,FALSE) -> 1097.991 | C17: 0.044570825 | D17: =(C17*$C$3)*B17/$B$3 -> 435887.12 | F17: 0.044570825 | G17: =F17*($C$3/$B$3*B17) -> 435887.12 | I17: 202950.99
A18: 45444 | B18: =VLOOKUP(A18,'INCC - M'!$E:$F,2,FALSE) -> 1104.457 | C18: 0.028628016 | D18: =(C18*$C$3)*B18/$B$3 -> 281620.75 | F18: 0.028628016 | G18: =F18*($C$3/$B$3*B18) -> 281620.75 | I18: 221278.37
... A21: 45536 | B21: =VLOOKUP(A21,'INCC - M'!$E:$F,2,FALSE) -> 1129.639 | C21: 0.042585481 | D21: =(C21*$C$3)*B21/$B$3 -> 428475.33 | F21: 0.042585481 | G21: =F21*($C$3/$B$3*B21) -> 428475.33 | I21: 411661.14
A22: 45566 | B22: =VLOOKUP(A22,'INCC - M'!$E:$F,2,FALSE) -> 1136.521 | C22: 0.056026421 | D22: =(C22*$C$3)*B22/$B$3 -> 567146.07 | F22: 0.056026421 | G22: =F22*($C$3/$B$3*B22) -> 567146.07 | I22: 987706.94 | K22: =SUM(K4:K21) -> 11759.82
A23: 45597 | B23: =VLOOKUP(A23,'INCC - M'!$E:$F,2,FALSE) -> 1144.136 | C23: 0.038731061 | D23: =(C23*$C$3)*B23/$B$3 -> 394695 | F23: 0.038731061 | G23: =F23*($C$3/$B$3*B23) -> 394695 | I23: 382231.54
A24: 45627 | B24: =VLOOKUP(A24,'INCC - M'!$E:$F,2,FALSE) -> 1149.158 | C24: 0.027227772 | D24: =(C24*$C$3)*B24/$B$3 -> 278686.82 | F24: 0.027227772 | G24: =F24*($C$3/$B$3*B24) -> 278686.82 | I24: 295576.59
A25: 45658 | B25: =VLOOKUP(A25,'INCC - M'!$E:$F,2,FALSE) -> 1154.99 | C25: 0.021514779 | D25: =(C25*$C$3)*B25/$B$3 -> 221329.7 | F25: 0.021514779 | G25: =F25*($C$3/$B$3*B25) -> 221329.7 | I25: 214057.93
A26: 45689 | B26: =VLOOKUP(A26,'INCC - M'!$E:$F,2,FALSE) -> 1163.221 | C26: 0.035731168 | D26: =(C26*$C$3)*B26/$B$3 -> 370197.97 | F26: 0.035731168 | G26: =F26*($C$3/$B$3*B26) -> 370197.97 | I26: 358507.7
A27: 45717 | B27: =VLOOKUP(A27,'INCC - M'!$E:$F,2,FALSE) -> 1169.156 | C27: 0.036477711 | D27: =(C27*$C$3)*B27/$B$3 -> 379860.92 | F27: 0.036477711 | G27: =F27*($C$3/$B$3*B27) -> 379860.92 | I27: 367865.51
A28: 45748 | B28: =VLOOKUP(A28,'INCC - M'!$E:$F,2,FALSE) -> 1173.586 | C28: 0.032651479 | D28: =(C28*$C$3)*B28/$B$3 -> 341304.77 | F28: 0.032651479 | G28: =F28*($C$3/$B$3*B28) -> 341304.77 | I28: 330526.9
A29: 45778 | B29: =VLOOKUP(A29,'INCC - M'!$E:$F,2,FALSE) -> 1180.564 | C29: 0.03453947 | D29: =(C29*$C$3)*B29/$B$3 -> 363186.57 | F29: 0.03453947 | G29: =F29*($C$3/$B$3*B29) -> 363186.57 | I29: 351717.71
A30: 45809 | B30: =VLOOKUP(A30,'INCC - M'!$E:$F,2,FALSE) -> 1183.606 | C30: 0.030976831 | D30: =(C30*$C$3)*B30/$B$3 -> 326564.31 | F30: 0.030976831 | G30: =F30*($C$3/$B$3*B30) -> 326564.31 | I30: 316251.93
A31: 45839 | B31: =VLOOKUP(A31,'INCC - M'!$E:$F,2,FALSE) -> 1194.912 | C31: 0.023330078 | D31: =(C31*$C$3)*B31/$B$3 -> 248299.98 | F31: 0.023330078 | G31: =F31*($C$3/$B$3*B31) -> 248299.98 | I31: 240459.06
A32: 45870 | B32: =VLOOKUP(A32,'INCC - M'!$E:$F,2,FALSE) -> 1205.838 | C32: 0.030207081 | D32: =(C32*$C$3)*B32/$B$3 -> 324430.97 | F32: 0.030207081 | G32: =F32*($C$3/$B$3*B32) -> 324430.97 | I32: 314082.43
A33: 45901 | B33: =VLOOKUP(A33,'INCC - M'!$E:$F,2,FALSE) -> 1214.239 | C33: 0.041989093 | D33: =(C33*$C$3)*B33/$B$3 -> 454114.38 | F33: 0.041989093 | G33: =F33*($C$3/$B$3*B33) -> 454114.38 | I33: 330313.63
A34: 45931 | B34: =VLOOKUP(A34,'INCC - M'!$E:$F,2,FALSE) -> 1216.825 | C34: 0.04658823 | D34: =(C34*$C$3)*B34/$B$3 -> 504927.38 | F34: 0.04658823 | G34: =F34*($C$3/$B$3*B34) -> 504927.38 | I34: 598546.62
... A41: 46143 | B41: =VLOOKUP(A41,'INCC - M'!$E:$F,2,FALSE) -> 1254.655 | C41: 0.00467518 | D41: =(C41*$C$3)*B41/$B$3 -> 52245.302 | F41: 0.0088 | G41: =F41*($C$3/$B$3*B41) -> 98340.311 | I41: 58244.656
A42: =EDATE(A41,1) -> 46174 | B42: =VLOOKUP(A42,'INCC - M'!$E:$F,2,FALSE) -> 1264.353 | C42: 0.00616659 | D42: =(C42*$C$3)*B42/$B$3 -> 69444.523 | F42: 0.007728 | G42: =F42*($C$3/$B$3*B42) -> 87028.208 | I42: 69444.523
A43: =EDATE(A42,1) -> 46204 | B43: =VLOOKUP(A43,'INCC - M'!$E:$F,2,FALSE) -> 1264.353 | D43: =(C43*$C$3)*B43/$B$3 -> 0 | F43: 0.006258 | G43: =F43*($C$3/$B$3*B43) -> 70473.929 | H43: =(F43*$G$1/(SUM($F$43:$F$48))) -> 92412.321
A44: =EDATE(A43,1) -> 46235 | B44: =VLOOKUP(A44,'INCC - M'!$E:$F,2,FALSE) -> 1264.353 | D44: =(C44*$C$3)*B44/$B$3 -> 0 | F44: 0.005208 | G44: =F44*($C$3/$B$3*B44) -> 58649.445 | H44: =(F44*$G$1/(SUM($F$43:$F$48))) -> 76906.898
A45: =EDATE(A44,1) -> 46266 | B45: =VLOOKUP(A45,'INCC - M'!$E:$F,2,FALSE) -> 1264.353 | D45: =(C45*$C$3)*B45/$B$3 -> 0 | F45: 0.004137 | G45: =F45*($C$3/$B$3*B45) -> 46588.47 | H45: =(F45*$G$1/(SUM($F$43:$F$48))) -> 61091.366
A46: =EDATE(A45,1) -> 46296 | B46: =VLOOKUP(A46,'INCC - M'!$E:$F,2,FALSE) -> 1264.353 | D46: =(C46*$C$3)*B46/$B$3 -> 0 | F46: 0.002247 | G46: =F46*($C$3/$B$3*B46) -> 25304.397 | H46: =(F46*$G$1/(SUM($F$43:$F$48))) -> 33181.605
A47: =EDATE(A46,1) -> 46327 | B47: =VLOOKUP(A47,'INCC - M'!$E:$F,2,FALSE) -> 1264.353 | D47: =(C47*$C$3)*B47/$B$3 -> 0 | F47: 0.002 | G47: =F47*($C$3/$B$3*B47) -> 22522.828 | H47: =(F47*$G$1/(SUM($F$43:$F$48))) -> 29534.139
A48: =EDATE(A47,1) -> 46357 | B48: =VLOOKUP(A48,'INCC - M'!$E:$F,2,FALSE) -> 1264.353 | D48: =(C48*$C$3)*B48/$B$3 -> 0 | F48: 0.0005124 | G48: =F48*($C$3/$B$3*B48) -> 5770.3486 | H48: =(F48*$G$1/(SUM($F$43:$F$48))) -> 7566.6464
C49: =SUM(C5:C48) -> 0.97321068
C50: 0.97321068
C51: =C50-C49 -> 0

Sheet Qoya R01
A1: Qoya | F1: saldo | G1: =G3-D3 -> 3639935.1 | H1: =G3-I3 -> 3639935.1
A2: Data Base | B2: INCC Base | C2: Valor Orçado | D2: Valor da Taxa (Reaj) | G2: Valor Previsto Total | I2: Valor Cobrado
A3: 45170 | B3: =VLOOKUP(A3,'INCC - DI'!$E:$F,2,FALSE) -> 1078.412 | C3: 5245908.3 | D3: =SUM(D5:D45) -> 2395147.1 | G3: =SUM(G5:G45) -> 6035082.2 | I3: =SUM(I5:I45) -> 2395147.1 | J3: =D3-I3 -> 0
A4: Mês | B4: INCC DI (n-1) | C4: Medição | D4: Valor da Taxa (Reaj) | F4: Medição Prevista | G4: Valor Previsto | I4: Valor Cobrado
A5: 45413 | B5: =VLOOKUP(A5,'INCC - DI'!$E:$F,2,FALSE) -> 1101.389 | C5: 0.011376964 | D5: =(C5*$C$3)*B5/$B$3 -> 60954.127 | F5: 0.0112 | G5: =F5*($C$3/$B$3*B5) -> 60006.009 | I5: 40749.62
A6: 45444 | B6: =VLOOKUP(A6,'INCC - DI'!$E:$F,2,FALSE) -> 1110.887 | C6: 0.020986748 | D6: =(C6*$C$3)*B6/$B$3 -> 113409.91 | F6: 0.011 | G6: =F6*($C$3/$B$3*B6) -> 59442.704 | I6: 60954.13
A7: 45474 | B7: =VLOOKUP(A7,'INCC - DI'!$E:$F,2,FALSE) -> 1118.827 | C7: 0.020545121 | D7: =(C7*$C$3)*B7/$B$3 -> 111816.95 | F7: 0.0326 | G7: =F7*($C$3/$B$3*B7) -> 177425.7 | I7: 111023.41
A8: 45505 | B8: =VLOOKUP(A8,'INCC - DI'!$E:$F,2,FALSE) -> 1126.916 | C8: 0.017857073 | D8: =(C8*$C$3)*B8/$B$3 -> 97889.884 | F8: 0.0231 | G8: =F8*($C$3/$B$3*B8) -> 126630.85 | I8: 97187.23
A9: 45536 | B9: =VLOOKUP(A9,'INCC - DI'!$E:$F,2,FALSE) -> 1134.775 | C9: 0.0091972732 | D9: =(C9*$C$3)*B9/$B$3 -> 50769.727 | F9: 0.0116 | G9: =F9*($C$3/$B$3*B9) -> 64032.983 | I9: 50771.049
A10: 45566 | B10: =VLOOKUP(A10,'INCC - DI'!$E:$F,2,FALSE) -> 1141.398 | C10: 0.010291113 | D10: =(C10*$C$3)*B10/$B$3 -> 57139.371 | F10: 0.0082 | G10: =F10*($C$3/$B$3*B10) -> 45528.878 | I10: 93646.551
A11: 45597 | B11: =VLOOKUP(A11,'INCC - DI'!$E:$F,2,FALSE) -> 1149.17 | C11: 0.0087224533 | D11: =(C11*$C$3)*B11/$B$3 -> 48759.464 | F11: 0.0085 | G11: =F11*($C$3/$B$3*B11) -> 47515.925 | I11: 98510.99
A12: 45627 | B12: =VLOOKUP(A12,'INCC - DI'!$E:$F,2,FALSE) -> 1153.725 | C12: 0.0071784377 | D12: =(C12*$C$3)*B12/$B$3 -> 40287.306 | F12: 0.0049 | G12: =F12*($C$3/$B$3*B12) -> 27500.106 | I12: 50161.357
A13: 45658 | B13: =VLOOKUP(A13,'INCC - DI'!$E:$F,2,FALSE) -> 1159.536 | C13: 0.018751261 | D13: =(C13*$C$3)*B13/$B$3 -> 105767.13 | F13: 0.0121 | G13: =F13*($C$3/$B$3*B13) -> 68250.461 | I13: 85841.407
A14: 45689 | B14: =VLOOKUP(A14,'INCC - DI'!$E:$F,2,FALSE) -> 1169.116 | C14: 0.012703958 | D14: =(C14*$C$3)*B14/$B$3 -> 72249.131 | F14: 0.0213 | G14: =F14*($C$3/$B$3*B14) -> 121135.99 | I14: 72249.131
A15: 45717 | B15: =VLOOKUP(A15,'INCC - DI'!$E:$F,2,FALSE) -> 1173.775 | C15: 0.012229501 | D15: =(C15*$C$3)*B15/$B$3 -> 69827.993 | F15: 0.013 | G15: =F15*($C$3/$B$3*B15) -> 74227.39 | I15: 67776.115
A16: 45748 | B16: =VLOOKUP(A16,'INCC - DI'!$E:$F,2,FALSE) -> 1178.386 | C16: 0.012810321 | D16: =(C16*$C$3)*B16/$B$3 -> 73431.699 | F16: 0.0111 | G16: =F16*($C$3/$B$3*B16) -> 63627.746 | I16: 73144.363
... A30: 46174 | B30: =VLOOKUP(A30,'INCC - DI'!$E:$F,2,FALSE) -> 1270.695 | C30: 0.03908218 | D30: =(C30*$C$3)*B30/$B$3 -> 241577.28 | F30: 0.0412 | G30: =F30*($C$3/$B$3*B30) -> 254668.08 | I30: 243242.47
A31: 46204 | B31: =VLOOKUP(A31,'INCC - DI'!$E:$F,2,FALSE) -> 1270.695 | D31: =(C31*$C$3)*B31/$B$3 -> 0 | F31: 0.0427 | G31: =F31*($C$3/$B$3*B31) -> 263939.98 | H31: =(F31*$G$1/(SUM($F$31:$F$45))) -> 262542.61
A32: 46235 | B32: =VLOOKUP(A32,'INCC - DI'!$E:$F,2,FALSE) -> 1270.695 | D32: =(C32*$C$3)*B32/$B$3 -> 0 | F32: 0.0407 | G32: =F32*($C$3/$B$3*B32) -> 251577.45 | H32: =(F32*$G$1/(SUM($F$31:$F$45))) -> 250245.54
A33: 46266 | B33: =VLOOKUP(A33,'INCC - DI'!$E:$F,2,FALSE) -> 1270.695 | D33: =(C33*$C$3)*B33/$B$3 -> 0 | F33: 0.042 | G33: =F33*($C$3/$B$3*B33) -> 259613.1 | H33: =(F33*$G$1/(SUM($F$31:$F$45))) -> 258238.64
A34: 46296 | B34: =VLOOKUP(A34,'INCC - DI'!$E:$F,2,FALSE) -> 1270.695 | D34: =(C34*$C$3)*B34/$B$3 -> 0 | F34: 0.0454 | G34: =F34*($C$3/$B$3*B34) -> 280629.39 | H34: =(F34*$G$1/(SUM($F$31:$F$45))) -> 279143.67
A35: 46327 | B35: =VLOOKUP(A35,'INCC - DI'!$E:$F,2,FALSE) -> 1270.695 | D35: =(C35*$C$3)*B35/$B$3 -> 0 | F35: 0.0451 | G35: =F35*($C$3/$B$3*B35) -> 278775.02 | H35: =(F35*$G$1/(SUM($F$31:$F$45))) -> 277299.11
A36: 46357 | B36: =VLOOKUP(A36,'INCC - DI'!$E:$F,2,FALSE) -> 1270.695 | D36: =(C36*$C$3)*B36/$B$3 -> 0 | F36: 0.0333 | G36: =F36*($C$3/$B$3*B36) -> 205836.1 | H36: =(F36*$G$1/(SUM($F$31:$F$45))) -> 204746.35
A37: 46388 | B37: =VLOOKUP(A37,'INCC - DI'!$E:$F,2,FALSE) -> 1270.695 | D37: =(C37*$C$3)*B37/$B$3 -> 0 | F37: 0.0505 | G37: =F37*($C$3/$B$3*B37) -> 312153.84 | H37: =(F37*$G$1/(SUM($F$31:$F$45))) -> 310501.22
A38: 46419 | B38: =VLOOKUP(A38,'INCC - DI'!$E:$F,2,FALSE) -> 1270.695 | D38: =(C38*$C$3)*B38/$B$3 -> 0 | F38: 0.0577 | G38: =F38*($C$3/$B$3*B38) -> 356658.94 | H38: =(F38*$G$1/(SUM($F$31:$F$45))) -> 354770.7
A39: 46447 | B39: =VLOOKUP(A39,'INCC - DI'!$E:$F,2,FALSE) -> 1270.695 | D39: =(C39*$C$3)*B39/$B$3 -> 0 | F39: 0.0611 | G39: =F39*($C$3/$B$3*B39) -> 377675.24 | H39: =(F39*$G$1/(SUM($F$31:$F$45))) -> 375675.73
A40: 46478 | B40: =VLOOKUP(A40,'INCC - DI'!$E:$F,2,FALSE) -> 1270.695 | D40: =(C40*$C$3)*B40/$B$3 -> 0 | F40: 0.0576 | G40: =F40*($C$3/$B$3*B40) -> 356040.82 | H40: =(F40*$G$1/(SUM($F$31:$F$45))) -> 354155.85
A41: 46508 | B41: =VLOOKUP(A41,'INCC - DI'!$E:$F,2,FALSE) -> 1270.695 | D41: =(C41*$C$3)*B41/$B$3 -> 0 | F41: 0.0389 | G41: =F41*($C$3/$B$3*B41) -> 240451.18 | H41: =(F41*$G$1/(SUM($F$31:$F$45))) -> 239178.17
A42: 46539 | B42: =VLOOKUP(A42,'INCC - DI'!$E:$F,2,FALSE) -> 1270.695 | D42: =(C42*$C$3)*B42/$B$3 -> 0 | F42: 0.0355 | G42: =F42*($C$3/$B$3*B42) -> 219434.88 | H42: =(F42*$G$1/(SUM($F$31:$F$45))) -> 218273.13
... A45: 46631 | B45: =VLOOKUP(A45,'INCC - DI'!$E:$F,2,FALSE) -> 1270.695 | D45: =(C45*$C$3)*B45/$B$3 -> 0 | F45: 0.0006 | G45: =F45*($C$3/$B$3*B45) -> 3708.7585 | H45: =(F45*$G$1/(SUM($F$31:$F$45))) -> 3689.1234
C46: =SUM(C5:C45) -> 0.41102786
C47: 0.41102786
C48: =C47-C46 -> 0

Sheet Nizza
A1: Nizza | F1: saldo | G1: =G3-D3 -> 915103.41 | H1: =G3-I3 -> 915103.41
A2: Data Base | B2: INCC Base | C2: Valor Orçado | D2: Valor da Taxa (Reaj) | G2: Valor Previsto Total | I2: Valor Cobrado
A3: 45323 | B3: =VLOOKUP(A3,'INCC - DI'!$E:$F,2,FALSE) -> 1091.25 | C3: =2391293.1+K22 -> 2389464.3 | D3: =SUM(D5:D34) -> 1777550.8 | G3: =SUM(G5:G34) -> 2692654.2 | I3: =SUM(I5:I34) -> 1777550.8 | J3: =D3-I3 -> 0 | K3: Aditivos Incorporação | L3: Data | M3: Descrição
A4: Mês | B4: INCC DI (n-1) | C4: Medição | D4: Valor da Taxa (Reaj) | F4: Medição Prevista | G4: Valor Previsto | I4: Valor Cobrado | K4: -2855.41 | L4: 46139 | M4: Mudança banheira duplex
A5: 45536 | B5: =VLOOKUP(A5,'INCC - DI'!$E:$F,2,FALSE) -> 1134.775 | C5: 0.022264524 | D5: =(C5*$C$3)*B5/$B$3 -> 55322.202 | F5: 0.022264524 | G5: =F5*($C$3/$B$3*B5) -> 55322.202 | I5: 55364.544 | K5: 1026.58 | L5: 46174 | M5: Quebra duto chaminé
A6: =EDATE(A5,1) -> 45566 | B6: =VLOOKUP(A6,'INCC - DI'!$E:$F,2,FALSE) -> 1141.398 | C6: 0.023718825 | D6: =(C6*$C$3)*B6/$B$3 -> 59279.778 | F6: 0.023718825 | G6: =F6*($C$3/$B$3*B6) -> 59279.778 | I6: 59325.149
A7: =EDATE(A6,1) -> 45597 | B7: =VLOOKUP(A7,'INCC - DI'!$E:$F,2,FALSE) -> 1149.17 | C7: 0.01849369 | D7: =(C7*$C$3)*B7/$B$3 -> 46535.472 | F7: 0.01849369 | G7: =F7*($C$3/$B$3*B7) -> 46535.472 | I7: 47127.893
A8: =EDATE(A7,1) -> 45627 | B8: =VLOOKUP(A8,'INCC - DI'!$E:$F,2,FALSE) -> 1153.725 | C8: 0.0076900948 | D8: =(C8*$C$3)*B8/$B$3 -> 19427.203 | F8: 0.0076900948 | G8: =F8*($C$3/$B$3*B8) -> 19427.203 | I8: 26536.03
A9: =EDATE(A8,1) -> 45658 | B9: =VLOOKUP(A9,'INCC - DI'!$E:$F,2,FALSE) -> 1159.536 | C9: 0.019149474 | D9: =(C9*$C$3)*B9/$B$3 -> 48620.269 | F9: 0.019149474 | G9: =F9*($C$3/$B$3*B9) -> 48620.269 | I9: 41006.72
A10: =EDATE(A9,1) -> 45689 | B10: =VLOOKUP(A10,'INCC - DI'!$E:$F,2,FALSE) -> 1169.116 | C10: 0.011845312 | D10: =(C10*$C$3)*B10/$B$3 -> 30323.575 | F10: 0.011845312 | G10: =F10*($C$3/$B$3*B10) -> 30323.575 | I10: 30345.78
A11: =EDATE(A10,1) -> 45717 | B11: =VLOOKUP(A11,'INCC - DI'!$E:$F,2,FALSE) -> 1173.775 | C11: 0.01745414 | D11: =(C11*$C$3)*B11/$B$3 -> 44860.035 | F11: 0.01745414 | G11: =F11*($C$3/$B$3*B11) -> 44860.035 | I11: 44895.373
A12: =EDATE(A11,1) -> 45748 | B12: =VLOOKUP(A12,'INCC - DI'!$E:$F,2,FALSE) -> 1178.386 | C12: 0.030645598 | D12: =(C12*$C$3)*B12/$B$3 -> 79073.682 | F12: 0.030645598 | G12: =F12*($C$3/$B$3*B12) -> 79073.682 | I12: 78824.553
A13: =EDATE(A12,1) -> 45778 | B13: =VLOOKUP(A13,'INCC - DI'!$E:$F,2,FALSE) -> 1184.462 | C13: 0.042340208 | D13: =(C13*$C$3)*B13/$B$3 -> 109812.15 | F13: 0.042340208 | G13: =F13*($C$3/$B$3*B13) -> 109812.15 | I13: 110205.85
A14: =EDATE(A13,1) -> 45809 | B14: =VLOOKUP(A14,'INCC - DI'!$E:$F,2,FALSE) -> 1191.327 | C14: 0.027457723 | D14: =(C14*$C$3)*B14/$B$3 -> 71626.181 | F14: 0.027457723 | G14: =F14*($C$3/$B$3*B14) -> 71626.181 | I14: 71681.001
A15: =EDATE(A14,1) -> 45839 | B15: =VLOOKUP(A15,'INCC - DI'!$E:$F,2,FALSE) -> 1199.509 | C15: 0.042386792 | D15: =(C15*$C$3)*B15/$B$3 -> 111329.52 | F15: 0.042386792 | G15: =F15*($C$3/$B$3*B15) -> 111329.52 | I15: 111414.73
A16: =EDATE(A15,1) -> 45870 | B16: =VLOOKUP(A16,'INCC - DI'!$E:$F,2,FALSE) -> 1210.471 | C16: 0.042077977 | D16: =(C16*$C$3)*B16/$B$3 -> 111528.41 | F16: 0.042077977 | G16: =F16*($C$3/$B$3*B16) -> 111528.41 | I16: 111613.77
A17: =EDATE(A16,1) -> 45901 | B17: =VLOOKUP(A17,'INCC - DI'!$E:$F,2,FALSE) -> 1216.706 | C17: 0.040976342 | D17: =(C17*$C$3)*B17/$B$3 -> 109167.94 | F17: 0.040976342 | G17: =F17*($C$3/$B$3*B17) -> 109167.94 | I17: 109251.5
... A21: =EDATE(A20,1) -> 46023 | B21: =VLOOKUP(A21,'INCC - DI'!$E:$F,2,FALSE) -> 1228.161 | C21: 0.037622097 | D21: =(C21*$C$3)*B21/$B$3 -> 101175.32 | F21: 0.037622101 | G21: =F21*($C$3/$B$3*B21) -> 101175.33 | I21: 101252.76
A22: =EDATE(A21,1) -> 46054 | B22: =VLOOKUP(A22,'INCC - DI'!$E:$F,2,FALSE) -> 1237.036 | C22: 0.02499087 | D22: =(C22*$C$3)*B22/$B$3 -> 67692.413 | F22: 0.024797362 | G22: =F22*($C$3/$B$3*B22) -> 67168.261 | I22: 67744.223 | K22: =SUM(K4:K21) -> -1828.83
A23: =EDATE(A22,1) -> 46082 | B23: =VLOOKUP(A23,'INCC - DI'!$E:$F,2,FALSE) -> 1240.481 | C23: 0.03404703 | D23: =(C23*$C$3)*B23/$B$3 -> 92479.534 | F23: 0.041409091 | G23: =F23*($C$3/$B$3*B23) -> 112476.58 | I23: 92550.316
A24: =EDATE(A23,1) -> 46113 | B24: =VLOOKUP(A24,'INCC - DI'!$E:$F,2,FALSE) -> 1247.181 | C24: 0.05008716 | D24: =(C24*$C$3)*B24/$B$3 -> 136783.02 | F24: 0.056998845 | G24: =F24*($C$3/$B$3*B24) -> 155658.14 | I24: 136887.71
A25: =EDATE(A24,1) -> 46143 | B25: =VLOOKUP(A25,'INCC - DI'!$E:$F,2,FALSE) -> 1259.652 | C25: 0.022935 | D25: =(C25*$C$3)*B25/$B$3 -> 63259.479 | F25: 0.06491391 | G25: =F25*($C$3/$B$3*B25) -> 179046 | I25: 60757.706
A26: =EDATE(A25,1) -> 46174 | B26: =VLOOKUP(A26,'INCC - DI'!$E:$F,2,FALSE) -> 1270.695 | C26: 0.06015269 | D26: =(C26*$C$3)*B26/$B$3 -> 167368.09 | F26: 0.08785178 | G26: =F26*($C$3/$B$3*B26) -> 244437.69 | I26: 168685.89
A27: =EDATE(A26,1) -> 46204 | B27: =VLOOKUP(A27,'INCC - DI'!$E:$F,2,FALSE) -> 1270.695 | D27: =(C27*$C$3)*B27/$B$3 -> 0 | F27: 0.084873137 | G27: =F27*($C$3/$B$3*B27) -> 236149.95 | H27: =(F27*$G$1/(SUM($F$27:$F$46))) -> 315976.27
A28: =EDATE(A27,1) -> 46235 | B28: =VLOOKUP(A28,'INCC - DI'!$E:$F,2,FALSE) -> 1270.695 | D28: =(C28*$C$3)*B28/$B$3 -> 0 | F28: 0.067938376 | G28: =F28*($C$3/$B$3*B28) -> 189030.89 | H28: =(F28*$G$1/(SUM($F$27:$F$46))) -> 252929.44
A29: =EDATE(A28,1) -> 46266 | B29: =VLOOKUP(A29,'INCC - DI'!$E:$F,2,FALSE) -> 1270.695 | D29: =(C29*$C$3)*B29/$B$3 -> 0 | F29: 0.052792493 | G29: =F29*($C$3/$B$3*B29) -> 146889.17 | H29: =(F29*$G$1/(SUM($F$27:$F$46))) -> 196542.46
A30: =EDATE(A29,1) -> 46296 | B30: =VLOOKUP(A30,'INCC - DI'!$E:$F,2,FALSE) -> 1270.695 | D30: =(C30*$C$3)*B30/$B$3 -> 0 | F30: 0.027591773 | G30: =F30*($C$3/$B$3*B30) -> 76771.003 | H30: =(F30*$G$1/(SUM($F$27:$F$46))) -> 102722.08
A31: =EDATE(A30,1) -> 46327 | B31: =VLOOKUP(A31,'INCC - DI'!$E:$F,2,FALSE) -> 1270.695 | D31: =(C31*$C$3)*B31/$B$3 -> 0 | F31: 0.010680477 | G31: =F31*($C$3/$B$3*B31) -> 29717.224 | H31: =(F31*$G$1/(SUM($F$27:$F$46))) -> 39762.607
A32: =EDATE(A31,1) -> 46357 | B32: =VLOOKUP(A32,'INCC - DI'!$E:$F,2,FALSE) -> 1270.695 | D32: =(C32*$C$3)*B32/$B$3 -> 0 | F32: 0.00059921697 | G32: =F32*($C$3/$B$3*B32) -> 1667.2538 | H32: =(F32*$G$1/(SUM($F$27:$F$46))) -> 2230.8395
A33: =EDATE(A32,1) -> 46388 | B33: =VLOOKUP(A33,'INCC - DI'!$E:$F,2,FALSE) -> 1270.695 | D33: =(C33*$C$3)*B33/$B$3 -> 0 | F33: 0.00089882546 | G33: =F33*($C$3/$B$3*B33) -> 2500.8807 | H33: =(F33*$G$1/(SUM($F$27:$F$46))) -> 3346.2592
A34: =EDATE(A33,1) -> 46419 | B34: =VLOOKUP(A34,'INCC - DI'!$E:$F,2,FALSE) -> 1270.695 | D34: =(C34*$C$3)*B34/$B$3 -> 0 | F34: 0.00042801212 | G34: =F34*($C$3/$B$3*B34) -> 1190.8956 | H34: =(F34*$G$1/(SUM($F$27:$F$46))) -> 1593.4568
C35: =SUM(C5:C34) -> 0.6704879
C36: 0.6704879
C37: =C36-C35 -> 0

Sheet Lior
A1: Lior | F1: saldo | G1: =G3-D3 -> 251027.91 | H1: =G3-I3 -> 251027.91
A2: Data Base | B2: INCC Base | C2: Valor Orçado | D2: Valor da Taxa (Reaj) | G2: Valor Previsto Total | I2: Valor Cobrado
A3: 45231 | B3: =VLOOKUP(A3,'INCC - DI'!$E:$F,2,FALSE) -> 1084.242 | C3: =1789232.84+K22 -> 1789587.7 | D3: =SUM(D5:D34) -> 1740917.9 | G3: =SUM(G5:G34) -> 1991945.8 | I3: =SUM(I5:I34) -> 1740917.9 | J3: =D3-I3 -> 0 | K3: Aditivos Incorporação | L3: Data | M3: Descrição
A4: Mês | B4: INCC DI (n-1) | C4: Medição | D4: Valor da Taxa (Reaj) | F4: Medição Prevista | G4: Valor Previsto | I4: Valor Cobrado | K4: =2895.64*8% -> 231.6512 | L4: 46050 | M4: Execução em forro (material + mão de obra)
A5: 45444 | B5: =VLOOKUP(A5,'INCC - DI'!$E:$F,2,FALSE) -> 1110.887 | C5: 0.039456415 | D5: =(C5*$C$3)*B5/$B$3 -> 72345.956 | F5: 0.039456415 | G5: =F5*($C$3/$B$3*B5) -> 72345.956 | I5: 44403.901 | K5: =1539.63*8% -> 123.1704 | L5: 46050 | M5: Execução em textura rolada (material + mão de obra)
A6: 45474 | B6: =VLOOKUP(A6,'INCC - DI'!$E:$F,2,FALSE) -> 1118.827 | C6: 0.018879538 | D6: =(C6*$C$3)*B6/$B$3 -> 34864.308 | F6: 0.018879538 | G6: =F6*($C$3/$B$3*B6) -> 34864.308 | I6: 38627.574
A7: 45505 | B7: =VLOOKUP(A7,'INCC - DI'!$E:$F,2,FALSE) -> 1126.916 | C7: 0.020100982 | D7: =(C7*$C$3)*B7/$B$3 -> 37388.288 | F7: 0.020100982 | G7: =F7*($C$3/$B$3*B7) -> 37388.288 | I7: 36383.376
A8: 45536 | B8: =VLOOKUP(A8,'INCC - DI'!$E:$F,2,FALSE) -> 1134.775 | C8: 0.028013435 | D8: =(C8*$C$3)*B8/$B$3 -> 52469.011 | F8: 0.028013435 | G8: =F8*($C$3/$B$3*B8) -> 52469.011 | I8: 51058.763
A9: 45566 | B9: =VLOOKUP(A9,'INCC - DI'!$E:$F,2,FALSE) -> 1141.398 | C9: 0.022520492 | D9: =(C9*$C$3)*B9/$B$3 -> 42426.942 | F9: 0.022520492 | G9: =F9*($C$3/$B$3*B9) -> 42426.942 | I9: 67284.162
A10: 45597 | B10: =VLOOKUP(A10,'INCC - DI'!$E:$F,2,FALSE) -> 1149.17 | C10: 0.028623755 | D10: =(C10*$C$3)*B10/$B$3 -> 54292.224 | F10: 0.028623755 | G10: =F10*($C$3/$B$3*B10) -> 54292.224 | I10: 71309.804
A11: 45627 | B11: =VLOOKUP(A11,'INCC - DI'!$E:$F,2,FALSE) -> 1153.725 | C11: 0.031255531 | D11: =(C11*$C$3)*B11/$B$3 -> 59519.042 | F11: 0.031255531 | G11: =F11*($C$3/$B$3*B11) -> 59519.042 | I11: 34522.29
A12: 45658 | B12: =VLOOKUP(A12,'INCC - DI'!$E:$F,2,FALSE) -> 1159.536 | C12: 0.016029647 | D12: =(C12*$C$3)*B12/$B$3 -> 30678.559 | F12: 0.016029647 | G12: =F12*($C$3/$B$3*B12) -> 30678.559 | I12: 30073.834
A13: 45689 | B13: =VLOOKUP(A13,'INCC - DI'!$E:$F,2,FALSE) -> 1169.116 | C13: 0.026916266 | D13: =(C13*$C$3)*B13/$B$3 -> 51939.668 | F13: 0.026916266 | G13: =F13*($C$3/$B$3*B13) -> 51939.668 | I13: 53881.226
A14: 45717 | B14: =VLOOKUP(A14,'INCC - DI'!$E:$F,2,FALSE) -> 1173.775 | C14: 0.032724423 | D14: =(C14*$C$3)*B14/$B$3 -> 63399.174 | F14: 0.032724423 | G14: =F14*($C$3/$B$3*B14) -> 63399.174 | I14: 62717.953
A15: 45748 | B15: =VLOOKUP(A15,'INCC - DI'!$E:$F,2,FALSE) -> 1178.386 | C15: 0.034862822 | D15: =(C15*$C$3)*B15/$B$3 -> 67807.364 | F15: 0.034862822 | G15: =F15*($C$3/$B$3*B15) -> 67807.364 | I15: 66316.475
A16: 45778 | B16: =VLOOKUP(A16,'INCC - DI'!$E:$F,2,FALSE) -> 1184.462 | C16: 0.050790044 | D16: =(C16*$C$3)*B16/$B$3 -> 99294.793 | F16: 0.050790044 | G16: =F16*($C$3/$B$3*B16) -> 99294.793 | I16: 97753.589
A17: 45809 | B17: =VLOOKUP(A17,'INCC - DI'!$E:$F,2,FALSE) -> 1191.327 | C17: 0.043122788 | D17: =(C17*$C$3)*B17/$B$3 -> 84793.892 | F17: 0.043122788 | G17: =F17*($C$3/$B$3*B17) -> 84793.892 | I17: 85255.29
... A21: 45931 | B21: =VLOOKUP(A21,'INCC - DI'!$E:$F,2,FALSE) -> 1218.747 | C21: 0.053776678 | D21: =(C21*$C$3)*B21/$B$3 -> 108176.84 | F21: 0.053776679 | G21: =F21*($C$3/$B$3*B21) -> 108176.84 | I21: 106213.95
A22: 45962 | B22: =VLOOKUP(A22,'INCC - DI'!$E:$F,2,FALSE) -> 1222.356 | C22: 0.04465394 | D22: =(C22*$C$3)*B22/$B$3 -> 90091.588 | F22: 0.044653942 | G22: =F22*($C$3/$B$3*B22) -> 90091.592 | I22: 88456.864 | K22: =SUM(K4:K21) -> 354.8216
A23: 45992 | B23: =VLOOKUP(A23,'INCC - DI'!$E:$F,2,FALSE) -> 1225.633 | C23: 0.02926921 | D23: =(C23*$C$3)*B23/$B$3 -> 59210.428 | F23: 0.029269212 | G23: =F23*($C$3/$B$3*B23) -> 59210.432 | I23: 58136.046
A24: 46023 | B24: =VLOOKUP(A24,'INCC - DI'!$E:$F,2,FALSE) -> 1228.161 | C24: 0.0306 | D24: =(C24*$C$3)*B24/$B$3 -> 62030.243 | F24: 0.027149354 | G24: =F24*($C$3/$B$3*B24) -> 55035.327 | I24: 84936
A25: 46054 | B25: =VLOOKUP(A25,'INCC - DI'!$E:$F,2,FALSE) -> 1237.036 | C25: 0.02405107 | D25: =(C25*$C$3)*B25/$B$3 -> 49107.01 | F25: 0.027501714 | G25: =F25*($C$3/$B$3*B25) -> 56152.469 | I25: 49365.726
A26: 46082 | B26: =VLOOKUP(A26,'INCC - DI'!$E:$F,2,FALSE) -> 1240.481 | C26: 0.03721484 | D26: =(C26*$C$3)*B26/$B$3 -> 76196.149 | F26: 0.03258823 | G26: =F26*($C$3/$B$3*B26) -> 66723.319 | I26: 76474.34
A27: 46113 | B27: =VLOOKUP(A27,'INCC - DI'!$E:$F,2,FALSE) -> 1247.181 | C27: 0.029946162 | D27: =(C27*$C$3)*B27/$B$3 -> 61644.935 | F27: 0.022074526 | G27: =F27*($C$3/$B$3*B27) -> 45440.972 | I27: 61644.935
A28: 46143 | B28: =VLOOKUP(A28,'INCC - DI'!$E:$F,2,FALSE) -> 1259.652 | C28: 0.037260638 | D28: =(C28*$C$3)*B28/$B$3 -> 77468.942 | F28: 0.053621649 | G28: =F28*($C$3/$B$3*B28) -> 111485.27 | I28: 76701.972
A29: 46174 | B29: =VLOOKUP(A29,'INCC - DI'!$E:$F,2,FALSE) -> 1270.695 | C29: 0.05841594 | D29: =(C29*$C$3)*B29/$B$3 -> 122517.87 | F29: 0.062794275 | G29: =F29*($C$3/$B$3*B29) -> 131700.71 | I29: 123284.84
A30: 46204 | B30: =VLOOKUP(A30,'INCC - DI'!$E:$F,2,FALSE) -> 1270.695 | D30: =(C30*$C$3)*B30/$B$3 -> 0 | F30: 0.0517883 | G30: =F30*($C$3/$B$3*B30) -> 108617.48 | H30: =(F30*$G$1/(SUM($F$30:$F$46))) -> 116793.48
A31: 46235 | B31: =VLOOKUP(A31,'INCC - DI'!$E:$F,2,FALSE) -> 1270.695 | D31: =(C31*$C$3)*B31/$B$3 -> 0 | F31: 0.039085453 | G31: =F31*($C$3/$B$3*B31) -> 81975.339 | H31: =(F31*$G$1/(SUM($F$30:$F$46))) -> 88145.895
A32: 46266 | B32: =VLOOKUP(A32,'INCC - DI'!$E:$F,2,FALSE) -> 1270.695 | D32: =(C32*$C$3)*B32/$B$3 -> 0 | F32: 0.01633659 | G32: =F32*($C$3/$B$3*B32) -> 34263.323 | H32: =(F32*$G$1/(SUM($F$30:$F$46))) -> 36842.437
A33: 46296 | B33: =VLOOKUP(A33,'INCC - DI'!$E:$F,2,FALSE) -> 1270.695 | D33: =(C33*$C$3)*B33/$B$3 -> 0 | F33: 0.0020499421 | G33: =F33*($C$3/$B$3*B33) -> 4299.4179 | H33: =(F33*$G$1/(SUM($F$30:$F$46))) -> 4623.0494
A34: 46327 | B34: =VLOOKUP(A34,'INCC - DI'!$E:$F,2,FALSE) -> 1270.695 | D34: =(C34*$C$3)*B34/$B$3 -> 0 | F34: 0.0020499421 | G34: =F34*($C$3/$B$3*B34) -> 4299.4179 | H34: =(F34*$G$1/(SUM($F$30:$F$46))) -> 4623.0494
C35: =SUM(C5:C34) -> 0.88044899
C36: 0.88044899
C37: =C36-C35 -> 0

Sheet Amíz
A1: Amíz | F1: saldo | G1: =G3-D3 -> 2900498 | H1: =G3-I3 -> 2900498
A2: Data Base | B2: INCC Base | C2: Valor Orçado | D2: Valor da Taxa (Reaj) | G2: Valor Previsto Total | I2: Valor Cobrado
A3: 45444 | B3: =VLOOKUP(A3,'INCC - DI'!$E:$F,2,FALSE) -> 1110.887 | C3: =4387275.530048+K22 -> 4384297 | D3: =SUM(D5:D48) -> 2022858.9 | G3: =SUM(G5:G48) -> 4923356.9 | I3: =SUM(I5:I48) -> 2022858.9 | J3: =D3-I3 -> 0 | K3: Aditivos Incorporação | L3: Data | M3: Descrição
A4: Mês | B4: INCC DI (n-1) | C4: Medição | D4: Valor da Taxa (Reaj) | F4: Medição Prevista | G4: Valor Previsto | I4: Valor Cobrado | K4: -2978.52 | L4: 46124 | M4: DISTRATO REFERENTE AOS 32 MISTURADORES DA COZINHA
A5: 45597 | B5: =VLOOKUP(A5,'INCC - DI'!$E:$F,2,FALSE) -> 1149.17 | C5: 0.011380828 | D5: =(C5*$C$3)*B5/$B$3 -> 51616.459 | F5: 0.011380828 | G5: =F5*($C$3/$B$3*B5) -> 51616.459 | I5: 38437.81
A6: =EDATE(A5,1) -> 45627 | B6: =VLOOKUP(A6,'INCC - DI'!$E:$F,2,FALSE) -> 1153.725 | C6: 0.015123664 | D6: =(C6*$C$3)*B6/$B$3 -> 68863.55 | F6: 0.015123664 | G6: =F6*($C$3/$B$3*B6) -> 68863.55 | I6: 81848.039
A7: =EDATE(A6,1) -> 45658 | B7: =VLOOKUP(A7,'INCC - DI'!$E:$F,2,FALSE) -> 1159.536 | C7: 0.014536546 | D7: =(C7*$C$3)*B7/$B$3 -> 66523.569 | F7: 0.014536546 | G7: =F7*($C$3/$B$3*B7) -> 66523.569 | I7: 66335.944
A8: =EDATE(A7,1) -> 45689 | B8: =VLOOKUP(A8,'INCC - DI'!$E:$F,2,FALSE) -> 1169.116 | C8: 0.011429841 | D8: =(C8*$C$3)*B8/$B$3 -> 52738.512 | F8: 0.011429841 | G8: =F8*($C$3/$B$3*B8) -> 52738.512 | I8: 53208.476
A9: =EDATE(A8,1) -> 45717 | B9: =VLOOKUP(A9,'INCC - DI'!$E:$F,2,FALSE) -> 1173.775 | C9: 0.0090041098 | D9: =(C9*$C$3)*B9/$B$3 -> 41711.491 | F9: 0.0090041098 | G9: =F9*($C$3/$B$3*B9) -> 41711.491 | I9: 41726.833
A10: =EDATE(A9,1) -> 45748 | B10: =VLOOKUP(A10,'INCC - DI'!$E:$F,2,FALSE) -> 1178.386 | C10: 0.014780327 | D10: =(C10*$C$3)*B10/$B$3 -> 68738.763 | F10: 0.014780327 | G10: =F10*($C$3/$B$3*B10) -> 68738.763 | I10: 68494.973
A11: =EDATE(A10,1) -> 45778 | B11: =VLOOKUP(A11,'INCC - DI'!$E:$F,2,FALSE) -> 1184.462 | C11: 0.012970405 | D11: =(C11*$C$3)*B11/$B$3 -> 60632.401 | F11: 0.012970405 | G11: =F11*($C$3/$B$3*B11) -> 60632.401 | I11: 73417.827
A12: =EDATE(A11,1) -> 45809 | B12: =VLOOKUP(A12,'INCC - DI'!$E:$F,2,FALSE) -> 1191.327 | C12: 0.010041688 | D12: =(C12*$C$3)*B12/$B$3 -> 47213.672 | F12: 0.010275945 | G12: =F12*($C$3/$B$3*B12) -> 48315.094 | I12: 34736.985
A13: =EDATE(A12,1) -> 45839 | B13: =VLOOKUP(A13,'INCC - DI'!$E:$F,2,FALSE) -> 1199.509 | C13: 0.022967134 | D13: =(C13*$C$3)*B13/$B$3 -> 108727.75 | F13: 0.022967134 | G13: =F13*($C$3/$B$3*B13) -> 108727.75 | I13: 108767.74
A14: =EDATE(A13,1) -> 45870 | B14: =VLOOKUP(A14,'INCC - DI'!$E:$F,2,FALSE) -> 1210.471 | C14: 0.028324889 | D14: =(C14*$C$3)*B14/$B$3 -> 135317.1 | F14: 0.028324889 | G14: =F14*($C$3/$B$3*B14) -> 135317.1 | I14: 135366.87
A15: =EDATE(A14,1) -> 45901 | B15: =VLOOKUP(A15,'INCC - DI'!$E:$F,2,FALSE) -> 1216.706 | C15: 0.030828737 | D15: =(C15*$C$3)*B15/$B$3 -> 148037.41 | F15: 0.030828737 | G15: =F15*($C$3/$B$3*B15) -> 148037.41 | I15: 148091.86
A16: =EDATE(A15,1) -> 45931 | B16: =VLOOKUP(A16,'INCC - DI'!$E:$F,2,FALSE) -> 1218.747 | C16: 0.034398532 | D16: =(C16*$C$3)*B16/$B$3 -> 165456.39 | F16: 0.034398532 | G16: =F16*($C$3/$B$3*B16) -> 165456.39 | I16: 165517.25
A17: =EDATE(A16,1) -> 45962 | B17: =VLOOKUP(A17,'INCC - DI'!$E:$F,2,FALSE) -> 1222.356 | C17: 0.034189799 | D17: =(C17*$C$3)*B17/$B$3 -> 164939.38 | F17: 0.033955543 | G17: =F17*($C$3/$B$3*B17) -> 163809.27 | I17: 165000.04
... A21: =EDATE(A20,1) -> 46082 | B21: =VLOOKUP(A21,'INCC - DI'!$E:$F,2,FALSE) -> 1240.481 | C21: 0.02215241 | D21: =(C21*$C$3)*B21/$B$3 -> 108452.9 | F21: 0.022356243 | G21: =F21*($C$3/$B$3*B21) -> 109450.82 | I21: 108526.58
A22: =EDATE(A21,1) -> 46113 | B22: =VLOOKUP(A22,'INCC - DI'!$E:$F,2,FALSE) -> 1247.181 | C22: 0.023216832 | D22: =(C22*$C$3)*B22/$B$3 -> 114277.97 | F22: 0.023210595 | G22: =F22*($C$3/$B$3*B22) -> 114247.27 | I22: 114277.97 | K22: =SUM(K4:K21) -> -2978.52
A23: =EDATE(A22,1) -> 46143 | B23: =VLOOKUP(A23,'INCC - DI'!$E:$F,2,FALSE) -> 1259.652 | C23: 0.024085158 | D23: =(C23*$C$3)*B23/$B$3 -> 119737.49 | F23: 0.023550681 | G23: =F23*($C$3/$B$3*B23) -> 117080.38 | I23: 117414.45
A24: =EDATE(A23,1) -> 46174 | B24: =VLOOKUP(A24,'INCC - DI'!$E:$F,2,FALSE) -> 1270.695 | C24: 0.02279752 | D24: =(C24*$C$3)*B24/$B$3 -> 114329.69 | F24: 0.022938596 | G24: =F24*($C$3/$B$3*B24) -> 115037.18 | I24: 115515.13
A25: =EDATE(A24,1) -> 46204 | B25: =VLOOKUP(A25,'INCC - DI'!$E:$F,2,FALSE) -> 1270.695 | D25: =(C25*$C$3)*B25/$B$3 -> 0 | F25: 0.029805661 | G25: =F25*($C$3/$B$3*B25) -> 149475.55 | H25: =(F25*$G$1/(SUM($F$25:$F$48))) -> 149201.4
A26: =EDATE(A25,1) -> 46235 | B26: =VLOOKUP(A26,'INCC - DI'!$E:$F,2,FALSE) -> 1270.695 | D26: =(C26*$C$3)*B26/$B$3 -> 0 | F26: 0.029223208 | G26: =F26*($C$3/$B$3*B26) -> 146554.55 | H26: =(F26*$G$1/(SUM($F$25:$F$48))) -> 146285.75
A27: =EDATE(A26,1) -> 46266 | B27: =VLOOKUP(A27,'INCC - DI'!$E:$F,2,FALSE) -> 1270.695 | D27: =(C27*$C$3)*B27/$B$3 -> 0 | F27: 0.034226589 | G27: =F27*($C$3/$B$3*B27) -> 171646.53 | H27: =(F27*$G$1/(SUM($F$25:$F$48))) -> 171331.71
A28: =EDATE(A27,1) -> 46296 | B28: =VLOOKUP(A28,'INCC - DI'!$E:$F,2,FALSE) -> 1270.695 | D28: =(C28*$C$3)*B28/$B$3 -> 0 | F28: 0.037919847 | G28: =F28*($C$3/$B$3*B28) -> 190168.23 | H28: =(F28*$G$1/(SUM($F$25:$F$48))) -> 189819.44
A29: =EDATE(A28,1) -> 46327 | B29: =VLOOKUP(A29,'INCC - DI'!$E:$F,2,FALSE) -> 1270.695 | D29: =(C29*$C$3)*B29/$B$3 -> 0 | F29: 0.032884256 | G29: =F29*($C$3/$B$3*B29) -> 164914.72 | H29: =(F29*$G$1/(SUM($F$25:$F$48))) -> 164612.25
A30: =EDATE(A29,1) -> 46357 | B30: =VLOOKUP(A30,'INCC - DI'!$E:$F,2,FALSE) -> 1270.695 | D30: =(C30*$C$3)*B30/$B$3 -> 0 | F30: 0.017387386 | G30: =F30*($C$3/$B$3*B30) -> 87197.837 | H30: =(F30*$G$1/(SUM($F$25:$F$48))) -> 87037.906
A31: =EDATE(A30,1) -> 46388 | B31: =VLOOKUP(A31,'INCC - DI'!$E:$F,2,FALSE) -> 1270.695 | D31: =(C31*$C$3)*B31/$B$3 -> 0 | F31: 0.027509189 | G31: =F31*($C$3/$B$3*B31) -> 137958.73 | H31: =(F31*$G$1/(SUM($F$25:$F$48))) -> 137705.7
A32: =EDATE(A31,1) -> 46419 | B32: =VLOOKUP(A32,'INCC - DI'!$E:$F,2,FALSE) -> 1270.695 | D32: =(C32*$C$3)*B32/$B$3 -> 0 | F32: 0.033696962 | G32: =F32*($C$3/$B$3*B32) -> 168990.45 | H32: =(F32*$G$1/(SUM($F$25:$F$48))) -> 168680.5
A33: =EDATE(A32,1) -> 46447 | B33: =VLOOKUP(A33,'INCC - DI'!$E:$F,2,FALSE) -> 1270.695 | D33: =(C33*$C$3)*B33/$B$3 -> 0 | F33: 0.033557992 | G33: =F33*($C$3/$B$3*B33) -> 168293.51 | H33: =(F33*$G$1/(SUM($F$25:$F$48))) -> 167984.84
A34: =EDATE(A33,1) -> 46478 | B34: =VLOOKUP(A34,'INCC - DI'!$E:$F,2,FALSE) -> 1270.695 | D34: =(C34*$C$3)*B34/$B$3 -> 0 | F34: 0.055079113 | G34: =F34*($C$3/$B$3*B34) -> 276222.05 | H34: =(F34*$G$1/(SUM($F$25:$F$48))) -> 275715.43
A35: =EDATE(A34,1) -> 46508 | B35: =VLOOKUP(A35,'INCC - DI'!$E:$F,2,FALSE) -> 1270.695 | D35: =(C35*$C$3)*B35/$B$3 -> 0 | F35: 0.042880096 | G35: =F35*($C$3/$B$3*B35) -> 215043.91 | H35: =(F35*$G$1/(SUM($F$25:$F$48))) -> 214649.5
A36: =EDATE(A35,1) -> 46539 | B36: =VLOOKUP(A36,'INCC - DI'!$E:$F,2,FALSE) -> 1270.695 | D36: =(C36*$C$3)*B36/$B$3 -> 0 | F36: 0.060063165 | G36: =F36*($C$3/$B$3*B36) -> 301217.1 | H36: =(F36*$G$1/(SUM($F$25:$F$48))) -> 300664.63
... A48: =EDATE(A47,1) -> 46905 | B48: =VLOOKUP(A48,'INCC - DI'!$E:$F,2,FALSE) -> 1270.695 | D48: =(C48*$C$3)*B48/$B$3 -> 0 | F48: 0.0015 | G48: =F48*($C$3/$B$3*B48) -> 7522.5081 | H48: =(F48*$G$1/(SUM($F$25:$F$48))) -> 7508.7109
C49: =SUM(C5:C48) -> 0.4217
C50: 0.4217
C51: =C50-C49 -> 0

Sheet Poty
A1: Poty | F1: saldo | G1: =G3-D3 -> 3373721.1 | H1: =G3-I3 -> 3373721.1
A2: Data Base | B2: INCC Base | C2: Valor Orçado c/ Aditivos | D2: Valor da Taxa (Reaj) | G2: Valor Previsto Total | I2: Valor Cobrado
A3: 45413 | B3: =VLOOKUP(A3,'INCC - DI'!$E:$F,2,FALSE) -> 1101.389 | C3: 5840925.2 | D3: =SUM(D5:D45) -> 3203905.4 | G3: =SUM(G5:G45) -> 6577626.4 | I3: =SUM(I5:I45) -> 3203905.4 | J3: =D3-I3 -> 0 | K3: Aditivos Incorporação
A4: Mês | B4: INCC DI (n-1) | C4: Medição | D4: Valor da Taxa (Reaj) | F4: Medição Prevista | G4: Valor Previsto | I4: Valor Cobrado | K4: 17094.189
A5: 45474 | B5: =VLOOKUP(A5,'INCC - DI'!$E:$F,2,FALSE) -> 1118.827 | C5: 0.013032977 | D5: =(C5*$C$3)*B5/$B$3 -> 77329.905 | F5: 0.013032977 | G5: =F5*($C$3/$B$3*B5) -> 77329.905 | I5: 77343.145
A6: 45505 | B6: =VLOOKUP(A6,'INCC - DI'!$E:$F,2,FALSE) -> 1126.916 | C6: 0.015319593 | D6: =(C6*$C$3)*B6/$B$3 -> 91554.495 | F6: 0.015319593 | G6: =F6*($C$3/$B$3*B6) -> 91554.495 | I6: 91570.17
A7: 45536 | B7: =VLOOKUP(A7,'INCC - DI'!$E:$F,2,FALSE) -> 1134.775 | C7: 0.0098844824 | D7: =(C7*$C$3)*B7/$B$3 -> 59484.608 | F7: 0.0098844824 | G7: =F7*($C$3/$B$3*B7) -> 59484.608 | I7: 59494.792
A8: 45566 | B8: =VLOOKUP(A8,'INCC - DI'!$E:$F,2,FALSE) -> 1141.398 | C8: 0.013244555 | D8: =(C8*$C$3)*B8/$B$3 -> 80170.648 | F8: 0.013244878 | G8: =F8*($C$3/$B$3*B8) -> 80172.605 | I8: 80184.374
A9: 45597 | B9: =VLOOKUP(A9,'INCC - DI'!$E:$F,2,FALSE) -> 1149.17 | C9: 0.015527905 | D9: =(C9*$C$3)*B9/$B$3 -> 94632.009 | F9: 0.015527905 | G9: =F9*($C$3/$B$3*B9) -> 94632.009 | I9: 95096.189
A10: 45627 | B10: =VLOOKUP(A10,'INCC - DI'!$E:$F,2,FALSE) -> 1153.725 | C10: 0.0064818876 | D10: =(C10*$C$3)*B10/$B$3 -> 39659.27 | F10: 0.0064818876 | G10: =F10*($C$3/$B$3*B10) -> 39659.27 | I10: 43321.344
A11: 45658 | B11: =VLOOKUP(A11,'INCC - DI'!$E:$F,2,FALSE) -> 1159.536 | C11: 0.011316621 | D11: =(C11*$C$3)*B11/$B$3 -> 69589.214 | F11: 0.011316621 | G11: =F11*($C$3/$B$3*B11) -> 69589.214 | I11: 65453.892
A12: 45689 | B12: =VLOOKUP(A12,'INCC - DI'!$E:$F,2,FALSE) -> 1169.116 | C12: 0.017449319 | D12: =(C12*$C$3)*B12/$B$3 -> 108187.48 | F12: 0.017449219 | G12: =F12*($C$3/$B$3*B12) -> 108186.86 | I12: 108099.76
A13: 45717 | B13: =VLOOKUP(A13,'INCC - DI'!$E:$F,2,FALSE) -> 1173.775 | C13: 0.019519456 | D13: =(C13*$C$3)*B13/$B$3 -> 121504.81 | F13: 0.019519456 | G13: =F13*($C$3/$B$3*B13) -> 121504.81 | I13: 121504.81
A14: 45748 | B14: =VLOOKUP(A14,'INCC - DI'!$E:$F,2,FALSE) -> 1178.386 | C14: 0.021740683 | D14: =(C14*$C$3)*B14/$B$3 -> 135863.14 | F14: 0.021740683 | G14: =F14*($C$3/$B$3*B14) -> 135863.14 | I14: 135331.51
A15: 45778 | B15: =VLOOKUP(A15,'INCC - DI'!$E:$F,2,FALSE) -> 1184.462 | C15: 0.018877389 | D15: =(C15*$C$3)*B15/$B$3 -> 118577.96 | F15: 0.018877389 | G15: =F15*($C$3/$B$3*B15) -> 118577.96 | I15: 119109.59
A16: 45809 | B16: =VLOOKUP(A16,'INCC - DI'!$E:$F,2,FALSE) -> 1191.327 | C16: 0.017460095 | D16: =(C16*$C$3)*B16/$B$3 -> 110310.92 | F16: 0.017460095 | G16: =F16*($C$3/$B$3*B16) -> 110310.92 | I16: 110354.88
... A28: 46174 | B28: =VLOOKUP(A28,'INCC - DI'!$E:$F,2,FALSE) -> 1270.695 | C28: 0.0466934 | D28: =(C28*$C$3)*B28/$B$3 -> 314657.24 | F28: 0.041634208 | G28: =F28*($C$3/$B$3*B28) -> 280564.38 | I28: 317044.68
A29: 46204 | B29: =VLOOKUP(A29,'INCC - DI'!$E:$F,2,FALSE) -> 1270.695 | D29: =(C29*$C$3)*B29/$B$3 -> 0 | F29: 0.049093952 | G29: =F29*($C$3/$B$3*B29) -> 330834.07 | H29: =(F29*$G$1/(SUM($F$29:$F$46))) -> 340384.81
A30: 46235 | B30: =VLOOKUP(A30,'INCC - DI'!$E:$F,2,FALSE) -> 1270.695 | D30: =(C30*$C$3)*B30/$B$3 -> 0 | F30: 0.042424645 | G30: =F30*($C$3/$B$3*B30) -> 285890.98 | H30: =(F30*$G$1/(SUM($F$29:$F$46))) -> 294144.26
A31: 46266 | B31: =VLOOKUP(A31,'INCC - DI'!$E:$F,2,FALSE) -> 1270.695 | D31: =(C31*$C$3)*B31/$B$3 -> 0 | F31: 0.053209253 | G31: =F31*($C$3/$B$3*B31) -> 358566.24 | H31: =(F31*$G$1/(SUM($F$29:$F$46))) -> 368917.57
A32: 46296 | B32: =VLOOKUP(A32,'INCC - DI'!$E:$F,2,FALSE) -> 1270.695 | D32: =(C32*$C$3)*B32/$B$3 -> 0 | F32: 0.065214167 | G32: =F32*($C$3/$B$3*B32) -> 439464.89 | H32: =(F32*$G$1/(SUM($F$29:$F$46))) -> 452151.65
A33: 46327 | B33: =VLOOKUP(A33,'INCC - DI'!$E:$F,2,FALSE) -> 1270.695 | D33: =(C33*$C$3)*B33/$B$3 -> 0 | F33: 0.056950243 | G33: =F33*($C$3/$B$3*B33) -> 383776.01 | H33: =(F33*$G$1/(SUM($F$29:$F$46))) -> 394855.1
A34: 46357 | B34: =VLOOKUP(A34,'INCC - DI'!$E:$F,2,FALSE) -> 1270.695 | D34: =(C34*$C$3)*B34/$B$3 -> 0 | F34: 0.04010913 | G34: =F34*($C$3/$B$3*B34) -> 270287.2 | H34: =(F34*$G$1/(SUM($F$29:$F$46))) -> 278090.03
A35: 46388 | B35: =VLOOKUP(A35,'INCC - DI'!$E:$F,2,FALSE) -> 1270.695 | D35: =(C35*$C$3)*B35/$B$3 -> 0 | F35: 0.061220117 | G35: =F35*($C$3/$B$3*B35) -> 412549.81 | H35: =(F35*$G$1/(SUM($F$29:$F$46))) -> 424459.56
A36: 46419 | B36: =VLOOKUP(A36,'INCC - DI'!$E:$F,2,FALSE) -> 1270.695 | D36: =(C36*$C$3)*B36/$B$3 -> 0 | F36: 0.04859789 | G36: =F36*($C$3/$B$3*B36) -> 327491.21 | H36: =(F36*$G$1/(SUM($F$29:$F$46))) -> 336945.44
A37: 46447 | B37: =VLOOKUP(A37,'INCC - DI'!$E:$F,2,FALSE) -> 1270.695 | D37: =(C37*$C$3)*B37/$B$3 -> 0 | F37: 0.025858355 | G37: =F37*($C$3/$B$3*B37) -> 174254.15 | H37: =(F37*$G$1/(SUM($F$29:$F$46))) -> 179284.63
A38: 46478 | B38: =VLOOKUP(A38,'INCC - DI'!$E:$F,2,FALSE) -> 1270.695 | D38: =(C38*$C$3)*B38/$B$3 -> 0 | F38: 0.016471322 | G38: =F38*($C$3/$B$3*B38) -> 110996.86 | H38: =(F38*$G$1/(SUM($F$29:$F$46))) -> 114201.19
A39: 46508 | B39: =VLOOKUP(A39,'INCC - DI'!$E:$F,2,FALSE) -> 1270.695 | D39: =(C39*$C$3)*B39/$B$3 -> 0 | F39: 0.012132055 | G39: =F39*($C$3/$B$3*B39) -> 81755.428 | H39: =(F39*$G$1/(SUM($F$29:$F$46))) -> 84115.597
A40: 46539 | B40: =VLOOKUP(A40,'INCC - DI'!$E:$F,2,FALSE) -> 1270.695 | D40: =(C40*$C$3)*B40/$B$3 -> 0 | F40: 0.0069608481 | G40: =F40*($C$3/$B$3*B40) -> 46907.727 | H40: =(F40*$G$1/(SUM($F$29:$F$46))) -> 48261.89
... A45: 46692 | B45: =VLOOKUP(A45,'INCC - DI'!$E:$F,2,FALSE) -> 1270.695 | D45: =(C45*$C$3)*B45/$B$3 -> 0 | F45: 0.00051456484 | G45: =F45*($C$3/$B$3*B45) -> 3467.5469 | H45: =(F45*$G$1/(SUM($F$29:$F$46))) -> 3567.6503
C46: =SUM(C5:C45) -> 0.49906522
C47: 0.49906522
C48: =C47-C46 -> 0

Sheet Qoya
A1: Qoya
A2: Data Base | B2: INCC Base | D2: Valor da Taxa (Orç) | E2: Valor da Taxa (Reaj) | F2: Diferença
A3: 45170 | B3: 1078.412 | D3: =SUM(D7:D42) -> 5245908.3 | E3: =SUM(E7:E42) -> 5771767.4 | F3: =SUM(F7:F42) -> 525859.05
A4: Mês | B4: INCC | C4: INCC (Calc) | D4: Valor Base | E4: Valor Reajustado (Cobrado) | F4: Diferença
A5: 45352 | B5: =VLOOKUP(A5,'INCC - DI'!$A:$B,2,0) -> 1095.738
A6: 45383 | B6: =VLOOKUP(A6,'INCC - DI'!$A:$B,2,0) -> 1101.389
A7: 45413 | B7: =VLOOKUP(A7,'INCC - DI'!$A:$B,2,0) -> 1110.887 | C7: =B6 -> 1101.389 | D7: 40749.62 | E7: =D7 -> 40749.62 | F7: =E7-D7 -> 0
A8: 45444 | B8: =VLOOKUP(A8,'INCC - DI'!$A:$B,2,0) -> 1118.827 | C8: =B7 -> 1110.887 | D8: 62408.31 | E8: =D8*C8/$B$8 -> 61965.416 | F8: =E8-D8 -> -442.89419 | G8: Nova curva
A9: 45474 | B9: =VLOOKUP(A9,'INCC - DI'!$A:$B,2,0) -> 1126.916 | C9: =B8 -> 1118.827 | D9: 160279.44 | E9: =D9*C9/$B$8 -> 160279.44 | F9: =E9-D9 -> 0
A10: 45505 | B10: =VLOOKUP(A10,'INCC - DI'!$A:$B,2,0) -> 1134.775 | C10: =B9 -> 1126.916 | D10: 141857.8 | E10: =D10*C10/$B$8 -> 142883.42 | F10: =E10-D10 -> 1025.6168
A11: 45536 | B11: =VLOOKUP(A11,'INCC - DI'!$A:$B,2,0) -> 1141.398 | C11: =B10 -> 1134.775 | D11: 55955.58 | E11: =D11*C11/$B$8 -> 56753.183 | F11: =E11-D11 -> 797.60284
A12: 45566 | B12: =VLOOKUP(A12,'INCC - DI'!$A:$B,2,0) -> 1149.17 | C12: =B11 -> 1141.398 | D12: 38395.8 | E12: =D12*C12/$B$8 -> 39170.389 | F12: =E12-D12 -> 774.58946
A13: 45597 | B13: =VLOOKUP(A13,'INCC - DI'!$A:$B,2,0) -> 1153.725 | C13: =B12 -> 1149.17 | D13: 65574.31 | E13: =D13*C13/$B$8 -> 67352.709 | F13: =E13-D13 -> 1778.3994
A14: 45627 | B14: =VLOOKUP(A14,'INCC - DI'!$A:$B,2,0) -> 1159.536 | C14: =B13 -> 1153.725 | D14: 102291.57 | E14: =D14*C14/$B$8 -> 105482.21 | F14: =E14-D14 -> 3190.6373
A15: 45658 | B15: =VLOOKUP(A15,'INCC - DI'!$A:$B,2,0) -> 1169.116 | C15: =B14 -> 1159.536 | D15: 140682.99 | E15: =D15*C15/$B$8 -> 145801.8 | F15: =E15-D15 -> 5118.8109
A16: 45689 | B16: =VLOOKUP(A16,'INCC - DI'!$A:$B,2,0) -> 1173.775 | C16: =B15 -> 1169.116 | D16: 147575.79 | E16: =D16*C16/$B$8 -> 154209.02 | F16: =E16-D16 -> 6633.2319
A17: 45717 | B17: =VLOOKUP(A17,'INCC - DI'!$A:$B,2,0) -> 1178.386 | C17: =B16 -> 1173.775 | D17: 107920.65 | E17: =D17*C17/$B$8 -> 113220.87 | F17: =E17-D17 -> 5300.2152
A18: 45748 | B18: =VLOOKUP(A18,'INCC - DI'!$A:$B,2,0) -> 1184.462 | C18: =B17 -> 1178.386 | D18: 57327.63 | E18: =D18*C18/$B$8 -> 60379.376 | F18: =E18-D18 -> 3051.7464
A19: 45778 | B19: =VLOOKUP(A19,'INCC - DI'!$A:$B,2,0) -> 1191.327 | C19: =B18 -> 1184.462 | D19: 60057.52 | E19: =D19*C19/$B$8 -> 63580.741 | F19: =E19-D19 -> 3523.2215
A20: 45809 | B20: =VLOOKUP(A20,'INCC - DI'!$A:$B,2,0) -> 1199.509 | C20: =B19 -> 1191.327 | D20: 57327.63 | E20: =D20*C20/$B$8 -> 61042.461 | F20: =E20-D20 -> 3714.831
... A42: 46478 | B42: =VLOOKUP(A42,'INCC - DI'!$A:$B,2,0) -> 1270.695 | C42: =B41 -> 1270.695 | D42: 28086.91 | E42: =D42*C42/$B$8 -> 31899.388 | F42: =E42-D42 -> 3812.4776

Sheet Unna
A1: Unna | H1: OBS: - INCC MÊS ANTERIOR; - EMITE ND NO MÊS; - PAGAMENTO PRÓXIMO MÊS.
A2: Data Base | B2: INCC Base | D2: Valor da Taxa (Orç) | E2: Valor da Taxa (Reaj) | F2: Diferença
A3: 44774 | B3: =VLOOKUP(A3,'INCC - M'!$A:$F,2,FALSE) -> 1045.469 | D3: =SUM(D6:D39) -> 8946430.6 | E3: =SUM(E6:E39) -> 9991775.6 | F3: =SUM(F6:F39) -> 1045345
A4: Mês | B4: INCC | C4: INCC (Calc) | D4: Valor Base | E4: Valor Reajustado (Cobrado) | F4: Diferença
A5: 45017 | B5: =VLOOKUP(A5,'INCC - M'!$A:$F,2,FALSE) -> 1061.071
A6: 45047 | B6: =VLOOKUP(A6,'INCC - M'!$A:$F,2,FALSE) -> 1065.289 | C6: =B5 -> 1061.071 | D6: 118987.53 | E6: =D6*C6/$B$3 -> 120763.23 | F6: =E6-D6 -> 1775.7039
A7: 45078 | B7: =VLOOKUP(A7,'INCC - M'!$A:$F,2,FALSE) -> 1074.292 | C7: =B6 -> 1065.289 | D7: 94832.164 | E7: =D7*C7/$B$3 -> 96629.992 | F7: =E7-D7 -> 1797.828
A8: 45108 | B8: =VLOOKUP(A8,'INCC - M'!$A:$F,2,FALSE) -> 1074.895 | C8: =B7 -> 1074.292 | D8: 78728.589 | E8: =D8*C8/$B$3 -> 80899.093 | F8: =E8-D8 -> 2170.5035
A9: 45139 | B9: =VLOOKUP(A9,'INCC - M'!$A:$F,2,FALSE) -> 1077.497 | C9: =B8 -> 1074.895 | D9: 78728.589 | E9: =D9*C9/$B$3 -> 80944.501 | F9: =E9-D9 -> 2215.9122
A10: 45170 | B10: =VLOOKUP(A10,'INCC - M'!$A:$F,2,FALSE) -> 1080.071 | C10: =B9 -> 1077.497 | D10: 78728.589 | E10: =D10*C10/$B$3 -> 81140.444 | F10: =E10-D10 -> 2411.8546
A11: 45200 | B11: =VLOOKUP(A11,'INCC - M'!$A:$F,2,FALSE) -> 1082.251 | C11: =B10 -> 1080.071 | D11: 78728.589 | E11: =D11*C11/$B$3 -> 81334.278 | F11: =E11-D11 -> 2605.6886
A12: 45231 | B12: =VLOOKUP(A12,'INCC - M'!$A:$F,2,FALSE) -> 1083.335 | C12: =B11 -> 1082.251 | D12: 76939.303 | E12: =D12*C12/$B$3 -> 79646.204 | F12: =E12-D12 -> 2706.9013
A13: 45261 | B13: =VLOOKUP(A13,'INCC - M'!$A:$F,2,FALSE) -> 1086.15 | C13: =B12 -> 1083.335 | D13: 179823.25 | E13: =D13*C13/$B$3 -> 186336.3 | F13: =E13-D13 -> 6513.0457
A14: 45292 | B14: =VLOOKUP(A14,'INCC - M'!$A:$F,2,FALSE) -> 1088.663 | C14: =B13 -> 1086.15 | D14: 231712.55 | E14: =D14*C14/$B$3 -> 240728.89 | F14: =E14-D14 -> 9016.3346
A15: 45323 | B15: =VLOOKUP(A15,'INCC - M'!$A:$F,2,FALSE) -> 1090.871 | C15: =B14 -> 1088.663 | D15: 212030.4 | E15: =D15*C15/$B$3 -> 220790.53 | F15: =E15-D15 -> 8760.1271
A16: 45352 | B16: =VLOOKUP(A16,'INCC - M'!$A:$F,2,FALSE) -> 1093.503 | C16: =B15 -> 1090.871 | D16: 187875.04 | E16: =D16*C16/$B$3 -> 196033.97 | F16: =E16-D16 -> 8158.9245
A17: 45383 | B17: =VLOOKUP(A17,'INCC - M'!$A:$F,2,FALSE) -> 1097.991 | C17: =B16 -> 1093.503 | D17: 199505.4 | E17: =D17*C17/$B$3 -> 208671.66 | F17: =E17-D17 -> 9166.2617
... A39: 46054 | B39: =VLOOKUP(A39,'INCC - M'!$A:$F,2,FALSE) -> 1237.312 | C39: =B38 -> 1233.096 | D39: 158351.82 | E39: =D39*C39/$B$3 -> 186770.72 | F39: =E39-D39 -> 28418.898

Sheet Unna R01
A1: Unna | Q1: OBS: - INCC MÊS ANTERIOR; - EMITE ND NO MÊS; - PAGAMENTO PRÓXIMO MÊS.
A2: Data Base | B2: INCC Base | D2: Valor da Taxa (Orç) | E2: Valor da Taxa (Reaj) | F2: Diferença
A3: 44774 | B3: =VLOOKUP(A3,'INCC - M'!$A:$F,2,FALSE) -> 1045.469 | D3: =SUM(D6:D39) -> 8946430.6 | E3: =SUM(E6:E39) -> 9991775.6 | F3: =SUM(F6:F39) -> 1045345 | I3: Medição
A4: Mês | B4: INCC | C4: INCC (Calc) | D4: Valor Base | E4: Valor Reajustado (Cobrado) | F4: Diferença | I4: Realizado | J4: Previsto | K4: Valor Reajustado (Cobrado)
A5: 45017 | B5: =VLOOKUP(A5,'INCC - M'!$A:$F,2,FALSE) -> 1061.071
A6: 45047 | B6: =VLOOKUP(A6,'INCC - M'!$A:$F,2,FALSE) -> 1065.289 | C6: =B5 -> 1061.071 | D6: 118987.53 | E6: =D6*C6/$B$3 -> 120763.23 | F6: =E6-D6 -> 1775.7039 | H6: 45047 | I6: 0.0089087769 | K6: =I6*($D$3/$B$3*C6) -> 80891.179 | M6: 2532042 | N6: era pra ter sido cobrado
A7: 45078 | B7: =VLOOKUP(A7,'INCC - M'!$A:$F,2,FALSE) -> 1074.292 | C7: =B6 -> 1065.289 | D7: 94832.164 | E7: =D7*C7/$B$3 -> 96629.992 | F7: =E7-D7 -> 1797.828 | H7: 45078 | I7: 0.0093150901 | K7: =I7*($D$3/$B$3*C7) -> 84916.706 | M7: 2098148.5 | N7: cobrado
A8: 45108 | B8: =VLOOKUP(A8,'INCC - M'!$A:$F,2,FALSE) -> 1074.895 | C8: =B7 -> 1074.292 | D8: 78728.589 | E8: =D8*C8/$B$3 -> 80899.093 | F8: =E8-D8 -> 2170.5035 | H8: 45108 | I8: 0.0091427032 | K8: =I8*($D$3/$B$3*C8) -> 84049.59 | M8: =M6-M7 -> 433893.51 | N8: diferença
A9: 45139 | B9: =VLOOKUP(A9,'INCC - M'!$A:$F,2,FALSE) -> 1077.497 | C9: =B8 -> 1074.895 | D9: 78728.589 | E9: =D9*C9/$B$3 -> 80944.501 | F9: =E9-D9 -> 2215.9122 | H9: 45139 | I9: 0.012304597 | K9: =I9*($D$3/$B$3*C9) -> 113180.62 | M9: em 26/07
A10: 45170 | B10: =VLOOKUP(A10,'INCC - M'!$A:$F,2,FALSE) -> 1080.071 | C10: =B9 -> 1077.497 | D10: 78728.589 | E10: =D10*C10/$B$3 -> 81140.444 | F10: =E10-D10 -> 2411.8546 | H10: 45170 | I10: 0.012658837 | K10: =I10*($D$3/$B$3*C10) -> 116720.87
A11: 45200 | B11: =VLOOKUP(A11,'INCC - M'!$A:$F,2,FALSE) -> 1082.251 | C11: =B10 -> 1080.071 | D11: 78728.589 | E11: =D11*C11/$B$3 -> 81334.278 | F11: =E11-D11 -> 2605.6886 | H11: 45200 | I11: 0.014858479 | K11: =I11*($D$3/$B$3*C11) -> 137329.97
A12: 45231 | B12: =VLOOKUP(A12,'INCC - M'!$A:$F,2,FALSE) -> 1083.335 | C12: =B11 -> 1082.251 | D12: 76939.303 | E12: =D12*C12/$B$3 -> 79646.204 | F12: =E12-D12 -> 2706.9013 | H12: 45231 | I12: 0.011469743 | K12: =I12*($D$3/$B$3*C12) -> 106223.43
A13: 45261 | B13: =VLOOKUP(A13,'INCC - M'!$A:$F,2,FALSE) -> 1086.15 | C13: =B12 -> 1083.335 | D13: 179823.25 | E13: =D13*C13/$B$3 -> 186336.3 | F13: =E13-D13 -> 6513.0457 | H13: 45261 | I13: 0.011616776 | K13: =I13*($D$3/$B$3*C13) -> 107692.89
A14: 45292 | B14: =VLOOKUP(A14,'INCC - M'!$A:$F,2,FALSE) -> 1088.663 | C14: =B13 -> 1086.15 | D14: 231712.55 | E14: =D14*C14/$B$3 -> 240728.89 | F14: =E14-D14 -> 9016.3346 | H14: 45292 | I14: 0.026287543 | K14: =I14*($D$3/$B$3*C14) -> 244330.92
A15: 45323 | B15: =VLOOKUP(A15,'INCC - M'!$A:$F,2,FALSE) -> 1090.871 | C15: =B14 -> 1088.663 | D15: 212030.4 | E15: =D15*C15/$B$3 -> 220790.53 | F15: =E15-D15 -> 8760.1271 | H15: 45323 | I15: 0.024278094 | K15: =I15*($D$3/$B$3*C15) -> 226176.09
A16: 45352 | B16: =VLOOKUP(A16,'INCC - M'!$A:$F,2,FALSE) -> 1093.503 | C16: =B15 -> 1090.871 | D16: 187875.04 | E16: =D16*C16/$B$3 -> 196033.97 | F16: =E16-D16 -> 8158.9245 | H16: 45352 | I16: 0.022869584 | K16: =I16*($D$3/$B$3*C16) -> 213486.44
A17: 45383 | B17: =VLOOKUP(A17,'INCC - M'!$A:$F,2,FALSE) -> 1097.991 | C17: =B16 -> 1093.503 | D17: 199505.4 | E17: =D17*C17/$B$3 -> 208671.66 | F17: =E17-D17 -> 9166.2617 | H17: 45383 | I17: 0.035019256 | K17: =I17*($D$3/$B$3*C17) -> 327691.76
A18: 45413 | B18: =VLOOKUP(A18,'INCC - M'!$A:$F,2,FALSE) -> 1104.457 | C18: =B17 -> 1097.991 | D18: 193242.9 | E18: =D18*C18/$B$3 -> 202950.99 | F18: =E18-D18 -> 9708.0866 | H18: 45413 | I18: 0.044570825 | K18: =I18*($D$3/$B$3*C18) -> 418782.08
A19: 45444 | B19: =VLOOKUP(A19,'INCC - M'!$A:$F,2,FALSE) -> 1114.748 | C19: =B18 -> 1104.457 | D19: 195926.83 | E19: =D19*C19/$B$3 -> 206981.52 | F19: =E19-D19 -> 11054.686 | G19: Cancelado | H19: 45444 | I19: 0.028628016 | K19: =I19*($D$3/$B$3*C19) -> 270569.41 | L19: 221278.37
A20: 45474 | B20: =VLOOKUP(A20,'INCC - M'!$A:$F,2,FALSE) -> 1122.452 | C20: =B19 -> 1114.748 | D20: 193242.9 | E20: =D20*C20/$B$3 -> 206048.33 | F20: =E20-D20 -> 12805.425 | H20: 45474 | I20: 0.038359449 | K20: =I20*($D$3/$B$3*C20) -> 365921.31 | N20: =K41/20 -> 0
A21: 45505 | B21: =VLOOKUP(A21,'INCC - M'!$A:$F,2,FALSE) -> 1129.639 | C21: =B20 -> 1122.452 | D21: 193242.9 | E21: =D21*C21/$B$3 -> 207472.32 | F21: =E21-D21 -> 14229.421 | H21: 45505 | I21: 0.046803545 | J21: 0.058446532 | K21: =I21*($D$3/$B$3*C21) -> 449557.41 | M21: Taxa cfe execução e ajuste em Dez
A22: 45536 | B22: =VLOOKUP(A22,'INCC - M'!$A:$F,2,FALSE) -> 1136.521 | C22: =B21 -> 1129.639 | D22: 195926.83 | E22: =D22*C22/$B$3 -> 211700.77 | F22: =E22-D22 -> 15773.936 | H22: 45536 | I22: 0.042585481 | J22: 0.061169194 | K22: =I22*($D$3/$B$3*C22) -> 411661.14
A23: 45566 | B23: =VLOOKUP(A23,'INCC - M'!$A:$F,2,FALSE) -> 1144.136 | C23: =B22 -> 1136.521 | D23: 213819.69 | E23: =D23*C23/$B$3 -> 232441.68 | F23: =E23-D23 -> 18621.987 | H23: 45566 | J23: 0.06590707 | K23: =J23*($D$3/$B$3*C23) -> 640985.35
A24: 45597 | B24: =VLOOKUP(A24,'INCC - M'!$A:$F,2,FALSE) -> 1149.158 | C24: =B23 -> 1144.136 | D24: 212925.05 | E24: =D24*C24/$B$3 -> 233020.02 | F24: =E24-D24 -> 20094.977 | H24: 45597 | J24: 0.052108245 | K24: =J24*($D$3/$B$3*C24) -> 510179.19
A25: 45627 | B25: =VLOOKUP(A25,'INCC - M'!$A:$F,2,FALSE) -> 1154.99 | C25: =B24 -> 1149.158 | D25: 227239.34 | E25: =D25*C25/$B$3 -> 249776.8 | F25: =E25-D25 -> 22537.464 | H25: 45627 | J25: 0.03356944 | K25: =J25*($D$3/$B$3*C25) -> 330112.89
A26: 45658 | B26: =VLOOKUP(A26,'INCC - M'!$A:$F,2,FALSE) -> 1163.221 | C26: =B25 -> 1154.99 | D26: 220976.84 | E26: =D26*C26/$B$3 -> 244125.88 | F26: =E26-D26 -> 23149.04 | H26: 45658 | J26: 0.057676801 | K26: =J26*($D$3/$B$3*C26) -> 570056.67 | M26: =SUM(E6:E18)+SUM(K19:K25) -> 4855856.8
A27: 45689 | B27: =VLOOKUP(A27,'INCC - M'!$A:$F,2,FALSE) -> 1169.156 | C27: =B26 -> 1163.221 | D27: 221871.48 | E27: =D27*C27/$B$3 -> 246861.04 | F27: =E27-D27 -> 24989.56 | H27: 45689 | J27: 0.052632476 | K27: =J27*($D$3/$B$3*C27) -> 523907.57
A28: 45717 | B28: =VLOOKUP(A28,'INCC - M'!$A:$F,2,FALSE) -> 1173.586 | C28: =B27 -> 1169.156 | D28: 245132.2 | E28: =D28*C28/$B$3 -> 274133.22 | F28: =E28-D28 -> 29001.019 | H28: 45717 | J28: 0.040068676 | K28: =J28*($D$3/$B$3*C28) -> 400881.57
A29: 45748 | B29: =VLOOKUP(A29,'INCC - M'!$A:$F,2,FALSE) -> 1180.564 | C29: =B28 -> 1173.586 | D29: 240658.98 | E29: =D29*C29/$B$3 -> 270150.54 | F29: =E29-D29 -> 29491.555 | H29: 45748 | J29: 0.039442855 | K29: =J29*($D$3/$B$3*C29) -> 396115.56 | M29: 0.6004
A30: 45778 | B30: =VLOOKUP(A30,'INCC - M'!$A:$F,2,FALSE) -> 1183.606 | C30: =B29 -> 1180.564 | D30: 280917.92 | E30: =D30*C30/$B$3 -> 317218 | F30: =E30-D30 -> 36300.078 | H30: 45778 | J30: 0.055775677 | K30: =J30*($D$3/$B$3*C30) -> 563472.88 | M30: =M29*E3 -> 5999062.1
A31: 45809 | B31: =VLOOKUP(A31,'INCC - M'!$A:$F,2,FALSE) -> 1194.912 | C31: =B30 -> 1183.606 | D31: 395432.23 | E31: =D31*C31/$B$3 -> 447680.38 | F31: =E31-D31 -> 52248.151 | H31: 45809 | J31: 0.051131271 | K31: =J31*($D$3/$B$3*C31) -> 517883.87
A32: 45839 | B32: =VLOOKUP(A32,'INCC - M'!$A:$F,2,FALSE) -> 1205.838 | C32: =B31 -> 1194.912 | D32: 444637.6 | E32: =D32*C32/$B$3 -> 508195.66 | F32: =E32-D32 -> 63558.056 | H32: 45839 | J32: 0.042964763 | K32: =J32*($D$3/$B$3*C32) -> 439326.08 | M32: =M30-M26 -> 1143205.3
A33: 45870 | B33: =VLOOKUP(A33,'INCC - M'!$A:$F,2,FALSE) -> 1214.239 | C33: =B32 -> 1205.838 | D33: 514419.76 | E33: =D33*C33/$B$3 -> 593328.82 | F33: =E33-D33 -> 78909.066 | H33: 45870 | J33: 0.028552952 | K33: =J33*($D$3/$B$3*C33) -> 294631.12
A34: 45901 | B34: =VLOOKUP(A34,'INCC - M'!$A:$F,2,FALSE) -> 1216.825 | C34: =B33 -> 1214.239 | D34: 502789.4 | E34: =D34*C34/$B$3 -> 583954.66 | F34: =E34-D34 -> 81165.263 | H34: 45901 | J34: 0.010088484 | K34: =J34*($D$3/$B$3*C34) -> 104825.92
A35: 45931 | B35: =VLOOKUP(A35,'INCC - M'!$A:$F,2,FALSE) -> 1219.407 | C35: =B34 -> 1216.825 | D35: 640564.43 | E35: =D35*C35/$B$3 -> 745555.16 | F35: =E35-D35 -> 104990.73 | H35: 45931 | J35: 0.01299148 | K35: =J35*($D$3/$B$3*C35) -> 135277.45
A36: 45962 | B36: =VLOOKUP(A36,'INCC - M'!$A:$F,2,FALSE) -> 1222.865 | C36: =B35 -> 1219.407 | D36: 646826.93 | E36: =D36*C36/$B$3 -> 754441.58 | F36: =E36-D36 -> 107614.65 | H36: 45962 | J36: 0.0075173975 | K36: =J36*($D$3/$B$3*C36) -> 78443.116
A37: 45992 | B37: =VLOOKUP(A37,'INCC - M'!$A:$F,2,FALSE) -> 1225.398 | C37: =B36 -> 1222.865 | D37: 704084.09 | E37: =D37*C37/$B$3 -> 823553.63 | F37: =E37-D37 -> 119469.54 | H37: 45992 | J37: 0.003942212 | K37: =J37*($D$3/$B$3*C37) -> 41253.151
A38: 46023 | B38: =VLOOKUP(A38,'INCC - M'!$A:$F,2,FALSE) -> 1233.096 | C38: =B37 -> 1225.398 | D38: 487580.47 | E38: =D38*C38/$B$3 -> 571494.83 | F38: =E38-D38 -> 83914.364 | H38: 46023 | J38: 0.0037071158 | K38: =J38*($D$3/$B$3*C38) -> 38873.349
A39: 46054 | B39: =VLOOKUP(A39,'INCC - M'!$A:$F,2,FALSE) -> 1237.312 | C39: =B38 -> 1233.096 | D39: 158351.82 | E39: =D39*C39/$B$3 -> 186770.72 | F39: =E39-D39 -> 28418.898 | H39: 46054 | J39: 0.0034369235 | K39: =J39*($D$3/$B$3*C39) -> 36266.479
A40: 46082 | B40: =VLOOKUP(A40,'INCC - M'!$A:$F,2,FALSE) -> 1241.721 | C40: =B39 -> 1237.312 | J40: distribuido igualmente diferença de junho

Sheet Vivere
A1: Reserva Vivere | F1: saldo | G1: =G3-D3 -> 0.00053695177 | H1: =G3-I3 -> 0.00053695177
A2: Data Base | B2: INCC Base | C2: Valor Orçado | D2: Valor da Taxa (Reaj) | G2: Valor Previsto Total | I2: Valor Cobrado
A3: 45078 | B3: =VLOOKUP(A3,'INCC - DI'!$E:$F,2,FALSE) -> 1067.919 | C3: 100472.87 | D3: =SUM(D5:D16) -> 107528.66 | G3: =SUM(G5:G16) -> 107528.66 | I3: =SUM(I5:I15) -> 107528.66 | J3: =D3-I3 -> 0
A4: Mês | B4: INCC DI (n-1) | C4: Medição | D4: Valor da Taxa (Reaj) | F4: Medição Prevista | G4: Valor Previsto | I4: Valor Cobrado
A5: 45444 | B5: =VLOOKUP(A5,'INCC - DI'!$E:$F,2,FALSE) -> 1110.887 | C5: 0.05929519 | D5: =(C5*$C$3)*B5/$B$3 -> 6197.2616 | F5: 0.05929519 | G5: =F5*($C$3/$B$3*B5) -> 6197.2616 | I5: 6991.6729
A6: 45474 | B6: =VLOOKUP(A6,'INCC - DI'!$E:$F,2,FALSE) -> 1118.827 | C6: 0.13207428 | D6: =(C6*$C$3)*B6/$B$3 -> 13902.46 | F6: 0.13207428 | G6: =F6*($C$3/$B$3*B6) -> 13902.46 | I6: 13902.46
A7: 45505 | B7: =VLOOKUP(A7,'INCC - DI'!$E:$F,2,FALSE) -> 1126.916 | C7: 0.12008666 | D7: =(C7*$C$3)*B7/$B$3 -> 12732.005 | F7: 0.12008666 | G7: =F7*($C$3/$B$3*B7) -> 12732.005 | I7: 12732.005
A8: 45536 | B8: =VLOOKUP(A8,'INCC - DI'!$E:$F,2,FALSE) -> 1134.775 | C8: 0.073121263 | D8: =(C8*$C$3)*B8/$B$3 -> 7806.6358 | F8: 0.073121263 | G8: =F8*($C$3/$B$3*B8) -> 7806.6358 | I8: 7806.6358
A9: 45566 | B9: =VLOOKUP(A9,'INCC - DI'!$E:$F,2,FALSE) -> 1141.398 | C9: 0.14096626 | D9: =(C9*$C$3)*B9/$B$3 -> 15137.8 | F9: 0.14096626 | G9: =F9*($C$3/$B$3*B9) -> 15137.8 | I9: 14343.39
A10: 45597 | B10: =VLOOKUP(A10,'INCC - DI'!$E:$F,2,FALSE) -> 1149.17 | C10: 0.069431697 | D10: =(C10*$C$3)*B10/$B$3 -> 7506.7601 | F10: 0.069431697 | G10: =F10*($C$3/$B$3*B10) -> 7506.7601 | I10: 7506.76
A11: 45627 | B11: =VLOOKUP(A11,'INCC - DI'!$E:$F,2,FALSE) -> 1153.725 | C11: 0.043300323 | D11: =(C11*$C$3)*B11/$B$3 -> 4700.0656 | F11: 0.043300323 | G11: =F11*($C$3/$B$3*B11) -> 4700.0656 | I11: 4700.06
A12: 45658 | B12: =VLOOKUP(A12,'INCC - DI'!$E:$F,2,FALSE) -> 1159.536 | C12: 0.27272116 | D12: =(C12*$C$3)*B12/$B$3 -> 29751.821 | F12: 0.27893179 | G12: =F12*($C$3/$B$3*B12) -> 30429.354 | I12: 29751.825
A13: 45689 | B13: =VLOOKUP(A13,'INCC - DI'!$E:$F,2,FALSE) -> 1169.116 | C13: 0.04268105 | D13: =(C13*$C$3)*B13/$B$3 -> 4694.6495 | F13: 0.060937032 | G13: =F13*($C$3/$B$3*B13) -> 6702.6938 | I13: 4694.6495
A14: 45717 | B14: =VLOOKUP(A14,'INCC - DI'!$E:$F,2,FALSE) -> 1173.775 | C14: 0.030214648 | D14: =(C14*$C$3)*B14/$B$3 -> 3336.6671 | F14: 0.021690768 | G14: =F14*($C$3/$B$3*B14) -> 2395.3571 | I14: 3336.6671
A15: 45748 | B15: =VLOOKUP(A15,'INCC - DI'!$E:$F,2,FALSE) -> 1178.386 | C15: 0.003364793 | D15: 1762.53 | F15: 0.00016473215 | G15: =F15*($C$3/$B$3*B15) -> 18.263181 | I15: 1762.53
I16: FINALIZADO

Sheet Croma
A1: Croma | H1: OBS: - INCC MÊS ANTERIOR; - EMITE ND NO MÊS; - PAGAMENTO PRÓXIMO MÊS.
A2: Data Base | B2: INCC Base | D2: Valor da Taxa (Orç) | E2: Valor da Taxa (Reaj) | F2: Diferença
A3: 44805 | B3: =VLOOKUP(A3,'INCC - M'!$A:$F,2,FALSE) -> 1046.507 | D3: =SUM(D5:D37) -> 7331510.4 | E3: =SUM(E5:E37) -> 7641719.3 | F3: =SUM(F5:F35) -> 298732.56
A4: Mês | B4: INCC | C4: INCC (Calc) | D4: Valor Base | E4: Valor Reajustado (Cobrado) | F4: Diferença
A5: 44805 | B5: =VLOOKUP(A5,'INCC - M'!$A:$F,2,FALSE) -> 1046.507 | C5: - | D5: 65261.141 | E5: =D5 -> 65261.141 | F5: 0
A6: 44835 | B6: =VLOOKUP(A6,'INCC - M'!$A:$F,2,FALSE) -> 1046.956 | C6: - | D6: 76993.481 | E6: =D6 -> 76993.481 | F6: =E6-D6 -> 0
A7: 44866 | B7: =VLOOKUP(A7,'INCC - M'!$A:$F,2,FALSE) -> 1048.429 | C7: - | D7: 89459.092 | E7: =D7 -> 89459.092 | F7: =E7-D7 -> 0
A8: 44896 | B8: =VLOOKUP(A8,'INCC - M'!$A:$F,2,FALSE) -> 1051.249 | C8: =B8 -> 1051.249 | D8: 147746.59 | E8: =D8 -> 147746.59 | F8: =E8-D8 -> 0
A9: 44927 | B9: =VLOOKUP(A9,'INCC - M'!$A:$F,2,FALSE) -> 1054.561 | C9: =B9 -> 1054.561 | D9: 129512.84 | E9: =D9 -> 129512.84 | F9: =E9-D9 -> 0
A10: 44958 | B10: =VLOOKUP(A10,'INCC - M'!$A:$F,2,FALSE) -> 1056.775 | C10: =B10 -> 1056.775 | D10: 148727.02 | E10: =D10 -> 148727.02 | F10: =E10-D10 -> 0
A11: 44986 | B11: =VLOOKUP(A11,'INCC - M'!$A:$F,2,FALSE) -> 1058.65 | C11: =B11 -> 1058.65 | D11: 161939.65 | E11: =D11 -> 161939.65 | F11: =E11-D11 -> 0
A12: 45017 | B12: =VLOOKUP(A12,'INCC - M'!$A:$F,2,FALSE) -> 1061.071 | C12: =B12 -> 1061.071 | D12: 223185.61 | E12: 227086.8 | F12: =E12-D12 -> 3901.1919
A13: 45047 | B13: =VLOOKUP(A13,'INCC - M'!$A:$F,2,FALSE) -> 1065.289 | C13: =B12 -> 1061.071 | D13: 257916.98 | E13: =D13*C13/$C$8 -> 260326.74 | F13: =E13-D13 -> 2409.7626
A14: 45078 | B14: =VLOOKUP(A14,'INCC - M'!$A:$F,2,FALSE) -> 1074.292 | C14: =B13 -> 1065.289 | D14: 296628.61 | E14: =D14*C14/$C$8 -> 300590.25 | F14: =E14-D14 -> 3961.6358
A15: 45108 | B15: =VLOOKUP(A15,'INCC - M'!$A:$F,2,FALSE) -> 1074.895 | C15: =B14 -> 1074.292 | D15: 312081.02 | E15: =D15*C15/$C$8 -> 318921.73 | F15: =E15-D15 -> 6840.7038
A16: 45139 | B16: =VLOOKUP(A16,'INCC - M'!$A:$F,2,FALSE) -> 1077.497 | C16: =B15 -> 1074.895 | D16: 343287.26 | E16: =D16*C16/$C$8 -> 351008.9 | F16: =E16-D16 -> 7721.644
A17: 45170 | B17: =VLOOKUP(A17,'INCC - M'!$A:$F,2,FALSE) -> 1080.071 | C17: =B16 -> 1077.497 | D17: 366781.74 | E17: =D17*C17/$C$8 -> 375939.69 | F17: =E17-D17 -> 9157.9513
A18: 45200 | B18: =VLOOKUP(A18,'INCC - M'!$A:$F,2,FALSE) -> 1082.251 | C18: =B17 -> 1080.071 | D18: 372798.23 | E18: =D18*C18/$C$8 -> 383019.2 | F18: =E18-D18 -> 10220.976
A19: 45231 | B19: =VLOOKUP(A19,'INCC - M'!$A:$F,2,FALSE) -> 1083.335 | C19: =B18 -> 1082.251 | D19: 411937.07 | E19: =D19*C19/$C$8 -> 424085.36 | F19: =E19-D19 -> 12148.286
A20: 45261 | B20: =VLOOKUP(A20,'INCC - M'!$A:$F,2,FALSE) -> 1086.15 | C20: =B19 -> 1083.335 | D20: 319127.78 | E20: =D20*C20/$C$8 -> 328868.13 | F20: =E20-D20 -> 9740.3506
A21: 45292 | B21: =VLOOKUP(A21,'INCC - M'!$A:$F,2,FALSE) -> 1088.663 | C21: =B20 -> 1086.15 | D21: 329319.16 | E21: =D21*C21/$C$8 -> 340252.41 | F21: =E21-D21 -> 10933.25
A22: 45323 | B22: =VLOOKUP(A22,'INCC - M'!$A:$F,2,FALSE) -> 1090.871 | C22: =B21 -> 1088.663 | D22: 247621.21 | E22: =D22*C22/$C$8 -> 256434.06 | F22: =E22-D22 -> 8812.8503
A23: 45352 | B23: =VLOOKUP(A23,'INCC - M'!$A:$F,2,FALSE) -> 1093.503 | C23: =B22 -> 1090.871 | D23: 250855.25 | E23: =D23*C23/$C$8 -> 260310.09 | F23: =E23-D23 -> 9454.836
A24: 45383 | B24: =VLOOKUP(A24,'INCC - M'!$A:$F,2,FALSE) -> 1097.991 | C24: =B23 -> 1093.503 | D24: 267410.12 | E24: =D24*C24/$C$8 -> 278158.43 | F24: =E24-D24 -> 10748.307
... A37: 45778 | B37: =VLOOKUP(A37,'INCC - M'!$A:$F,2,FALSE) -> 1183.606 | C37: =B36 -> 1180.564 | D37: 22125.981 | E37: =D37*C37/$C$8 -> 24847.715 | F37: =E37-D37 -> 2721.735

Sheet Croma R01
A1: Croma | R1: OBS: - INCC MÊS ANTERIOR; - EMITE ND NO MÊS; - PAGAMENTO PRÓXIMO MÊS.
A2: Data Base | B2: INCC Base | D2: Valor da Taxa (Orç) | E2: Valor da Taxa (Reaj) | F2: Diferença | H2: Aram Aba Resumo (coluna AA) | P2: 5123495
A3: 44562 | B3: =VLOOKUP(A3,'INCC - M'!$A:$F,2,FALSE) -> 967.003 | D3: =SUM(D5:D37) -> 7331510.4 | E3: =SUM(E5:E37) -> 7641719.3 | F3: =SUM(F5:F37) -> 310208.84 | G3: 5123495 | H3: Medição | P3: 5582324.3
A4: Mês | B4: INCC | C4: INCC (Calc) | D4: Valor Base | E4: Valor Reajustado (Cobrado) | F4: Diferença | G4: =E3-G3 -> 2518224.2 | H4: Realizado | I4: Previsto | J4: Valor Reajustado (Cobrado) | L4: Taxa Realizado Reajustado | N4: Taxa Fixa Reajustada | P4: =P3-P2 -> 458829.31
A5: 44805 | B5: =VLOOKUP(A5,'INCC - M'!$A:$F,2,FALSE) -> 1046.507 | C5: - | D5: 65261.141 | E5: =D5 -> 65261.141 | F5: 0 | H5: 0.0088722564 | J5: =H5*$E$3 -> 67799.292 | L5: =H5*($D$3/$B$3*B5) -> 70395.007 | N5: =D5/$B$3*B5 -> 70626.71
A6: 44835 | B6: =VLOOKUP(A6,'INCC - M'!$A:$F,2,FALSE) -> 1046.956 | C6: - | D6: 76993.481 | E6: =D6 -> 76993.481 | F6: =E6-D6 -> 0 | H6: 0.010507913 | J6: =H6*$E$3 -> 80298.52 | L6: =H6*($D$3/$B$3*B6) -> 83408.541 | N6: =D6/$B$3*B6 -> 83359.397
A7: 44866 | B7: =VLOOKUP(A7,'INCC - M'!$A:$F,2,FALSE) -> 1048.429 | C7: - | D7: 89459.092 | E7: =D7 -> 89459.092 | F7: =E7-D7 -> 0 | H7: 0.012182026 | J7: =H7*$E$3 -> 93091.622 | L7: =H7*($D$3/$B$3*B7) -> 96833.177 | N7: =D7/$B$3*B7 -> 96991.95
A8: 44896 | B8: =VLOOKUP(A8,'INCC - M'!$A:$F,2,FALSE) -> 1051.249 | C8: =B8 -> 1051.249 | D8: 147746.59 | E8: =D8 -> 147746.59 | F8: =E8-D8 -> 0 | H8: 0.0073798258 | J8: =H8*$E$3 -> 56394.557 | L8: =H8*($D$3/$B$3*B8) -> 58818.96 | N8: =D8/$B$3*B8 -> 160618.38
A9: 44927 | B9: =VLOOKUP(A9,'INCC - M'!$A:$F,2,FALSE) -> 1054.561 | C9: =B9 -> 1054.561 | D9: 129512.84 | E9: =D9 -> 129512.84 | F9: =E9-D9 -> 0 | H9: 0.0085197165 | J9: =H9*$E$3 -> 65105.282 | L9: =H9*($D$3/$B$3*B9) -> 68118.093 | N9: =D9/$B$3*B9 -> 141239.68
A10: 44958 | B10: =VLOOKUP(A10,'INCC - M'!$A:$F,2,FALSE) -> 1056.775 | C10: =B10 -> 1056.775 | D10: 148727.02 | E10: =D10 -> 148727.02 | F10: =E10-D10 -> 0 | H10: 0.0080329958 | J10: =H10*$E$3 -> 61385.899 | L10: =H10*($D$3/$B$3*B10) -> 64361.433 | N10: =D10/$B$3*B10 -> 162534.14
A11: 44986 | B11: =VLOOKUP(A11,'INCC - M'!$A:$F,2,FALSE) -> 1058.65 | C11: =B11 -> 1058.65 | D11: 161939.65 | E11: =D11 -> 161939.65 | F11: =E11-D11 -> 0 | H11: 0.012312466 | J11: =H11*$E$3 -> 94088.405 | L11: =H11*($D$3/$B$3*B11) -> 98824.145 | N11: =D11/$B$3*B11 -> 177287.36
A12: 45017 | B12: =VLOOKUP(A12,'INCC - M'!$A:$F,2,FALSE) -> 1061.071 | C12: =B12 -> 1061.071 | D12: 223185.61 | E12: 227086.8 | F12: =E12-D12 -> 3901.1919 | H12: 0.015471498 | J12: =H12*$E$3 -> 118228.84 | L12: =H12*($D$3/$B$3*B12) -> 124463.62 | N12: =D12/$B$3*B12 -> 244896.63
A13: 45047 | B13: =VLOOKUP(A13,'INCC - M'!$A:$F,2,FALSE) -> 1065.289 | C13: =B12 -> 1061.071 | D13: 257916.98 | E13: =D13*C13/$C$8 -> 260326.74 | F13: =E13-D13 -> 2409.7626 | H13: 0.010770974 | J13: =H13*$E$3 -> 82308.76 | L13: =H13*($D$3/$B$3*B13) -> 86993.751 | N13: =D13/$B$3*B13 -> 284131.61
A14: 45078 | B14: =VLOOKUP(A14,'INCC - M'!$A:$F,2,FALSE) -> 1074.292 | C14: =B13 -> 1065.289 | D14: 296628.61 | E14: =D14*C14/$C$8 -> 300590.25 | F14: =E14-D14 -> 3961.6358 | H14: 0.0099065106 | J14: =H14*$E$3 -> 75702.773 | L14: =H14*($D$3/$B$3*B14) -> 80687.951 | N14: =D14/$B$3*B14 -> 329539.56
A15: 45108 | B15: =VLOOKUP(A15,'INCC - M'!$A:$F,2,FALSE) -> 1074.895 | C15: =B14 -> 1074.292 | D15: 312081.02 | E15: =D15*C15/$C$8 -> 318921.73 | F15: =E15-D15 -> 6840.7038 | H15: 0.0084854621 | J15: =H15*$E$3 -> 64843.519 | L15: =H15*($D$3/$B$3*B15) -> 69152.387 | N15: =D15/$B$3*B15 -> 346901.02
A16: 45139 | B16: =VLOOKUP(A16,'INCC - M'!$A:$F,2,FALSE) -> 1077.497 | C16: =B15 -> 1074.895 | D16: 343287.26 | E16: =D16*C16/$C$8 -> 351008.9 | F16: =E16-D16 -> 7721.644 | H16: 0.021512494 | J16: =H16*$E$3 -> 164392.44 | L16: =H16*($D$3/$B$3*B16) -> 175740.74 | N16: =D16/$B$3*B16 -> 382512.77
A17: 45170 | B17: =VLOOKUP(A17,'INCC - M'!$A:$F,2,FALSE) -> 1080.071 | C17: =B16 -> 1077.497 | D17: 366781.74 | E17: =D17*C17/$C$8 -> 375939.69 | F17: =E17-D17 -> 9157.9513 | H17: 0.024633893 | J17: =H17*$E$3 -> 188245.29 | L17: =H17*($D$3/$B$3*B17) -> 201720.94 | N17: =D17/$B$3*B17 -> 409668.14
A18: 45200 | B18: =VLOOKUP(A18,'INCC - M'!$A:$F,2,FALSE) -> 1082.251 | C18: =B17 -> 1080.071 | D18: 372798.23 | E18: =D18*C18/$C$8 -> 383019.2 | F18: =E18-D18 -> 10220.976 | H18: 0.013053823 | J18: =H18*$E$3 -> 99753.649 | L18: =H18*($D$3/$B$3*B18) -> 107110.33 | N18: =D18/$B$3*B18 -> 417228.54
A19: 45231 | B19: =VLOOKUP(A19,'INCC - M'!$A:$F,2,FALSE) -> 1083.335 | C19: =B18 -> 1082.251 | D19: 411937.07 | E19: =D19*C19/$C$8 -> 424085.36 | F19: =E19-D19 -> 12148.286 | H19: 0.029865195 | J19: =H19*$E$3 -> 228221.44 | L19: =H19*($D$3/$B$3*B19) -> 245297.86 | N19: =D19/$B$3*B19 -> 461493.76
A20: 45261 | B20: =VLOOKUP(A20,'INCC - M'!$A:$F,2,FALSE) -> 1086.15 | C20: =B19 -> 1083.335 | D20: 319127.78 | E20: =D20*C20/$C$8 -> 328868.13 | F20: =E20-D20 -> 9740.3506 | H20: 0.012921887 | J20: =H20*$E$3 -> 98745.431 | L20: =H20*($D$3/$B$3*B20) -> 106409.74 | N20: =D20/$B$3*B20 -> 358448.36
A21: 45292 | B21: =VLOOKUP(A21,'INCC - M'!$A:$F,2,FALSE) -> 1088.663 | C21: =B20 -> 1086.15 | D21: 329319.16 | E21: =D21*C21/$C$8 -> 340252.41 | F21: =E21-D21 -> 10933.25 | H21: 0.021730405 | J21: =H21*$E$3 -> 166057.66 | L21: =H21*($D$3/$B$3*B21) -> 179360.55 | N21: =D21/$B$3*B21 -> 370751.27
A22: 45323 | B22: =VLOOKUP(A22,'INCC - M'!$A:$F,2,FALSE) -> 1090.871 | C22: =B21 -> 1088.663 | D22: 247621.21 | E22: =D22*C22/$C$8 -> 256434.06 | F22: =E22-D22 -> 8812.8503 | H22: 0.013752884 | J22: =H22*$E$3 -> 105095.68 | L22: =H22*($D$3/$B$3*B22) -> 113745.13 | N22: =D22/$B$3*B22 -> 279340.19
A23: 45352 | B23: =VLOOKUP(A23,'INCC - M'!$A:$F,2,FALSE) -> 1093.503 | C23: =B22 -> 1090.871 | D23: 250855.25 | E23: =D23*C23/$C$8 -> 260310.09 | F23: =E23-D23 -> 9454.836 | H23: 0.021040653 | J23: =H23*$E$3 -> 160786.76 | L23: =H23*($D$3/$B$3*B23) -> 174439.5 | N23: =D23/$B$3*B23 -> 283671.27
A24: 45383 | B24: =VLOOKUP(A24,'INCC - M'!$A:$F,2,FALSE) -> 1097.991 | C24: =B23 -> 1093.503 | D24: 267410.12 | E24: =D24*C24/$C$8 -> 278158.43 | F24: =E24-D24 -> 10748.307 | H24: 0.028439779 | J24: =H24*$E$3 -> 217328.81 | L24: =H24*($D$3/$B$3*B24) -> 236750.35 | N24: =D24/$B$3*B24 -> 303632.88
A25: 45413 | B25: =VLOOKUP(A25,'INCC - M'!$A:$F,2,FALSE) -> 1104.457 | C25: =B24 -> 1097.991 | D25: 190388.13 | E25: =D25*C25/$C$8 -> 198853.41 | F25: =E25-D25 -> 8465.2845 | H25: 0.029307636 | J25: =H25*$E$3 -> 223960.73 | L25: =H25*($D$3/$B$3*B25) -> 245411.69 | N25: =D25/$B$3*B25 -> 217450.72
A26: 45444 | B26: =VLOOKUP(A26,'INCC - M'!$A:$F,2,FALSE) -> 1114.748 | C26: =B25 -> 1104.457 | D26: 169808.69 | E26: =D26*C26/$C$8 -> 178403.41 | F26: =E26-D26 -> 8594.7107 | G26: Cancelado! | H26: 0.033383993 | I26: 0.037166297 | J26: =I26*$E$3 -> 284014.41 | L26: =H26*($D$3/$B$3*B26) -> 282150.37 | N26: =D26/$B$3*B26 -> 195753.17
A27: 45474 | B27: =VLOOKUP(A27,'INCC - M'!$A:$F,2,FALSE) -> 1122.452 | C27: =B26 -> 1114.748 | D27: 224047.11 | E27: =D27*C27/$C$8 -> 237580.32 | F27: =E27-D27 -> 13533.204 | G27: Sem taxa até Dez | H27: 0.04164172 | I27: 0.052295198 | J27: =I27*$E$3 -> 399625.22 | L27: =H27*($D$3/$B$3*B27) -> 354374.18 | N27: =D27/$B$3*B27 -> 260063.44
A28: 45505 | B28: =VLOOKUP(A28,'INCC - M'!$A:$F,2,FALSE) -> 1129.639 | C28: =B27 -> 1122.452 | D28: 256507.96 | E28: =D28*C28/$C$8 -> 273881.7 | F28: =E28-D28 -> 17373.749 | H28: 0.041077048 | I28: 0.04890592 | J28: =H28*$E$3 -> 313899.27 | L28: =H28*($D$3/$B$3*B28) -> 351807.05 | N28: =D28/$B$3*B28 -> 299648.91
A29: 45536 | B29: =VLOOKUP(A29,'INCC - M'!$A:$F,2,FALSE) -> 1136.521 | C29: =B28 -> 1129.639 | D29: 241350.52 | E29: =D29*C29/$C$8 -> 259347.65 | F29: =E29-D29 -> 17997.132 | I29: 0.038817537 | J29: =I29*$E$3 -> 296632.72 | N29: =D29/$B$3*B29 -> 283659.85
A30: 45566 | B30: =VLOOKUP(A30,'INCC - M'!$A:$F,2,FALSE) -> 1144.136 | C30: =B29 -> 1136.521 | D30: 249851.59 | E30: =D30*C30/$C$8 -> 270118.29 | F30: =E30-D30 -> 20266.697 | I30: 0.041396476 | J30: =I30*$E$3 -> 316340.25 | N30: =D30/$B$3*B30 -> 295618.73
A31: 45597 | B31: =VLOOKUP(A31,'INCC - M'!$A:$F,2,FALSE) -> 1149.158 | C31: =B30 -> 1144.136 | D31: 259759.9 | E31: =D31*C31/$C$8 -> 282711.95 | F31: =E31-D31 -> 22952.048 | I31: 0.044847063 | J31: =I31*$E$3 -> 342708.67 | N31: =D31/$B$3*B31 -> 308691.05
A32: 45627 | B32: =VLOOKUP(A32,'INCC - M'!$A:$F,2,FALSE) -> 1154.99 | C32: =B31 -> 1149.158 | D32: 264381.13 | E32: =D32*C32/$C$8 -> 289004.5 | F32: =E32-D32 -> 24623.369 | I32: 0.056331292 | J32: =I32*$E$3 -> 430467.92 | N32: =D32/$B$3*B32 -> 315777.27
A33: 45658 | B33: =VLOOKUP(A33,'INCC - M'!$A:$F,2,FALSE) -> 1163.221 | C33: =B32 -> 1154.99 | D33: 213673.75 | E33: =D33*C33/$C$8 -> 234759.84 | F33: =E33-D33 -> 21086.088 | I33: 0.056519556 | J33: =I33*$E$3 -> 431906.58 | N33: =D33/$B$3*B33 -> 257031.05
A34: 45689 | B34: =VLOOKUP(A34,'INCC - M'!$A:$F,2,FALSE) -> 1169.156 | C34: =B33 -> 1163.221 | D34: 176375.67 | E34: =D34*C34/$C$8 -> 195162.03 | F34: =E34-D34 -> 18786.355 | I34: 0.042605775 | J34: =I34*$E$3 -> 325581.37 | N34: =D34/$B$3*B34 -> 213247.19
A35: 45717 | B35: =VLOOKUP(A35,'INCC - M'!$A:$F,2,FALSE) -> 1173.586 | C35: =B34 -> 1169.156 | D35: 169421.79 | E35: =D35*C35/$C$8 -> 188423.97 | F35: =E35-D35 -> 19002.173 | I35: 0.040769748 | J35: =I35*$E$3 -> 311550.97 | N35: =D35/$B$3*B35 -> 205615.75
A36: 45748 | B36: =VLOOKUP(A36,'INCC - M'!$A:$F,2,FALSE) -> 1180.564 | C36: =B35 -> 1173.586 | D36: 75228.334 | E36: =D36*C36/$C$8 -> 83982.881 | F36: =E36-D36 -> 8754.5469 | I36: 0.037946793 | J36: =I36*$E$3 -> 289978.74 | N36: =D36/$B$3*B36 -> 91842.386
A37: 45778 | B37: =VLOOKUP(A37,'INCC - M'!$A:$F,2,FALSE) -> 1183.606 | C37: =B36 -> 1180.564 | D37: 22125.981 | E37: =D37*C37/$C$8 -> 24847.715 | F37: =E37-D37 -> 2721.735 | I37: 0.047020131 | J37: =I37*$E$3 -> 359314.64 | N37: =D37/$B$3*B37 -> 27082.07
A38: 45809 | B38: =VLOOKUP(A38,'INCC - M'!$A:$F,2,FALSE) -> 1194.912 | C38: =B37 -> 1183.606 | I38: 0.045399231 | J38: =I38*$E$3 -> 346928.18
A39: 45839 | B39: =VLOOKUP(A39,'INCC - M'!$A:$F,2,FALSE) -> 1205.838 | C39: =B38 -> 1194.912 | I39: 0.044747319 | J39: =I39*$E$3 -> 341946.45
A40: 45870 | B40: =VLOOKUP(A40,'INCC - M'!$A:$F,2,FALSE) -> 1214.239 | C40: =B39 -> 1205.838 | I40: 0.01724061 | J40: =I40*$E$3 -> 131747.9
A41: 45901 | B41: =VLOOKUP(A41,'INCC - M'!$A:$F,2,FALSE) -> 1216.825 | C41: =B40 -> 1214.239 | I41: 0.0085979439 | J41: =I41*$E$3 -> 65703.073
A42: 45931 | B42: =VLOOKUP(A42,'INCC - M'!$A:$F,2,FALSE) -> 1219.407 | C42: =B41 -> 1216.825 | I42: 0.004666734 | J42: =I42*$E$3 -> 35661.871
A43: 45962 | B43: =VLOOKUP(A43,'INCC - M'!$A:$F,2,FALSE) -> 1222.865 | C43: =B42 -> 1219.407 | I43: 0.0032688574 | J43: =I43*$E$3 -> 24979.691

Sheet Reserva Amati
A1: Reserva Amati | F1: saldo | G1: =G3-D3 -> 630937.27 | H1: =G3-I3 -> 630937.27
A2: Data Base | B2: INCC Base | C2: Valor Orçado | D2: Valor da Taxa (Reaj) | G2: Valor Previsto Total | I2: Valor Cobrado
A3: 45474 | B3: 1126.916 | C3: =1073123.83+K22 -> 1049637 | D3: =SUM(D5:D25) -> 533383.22 | G3: =SUM(G5:G25) -> 1164320.5 | I3: =SUM(I5:I25) -> 533383.22 | J3: =D3-I3 -> 0 | K3: Aditivos Incorporação | L3: Data | M3: Descrição
A4: Mês | B4: INCC DI (n-1) | C4: Medição | D4: Valor da Taxa (Reaj) | F4: Medição Prevista | G4: Valor Previsto | I4: Valor Cobrado | K4: -23842.3 | L4: 46107 | M4: Distrato dos muros referente ao reaproveitamento do muro existente na obraADITIVO
A5: 45839 | B5: =VLOOKUP(A5,'INCC - DI'!$E:$F,2,FALSE) -> 1199.509 | C5: 0.022100372 | D5: =(C5*$C$3)*B5/$B$3 -> 24691.682 | F5: 0.022100372 | G5: =F5*($C$3/$B$3*B5) -> 24691.682 | I5: 25212.525 | K5: 355.45 | L5: 46098 | M5: Necessidade de aprovação de aditivo devido a divergências entre os revestimentos utilizados para a execução do orçamento e os revestimentos descritos no projeto executivo que temos em obraADITIVO
A6: =EDATE(A5,1) -> 45870 | B6: =VLOOKUP(A6,'INCC - DI'!$E:$F,2,FALSE) -> 1210.471 | C6: 0.058375728 | D6: =(C6*$C$3)*B6/$B$3 -> 65816.423 | F6: 0.058375728 | G6: =F6*($C$3/$B$3*B6) -> 65816.423 | I6: 67204.745
A7: =EDATE(A6,1) -> 45901 | B7: =VLOOKUP(A7,'INCC - DI'!$E:$F,2,FALSE) -> 1216.706 | C7: 0.070445936 | D7: =(C7*$C$3)*B7/$B$3 -> 79834.236 | F7: 0.070445936 | G7: =F7*($C$3/$B$3*B7) -> 79834.236 | I7: 81518.248
A8: =EDATE(A7,1) -> 45931 | B8: =VLOOKUP(A8,'INCC - DI'!$E:$F,2,FALSE) -> 1218.747 | C8: 0.046982354 | D8: =(C8*$C$3)*B8/$B$3 -> 53332.987 | F8: 0.046982354 | G8: =F8*($C$3/$B$3*B8) -> 53332.987 | I8: 54457.985
A9: =EDATE(A8,1) -> 45962 | B9: =VLOOKUP(A9,'INCC - DI'!$E:$F,2,FALSE) -> 1222.356 | C9: 0.03942982 | D9: =(C9*$C$3)*B9/$B$3 -> 44892.117 | F9: 0.039429823 | G9: =F9*($C$3/$B$3*B9) -> 44892.119 | I9: 45839.064
A10: =EDATE(A9,1) -> 45992 | B10: =VLOOKUP(A10,'INCC - DI'!$E:$F,2,FALSE) -> 1225.633 | C10: 0.026394828 | D10: =(C10*$C$3)*B10/$B$3 -> 30131.923 | F10: 0.026394825 | G10: =F10*($C$3/$B$3*B10) -> 30131.921 | I10: 30767.522
A11: =EDATE(A10,1) -> 46023 | B11: =VLOOKUP(A11,'INCC - DI'!$E:$F,2,FALSE) -> 1228.161 | C11: 0.050539382 | D11: =(C11*$C$3)*B11/$B$3 -> 57813.972 | F11: 0.050539387 | G11: =F11*($C$3/$B$3*B11) -> 57813.978 | I11: 59033.492
A12: =EDATE(A11,1) -> 46054 | B12: =VLOOKUP(A12,'INCC - DI'!$E:$F,2,FALSE) -> 1237.036 | C12: 0.03659317 | D12: =(C12*$C$3)*B12/$B$3 -> 42162.849 | F12: 0.036593169 | G12: =F12*($C$3/$B$3*B12) -> 42162.848 | I12: 43563.452
A13: =EDATE(A12,1) -> 46082 | B13: =VLOOKUP(A13,'INCC - DI'!$E:$F,2,FALSE) -> 1240.481 | C13: 0.0438085 | D13: =(C13*$C$3)*B13/$B$3 -> 50616.962 | F13: 0.043808492 | G13: =F13*($C$3/$B$3*B13) -> 50616.953 | I13: 41696.118
A14: =EDATE(A13,1) -> 46113 | B14: =VLOOKUP(A14,'INCC - DI'!$E:$F,2,FALSE) -> 1247.181 | C14: 0.020674775 | D14: =(C14*$C$3)*B14/$B$3 -> 24016.951 | F14: 0.020674775 | G14: =F14*($C$3/$B$3*B14) -> 24016.951 | I14: 24016.951
A15: =EDATE(A14,1) -> 46143 | B15: =VLOOKUP(A15,'INCC - DI'!$E:$F,2,FALSE) -> 1259.652 | C15: 0.019178865 | D15: =(C15*$C$3)*B15/$B$3 -> 22501.996 | F15: 0.019178872 | G15: =F15*($C$3/$B$3*B15) -> 22502.005 | I15: 22279.219
A16: =EDATE(A15,1) -> 46174 | B16: =VLOOKUP(A16,'INCC - DI'!$E:$F,2,FALSE) -> 1270.695 | C16: 0.03174426 | D16: =(C16*$C$3)*B16/$B$3 -> 37571.117 | F16: 0.018850104 | G16: =F16*($C$3/$B$3*B16) -> 22310.158 | I16: 37793.895
A17: =EDATE(A16,1) -> 46204 | B17: =VLOOKUP(A17,'INCC - DI'!$E:$F,2,FALSE) -> 1270.695 | D17: =(C17*$C$3)*B17/$B$3 -> 0 | F17: 0.043051372 | G17: =F17*($C$3/$B$3*B17) -> 50953.72 | H17: =(F17*$G$1/(SUM($F$17:$F$26))) -> 49691.786
A18: =EDATE(A17,1) -> 46235 | B18: =VLOOKUP(A18,'INCC - DI'!$E:$F,2,FALSE) -> 1270.695 | D18: =(C18*$C$3)*B18/$B$3 -> 0 | F18: 0.046649778 | G18: =F18*($C$3/$B$3*B18) -> 55212.636 | H18: =(F18*$G$1/(SUM($F$17:$F$26))) -> 53845.225
A19: =EDATE(A18,1) -> 46266 | B19: =VLOOKUP(A19,'INCC - DI'!$E:$F,2,FALSE) -> 1270.695 | D19: =(C19*$C$3)*B19/$B$3 -> 0 | F19: 0.091938795 | G19: =F19*($C$3/$B$3*B19) -> 108814.73 | H19: =(F19*$G$1/(SUM($F$17:$F$26))) -> 106119.8
A20: =EDATE(A19,1) -> 46296 | B20: =VLOOKUP(A20,'INCC - DI'!$E:$F,2,FALSE) -> 1270.695 | D20: =(C20*$C$3)*B20/$B$3 -> 0 | F20: 0.065840295 | G20: =F20*($C$3/$B$3*B20) -> 77925.691 | H20: =(F20*$G$1/(SUM($F$17:$F$26))) -> 75995.763
A21: =EDATE(A20,1) -> 46327 | B21: =VLOOKUP(A21,'INCC - DI'!$E:$F,2,FALSE) -> 1270.695 | D21: =(C21*$C$3)*B21/$B$3 -> 0 | F21: 0.13256908 | G21: =F21*($C$3/$B$3*B21) -> 156902.96 | H21: =(F21*$G$1/(SUM($F$17:$F$26))) -> 153017.06
A22: =EDATE(A21,1) -> 46357 | B22: =VLOOKUP(A22,'INCC - DI'!$E:$F,2,FALSE) -> 1270.695 | D22: =(C22*$C$3)*B22/$B$3 -> 0 | F22: 0.083134747 | G22: =F22*($C$3/$B$3*B22) -> 98394.648 | H22: =(F22*$G$1/(SUM($F$17:$F$26))) -> 95957.78 | K22: =SUM(K4:K21) -> -23486.85
A23: =EDATE(A22,1) -> 46388 | B23: =VLOOKUP(A23,'INCC - DI'!$E:$F,2,FALSE) -> 1270.695 | D23: =(C23*$C$3)*B23/$B$3 -> 0 | F23: 0.081339351 | G23: =F23*($C$3/$B$3*B23) -> 96269.697 | H23: =(F23*$G$1/(SUM($F$17:$F$26))) -> 93885.456
A24: =EDATE(A23,1) -> 46419 | B24: =VLOOKUP(A24,'INCC - DI'!$E:$F,2,FALSE) -> 1270.695 | D24: =(C24*$C$3)*B24/$B$3 -> 0 | F24: 0.00067755649 | G24: =F24*($C$3/$B$3*B24) -> 801.92622 | H24: =(F24*$G$1/(SUM($F$17:$F$26))) -> 782.0655
A25: =EDATE(A24,1) -> 46447 | B25: =VLOOKUP(A25,'INCC - DI'!$E:$F,2,FALSE) -> 1270.695 | D25: =(C25*$C$3)*B25/$B$3 -> 0 | F25: 0.00077918997 | G25: =F25*($C$3/$B$3*B25) -> 922.21515 | H25: =(F25*$G$1/(SUM($F$17:$F$26))) -> 899.37532
A26: =EDATE(A25,1) -> 46478 | B26: =VLOOKUP(A26,'INCC - DI'!$E:$F,2,FALSE) -> 1270.695 | D26: =(C26*$C$3)*B26/$B$3 -> 0 | F26: 0.00064367867 | G26: =F26*($C$3/$B$3*B26) -> 761.82991 | H26: =(F26*$G$1/(SUM($F$17:$F$26))) -> 742.96222
C28: =SUM(C5:C27) -> 0.46626799
C29: 0.46626799
C30: =C29-C28 -> 0

Sheet PDV Alberi
A1: PDV Alberi
B2: Valor Gasto (GRD) | C2: Valor Cobrado | D2: Valor Taxa
B3: =SUM(B5:B7) -> 2575410.2 | C3: =SUM(C5:C7) -> 206032.82 | D3: 174517.25
A4: Mês | B4: Valor Gasto (GRD) | C4: Valor Cobrado | D4: Valor Taxa
A5: 45839 | B5: 2023811.1 | C5: =B5*0.08 -> 161904.89 | D5: =D3-C5 -> 12612.363
A6: 45870 | B6: 551599.14 | C6: =B6*0.08 -> 44127.931 | D6: =C6*0.1 -> 4412.7931
A7: 45901 | C7: =B7*0.08 -> 0 | D7: =C7*0.1 -> 0

Sheet Alberi
A1: Alberi | F1: saldo | G1: =G3-D3 -> 8019623.5 | H1: =G3-I3 -> 8019623.5
A2: Data Base | B2: INCC Base | C2: Valor Orçado | D2: Valor da Taxa (Reaj) | G2: Valor Previsto Total | I2: Valor Cobrado
A3: 45748 | B3: 1184.462 | C3: 8089512 | D3: =SUM(D5:D48) -> 644802.97 | G3: =SUM(G5:G48) -> 8664426.5 | I3: =SUM(I5:I48) -> 644802.97 | J3: =D3-I3 -> 0
A4: Mês | B4: INCC DI (n-1) | C4: Medição | D4: Valor da Taxa (Reaj) | F4: Medição Prevista | G4: Valor Previsto | I4: Valor Cobrado
A5: 46082 | B5: =VLOOKUP(A5,'INCC - DI'!$E:$F,2,FALSE) -> 1240.481 | C5: 0.01541031 | D5: =(C5*$C$3)*B5/$B$3 -> 130557.76 | F5: 0.014365597 | G5: =F5*($C$3/$B$3*B5) -> 121706.84 | I5: 130557.76
A6: =EDATE(A5,1) -> 46113 | B6: =VLOOKUP(A6,'INCC - DI'!$E:$F,2,FALSE) -> 1247.181 | C6: 0.0170838 | D6: =(C6*$C$3)*B6/$B$3 -> 145517.48 | F6: 0.018817238 | G6: =F6*($C$3/$B$3*B6) -> 160282.66 | I6: 145517.48
A7: =EDATE(A6,1) -> 46143 | B7: =VLOOKUP(A7,'INCC - DI'!$E:$F,2,FALSE) -> 1259.652 | C7: 0.02510589 | D7: =(C7*$C$3)*B7/$B$3 -> 215986.89 | F7: 0.016219251 | G7: =F7*($C$3/$B$3*B7) -> 139534.81 | I7: 213848.55
A8: =EDATE(A7,1) -> 46174 | B8: =VLOOKUP(A8,'INCC - DI'!$E:$F,2,FALSE) -> 1270.695 | C8: 0.0176 | D8: =(C8*$C$3)*B8/$B$3 -> 152740.84 | F8: 0.021967511 | G8: =F8*($C$3/$B$3*B8) -> 190644.1 | I8: 154879.19
A9: =EDATE(A8,1) -> 46204 | B9: =VLOOKUP(A9,'INCC - DI'!$E:$F,2,FALSE) -> 1270.695 | D9: =(C9*$C$3)*B9/$B$3 -> 0 | F9: 0.025320307 | G9: =F9*($C$3/$B$3*B9) -> 219741.2 | H9: =(F9*$G$1/(SUM($F$9:$F$49))) -> 218665.07
A10: =EDATE(A9,1) -> 46235 | B10: =VLOOKUP(A10,'INCC - DI'!$E:$F,2,FALSE) -> 1270.695 | D10: =(C10*$C$3)*B10/$B$3 -> 0 | F10: 0.022515032 | G10: =F10*($C$3/$B$3*B10) -> 195395.74 | H10: =(F10*$G$1/(SUM($F$9:$F$49))) -> 194438.84
A11: =EDATE(A10,1) -> 46266 | B11: =VLOOKUP(A11,'INCC - DI'!$E:$F,2,FALSE) -> 1270.695 | D11: =(C11*$C$3)*B11/$B$3 -> 0 | F11: 0.024630281 | G11: =F11*($C$3/$B$3*B11) -> 213752.84 | H11: =(F11*$G$1/(SUM($F$9:$F$49))) -> 212706.04
A12: =EDATE(A11,1) -> 46296 | B12: =VLOOKUP(A12,'INCC - DI'!$E:$F,2,FALSE) -> 1270.695 | D12: =(C12*$C$3)*B12/$B$3 -> 0 | F12: 0.023348669 | G12: =F12*($C$3/$B$3*B12) -> 202630.42 | H12: =(F12*$G$1/(SUM($F$9:$F$49))) -> 201638.09
A13: =EDATE(A12,1) -> 46327 | B13: =VLOOKUP(A13,'INCC - DI'!$E:$F,2,FALSE) -> 1270.695 | D13: =(C13*$C$3)*B13/$B$3 -> 0 | F13: 0.029355337 | G13: =F13*($C$3/$B$3*B13) -> 254759.03 | H13: =(F13*$G$1/(SUM($F$9:$F$49))) -> 253511.41
A14: =EDATE(A13,1) -> 46357 | B14: =VLOOKUP(A14,'INCC - DI'!$E:$F,2,FALSE) -> 1270.695 | D14: =(C14*$C$3)*B14/$B$3 -> 0 | F14: 0.021156096 | G14: =F14*($C$3/$B$3*B14) -> 183602.27 | H14: =(F14*$G$1/(SUM($F$9:$F$49))) -> 182703.12
A15: =EDATE(A14,1) -> 46388 | B15: =VLOOKUP(A15,'INCC - DI'!$E:$F,2,FALSE) -> 1270.695 | D15: =(C15*$C$3)*B15/$B$3 -> 0 | F15: 0.031869166 | G15: =F15*($C$3/$B$3*B15) -> 276575.19 | H15: =(F15*$G$1/(SUM($F$9:$F$49))) -> 275220.73
A16: =EDATE(A15,1) -> 46419 | B16: =VLOOKUP(A16,'INCC - DI'!$E:$F,2,FALSE) -> 1270.695 | D16: =(C16*$C$3)*B16/$B$3 -> 0 | F16: 0.030129728 | G16: =F16*($C$3/$B$3*B16) -> 261479.55 | H16: =(F16*$G$1/(SUM($F$9:$F$49))) -> 260199.02
A17: =EDATE(A16,1) -> 46447 | B17: =VLOOKUP(A17,'INCC - DI'!$E:$F,2,FALSE) -> 1270.695 | D17: =(C17*$C$3)*B17/$B$3 -> 0 | F17: 0.043138415 | G17: =F17*($C$3/$B$3*B17) -> 374374.88 | H17: =(F17*$G$1/(SUM($F$9:$F$49))) -> 372541.47
A18: =EDATE(A17,1) -> 46478 | B18: =VLOOKUP(A18,'INCC - DI'!$E:$F,2,FALSE) -> 1270.695 | D18: =(C18*$C$3)*B18/$B$3 -> 0 | F18: 0.040112449 | G18: =F18*($C$3/$B$3*B18) -> 348114.16 | H18: =(F18*$G$1/(SUM($F$9:$F$49))) -> 346409.36
A19: =EDATE(A18,1) -> 46508 | B19: =VLOOKUP(A19,'INCC - DI'!$E:$F,2,FALSE) -> 1270.695 | D19: =(C19*$C$3)*B19/$B$3 -> 0 | F19: 0.04450885 | G19: =F19*($C$3/$B$3*B19) -> 386268.14 | H19: =(F19*$G$1/(SUM($F$9:$F$49))) -> 384376.49
A20: =EDATE(A19,1) -> 46539 | B20: =VLOOKUP(A20,'INCC - DI'!$E:$F,2,FALSE) -> 1270.695 | D20: =(C20*$C$3)*B20/$B$3 -> 0 | F20: 0.049597224 | G20: =F20*($C$3/$B$3*B20) -> 430427.37 | H20: =(F20*$G$1/(SUM($F$9:$F$49))) -> 428319.46
... A49: =EDATE(A48,1) -> 47423 | B49: =VLOOKUP(A49,'INCC - DI'!$E:$F,2,FALSE) -> 1270.695 | D49: =(C49*$C$3)*B49/$B$3 -> 0 | F49: 0.00078733055 | G49: =F49*($C$3/$B$3*B49) -> 6832.8143 | H49: =(F49*$G$1/(SUM($F$9:$F$49))) -> 6799.3524
C50: =SUM(C5:C48) -> 0.0752
C51: 0.0752
C52: =C51-C50 -> 0

Sheet Hall Design
A1: Hall Design | H1: PERMUTA | J1: Mudar
A2: Data Base | B2: INCC Base | C2: Valor Gasto (GRD) | D2: Valor da Taxa (Reaj) | E2: Caução | F2: Permuta | G2: Valor Líquido | H2: % | J2: 30164467 | K2: =J2*0.1 -> 3016446.7 | L2: =K2-D3 -> -101031.7 | M2: =K2-D3 -> -101031.7
A3: 45139 | B3: =VLOOKUP(A3,'INCC - DI'!$H:$I,2,FALSE) -> 1075.54 | C3: =SUM(C5:C38) -> 31174784 | D3: =SUM(D5:D38) -> 3117478.4 | E3: =SUM(E5:E38) -> 311747.84 | F3: =SUM(F5:F38) -> 906298.27 | G3: =SUM(G5:G38) -> 1899432.3 | H3: 0.2997 | J3: =G3/D3 -> 0.60928482 | K3: =K2-D3 -> -101031.7 | L3: =L2*J3 -> -61557.083
A4: Mês | B4: INCC DI (n-2) | C4: Valor Gasto (GRD) | D4: Valor da Taxa (Reaj) | E4: Caução | F4: Permuta | G4: Valor Líquido
A5: 45170 | B5: =VLOOKUP(A5,'INCC - DI'!$H:$I,2,FALSE) -> 1076.626 | C5: 301307.75 | D5: =C5*0.1 -> 30130.775 | E5: =D5*0.1 -> 3013.0775 | F5: =D5*$H$3 -> 9030.1933 | G5: =D5-E5-F5 -> 18087.504
A6: 45200 | B6: =VLOOKUP(A6,'INCC - DI'!$H:$I,2,FALSE) -> 1078.412 | C6: 385589.61 | D6: =C6*0.1 -> 38558.961 | E6: =D6*0.1 -> 3855.8961 | F6: =D6*$H$3 -> 11556.121 | G6: =D6-E6-F6 -> 23146.944 | J6: =J2-C3 -> -1010317
A7: 45231 | B7: =VLOOKUP(A7,'INCC - DI'!$H:$I,2,FALSE) -> 1082.104 | C7: 774859.78 | D7: =C7*0.1 -> 77485.978 | E7: =D7*0.1 -> 7748.5978 | F7: =D7*$H$3 -> 23222.548 | G7: =D7-E7-F7 -> 46514.833 | L7: =L3/2 -> -30778.541
A8: 45261 | B8: =VLOOKUP(A8,'INCC - DI'!$H:$I,2,FALSE) -> 1084.242 | C8: 241785.72 | D8: =C8*0.1 -> 24178.572 | E8: =D8*0.1 -> 2417.8572 | F8: =D8*$H$3 -> 7246.318 | G8: =D8-E8-F8 -> 14514.397
A9: 45292 | B9: =VLOOKUP(A9,'INCC - DI'!$H:$I,2,FALSE) -> 1084.986 | C9: 621085.62 | D9: =C9*0.1 -> 62108.562 | E9: =D9*0.1 -> 6210.8562 | F9: =D9*$H$3 -> 18613.936 | G9: =D9-E9-F9 -> 37283.77
A10: 45323 | B10: =VLOOKUP(A10,'INCC - DI'!$H:$I,2,FALSE) -> 1088.312 | C10: 371238.02 | D10: =C10*0.1 -> 37123.802 | E10: =D10*0.1 -> 3712.3802 | F10: =D10*$H$3 -> 11126.003 | G10: =D10-E10-F10 -> 22285.418 | I10: 0.079345158 | J10: 0.069226506 | K10: 0.0579143 | L10: 0.012238014
A11: 45352 | B11: =VLOOKUP(A11,'INCC - DI'!$H:$I,2,FALSE) -> 1091.25 | C11: 206662.42 | D11: =C11*0.1 -> 20666.242 | E11: =D11*0.1 -> 2066.6242 | F11: =D11*$H$3 -> 6193.6727 | G11: =D11-E11-F11 -> 12405.945
A12: 45383 | B12: =VLOOKUP(A12,'INCC - DI'!$H:$I,2,FALSE) -> 1092.685 | C12: 703323.95 | D12: =C12*0.1 -> 70332.395 | E12: =D12*0.1 -> 7033.2395 | F12: =D12*$H$3 -> 21078.619 | G12: =D12-E12-F12 -> 42220.537
A13: 45413 | B13: =VLOOKUP(A13,'INCC - DI'!$H:$I,2,FALSE) -> 1095.738 | C13: 467712.65 | D13: =C13*0.1 -> 46771.265 | E13: =D13*0.1 -> 4677.1265 | F13: =D13*$H$3 -> 14017.348 | G13: =D13-E13-F13 -> 28076.79
A14: 45444 | B14: =VLOOKUP(A14,'INCC - DI'!$H:$I,2,FALSE) -> 1101.389 | C14: 439239.28 | D14: =C14*0.1 -> 43923.928 | E14: =D14*0.1 -> 4392.3928 | F14: =D14*$H$3 -> 13164.001 | G14: =D14-E14-F14 -> 26367.534 | L14: =L2-L3 -> -39474.619
A15: 45474 | B15: =VLOOKUP(A15,'INCC - DI'!$H:$I,2,FALSE) -> 1110.887 | C15: 468343.31 | D15: =C15*0.1 -> 46834.331 | E15: =D15*0.1 -> 4683.4331 | F15: =D15*$H$3 -> 14036.249 | G15: =D15-E15-F15 -> 28114.649 | M15: =J10*($L$14/SUM($J$10:$P$10)) -> -19606.207 | N15: =K10*($L$14/SUM($J$10:$P$10)) -> -16402.384 | O15: =L10*($L$14/SUM($J$10:$P$10)) -> -3466.0283 | P15: =M10*($L$14/SUM($I$10:$P$10)) -> 0 | Q15: =N10*($L$14/SUM($I$10:$P$10)) -> 0 | R15: =O10*($L$14/SUM($I$10:$P$10)) -> 0 | S15: =P10*($L$14/SUM($I$10:$P$10)) -> 0 | T15: =Q10*($L$14/SUM($I$10:$P$10)) -> 0 | U15: =R10*($L$14/SUM($I$10:$P$10)) -> 0
A16: 45505 | B16: =VLOOKUP(A16,'INCC - DI'!$H:$I,2,FALSE) -> 1118.827 | C16: 786706.39 | D16: =C16*0.1 -> 78670.639 | E16: =D16*0.1 -> 7867.0639 | F16: =D16*$H$3 -> 23577.591 | G16: =D16-E16-F16 -> 47225.985
A17: 45536 | B17: =VLOOKUP(A17,'INCC - DI'!$H:$I,2,FALSE) -> 1126.916 | C17: 1037696.4 | D17: =C17*0.1 -> 103769.64 | E17: =D17*0.1 -> 10376.964 | F17: =D17*$H$3 -> 31099.762 | G17: =D17-E17-F17 -> 62292.916
A18: 45566 | B18: =VLOOKUP(A18,'INCC - DI'!$H:$I,2,FALSE) -> 1134.775 | C18: 877827.81 | D18: =C18*0.1 -> 87782.781 | E18: =D18*0.1 -> 8778.2781 | F18: =D18*$H$3 -> 26308.499 | G18: =D18-E18-F18 -> 52696.003
A19: 45597 | B19: =VLOOKUP(A19,'INCC - DI'!$H:$I,2,FALSE) -> 1141.398 | C19: 765687.33 | D19: =C19*0.1 -> 76568.733 | E19: =D19*0.1 -> 7656.8733 | F19: =D19*$H$3 -> 22947.649 | G19: =D19-E19-F19 -> 45964.21
A20: 45627 | B20: =VLOOKUP(A20,'INCC - DI'!$H:$I,2,FALSE) -> 1149.17 | C20: 1078375.7 | D20: =C20*0.1 -> 107837.57 | E20: =D20*0.1 -> 10783.757 | F20: =D20*$H$3 -> 32318.919 | G20: =D20-E20-F20 -> 64734.893
A21: 45658 | B21: =VLOOKUP(A21,'INCC - DI'!$H:$I,2,FALSE) -> 1153.725 | C21: 885961.03 | D21: =C21*0.1 -> 88596.103 | E21: =D21*0.1 -> 8859.6103 | F21: =D21*$H$3 -> 26552.252 | G21: =D21-E21-F21 -> 53184.241
A22: 45689 | B22: =VLOOKUP(A22,'INCC - DI'!$H:$I,2,FALSE) -> 1159.536 | C22: 1500265.2 | D22: =C22*0.1 -> 150026.52 | E22: =D22*0.1 -> 15002.652 | F22: =D22*$H$3 -> 44962.947 | G22: =D22-E22-F22 -> 90060.918
A23: 45717 | B23: =VLOOKUP(A23,'INCC - DI'!$H:$I,2,FALSE) -> 1169.116 | C23: 1791514 | D23: =C23*0.1 -> 179151.4 | E23: =D23*0.1 -> 17915.14 | F23: =D23*$H$3 -> 53691.673 | G23: =D23-E23-F23 -> 107544.58
A24: 45748 | B24: =VLOOKUP(A24,'INCC - DI'!$H:$I,2,FALSE) -> 1173.775 | C24: 1520454 | D24: =C24*0.1 -> 152045.4 | E24: =D24*0.1 -> 15204.54 | F24: =D24*$H$3 -> 45568.006 | G24: =D24-E24-F24 -> 91272.854
A25: 45778 | B25: =VLOOKUP(A25,'INCC - DI'!$H:$I,2,FALSE) -> 1178.386 | C25: 1673636.4 | D25: =C25*0.1 -> 167363.64 | E25: =D25*0.1 -> 16736.364 | F25: =D25*$H$3 -> 50158.884 | G25: =D25-E25-F25 -> 100468.39
A26: 45809 | B26: =VLOOKUP(A26,'INCC - DI'!$H:$I,2,FALSE) -> 1184.462 | C26: 1779707.5 | D26: =C26*0.1 -> 177970.75 | E26: =D26*0.1 -> 17797.075 | F26: =D26*$H$3 -> 53337.833 | G26: =D26-E26-F26 -> 106835.84
A27: 45839 | B27: =VLOOKUP(A27,'INCC - DI'!$H:$I,2,FALSE) -> 1191.327 | C27: 2100392.8 | D27: =C27*0.1 -> 210039.28 | E27: =D27*0.1 -> 21003.928 | F27: =D27*$H$3 -> 62948.773 | G27: =D27-E27-F27 -> 126086.58
A28: 45870 | B28: =VLOOKUP(A28,'INCC - DI'!$H:$I,2,FALSE) -> 1199.509 | C28: 1065288.8 | D28: =C28*0.1 -> 106528.88 | E28: =D28*0.1 -> 10652.888 | F28: =D28*$H$3 -> 31926.707 | G28: =D28-E28-F28 -> 63949.289
A29: 45901 | B29: =VLOOKUP(A29,'INCC - DI'!$H:$I,2,FALSE) -> 1210.471 | C29: 1406905.9 | D29: =C29*0.1 -> 140690.59 | E29: =D29*0.1 -> 14069.059 | F29: =D29*$H$3 -> 42164.969 | G29: =D29-E29-F29 -> 84456.56 | H29: COBRADO SOMENTE A PERMUTA
A30: 45931 | B30: =VLOOKUP(A30,'INCC - DI'!$H:$I,2,FALSE) -> 1216.706 | C30: 1912610.4 | D30: =C30*0.1 -> 191261.04 | E30: =D30*0.1 -> 19126.104 | F30: =D30*$H$3 -> 57320.932 | G30: =D30-E30-F30 -> 114814 | H30: COBRADO SOMENTE A PERMUTA
A31: 45962 | B31: =VLOOKUP(A31,'INCC - DI'!$H:$I,2,FALSE) -> 1218.747 | C31: 702534.79 | D31: =C31*0.1 -> 70253.479 | E31: =D31*0.1 -> 7025.3479 | F31: =D31*$H$3 -> 21054.968 | G31: =D31-E31-F31 -> 42173.163 | H31: COBRADO SOMENTE A PERMUTA
A32: 45992 | B32: =VLOOKUP(A32,'INCC - DI'!$H:$I,2,FALSE) -> 1222.356 | C32: 1665156.9 | D32: =C32*0.1 -> 166515.69 | E32: =D32*0.1 -> 16651.569 | F32: =D32*$H$3 -> 49904.752 | G32: =D32-E32-F32 -> 99959.368 | H32: COBRADO SOMENTE A PERMUTA
A33: 46023 | B33: =VLOOKUP(A33,'INCC - DI'!$H:$I,2,FALSE) -> 1225.633 | C33: 868319.98 | D33: =C33*0.1 -> 86831.998 | E33: =D33*0.1 -> 8683.1998 | F33: =D33*$H$3-1342.66 -> 24680.89 | G33: =D33-E33-F33 -> 53467.908 | H33: COBRADO SOMENTE A PERMUTA
A34: 46054 | B34: =VLOOKUP(A34,'INCC - DI'!$H:$I,2,FALSE) -> 1228.161 | C34: 738730.9 | D34: =C34*0.1 -> 73873.09 | E34: =D34*0.1 -> 7387.309 | F34: 20797.11 | G34: =D34-E34-F34 -> 45688.671 | H34: COBRADO SOMENTE A PERMUTA
A35: 46082 | B35: =VLOOKUP(A35,'INCC - DI'!$H:$I,2,FALSE) -> 1237.036 | C35: 2035863.4 | D35: =C35*0.1 -> 203586.34 | E35: =D35*0.1 -> 20358.634 | F35: 35690.15 | G35: =D35-E35-F35 -> 147537.55 | H35: COBRADO SOMENTE A PERMUTA
A36: 46113 | B36: =VLOOKUP(A36,'INCC - DI'!$H:$I,2,FALSE) -> 1240.481 | D36: =C36*0.1 -> 0 | E36: =D36*0.1 -> 0 | F36: =D36*$H$3 -> 0 | G36: =D36-E36-F36 -> 0
A37: 46143 | B37: =VLOOKUP(A37,'INCC - DI'!$H:$I,2,FALSE) -> 1247.181 | D37: =C37*0.1 -> 0 | E37: =D37*0.1 -> 0 | F37: =D37*$H$3 -> 0 | G37: =D37-E37-F37 -> 0
A38: 46174 | B38: =VLOOKUP(A38,'INCC - DI'!$H:$I,2,FALSE) -> 1259.652 | D38: =C38*0.1 -> 0 | E38: =D38*0.1 -> 0 | F38: =D38*$H$3 -> 0 | G38: =D38-E38-F38 -> 0
C39: aba financ compet.

Sheet Varanda PMG
F1: SALDO | H1: ACUMULADO | J1: 1° MEDIÇÃO | L1: 2° MEDIÇÃO | N1: 3° MEDIÇÃO | P1: 4° MEDIÇÃO | R1: 5° MEDIÇÃO | T1: 6° MEDIÇÃO | V1: 7° MEDIÇÃO | X1: 8° MEDIÇÃO | Z1: 9° MEDIÇÃO | AB1: 10° MEDIÇÃO | AD1: 11° MEDIÇÃO | AF1: 12° MEDIÇÃO | AH1: 13° MEDIÇÃO | AJ1: 14° MEDIÇÃO | AL1: 15° MEDIÇÃO | AN1: 16° MEDIÇÃO | AP1: 17° MEDIÇÃO | AR1: 18° MEDIÇÃO | AT1: 19° MEDIÇÃO | AV1: 20° MEDIÇÃO | AX1: 21° MEDIÇÃO | AZ1: 22° MEDIÇÃO | BB1: 23° MEDIÇÃO | BD1: 24° MEDIÇÃO | BF1: 25° MEDIÇÃO | BH1: 26° MEDIÇÃO | BJ1: 27° MEDIÇÃO | BL1: 28° MEDIÇÃO | BN1: 29° MEDIÇÃO | BP1: 30° MEDIÇÃO
J2: 44805 | L2: 44835 | N2: 44866 | P2: 44896 | R2: 44927 | T2: 44958 | V2: 44986 | X2: 45017 | Z2: 45047 | AB2: 45078 | AD2: 45108 | AF2: 45139 | AH2: 45170 | AJ2: 45200 | AL2: 45231 | AN2: 45261 | AP2: 45292 | AR2: 45323 | AT2: 45352 | AV2: 45383 | AX2: 45413 | AZ2: 45444 | BB2: 45474 | BD2: 45505 | BF2: 45536 | BH2: 45566 | BJ2: 45597 | BL2: 45627 | BN2: 45658 | BP2: 45689
A3: TAXA DE ADMINISTRAÇÃO | B3: UNIDADE | C3: QUANTIDADE | D3: VALOR UNITÁRIO | E3: VALOR TOTAL | F3: QTD | G3: R$ | H3: QTD | I3: R$ | J3: QTD | K3: R$ | L3: QTD | M3: R$ | N3: QTD | O3: R$ | P3: QTD | Q3: R$ | R3: QTD | S3: R$ | T3: QTD | U3: R$ | V3: QTD | W3: R$ | X3: QTD | Y3: R$ | Z3: QTD | AA3: R$ | AB3: QTD | AC3: R$ | AD3: QTD | AE3: R$ | AF3: QTD | AG3: R$ | AH3: QTD | AI3: R$ | AJ3: QTD | AK3: R$ | AL3: QTD | AM3: R$ | AN3: QTD | AO3: R$ | AP3: QTD | AQ3: R$ | AR3: QTD | AS3: R$ | AT3: QTD | AU3: R$ | AV3: QTD | AW3: R$ | AX3: QTD | AY3: R$ | AZ3: QTD | BA3: R$ | BB3: QTD | BC3: R$ | BD3: QTD | BE3: R$ | BF3: QTD | BG3: R$ | BH3: QTD | BI3: R$ | BJ3: QTD | BK3: R$ | BL3: QTD | BM3: R$ | BN3: QTD | BO3: R$ | BP3: QTD | BQ3: R$
A4: PARCELAS FIXAS E MENSAIS | B4: MES | C4: 32 | D4: 69023 | E4: =C4*D4 -> 2208736 | F4: =C4-H4 -> 2 | G4: =E4-I4 -> 138046 | H4: =SUMIFS($J$4:$CU$4,$J$3:$CU$3,$J$3) -> 30 | I4: =SUMIFS($J$4:$CU$4,$J$3:$CU$3,$K$3) -> 2070690 | J4: 1 | K4: =D4*J4 -> 69023 | L4: 1 | M4: 69023 | N4: 1 | O4: 69023 | P4: 1 | Q4: 69023 | R4: 1 | S4: 69023 | T4: 1 | U4: 69023 | V4: 1 | W4: 69023 | X4: 1 | Y4: 69023 | Z4: 1 | AA4: 69023 | AB4: 1 | AC4: 69023 | AD4: 1 | AE4: 69023 | AF4: 1 | AG4: 69023 | AH4: 1 | AI4: 69023 | AJ4: 1 | AK4: 69023 | AL4: 1 | AM4: 69023 | AN4: 1 | AO4: 69023 | AP4: 1 | AQ4: 69023 | AR4: 1 | AS4: 69023 | AT4: 1 | AU4: 69023 | AV4: 1 | AW4: 69023 | AX4: 1 | AY4: 69023 | AZ4: 1 | BA4: 69023 | BB4: 1 | BC4: 69023 | BD4: 1 | BE4: 69023 | BF4: 1 | BG4: 69023 | BH4: 1 | BI4: 69023 | BJ4: 1 | BK4: 69023 | BL4: 1 | BM4: 69023 | BN4: 1 | BO4: 69023 | BP4: 1 | BQ4: 69023
A5: PARCELA FIXA (30 DIAS APÓS A CONCLUSÃO) | B5: MES | C5: 1 | D5: 1767000 | E5: =C5*D5 -> 1767000 | F5: =C5-H5 -> 1 | G5: =D5-I5 -> 1767000
A6: PARCELA REAJUSTADA (60 DIAS APÓS A CONCLUSÃO) | B6: MES | C6: 1 | D6: 54264 | E6: =C6*D6 -> 54264 | F6: =C6-H6 -> 1 | G6: =D6-I6 -> 54264
E7: =SUM(E4:E6) -> 4030000 | G7: =SUM(G4:G6) -> 1959310 | I7: =SUM(I4:I6) -> 2070690 | K7: =SUM(K4:K6) -> 69023 | M7: =SUM(M4:M6) -> 69023 | O7: =SUM(O4:O6) -> 69023 | Q7: =SUM(Q4:Q6) -> 69023 | S7: =SUM(S4:S6) -> 69023 | U7: =SUM(U4:U6) -> 69023 | W7: =SUM(W4:W6) -> 69023 | Y7: =SUM(Y4:Y6) -> 69023 | AA7: =SUM(AA4:AA6) -> 69023 | AC7: =SUM(AC4:AC6) -> 69023 | AE7: =SUM(AE4:AE6) -> 69023 | AG7: =SUM(AG4:AG6) -> 69023 | AI7: =SUM(AI4:AI6) -> 69023 | AK7: =SUM(AK4:AK6) -> 69023 | AM7: =SUM(AM4:AM6) -> 69023 | AO7: =SUM(AO4:AO6) -> 69023 | AQ7: =SUM(AQ4:AQ6) -> 69023 | AS7: =SUM(AS4:AS6) -> 69023 | AU7: =SUM(AU4:AU6) -> 69023 | AW7: =SUM(AW4:AW6) -> 69023 | AY7: =SUM(AY4:AY6) -> 69023 | BA7: =SUM(BA4:BA6) -> 69023 | BC7: =SUM(BC4:BC6) -> 69023 | BE7: =SUM(BE4:BE6) -> 69023 | BG7: =SUM(BG4:BG6) -> 69023 | BI7: =SUM(BI4:BI6) -> 69023 | BK7: =SUM(BK4:BK6) -> 69023 | BM7: =SUM(BM4:BM6) -> 69023 | BO7: =SUM(BO4:BO6) -> 69023 | BQ7: =SUM(BQ4:BQ6) -> 69023

Sheet Ristreto
A1: Ristreto | F1: saldo | G1: =G3-D3 -> 87213.867 | H1: =G3-I3 -> 87213.867
A2: Data Base | B2: INCC Base | C2: Valor Orçado | D2: Valor da Taxa (Reaj) | G2: Valor Previsto Total | I2: Valor Cobrado
A3: 45566 | B3: 1149.17 | C3: 139872.46 | D3: =SUM(D5:D19) -> 67040.993 | G3: =SUM(G5:G19) -> 154254.86 | I3: =SUM(I5:I19) -> 67040.993 | J3: =D3-I3 -> 0
A4: Mês | B4: INCC DI (n-1) | C4: Medição | D4: Valor da Taxa (Reaj) | F4: Medição Prevista | G4: Valor Previsto | I4: Valor Cobrado
A5: 46113 | B5: =VLOOKUP(A5,'INCC - DI'!$E:$F,2,FALSE) -> 1247.181 | C5: 0.16421178 | D5: =(C5*$C$3)*B5/$B$3 -> 24927.673 | F5: 0.0743917 | G5: =F5*($C$3/$B$3*B5) -> 11292.807 | I5: 24793.76
A6: =EDATE(A5,1) -> 46143 | B6: =VLOOKUP(A6,'INCC - DI'!$E:$F,2,FALSE) -> 1259.652 | C6: 0.10301388 | D6: =(C6*$C$3)*B6/$B$3 -> 15794.077 | F6: 0.14599751 | G6: =F6*($C$3/$B$3*B6) -> 22384.324 | I6: 15771.623
A7: =EDATE(A6,1) -> 46174 | B7: =VLOOKUP(A7,'INCC - DI'!$E:$F,2,FALSE) -> 1270.695 | C7: 0.17017044 | D7: =(C7*$C$3)*B7/$B$3 -> 26319.242 | F7: 0.18506957 | G7: =F7*($C$3/$B$3*B7) -> 28623.602 | I7: 26475.609
A8: =EDATE(A7,1) -> 46204 | B8: =VLOOKUP(A8,'INCC - DI'!$E:$F,2,FALSE) -> 1270.695 | D8: =(C8*$C$3)*B8/$B$3 -> 0 | F8: 0.11323795 | G8: =F8*($C$3/$B$3*B8) -> 17513.835 | H8: =(F8*$G$1/(SUM($F$8:$F$19))) -> 16610.992
A9: =EDATE(A8,1) -> 46235 | B9: =VLOOKUP(A9,'INCC - DI'!$E:$F,2,FALSE) -> 1270.695 | D9: =(C9*$C$3)*B9/$B$3 -> 0 | F9: 0.093639656 | G9: =F9*($C$3/$B$3*B9) -> 14482.685 | H9: =(F9*$G$1/(SUM($F$8:$F$19))) -> 13736.098
A10: =EDATE(A9,1) -> 46266 | B10: =VLOOKUP(A10,'INCC - DI'!$E:$F,2,FALSE) -> 1270.695 | D10: =(C10*$C$3)*B10/$B$3 -> 0 | F10: 0.08996861 | G10: =F10*($C$3/$B$3*B10) -> 13914.906 | H10: =(F10*$G$1/(SUM($F$8:$F$19))) -> 13197.589
A11: =EDATE(A10,1) -> 46296 | B11: =VLOOKUP(A11,'INCC - DI'!$E:$F,2,FALSE) -> 1270.695 | D11: =(C11*$C$3)*B11/$B$3 -> 0 | F11: 0.089219311 | G11: =F11*($C$3/$B$3*B11) -> 13799.016 | H11: =(F11*$G$1/(SUM($F$8:$F$19))) -> 13087.673
A12: =EDATE(A11,1) -> 46327 | B12: =VLOOKUP(A12,'INCC - DI'!$E:$F,2,FALSE) -> 1270.695 | D12: =(C12*$C$3)*B12/$B$3 -> 0 | F12: 0.12491607 | G12: =F12*($C$3/$B$3*B12) -> 19320.02 | H12: =(F12*$G$1/(SUM($F$8:$F$19))) -> 18324.068
A13: =EDATE(A12,1) -> 46357 | B13: =VLOOKUP(A13,'INCC - DI'!$E:$F,2,FALSE) -> 1270.695 | D13: =(C13*$C$3)*B13/$B$3 -> 0 | F13: 0.022545244 | G13: =F13*($C$3/$B$3*B13) -> 3486.9378 | H13: =(F13*$G$1/(SUM($F$8:$F$19))) -> 3307.1853
A14: =EDATE(A13,1) -> 46388 | B14: =VLOOKUP(A14,'INCC - DI'!$E:$F,2,FALSE) -> 1270.695 | D14: =(C14*$C$3)*B14/$B$3 -> 0 | F14: 0.030090524 | G14: =F14*($C$3/$B$3*B14) -> 4653.9211 | H14: =(F14*$G$1/(SUM($F$8:$F$19))) -> 4414.0102
A15: =EDATE(A14,1) -> 46419 | B15: =VLOOKUP(A15,'INCC - DI'!$E:$F,2,FALSE) -> 1270.695 | D15: =(C15*$C$3)*B15/$B$3 -> 0 | F15: 0.027486351 | G15: =F15*($C$3/$B$3*B15) -> 4251.1492 | H15: =(F15*$G$1/(SUM($F$8:$F$19))) -> 4032.0014
A16: =EDATE(A15,1) -> 46447 | B16: =VLOOKUP(A16,'INCC - DI'!$E:$F,2,FALSE) -> 1270.695 | D16: =(C16*$C$3)*B16/$B$3 -> 0 | F16: 0.0012517614 | G16: =F16*($C$3/$B$3*B16) -> 193.60243 | H16: =(F16*$G$1/(SUM($F$8:$F$19))) -> 183.62218
A17: =EDATE(A16,1) -> 46478 | B17: =VLOOKUP(A17,'INCC - DI'!$E:$F,2,FALSE) -> 1270.695 | D17: =(C17*$C$3)*B17/$B$3 -> 0 | F17: 0.00069215047 | G17: =F17*($C$3/$B$3*B17) -> 107.05077 | H17: =(F17*$G$1/(SUM($F$8:$F$19))) -> 101.53227
A18: =EDATE(A17,1) -> 46508 | B18: =VLOOKUP(A18,'INCC - DI'!$E:$F,2,FALSE) -> 1270.695 | D18: =(C18*$C$3)*B18/$B$3 -> 0 | F18: 0.00080143738 | G18: =F18*($C$3/$B$3*B18) -> 123.95352 | H18: =(F18*$G$1/(SUM($F$8:$F$19))) -> 117.56368
A19: =EDATE(A18,1) -> 46539 | B19: =VLOOKUP(A19,'INCC - DI'!$E:$F,2,FALSE) -> 1270.695 | D19: =(C19*$C$3)*B19/$B$3 -> 0 | F19: 0.00069215047 | G19: =F19*($C$3/$B$3*B19) -> 107.05077 | H19: =(F19*$G$1/(SUM($F$8:$F$19))) -> 101.53227
C20: =SUM(C5:C19) -> 0.4373961
C21: 0.4373961
C22: =C21-C20 -> 0

Sheet Pace
B1: Pace | G1: Valor Taxa ADM Base | H1: Valor Taxa ADM Reajustado
B2: Piemonte | D2: Pereira & Decol | G2: 12000000 | H2: =F57 -> 12226675
B3: Valor Total Taxa ADM | D3: Valor Total Taxa ADM
B4: =H2*0.82 -> 10025873 | D4: =H2*0.18 -> 2200801.5 | G4: 2200801.5
B5: Medição Acumulada | C5: Valor Total Taxa Medido | D5: Medição Acumulada | E5: Valor Total Taxa Medido | M5: Valor Cobrado
B6: =SUM(B8:B52) -> 0.44517706 | C6: =SUM(C8:C52) -> 4463288.8 | D6: =SUM(D8:D52) -> 0.44517706 | E6: =SUM(E8:E52) -> 979746.33 | H6: =B4-C6 -> 5562584.6 | J6: =D4-E6 -> 1221055.1 | M6: =SUM(M8:M50) -> 4463288.8 | N6: =SUM(N8:N50) -> 979746.33 | O6: =C6-M6 -> 0 | P6: =E6-N6 -> 0
A7: Mês | B7: Medição | C7: Valor Taxa ADM | D7: Medição | E7: Valor Taxa ADM | G7: Medição Prevista | H7: Valor Previsto Piemonte | J7: Valor Previsto Pereira | M7: Piemonte | N7: Pereira & Decol | O7: =SUM(O8:O32) -> 3373213.7
A8: 45292 | B8: 0.0027288435 | C8: =B8*$B$4 -> 27359.039 | D8: 0.0027288435 | E8: =D8*$D$4 -> 6005.6428 | G8: 0.0073303195 | H8: =G8*$B$4 -> 73492.855 | J8: =G8*$D$4 -> 16132.578 | M8: 26851.82 | N8: 5894.302 | O8: 26851.82 | P8: =O8=M8 -> TRUE
A9: 45323 | B9: 0.016952376 | C9: =B9*$B$4 -> 169962.38 | D9: 0.016952376 | E9: =D9*$D$4 -> 37308.814 | G9: 0.019498282 | H9: =G9*$B$4 -> 195487.31 | J9: =G9*$D$4 -> 42911.849 | M9: 166811.38 | N9: 36617.132 | O9: 166811.38 | P9: =O9=M9 -> TRUE
A10: 45352 | B10: 0.015732708 | C10: =B10*$B$4 -> 157734.14 | D10: 0.015732708 | E10: =D10*$D$4 -> 34624.568 | G10: 0.022417668 | H10: =G10*$B$4 -> 224756.7 | J10: =G10*$D$4 -> 49336.836 | M10: 154809.85 | N10: 33982.65 | O10: 154672.8 | P10: =O10=M10 -> FALSE
A11: 45383 | B11: 0.025938172 | C11: =B11*$B$4 -> 260052.83 | D11: 0.025938172 | E11: =D11*$D$4 -> 57084.768 | G11: 0.022252152 | H11: =G11*$B$4 -> 223097.26 | J11: =G11*$D$4 -> 48972.57 | M11: 255368.67 | N11: 56026.452 | O11: 255368.67 | P11: =O11=M11 -> FALSE
A12: 45413 | B12: 0.016552997 | C12: =B12*$B$4 -> 165958.25 | D12: 0.016552997 | E12: =D12*$D$4 -> 36429.861 | G12: 0.014642618 | H12: =G12*$B$4 -> 146805.03 | J12: =G12*$D$4 -> 32225.495 | M12: 162881.49 | N12: 35754.474 | O12: 162881.49 | P12: =O12=M12 -> TRUE
A13: 45444 | B13: 0.010358759 | C13: =B13*$B$4 -> 103855.6 | D13: 0.010358759 | E13: =D13*$D$4 -> 22797.571 | G13: 0.011431691 | H13: =G13*$B$4 -> 114612.69 | J13: =G13*$D$4 -> 25158.883 | M13: 101930.18 | N13: 22374.919 | O13: 101930.18 | P13: =O13=M13 -> TRUE
A14: 45474 | B14: 0.017455831 | C14: =B14*$B$4 -> 175009.95 | D14: 0.017455831 | E14: =D14*$D$4 -> 38416.818 | G14: 0.016505289 | H14: =G14*$B$4 -> 165479.94 | J14: =G14*$D$4 -> 36324.865 | M14: 171765.37 | N14: 37704.594 | O14: 171765.37 | P14: =O14=M14 -> TRUE
A15: 45505 | B15: 0.020337346 | C15: =B15*$B$4 -> 203899.66 | D15: 0.020337346 | E15: =D15*$D$4 -> 44758.461 | G15: 0.015284011 | H15: =G15*$B$4 -> 153235.56 | J15: =G15*$D$4 -> 33637.075 | M15: 200119.49 | N15: 43928.667 | O15: 200119.49 | P15: =O15=M15 -> TRUE
A16: 45536 | B16: 0.012461192 | C16: =B16*$B$4 -> 124934.33 | D16: 0.012461192 | E16: =D16*$D$4 -> 27424.609 | G16: 0.01703232 | H16: =G16*$B$4 -> 170763.88 | J16: =G16*$D$4 -> 37484.755 | M16: 122618.13 | N16: 26916.174 | O16: 122618.13 | P16: =O16=M16 -> TRUE
A17: 45566 | B17: 0.01109483 | C17: =B17*$B$4 -> 111235.36 | D17: 0.01109483 | E17: =D17*$D$4 -> 24417.518 | G17: 0.0094254815 | H17: =G17*$B$4 -> 94498.685 | J17: =G17*$D$4 -> 20743.614 | M17: 109173.13 | N17: 23964.833 | O17: 109173.13 | P17: =O17=M17 -> TRUE | S17: Piemonte | W17: Pereira
A18: 45597 | B18: 0.00659954 | C18: =B18*$B$4 -> 66166.152 | D18: 0.00659954 | E18: =D18*$D$4 -> 14524.277 | G18: 0.009693056 | H18: =G18*$B$4 -> 97181.352 | J18: =G18*$D$4 -> 21332.492 | M18: 64939.473 | N18: 14255.006 | O18: 64939.473 | P18: =O18=M18 -> TRUE | S18: 2025 | W18: 2025 | X18: 2025
A19: 45627 | B19: 0.0099995249 | C19: =B19*$B$4 -> 100253.97 | D19: 0.0099995249 | E19: =D19*$D$4 -> 22006.969 | G19: 0.0081490613 | H19: =G19*$B$4 -> 81701.456 | J19: =G19*$D$4 -> 17934.466 | M19: 98395.325 | N19: 21598.974 | O19: 98395.325 | P19: =O19=M19 -> TRUE | T19: Previsto | U19: Realizado | X19: Previsto | Y19: Realizado
A20: 45658 | B20: 0.010513317 | C20: =B20*$B$4 -> 105405.19 | D20: 0.010513317 | E20: =D20*$D$4 -> 23137.724 | G20: 0.0061149758 | H20: =G20*$B$4 -> 61307.973 | J20: =G20*$D$4 -> 13457.848 | M20: 103451.04 | N20: 22708.765 | O20: 103451.04 | P20: =O20=M20 -> TRUE | S20: Taxa ADM | T20: 2019585 | U20: =SUM(M20:M31) -> 1860765.5 | W20: Taxa ADM | X20: 443323.53 | Y20: =SUM(N20:N31) -> 403720.58
A21: 45689 | B21: 0.010092887 | C21: =B21*$B$4 -> 101190 | D21: 0.010092887 | E21: =D21*$D$4 -> 22212.44 | G21: 0.012640077 | H21: =G21*$B$4 -> 126727.81 | J21: =G21*$D$4 -> 27818.3 | M21: 122918.29 | N21: 22080.56 | O21: 122918.29 | P21: =O21=M21 -> FALSE
A22: 45717 | B22: 0.013711231 | C22: =B22*$B$4 -> 137467.06 | D22: 0.013711231 | E22: =D22*$D$4 -> 30175.697 | G22: 0.013747871 | H22: =G22*$B$4 -> 137834.41 | J22: =G22*$D$4 -> 30256.335 | M22: 136650.91 | N22: 29996.54 | O22: 136650.91 | P22: =O22=M22 -> FALSE
A23: 45748 | B23: 0.013662556 | C23: =B23*$B$4 -> 136979.05 | D23: 0.013662556 | E23: =D23*$D$4 -> 30068.572 | G23: 0.01527985 | H23: =G23*$B$4 -> 153193.84 | J23: =G23*$D$4 -> 33627.916 | M23: 136165.8 | N23: 29890.053 | O23: 136165.8 | P23: =O23=M23 -> TRUE | S23: Acumulado | T23: Acumulado | W23: Acumulado | X23: Acumulado
A24: 45778 | B24: 0.020049794 | C24: =B24*$B$4 -> 201016.7 | D24: 0.020049794 | E24: =D24*$D$4 -> 44125.617 | G24: 0.014441966 | H24: =G24*$B$4 -> 144793.33 | J24: =G24*$D$4 -> 31783.901 | M24: 199823.24 | N24: 43863.639 | O24: 199823.24 | P24: =O24=M24 -> TRUE | T24: Previsto | U24: Realizado | X24: Previsto | Y24: Realizado
A25: 45809 | B25: 0.016762371 | C25: =B25*$B$4 -> 168057.41 | D25: 0.016762371 | E25: =D25*$D$4 -> 36890.651 | G25: 0.016952051 | H25: =G25*$B$4 -> 169959.11 | J25: =G25*$D$4 -> 37308.098 | M25: 167059.64 | N25: 36671.628 | O25: 167059.64 | P25: =O25=M25 -> TRUE | S25: Taxa ADM | T25: 3310262.6 | U25: =SUM(M8:M31) -> 3496429.8 | W25: Taxa ADM | X25: 726643.01 | Y25: =SUM(N8:N31) -> 762738.76
A26: 45839 | B26: 0.016098779 | C26: =B26*$B$4 -> 161404.32 | D26: 0.016098779 | E26: =D26*$D$4 -> 35430.216 | G26: 0.019572366 | H26: =G26*$B$4 -> 196230.06 | J26: =G26*$D$4 -> 43074.892 | M26: 160446.05 | N26: 35219.864 | O26: 160446.05 | P26: =O26=M26 -> TRUE
A27: 45870 | B27: 0.019955053 | C27: =B27*$B$4 -> 200066.83 | D27: 0.019955053 | E27: =D27*$D$4 -> 43917.11 | G27: 0.017016178 | H27: =G27*$B$4 -> 170602.04 | J27: =G27*$D$4 -> 37449.229 | M27: 198879.02 | N27: 43656.37 | O27: 198879.02 | P27: =O27=M27 -> TRUE
A28: 45901 | B28: 0.020105592 | C28: =B28*$B$4 -> 201576.12 | D28: 0.020105592 | E28: =D28*$D$4 -> 44248.416 | G28: 0.014169663 | H28: =G28*$B$4 -> 142063.25 | J28: =G28*$D$4 -> 31184.616 | M28: 200379.34 | N28: 43985.71 | O28: 200379.34 | P28: =O28=M28 -> FALSE
A29: 45931 | B29: 0.021569596 | C29: =B29*$B$4 -> 216254.04 | D29: 0.021569596 | E29: =D29*$D$4 -> 47470.4 | G29: 0.014443061 | H29: =G29*$B$4 -> 144804.31 | J29: =G29*$D$4 -> 31786.311 | M29: 214970.12 | N29: 47188.563 | O29: 214970.12 | P29: =O29=M29 -> TRUE
A30: 45962 | B30: 0.0097270333 | C30: =B30*$B$4 -> 97522.004 | D30: 0.0097270333 | E30: =D30*$D$4 -> 21407.269 | G30: 0.015167868 | H30: =G30*$B$4 -> 152071.12 | J30: =G30*$D$4 -> 33381.466 | M30: 96943.01 | N30: 21280.17 | O30: 96943.007 | P30: =O30=M30 -> FALSE
A31: 45992 | B31: 0.012349465 | C31: =B31*$B$4 -> 123814.17 | D31: 0.012349465 | E31: =D31*$D$4 -> 27178.721 | G31: 0.011068021 | H31: =G31*$B$4 -> 110966.58 | J31: =G31*$D$4 -> 24358.517 | M31: 123079.08 | N31: 27178.721 | P31: =O31=M31 -> FALSE
A32: 46023 | B32: 0.015870766 | C32: =B32*$B$4 -> 159118.29 | D32: 0.015870766 | E32: =D32*$D$4 -> 34928.406 | G32: 0.016415275 | H32: =G32*$B$4 -> 164577.47 | J32: =G32*$D$4 -> 36126.761 | M32: 179863.01 | N32: 44252.355 | P32: =O32=M32 -> FALSE
A33: 46054 | B33: 0.016365188 | C33: =B33*$B$4 -> 164075.3 | D33: 0.016365188 | E33: =D33*$D$4 -> 36016.529 | G33: 0.019405102 | H33: =G33*$B$4 -> 194553.1 | J33: =G33*$D$4 -> 42706.778 | M33: 164075.3 | N33: 36016.529
A34: 46082 | B34: 0.018146249 | C34: =B34*$B$4 -> 181932 | D34: 0.018146249 | E34: =D34*$D$4 -> 39936.292 | G34: 0.031912502 | H34: =G34*$B$4 -> 319950.7 | J34: =G34*$D$4 -> 70233.081 | M34: 181932 | N34: 39936.292
A35: 46113 | B35: 0.016317928 | C35: =B35*$B$4 -> 163601.48 | D35: 0.016317928 | E35: =D35*$D$4 -> 35912.521 | G35: 0.027416156 | H35: =G35*$B$4 -> 274870.91 | J35: =G35*$D$4 -> 60337.516 | M35: 163601.48 | N35: 35912.521
A36: 46143 | B36: 0.012086876 | C36: =B36*$B$4 -> 121181.49 | D36: 0.012086876 | E36: =D36*$D$4 -> 26600.815 | G36: 0.032441784 | H36: =G36*$B$4 -> 325257.22 | J36: =G36*$D$4 -> 71397.927 | M36: 121181.49 | N36: 26600.815
A37: 46174 | B37: 0.01558026 | C37: =B37*$B$4 -> 156205.72 | D37: 0.01558026 | E37: =D37*$D$4 -> 34289.06 | G37: 0.030937509 | H37: =G37*$B$4 -> 310175.55 | J37: =G37*$D$4 -> 68087.316 | M37: 156205.72 | N37: 34289.06
A38: 46204 | C38: =B38*$B$4 -> 0 | E38: =D38*$D$4 -> 0 | G38: 0.02479245 | H38: =G38*$B$4 -> 248565.97 | I38: =(G38*$H$6/(SUM($G$38:$G$54))) -> 277375.85 | J38: =G38*$D$4 -> 54563.261 | K38: =(G38*$J$6/(SUM($G$38:$G$54))) -> 60887.382
A39: 46235 | C39: =B39*$B$4 -> 0 | E39: =D39*$D$4 -> 0 | G39: 0.031104821 | H39: =G39*$B$4 -> 311853 | I39: =(G39*$H$6/(SUM($G$38:$G$54))) -> 347998.13 | J39: =G39*$D$4 -> 68455.537 | K39: =(G39*$J$6/(SUM($G$38:$G$54))) -> 76389.833
A40: 46266 | C40: =B40*$B$4 -> 0 | E40: =D40*$D$4 -> 0 | G40: 0.032509554 | H40: =G40*$B$4 -> 325936.67 | I40: =(G40*$H$6/(SUM($G$38:$G$54))) -> 363714.15 | J40: =G40*$D$4 -> 71547.074 | K40: =(G40*$J$6/(SUM($G$38:$G$54))) -> 79839.693
A41: 46296 | C41: =B41*$B$4 -> 0 | E41: =D41*$D$4 -> 0 | G41: 0.044382403 | H41: =G41*$B$4 -> 444972.36 | I41: =(G41*$H$6/(SUM($G$38:$G$54))) -> 496546.6 | J41: =G41*$D$4 -> 97676.859 | K41: =(G41*$J$6/(SUM($G$38:$G$54))) -> 108998.03
A42: 46327 | C42: =B42*$B$4 -> 0 | E42: =D42*$D$4 -> 0 | G42: 0.039191314 | H42: =G42*$B$4 -> 392927.15 | I42: =(G42*$H$6/(SUM($G$38:$G$54))) -> 438469.13 | J42: =G42*$D$4 -> 86252.302 | K42: =(G42*$J$6/(SUM($G$38:$G$54))) -> 96249.322
A43: 46357 | C43: =B43*$B$4 -> 0 | E43: =D43*$D$4 -> 0 | G43: 0.020692974 | H43: =G43*$B$4 -> 207465.13 | I43: =(G43*$H$6/(SUM($G$38:$G$54))) -> 231511.25 | J43: =G43*$D$4 -> 45541.127 | K43: =(G43*$J$6/(SUM($G$38:$G$54))) -> 50819.543
A44: 46388 | C44: =B44*$B$4 -> 0 | E44: =D44*$D$4 -> 0 | G44: 0.023059642 | H44: =G44*$B$4 -> 231193.05 | I44: =(G44*$H$6/(SUM($G$38:$G$54))) -> 257989.34 | J44: =G44*$D$4 -> 50749.694 | K44: =(G44*$J$6/(SUM($G$38:$G$54))) -> 56631.805
A45: 46419 | C45: =B45*$B$4 -> 0 | E45: =D45*$D$4 -> 0 | G45: 0.037686683 | H45: =G45*$B$4 -> 377841.91 | I45: =(G45*$H$6/(SUM($G$38:$G$54))) -> 421635.44 | J45: =G45*$D$4 -> 82940.907 | K45: =(G45*$J$6/(SUM($G$38:$G$54))) -> 92554.122 | O45: TOTAL PAGO TAXA | P45: 3373213.7
A46: 46447 | C46: =B46*$B$4 -> 0 | E46: =D46*$D$4 -> 0 | G46: 0.057833171 | H46: =G46*$B$4 -> 579828.05 | I46: =(G46*$H$6/(SUM($G$38:$G$54))) -> 647032.66 | J46: =G46*$D$4 -> 127279.33 | K46: =(G46*$J$6/(SUM($G$38:$G$54))) -> 142031.56 | O46: SALDO TAXA | P46: =6652659.6911204-E57 -> 6580068.8
A47: 46478 | C47: =B47*$B$4 -> 0 | E47: =D47*$D$4 -> 0 | G47: 0.055384328 | H47: =G47*$B$4 -> 555276.26 | I47: =(G47*$H$6/(SUM($G$38:$G$54))) -> 619635.21 | J47: =G47*$D$4 -> 121889.91 | K47: =(G47*$J$6/(SUM($G$38:$G$54))) -> 136017.48 | O47: PERMUTA | P47: 1970875.9
A48: 46508 | C48: =B48*$B$4 -> 0 | E48: =D48*$D$4 -> 0 | G48: 0.042292316 | H48: =G48*$B$4 -> 424017.41 | I48: =(G48*$H$6/(SUM($G$38:$G$54))) -> 473162.88 | J48: =G48*$D$4 -> 93076.992 | K48: =(G48*$J$6/(SUM($G$38:$G$54))) -> 103865.02 | O48: % ABATIMENTO | P48: =P47/P46 -> 0.29952208
A49: 46539 | C49: =B49*$B$4 -> 0 | E49: =D49*$D$4 -> 0 | G49: 0.039944724 | H49: =G49*$B$4 -> 400480.75 | I49: =(G49*$H$6/(SUM($G$38:$G$54))) -> 446898.22 | J49: =G49*$D$4 -> 87910.408 | K49: =(G49*$J$6/(SUM($G$38:$G$54))) -> 98099.609
A50: 46569 | C50: =B50*$B$4 -> 0 | E50: =D50*$D$4 -> 0 | G50: 0.030422333 | H50: =G50*$B$4 -> 305010.46 | I50: =(G50*$H$6/(SUM($G$38:$G$54))) -> 340362.5 | J50: =G50*$D$4 -> 66953.515 | K50: =(G50*$J$6/(SUM($G$38:$G$54))) -> 74713.72
A51: 46600 | C51: =B51*$B$4 -> 0 | E51: =D51*$D$4 -> 0 | G51: 0.01789906 | H51: =G51*$B$4 -> 179453.71 | I51: =(G51*$H$6/(SUM($G$38:$G$54))) -> 200253.19 | J51: =G51*$D$4 -> 39392.279 | K51: =(G51*$J$6/(SUM($G$38:$G$54))) -> 43958.016
A55: Mês | B55: Saldo Taxa ADM (a) | C55: Variação INCC no Ano (b) | D55: Δ Diferença 5,00% (c) | E55: Reajuste (d) (a) * (c) | F55: Total Taxa ADM Reajustado
A56: 45658 | B56: 10005455 | C56: 0.0654 | D56: =C56-5% -> 0.0154 | E56: =B56*D56 -> 154084 | F56: =E56+G2 -> 12154084
A57: 46023 | B57: 7890312.3 | C57: 0.0592 | D57: =C57-5% -> 0.0092 | E57: =B57*D57 -> 72590.873 | F57: =F56+E57 -> 12226675
F58: =F57 -> 12226675
F59: =F58 -> 12226675
F60: =F59 -> 12226675
F61: =F60 -> 12226675

Sheet Ícaro
B1: Icaro_F01
B2: Piemonte
B3: Valor Total Taxa ADM
B4: 1804851.9
B5: Medição Acumulada | C5: Valor Total Taxa Medido | H5: Valor Cobrado
B6: =SUM(B8:B51) -> 0.5536 | C6: =SUM(C8:C51) -> 999166.02 | F6: =B4-C6 -> 805685.9 | H6: =SUM(H8:H50) -> 999166.02 | I6: =C6-H6 -> 0
A7: Mês | B7: Medição | C7: Valor Taxa ADM | E7: Medição Prevista | F7: Valor Previsto Piemonte | H7: Piemonte
A8: 45992 | B8: 0.0522 | C8: =B8*$B$4 -> 94213.27 | E8: 0.05222827 | H8: 92993.945
A9: =EDATE(A8,1) -> 46023 | B9: 0.0664 | C9: =B9*$B$4 -> 119842.17 | E9: 0.06635268 | F9: =E9*$B$4 -> 119756.76 | H9: 119807.98
A10: =EDATE(A9,1) -> 46054 | B10: 0.0924 | C10: =B10*$B$4 -> 166768.32 | E10: 0.09242526 | F10: =E10*$B$4 -> 166813.91 | H10: 167984.15
A11: =EDATE(A10,1) -> 46082 | B11: 0.1195 | C11: =B11*$B$4 -> 215679.8 | E11: 0.11946191 | F11: =E11*$B$4 -> 215611.06 | H11: 215703.31
A12: =EDATE(A11,1) -> 46113 | B12: 0.079 | C12: =B12*$B$4 -> 142583.3 | E12: 0.07902533 | F12: =E12*$B$4 -> 142629.02 | H12: 178228.67
A13: =EDATE(A12,1) -> 46143 | B13: 0.0746 | C13: =B13*$B$4 -> 134641.95 | E13: 0.06646698 | F13: =E13*$B$4 -> 119963.06 | H13: 99010.759
A14: =EDATE(A13,1) -> 46174 | B14: 0.0695 | C14: =B14*$B$4 -> 125437.21 | E14: 0.11794413 | F14: =E14*$B$4 -> 212871.69 | H14: 125437.21
A15: =EDATE(A14,1) -> 46204 | C15: =B15*$B$4 -> 0 | E15: 0.15264993 | F15: =E15*$B$4 -> 275510.52 | G15: =(E15*$F$6/(SUM($E$15:$E$31))) -> 302854.66
A16: =EDATE(A15,1) -> 46235 | C16: =B16*$B$4 -> 0 | E16: 0.14121407 | F16: =E16*$B$4 -> 254870.49 | G16: =(E16*$F$6/(SUM($E$15:$E$31))) -> 280166.12
A17: =EDATE(A16,1) -> 46266 | C17: =B17*$B$4 -> 0 | E17: 0.08951204 | F17: =E17*$B$4 -> 161555.98 | G17: =(E17*$F$6/(SUM($E$15:$E$31))) -> 177590.24
A18: =EDATE(A17,1) -> 46296 | C18: =B18*$B$4 -> 0 | E18: 0.0227194 | F18: =E18*$B$4 -> 41005.153 | G18: =(E18*$F$6/(SUM($E$15:$E$31))) -> 45074.872
A19: =EDATE(A18,1) -> 46327 | C19: =B19*$B$4 -> 0
C20: =B20*$B$4 -> 0
C21: =B21*$B$4 -> 0
C22: =B22*$B$4 -> 0
C23: =B23*$B$4 -> 0
C24: =B24*$B$4 -> 0
C25: =B25*$B$4 -> 0
C26: =B26*$B$4 -> 0
C27: =B27*$B$4 -> 0
C28: =B28*$B$4 -> 0
C29: =B29*$B$4 -> 0
C30: =B30*$B$4 -> 0
C31: =B31*$B$4 -> 0
... C51: =B51*$B$4 -> 0

Sheet Aretha
A1: Aretha | F1: saldo | G1: =G3-D3 -> 0 | H1: =G3-I3 -> 0
A2: Data Base | B2: INCC Base | C2: Valor Orçado | D2: Valor da Taxa (Reaj) | G2: Valor Previsto Total | I2: Valor Cobrado
A3: 45108 | B3: =VLOOKUP(A3,'INCC - M'!$E:$F,2,FALSE) -> 1074.292 | C3: 1526854.4 | D3: =SUM(D5:D36) -> 1631625.1 | G3: =SUM(G5:G32) -> 1631625.1 | I3: =SUM(I5:I35) -> 1631625.1 | J3: =D3-I3 -> 0
A4: Mês | B4: INCC M (n-1) | C4: Medição | D4: Valor da Taxa (Reaj) | F4: Medição Prevista | G4: Valor Previsto | I4: Valor Cobrado
A5: 45170 | B5: =VLOOKUP(A5,'INCC - M'!$E:$F,2,FALSE) -> 1077.497 | C5: 0.012788427 | D5: =(C5*$C$3)*B5/$B$3 -> 19584.319 | F5: 0.012788427 | G5: =F5*($C$3/$B$3*B5) -> 19584.319 | I5: 19584.319
A6: 45200 | B6: =VLOOKUP(A6,'INCC - M'!$E:$F,2,FALSE) -> 1080.071 | C6: 0.021628597 | D6: =(C6*$C$3)*B6/$B$3 -> 33201.364 | F6: 0.021628597 | G6: =F6*($C$3/$B$3*B6) -> 33201.364 | I6: 33157.466
A7: 45231 | B7: =VLOOKUP(A7,'INCC - M'!$E:$F,2,FALSE) -> 1082.251 | C7: 0.03347299 | D7: =(C7*$C$3)*B7/$B$3 -> 51487.023 | F7: 0.03347299 | G7: =F7*($C$3/$B$3*B7) -> 51487.023 | I7: 51487.023
A8: 45261 | B8: =VLOOKUP(A8,'INCC - M'!$E:$F,2,FALSE) -> 1083.335 | C8: 0.019473169 | D8: =(C8*$C$3)*B8/$B$3 -> 29982.972 | F8: 0.019473169 | G8: =F8*($C$3/$B$3*B8) -> 29982.972 | I8: 29982.972
A9: 45292 | B9: =VLOOKUP(A9,'INCC - M'!$E:$F,2,FALSE) -> 1086.15 | C9: 0.029123171 | D9: =(C9*$C$3)*B9/$B$3 -> 44957.665 | F9: 0.029123171 | G9: =F9*($C$3/$B$3*B9) -> 44957.665 | I9: 44957.665
A10: 45323 | B10: =VLOOKUP(A10,'INCC - M'!$E:$F,2,FALSE) -> 1088.663 | C10: 0.013918549 | D10: =(C10*$C$3)*B10/$B$3 -> 21535.884 | F10: 0.013918549 | G10: =F10*($C$3/$B$3*B10) -> 21535.884 | I10: 21535.884
A11: 45352 | B11: =VLOOKUP(A11,'INCC - M'!$E:$F,2,FALSE) -> 1090.871 | C11: 0.014250305 | D11: =(C11*$C$3)*B11/$B$3 -> 22093.923 | F11: 0.014250305 | G11: =F11*($C$3/$B$3*B11) -> 22093.923 | I11: 22093.923
A12: 45383 | B12: =VLOOKUP(A12,'INCC - M'!$E:$F,2,FALSE) -> 1093.503 | C12: 0.029795405 | D12: =(C12*$C$3)*B12/$B$3 -> 46306.777 | F12: 0.029795405 | G12: =F12*($C$3/$B$3*B12) -> 46306.777 | I12: 46306.777
A13: 45413 | B13: =VLOOKUP(A13,'INCC - M'!$E:$F,2,FALSE) -> 1097.991 | C13: 0.03069331 | D13: =(C13*$C$3)*B13/$B$3 -> 47898.045 | F13: 0.03069331 | G13: =F13*($C$3/$B$3*B13) -> 47898.045 | I13: 47898.045
A14: 45444 | B14: =VLOOKUP(A14,'INCC - M'!$E:$F,2,FALSE) -> 1104.457 | C14: 0.025690371 | D14: =(C14*$C$3)*B14/$B$3 -> 40326.865 | F14: 0.025690371 | G14: =F14*($C$3/$B$3*B14) -> 40326.865 | I14: 40326.865
A15: 45474 | B15: =VLOOKUP(A15,'INCC - M'!$E:$F,2,FALSE) -> 1114.748 | C15: 0.036483213 | D15: =(C15*$C$3)*B15/$B$3 -> 57802.292 | F15: 0.036483213 | G15: =F15*($C$3/$B$3*B15) -> 57802.292 | I15: 57802.292
A16: 45505 | B16: =VLOOKUP(A16,'INCC - M'!$E:$F,2,FALSE) -> 1122.452 | C16: 0.055497132 | D16: =(C16*$C$3)*B16/$B$3 -> 88534.715 | F16: 0.055497132 | G16: =F16*($C$3/$B$3*B16) -> 88534.715 | I16: 88534.715
... A23: 45717 | B23: =VLOOKUP(A23,'INCC - M'!$E:$F,2,FALSE) -> 1169.156 | C23: 0.063148702 | D23: =(C23*$C$3)*B23/$B$3 -> 104933.02 | F23: 0.063148702 | G23: =F23*($C$3/$B$3*B23) -> 104933.02 | I23: 104933.02
A24: 45748 | B24: =VLOOKUP(A24,'INCC - M'!$E:$F,2,FALSE) -> 1173.586 | C24: 0.062953527 | D24: =(C24*$C$3)*B24/$B$3 -> 105005.07 | F24: 0.062953527 | G24: =F24*($C$3/$B$3*B24) -> 105005.07 | I24: =103892.449902629+43.9 -> 103936.35
A25: 45778 | B25: =VLOOKUP(A25,'INCC - M'!$E:$F,2,FALSE) -> 1180.564 | C25: 0.059440422 | D25: =(C25*$C$3)*B25/$B$3 -> 99734.794 | F25: 0.059440422 | G25: =F25*($C$3/$B$3*B25) -> 99734.794 | I25: 100847.41
A26: 45809 | B26: =VLOOKUP(A26,'INCC - M'!$E:$F,2,FALSE) -> 1183.606 | C26: 0.047276531 | D26: =(C26*$C$3)*B26/$B$3 -> 79529.461 | F26: 0.047276531 | G26: =F26*($C$3/$B$3*B26) -> 79529.461 | I26: 79529.461
A27: 45839 | B27: =VLOOKUP(A27,'INCC - M'!$E:$F,2,FALSE) -> 1194.912 | C27: 0.045597 | D27: =(C27*$C$3)*B27/$B$3 -> 77436.813 | F27: 0.045597 | G27: =F27*($C$3/$B$3*B27) -> 77436.813 | I27: 77436.813
A28: 45870 | B28: =VLOOKUP(A28,'INCC - M'!$E:$F,2,FALSE) -> 1205.838 | C28: 0.053645765 | D28: =(C28*$C$3)*B28/$B$3 -> 91938.98 | F28: 0.053645765 | G28: =F28*($C$3/$B$3*B28) -> 91938.98 | I28: 91938.98
A29: 45901 | B29: =VLOOKUP(A29,'INCC - M'!$E:$F,2,FALSE) -> 1214.239 | C29: 0.046000673 | D29: =(C29*$C$3)*B29/$B$3 -> 79385.948 | F29: 0.046000673 | G29: =F29*($C$3/$B$3*B29) -> 79385.948 | I29: 79385.948
A30: 45931 | B30: =VLOOKUP(A30,'INCC - M'!$E:$F,2,FALSE) -> 1216.825 | C30: 0.015312585 | D30: =(C30*$C$3)*B30/$B$3 -> 26482.069 | F30: 0.015312585 | G30: =F30*($C$3/$B$3*B30) -> 26482.069 | I30: 26482.069
A31: 45962 | B31: =VLOOKUP(A31,'INCC - M'!$E:$F,2,FALSE) -> 1219.407 | C31: 0.0073344789 | D31: =(C31*$C$3)*B31/$B$3 -> 12711.395 | F31: 0.0073344789 | G31: =F31*($C$3/$B$3*B31) -> 12711.395 | I31: 12711.395
A32: 45992 | B32: =VLOOKUP(A32,'INCC - M'!$E:$F,2,FALSE) -> 1222.865 | C32: 0.0023121487 | D32: =(C32*$C$3)*B32/$B$3 -> 4018.5517 | F32: 0.0023121487 | G32: =F32*($C$3/$B$3*B32) -> 4018.5517 | I32: 4018.5517

Sheet Varanda ADM
A1: Varanda ADM
B2: Valor Gasto (GRD) | C2: Valor Cobrado
B3: =SUM(B5:B7) -> 389884.1 | C3: =SUM(C5:C7) -> 38988.41
A4: Mês | B4: Valor Gasto (GRD) | C4: Valor Cobrado
A5: 45839 | B5: 389884.1 | C5: =B5*0.1 -> 38988.41
A6: 45870 | C6: =B6*0.08 -> 0
A7: 45901 | C7: =B7*0.08 -> 0
A8: 45931 | C8: =B8*0.08 -> 0
A9: 45962 | C9: =B9*0.08 -> 0
A10: 45992 | C10: =B10*0.08 -> 0
A11: 46023 | C11: =B11*0.08 -> 0

Sheet Posto Campo Largo
A1: Posto Campo Largo | E1: saldo | F1: =F3-C3 -> 0 | G1: =F3-H3 -> 0
B2: Valor Orçado | C2: Valor da Taxa | F2: Valor Previsto Total | H2: Valor Cobrado
B3: 189972.83 | C3: =SUM(C5:C15) -> 189972.83 | F3: =SUM(F5:F15) -> 189972.83 | H3: =SUM(H5:H15) -> 189972.83 | I3: =C3-H3 -> 0
A4: Mês | B4: Medição | C4: Valor da Taxa | E4: Medição Prevista | F4: Valor Previsto | H4: Valor Cobrado
A5: 45809 | B5: 0.15042737 | C5: =B5*$B$3 -> 28577.114 | E5: 0.16184902 | F5: =E5*$B$3 -> 30746.917 | H5: 27356.088
A6: =EDATE(A5,1) -> 45839 | B6: 0.18459344 | C6: =B6*$B$3 -> 35067.739 | E6: 0.19360695 | F6: =E6*$B$3 -> 36780.06 | H6: 37510.258
A7: =EDATE(A6,1) -> 45870 | B7: 0.14861635 | C7: =B7*$B$3 -> 28233.068 | E7: 0.18749134 | F7: =E7*$B$3 -> 35618.261 | H7: 27011.575
A8: =EDATE(A7,1) -> 45901 | B8: 0.15771282 | C8: =B8*$B$3 -> 29961.151 | E8: 0.18062221 | F8: =E8*$B$3 -> 34313.313 | H8: 29961.151
A9: =EDATE(A8,1) -> 45931 | B9: 0.22679016 | C9: =B9*$B$3 -> 43083.97 | E9: 0.12579737 | F9: =E9*$B$3 -> 23898.084 | H9: 43083.97
A10: =EDATE(A9,1) -> 45962 | B10: 0.13185985 | C10: =B10*$B$3 -> 25049.789 | E10: 0.1506331 | F10: =E10*$B$3 -> 28616.197 | H10: 25049.789
A11: =EDATE(A10,1) -> 45992 | C11: =B11*$B$3 -> 0 | F11: =E11*$B$3 -> 0
A12: =EDATE(A11,1) -> 46023 | C12: =B12*$B$3 -> 0 | F12: =E12*$B$3 -> 0
A13: =EDATE(A12,1) -> 46054 | C13: =B13*$B$3 -> 0 | F13: =E13*$B$3 -> 0
A14: =EDATE(A13,1) -> 46082 | C14: =B14*$B$3 -> 0 | F14: =E14*$B$3 -> 0
A15: =EDATE(A14,1) -> 46113 | C15: =B15*$B$3 -> 0 | F15: =E15*$B$3 -> 0

Sheet Solenne
A1: Solenne | H1: OBS: - INCC MÊS ANTERIOR; - EMITE ND NO MÊS; - PAGAMENTO PRÓXIMO MÊS.
A2: Data Base | B2: INCC Base | D2: Valor da Taxa (Orç) | E2: Valor da Taxa (Reaj) | F2: Diferença
A3: 44621 | B3: =VLOOKUP(A3,'INCC - M'!$A:$F,2,FALSE) -> 978.717 | D3: =SUM(D5:D30) -> 2759291 | E3: =SUM(E5:E30) -> 2806222.8 | F3: =SUM(F5:F30) -> 46931.834
A4: Mês | B4: INCC | C4: INCC (Calc) | D4: Valor Base | E4: Valor Reajustado (Cobrado) | F4: Diferença
A5: 44621 | B5: =VLOOKUP(A5,'INCC - M'!$A:$F,2,FALSE) -> 978.717 | C5: - | D5: 118649.51 | E5: =D5 -> 118649.51 | F5: 0
A6: 44652 | B6: =VLOOKUP(A6,'INCC - M'!$A:$F,2,FALSE) -> 987.218 | C6: - | D6: 41389.365 | E6: =D6 -> 41389.365 | F6: =E6-D6 -> 0
A7: 44682 | B7: =VLOOKUP(A7,'INCC - M'!$A:$F,2,FALSE) -> 1001.923 | C7: - | D7: 33111.492 | E7: =D7 -> 33111.492 | F7: =E7-D7 -> 0
A8: 44713 | B8: =VLOOKUP(A8,'INCC - M'!$A:$F,2,FALSE) -> 1030.105 | C8: - | D8: 35870.783 | E8: =D8 -> 35870.783 | F8: =E8-D8 -> 0
A9: 44743 | B9: =VLOOKUP(A9,'INCC - M'!$A:$F,2,FALSE) -> 1042.029 | C9: - | D9: 46907.946 | E9: =D9 -> 46907.946 | F9: =E9-D9 -> 0
A10: 44774 | B10: =VLOOKUP(A10,'INCC - M'!$A:$F,2,FALSE) -> 1045.469 | C10: - | D10: 27592.91 | E10: =D10 -> 27592.91 | F10: =E10-D10 -> 0
A11: 44805 | B11: =VLOOKUP(A11,'INCC - M'!$A:$F,2,FALSE) -> 1046.507 | C11: - | D11: 38906.003 | E11: =D11 -> 38906.003 | F11: =E11-D11 -> 0
A12: 44835 | B12: =VLOOKUP(A12,'INCC - M'!$A:$F,2,FALSE) -> 1046.956 | C12: - | D12: 77536.076 | E12: =D12 -> 77536.076 | F12: =E12-D12 -> 0
A13: 44866 | B13: =VLOOKUP(A13,'INCC - M'!$A:$F,2,FALSE) -> 1048.429 | C13: - | D13: 84986.162 | E13: =D13 -> 84986.162 | F13: =E13-D13 -> 0
A14: 44896 | B14: =VLOOKUP(A14,'INCC - M'!$A:$F,2,FALSE) -> 1051.249 | C14: =B14 -> 1051.249 | D14: 97140.87 | E14: =D14 -> 97140.87 | F14: =E14-D14 -> 0
A15: 44927 | B15: =VLOOKUP(A15,'INCC - M'!$A:$F,2,FALSE) -> 1054.561 | C15: =B15 -> 1054.561 | D15: 134653.4 | E15: 134653.4 | F15: =E15-D15 -> 0
A16: 44958 | B16: =VLOOKUP(A16,'INCC - M'!$A:$F,2,FALSE) -> 1056.775 | C16: =B16 -> 1056.775 | D16: 144034.99 | E16: 144034.99 | F16: =E16-D16 -> 0
A17: 44986 | B17: =VLOOKUP(A17,'INCC - M'!$A:$F,2,FALSE) -> 1058.65 | C17: =B17 -> 1058.65 | D17: 181009.49 | E17: 181009.49 | F17: =E17-D17 -> 0
A18: 45017 | B18: =VLOOKUP(A18,'INCC - M'!$A:$F,2,FALSE) -> 1061.071 | C18: =B17 -> 1058.65 | D18: 122788.45 | E18: 126108.61 | F18: =E18-D18 -> 3320.1629
A19: 45047 | B19: =VLOOKUP(A19,'INCC - M'!$A:$F,2,FALSE) -> 1065.289 | C19: =B18 -> 1061.071 | D19: 107060.49 | E19: =D19*C19/$C$14 -> 108060.77 | F19: =E19-D19 -> 1000.2845
A20: 45078 | B20: =VLOOKUP(A20,'INCC - M'!$A:$F,2,FALSE) -> 1074.292 | C20: =B19 -> 1065.289 | D20: 102369.7 | E20: =D20*C20/$C$14 -> 103736.9 | F20: =E20-D20 -> 1367.2027
A21: 45108 | B21: =VLOOKUP(A21,'INCC - M'!$A:$F,2,FALSE) -> 1074.895 | C21: =B20 -> 1074.292 | D21: 124719.95 | E21: =D21*C21/$C$14 -> 127453.77 | F21: =E21-D21 -> 2733.8165
A22: 45139 | B22: =VLOOKUP(A22,'INCC - M'!$A:$F,2,FALSE) -> 1077.497 | C22: =B21 -> 1074.895 | D22: 125547.74 | E22: =D22*C22/$C$14 -> 128371.72 | F22: =E22-D22 -> 2823.9759
A23: 45170 | B23: =VLOOKUP(A23,'INCC - M'!$A:$F,2,FALSE) -> 1080.071 | C23: =B22 -> 1077.497 | D23: 123616.24 | E23: =D23*C23/$C$14 -> 126702.73 | F23: =E23-D23 -> 3086.499
A24: 45200 | B24: =VLOOKUP(A24,'INCC - M'!$A:$F,2,FALSE) -> 1082.251 | C24: =B23 -> 1080.071 | D24: 119201.37 | E24: =D24*C24/$C$14 -> 122469.5 | F24: =E24-D24 -> 3268.1333
A25: 45231 | B25: =VLOOKUP(A25,'INCC - M'!$A:$F,2,FALSE) -> 1083.335 | C25: =B24 -> 1082.251 | D25: 132445.97 | E25: =D25*C25/$C$14 -> 136351.88 | F25: =E25-D25 -> 3905.9156
A26: 45261 | B26: =VLOOKUP(A26,'INCC - M'!$A:$F,2,FALSE) -> 1086.15 | C26: =B25 -> 1083.335 | D26: 176318.69 | E26: =D26*C26/$C$14 -> 181700.26 | F26: =E26-D26 -> 5381.5619
A27: 45292 | B27: =VLOOKUP(A27,'INCC - M'!$A:$F,2,FALSE) -> 1088.663 | C27: =B26 -> 1086.15 | D27: 204187.53 | E27: =D27*C27/$C$14 -> 210966.47 | F27: =E27-D27 -> 6778.9354
A28: 45323 | B28: =VLOOKUP(A28,'INCC - M'!$A:$F,2,FALSE) -> 1090.871 | C28: =B27 -> 1088.663 | D28: 199220.81 | E28: =D28*C28/$C$14 -> 206311.09 | F28: =E28-D28 -> 7090.2777
A29: 45352 | B29: =VLOOKUP(A29,'INCC - M'!$A:$F,2,FALSE) -> 1093.503 | C29: =B28 -> 1090.871 | D29: 102645.62 | E29: =D29*C29/$C$14 -> 106514.38 | F29: =E29-D29 -> 3868.7551
A30: 45383 | B30: =VLOOKUP(A30,'INCC - M'!$A:$F,2,FALSE) -> 1097.991 | C30: =B29 -> 1093.503 | D30: 57379.422 | E30: =D30*C30/$C$14 -> 59685.736 | F30: =E30-D30 -> 2306.3138
F31: Finalizado

Sheet Origens
A1: Origens | H1: OBS: - INCC MÊS ANTERIOR; - EMITE ND NO MÊS; - PAGAMENTO PRÓXIMO MÊS.
A2: Data Base | B2: INCC Base | D2: Valor da Taxa (Orç) | E2: Valor da Taxa (Reaj) | F2: Diferença
A3: 45078 | B3: =VLOOKUP(A3,'INCC - M'!$A:$F,2,FALSE) -> 1074.292 | D3: =SUM(D5:D17) -> 554326.25 | E3: =SUM(E5:E17) -> 562363.6 | F3: =SUM(F5:F17) -> 8037.3508
A4: Mês | B4: INCC | C4: INCC (Calc) | D4: Valor Base | E4: Valor Reajustado (Cobrado) | F4: Diferença
A5: 45108 | B5: =VLOOKUP(A5,'INCC - M'!$A:$F,2,FALSE) -> 1074.895
A6: 45139 | B6: =VLOOKUP(A6,'INCC - M'!$A:$F,2,FALSE) -> 1077.497 | C6: =B5 -> 1074.895 | D6: 33543.403 | E6: =D6*C6/$B$3 -> 33562.23 | F6: =E6-D6 -> 18.827909
A7: 45170 | B7: =VLOOKUP(A7,'INCC - M'!$A:$F,2,FALSE) -> 1080.071 | C7: =B6 -> 1077.497 | D7: 11596.168 | E7: =D7*C7/$B$3 -> 11630.763 | F7: =E7-D7 -> 34.595545
A8: 45200 | B8: =VLOOKUP(A8,'INCC - M'!$A:$F,2,FALSE) -> 1082.251 | C8: =B7 -> 1080.071 | D8: 51020.724 | E8: =D8*C8/$B$3 -> 51295.182 | F8: =E8-D8 -> 274.45868
A9: 45231 | B9: =VLOOKUP(A9,'INCC - M'!$A:$F,2,FALSE) -> 1083.335 | C9: =B8 -> 1082.251 | D9: 62448.698 | E9: =D9*C9/$B$3 -> 62911.356 | F9: =E9-D9 -> 462.65744
A10: 45261 | B10: =VLOOKUP(A10,'INCC - M'!$A:$F,2,FALSE) -> 1086.15 | C10: =B9 -> 1083.335 | D10: 74220.114 | E10: =D10*C10/$B$3 -> 74844.872 | F10: =E10-D10 -> 624.75797
A11: 45292 | B11: =VLOOKUP(A11,'INCC - M'!$A:$F,2,FALSE) -> 1088.663 | C11: =B10 -> 1086.15 | D11: 61711.735 | E11: =D11*C11/$B$3 -> 62392.907 | F11: =E11-D11 -> 681.17211
A12: 45323 | B12: =VLOOKUP(A12,'INCC - M'!$A:$F,2,FALSE) -> 1090.871 | C12: =B11 -> 1088.663 | D12: 40896.72 | E12: =D12*C12/$B$3 -> 41443.802 | F12: =E12-D12 -> 547.08288
A13: 45352 | B13: =VLOOKUP(A13,'INCC - M'!$A:$F,2,FALSE) -> 1093.503 | C13: =B12 -> 1090.871 | D13: 49484.777 | E13: =D13*C13/$B$3 -> 50248.45 | F13: =E13-D13 -> 763.6733
A14: 45383 | B14: =VLOOKUP(A14,'INCC - M'!$A:$F,2,FALSE) -> 1097.991 | C14: =B13 -> 1093.503 | D14: 19265.095 | E14: =D14*C14/$B$3 -> 19609.603 | F14: =E14-D14 -> 344.50759
A15: 45413 | B15: =VLOOKUP(A15,'INCC - M'!$A:$F,2,FALSE) -> 1104.457 | C15: =B14 -> 1097.991 | D15: 52699.345 | E15: =D15*C15/$B$3 -> 53861.898 | F15: =E15-D15 -> 1162.5534
A16: 45444 | B16: =VLOOKUP(A16,'INCC - M'!$A:$F,2,FALSE) -> 1114.748 | C16: =B15 -> 1104.457 | D16: 57033.187 | E16: =D16*C16/$B$3 -> 58634.62 | F16: =E16-D16 -> 1601.4325
A17: 45474 | B17: =VLOOKUP(A17,'INCC - M'!$A:$F,2,FALSE) -> 1122.452 | C17: =B16 -> 1114.748 | D17: 40406.282 | E17: =D17*C17/$B$3 -> 41927.914 | F17: =E17-D17 -> 1521.6315
E18: Finalizado

Sheet Comporta Demolição
A1: Comporta | F1: OBS: - INCC MÊS ANTERIOR; - EMITE ND NO MÊS; - PAGAMENTO PRÓXIMO MÊS.
A2: CONTRATO FAS | B2: Valor da Taxa (Orç) | C2: Saldo
B3: 166555.46 | C3: =B3-B5-B6-B7-B8-B9 -> 0.00039999999
A4: Mês | B4: Valor Cobrado
A5: 45292 | B5: 38174.58
A6: 45323 | B6: 31694.34
A7: 45352 | B7: =D7*0.08 -> 34253.35 | C7: Medição Miguel | D7: =64225.03+363941.84 -> 428166.87 | G7: Valor contrato FAS | I7: 2081943.3
A8: 45383 | B8: =D8*0.08 -> 26312 | C8: Medição Miguel | D8: =49335+279565 -> 328900 | G8: Contrato Piemonte 8% | I8: =I7*0.08 -> 166555.46
A9: 45413 | B9: 36121.19 | C9: Medição Miguel | D9: =48287.41+337378.64+11250 -> 396916.05
B10: Finalizado

Sheet Shopping
A1: Floripa Shopping | H1: OBS: - VALOR FIXO; - EMITE ATÉ DIA 17; - PAGAMENTO NO DIA 5 PRÓXIMO MÊS; - LANÇA NO PROTHEUS; - FAZ MEDIÇÃO NO RM.
A2: Data Base | B2: INCC Base | D2: Valor da Taxa (Orç) | E2: Valor da Taxa (Reaj) | F2: Diferença
A3: - | B3: - | D3: =SUM(D5:D21) -> 2715452.9 | E3: =SUM(E5:E21) -> 2715452.9 | F3: =SUM(F5:F14) -> 0
A4: Mês | B4: INCC | C4: INCC (Calc) | D4: Valor Base | E4: Valor Reajustado (Cobrado) | F4: Diferença
A5: 45017 | B5: - | C5: =B5 -> - | D5: 194565.89 | E5: =D5 -> 194565.89 | F5: =E5-D5 -> 0
A6: 45047 | B6: - | C6: =B5 -> - | D6: 194565.89 | E6: =D6 -> 194565.89 | F6: =E6-D6 -> 0
A7: 45078 | B7: - | C7: =B6 -> - | D7: 200065.89 | E7: =D7 -> 200065.89 | F7: =E7-D7 -> 0
A8: 45108 | B8: - | C8: =B7 -> - | D8: 200065.89 | E8: =D8 -> 200065.89 | F8: =E8-D8 -> 0
A9: 45139 | B9: - | C9: =B8 -> - | D9: 200065.89 | E9: =D9 -> 200065.89 | F9: =E9-D9 -> 0
A10: 45170 | B10: - | C10: =B9 -> - | D10: 200065.89 | E10: =D10 -> 200065.89 | F10: =E10-D10 -> 0
A11: 45200 | B11: - | C11: =B10 -> - | D11: 200065.89 | E11: =D11 -> 200065.89 | F11: =E11-D11 -> 0
A12: 45231 | B12: - | C12: =B11 -> - | D12: 200065.89 | E12: =D12 -> 200065.89 | F12: =E12-D12 -> 0
A13: 45261 | B13: - | C13: =B12 -> - | D13: 200065.89 | E13: =D13 -> 200065.89 | F13: =E13-D13 -> 0
A14: 45292 | B14: - | C14: =B13 -> - | D14: 200065.89 | E14: =D14 -> 200065.89 | F14: =E14-D14 -> 0
A15: 45323 | B15: - | C15: - | D15: 72753.84 | E15: =D15 -> 72753.84 | F15: =E15-D15 -> 0
A16: 45352 | B16: - | C16: - | D16: 150468.19 | E16: =D16 -> 150468.19 | F16: =E16-D16 -> 0
A17: 45383 | B17: - | C17: - | D17: 150468.19 | E17: =D17 -> 150468.19 | F17: =E17-D17 -> 0
A18: 45413 | B18: - | C18: - | D18: 150468.19 | E18: =D18 -> 150468.19 | F18: =E18-D18 -> 0
A19: 45444 | B19: - | C19: - | D19: 66053.24 | E19: =D19 -> 66053.24 | F19: =E19-D19 -> 0
A20: 45474 | B20: - | C20: - | D20: 67791.18 | E20: =D20 -> 67791.18 | F20: =E20-D20 -> 0
A21: 45505 | B21: - | C21: - | D21: 67791.18 | E21: =D21 -> 67791.18 | F21: =E21-D21 -> 0
E22: Finalizado

Sheet Vizione
A1: Vizione | H1: OBS: - INCC MÊS ANTERIOR; - EMITE ND NO MÊS; - PAGAMENTO PRÓXIMO MÊS.
A2: Data Base | B2: INCC Base | D2: Valor da Taxa (Orç) | E2: Valor da Taxa (Reaj) | F2: Diferença
A3: 44470 | B3: =VLOOKUP(A3,'INCC - M'!$A:$F,2,FALSE) -> 951.249 | D3: =SUM(D5:D30) -> 2544559.8 | E3: =SUM(E5:E30) -> 2568942.7 | F3: =SUM(F5:F30) -> 24382.874
A4: Mês | B4: INCC | C4: INCC (Calc) | D4: Valor Base | E4: Valor Reajustado (Cobrado) | F4: Diferença
A5: 44470 | B5: =VLOOKUP(A5,'INCC - M'!$A:$F,2,FALSE) -> 951.249 | C5: - | D5: 99237.832 | E5: =D5 -> 99237.832 | F5: 0
A6: 44501 | B6: =VLOOKUP(A6,'INCC - M'!$A:$F,2,FALSE) -> 957.984 | C6: - | D6: 66158.555 | E6: =D6 -> 66158.555 | F6: =E6-D6 -> 0
A7: 44531 | B7: =VLOOKUP(A7,'INCC - M'!$A:$F,2,FALSE) -> 960.894 | C7: - | D7: 43257.516 | E7: =D7 -> 43257.516 | F7: =E7-D7 -> 0
A8: 44562 | B8: =VLOOKUP(A8,'INCC - M'!$A:$F,2,FALSE) -> 967.003 | C8: - | D8: 33079.277 | E8: =D8 -> 33079.277 | F8: =E8-D8 -> 0
A9: 44593 | B9: =VLOOKUP(A9,'INCC - M'!$A:$F,2,FALSE) -> 971.651 | C9: - | D9: 40712.957 | E9: =D9 -> 40712.957 | F9: =E9-D9 -> 0
A10: 44621 | B10: =VLOOKUP(A10,'INCC - M'!$A:$F,2,FALSE) -> 978.717 | C10: - | D10: 33079.277 | E10: =D10 -> 33079.277 | F10: =E10-D10 -> 0
A11: 44652 | B11: =VLOOKUP(A11,'INCC - M'!$A:$F,2,FALSE) -> 987.218 | C11: - | D11: 48346.636 | E11: =D11 -> 48346.636 | F11: =E11-D11 -> 0
A12: 44682 | B12: =VLOOKUP(A12,'INCC - M'!$A:$F,2,FALSE) -> 1001.923 | C12: - | D12: 86515.033 | E12: =D12 -> 86515.033 | F12: =E12-D12 -> 0
A13: 44713 | B13: =VLOOKUP(A13,'INCC - M'!$A:$F,2,FALSE) -> 1030.105 | C13: - | D13: 58524.875 | E13: =D13 -> 58524.875 | F13: =E13-D13 -> 0
A14: 44743 | B14: =VLOOKUP(A14,'INCC - M'!$A:$F,2,FALSE) -> 1042.029 | C14: - | D14: 71247.674 | E14: =D14 -> 71247.674 | F14: =E14-D14 -> 0
A15: 44774 | B15: =VLOOKUP(A15,'INCC - M'!$A:$F,2,FALSE) -> 1045.469 | C15: - | D15: 50891.196 | E15: =D15 -> 50891.196 | F15: =E15-D15 -> 0
A16: 44805 | B16: =VLOOKUP(A16,'INCC - M'!$A:$F,2,FALSE) -> 1046.507 | C16: - | D16: 90331.873 | E16: =D16 -> 90331.873 | F16: =E16-D16 -> 0
A17: 44835 | B17: =VLOOKUP(A17,'INCC - M'!$A:$F,2,FALSE) -> 1046.956 | C17: - | D17: 94148.712 | E17: =D17 -> 94148.712 | F17: =E17-D17 -> 0
A18: 44866 | B18: =VLOOKUP(A18,'INCC - M'!$A:$F,2,FALSE) -> 1048.429 | C18: - | D18: 75318.97 | E18: =D18 -> 75318.97 | F18: =E18-D18 -> 0
A19: 44896 | B19: =VLOOKUP(A19,'INCC - M'!$A:$F,2,FALSE) -> 1051.249 | C19: 1051.249 | D19: 154709.24 | E19: =D19 -> 154709.24 | F19: =E19-D19 -> 0
A20: 44927 | B20: =VLOOKUP(A20,'INCC - M'!$A:$F,2,FALSE) -> 1054.561 | C20: 1054.561 | D20: 108398.25 | E20: =D20*C20/$C$19 -> 108739.76 | F20: =E20-D20 -> 341.51281
A21: 44958 | B21: =VLOOKUP(A21,'INCC - M'!$A:$F,2,FALSE) -> 1056.775 | C21: 1056.775 | D21: 130027.01 | E21: =D21*C21/$C$19 -> 130710.51 | F21: =E21-D21 -> 683.50054
A22: 44986 | B22: =VLOOKUP(A22,'INCC - M'!$A:$F,2,FALSE) -> 1058.65 | C22: 1058.65 | D22: 119848.77 | E22: =D22*C22/$C$19 -> 120692.53 | F22: =E22-D22 -> 843.75894
A23: 45017 | B23: =VLOOKUP(A23,'INCC - M'!$A:$F,2,FALSE) -> 1061.071 | C23: =B22 -> 1058.65 | D23: 119848.77 | E23: =D23*C23/$C$19 -> 120692.53 | F23: =E23-D23 -> 843.75894
A24: 45047 | B24: =VLOOKUP(A24,'INCC - M'!$A:$F,2,FALSE) -> 1065.289 | C24: =B23 -> 1061.071 | D24: 125192.34 | E24: =D24*C24/$C$19 -> 126362.04 | F24: =E24-D24 -> 1169.6936
A25: 45078 | B25: =VLOOKUP(A25,'INCC - M'!$A:$F,2,FALSE) -> 1074.292 | C25: =B24 -> 1065.289 | D25: 162851.83 | E25: =D25*C25/$C$19 -> 165026.8 | F25: =E25-D25 -> 2174.9744
A26: 45108 | B26: =VLOOKUP(A26,'INCC - M'!$A:$F,2,FALSE) -> 1074.895 | C26: =B25 -> 1074.292 | D26: 154709.24 | E26: =D26*C26/$C$19 -> 158100.41 | F26: =E26-D26 -> 3391.1708
A27: 45139 | B27: =VLOOKUP(A27,'INCC - M'!$A:$F,2,FALSE) -> 1077.497 | C27: 1074.895 | D27: 142240.89 | E27: =D27*C27/$C$19 -> 145440.35 | F27: =E27-D27 -> 3199.4591
A28: 45170 | B28: =VLOOKUP(A28,'INCC - M'!$A:$F,2,FALSE) -> 1080.071 | C28: =B27 -> 1077.497 | D28: 173793.43 | E28: =D28*C28/$C$19 -> 178132.78 | F28: =E28-D28 -> 4339.3431
A29: 45200 | B29: =VLOOKUP(A29,'INCC - M'!$A:$F,2,FALSE) -> 1082.251 | C29: =B28 -> 1080.071 | D29: 160816.18 | E29: =D29*C29/$C$19 -> 165225.26 | F29: =E29-D29 -> 4409.0828
A30: 45231 | B30: =VLOOKUP(A30,'INCC - M'!$A:$F,2,FALSE) -> 1083.335 | C30: =B29 -> 1082.251 | D30: 101273.48 | E30: =D30*C30/$C$19 -> 104260.1 | F30: =E30-D30 -> 2986.6192
F31: Finalizado

Sheet PDV Buenos Aires
A1: PDV Buenos Aires
A2: Data Base | B2: INCC Base | D2: Valor da Taxa (Orç) | E2: Valor da Taxa (Reaj)
A3: - | B3: - | D3: =SUM(D5:D11) -> 1529549.4 | E3: =SUM(E5:E11) -> 122363.95
A4: Mês | B4: INCC | C4: INCC (Calc) | D4: Valor Gasto (GRD) | E4: Valor Reajustado (Cobrado)
A5: 45078 | B5: - | C5: - | D5: 266496.71 | E5: =D5*0.08 -> 21319.737
A6: 45108 | B6: - | C6: =B5 -> - | D6: 357316.6 | E6: =D6*0.08 -> 28585.328
A7: 45139 | B7: - | C7: =B6 -> - | D7: 379200.49 | E7: =D7*0.08 -> 30336.039
A8: 45170 | B8: - | C8: =B7 -> - | D8: 217630.49 | E8: =D8*0.08 -> 17410.439
A9: 45200 | B9: - | C9: - | D9: 308905.13 | E9: =D9*0.08 -> 24712.41

Sheet Manacás
A1: Jardim dos Manacás | H1: OBS: - INCC M MÊS ANTERIOR; - EMITE ND NO MÊS; - PAGAMENTO PRÓXIMO MÊS.
A2: Data Base | B2: INCC Base | D2: Valor da Taxa (Orç) | E2: Valor da Taxa (Reaj) | F2: Diferença
A3: 44378 | B3: =VLOOKUP(A3,'INCC - M'!$A:$F,2,FALSE) -> 933.23 | D3: =SUM(D5:D34) -> 4028195.1 | E3: =SUM(E5:E34) -> 4105210.9 | F3: =SUM(F5:F34) -> 77015.82
A4: Mês | B4: INCC | C4: INCC (Calc) | D4: Valor Base | E4: Valor Reajustado (Cobrado) | F4: Diferença
A5: 44682 | B5: =VLOOKUP(A5,'INCC - M'!$A:$F,2,FALSE) -> 1001.923 | C5: - | D5: 32224.207 | E5: 32224.207 | F5: 0
A6: 44713 | B6: =VLOOKUP(A6,'INCC - M'!$A:$F,2,FALSE) -> 1030.105 | C6: - | D6: 36252.233 | E6: 36252.233 | F6: =E6-D6 -> 0
A7: 44743 | B7: =VLOOKUP(A7,'INCC - M'!$A:$F,2,FALSE) -> 1042.029 | C7: - | D7: 92644.596 | E7: 92644.596 | F7: =E7-D7 -> 0
A8: 44774 | B8: =VLOOKUP(A8,'INCC - M'!$A:$F,2,FALSE) -> 1045.469 | C8: - | D8: 84991.347 | E8: 84991.347 | F8: =E8-D8 -> 0
A9: 44805 | B9: =VLOOKUP(A9,'INCC - M'!$A:$F,2,FALSE) -> 1046.507 | C9: - | D9: 33835.418 | E9: 33835.418 | F9: =E9-D9 -> 0
A10: 44835 | B10: =VLOOKUP(A10,'INCC - M'!$A:$F,2,FALSE) -> 1046.956 | C10: - | D10: 109965.11 | E10: 109965.11 | F10: =E10-D10 -> 0
A11: 44866 | B11: =VLOOKUP(A11,'INCC - M'!$A:$F,2,FALSE) -> 1048.429 | C11: - | D11: 174816.33 | E11: 174816.33 | F11: =E11-D11 -> 0
A12: 44896 | B12: =VLOOKUP(A12,'INCC - M'!$A:$F,2,FALSE) -> 1051.249 | C12: =B12 -> 1051.249 | D12: 125674.41 | E12: 125674.41 | F12: =E12-D12 -> 0
A13: 44927 | B13: =VLOOKUP(A13,'INCC - M'!$A:$F,2,FALSE) -> 1054.561 | C13: =B13 -> 1054.561 | D13: 186094.8 | E13: =D13 -> 186094.8 | F13: =E13-D13 -> 0
A14: 44958 | B14: =VLOOKUP(A14,'INCC - M'!$A:$F,2,FALSE) -> 1056.775 | C14: =B14 -> 1056.775 | D14: 178844.35 | E14: =D14 -> 178844.35 | F14: =E14-D14 -> 0
A15: 44986 | B15: =VLOOKUP(A15,'INCC - M'!$A:$F,2,FALSE) -> 1058.65 | C15: =B15 -> 1058.65 | D15: 165551.87 | E15: =D15 -> 165551.87 | F15: =E15-D15 -> 0
A16: 45017 | B16: =VLOOKUP(A16,'INCC - M'!$A:$F,2,FALSE) -> 1061.071 | C16: =B15 -> 1058.65 | D16: 193345.24 | E16: 197398.36 | F16: =E16-D16 -> 4053.1191
A17: 45047 | B17: =VLOOKUP(A17,'INCC - M'!$A:$F,2,FALSE) -> 1065.289 | C17: =B16 -> 1061.071 | D17: 225569.45 | E17: =D17*C17/$C$12 -> 227676.99 | F17: =E17-D17 -> 2107.5341
A18: 45078 | B18: =VLOOKUP(A18,'INCC - M'!$A:$F,2,FALSE) -> 1074.292 | C18: =B17 -> 1065.289 | D18: 239264.74 | E18: =D18*C18/$C$12 -> 242460.25 | F18: =E18-D18 -> 3195.5102
A19: 45108 | B19: =VLOOKUP(A19,'INCC - M'!$A:$F,2,FALSE) -> 1074.895 | C19: =B18 -> 1074.292 | D19: 259404.87 | E19: =D19*C19/$C$12 -> 265090.93 | F19: =E19-D19 -> 5686.0614
A20: 45139 | B20: =VLOOKUP(A20,'INCC - M'!$A:$F,2,FALSE) -> 1077.497 | C20: =B19 -> 1074.895 | D20: 248529.2 | E20: =D20*C20/$C$12 -> 254119.43 | F20: =E20-D20 -> 5590.2279
A21: 45170 | B21: =VLOOKUP(A21,'INCC - M'!$A:$F,2,FALSE) -> 1080.071 | C21: =B20 -> 1077.497 | D21: 244903.98 | E21: =D21*C21/$C$12 -> 251018.83 | F21: =E21-D21 -> 6114.8591
A22: 45200 | B22: =VLOOKUP(A22,'INCC - M'!$A:$F,2,FALSE) -> 1082.251 | C22: =B21 -> 1080.071 | D22: 221944.23 | E22: =D22*C22/$C$12 -> 228029.25 | F22: =E22-D22 -> 6085.0251
A23: 45231 | B23: =VLOOKUP(A23,'INCC - M'!$A:$F,2,FALSE) -> 1083.335 | C23: =B22 -> 1082.251 | D23: 201804.1 | E23: =D23*C23/$C$12 -> 207755.43 | F23: =E23-D23 -> 5951.3309
A24: 45261 | B24: =VLOOKUP(A24,'INCC - M'!$A:$F,2,FALSE) -> 1086.15 | C24: =B23 -> 1083.335 | D24: 186900.4 | E24: =D24*C24/$C$12 -> 192604.94 | F24: =E24-D24 -> 5704.5346
A25: 45292 | B25: =VLOOKUP(A25,'INCC - M'!$A:$F,2,FALSE) -> 1088.663 | C25: =B24 -> 1086.15 | D25: 188108.81 | E25: =D25*C25/$C$12 -> 194353.94 | F25: =E25-D25 -> 6245.129
A26: 45323 | B26: =VLOOKUP(A26,'INCC - M'!$A:$F,2,FALSE) -> 1090.871 | C26: =B25 -> 1088.663 | D26: 140175.3 | E26: =D26*C26/$C$12 -> 145164.15 | F26: =E26-D26 -> 4988.8454
A27: 45352 | B27: =VLOOKUP(A27,'INCC - M'!$A:$F,2,FALSE) -> 1093.503 | C27: =B26 -> 1090.871 | D27: 126480.01 | E27: =D27*C27/$C$12 -> 131247.1 | F27: =E27-D27 -> 4767.0829
A28: 45383 | B28: =VLOOKUP(A28,'INCC - M'!$A:$F,2,FALSE) -> 1097.991 | C28: =B27 -> 1093.503 | D28: 136550.08 | E28: =D28*C28/$C$12 -> 142038.59 | F28: =E28-D28 -> 5488.5065
... A34: 45566 | B34: =VLOOKUP(A34,'INCC - M'!$A:$F,2,FALSE) -> 1144.136 | C34: =B33 -> 1136.521 | D34: 201.4013 | E34: =D34*C34/$C$12 -> 217.73795 | F34: =E34-D34 -> 16.336654
F35: Finalizado

Sheet Reforma Nova Frota
A1: Reforma Nova Frota
A2: Data Base | B2: INCC Base | C2: Valor Orçado | D2: Valor da Taxa (Reaj) | G2: Valor Previsto Total | I2: Valor Cobrado
A3: 44986 | B3: 1065.289 | C3: 69146.988 | D3: =SUM(D5:D15) -> 78561.513 | G3: =SUM(G5:G15) -> 78267.974 | I3: =SUM(I5:I15) -> 78561.513 | J3: =D3-I3 -> 0
A4: Mês | B4: INCC M (n-1) | C4: Medição | D4: Valor da Taxa (Reaj) | F4: Medição Prevista | G4: Valor Previsto | I4: Valor Cobrado
A5: 45809 | B5: =VLOOKUP(A5,'INCC - M'!$E:$F,2,FALSE) -> 1183.606 | C5: 0.19240752 | D5: =(C5*$C$3)*B5/$B$3 -> 14782.062 | F5: 0.19240752 | G5: =F5*($C$3/$B$3*B5) -> 14782.062 | I5: 14782.062
A6: =EDATE(A5,1) -> 45839 | B6: =VLOOKUP(A6,'INCC - M'!$E:$F,2,FALSE) -> 1194.912 | C6: 0.050599828 | D6: =(C6*$C$3)*B6/$B$3 -> 3924.5583 | F6: 0.050599828 | G6: =F6*($C$3/$B$3*B6) -> 3924.5583 | I6: 18706.62
A7: =EDATE(A6,1) -> 45870 | B7: =VLOOKUP(A7,'INCC - M'!$E:$F,2,FALSE) -> 1205.838 | C7: 0.087929501 | D7: =(C7*$C$3)*B7/$B$3 -> 6882.2334 | F7: 0.23602547 | G7: =F7*($C$3/$B$3*B7) -> 18473.691 | I7: 0
A8: =EDATE(A7,1) -> 45901 | B8: =VLOOKUP(A8,'INCC - M'!$E:$F,2,FALSE) -> 1214.239 | C8: 0.099331674 | D8: =(C8*$C$3)*B8/$B$3 -> 7828.8462 | F8: 0.35696451 | G8: =F8*($C$3/$B$3*B8) -> 28134.231 | I8: 0
A9: =EDATE(A8,1) -> 45931 | B9: =VLOOKUP(A9,'INCC - M'!$E:$F,2,FALSE) -> 1216.825 | C9: 0.26634203 | D9: =(C9*$C$3)*B9/$B$3 -> 21036.509 | F9: 0.16400267 | G9: =F9*($C$3/$B$3*B9) -> 12953.432 | I9: 20965.526
A10: =EDATE(A9,1) -> 45962 | B10: =VLOOKUP(A10,'INCC - M'!$E:$F,2,FALSE) -> 1219.407 | C10: 0.077445685 | D10: =(C10*$C$3)*B10/$B$3 -> 6129.8766 | G10: =F10*($C$3/$B$3*B10) -> 0 | I10: 6129.8766
A11: =EDATE(A10,1) -> 45992 | B11: =VLOOKUP(A11,'INCC - M'!$E:$F,2,FALSE) -> 1222.865 | C11: 0.12271396 | D11: =(C11*$C$3)*B11/$B$3 -> 9740.4341 | G11: =F11*($C$3/$B$3*B11) -> 0 | I11: 9740.4341
A12: =EDATE(A11,1) -> 46023 | B12: =VLOOKUP(A12,'INCC - M'!$E:$F,2,FALSE) -> 1225.398 | C12: 0.07855405 | D12: =(C12*$C$3)*B12/$B$3 -> 6248.1518 | G12: =F12*($C$3/$B$3*B12) -> 0 | I12: 6248.1518
A13: =EDATE(A12,1) -> 46054 | B13: =VLOOKUP(A13,'INCC - M'!$E:$F,2,FALSE) -> 1233.096 | C13: 0 | D13: =(C13*$C$3)*B13/$B$3 -> 0 | G13: =F13*($C$3/$B$3*B13) -> 0 | I13: 0
A14: =EDATE(A13,1) -> 46082 | B14: =VLOOKUP(A14,'INCC - M'!$E:$F,2,FALSE) -> 1237.312 | C14: 0 | D14: =(C14*$C$3)*B14/$B$3 -> 0 | G14: =F14*($C$3/$B$3*B14) -> 0 | I14: 0
A15: =EDATE(A14,1) -> 46113 | B15: =VLOOKUP(A15,'INCC - M'!$E:$F,2,FALSE) -> 1241.721 | C15: 0.02467575 | D15: =(C15*$C$3)*B15/$B$3 -> 1988.8417 | G15: =F15*($C$3/$B$3*B15) -> 0 | I15: 1988.8417

Sheet GLB
A1: GLB | H1: saldo | I1: =I3-D3 -> 4425155.1 | J1: =I3-K3 -> 4424539.6 | R1: R$
A2: Data Base | B2: INCC Base | C2: Valor Orçado c/ Aditivos | D2: Valor da Taxa (Reaj) | E2: Valor Permuta (Reaj) | F2: Valor Liquido (Reaj) | I2: Valor Previsto Total | K2: Valor Cobrado | L2: Valor Cobrado Permuta | M2: Valor Cobrado Liquido | Q2: Valor Orçado | R2: 4369317
A3: 45931 | B3: =VLOOKUP(A3,'INCC - M'!$E:$F,2,FALSE) -> 1216.825 | C3: 4369317 | D3: =SUM(D5:D34) -> 114617.69 | E3: =SUM(E5:E34) -> 56247.086 | F3: =SUM(F5:F34) -> 58370.602 | I3: =SUM(I5:I34) -> 4539772.8 | K3: =SUM(K5:K34) -> 115233.2 | L3: =SUM(L5:L34) -> 56247.41 | M3: =SUM(M5:M34) -> 58985.8 | N3: =D3-K3 -> -615.5101 | O3: =E3-L3 -> -0.32392326 | P3: =F3-M3 -> -615.19847 | Q3: Valor Permuta | R3: 2144183.4
A4: Mês | B4: INCC DI (n-1) | C4: Medição | D4: Valor da Taxa (Reaj) | E4: Valor Permuta (Reaj) | F4: Valor Liquido (Reaj) | H4: Medição Prevista | I4: Valor Previsto | K4: Valor Cobrado | L4: Valor Cobrado Permuta | M4: Valor Cobrado Liquido | Q4: % | R4: =R3/R2 -> 0.49073653
A5: 46143 | B5: =VLOOKUP(A5,'INCC - M'!$E:$F,2,FALSE) -> 1254.655 | C5: 0.007 | D5: =(C5*$C$3)*B5/$B$3 -> 31536.086 | E5: =D5*$R$4 -> 15475.909 | F5: =D5-E5 -> 16060.177 | H5: 0.0059 | I5: =H5*($C$3/$B$3*B5) -> 26580.415 | K5: 31705.258 | L5: 15475.91 | M5: 16229.35
A6: =EDATE(A5,1) -> 46174 | B6: =VLOOKUP(A6,'INCC - M'!$E:$F,2,FALSE) -> 1264.353 | C6: 0.0183 | D6: =(C6*$C$3)*B6/$B$3 -> 83081.602 | E6: =D6*$R$4 -> 40771.177 | F6: =D6-E6 -> 42310.425 | H6: 0.0189 | I6: =H6*($C$3/$B$3*B6) -> 85805.589 | K6: 83527.94 | L6: 40771.5 | M6: 42756.45
A7: =EDATE(A6,1) -> 46204 | B7: =VLOOKUP(A7,'INCC - M'!$E:$F,2,FALSE) -> 1264.353 | D7: =(C7*$C$3)*B7/$B$3 -> 0 | E7: =D7*$R$4 -> 0 | F7: =D7-E7 -> 0 | H7: 0.0191 | I7: =H7*($C$3/$B$3*B7) -> 86713.584 | J7: =(H7*$I$1/(SUM($H$7:$H$34))) -> 86669.875
A8: =EDATE(A7,1) -> 46235 | B8: =VLOOKUP(A8,'INCC - M'!$E:$F,2,FALSE) -> 1264.353 | D8: =(C8*$C$3)*B8/$B$3 -> 0 | E8: =D8*$R$4 -> 0 | F8: =D8-E8 -> 0 | H8: 0.0178 | I8: =H8*($C$3/$B$3*B8) -> 80811.613 | J8: =(H8*$I$1/(SUM($H$6:$H$35))) -> 79235.249
A9: =EDATE(A8,1) -> 46266 | B9: =VLOOKUP(A9,'INCC - M'!$E:$F,2,FALSE) -> 1264.353 | D9: =(C9*$C$3)*B9/$B$3 -> 0 | E9: =D9*$R$4 -> 0 | F9: =D9-E9 -> 0 | H9: 0.0129 | I9: =H9*($C$3/$B$3*B9) -> 58565.719 | J9: =(H9*$I$1/(SUM($H$6:$H$35))) -> 57423.298
A10: =EDATE(A9,1) -> 46296 | B10: =VLOOKUP(A10,'INCC - M'!$E:$F,2,FALSE) -> 1264.353 | D10: =(C10*$C$3)*B10/$B$3 -> 0 | E10: =D10*$R$4 -> 0 | F10: =D10-E10 -> 0 | H10: 0.0138 | I10: =H10*($C$3/$B$3*B10) -> 62651.7 | J10: =(H10*$I$1/(SUM($H$6:$H$35))) -> 61429.575
A11: =EDATE(A10,1) -> 46327 | B11: =VLOOKUP(A11,'INCC - M'!$E:$F,2,FALSE) -> 1264.353 | D11: =(C11*$C$3)*B11/$B$3 -> 0 | E11: =D11*$R$4 -> 0 | F11: =D11-E11 -> 0 | H11: 0.0244 | I11: =H11*($C$3/$B$3*B11) -> 110775.47 | J11: =(H11*$I$1/(SUM($H$6:$H$35))) -> 108614.61
A12: =EDATE(A11,1) -> 46357 | B12: =VLOOKUP(A12,'INCC - M'!$E:$F,2,FALSE) -> 1264.353 | D12: =(C12*$C$3)*B12/$B$3 -> 0 | E12: =D12*$R$4 -> 0 | F12: =D12-E12 -> 0 | H12: 0.0216 | I12: =H12*($C$3/$B$3*B12) -> 98063.53 | J12: =(H12*$I$1/(SUM($H$6:$H$35))) -> 96150.639
A13: =EDATE(A12,1) -> 46388 | B13: =VLOOKUP(A13,'INCC - M'!$E:$F,2,FALSE) -> 1264.353 | D13: =(C13*$C$3)*B13/$B$3 -> 0 | E13: =D13*$R$4 -> 0 | F13: =D13-E13 -> 0 | H13: 0.021 | I13: =H13*($C$3/$B$3*B13) -> 95339.543 | J13: =(H13*$I$1/(SUM($H$6:$H$35))) -> 93479.788
A14: =EDATE(A13,1) -> 46419 | B14: =VLOOKUP(A14,'INCC - M'!$E:$F,2,FALSE) -> 1264.353 | D14: =(C14*$C$3)*B14/$B$3 -> 0 | E14: =D14*$R$4 -> 0 | F14: =D14-E14 -> 0 | H14: 0.0242 | I14: =H14*($C$3/$B$3*B14) -> 109867.47 | J14: =(H14*$I$1/(SUM($H$6:$H$35))) -> 107724.33
A15: =EDATE(A14,1) -> 46447 | B15: =VLOOKUP(A15,'INCC - M'!$E:$F,2,FALSE) -> 1264.353 | D15: =(C15*$C$3)*B15/$B$3 -> 0 | E15: =D15*$R$4 -> 0 | F15: =D15-E15 -> 0 | H15: 0.0298 | I15: =H15*($C$3/$B$3*B15) -> 135291.35 | J15: =(H15*$I$1/(SUM($H$6:$H$35))) -> 132652.27
A16: =EDATE(A15,1) -> 46478 | B16: =VLOOKUP(A16,'INCC - M'!$E:$F,2,FALSE) -> 1264.353 | D16: =(C16*$C$3)*B16/$B$3 -> 0 | E16: =D16*$R$4 -> 0 | F16: =D16-E16 -> 0 | H16: 0.016 | I16: =H16*($C$3/$B$3*B16) -> 72639.652 | J16: =(H16*$I$1/(SUM($H$6:$H$35))) -> 71222.695
A17: =EDATE(A16,1) -> 46508 | B17: =VLOOKUP(A17,'INCC - M'!$E:$F,2,FALSE) -> 1264.353 | D17: =(C17*$C$3)*B17/$B$3 -> 0 | E17: =D17*$R$4 -> 0 | F17: =D17-E17 -> 0 | H17: 0.028 | I17: =H17*($C$3/$B$3*B17) -> 127119.39 | J17: =(H17*$I$1/(SUM($H$6:$H$35))) -> 124639.72
A18: =EDATE(A17,1) -> 46539 | B18: =VLOOKUP(A18,'INCC - M'!$E:$F,2,FALSE) -> 1264.353 | D18: =(C18*$C$3)*B18/$B$3 -> 0 | E18: =D18*$R$4 -> 0 | F18: =D18-E18 -> 0 | H18: 0.0405 | I18: =H18*($C$3/$B$3*B18) -> 183869.12 | J18: =(H18*$I$1/(SUM($H$6:$H$35))) -> 180282.45
A19: =EDATE(A18,1) -> 46569 | B19: =VLOOKUP(A19,'INCC - M'!$E:$F,2,FALSE) -> 1264.353 | D19: =(C19*$C$3)*B19/$B$3 -> 0 | E19: =D19*$R$4 -> 0 | F19: =D19-E19 -> 0 | H19: 0.0416 | I19: =H19*($C$3/$B$3*B19) -> 188863.09 | J19: =(H19*$I$1/(SUM($H$6:$H$35))) -> 185179.01
... A34: =EDATE(A33,1) -> 47027 | B34: =VLOOKUP(A34,'INCC - M'!$E:$F,2,FALSE) -> 1264.353 | D34: =(C34*$C$3)*B34/$B$3 -> 0 | E34: =D34*$R$4 -> 0 | F34: =D34-E34 -> 0 | H34: 0.0001 | I34: =H34*($C$3/$B$3*B34) -> 453.99782 | J34: =(H34*$I$1/(SUM($H$6:$H$35))) -> 445.14185
C35: =SUM(C5:C34) -> 0.0253
C36: 0.45237182
C37: =C36-C35 -> 0.42707182

Sheet Platea
A1: Platea | G1: Taxa ADM (R$) | H1: Taxa ADM (INCC) | I1: Saldo (INCC)
A2: Data Base | B2: INCC Base | C2: Competência (R$) | D2: Valor da Taxa (R$) | E2: Valor da Taxa (INCC) | G2: 1908100 | H2: =G2/B3 -> 1619.2487 | I2: =H2-E3 -> 1254.3233 | L2: Valor Cobrado
A3: 45748 | B3: =VLOOKUP(A3,'INCC - DI'!$E:$F,2,FALSE) -> 1178.386 | C3: =SUM(C5:C31) -> 4447517.4 | D3: =SUM(D5:D31) -> 444751.74 | E3: =SUM(E5:E31) -> 364.9254 | L3: =SUM(L5:L19) -> 444751.74 | M3: =D3-L3 -> 0
A4: Mês | C4: Competência (R$) | D4: Valor da Taxa (R$) | E4: Valor da Taxa (INCC) | L4: Valor Cobrado
A5: 45931 | B5: =VLOOKUP(A5,'INCC - DI'!$E:$F,2,FALSE) -> 1218.747 | C5: 440473.7 | D5: =C5*0.1 -> 44047.37 | E5: =D5/$B$5 -> 36.141521 | L5: 42885.197
A6: =EDATE(A5,1) -> 45962 | B6: =VLOOKUP(A6,'INCC - DI'!$E:$F,2,FALSE) -> 1222.356 | C6: 695615.99 | D6: =C6*0.1 -> 69561.599 | E6: =D6/$B$5 -> 57.076324 | L6: 60954.31
A7: =EDATE(A6,1) -> 45992 | B7: =VLOOKUP(A7,'INCC - DI'!$E:$F,2,FALSE) -> 1225.633 | C7: 310378.64 | D7: =C7*0.1 -> 31037.864 | E7: =D7/$B$5 -> 25.467028 | L7: 47204.33
A8: =EDATE(A7,1) -> 46023 | B8: =VLOOKUP(A8,'INCC - DI'!$E:$F,2,FALSE) -> 1228.161 | C8: 295121.23 | D8: =C8*0.1 -> 29512.123 | E8: =D8/$B$5 -> 24.215135 | L8: 24668.96
A9: =EDATE(A8,1) -> 46054 | B9: =VLOOKUP(A9,'INCC - DI'!$E:$F,2,FALSE) -> 1237.036 | C9: 247692.76 | D9: =C9*0.1 -> 24769.276 | E9: =D9/$B$5 -> 20.323559 | L9: 40298.53
A10: =EDATE(A9,1) -> 46082 | B10: =VLOOKUP(A10,'INCC - DI'!$E:$F,2,FALSE) -> 1240.481 | C10: 761609.08 | D10: =C10*0.1 -> 76160.908 | E10: =D10/$B$5 -> 62.491155 | L10: 65823.18
A11: =EDATE(A10,1) -> 46113 | B11: =VLOOKUP(A11,'INCC - DI'!$E:$F,2,FALSE) -> 1247.181 | C11: 458142.75 | D11: =C11*0.1 -> 45814.275 | E11: =D11/$B$5 -> 37.591293 | L11: 55154.35
A12: =EDATE(A11,1) -> 46143 | B12: =VLOOKUP(A12,'INCC - DI'!$E:$F,2,FALSE) -> 1259.652 | C12: 577658.88 | D12: =C12*0.1 -> 57765.888 | E12: =D12/$B$5 -> 47.397768 | L12: 69303.728
A13: =EDATE(A12,1) -> 46174 | B13: =VLOOKUP(A13,'INCC - DI'!$E:$F,2,FALSE) -> 1270.695 | C13: 660824.32 | D13: =C13*0.1 -> 66082.432 | E13: =D13/$B$5 -> 54.221616 | L13: 38459.149
A14: =EDATE(A13,1) -> 46204 | B14: =VLOOKUP(A14,'INCC - DI'!$E:$F,2,FALSE) -> 1270.695 | D14: =C14*0.1 -> 0 | E14: =D14/$B$5 -> 0
A15: =EDATE(A14,1) -> 46235 | B15: =VLOOKUP(A15,'INCC - DI'!$E:$F,2,FALSE) -> 1270.695 | D15: =C15*0.1 -> 0 | E15: =D15/$B$5 -> 0
A16: =EDATE(A15,1) -> 46266 | B16: =VLOOKUP(A16,'INCC - DI'!$E:$F,2,FALSE) -> 1270.695 | D16: =C16*0.1 -> 0 | E16: =D16/$B$5 -> 0
A17: =EDATE(A16,1) -> 46296 | B17: =VLOOKUP(A17,'INCC - DI'!$E:$F,2,FALSE) -> 1270.695 | D17: =C17*0.1 -> 0 | E17: =D17/$B$5 -> 0
A18: =EDATE(A17,1) -> 46327 | B18: =VLOOKUP(A18,'INCC - DI'!$E:$F,2,FALSE) -> 1270.695 | D18: =C18*0.1 -> 0 | E18: =D18/$B$5 -> 0
A19: =EDATE(A18,1) -> 46357 | B19: =VLOOKUP(A19,'INCC - DI'!$E:$F,2,FALSE) -> 1270.695 | D19: =C19*0.1 -> 0 | E19: =D19/$B$5 -> 0
A20: =EDATE(A19,1) -> 46388 | B20: =VLOOKUP(A20,'INCC - DI'!$E:$F,2,FALSE) -> 1270.695 | D20: =C20*0.1 -> 0 | E20: =D20/$B$5 -> 0
A21: =EDATE(A20,1) -> 46419 | B21: =VLOOKUP(A21,'INCC - DI'!$E:$F,2,FALSE) -> 1270.695 | D21: =C21*0.1 -> 0 | E21: =D21/$B$5 -> 0
A22: =EDATE(A21,1) -> 46447 | B22: =VLOOKUP(A22,'INCC - DI'!$E:$F,2,FALSE) -> 1270.695 | D22: =C22*0.1 -> 0 | E22: =D22/$B$5 -> 0
A23: =EDATE(A22,1) -> 46478 | B23: =VLOOKUP(A23,'INCC - DI'!$E:$F,2,FALSE) -> 1270.695 | D23: =C23*0.1 -> 0 | E23: =D23/$B$5 -> 0
A24: =EDATE(A23,1) -> 46508 | B24: =VLOOKUP(A24,'INCC - DI'!$E:$F,2,FALSE) -> 1270.695 | D24: =C24*0.1 -> 0 | E24: =D24/$B$5 -> 0
A25: =EDATE(A24,1) -> 46539 | B25: =VLOOKUP(A25,'INCC - DI'!$E:$F,2,FALSE) -> 1270.695 | D25: =C25*0.1 -> 0 | E25: =D25/$B$5 -> 0
... A31: =EDATE(A30,1) -> 46722 | B31: =VLOOKUP(A31,'INCC - DI'!$E:$F,2,FALSE) -> 1270.695 | D31: =C31*0.1 -> 0 | E31: =D31/$B$5 -> 0
C32: aba financ compet.

Sheet Centro de Eventos Unna
A1: Centro de Eventos Unna
A2: Data Base | B2: INCC Base | C2: Medição Piemonte | D2: Medição Voss | E2: Valor da Taxa (Reaj) Piemonte | F2: Valor da Taxa (Reaj) Voss
A3: 45901 | B3: 1218.747 | C3: =937345.658366678*0.6 -> 562407.4 | D3: =937345.658366678*0.4 -> 374938.26 | E3: =SUM(E5:E14) -> 58637.953 | F3: =SUM(F5:F14) -> 39091.969
A4: Mês | B4: INCC DI (n-1) | C4: Medição Piemonte | D4: Medição Voss | E4: Valor da Taxa (Reaj) Piemonte | F4: Valor da Taxa (Reaj) Voss
A5: 46204 | B5: =VLOOKUP(A5,'INCC - DI'!$E:$F,2,FALSE) -> 1270.695 | C5: =93734.57*0.6 -> 56240.742 | D5: =93734.57*0.4 -> 37493.828 | E5: =C5/$B$3*B5 -> 58637.953 | F5: =D5/$B$3*B5 -> 39091.969
A6: =EDATE(A5,1) -> 46235 | B6: =VLOOKUP(A6,'INCC - DI'!$E:$F,2,FALSE) -> 1270.695 | E6: =C6/$B$3*B6 -> 0 | F6: =D6/$B$3*B6 -> 0
A7: =EDATE(A6,1) -> 46266 | B7: =VLOOKUP(A7,'INCC - DI'!$E:$F,2,FALSE) -> 1270.695 | E7: =C7/$B$3*B7 -> 0 | F7: =D7/$B$3*B7 -> 0
A8: =EDATE(A7,1) -> 46296 | B8: =VLOOKUP(A8,'INCC - DI'!$E:$F,2,FALSE) -> 1270.695 | E8: =C8/$B$3*B8 -> 0 | F8: =D8/$B$3*B8 -> 0
A9: =EDATE(A8,1) -> 46327 | B9: =VLOOKUP(A9,'INCC - DI'!$E:$F,2,FALSE) -> 1270.695 | E9: =C9/$B$3*B9 -> 0 | F9: =D9/$B$3*B9 -> 0
A10: =EDATE(A9,1) -> 46357 | B10: =VLOOKUP(A10,'INCC - DI'!$E:$F,2,FALSE) -> 1270.695 | E10: =C10/$B$3*B10 -> 0 | F10: =D10/$B$3*B10 -> 0
A11: =EDATE(A10,1) -> 46388 | B11: =VLOOKUP(A11,'INCC - DI'!$E:$F,2,FALSE) -> 1270.695 | E11: =C11/$B$3*B11 -> 0 | F11: =D11/$B$3*B11 -> 0
A12: =EDATE(A11,1) -> 46419 | B12: =VLOOKUP(A12,'INCC - DI'!$E:$F,2,FALSE) -> 1270.695 | E12: =C12/$B$3*B12 -> 0 | F12: =D12/$B$3*B12 -> 0
A13: =EDATE(A12,1) -> 46447 | B13: =VLOOKUP(A13,'INCC - DI'!$E:$F,2,FALSE) -> 1270.695 | E13: =C13/$B$3*B13 -> 0 | F13: =D13/$B$3*B13 -> 0
A14: =EDATE(A13,1) -> 46478 | B14: =VLOOKUP(A14,'INCC - DI'!$E:$F,2,FALSE) -> 1270.695 | E14: =C14/$B$3*B14 -> 0 | F14: =D14/$B$3*B14 -> 0

Sheet Shopping Reforma
A1: Shopping
A2: Data Base | B2: CUB Base | C2: Medição Piemonte | D2: Medição Voss | E2: Valor Total | F2: Valor Orçado | I2: Valor Cobrado
A3: 45717 | B3: 3113.61 | C3: =SUM(C5:C34) -> 462077.83 | D3: =SUM(D5:D34) -> 462077.83 | E3: =SUM(E5:E34) -> 924155.66 | F3: =F4+F5+F6+F7 -> 924155.66 | G3: =F3-E3 -> 0 | I3: =SUM(I5:I46) -> 462077.83 | J3: =SUM(J5:J46) -> 462077.83 | K3: =C3-I3 -> 0 | L3: =D3-J3 -> 0
A4: Mês | B4: CUB | C4: Medição Piemonte | D4: Medição Voss | E4: Valor Total | F4: 887975.39 | G4: Orç Base | I4: Valor Cobrado Piemonte | J4: Valor Cobrado Voss
A5: 45778 | B5: 3129.12 | C5: =((($F$3/$B$3)*$B5)/12)/2 -> 38698.3 | D5: =((($F$3/$B$3)*$B5)/12)/2 -> 38698.3 | E5: =C5+D5 -> 77396.6 | F5: 11387.61 | G5: Aditivo Vidro | I5: 36998.97 | J5: 36998.97
A6: =EDATE(A5,1) -> 45809 | B6: 3138.86 | C6: =((($F$3/$B$3)*$B6)/12)/2 -> 38818.756 | D6: =((($F$3/$B$3)*$B6)/12)/2 -> 38818.756 | E6: =C6+D6 -> 77637.512 | F6: =246597.6*8.5% -> 20960.796 | G6: Aditivo Praça Alim | I6: 40913.248 | J6: 40913.248
A7: =EDATE(A6,1) -> 45839 | B7: 3170.14 | C7: =((($F$3/$B$3)*$B7)/12)/2 -> 39205.601 | D7: =((($F$3/$B$3)*$B7)/12)/2 -> 39205.601 | E7: =C7+D7 -> 78411.201 | F7: 3831.86 | G7: Aditivo Marcenaria | I7: 34240.801 | J7: 34240.801
A8: =EDATE(A7,1) -> 45870 | B8: 3181.03 | C8: =((($F$3/$B$3)*$B8)/12)/2 -> 39340.279 | D8: =((($F$3/$B$3)*$B8)/12)/2 -> 39340.279 | E8: =C8+D8 -> 78680.558 | I8: 37800.125 | J8: 37800.125
A9: =EDATE(A8,1) -> 45901 | B9: 3196.21 | C9: =((($F$3/$B$3)*$B9)/12)/2 -> 39528.012 | D9: =((($F$3/$B$3)*$B9)/12)/2 -> 39528.012 | E9: =C9+D9 -> 79056.025 | I9: 37980.509 | J9: 37980.509
A10: =EDATE(A9,1) -> 45931 | B10: 3201.33 | C10: =((($F$3/$B$3)*$B10)/12)/2 -> 39591.332 | D10: =((($F$3/$B$3)*$B10)/12)/2 -> 39591.332 | E10: =C10+D10 -> 79182.664 | I10: 38041.35 | J10: 38041.35
A11: =EDATE(A10,1) -> 45962 | B11: 3205.55 | C11: =((($F$3/$B$3)*$B11)/12)/2 -> 39643.522 | D11: =((($F$3/$B$3)*$B11)/12)/2 -> 39643.522 | E11: =C11+D11 -> 79287.043 | I11: 38091.496 | J11: 38091.496
A12: =EDATE(A11,1) -> 45992 | B12: 3211.11 | C12: =((($F$3/$B$3)*$B12)/12)/2 -> 39712.283 | D12: =((($F$3/$B$3)*$B12)/12)/2 -> 39712.283 | E12: =C12+D12 -> 79424.566 | I12: 49418.488 | J12: 49418.488
A13: =EDATE(A12,1) -> 46023 | B13: 3215.75 | C13: =((($F$3/$B$3)*$B13)/12)/2 -> 39769.666 | D13: =((($F$3/$B$3)*$B13)/12)/2 -> 39769.666 | E13: =C13+D13 -> 79539.333 | I13: 39353.685 | J13: 39353.685
A14: =EDATE(A13,1) -> 46054 | B14: 3222.03 | C14: =((($F$3/$B$3)*$B14)/12)/2 -> 39847.332 | D14: =((($F$3/$B$3)*$B14)/12)/2 -> 39847.332 | E14: =C14+D14 -> 79694.664 | I14: 41316.411 | J14: 41316.411
A15: =EDATE(A14,1) -> 46082 | B15: 3230.89 | C15: =((($F$3/$B$3)*$B15)/12)/2 -> 39956.905 | D15: =((($F$3/$B$3)*$B15)/12)/2 -> 39956.905 | E15: =C15+D15 -> 79913.81 | I15: 39956.905 | J15: 39956.905
A16: =EDATE(A15,1) -> 46113 | B16: 3236.24 | C16: 27965.839 | D16: 27965.839 | E16: =C16+D16 -> 55931.678 | I16: 27965.839 | J16: 27965.839
A17: =EDATE(A16,1) -> 46143 | C17: =((($F$3/$B$3)*$B17)/12)/2 -> 0 | D17: =((($F$3/$B$3)*$B17)/12)/2 -> 0 | E17: =C17+D17 -> 0
A18: =EDATE(A17,1) -> 46174 | C18: =((($F$3/$B$3)*$B18)/12)/2 -> 0 | D18: =((($F$3/$B$3)*$B18)/12)/2 -> 0 | E18: =C18+D18 -> 0
A19: =EDATE(A18,1) -> 46204 | C19: =((($F$3/$B$3)*$B19)/12)/2 -> 0 | D19: =((($F$3/$B$3)*$B19)/12)/2 -> 0 | E19: =C19+D19 -> 0
A20: =EDATE(A19,1) -> 46235 | C20: =((($F$3/$B$3)*$B20)/12)/2 -> 0 | D20: =((($F$3/$B$3)*$B20)/12)/2 -> 0 | E20: =C20+D20 -> 0
A21: =EDATE(A20,1) -> 46266 | C21: =((($F$3/$B$3)*$B21)/12)/2 -> 0 | D21: =((($F$3/$B$3)*$B21)/12)/2 -> 0 | E21: =C21+D21 -> 0
A22: =EDATE(A21,1) -> 46296 | C22: =((($F$3/$B$3)*$B22)/12)/2 -> 0 | D22: =((($F$3/$B$3)*$B22)/12)/2 -> 0 | E22: =C22+D22 -> 0
A23: =EDATE(A22,1) -> 46327 | C23: =((($F$3/$B$3)*$B23)/12)/2 -> 0 | D23: =((($F$3/$B$3)*$B23)/12)/2 -> 0 | E23: =C23+D23 -> 0
A24: =EDATE(A23,1) -> 46357 | C24: =((($F$3/$B$3)*$B24)/12)/2 -> 0 | D24: =((($F$3/$B$3)*$B24)/12)/2 -> 0 | E24: =C24+D24 -> 0
A25: =EDATE(A24,1) -> 46388 | C25: =((($F$3/$B$3)*$B25)/12)/2 -> 0 | D25: =((($F$3/$B$3)*$B25)/12)/2 -> 0 | E25: =C25+D25 -> 0
A26: =EDATE(A25,1) -> 46419 | C26: =((($F$3/$B$3)*$B26)/12)/2 -> 0 | D26: =((($F$3/$B$3)*$B26)/12)/2 -> 0 | E26: =C26+D26 -> 0
A27: =EDATE(A26,1) -> 46447 | C27: =((($F$3/$B$3)*$B27)/12)/2 -> 0 | D27: =((($F$3/$B$3)*$B27)/12)/2 -> 0 | E27: =C27+D27 -> 0
A28: =EDATE(A27,1) -> 46478 | C28: =((($F$3/$B$3)*$B28)/12)/2 -> 0 | D28: =((($F$3/$B$3)*$B28)/12)/2 -> 0 | E28: =C28+D28 -> 0
... A34: =EDATE(A33,1) -> 46661 | C34: =((($F$3/$B$3)*$B34)/12)/2 -> 0 | D34: =((($F$3/$B$3)*$B34)/12)/2 -> 0 | E34: =C34+D34 -> 0

Sheet Assistência
A1: 45200 | D1: 45261 | G1: 45292 | J1: 45323 | M1: 45352 | P1: 45383 | S1: 45413 | V1: 45444 | Y1: 45474 | AB1: 45505 | AE1: 45536 | AH1: 45566 | AK1: 45597 | AN1: 45627
A2: Descrição | B2: Valor | D2: Descrição | E2: Valor | G2: Descrição | H2: Valor | J2: Descrição | K2: Valor | M2: Descrição | N2: Valor | P2: Descrição | Q2: Valor | S2: Descrição | T2: Valor | V2: Descrição | W2: Valor | Y2: Descrição | Z2: Valor | AB2: Descrição | AC2: Valor | AE2: Descrição | AF2: Valor | AH2: Descrição | AI2: Valor | AK2: Descrição | AL2: Valor | AN2: Descrição | AO2: Valor
A3: Assistência técnica S.A | B3: 49524.3 | D3: Assistência técnica S.A | E3: 48131 | G3: Assistência técnica S.A | H3: 73157.52 | J3: Assistência técnica S.A | K3: 73157.52 | M3: Assistência técnica S.A | N3: 0 | P3: Assistência técnica S.A | Q3: 0 | S3: Terrenos LTDA | T3: 27547.65 | V3: Terrenos LTDA | W3: 32875.77 | Y3: Terrenos LTDA | Z3: 36963.58 | AB3: Terrenos LTDA | AC3: 35265.34 | AE3: Terrenos LTDA | AF3: 38722.99 | AH3: Terrenos LTDA | AI3: 35769.94 | AK3: Terrenos LTDA | AL3: 37418.15 | AN3: Terrenos LTDA
A4: Caseiros - Piemonte Ltda | B4: 31801.01 | D4: Caseiros - Piemonte Ltda | E4: 27741.7 | G4: Caseiros - Piemonte Ltda | H4: 39596.37 | J4: Caseiros - Piemonte Ltda | K4: 27588.74 | M4: Caseiros - Piemonte Ltda | N4: 26130.28 | P4: Caseiros - Piemonte Ltda | Q4: 28507.45 | S4: SPE Biguaçu | T4: 6508.1 | V4: SPE Biguaçu | W4: 6954.5 | Y4: SPE Biguaçu | Z4: 9298.98 | AB4: SPE Biguaçu | AC4: 6927.77 | AE4: SPE Biguaçu | AF4: 7505.52 | AH4: SPE Biguaçu | AI4: 7551.75 | AK4: SPE Biguaçu | AL4: 7441.7 | AN4: SPE Biguaçu
A5: Caseiro Biguaçu | B5: 6475.11 | D5: Caseiro Biguaçu | E5: 6475.1 | G5: Caseiro Biguaçu | H5: 10548.36 | J5: Caseiro Biguaçu | K5: 6475.1 | M5: Caseiro Biguaçu | N5: 6508.1 | P5: Caseiro Biguaçu | Q5: 6508.1 | S5: Cantu FORTALEZA | T5: 6396.37 | V5: Cantu FORTALEZA | W5: 6402.41 | Y5: Cantu FORTALEZA | Z5: 6439.69 | AB5: Cantu FORTALEZA | AC5: 6745.52 | AE5: Cantu FORTALEZA | AF5: 7342.01 | AH5: Cantu FORTALEZA | AI5: 6886.58 | AK5: Cantu FORTALEZA | AL5: 7958.65 | AN5: Cantu FORTALEZA
A6: Caseiro Cantu Fortaleza | B6: 6878.8 | D6: Caseiro Cantu Fortaleza | E6: 6363.37 | G6: Caseiro Cantu Fortaleza | H6: 12523.89 | J6: Caseiro Cantu Fortaleza | K6: 4614.92 | M6: Caseiro Cantu Fortaleza | N6: 6522.68 | P6: Caseiro Cantu Fortaleza | Q6: 6396.37 | S6: Ass. Téc CANTU | T6: 3160 | V6: Ass. Téc CANTU | W6: 3160 | Y6: Ass. Téc CANTU | Z6: 3160 | AB6: Ass. Téc CANTU | AC6: 3160 | AE6: SPE Parque das Artes | AF6: 8430.3 | AH6: SPE Parque das Artes | AI6: 7974.87 | AK6: SPE Parque das Artes | AL6: 7986.45 | AN6: SPE Parque das Artes
A7: Caseiro Parque das Artes | B7: 10340.59 | D7: Caseiro Parque das Artes | E7: 6976.76 | G7: Caseiro Parque das Artes | H7: 10890.4 | J7: Caseiro Parque das Artes | K7: 7690.83 | M7: Caseiro Parque das Artes | N7: 7050.47 | P7: Caseiro Parque das Artes | Q7: 7461.49 | S7: SPE Parque das Artes | T7: 7938.13 | V7: SPE Parque das Artes | W7: 7834.08 | Y7: SPE Parque das Artes | Z7: 8407.9 | AB7: SPE Parque das Artes | AC7: 8942.89 | AE7: Ass. Téc CANTU | AF7: 3160 | AH7: Ass. Téc CANTU | AI7: 3160 | AK7: Ass. Téc CANTU | AL7: 3160 | AN7: Ass. Téc CANTU
A8: Taxa Cantu mensal | B8: 3000 | D8: Taxa Cantu mensal | E8: 3000 | G8: Taxa Cantu mensal | H8: 3160 | J8: Taxa Cantu mensal | K8: 3160 | M8: Taxa Cantu mensal | N8: 3160 | P8: Taxa Cantu mensal | Q8: 3160 | S8: Bobcat Manacás | T8: 22000 | V8: Bobcat Manacás | W8: 22000 | Y8: Manitou Manacás | Z8: 16133.33 | AB8: Manitou Poty | AC8: 12600 | AE8: Manitou Poty | AF8: 0 | AH8: Manitou Poty | AI8: 0 | AK8: Manitou Poty | AL8: 0 | AN8: Manitou Poty | AO8: 0
A9: Locação Manitu (Manacás) | B9: 22000 | D9: Locação Manitu (Manacás) | E9: 22000 | G9: Locação Manitu (Manacás) | H9: 22000 | J9: Locação Manitu (Manacás) | K9: 22000 | M9: Locação Manitu (Manacás) | N9: 22000 | P9: Locação Manitu (Manacás) | Q9: 22000 | S9: Bobcat Lotes Campo Santana | T9: 14900 | V9: Bobcat Lotes Campo Santana | W9: 14900 | Y9: Bobcat Lotes Campo Santana | Z9: 14900 | AB9: Bobcat Lotes Campo Santana | AC9: 14900 | AE9: Bobcat Lotes Campo Santana | AF9: 14900 | AH9: Bobcat Lotes Campo Santana | AI9: 14900 | AK9: Bobcat Lotes Campo Santana | AL9: 14900 | AN9: Bobcat Lotes Campo Santana
A10: Locação Bobcat (Limpeza terreno) | B10: 14900 | D10: Locação Bobcat (Limpeza terreno) | E10: 14900 | G10: Locação Bobcat (Limpeza terreno) | H10: 14900 | J10: Locação Bobcat (Limpeza terreno) | K10: 14900 | M10: Locação Bobcat (Limpeza terreno) | N10: 14900 | P10: Locação Bobcat (Limpeza terreno) | Q10: 14900
P11: MO Assist. Técnica | Q11: 12000 | Y11: pegar informações com o Gustavo e validar com o Luis
