Workbook
Name \0: #N/A
Name \1: #REF!
Name \a: #REF!
Name \e: #N/A
Name \m: [1]TUBULÃO!#REF!
Name \s: #N/A
Name _________________la29: #REF!
Name _________________la3: #REF!
Name _________________la31: #REF!
Name _________________la32: #REF!
Name _________________la4: #REF!
Name _________________la5: #REF!
Name _________________la6: #REF!
Name _________________la7: #REF!
Name _________________la8: #REF!
Name _________________la9: #REF!
Name _________________lb1: #REF!
Name _________________lb10: #REF!
Name _________________lb11: #REF!
Name _________________lb12: #REF!
Name _________________lb13: #REF!
Name _________________lb14: #REF!
Name _________________lb15: #REF!
Name _________________lb16: #REF!
Name _________________lb17: #REF!
Name _________________lb18: #REF!
Name _________________lb19: #REF!
Name _________________lb2: #REF!
Name _________________lb20: #REF!
Name _________________lb21: #REF!
Name _________________lb22: #REF!
Name _________________lb23: #REF!
Name _________________lb24: #REF!
Name _________________lb25: #REF!
Name _________________lb27: #REF!
Name _________________lb28: #REF!
Name _________________lb29: #REF!
Name _________________lb3: #REF!
Name _________________lb30: #REF!
Name _________________lb31: #REF!
Name _________________lb32: #REF!
Name _________________lb4: #REF!
Name _________________lb5: #REF!
Name _________________lb6: #REF!
Name _________________lb7: #REF!
Name _________________lb8: #REF!
Name _________________lb9: #REF!
Name _________________lbc1: #REF!
Name _________________lbc10: #REF!
Name _________________lbc11: #REF!
Name _________________lbc12: #REF!
Name _________________lbc13: #REF!
Name _________________lbc14: #REF!
Name _________________lbc15: #REF!
Name _________________lbc16: #REF!
Name _________________lbc17: #REF!
Name _________________lbc18: #REF!
Name _________________lbc19: #REF!
Name _________________lbc2: #REF!
Name _________________lbc20: #REF!

Sheet Miragio
I2: INCC - M (Abr/23) | L2: INCC - M (Mai/23) | O2: INCC - M (Jun/23) | R2: INCC - M (Jul/23)
B3: INCC - Base | C3: 44075 | D3: 810.965 | I3: 1061.071 | L3: 1065.289 | O3: 1074.292 | R3: 1074.895
A4: Orçamento base | C4: Periodo | E4: Prazo | F4: Valor total | G4: Valor unitário | I4: Medição - Maio 2023 | L4: Medição - Junho 2023 | O4: Medição - Julho 2023 | R4: Medição - Agosto 2023
A5: 01.01.04.01 | B5: PESSOAL | C5: 44166 | D5: 45139 | I5: Orç. Piemonte Reaj | J5: Medido Terceiros RM | K5: Valor MO ADM | L5: Orç. Piemonte Reaj | M5: Medido Terceiros RM | N5: Valor MO ADM | O5: Orç. Piemonte Reaj | P5: Medido Terceiros RM | Q5: Valor MO ADM | R5: Orç. Piemonte Reaj | S5: Medido Terceiros RM | T5: Valor MO ADM
A6: 01.01.04.01.001 | B6: ENGENHEIRO PRODUCAO | C6: 44166 | D6: 45139 | E6: 33 | F6: 462000 | G6: =F6/E6 -> 14000 | I6: =$G6*I$3/$D$3 -> 18317.676 | K6: =IF(J6>I6,0,I6-J6) -> 18317.676 | L6: =$G6*L$3/$D$3 -> 18390.493 | N6: =IF(M6>L6,0,L6-M6) -> 18390.493 | O6: =$G6*O$3/$D$3 -> 18545.915 | Q6: =IF(P6>O6,0,O6-P6) -> 18545.915 | R6: =$G6*R$3/$D$3 -> 18556.325 | T6: =IF(S6>R6,0,R6-S6) -> 18556.325
A7: 01.01.04.01.002 | B7: ENGENHEIRO SEGURANCA DO TRABALHO | C7: 44166 | D7: 45139 | E7: 33 | F7: 99000 | G7: =F7/E7 -> 3000 | I7: =$G7*I$3/$D$3 -> 3925.2163 | K7: =IF(J7>I7,0,I7-J7) -> 3925.2163 | L7: =$G7*L$3/$D$3 -> 3940.8199 | N7: =IF(M7>L7,0,L7-M7) -> 3940.8199 | O7: =$G7*O$3/$D$3 -> 3974.1247 | Q7: =IF(P7>O7,0,O7-P7) -> 3974.1247 | R7: =$G7*R$3/$D$3 -> 3976.3553 | T7: =IF(S7>R7,0,R7-S7) -> 3976.3553
A8: 01.01.04.01.003 | B8: MESTRE DE OBRAS | C8: 44166 | D8: 45139 | E8: 33 | F8: 409008.6 | G8: =F8/E8 -> 12394.2 | I8: =$G8*I$3/$D$3 -> 16216.638 | J8: 12244.56 | K8: =IF(J8>I8,0,I8-J8) -> 3972.0784 | L8: =$G8*L$3/$D$3 -> 16281.103 | M8: 12244.56 | N8: =IF(M8>L8,0,L8-M8) -> 4036.5433 | O8: =$G8*O$3/$D$3 -> 16418.699 | P8: 12244.56 | Q8: =IF(P8>O8,0,O8-P8) -> 4174.1386 | R8: =$G8*R$3/$D$3 -> 16427.914 | S8: 14448.58 | T8: =IF(S8>R8,0,R8-S8) -> 1979.3344
A9: 01.01.04.01.004 | B9: MESTRE DE OBRAS _EMPREITEIRA | C9: 44256 | D9: 45139 | E9: 30 | F9: 120000 | G9: =F9/E9 -> 4000 | I9: =$G9*I$3/$D$3 -> 5233.6217 | J9: =3636+453.41 -> 4089.41 | K9: =IF(J9>I9,0,I9-J9) -> 1144.2117 | L9: =$G9*L$3/$D$3 -> 5254.4265 | M9: =3636+453.41 -> 4089.41 | N9: =IF(M9>L9,0,L9-M9) -> 1165.0165 | O9: =$G9*O$3/$D$3 -> 5298.8329 | P9: =3636+453.41 -> 4089.41 | Q9: =IF(P9>O9,0,O9-P9) -> 1209.4229 | R9: =$G9*R$3/$D$3 -> 5301.8071 | S9: =3636+453.41 -> 4089.41 | T9: =IF(S9>R9,0,R9-S9) -> 1212.3971
A10: 01.01.04.01.005 | B10: CONTRA MESTRE | C10: 44166 | D10: 45139 | E10: 33 | F10: 189000 | G10: =F10/E10 -> 5727.2727 | I10: =$G10*I$3/$D$3 -> 7493.5947 | K10: =IF(J10>I10,0,I10-J10) -> 7493.5947 | L10: =$G10*L$3/$D$3 -> 7523.3834 | N10: =IF(M10>L10,0,L10-M10) -> 7523.3834 | O10: =$G10*O$3/$D$3 -> 7586.9652 | Q10: =IF(P10>O10,0,O10-P10) -> 7586.9652 | R10: =$G10*R$3/$D$3 -> 7591.2238 | T10: =IF(S10>R10,0,R10-S10) -> 7591.2238
A11: 01.01.04.01.006 | B11: ALMOXARIFE | C11: 44166 | D11: 45139 | E11: 33 | F11: 197174.34 | G11: =F11/E11 -> 5974.98 | I11: =$G11*I$3/$D$3 -> 7817.6962 | J11: =2799.72+349.13 -> 3148.85 | K11: =IF(J11>I11,0,I11-J11) -> 4668.8462 | L11: =$G11*L$3/$D$3 -> 7848.7733 | M11: =349.13+2799.72 -> 3148.85 | N11: =IF(M11>L11,0,L11-M11) -> 4699.9233 | O11: =$G11*O$3/$D$3 -> 7915.1051 | P11: =349.13+2799.72 -> 3148.85 | Q11: =IF(P11>O11,0,O11-P11) -> 4766.2551 | R11: =$G11*R$3/$D$3 -> 7919.5479 | S11: =349.13+2799.72 -> 3148.85 | T11: =IF(S11>R11,0,R11-S11) -> 4770.6979
A12: 01.01.04.01.007 | B12: TECNICO SEGURANCA_EMPREITEIRO | C12: 44256 | D12: 45139 | E12: 30 | F12: 87000 | G12: =F12/E12 -> 2900 | I12: =$G12*I$3/$D$3 -> 3794.3757 | J12: 2880 | K12: =IF(J12>I12,0,I12-J12) -> 914.37571 | L12: =$G12*L$3/$D$3 -> 3809.4592 | M12: 2880 | N12: =IF(M12>L12,0,L12-M12) -> 929.45922 | O12: =$G12*O$3/$D$3 -> 3841.6538 | P12: 2880 | Q12: =IF(P12>O12,0,O12-P12) -> 961.65383 | R12: =$G12*R$3/$D$3 -> 3843.8102 | S12: 2880 | T12: =IF(S12>R12,0,R12-S12) -> 963.81015
A13: 01.01.04.01.008 | B13: ADMINISTRATIVO DE OBRA | C13: 44166 | D13: 45139 | E13: 33 | F13: 221649.78 | G13: =F13/E13 -> 6716.66 | I13: =$G13*I$3/$D$3 -> 8788.1143 | K13: =IF(J13>I13,0,I13-J13) -> 8788.1143 | L13: =$G13*L$3/$D$3 -> 8823.0491 | N13: =IF(M13>L13,0,L13-M13) -> 8823.0491 | O13: =$G13*O$3/$D$3 -> 8897.6147 | Q13: =IF(P13>O13,0,O13-P13) -> 8897.6147 | R13: =$G13*R$3/$D$3 -> 8902.6089 | T13: =IF(S13>R13,0,R13-S13) -> 8902.6089
A14: 01.01.04.01.010 | B14: ESTAGIARIO (3X) | C14: 44166 | D14: 45139 | E14: 33 | F14: 143550 | G14: =F14/E14 -> 4350 | I14: =$G14*I$3/$D$3 -> 5691.5636 | K14: =IF(J14>I14,0,I14-J14) -> 5691.5636 | L14: =$G14*L$3/$D$3 -> 5714.1888 | N14: =IF(M14>L14,0,L14-M14) -> 5714.1888 | O14: =$G14*O$3/$D$3 -> 5762.4807 | Q14: =IF(P14>O14,0,O14-P14) -> 5762.4807 | R14: =$G14*R$3/$D$3 -> 5765.7152 | T14: =IF(S14>R14,0,R14-S14) -> 5765.7152
A15: 01.01.04.01.011 | B15: COORDENADOR DE OBRAS (1X) | C15: 44166 | D15: 45139 | E15: 33 | F15: 204430.38 | G15: =F15/E15 -> 6194.86 | I15: =$G15*I$3/$D$3 -> 8105.3884 | K15: =IF(J15>I15,0,I15-J15) -> 8105.3884 | L15: =$G15*L$3/$D$3 -> 8137.6092 | N15: =IF(M15>L15,0,L15-M15) -> 8137.6092 | O15: =$G15*O$3/$D$3 -> 8206.382 | Q15: =IF(P15>O15,0,O15-P15) -> 8206.382 | R15: =$G15*R$3/$D$3 -> 8210.9882 | T15: =IF(S15>R15,0,R15-S15) -> 8210.9882
A16: 01.01.04.01.012 | B16: TECNICO SEGURANCA (1X) | C16: 44166 | D16: 45139 | E16: 33 | F16: 132000 | G16: =F16/E16 -> 4000 | I16: =$G16*I$3/$D$3 -> 5233.6217 | K16: =IF(J16>I16,0,I16-J16) -> 5233.6217 | L16: =$G16*L$3/$D$3 -> 5254.4265 | N16: =IF(M16>L16,0,L16-M16) -> 5254.4265 | O16: =$G16*O$3/$D$3 -> 5298.8329 | Q16: =IF(P16>O16,0,O16-P16) -> 5298.8329 | R16: =$G16*R$3/$D$3 -> 5301.8071 | T16: =IF(S16>R16,0,R16-S16) -> 5301.8071
G17: =SUM(G6:G16) -> 69257.973 | I17: =SUM(I6:I16) -> 90617.507 | J17: =SUM(J6:J16) -> 22362.82 | K17: =SUM(K6:K16) -> 68254.687 | L17: =SUM(L6:L16) -> 90977.732 | M17: =SUM(M6:M16) -> 22362.82 | N17: =SUM(N6:N16) -> 68614.912 | O17: =SUM(O6:O16) -> 91746.606 | P17: =SUM(P6:P16) -> 22362.82 | ... T17: =SUM(T6:T16) -> 67231.263

Sheet IND. FIN.
A1: INCC - DI | H1: INCC - M | O1: CUB2006 MÉDIO | U1: Mês Vigente | V1: 46204 | W1: https://sindusconpr.com.br/incc-di-fgv-310-p
A2: (n) | C2: (n-1) | E2: (n-2) | H2: (n) | J2: (n-1) | L2: (n-2) | O2: (n) | Q2: (n-1) | S2: (n-2) | W2: https://sindusconpr.com.br/tabela-completa-370-p
A3: MÊS | B3: INDÍCE | C3: MÊS | D3: INDÍCE | E3: MÊS | F3: INDÍCE | H3: MÊS | I3: INDÍCE | J3: MÊS | K3: INDÍCE | L3: MÊS | M3: INDÍCE | O3: MÊS | P3: INDÍCE | Q3: MÊS | R3: INDÍCE | S3: MÊS | T3: INDÍCE | W3: https://sindusconpr.com.br/incc-m-fgv-1364-p
A4: 44197 | B4: 852.809 | C4: =A5 -> 44228 | D4: =B4 -> 852.809 | E4: =A6 -> 44256 | F4: =B4 -> 852.809 | H4: 44197 | I4: 850.495 | J4: =H5 -> 44228 | K4: =I4 -> 850.495 | L4: =H6 -> 44256 | M4: =I4 -> 850.495 | O4: 44197 | P4: 2273.96 | Q4: =O5 -> 44228 | R4: =P4 -> 2273.96 | S4: =O6 -> 44256 | T4: =P4 -> 2273.96
A5: 44228 | B5: 868.929 | C5: =A6 -> 44256 | D5: =B5 -> 868.929 | E5: =A7 -> 44287 | F5: =B5 -> 868.929 | H5: 44228 | I5: 859.573 | J5: =H6 -> 44256 | K5: =I5 -> 859.573 | L5: =H7 -> 44287 | M5: =I5 -> 859.573 | O5: 44228 | P5: 2293.94 | Q5: =O6 -> 44256 | R5: =P5 -> 2293.94 | S5: =O7 -> 44287 | T5: =P5 -> 2293.94
A6: 44256 | B6: 880.265 | C6: =A7 -> 44287 | D6: =B6 -> 880.265 | E6: =A8 -> 44317 | F6: =B6 -> 880.265 | H6: 44256 | I6: 876.75 | J6: =H7 -> 44287 | K6: =I6 -> 876.75 | L6: =H8 -> 44317 | M6: =I6 -> 876.75 | O6: 44256 | P6: 2323.15 | Q6: =O7 -> 44287 | R6: =P6 -> 2323.15 | S6: =O8 -> 44317 | T6: =P6 -> 2323.15
A7: 44287 | B7: 888.191 | C7: =A8 -> 44317 | D7: =B7 -> 888.191 | E7: =A9 -> 44348 | F7: =B7 -> 888.191 | H7: 44287 | I7: 885.093 | J7: =H8 -> 44317 | K7: =I7 -> 885.093 | L7: =H9 -> 44348 | M7: =I7 -> 885.093 | O7: 44287 | P7: 2357.58 | Q7: =O8 -> 44317 | R7: =P7 -> 2357.58 | S7: =O9 -> 44348 | T7: =P7 -> 2357.58
A8: 44317 | B8: 907.899 | C8: =A9 -> 44348 | D8: =B8 -> 907.899 | E8: =A10 -> 44378 | F8: =B8 -> 907.899 | H8: 44317 | I8: 901.032 | J8: =H9 -> 44348 | K8: =I8 -> 901.032 | L8: =H10 -> 44378 | M8: =I8 -> 901.032 | O8: 44317 | P8: 2394.27 | Q8: =O9 -> 44348 | R8: =P8 -> 2394.27 | S8: =O10 -> 44378 | T8: =P8 -> 2394.27
A9: 44348 | B9: 927.512 | C9: =A10 -> 44378 | D9: =B9 -> 927.512 | E9: =A11 -> 44409 | F9: =B9 -> 927.512 | H9: 44348 | I9: 921.762 | J9: =H10 -> 44378 | K9: =I9 -> 921.762 | L9: =H11 -> 44409 | M9: =I9 -> 921.762 | O9: 44348 | P9: 2441.78 | Q9: =O10 -> 44378 | R9: =P9 -> 2441.78 | S9: =O11 -> 44409 | T9: =P9 -> 2441.78
A10: 44378 | B10: 935.359 | C10: =A11 -> 44409 | D10: =B10 -> 935.359 | E10: =A12 -> 44440 | F10: =B10 -> 935.359 | H10: 44378 | I10: 933.23 | J10: =H11 -> 44409 | K10: =I10 -> 933.23 | L10: =H12 -> 44440 | M10: =I10 -> 933.23 | O10: 44378 | P10: 2497.79 | Q10: =O11 -> 44409 | R10: =P10 -> 2497.79 | S10: =O12 -> 44440 | T10: =P10 -> 2497.79
A11: 44409 | B11: 939.699 | C11: =A12 -> 44440 | D11: =B11 -> 939.699 | E11: =A13 -> 44470 | F11: =B11 -> 939.699 | H11: 44409 | I11: 938.475 | J11: =H12 -> 44440 | K11: =I11 -> 938.475 | L11: =H13 -> 44470 | M11: =I11 -> 938.475 | O11: 44409 | P11: 2523.29 | Q11: =O12 -> 44440 | R11: =P11 -> 2523.29 | S11: =O13 -> 44470 | T11: =P11 -> 2523.29
A12: 44440 | B12: 944.52 | C12: =A13 -> 44470 | D12: =B12 -> 944.52 | E12: =A14 -> 44501 | F12: =B12 -> 944.52 | H12: 44440 | I12: 943.736 | J12: =H13 -> 44470 | K12: =I12 -> 943.736 | L12: =H14 -> 44501 | M12: =I12 -> 943.736 | O12: 44440 | P12: 2551.83 | Q12: =O13 -> 44470 | R12: =P12 -> 2551.83 | S12: =O14 -> 44501 | T12: =P12 -> 2551.83
A13: 44470 | B13: 952.596 | C13: =A14 -> 44501 | D13: =B13 -> 952.596 | E13: =A15 -> 44531 | F13: =B13 -> 952.596 | H13: 44470 | I13: 951.249 | J13: =H14 -> 44501 | K13: =I13 -> 951.249 | L13: =H15 -> 44531 | M13: =I13 -> 951.249 | O13: 44470 | P13: 2577.05 | Q13: =O14 -> 44501 | R13: =P13 -> 2577.05 | S13: =O15 -> 44531 | T13: =P13 -> 2577.05
A14: 44501 | B14: 959.001 | C14: =A15 -> 44531 | D14: =B14 -> 959.001 | E14: =A16 -> 44562 | F14: =B14 -> 959.001 | H14: 44501 | I14: 957.984 | J14: =H15 -> 44531 | K14: =I14 -> 957.984 | L14: =H16 -> 44562 | M14: =I14 -> 957.984 | O14: 44501 | P14: 2603.53 | Q14: =O15 -> 44531 | R14: =P14 -> 2603.53 | S14: =O16 -> 44562 | T14: =P14 -> 2603.53
A15: 44531 | B15: 962.321 | C15: =A16 -> 44562 | D15: =B15 -> 962.321 | E15: =A17 -> 44593 | F15: =B15 -> 962.321 | H15: 44531 | I15: 960.894 | J15: =H16 -> 44562 | K15: =I15 -> 960.894 | L15: =H17 -> 44593 | M15: =I15 -> 960.894 | O15: 44531 | P15: 2617.93 | Q15: =O16 -> 44562 | R15: =P15 -> 2617.93 | S15: =O17 -> 44593 | T15: =P15 -> 2617.93
... A68: 46143 | B68: 1270.695 | C68: =A69 -> 46174 | D68: =B68 -> 1270.695 | E68: =A70 -> 46204 | F68: =B68 -> 1270.695 | H68: 46143 | I68: 1264.363 | J68: =H69 -> 46174 | K68: =I68 -> 1264.363 | L68: =H70 -> 46204 | M68: =I68 -> 1264.363 | O68: 46143 | P68: 3291.09 | Q68: =O69 -> 46174 | R68: =P68 -> 3291.09 | S68: =O70 -> 46204 | T68: =P68 -> 3291.09
A69: 46174 | B69: 1280.641 | C69: =A70 -> 46204 | D69: =B69 -> 1280.641 | E69: =A71 -> 46235 | F69: =B69 -> 1280.641 | H69: 46174 | I69: 1275.085 | J69: =H70 -> 46204 | K69: =I69 -> 1275.085 | L69: =H71 -> 46235 | M69: =I69 -> 1275.085 | O69: 46174 | Q69: =O70 -> 46204 | R69: =P69 -> 0 | S69: =O71 -> 46235 | T69: =P69 -> 0
A70: 46204 | C70: =A71 -> 46235 | D70: =B70 -> 0 | E70: =A72 -> 46266 | F70: =B70 -> 0 | H70: 46204 | J70: =H71 -> 46235 | K70: =I70 -> 0 | L70: =H72 -> 46266 | M70: =I70 -> 0 | O70: 46204 | Q70: =O71 -> 46235 | R70: =P70 -> 0 | S70: =O72 -> 46266 | T70: =P70 -> 0
A71: 46235 | C71: =A72 -> 46266 | D71: =B71 -> 0 | E71: =A73 -> 46296 | F71: =B71 -> 0 | H71: 46235 | J71: =H72 -> 46266 | K71: =I71 -> 0 | L71: =H73 -> 46296 | M71: =I71 -> 0 | O71: 46235 | Q71: =O72 -> 46266 | R71: =P71 -> 0 | S71: =O73 -> 46296 | T71: =P71 -> 0
A72: 46266 | C72: =A73 -> 46296 | D72: =B72 -> 0 | E72: =A74 -> 46327 | F72: =B72 -> 0 | H72: 46266 | J72: =H73 -> 46296 | K72: =I72 -> 0 | L72: =H74 -> 46327 | M72: =I72 -> 0 | O72: 46266 | Q72: =O73 -> 46296 | R72: =P72 -> 0 | S72: =O74 -> 46327 | T72: =P72 -> 0
A73: 46296 | C73: =A74 -> 46327 | D73: =B73 -> 0 | E73: =A75 -> 46357 | F73: =B73 -> 0 | H73: 46296 | J73: =H74 -> 46327 | K73: =I73 -> 0 | L73: =H75 -> 46357 | M73: =I73 -> 0 | O73: 46296 | Q73: =O74 -> 46327 | R73: =P73 -> 0 | S73: =O75 -> 46357 | T73: =P73 -> 0
A74: 46327 | C74: =A75 -> 46357 | D74: =B74 -> 0 | E74: =A76 -> 46388 | F74: =B74 -> 0 | H74: 46327 | J74: =H75 -> 46357 | K74: =I74 -> 0 | L74: =H76 -> 46388 | M74: =I74 -> 0 | O74: 46327 | Q74: =O75 -> 46357 | R74: =P74 -> 0 | S74: =O76 -> 46388 | T74: =P74 -> 0
A75: 46357 | C75: =A76 -> 46388 | D75: =B75 -> 0 | E75: =A77 -> 46419 | F75: =B75 -> 0 | H75: 46357 | J75: =H76 -> 46388 | K75: =I75 -> 0 | L75: =H77 -> 46419 | M75: =I75 -> 0 | O75: 46357 | Q75: =O76 -> 46388 | R75: =P75 -> 0 | S75: =O77 -> 46419 | T75: =P75 -> 0
A76: 46388 | C76: =A77 -> 46419 | D76: =B76 -> 0 | E76: =A78 -> 46447 | F76: =B76 -> 0 | H76: 46388 | J76: =H77 -> 46419 | K76: =I76 -> 0 | L76: =H78 -> 46447 | M76: =I76 -> 0 | O76: 46388 | Q76: =O77 -> 46419 | R76: =P76 -> 0 | S76: =O78 -> 46447 | T76: =P76 -> 0
A77: 46419 | C77: =A78 -> 46447 | D77: =B77 -> 0 | E77: =A79 -> 46478 | F77: =B77 -> 0 | H77: 46419 | J77: =H78 -> 46447 | K77: =I77 -> 0 | L77: =H79 -> 46478 | M77: =I77 -> 0 | O77: 46419 | Q77: =O78 -> 46447 | R77: =P77 -> 0 | S77: =O79 -> 46478 | T77: =P77 -> 0
A78: 46447 | C78: =A79 -> 46478 | D78: =B78 -> 0 | E78: =A80 -> 46508 | F78: =B78 -> 0 | H78: 46447 | J78: =H79 -> 46478 | K78: =I78 -> 0 | L78: =H80 -> 46508 | M78: =I78 -> 0 | O78: 46447 | Q78: =O79 -> 46478 | R78: =P78 -> 0 | S78: =O80 -> 46508 | T78: =P78 -> 0
A79: 46478 | C79: =A80 -> 46508 | D79: =B79 -> 0 | E79: =A81 -> 46539 | F79: =B79 -> 0 | H79: 46478 | J79: =H80 -> 46508 | K79: =I79 -> 0 | L79: =H81 -> 46539 | M79: =I79 -> 0 | O79: 46478 | Q79: =O80 -> 46508 | R79: =P79 -> 0 | S79: =O81 -> 46539 | T79: =P79 -> 0
A80: 46508 | C80: =A81 -> 46539 | D80: =B80 -> 0 | E80: =A82 -> 46569 | F80: =B80 -> 0 | H80: 46508 | J80: =H81 -> 46539 | K80: =I80 -> 0 | L80: =H82 -> 46569 | M80: =I80 -> 0 | O80: 46508 | Q80: =O81 -> 46539 | R80: =P80 -> 0 | S80: =O82 -> 46569 | T80: =P80 -> 0
A81: 46539 | C81: =A82 -> 46569 | D81: =B81 -> 0 | E81: =A83 -> 46600 | F81: =B81 -> 0 | H81: 46539 | J81: =H82 -> 46569 | K81: =I81 -> 0 | L81: =H83 -> 46600 | M81: =I81 -> 0 | O81: 46539 | Q81: =O82 -> 46569 | R81: =P81 -> 0 | S81: =O83 -> 46600 | T81: =P81 -> 0
... A96: 46997 | C96: =A97 -> 47027 | D96: =B96 -> 0 | E96: =A98 -> 47058 | F96: =B96 -> 0 | H96: 46997 | J96: =H97 -> 47027 | K96: =I96 -> 0 | L96: =H98 -> 47058 | M96: =I96 -> 0 | O96: 46997 | Q96: =O97 -> 47027 | R96: =P96 -> 0 | S96: =O98 -> 47058 | T96: =P96 -> 0
A97: 47027 | C97: =A98 -> 47058 | D97: =B97 -> 0 | E97: =A99 -> 47088 | F97: =B97 -> 0 | H97: 47027 | J97: =H98 -> 47058 | K97: =I97 -> 0 | L97: =H99 -> 47088 | M97: =I97 -> 0 | O97: 47027 | Q97: =O98 -> 47058 | R97: =P97 -> 0
A98: 47058 | C98: =A99 -> 47088 | D98: =B98 -> 0 | E98: =A100 -> 47119 | F98: =B98 -> 0 | H98: 47058 | J98: =H99 -> 47088 | K98: =I98 -> 0 | L98: =H100 -> 47119 | M98: =I98 -> 0 | O98: 47058
A99: 47088 | C99: =A100 -> 47119 | D99: =B99 -> 0 | E99: =A101 -> 47150 | F99: =B99 -> 0 | H99: 47088 | J99: =H100 -> 47119 | K99: =I99 -> 0 | L99: =H101 -> 47150 | M99: =I99 -> 0
A100: 47119 | C100: =A101 -> 47150 | D100: =B100 -> 0 | E100: =A102 -> 47178 | F100: =B100 -> 0 | H100: 47119 | J100: =H101 -> 47150 | K100: =I100 -> 0 | L100: =H102 -> 47178 | M100: =I100 -> 0
A101: 47150 | C101: =A102 -> 47178 | D101: =B101 -> 0 | E101: =A103 -> 47209 | F101: =B101 -> 0 | H101: 47150 | J101: =H102 -> 47178 | K101: =I101 -> 0 | L101: =H103 -> 47209 | M101: =I101 -> 0
A102: 47178 | C102: =A103 -> 47209 | D102: =B102 -> 0 | E102: =A104 -> 47239 | F102: =B102 -> 0 | H102: 47178 | J102: =H103 -> 47209 | K102: =I102 -> 0 | L102: =H104 -> 47239 | M102: =I102 -> 0
A103: 47209 | C103: =A104 -> 47239 | D103: =B103 -> 0 | E103: =A105 -> 47270 | F103: =B103 -> 0 | H103: 47209 | J103: =H104 -> 47239 | K103: =I103 -> 0 | L103: =H105 -> 47270 | M103: =I103 -> 0
A104: 47239 | C104: =A105 -> 47270 | D104: =B104 -> 0 | E104: =A106 -> 47300 | F104: =B104 -> 0 | H104: 47239 | J104: =H105 -> 47270 | K104: =I104 -> 0 | L104: =H106 -> 47300 | M104: =I104 -> 0
A105: 47270 | C105: =A106 -> 47300 | D105: =B105 -> 0 | E105: =A107 -> 47331 | F105: =B105 -> 0 | H105: 47270 | J105: =H106 -> 47300 | K105: =I105 -> 0 | L105: =H107 -> 47331 | M105: =I105 -> 0
A106: 47300 | C106: =A107 -> 47331 | D106: =B106 -> 0 | E106: =A108 -> 47362 | F106: =B106 -> 0 | H106: 47300 | J106: =H107 -> 47331 | K106: =I106 -> 0 | L106: =H108 -> 47362 | M106: =I106 -> 0
A107: 47331 | C107: =A108 -> 47362 | D107: =B107 -> 0 | E107: =A109 -> 47392 | F107: =B107 -> 0 | H107: 47331 | J107: =H108 -> 47362 | K107: =I107 -> 0 | L107: =H109 -> 47392 | M107: =I107 -> 0
A108: 47362 | C108: =A109 -> 47392 | D108: =B108 -> 0 | E108: =A110 -> 47423 | F108: =B108 -> 0 | H108: 47362 | J108: =H109 -> 47392 | K108: =I108 -> 0 | L108: =H110 -> 47423 | M108: =I108 -> 0
A109: 47392 | C109: =A110 -> 47423 | D109: =B109 -> 0 | E109: =A111 -> 47453 | F109: =B109 -> 0 | H109: 47392 | J109: =H110 -> 47423 | K109: =I109 -> 0 | L109: =H111 -> 47453 | M109: =I109 -> 0
A110: 47423 | C110: =A111 -> 47453 | D110: =B110 -> 0 | E110: =A112 -> 47484 | F110: =B110 -> 0 | H110: 47423 | J110: =H111 -> 47453 | K110: =I110 -> 0 | L110: =H112 -> 47484 | M110: =I110 -> 0
A111: 47453 | C111: =A112 -> 47484 | D111: =B111 -> 0 | H111: 47453 | J111: =H112 -> 47484 | K111: =I111 -> 0
A112: 47484 | H112: 47484

Sheet Croma
A1: INCC M - Vigente | B1: ='IND. FIN.'!V1 -> 46204 | C1: =VLOOKUP(B1,'IND. FIN.'!$J$4:$K$97,2,0) -> 1275.085 | D1: Contrato Piemonte | L1: Contratos Terceiro
A2: INCC - Base | B2: 44958 | C2: ='IND. FIN.'!K16 -> 967.003 | D2: R$ | G2: INCC | L2: Thal | S2: =IF(S3>$B$1,0,VLOOKUP(S$3,'IND. FIN.'!$C$4:$D$97,2,0)) -> 1043.76 | W2: =IF(W3>$B$1,0,VLOOKUP(W$3,'IND. FIN.'!$C$4:$D$97,2,0)) -> 1044.679 | AA2: =IF(AA3>$B$1,0,VLOOKUP(AA$3,'IND. FIN.'!$C$4:$D$97,2,0)) -> 1045.616 | AE2: =IF(AE3>$B$1,0,VLOOKUP(AE$3,'IND. FIN.'!$C$4:$D$97,2,0)) -> 1046.896 | AI2: =IF(AI3>$B$1,0,VLOOKUP(AI$3,'IND. FIN.'!$C$4:$D$97,2,0)) -> 1050.701 | AM2: =IF(AM3>$B$1,0,VLOOKUP(AM$3,'IND. FIN.'!$C$4:$D$97,2,0)) -> 1051.632 | AQ2: =IF(AQ3>$B$1,0,VLOOKUP(AQ$3,'IND. FIN.'!$C$4:$D$97,2,0)) -> 1056.418 | AU2: =IF(AU3>$B$1,0,VLOOKUP(AU$3,'IND. FIN.'!$C$4:$D$97,2,0)) -> 1056.896 | AY2: =IF(AY3>$B$1,0,VLOOKUP(AY$3,'IND. FIN.'!$C$4:$D$97,2,0)) -> 1060.116 | BC2: =IF(BC3>$B$1,0,VLOOKUP(BC$3,'IND. FIN.'!$C$4:$D$97,2,0)) -> 1061.635 | BG2: =IF(BG3>$B$1,0,VLOOKUP(BG$3,'IND. FIN.'!$C$4:$D$97,2,0)) -> 1067.919 | BK2: =IF(BK3>$B$1,0,VLOOKUP(BK$3,'IND. FIN.'!$C$4:$D$97,2,0)) -> 1075.54 | BO2: =IF(BO3>$B$1,0,VLOOKUP(BO$3,'IND. FIN.'!$C$4:$D$97,2,0)) -> 1076.626 | BS2: =IF(BS3>$B$1,0,VLOOKUP(BS$3,'IND. FIN.'!$C$4:$D$97,2,0)) -> 1078.412 | BW2: =IF(BW3>$B$1,0,VLOOKUP(BW$3,'IND. FIN.'!$C$4:$D$97,2,0)) -> 1082.104 | CA2: =IF(CA3>$B$1,0,VLOOKUP(CA$3,'IND. FIN.'!$C$4:$D$97,2,0)) -> 1084.242 | CE2: =IF(CE3>$B$1,0,VLOOKUP(CE$3,'IND. FIN.'!$C$4:$D$97,2,0)) -> 1084.986 | CI2: =IF(CI3>$B$1,0,VLOOKUP(CI$3,'IND. FIN.'!$C$4:$D$97,2,0)) -> 1088.312 | CM2: =IF(CM3>$B$1,0,VLOOKUP(CM$3,'IND. FIN.'!$C$4:$D$97,2,0)) -> 1091.25 | CQ2: =IF(CQ3>$B$1,0,VLOOKUP(CQ$3,'IND. FIN.'!$C$4:$D$97,2,0)) -> 1092.685 | CU2: =IF(CU3>$B$1,0,VLOOKUP(CU$3,'IND. FIN.'!$C$4:$D$97,2,0)) -> 1095.738 | CY2: =IF(CY3>$B$1,0,VLOOKUP(CY$3,'IND. FIN.'!$C$4:$D$97,2,0)) -> 1101.389 | DC2: =IF(DC3>$B$1,0,VLOOKUP(DC$3,'IND. FIN.'!$C$4:$D$97,2,0)) -> 1110.887 | DG2: =IF(DG3>$B$1,0,VLOOKUP(DG$3,'IND. FIN.'!$C$4:$D$97,2,0)) -> 1118.827 | DK2: =IF(DK3>$B$1,0,VLOOKUP(DK$3,'IND. FIN.'!$C$4:$D$97,2,0)) -> 1126.916 | DO2: =IF(DO3>$B$1,0,VLOOKUP(DO$3,'IND. FIN.'!$C$4:$D$97,2,0)) -> 1134.775 | DS2: =IF(DS3>$B$1,0,VLOOKUP(DS$3,'IND. FIN.'!$C$4:$D$97,2,0)) -> 1141.398 | DW2: =IF(DW3>$B$1,0,VLOOKUP(DW$3,'IND. FIN.'!$C$4:$D$97,2,0)) -> 1149.17 | EA2: =IF(EA3>$B$1,0,VLOOKUP(EA$3,'IND. FIN.'!$C$4:$D$97,2,0)) -> 1153.725 | EE2: =IF(EE3>$B$1,0,VLOOKUP(EE$3,'IND. FIN.'!$C$4:$D$97,2,0)) -> 1159.536 | EI2: =IF(EI3>$B$1,0,VLOOKUP(EI$3,'IND. FIN.'!$C$4:$D$97,2,0)) -> 1169.116 | EM2: =IF(EM3>$B$1,0,VLOOKUP(EM$3,'IND. FIN.'!$C$4:$D$97,2,0)) -> 1173.775 | EQ2: =IF(EQ3>$B$1,0,VLOOKUP(EQ$3,'IND. FIN.'!$C$4:$D$97,2,0)) -> 1178.386 | EU2: =IF(EU3>$B$1,0,VLOOKUP(EU$3,'IND. FIN.'!$C$4:$D$97,2,0)) -> 1184.462 | EY2: =IF(EY3>$B$1,0,VLOOKUP(EY$3,'IND. FIN.'!$C$4:$D$97,2,0)) -> 1191.327 | FC2: =IF(FC3>$B$1,0,VLOOKUP(FC$3,'IND. FIN.'!$C$4:$D$97,2,0)) -> 1199.509 | FG2: =IF(FG3>$B$1,0,VLOOKUP(FG$3,'IND. FIN.'!$C$4:$D$97,2,0)) -> 1210.471 | FK2: =IF(FK3>$B$1,0,VLOOKUP(FK$3,'IND. FIN.'!$C$4:$D$97,2,0)) -> 1216.706
A3: Orçamento base | D3: Valor total | E3: Valor unitário | F3: Saldo | G3: Valor total | H3: Valor unitário | I3: Total medido Piemonte | J3: Total medido Terceiros | K3: Saldo | L3: Prazo | M3: Valor total | N3: Valor unitário | O3: Prazo | P3: Valor total | Q3: Valor unitário | R3: Saldo | S3: 44774 | W3: =EDATE(S3,1) -> 44805 | AA3: =EDATE(W3,1) -> 44835 | AE3: =EDATE(AA3,1) -> 44866 | AI3: =EDATE(AE3,1) -> 44896 | AM3: =EDATE(AI3,1) -> 44927 | AQ3: =EDATE(AM3,1) -> 44958 | AU3: =EDATE(AQ3,1) -> 44986 | AY3: =EDATE(AU3,1) -> 45017 | BC3: =EDATE(AY3,1) -> 45047 | BG3: =EDATE(BC3,1) -> 45078 | BK3: =EDATE(BG3,1) -> 45108 | BO3: =EDATE(BK3,1) -> 45139 | BS3: =EDATE(BO3,1) -> 45170 | BW3: =EDATE(BS3,1) -> 45200 | CA3: =EDATE(BW3,1) -> 45231 | CE3: =EDATE(CA3,1) -> 45261 | CI3: =EDATE(CE3,1) -> 45292 | CM3: =EDATE(CI3,1) -> 45323 | CQ3: =EDATE(CM3,1) -> 45352 | CU3: =EDATE(CQ3,1) -> 45383 | CY3: =EDATE(CU3,1) -> 45413 | DC3: =EDATE(CY3,1) -> 45444 | DG3: =EDATE(DC3,1) -> 45474 | DK3: =EDATE(DG3,1) -> 45505 | DO3: =EDATE(DK3,1) -> 45536 | DS3: =EDATE(DO3,1) -> 45566 | DW3: =EDATE(DS3,1) -> 45597 | EA3: =EDATE(DW3,1) -> 45627 | EE3: =EDATE(EA3,1) -> 45658 | EI3: =EDATE(EE3,1) -> 45689 | EM3: =EDATE(EI3,1) -> 45717 | EQ3: =EDATE(EM3,1) -> 45748 | EU3: =EDATE(EQ3,1) -> 45778 | EY3: =EDATE(EU3,1) -> 45809 | FC3: =EDATE(EY3,1) -> 45839 | FG3: =EDATE(FC3,1) -> 45870 | FK3: =EDATE(FG3,1) -> 45901
A4: 01.01.04.01 | B4: PESSOAL | C4: Prazo | S4: Medido Piemonte | T4: Medido Piemonte INCC | U4: Medido Terceiros INCC | V4: Medido Terceiros | W4: Medido Piemonte | X4: Medido Piemonte INCC | Y4: Medido Terceiros INCC | Z4: Medido Terceiros | AA4: Medido Piemonte | AB4: Medido Piemonte INCC | AC4: Medido Terceiros INCC | AD4: Medido Terceiros | AE4: Medido Piemonte | AF4: Medido Piemonte INCC | AG4: Medido Terceiros INCC | AH4: Medido Terceiros | AI4: Medido Piemonte | AJ4: Medido Piemonte INCC | AK4: Medido Terceiros INCC | AL4: Medido Terceiros | AM4: Medido Piemonte | AN4: Medido Piemonte INCC | AO4: Medido Terceiros INCC | AP4: Medido Terceiros | AQ4: Medido Piemonte | AR4: Medido Piemonte INCC | AS4: Medido Terceiros INCC | AT4: Medido Terceiros | AU4: Medido Piemonte | AV4: Medido Piemonte INCC | AW4: Medido Terceiros INCC | AX4: Medido Terceiros | AY4: Medido Piemonte | AZ4: Medido Piemonte INCC | BA4: Medido Terceiros INCC | BB4: Medido Terceiros | BC4: Medido Piemonte | BD4: Medido Piemonte INCC | BE4: Medido Terceiros INCC | BF4: Medido Terceiros | BG4: Medido Piemonte | BH4: Medido Piemonte INCC | BI4: Medido Terceiros INCC | BJ4: Medido Terceiros | BK4: Medido Piemonte | BL4: Medido Piemonte INCC | BM4: Medido Terceiros INCC | BN4: Medido Terceiros | BO4: Medido Piemonte | BP4: Medido Piemonte INCC | BQ4: Medido Terceiros INCC | BR4: Medido Terceiros | BS4: Medido Piemonte | BT4: Medido Piemonte INCC | BU4: Medido Terceiros INCC | BV4: Medido Terceiros | BW4: Medido Piemonte | BX4: Medido Piemonte INCC | BY4: Medido Terceiros INCC | BZ4: Medido Terceiros | CA4: Medido Piemonte | CB4: Medido Piemonte INCC | CC4: Medido Terceiros INCC | CD4: Medido Terceiros | CE4: Medido Piemonte | CF4: Medido Piemonte INCC | CG4: Medido Terceiros INCC | CH4: Medido Terceiros | CI4: Medido Piemonte | CJ4: Medido Piemonte INCC | CK4: Medido Terceiros INCC | CL4: Medido Terceiros | CM4: Medido Piemonte | CN4: Medido Piemonte INCC | CO4: Medido Terceiros INCC | CP4: Medido Terceiros | CQ4: Medido Piemonte | CR4: Medido Piemonte INCC | CS4: Medido Terceiros INCC | CT4: Medido Terceiros | CU4: Medido Piemonte | CV4: Medido Piemonte INCC | CW4: Medido Terceiros INCC | CX4: Medido Terceiros | CY4: Medido Piemonte | CZ4: Medido Piemonte INCC | DA4: Medido Terceiros INCC | DB4: Medido Terceiros | DC4: Medido Piemonte | DD4: Medido Piemonte INCC | DE4: Medido Terceiros INCC | DF4: Medido Terceiros | DG4: Medido Piemonte | DH4: Medido Piemonte INCC | DI4: Medido Terceiros INCC | DJ4: Medido Terceiros | DK4: Medido Piemonte | DL4: Medido Piemonte INCC | DM4: Medido Terceiros INCC | DN4: Medido Terceiros | DO4: Medido Piemonte | DP4: Medido Piemonte INCC | DQ4: Medido Terceiros INCC | DR4: Medido Terceiros | DS4: Medido Piemonte | DT4: Medido Piemonte INCC | DU4: Medido Terceiros INCC | DV4: Medido Terceiros | DW4: Medido Piemonte | DX4: Medido Piemonte INCC | DY4: Medido Terceiros INCC | DZ4: Medido Terceiros | EA4: Medido Piemonte | EB4: Medido Piemonte INCC | EC4: Medido Terceiros INCC | ED4: Medido Terceiros | EE4: Medido Piemonte | EF4: Medido Piemonte INCC | EG4: Medido Terceiros INCC | EH4: Medido Terceiros | EI4: Medido Piemonte | EJ4: Medido Piemonte INCC | EK4: Medido Terceiros INCC | EL4: Medido Terceiros | EM4: Medido Piemonte | EN4: Medido Piemonte INCC | EO4: Medido Terceiros INCC | EP4: Medido Terceiros | EQ4: Medido Piemonte | ER4: Medido Piemonte INCC | ES4: Medido Terceiros INCC | ET4: Medido Terceiros | EU4: Medido Piemonte | EV4: Medido Piemonte INCC | EW4: Medido Terceiros INCC | EX4: Medido Terceiros | EY4: Medido Piemonte | EZ4: Medido Piemonte INCC | FA4: Medido Terceiros INCC | FB4: Medido Terceiros | FC4: Medido Piemonte | FD4: Medido Piemonte INCC | FE4: Medido Terceiros INCC | FF4: Medido Terceiros | FG4: Medido Piemonte | FH4: Medido Piemonte INCC | FI4: Medido Terceiros INCC | FJ4: Medido Terceiros | FK4: Medido Piemonte | FL4: Medido Piemonte INCC | FM4: Medido Terceiros INCC | FN4: Medido Terceiros
A5: 01.01.04.01.001 | B5: COORDENADOR DE OBRAS | C5: 37 | D5: =E5*C5 -> 666000 | E5: 18000 | F5: =K5*$C$1 -> -75090.788 | G5: =D5/$C$2 -> 688.72589 | H5: =E5/$C$2 -> 18.614213 | I5: =SUMIFS($S5:$FN5,$S$4:$FN$4,$T$4) -> 747.6167 | J5: =SUMIFS($S5:$FN5,$S$4:$FN$4,$U$4) -> 0 | K5: =G5-I5-J5 -> -58.890809 | R5: =M5-SUMIFS(S5:ET5,$S$4:$ET$4,$V$4) -> 0 | S5: 19460.583 | T5: 18.675664 | U5: 0 | W5: 19460.583 | X5: 18.614213 | Y5: 0 | AA5: 19460.573 | AB5: 18.595741 | AC5: 0 | AE5: 19513.722 | AF5: 18.638532 | AG5: 0 | AI5: 19109.02 | AJ5: 18.226336 | AK5: 0 | AM5: 19617.552 | AN5: 18.661185 | AO5: 0 | AQ5: 19670.986 | AR5: 18.653246 | AS5: 0 | AU5: 19705.886 | AV5: 18.647192 | AW5: 0 | AY5: 19750.951 | AZ5: 18.656734 | BA5: 0 | BC5: 19829.57 | BD5: 18.688259 | BE5: 0 | BG5: 19997.051 | BH5: 18.77148 | BI5: 0 | BK5: 20008.371 | BL5: 18.624704 | BM5: 0 | BO5: 62392.633 | BP5: 58.045329 | BQ5: 0 | BS5: 20104.599 | BT5: 18.658613 | BU5: 0 | BW5: 20145.163 | BX5: 18.651703 | BY5: 0 | CA5: 20165.389 | CB5: 18.632821 | CC5: 0 | CE5: 20217.845 | CF5: 18.662598 | CG5: 0 | CI5: 20264.678 | CJ5: 18.657348 | CK5: 0 | CM5: 20305.624 | CN5: 18.651892 | CO5: 0 | CQ5: 20354.652 | CR5: 18.659083 | CS5: 0 | CU5: 20438.262 | CV5: 18.690631 | CW5: 0 | CY5: 20558.663 | CZ5: 18.72389 | DA5: 0 | DC5: 20750.151 | DD5: 18.78765 | DE5: 0 | DG5: 20893.578 | DH5: 18.742871 | DI5: 0 | DK5: 20893.561 | DL5: 18.614213 | DM5: 0 | DO5: 21027.341 | DP5: 18.614213 | DQ5: 0 | DS5: 21155.444 | DT5: 18.614213 | DU5: 0 | DW5: 21297.191 | DX5: 18.614213 | DY5: 0 | EA5: 21390.672 | EB5: 18.614213 | EC5: 0 | EE5: 21499.23 | EF5: 18.614213 | EG5: 0 | EI5: =IF($E5*EI$2/$C$2-EL5>0,$E5*EI$2/$C$2-EL5,0) -> 21762.174 | EJ5: =IFERROR(EI5/EI$2,0) -> 18.614213 | EK5: =IFERROR(EL5/EI$2,0) -> 0 | EM5: =IF($E5*EM$2/$C$2-EP5>0,$E5*EM$2/$C$2-EP5,0) -> 21848.898 | EN5: =IFERROR(EM5/EM$2,0) -> 18.614213 | EO5: =IFERROR(EP5/EM$2,0) -> 0 | EQ5: =IF($E5*EQ$2/$C$2-ET5>0,$E5*EQ$2/$C$2-ET5,0) -> 21934.728 | ER5: =IFERROR(EQ5/EQ$2,0) -> 18.614213 | ES5: =IFERROR(ET5/EQ$2,0) -> 0 | EU5: =IF($E5*EU$2/$C$2-EX5>0,$E5*EU$2/$C$2-EX5,0) -> 22047.828 | EV5: =IFERROR(EU5/EU$2,0) -> 18.614213 | EW5: =IFERROR(EX5/EU$2,0) -> 0 | EY5: =IF($E5*EY$2/$C$2-FB5>0,$E5*EY$2/$C$2-FB5,0) -> 22175.615 | EZ5: =IFERROR(EY5/EY$2,0) -> 18.614213 | FA5: =IFERROR(FB5/EY$2,0) -> 0 | FC5: =IF($E5*FC$2/$C$2-FF5>0,$E5*FC$2/$C$2-FF5,0) -> 22327.916 | FD5: =IFERROR(FC5/FC$2,0) -> 18.614213 | FE5: =IFERROR(FF5/FC$2,0) -> 0 | FG5: =IF($E5*FG$2/$C$2-FJ5>0,$E5*FG$2/$C$2-FJ5,0) -> 22531.965 | FH5: =IFERROR(FG5/FG$2,0) -> 18.614213 | FI5: =IFERROR(FJ5/FG$2,0) -> 0 | FK5: =IF($E5*FK$2/$C$2-FN5>0,$E5*FK$2/$C$2-FN5,0) -> 22648.025 | FL5: =IFERROR(FK5/FK$2,0) -> 18.614213 | FM5: =IFERROR(FN5/FK$2,0) -> 0
A6: 01.01.04.01.002 | B6: ENGENHEIRO RESIDENTE | C6: 37 | D6: =E6*C6 -> 518000 | E6: 14000 | F6: =K6*$C$1 -> -838.73931 | G6: =D6/$C$2 -> 535.67569 | H6: =E6/$C$2 -> 14.477721 | I6: =SUMIFS($S6:$FN6,$S$4:$FN$4,$T$4) -> 536.33348 | J6: =SUMIFS($S6:$FN6,$S$4:$FN$4,$U$4) -> 0 | K6: =G6-I6-J6 -> -0.6577909 | R6: =M6-SUMIFS(S6:ET6,$S$4:$ET$4,$V$4) -> 0 | S6: 15136.009 | T6: 14.525516 | U6: 0 | W6: 15136.009 | X6: 14.477721 | Y6: 0 | AA6: 15136.016 | AB6: 14.463368 | AC6: 0 | AE6: 15177.29 | AF6: 14.496588 | AG6: 0 | AI6: 14862.564 | AJ6: 14.176033 | AK6: 0 | AM6: 15258.046 | AN6: 14.514207 | AO6: 0 | AQ6: 15299.711 | AR6: 14.508133 | AS6: 0 | AU6: 15326.856 | AV6: 14.503424 | AW6: 0 | AY6: 15361.907 | AZ6: 14.510846 | BA6: 0 | BC6: 15422.934 | BD6: 14.535252 | BE6: 0 | BG6: 15553.322 | BH6: 14.600096 | BI6: 0 | BK6: 15561.999 | BL6: 14.485818 | BM6: 0 | BO6: 0 | BP6: 0 | BQ6: 0 | BS6: 15636.985 | BT6: 14.512323 | BU6: 0 | BW6: 15668.549 | BX6: 14.506962 | BY6: 0 | CA6: 15684.244 | CB6: 14.492242 | CC6: 0 | CE6: 15724.976 | CF6: 14.51534 | CG6: 0 | CI6: 15761.341 | CJ6: 14.511201 | CK6: 0 | CM6: 15793.361 | CN6: 14.507117 | CO6: 0 | CQ6: 15831.449 | CR6: 14.512668 | CS6: 0 | CU6: 15896.441 | CV6: 14.537172 | CW6: 0 | CY6: 15989.987 | CZ6: 14.562949 | DA6: 0 | DC6: 16138.999 | DD6: 14.61261 | DE6: 0 | DG6: 16250.568 | DH6: 14.577796 | DI6: 0 | DK6: 16250.547 | DL6: 14.477721 | DM6: 0 | DO6: 16354.599 | DP6: 14.477721 | DQ6: 0 | DS6: 16454.234 | DT6: 14.477721 | DU6: 0 | DW6: 16564.482 | DX6: 14.477721 | DY6: 0 | EA6: 16637.189 | EB6: 14.477721 | EC6: 0 | EE6: 16721.623 | EF6: 14.477721 | EG6: 0 | EI6: =IF($E6*EI$2/$C$2-EL6>0,$E6*EI$2/$C$2-EL6,0) -> 16926.136 | EJ6: =IFERROR(EI6/EI$2,0) -> 14.477721 | EK6: =IFERROR(EL6/EI$2,0) -> 0 | EM6: =IF($E6*EM$2/$C$2-EP6>0,$E6*EM$2/$C$2-EP6,0) -> 16993.587 | EN6: =IFERROR(EM6/EM$2,0) -> 14.477721 | EO6: =IFERROR(EP6/EM$2,0) -> 0 | EQ6: =IF($E6*EQ$2/$C$2-ET6>0,$E6*EQ$2/$C$2-ET6,0) -> 17060.344 | ER6: =IFERROR(EQ6/EQ$2,0) -> 14.477721 | ES6: =IFERROR(ET6/EQ$2,0) -> 0 | EU6: =IF($E6*EU$2/$C$2-EX6>0,$E6*EU$2/$C$2-EX6,0) -> 17148.311 | EV6: =IFERROR(EU6/EU$2,0) -> 14.477721 | EW6: =IFERROR(EX6/EU$2,0) -> 0 | EY6: =IF($E6*EY$2/$C$2-FB6>0,$E6*EY$2/$C$2-FB6,0) -> 17247.7 | EZ6: =IFERROR(EY6/EY$2,0) -> 14.477721 | FA6: =IFERROR(FB6/EY$2,0) -> 0 | FC6: =IF($E6*FC$2/$C$2-FF6>0,$E6*FC$2/$C$2-FF6,0) -> 17366.157 | FD6: =IFERROR(FC6/FC$2,0) -> 14.477721 | FE6: =IFERROR(FF6/FC$2,0) -> 0 | FG6: =IF($E6*FG$2/$C$2-FJ6>0,$E6*FG$2/$C$2-FJ6,0) -> 17524.862 | FH6: =IFERROR(FG6/FG$2,0) -> 14.477721 | FI6: =IFERROR(FJ6/FG$2,0) -> 0 | FK6: =IF($E6*FK$2/$C$2-FN6>0,$E6*FK$2/$C$2-FN6,0) -> 17615.13 | FL6: =IFERROR(FK6/FK$2,0) -> 14.477721 | FM6: =IFERROR(FN6/FK$2,0) -> 0
A7: 01.01.04.01.003 | B7: ESTAGIARIO | C7: 37 | D7: =E7*C7 -> 107300 | E7: 2900 | F7: =K7*$C$1 -> -173.6174 | G7: =D7/$C$2 -> 110.96139 | H7: =E7/$C$2 -> 2.9989566 | I7: =SUMIFS($S7:$FN7,$S$4:$FN$4,$T$4) -> 111.09755 | J7: =SUMIFS($S7:$FN7,$S$4:$FN$4,$U$4) -> 0 | K7: =G7-I7-J7 -> -0.13616143 | R7: =M7-SUMIFS(S7:ET7,$S$4:$ET$4,$V$4) -> 0 | S7: 3135.316 | T7: 3.0088568 | U7: 0 | W7: 3135.316 | X7: 2.9989564 | Y7: 0 | AA7: 3135.3301 | AB7: 2.9959953 | AC7: 0 | AE7: 3143.8386 | AF7: 3.0028374 | AG7: 0 | AI7: 3078.7038 | AJ7: 2.9364924 | AK7: 0 | AM7: 3160.5826 | AN7: 3.0065024 | AO7: 0 | AQ7: 3169.2053 | AR7: 3.0052366 | AS7: 0 | AU7: 3174.8282 | AV7: 3.0042613 | AW7: 0 | AY7: 3182.0886 | AZ7: 3.0057985 | BA7: 0 | BC7: 3194.7608 | BD7: 3.0108832 | BE7: 0 | BG7: 3221.7845 | BH7: 3.0243291 | BI7: 0 | BK7: 3223.5675 | BL7: 3.0006437 | BM7: 0 | BO7: 0 | BP7: 0 | BQ7: 0 | BS7: 3239.0873 | BT7: 3.0061219 | BU7: 0 | BW7: 3245.5985 | BX7: 3.0049862 | BY7: 0 | CA7: 3248.8892 | CB7: 3.0019738 | CC7: 0 | CE7: 3257.2866 | CF7: 3.0067215 | CG7: 0 | CI7: 3264.8213 | CJ7: 3.0058659 | CK7: 0 | CM7: 3271.4839 | CN7: 3.0050474 | CO7: 0 | CQ7: 3279.3614 | CR7: 3.0061862 | CS7: 0 | CU7: 3292.8303 | CV7: 3.0112677 | CW7: 0 | CY7: 3312.2469 | CZ7: 3.016643 | DA7: 0 | DC7: 3343.0527 | DD7: 3.0268745 | DE7: 0 | DG7: 3366.1837 | DH7: 3.0196813 | DI7: 0 | DK7: 3366.1848 | DL7: 2.9989566 | DM7: 0 | DO7: 3387.7383 | DP7: 2.9989566 | DQ7: 0 | DS7: 3408.3771 | DT7: 2.9989566 | DU7: 0 | DW7: 3431.2142 | DX7: 2.9989566 | DY7: 0 | EA7: 3446.2749 | EB7: 2.9989566 | EC7: 0 | EE7: 3463.7648 | EF7: 2.9989566 | EG7: 0 | EI7: =IF($E7*EI$2/$C$2-EL7>0,$E7*EI$2/$C$2-EL7,0) -> 3506.1281 | EJ7: =IFERROR(EI7/EI$2,0) -> 2.9989566 | EK7: =IFERROR(EL7/EI$2,0) -> 0 | EM7: =IF($E7*EM$2/$C$2-EP7>0,$E7*EM$2/$C$2-EP7,0) -> 3520.1002 | EN7: =IFERROR(EM7/EM$2,0) -> 2.9989566 | EO7: =IFERROR(EP7/EM$2,0) -> 0 | EQ7: =IF($E7*EQ$2/$C$2-ET7>0,$E7*EQ$2/$C$2-ET7,0) -> 3533.9284 | ER7: =IFERROR(EQ7/EQ$2,0) -> 2.9989566 | ES7: =IFERROR(ET7/EQ$2,0) -> 0 | EU7: =IF($E7*EU$2/$C$2-EX7>0,$E7*EU$2/$C$2-EX7,0) -> 3552.1501 | EV7: =IFERROR(EU7/EU$2,0) -> 2.9989566 | EW7: =IFERROR(EX7/EU$2,0) -> 0 | EY7: =IF($E7*EY$2/$C$2-FB7>0,$E7*EY$2/$C$2-FB7,0) -> 3572.7379 | EZ7: =IFERROR(EY7/EY$2,0) -> 2.9989566 | FA7: =IFERROR(FB7/EY$2,0) -> 0 | FC7: =IF($E7*FC$2/$C$2-FF7>0,$E7*FC$2/$C$2-FF7,0) -> 3597.2754 | FD7: =IFERROR(FC7/FC$2,0) -> 2.9989566 | FE7: =IFERROR(FF7/FC$2,0) -> 0 | FG7: =IF($E7*FG$2/$C$2-FJ7>0,$E7*FG$2/$C$2-FJ7,0) -> 3630.15 | FH7: =IFERROR(FG7/FG$2,0) -> 2.9989566 | FI7: =IFERROR(FJ7/FG$2,0) -> 0 | FK7: =IF($E7*FK$2/$C$2-FN7>0,$E7*FK$2/$C$2-FN7,0) -> 3648.8485 | FL7: =IFERROR(FK7/FK$2,0) -> 2.9989566 | FM7: =IFERROR(FN7/FK$2,0) -> 0
A8: 01.01.04.01.004 | B8: MESTRE DE OBRAS | C8: 37 | D8: =E8*C8 -> 764283.47 | E8: 20656.31 | F8: =K8*$C$1 -> -256965.28 | G8: =D8/$C$2 -> 790.36308 | H8: =E8/$C$2 -> 21.361164 | I8: =SUMIFS($S8:$FN8,$S$4:$FN$4,$T$4) -> 215.47715 | J8: =SUMIFS($S8:$FN8,$S$4:$FN$4,$U$4) -> 776.41389 | K8: =G8-I8-J8 -> -201.52796 | L8: 36 | M8: 934937.64 | N8: =M8/L8 -> 25970.49 | O8: 21 | P8: 37339.708 | Q8: =P8/O8 -> 1778.0814 | R8: =M8-SUMIFS(S8:ET8,$S$4:$ET$4,$V$4) -> 97977.963 | S8: 0 | T8: 0 | U8: 22.077255 | V8: 23005.14 | W8: 0 | X8: 0 | Y8: 22.004612 | Z8: 23005.14 | AA8: 0 | AB8: 0 | AC8: 21.982723 | AD8: 23005.073 | AE8: 0 | AF8: 0 | AG8: 21.973356 | AH8: 23005.136 | AI8: 0 | AJ8: 0 | AK8: 36.084415 | AL8: 37831.947 | AM8: 0 | AN8: 0 | AO8: 24.704448 | AP8: 25970.526 | AQ8: 0 | AR8: 0 | AS8: 104.29878 | AT8: 109989.42 | AU8: 0 | AV8: 0 | AW8: 19.660145 | AX8: 20776.35 | AY8: 0 | AZ8: 0 | BA8: 24.531701 | BB8: 25970.485 | BC8: 1979.4356 | BD8: 1.8655072 | BE8: 19.580555 | BF8: 20776.359 | BG8: 0 | BH8: 0 | BI8: 24.196671 | BJ8: 25776.447 | BK8: 0 | BL8: 0 | BM8: 28.89792 | BN8: 31044.805 | BO8: 0 | BP8: 0 | BQ8: 27.796914 | BR8: 29878.764 | BS8: 0 | BT8: 0 | BU8: 18.221114 | BV8: 19633.196 | BW8: 0 | BX8: 0 | BY8: 25.487614 | BZ8: 27528.433 | CA8: 0 | CB8: 0 | CC8: 25.436694 | CD8: 27528.887 | CE8: 0 | CF8: 0 | CG8: 25.410912 | CH8: 27528.53 | CI8: 0 | CJ8: 0 | CK8: 20.276185 | CL8: 22022.978 | CM8: 0 | CN8: 0 | CO8: 30.951043 | CP8: 33695.255 | CQ8: 0 | CR8: 0 | CS8: 25.235491 | CT8: 27528.665 | CU8: 0 | CV8: 0 | CW8: 25.175094 | CX8: 27529.041 | CY8: 0 | CZ8: 0 | DA8: 25.072066 | DB8: 27528.903 | DC8: 0 | DD8: 0 | DE8: 43.103628 | DF8: 47606.103 | DG8: 0 | DH8: 0 | DI8: 36.512471 | DJ8: 40702.204 | DK8: 0 | DL8: 0 | DM8: 19.620413 | DN8: 22022.972 | DO8: 0 | DP8: 0 | DQ8: 19.495584 | DR8: 22022.972 | DS8: 0 | DT8: 0 | DU8: 19.377532 | DV8: 22022.972 | DW8: 0 | DX8: 0 | DY8: 19.248561 | DZ8: 22022.972 | EA8: 24547.353 | EB8: 21.361164 | EC8: 0 | EE8: 24671.931 | EF8: 21.361164 | EG8: 0 | EI8: =IF($E8*EI$2/$C$2-EL8>0,$E8*EI$2/$C$2-EL8,0) -> 24973.679 | EJ8: =IFERROR(EI8/EI$2,0) -> 21.361164 | EK8: =IFERROR(EL8/EI$2,0) -> 0 | EM8: =IF($E8*EM$2/$C$2-EP8>0,$E8*EM$2/$C$2-EP8,0) -> 25073.201 | EN8: =IFERROR(EM8/EM$2,0) -> 21.361164 | EO8: =IFERROR(EP8/EM$2,0) -> 0 | EQ8: =IF($E8*EQ$2/$C$2-ET8>0,$E8*EQ$2/$C$2-ET8,0) -> 25171.697 | ER8: =IFERROR(EQ8/EQ$2,0) -> 21.361164 | ES8: =IFERROR(ET8/EQ$2,0) -> 0 | EU8: =IF($E8*EU$2/$C$2-EX8>0,$E8*EU$2/$C$2-EX8,0) -> 25301.487 | EV8: =IFERROR(EU8/EU$2,0) -> 21.361164 | EW8: =IFERROR(EX8/EU$2,0) -> 0 | EY8: =IF($E8*EY$2/$C$2-FB8>0,$E8*EY$2/$C$2-FB8,0) -> 25448.132 | EZ8: =IFERROR(EY8/EY$2,0) -> 21.361164 | FA8: =IFERROR(FB8/EY$2,0) -> 0 | FC8: =IF($E8*FC$2/$C$2-FF8>0,$E8*FC$2/$C$2-FF8,0) -> 25622.909 | FD8: =IFERROR(FC8/FC$2,0) -> 21.361164 | FE8: =IFERROR(FF8/FC$2,0) -> 0 | FG8: =IF($E8*FG$2/$C$2-FJ8>0,$E8*FG$2/$C$2-FJ8,0) -> 25857.07 | FH8: =IFERROR(FG8/FG$2,0) -> 21.361164 | FI8: =IFERROR(FJ8/FG$2,0) -> 0 | FK8: =IF($E8*FK$2/$C$2-FN8>0,$E8*FK$2/$C$2-FN8,0) -> 25990.257 | FL8: =IFERROR(FK8/FK$2,0) -> 21.361164 | FM8: =IFERROR(FN8/FK$2,0) -> 0
A9: 01.01.04.01.005 | B9: CONTRA-MESTRE DE OBRAS | C9: 37 | D9: =E9*C9 -> 467752.52 | E9: 12641.96 | F9: =K9*$C$1 -> -32941.994 | G9: =D9/$C$2 -> 483.71362 | H9: =E9/$C$2 -> 13.073341 | I9: =SUMIFS($S9:$FN9,$S$4:$FN$4,$T$4) -> 104.58673 | J9: =SUMIFS($S9:$FN9,$S$4:$FN$4,$U$4) -> 404.96203 | K9: =G9-I9-J9 -> -25.835136 | L9: 30 | M9: 476829.36 | N9: =M9/L9 -> 15894.312 | O9: 21 | P9: 28609.754 | Q9: =P9/O9 -> 1362.3693 | R9: =M9-SUMIFS(S9:ET9,$S$4:$ET$4,$V$4) -> 29545.247 | S9: 0 | T9: 0 | U9: 0 | V9: 0 | W9: 0 | X9: 0 | Y9: 0 | Z9: 0 | AA9: 0 | AB9: 0 | AC9: 0 | AD9: 0 | AE9: 0 | AF9: 0 | AG9: 0 | AH9: 0 | AI9: 0 | AJ9: 0 | AK9: 0 | AL9: 0 | AM9: 0 | AN9: 0 | AO9: 0 | AP9: 0 | AQ9: 0 | AR9: 0 | AS9: 0 | AT9: 0 | AU9: 0 | AV9: 0 | AW9: 0 | AX9: 0 | AY9: 0 | AZ9: 0 | BA9: 0 | BB9: 0 | BC9: 0 | BD9: 0 | BE9: 0 | BF9: 0 | BG9: 0 | BH9: 0 | BI9: 0 | BJ9: 0 | BK9: 0 | BL9: 0 | BM9: 15.023643 | BN9: 16139.78 | BO9: 0 | BP9: 0 | BQ9: 25.710129 | BR9: 27635.689 | BS9: 0 | BT9: 0 | BU9: 13.93952 | BV9: 15019.791 | BW9: 0 | BX9: 0 | BY9: 15.598645 | BZ9: 16847.644 | CA9: 0 | CB9: 0 | CC9: 12.579354 | CD9: 13614.018 | CE9: 0 | CF9: 0 | CG9: 15.552086 | CH9: 16848.12 | CI9: 0 | CJ9: 0 | CK9: 12.409331 | CL9: 13478.394 | CM9: 0 | CN9: 0 | CO9: 18.756502 | CP9: 20419.51 | CQ9: 0 | CR9: 0 | CS9: 15.44444 | CT9: 16847.892 | CU9: 0 | CV9: 0 | CW9: 15.406998 | CX9: 16847.598 | CY9: 0 | CZ9: 0 | DA9: 15.34399 | DB9: 16847.562 | DC9: 0 | DD9: 0 | DE9: 118.64585 | DF9: 131039.24 | DG9: 0 | DH9: 0 | DI9: 10.57957 | DJ9: 11793.555 | DK9: 0 | DL9: 0 | DM9: 16.913169 | DN9: 18984.221 | DO9: 0 | DP9: 0 | DQ9: 16.805564 | DR9: 18984.221 | DS9: 0 | DT9: 0 | DU9: 16.703801 | DV9: 18984.221 | DW9: 0 | DX9: 0 | DY9: 16.592626 | DZ9: 18984.221 | EB9: 0 | EC9: 16.520114 | ED9: 18984.221 | EF9: 0 | EG9: 16.436697 | EH9: 18984.221 | EI9: =IF($E9*EI$2/$C$2-EL9>0,$E9*EI$2/$C$2-EL9,0) -> 15284.252 | EJ9: =IFERROR(EI9/EI$2,0) -> 13.073341 | EK9: =IFERROR(EL9/EI$2,0) -> 0 | EM9: =IF($E9*EM$2/$C$2-EP9>0,$E9*EM$2/$C$2-EP9,0) -> 15345.161 | EN9: =IFERROR(EM9/EM$2,0) -> 13.073341 | EO9: =IFERROR(EP9/EM$2,0) -> 0 | EQ9: =IF($E9*EQ$2/$C$2-ET9>0,$E9*EQ$2/$C$2-ET9,0) -> 15405.442 | ER9: =IFERROR(EQ9/EQ$2,0) -> 13.073341 | ES9: =IFERROR(ET9/EQ$2,0) -> 0 | EU9: =IF($E9*EU$2/$C$2-EX9>0,$E9*EU$2/$C$2-EX9,0) -> 15484.876 | EV9: =IFERROR(EU9/EU$2,0) -> 13.073341 | EW9: =IFERROR(EX9/EU$2,0) -> 0 | EY9: =IF($E9*EY$2/$C$2-FB9>0,$E9*EY$2/$C$2-FB9,0) -> 15574.624 | EZ9: =IFERROR(EY9/EY$2,0) -> 13.073341 | FA9: =IFERROR(FB9/EY$2,0) -> 0 | FC9: =IF($E9*FC$2/$C$2-FF9>0,$E9*FC$2/$C$2-FF9,0) -> 15681.59 | FD9: =IFERROR(FC9/FC$2,0) -> 13.073341 | FE9: =IFERROR(FF9/FC$2,0) -> 0 | FG9: =IF($E9*FG$2/$C$2-FJ9>0,$E9*FG$2/$C$2-FJ9,0) -> 15824.9 | FH9: =IFERROR(FG9/FG$2,0) -> 13.073341 | FI9: =IFERROR(FJ9/FG$2,0) -> 0 | FK9: =IF($E9*FK$2/$C$2-FN9>0,$E9*FK$2/$C$2-FN9,0) -> 15906.412 | FL9: =IFERROR(FK9/FK$2,0) -> 13.073341 | FM9: =IFERROR(FN9/FK$2,0) -> 0
A10: 01.01.04.01.006 | B10: ADMINISTRATIVO DE OBRAS | C10: 37 | D10: =E10*C10 -> 467752.52 | E10: 12641.96 | F10: =K10*$C$1 -> -11050.301 | G10: =D10/$C$2 -> 483.71362 | H10: =E10/$C$2 -> 13.073341 | I10: =SUMIFS($S10:$FN10,$S$4:$FN$4,$T$4) -> 492.37994 | J10: =SUMIFS($S10:$FN10,$S$4:$FN$4,$U$4) -> 0 | K10: =G10-I10-J10 -> -8.6663252 | R10: =M10-SUMIFS(S10:ET10,$S$4:$ET$4,$V$4) -> 0 | S10: 13667.773 | T10: 13.1165 | U10: 0 | W10: 13667.773 | X10: 13.073341 | Y10: 0 | AA10: 13667.773 | AB10: 13.060374 | AC10: 0 | AE10: 13705.04 | AF10: 13.090369 | AG10: 0 | AI10: 13420.874 | AJ10: 12.800937 | AK10: 0 | AM10: 13777.97 | AN10: 13.106286 | AO10: 0 | AQ10: 13815.58 | AR10: 13.100788 | AS10: 0 | AU10: 13840.09 | AV10: 13.096534 | AW10: 0 | AY10: 13871.743 | AZ10: 13.103238 | BA10: 0 | BB10: 0 | BC10: 13871.743 | BD10: 13.073341 | BE10: 0 | BF10: 0 | BG10: 13871.743 | BH10: 13.021577 | BI10: 0 | BJ10: 0 | BK10: 13871.743 | BL10: 12.912451 | BM10: 0 | BN10: 0 | BO10: 13871.743 | BP10: 12.905208 | BQ10: 0 | BR10: 0 | BS10: 13871.743 | BT10: 12.874043 | BU10: 0 | BV10: 0 | BW10: 13871.743 | BX10: 12.843362 | BY10: 0 | BZ10: 0 | CA10: 13871.743 | CB10: 12.817492 | CC10: 0 | CD10: 0 | CE10: 13871.743 | CF10: 12.804666 | CG10: 0 | CH10: 0 | CI10: 13871.743 | CJ10: 12.77148 | CK10: 0 | CL10: 0 | CM10: 13871.743 | CN10: 12.741999 | CO10: 0 | CP10: 0 | CQ10: 13871.743 | CR10: 12.716208 | CS10: 0 | CT10: 0 | CU10: 13871.743 | CV10: 12.685601 | CW10: 0 | CX10: 0 | CY10: 13871.743 | CZ10: 12.633749 | DA10: 0 | DB10: 0 | DC10: 13871.743 | DD10: 12.559786 | DE10: 0 | DF10: 0 | DG10: 13871.743 | DH10: 12.443838 | DI10: 0 | DJ10: 0 | DK10: 14674.198 | DL10: 13.073341 | DM10: 0 | DN10: 0 | DO10: 14768.156 | DP10: 13.073341 | DQ10: 0 | DR10: 0 | DS10: 14858.127 | DT10: 13.073341 | DU10: 0 | DV10: 0 | DW10: 14957.68 | DX10: 13.073341 | DY10: 0 | DZ10: 0 | EA10: 15023.334 | EB10: 13.073341 | EC10: 0 | ED10: 0 | EE10: 15099.578 | EF10: 13.073341 | EG10: 0 | EH10: 0 | EI10: =IF($E10*EI$2/$C$2-EL10>0,$E10*EI$2/$C$2-EL10,0) -> 15284.252 | EJ10: =IFERROR(EI10/EI$2,0) -> 13.073341 | EK10: =IFERROR(EL10/EI$2,0) -> 0 | EM10: =IF($E10*EM$2/$C$2-EP10>0,$E10*EM$2/$C$2-EP10,0) -> 15345.161 | EN10: =IFERROR(EM10/EM$2,0) -> 13.073341 | EO10: =IFERROR(EP10/EM$2,0) -> 0 | EQ10: =IF($E10*EQ$2/$C$2-ET10>0,$E10*EQ$2/$C$2-ET10,0) -> 15405.442 | ER10: =IFERROR(EQ10/EQ$2,0) -> 13.073341 | ES10: =IFERROR(ET10/EQ$2,0) -> 0 | EU10: =IF($E10*EU$2/$C$2-EX10>0,$E10*EU$2/$C$2-EX10,0) -> 15484.876 | EV10: =IFERROR(EU10/EU$2,0) -> 13.073341 | EW10: =IFERROR(EX10/EU$2,0) -> 0 | EY10: =IF($E10*EY$2/$C$2-FB10>0,$E10*EY$2/$C$2-FB10,0) -> 15574.624 | EZ10: =IFERROR(EY10/EY$2,0) -> 13.073341 | FA10: =IFERROR(FB10/EY$2,0) -> 0 | FC10: =IF($E10*FC$2/$C$2-FF10>0,$E10*FC$2/$C$2-FF10,0) -> 15681.59 | FD10: =IFERROR(FC10/FC$2,0) -> 13.073341 | FE10: =IFERROR(FF10/FC$2,0) -> 0 | FG10: =IF($E10*FG$2/$C$2-FJ10>0,$E10*FG$2/$C$2-FJ10,0) -> 15824.9 | FH10: =IFERROR(FG10/FG$2,0) -> 13.073341 | FI10: =IFERROR(FJ10/FG$2,0) -> 0 | FK10: =IF($E10*FK$2/$C$2-FN10>0,$E10*FK$2/$C$2-FN10,0) -> 15906.412 | FL10: =IFERROR(FK10/FK$2,0) -> 13.073341 | FM10: =IFERROR(FN10/FK$2,0) -> 0
A11: 01.01.04.01.007 | B11: ENCARREGADO | C11: 31 | D11: =E11*C11 -> 296054.96 | E11: 9550.16 | F11: =K11*$C$1 -> 264448.59 | G11: =D11/$C$2 -> 306.15723 | H11: =E11/$C$2 -> 9.8760397 | I11: =SUMIFS($S11:$FN11,$S$4:$FN$4,$T$4) -> 98.760397 | J11: =SUMIFS($S11:$FN11,$S$4:$FN$4,$U$4) -> 0 | K11: =G11-I11-J11 -> 207.39683 | L11: 21 | M11: 252149.04 | N11: =M11/L11 -> 12007.097 | O11: 21 | P11: 15128.946 | Q11: =P11/O11 -> 720.426 | R11: =M11-SUMIFS(S11:ET11,$S$4:$ET$4,$V$4) -> 252149.04 | S11: 0 | T11: 0 | U11: 0 | W11: 0 | X11: 0 | Y11: 0 | AA11: 0 | AB11: 0 | AC11: 0 | AE11: 0 | AF11: 0 | AG11: 0 | AI11: 0 | AJ11: 0 | AK11: 0 | AM11: 0 | AN11: 0 | AO11: 0 | AQ11: 0 | AR11: 0 | AS11: 0 | AU11: 0 | AV11: 0 | AW11: 0 | AZ11: 0 | BA11: 0 | BB11: 0 | BD11: 0 | BE11: 0 | BF11: 0 | BH11: 0 | BI11: 0 | BJ11: 0 | BL11: 0 | BM11: 0 | BN11: 0 | BP11: 0 | BQ11: 0 | BR11: 0 | BT11: 0 | BU11: 0 | BV11: 0 | BX11: 0 | BY11: 0 | BZ11: 0 | CB11: 0 | CC11: 0 | CD11: 0 | CF11: 0 | CG11: 0 | CH11: 0 | CJ11: 0 | CK11: 0 | CL11: 0 | CN11: 0 | CO11: 0 | CP11: 0 | CR11: 0 | CS11: 0 | CT11: 0 | CV11: 0 | CW11: 0 | CX11: 0 | CZ11: 0 | DA11: 0 | DB11: 0 | DD11: 0 | DE11: 0 | DF11: 0 | DH11: 0 | DI11: 0 | DJ11: 0 | DL11: 0 | DM11: 0 | DN11: 0 | DP11: 0 | DQ11: 0 | DR11: 0 | DT11: 0 | DU11: 0 | DV11: 0 | DX11: 0 | DY11: 0 | DZ11: 0 | EA11: 11349.13 | EB11: 9.8760397 | EC11: 0 | ED11: 0 | EE11: 11406.727 | EF11: 9.8760397 | EG11: 0 | EH11: 0 | EI11: =IF($E11*EI$2/$C$2-EL11>0,$E11*EI$2/$C$2-EL11,0) -> 11546.236 | EJ11: =IFERROR(EI11/EI$2,0) -> 9.8760397 | EK11: =IFERROR(EL11/EI$2,0) -> 0 | EM11: =IF($E11*EM$2/$C$2-EP11>0,$E11*EM$2/$C$2-EP11,0) -> 11592.248 | EN11: =IFERROR(EM11/EM$2,0) -> 9.8760397 | EO11: =IFERROR(EP11/EM$2,0) -> 0 | EQ11: =IF($E11*EQ$2/$C$2-ET11>0,$E11*EQ$2/$C$2-ET11,0) -> 11637.787 | ER11: =IFERROR(EQ11/EQ$2,0) -> 9.8760397 | ES11: =IFERROR(ET11/EQ$2,0) -> 0 | EU11: =IF($E11*EU$2/$C$2-EX11>0,$E11*EU$2/$C$2-EX11,0) -> 11697.794 | EV11: =IFERROR(EU11/EU$2,0) -> 9.8760397 | EW11: =IFERROR(EX11/EU$2,0) -> 0 | EY11: =IF($E11*EY$2/$C$2-FB11>0,$E11*EY$2/$C$2-FB11,0) -> 11765.593 | EZ11: =IFERROR(EY11/EY$2,0) -> 9.8760397 | FA11: =IFERROR(FB11/EY$2,0) -> 0 | FC11: =IF($E11*FC$2/$C$2-FF11>0,$E11*FC$2/$C$2-FF11,0) -> 11846.398 | FD11: =IFERROR(FC11/FC$2,0) -> 9.8760397 | FE11: =IFERROR(FF11/FC$2,0) -> 0 | FG11: =IF($E11*FG$2/$C$2-FJ11>0,$E11*FG$2/$C$2-FJ11,0) -> 11954.66 | FH11: =IFERROR(FG11/FG$2,0) -> 9.8760397 | FI11: =IFERROR(FJ11/FG$2,0) -> 0 | FK11: =IF($E11*FK$2/$C$2-FN11>0,$E11*FK$2/$C$2-FN11,0) -> 12016.237 | FL11: =IFERROR(FK11/FK$2,0) -> 9.8760397 | FM11: =IFERROR(FN11/FK$2,0) -> 0
A12: 01.01.04.01.008 | B12: ALMOXARIFE | C12: 37 | D12: =E12*C12 -> 176677.96 | E12: 4775.08 | F12: =K12*$C$1 -> -191096.57 | G12: =D12/$C$2 -> 182.70673 | H12: =E12/$C$2 -> 4.9380198 | I12: =SUMIFS($S12:$FN12,$S$4:$FN$4,$T$4) -> 58.86236 | J12: =SUMIFS($S12:$FN12,$S$4:$FN$4,$U$4) -> 273.71404 | K12: =G12-I12-J12 -> -149.86967 | L12: 36 | M12: 432255.5 | N12: =M12/L12 -> 12007.097 | O12: 21 | P12: 18269.21 | Q12: =P12/O12 -> 869.96238 | R12: =M12-SUMIFS(S12:ET12,$S$4:$ET$4,$V$4) -> 137254.95 | S12: 5162.547 | T12: 4.9543218 | U12: 10.207106 | V12: 10636.1 | W12: 0 | X12: 0 | Y12: 7.1214641 | Z12: 7445.27 | AA12: 1568.02 | AB12: 1.4983368 | AC12: 10.163429 | AD12: 10636.1 | AE12: 1586.49 | AF12: 1.5153359 | AG12: 10.159052 | AH12: 10636.08 | AI12: 1587.497 | AJ12: 1.5141674 | AK12: 0 | AM12: 0 | AN12: 0 | AO12: 11.421747 | AP12: 12007.1 | AQ12: 0 | AR12: 0 | AS12: 39.752124 | AT12: 41921.04 | AU12: 0 | AV12: 0 | AW12: 9.0895981 | AX12: 9605.66 | AY12: 0 | AZ12: 0 | BA12: 9.0734993 | BB12: 9605.66 | BC12: 0 | BD12: 0 | BE12: 9.0527967 | BF12: 9605.66 | BG12: 0 | BH12: 0 | BI12: 9.0169522 | BJ12: 9605.66 | BK12: 0 | BL12: 0 | BM12: 8.9413865 | BN12: 9605.66 | BO12: 0 | BP12: 0 | BQ12: 8.9363705 | BR12: 9605.66 | BS12: 0 | BT12: 0 | BU12: 8.9147905 | BV12: 9605.66 | BW12: 0 | BX12: 0 | BY12: 8.893545 | BZ12: 9605.66 | CA12: 0 | CB12: 0 | CC12: 8.8756305 | CD12: 9605.66 | CE12: 0 | CF12: 0 | CG12: 8.8667494 | CH12: 9605.66 | CI12: 0 | CJ12: 0 | CK12: 8.8437693 | CL12: 9605.66 | CM12: 0 | CN12: 0 | CO12: 8.8233549 | CP12: 9605.66 | CQ12: 0 | CR12: 0 | CS12: 8.8054958 | CT12: 9605.66 | CU12: 0 | CV12: 0 | CW12: 8.7843015 | CX12: 9605.66 | CY12: 0 | CZ12: 0 | DA12: 8.7483959 | DB12: 9605.66 | DC12: 0 | DD12: 0 | DE12: 8.6971788 | DF12: 9605.66 | DG12: 0 | DH12: 0 | DI12: 8.6168892 | DJ12: 9605.66 | DK12: 0 | DL12: 0 | DM12: 8.5577468 | DN12: 9605.66 | DO12: 0 | DP12: 0 | DQ12: 8.5033006 | DR12: 9605.66 | DS12: 0 | DT12: 0 | DU12: 8.4518104 | DV12: 9605.66 | DW12: 0 | DX12: 0 | DY12: 8.3955579 | DZ12: 9605.66 | EA12: 5674.565 | EB12: 4.9380198 | EC12: 0 | EE12: 5703.3635 | EF12: 4.9380198 | EG12: 0 | EI12: =IF($E12*EI$2/$C$2-EL12>0,$E12*EI$2/$C$2-EL12,0) -> 5773.118 | EJ12: =IFERROR(EI12/EI$2,0) -> 4.9380198 | EK12: =IFERROR(EL12/EI$2,0) -> 0 | EM12: =IF($E12*EM$2/$C$2-EP12>0,$E12*EM$2/$C$2-EP12,0) -> 5796.1242 | EN12: =IFERROR(EM12/EM$2,0) -> 4.9380198 | EO12: =IFERROR(EP12/EM$2,0) -> 0 | EQ12: =IF($E12*EQ$2/$C$2-ET12>0,$E12*EQ$2/$C$2-ET12,0) -> 5818.8934 | ER12: =IFERROR(EQ12/EQ$2,0) -> 4.9380198 | ES12: =IFERROR(ET12/EQ$2,0) -> 0 | EU12: =IF($E12*EU$2/$C$2-EX12>0,$E12*EU$2/$C$2-EX12,0) -> 5848.8969 | EV12: =IFERROR(EU12/EU$2,0) -> 4.9380198 | EW12: =IFERROR(EX12/EU$2,0) -> 0 | EY12: =IF($E12*EY$2/$C$2-FB12>0,$E12*EY$2/$C$2-FB12,0) -> 5882.7964 | EZ12: =IFERROR(EY12/EY$2,0) -> 4.9380198 | FA12: =IFERROR(FB12/EY$2,0) -> 0 | FC12: =IF($E12*FC$2/$C$2-FF12>0,$E12*FC$2/$C$2-FF12,0) -> 5923.1992 | FD12: =IFERROR(FC12/FC$2,0) -> 4.9380198 | FE12: =IFERROR(FF12/FC$2,0) -> 0 | FG12: =IF($E12*FG$2/$C$2-FJ12>0,$E12*FG$2/$C$2-FJ12,0) -> 5977.3298 | FH12: =IFERROR(FG12/FG$2,0) -> 4.9380198 | FI12: =IFERROR(FJ12/FG$2,0) -> 0 | FK12: =IF($E12*FK$2/$C$2-FN12>0,$E12*FK$2/$C$2-FN12,0) -> 6008.1184 | FL12: =IFERROR(FK12/FK$2,0) -> 4.9380198 | FM12: =IFERROR(FN12/FK$2,0) -> 0
A13: 01.01.04.01.009 | B13: AUXILIAR DE ALMOXARIFE | C13: 37 | D13: =E13*C13 -> 353355.92 | E13: 9550.16 | F13: =K13*$C$1 -> 306538.49 | G13: =D13/$C$2 -> 365.41347 | H13: =E13/$C$2 -> 9.8760397 | I13: =SUMIFS($S13:$FN13,$S$4:$FN$4,$T$4) -> 108.32408 | J13: =SUMIFS($S13:$FN13,$S$4:$FN$4,$U$4) -> 16.683075 | K13: =G13-I13-J13 -> 240.40632 | S13: 0 | T13: 0 | U13: 0 | W13: 0 | X13: 0 | Y13: 0 | AA13: 1568.023 | AB13: 1.4983397 | AC13: 0 | AE13: 0 | AF13: 0 | AG13: 0 | AI13: 0 | AJ13: 0 | AK13: 16.683075 | AL13: 17491.02 | AM13: 0 | AN13: 0 | AO13: 0 | AQ13: 0 | AR13: 0 | AS13: 0 | AU13: 0 | AV13: 0 | AW13: 0 | AZ13: 0 | BA13: 0 | BB13: 0 | BD13: 0 | BE13: 0 | BF13: 0 | BH13: 0 | BI13: 0 | BJ13: 0 | BL13: 0 | BM13: 0 | BN13: 0 | BP13: 0 | BQ13: 0 | BR13: 0 | BT13: 0 | BU13: 0 | BV13: 0 | BX13: 0 | BY13: 0 | BZ13: 0 | CB13: 0 | CC13: 0 | CD13: 0 | CF13: 0 | CG13: 0 | CH13: 0 | CJ13: 0 | CK13: 0 | CL13: 0 | CN13: 0 | CO13: 0 | CP13: 0 | CR13: 0 | CS13: 0 | CT13: 0 | CV13: 0 | CW13: 0 | CX13: 0 | CZ13: 0 | DA13: 0 | DB13: 0 | DD13: 0 | DE13: 0 | DF13: 0 | DH13: 0 | DI13: 0 | DJ13: 0 | DL13: 0 | DM13: 0 | DN13: 0 | DO13: 3056.05 | DP13: 2.7053333 | DQ13: 0 | DR13: 0 | DS13: 3056.05 | DT13: 2.6889516 | DU13: 0 | DV13: 0 | DW13: 3056.05 | DX13: 2.6710548 | DY13: 0 | DZ13: 0 | EA13: 11349.13 | EB13: 9.8760397 | EC13: 0 | ED13: 0 | EE13: 11406.727 | EF13: 9.8760397 | EG13: 0 | EH13: 0 | EI13: =IF($E13*EI$2/$C$2-EL13>0,$E13*EI$2/$C$2-EL13,0) -> 11546.236 | EJ13: =IFERROR(EI13/EI$2,0) -> 9.8760397 | EK13: =IFERROR(EL13/EI$2,0) -> 0 | EM13: =IF($E13*EM$2/$C$2-EP13>0,$E13*EM$2/$C$2-EP13,0) -> 11592.248 | EN13: =IFERROR(EM13/EM$2,0) -> 9.8760397 | EO13: =IFERROR(EP13/EM$2,0) -> 0 | EQ13: =IF($E13*EQ$2/$C$2-ET13>0,$E13*EQ$2/$C$2-ET13,0) -> 11637.787 | ER13: =IFERROR(EQ13/EQ$2,0) -> 9.8760397 | ES13: =IFERROR(ET13/EQ$2,0) -> 0 | EU13: =IF($E13*EU$2/$C$2-EX13>0,$E13*EU$2/$C$2-EX13,0) -> 11697.794 | EV13: =IFERROR(EU13/EU$2,0) -> 9.8760397 | EW13: =IFERROR(EX13/EU$2,0) -> 0 | EY13: =IF($E13*EY$2/$C$2-FB13>0,$E13*EY$2/$C$2-FB13,0) -> 11765.593 | EZ13: =IFERROR(EY13/EY$2,0) -> 9.8760397 | FA13: =IFERROR(FB13/EY$2,0) -> 0 | FC13: =IF($E13*FC$2/$C$2-FF13>0,$E13*FC$2/$C$2-FF13,0) -> 11846.398 | FD13: =IFERROR(FC13/FC$2,0) -> 9.8760397 | FE13: =IFERROR(FF13/FC$2,0) -> 0 | FG13: =IF($E13*FG$2/$C$2-FJ13>0,$E13*FG$2/$C$2-FJ13,0) -> 11954.66 | FH13: =IFERROR(FG13/FG$2,0) -> 9.8760397 | FI13: =IFERROR(FJ13/FG$2,0) -> 0 | FK13: =IF($E13*FK$2/$C$2-FN13>0,$E13*FK$2/$C$2-FN13,0) -> 12016.237 | FL13: =IFERROR(FK13/FK$2,0) -> 9.8760397 | FM13: =IFERROR(FN13/FK$2,0) -> 0
A14: 01.01.04.01.010 | B14: ENGENHEIRO DE SEGURANÇA | C14: 37 | D14: =E14*C14 -> 166500 | E14: 4500 | F14: =K14*$C$1 -> -3937.1825 | G14: =D14/$C$2 -> 172.18147 | H14: =E14/$C$2 -> 4.6535533 | I14: =SUMIFS($S14:$FN14,$S$4:$FN$4,$T$4) -> 175.26925 | J14: =SUMIFS($S14:$FN14,$S$4:$FN$4,$U$4) -> 0 | K14: =G14-I14-J14 -> -3.0877804 | S14: 4865.146 | T14: 4.6689161 | U14: 0 | W14: 4865.146 | X14: 4.6535536 | Y14: 0 | AA14: 4865.146 | AB14: 4.6489378 | AC14: 0 | AE14: 4878.41 | AF14: 4.6596132 | AG14: 0 | AI14: 4777.262 | AJ14: 4.5565909 | AK14: 0 | AM14: 4907.46 | AN14: 4.6682185 | AO14: 0 | AQ14: 4917.76 | AR14: 4.6633244 | AS14: 0 | AU14: 4926.48 | AV14: 4.661806 | AW14: 0 | AY14: 4937.7505 | AZ14: 4.6641954 | BA14: 0 | BB14: 0 | BC14: 4937.7505 | BD14: 4.6535533 | BE14: 0 | BF14: 0 | BG14: 4937.7505 | BH14: 4.6351276 | BI14: 0 | BJ14: 0 | BK14: 4937.7505 | BL14: 4.5962834 | BM14: 0 | BN14: 0 | BO14: 4937.7505 | BP14: 4.5937049 | BQ14: 0 | BR14: 0 | BS14: 4937.7505 | BT14: 4.5826118 | BU14: 0 | BV14: 0 | BW14: 4937.7505 | BX14: 4.5716906 | BY14: 0 | BZ14: 0 | CA14: 4937.7505 | CB14: 4.5624818 | CC14: 0 | CD14: 0 | CE14: 4937.7505 | CF14: 4.5579165 | CG14: 0 | CH14: 0 | CI14: 4937.7505 | CJ14: 4.5461036 | CK14: 0 | CL14: 0 | CM14: 4937.7505 | CN14: 4.5356097 | CO14: 0 | CP14: 0 | CQ14: 4937.7505 | CR14: 4.5264293 | CS14: 0 | CT14: 0 | CU14: 4937.7505 | CV14: 4.5155344 | CW14: 0 | CX14: 0 | CY14: 4937.7505 | CZ14: 4.4970773 | DA14: 0 | DB14: 0 | DC14: 4937.7505 | DD14: 4.4707494 | DE14: 0 | DF14: 0 | DG14: 4937.7505 | DH14: 4.4294768 | DI14: 0 | DJ14: 0 | DK14: 5223.3902 | DL14: 4.6535533 | DM14: 0 | DN14: 0 | DO14: 5256.8353 | DP14: 4.6535533 | DQ14: 0 | DR14: 0 | DS14: 5288.861 | DT14: 4.6535533 | DU14: 0 | DV14: 0 | DW14: 5324.2979 | DX14: 4.6535533 | DY14: 0 | DZ14: 0 | EA14: 5347.668 | EB14: 4.6535533 | EC14: 0 | ED14: 0 | EE14: 5374.8075 | EF14: 4.6535533 | EG14: 0 | EH14: 0 | EI14: =IF($E14*EI$2/$C$2-EL14>0,$E14*EI$2/$C$2-EL14,0) -> 5440.5436 | EJ14: =IFERROR(EI14/EI$2,0) -> 4.6535533 | EK14: =IFERROR(EL14/EI$2,0) -> 0 | EM14: =IF($E14*EM$2/$C$2-EP14>0,$E14*EM$2/$C$2-EP14,0) -> 5462.2245 | EN14: =IFERROR(EM14/EM$2,0) -> 4.6535533 | EO14: =IFERROR(EP14/EM$2,0) -> 0 | EQ14: =IF($E14*EQ$2/$C$2-ET14>0,$E14*EQ$2/$C$2-ET14,0) -> 5483.6821 | ER14: =IFERROR(EQ14/EQ$2,0) -> 4.6535533 | ES14: =IFERROR(ET14/EQ$2,0) -> 0 | EU14: =IF($E14*EU$2/$C$2-EX14>0,$E14*EU$2/$C$2-EX14,0) -> 5511.957 | EV14: =IFERROR(EU14/EU$2,0) -> 4.6535533 | EW14: =IFERROR(EX14/EU$2,0) -> 0 | EY14: =IF($E14*EY$2/$C$2-FB14>0,$E14*EY$2/$C$2-FB14,0) -> 5543.9037 | EZ14: =IFERROR(EY14/EY$2,0) -> 4.6535533 | FA14: =IFERROR(FB14/EY$2,0) -> 0 | FC14: =IF($E14*FC$2/$C$2-FF14>0,$E14*FC$2/$C$2-FF14,0) -> 5581.9791 | FD14: =IFERROR(FC14/FC$2,0) -> 4.6535533 | FE14: =IFERROR(FF14/FC$2,0) -> 0 | FG14: =IF($E14*FG$2/$C$2-FJ14>0,$E14*FG$2/$C$2-FJ14,0) -> 5632.9913 | FH14: =IFERROR(FG14/FG$2,0) -> 4.6535533 | FI14: =IFERROR(FJ14/FG$2,0) -> 0 | FK14: =IF($E14*FK$2/$C$2-FN14>0,$E14*FK$2/$C$2-FN14,0) -> 5662.0062 | FL14: =IFERROR(FK14/FK$2,0) -> 4.6535533 | FM14: =IFERROR(FN14/FK$2,0) -> 0
A15: 01.01.04.01.011 | B15: TECNICO SEGURANCA | C15: 37 | D15: =E15*C15 -> 194151.58 | E15: 5247.34 | F15: =K15*$C$1 -> 2349.8662 | G15: =D15/$C$2 -> 200.77661 | H15: =E15/$C$2 -> 5.4263947 | I15: =SUMIFS($S15:$FN15,$S$4:$FN$4,$T$4) -> 198.9337 | J15: =SUMIFS($S15:$FN15,$S$4:$FN$4,$U$4) -> 0 | K15: =G15-I15-J15 -> 1.8429095 | S15: 5673.127 | T15: 5.4443082 | U15: 0 | W15: 5673.127 | X15: 5.4263943 | Y15: 0 | AA15: 5673.127 | AB15: 5.421012 | AC15: 0 | AE15: 5688.6 | AF15: 5.4334662 | AG15: 0 | AI15: 5570.644 | AJ15: 5.313325 | AK15: 0 | AM15: 0 | AN15: 0 | AO15: 0 | AQ15: 5734.48 | AR15: 5.4377888 | AS15: 0 | AU15: 5744.65 | AV15: 5.43602 | AW15: 0 | AY15: 5757.7901 | AZ15: 5.4388042 | BA15: 0 | BB15: 0 | BC15: 5757.7901 | BD15: 5.4263947 | BE15: 0 | BF15: 0 | BG15: 5757.7901 | BH15: 5.404909 | BI15: 0 | BJ15: 0 | BK15: 5757.7901 | BL15: 5.3596137 | BM15: 0 | BN15: 0 | BO15: 5757.7901 | BP15: 5.356607 | BQ15: 0 | BR15: 0 | BS15: 5757.7901 | BT15: 5.3436716 | BU15: 0 | BV15: 0 | BW15: 5757.7901 | BX15: 5.3309367 | BY15: 0 | BZ15: 0 | CA15: 5757.7901 | CB15: 5.3201985 | CC15: 0 | CD15: 0 | CE15: 5757.7901 | CF15: 5.314875 | CG15: 0 | CH15: 0 | CI15: 5757.7901 | CJ15: 5.3011003 | CK15: 0 | CL15: 0 | CM15: 5757.7901 | CN15: 5.2888636 | CO15: 0 | CP15: 0 | CQ15: 5757.7901 | CR15: 5.2781586 | CS15: 0 | CT15: 0 | CU15: 5757.7901 | CV15: 5.2654543 | CW15: 0 | CX15: 0 | CY15: 5757.7901 | CZ15: 5.243932 | DA15: 0 | DB15: 0 | DC15: 5757.7901 | DD15: 5.2132316 | DE15: 0 | DF15: 0 | DG15: 5757.7901 | DH15: 5.1651047 | DI15: 0 | DJ15: 0 | DK15: 6090.8676 | DL15: 5.4263947 | DM15: 0 | DN15: 0 | DO15: 6129.8671 | DP15: 5.4263947 | DQ15: 0 | DR15: 0 | DS15: 6167.2116 | DT15: 5.4263947 | DU15: 0 | DV15: 0 | DW15: 6208.5336 | DX15: 5.4263947 | DY15: 0 | DZ15: 0 | EA15: 6235.7849 | EB15: 5.4263947 | EC15: 0 | ED15: 0 | EE15: 6267.4317 | EF15: 5.4263947 | EG15: 0 | EH15: 0 | EI15: =IF($E15*EI$2/$C$2-EL15>0,$E15*EI$2/$C$2-EL15,0) -> 6344.0849 | EJ15: =IFERROR(EI15/EI$2,0) -> 5.4263947 | EK15: =IFERROR(EL15/EI$2,0) -> 0 | EM15: =IF($E15*EM$2/$C$2-EP15>0,$E15*EM$2/$C$2-EP15,0) -> 6369.3665 | EN15: =IFERROR(EM15/EM$2,0) -> 5.4263947 | EO15: =IFERROR(EP15/EM$2,0) -> 0 | EQ15: =IF($E15*EQ$2/$C$2-ET15>0,$E15*EQ$2/$C$2-ET15,0) -> 6394.3876 | ER15: =IFERROR(EQ15/EQ$2,0) -> 5.4263947 | ES15: =IFERROR(ET15/EQ$2,0) -> 0 | EU15: =IF($E15*EU$2/$C$2-EX15>0,$E15*EU$2/$C$2-EX15,0) -> 6427.3584 | EV15: =IFERROR(EU15/EU$2,0) -> 5.4263947 | EW15: =IFERROR(EX15/EU$2,0) -> 0 | EY15: =IF($E15*EY$2/$C$2-FB15>0,$E15*EY$2/$C$2-FB15,0) -> 6464.6106 | EZ15: =IFERROR(EY15/EY$2,0) -> 5.4263947 | FA15: =IFERROR(FB15/EY$2,0) -> 0 | FC15: =IF($E15*FC$2/$C$2-FF15>0,$E15*FC$2/$C$2-FF15,0) -> 6509.0093 | FD15: =IFERROR(FC15/FC$2,0) -> 5.4263947 | FE15: =IFERROR(FF15/FC$2,0) -> 0 | FG15: =IF($E15*FG$2/$C$2-FJ15>0,$E15*FG$2/$C$2-FJ15,0) -> 6568.4935 | FH15: =IFERROR(FG15/FG$2,0) -> 5.4263947 | FI15: =IFERROR(FJ15/FG$2,0) -> 0 | FK15: =IF($E15*FK$2/$C$2-FN15>0,$E15*FK$2/$C$2-FN15,0) -> 6602.327 | FL15: =IFERROR(FK15/FK$2,0) -> 5.4263947 | FM15: =IFERROR(FN15/FK$2,0) -> 0
D16: =SUM(D5:D15) -> 4177828.9 | E16: =SUM(E5:E15) -> 114462.97 | F16: =SUM(F5:F15) -> 1242.4779 | G16: =SUM(G5:G15) -> 4320.3888 | H16: =SUM(H5:H15) -> 118.36878 | I16: =SUM(I5:I15) -> 2847.6413 | J16: =SUM(J5:J15) -> 1471.773 | K16: =SUM(K5:K15) -> 0.97442752 | ... FN16: =SUM(FN5:FN15) -> 0

Sheet Unna
A1: INCC M - Vigente | B1: ='IND. FIN.'!V1 -> 46204 | C1: =VLOOKUP(B1,'IND. FIN.'!$J$3:$K$97,2,0) -> 1275.085 | D1: Contrato Piemonte
A2: INCC - Base | B2: 44805 | C2: ='IND. FIN.'!K23 -> 1045.469 | D2: R$ | G2: INCC | L2: =IF(L3>$B$1,0,VLOOKUP(L$3,'IND. FIN.'!$J$4:$K$97,2,0)) -> 1061.071 | P2: =IF(P3>$B$1,0,VLOOKUP(P$3,'IND. FIN.'!$J$4:$K$97,2,0)) -> 1065.289 | T2: =IF(T3>$B$1,0,VLOOKUP(T$3,'IND. FIN.'!$J$4:$K$97,2,0)) -> 1074.292 | X2: =IF(X3>$B$1,0,VLOOKUP(X$3,'IND. FIN.'!$J$4:$K$97,2,0)) -> 1074.895 | AB2: =IF(AB3>$B$1,0,VLOOKUP(AB$3,'IND. FIN.'!$J$4:$K$97,2,0)) -> 1077.497 | AF2: =IF(AF3>$B$1,0,VLOOKUP(AF$3,'IND. FIN.'!$J$4:$K$97,2,0)) -> 1080.071 | AJ2: =IF(AJ3>$B$1,0,VLOOKUP(AJ$3,'IND. FIN.'!$J$4:$K$97,2,0)) -> 1082.251 | AN2: =IF(AN3>$B$1,0,VLOOKUP(AN$3,'IND. FIN.'!$J$4:$K$97,2,0)) -> 1083.335 | AR2: =IF(AR3>$B$1,0,VLOOKUP(AR$3,'IND. FIN.'!$J$4:$K$97,2,0)) -> 1086.15 | AV2: =IF(AV3>$B$1,0,VLOOKUP(AV$3,'IND. FIN.'!$J$4:$K$97,2,0)) -> 1088.663 | AZ2: =IF(AZ3>$B$1,0,VLOOKUP(AZ$3,'IND. FIN.'!$J$4:$K$97,2,0)) -> 1090.871 | BD2: =IF(BD3>$B$1,0,VLOOKUP(BD$3,'IND. FIN.'!$J$4:$K$97,2,0)) -> 1093.503 | BH2: =IF(BH3>$B$1,0,VLOOKUP(BH$3,'IND. FIN.'!$J$4:$K$97,2,0)) -> 1097.991 | BL2: =IF(BL3>$B$1,0,VLOOKUP(BL$3,'IND. FIN.'!$J$4:$K$97,2,0)) -> 1104.457 | BP2: =IF(BP3>$B$1,0,VLOOKUP(BP$3,'IND. FIN.'!$J$4:$K$97,2,0)) -> 1114.748 | BT2: =IF(BT3>$B$1,0,VLOOKUP(BT$3,'IND. FIN.'!$J$4:$K$97,2,0)) -> 1122.452 | BX2: =IF(BX3>$B$1,0,VLOOKUP(BX$3,'IND. FIN.'!$J$4:$K$97,2,0)) -> 1129.639 | CB2: =IF(CB3>$B$1,0,VLOOKUP(CB$3,'IND. FIN.'!$J$4:$K$97,2,0)) -> 1136.521 | CF2: =IF(CF3>$B$1,0,VLOOKUP(CF$3,'IND. FIN.'!$J$4:$K$97,2,0)) -> 1144.136 | CJ2: =IF(CJ3>$B$1,0,VLOOKUP(CJ$3,'IND. FIN.'!$J$4:$K$97,2,0)) -> 1149.158 | CN2: =IF(CN3>$B$1,0,VLOOKUP(CN$3,'IND. FIN.'!$J$4:$K$97,2,0)) -> 1154.99 | CR2: =IF(CR3>$B$1,0,VLOOKUP(CR$3,'IND. FIN.'!$J$4:$K$97,2,0)) -> 1163.221 | CV2: =IF(CV3>$B$1,0,VLOOKUP(CV$3,'IND. FIN.'!$J$4:$K$97,2,0)) -> 1169.156 | CZ2: =IF(CZ3>$B$1,0,VLOOKUP(CZ$3,'IND. FIN.'!$J$4:$K$97,2,0)) -> 1173.586 | DD2: =IF(DD3>$B$1,0,VLOOKUP(DD$3,'IND. FIN.'!$J$4:$K$97,2,0)) -> 1180.564 | DH2: =IF(DH3>$B$1,0,VLOOKUP(DH$3,'IND. FIN.'!$J$4:$K$97,2,0)) -> 1183.606 | DL2: =IF(DL3>$B$1,0,VLOOKUP(DL$3,'IND. FIN.'!$J$4:$K$97,2,0)) -> 1194.912 | DP2: =IF(DP3>$B$1,0,VLOOKUP(DP$3,'IND. FIN.'!$J$4:$K$97,2,0)) -> 1205.838 | DT2: =IF(DT3>$B$1,0,VLOOKUP(DT$3,'IND. FIN.'!$J$4:$K$97,2,0)) -> 1214.239 | DX2: =IF(DX3>$B$1,0,VLOOKUP(DX$3,'IND. FIN.'!$J$4:$K$97,2,0)) -> 1216.825 | EB2: =IF(EB3>$B$1,0,VLOOKUP(EB$3,'IND. FIN.'!$J$4:$K$97,2,0)) -> 1219.407 | EF2: =IF(EF3>$B$1,0,VLOOKUP(EF$3,'IND. FIN.'!$J$4:$K$97,2,0)) -> 1222.865 | EJ2: =IF(EJ3>$B$1,0,VLOOKUP(EJ$3,'IND. FIN.'!$J$4:$K$97,2,0)) -> 1225.398 | EN2: =IF(EN3>$B$1,0,VLOOKUP(EN$3,'IND. FIN.'!$J$4:$K$97,2,0)) -> 1233.096 | ER2: =IF(ER3>$B$1,0,VLOOKUP(ER$3,'IND. FIN.'!$J$4:$K$97,2,0)) -> 1237.312 | EV2: =IF(EV3>$B$1,0,VLOOKUP(EV$3,'IND. FIN.'!$J$4:$K$97,2,0)) -> 1241.721
A3: Orçamento base | D3: Valor total | E3: Valor unitário | F3: Saldo | G3: Valor total | H3: Valor unitário | I3: Total medido Piemonte | J3: Total medido Terceiros | K3: Saldo | L3: 45047 | P3: =EDATE(L3,1) -> 45078 | T3: =EDATE(P3,1) -> 45108 | X3: =EDATE(T3,1) -> 45139 | AB3: =EDATE(X3,1) -> 45170 | AF3: =EDATE(AB3,1) -> 45200 | AJ3: =EDATE(AF3,1) -> 45231 | AN3: =EDATE(AJ3,1) -> 45261 | AR3: =EDATE(AN3,1) -> 45292 | AV3: =EDATE(AR3,1) -> 45323 | AZ3: =EDATE(AV3,1) -> 45352 | BD3: =EDATE(AZ3,1) -> 45383 | BH3: =EDATE(BD3,1) -> 45413 | BL3: =EDATE(BH3,1) -> 45444 | BP3: =EDATE(BL3,1) -> 45474 | BT3: =EDATE(BP3,1) -> 45505 | BX3: =EDATE(BT3,1) -> 45536 | CB3: =EDATE(BX3,1) -> 45566 | CF3: =EDATE(CB3,1) -> 45597 | CJ3: =EDATE(CF3,1) -> 45627 | CN3: =EDATE(CJ3,1) -> 45658 | CR3: =EDATE(CN3,1) -> 45689 | CV3: =EDATE(CR3,1) -> 45717 | CZ3: =EDATE(CV3,1) -> 45748 | DD3: =EDATE(CZ3,1) -> 45778 | DH3: =EDATE(DD3,1) -> 45809 | DL3: =EDATE(DH3,1) -> 45839 | DP3: =EDATE(DL3,1) -> 45870 | DT3: =EDATE(DP3,1) -> 45901 | DX3: =EDATE(DT3,1) -> 45931 | EB3: =EDATE(DX3,1) -> 45962 | EF3: =EDATE(EB3,1) -> 45992 | EJ3: =EDATE(EF3,1) -> 46023 | EN3: =EDATE(EJ3,1) -> 46054 | ER3: =EDATE(EN3,1) -> 46082 | EV3: =EDATE(ER3,1) -> 46113
A4: 01.01.04.01 | B4: PESSOAL | C4: Prazo | L4: Medido Piemonte | M4: Medido Piemonte INCC | N4: Medido Terceiros INCC | O4: Medido Terceiros | P4: Medido Piemonte | Q4: Medido Piemonte INCC | R4: Medido Terceiros INCC | S4: Medido Terceiros | T4: Medido Piemonte | U4: Medido Piemonte INCC | V4: Medido Terceiros INCC | W4: Medido Terceiros | X4: Medido Piemonte | Y4: Medido Piemonte INCC | Z4: Medido Terceiros INCC | AA4: Medido Terceiros | AB4: Medido Piemonte | AC4: Medido Piemonte INCC | AD4: Medido Terceiros INCC | AE4: Medido Terceiros | AF4: Medido Piemonte | AG4: Medido Piemonte INCC | AH4: Medido Terceiros INCC | AI4: Medido Terceiros | AJ4: Medido Piemonte | AK4: Medido Piemonte INCC | AL4: Medido Terceiros INCC | AM4: Medido Terceiros | AN4: Medido Piemonte | AO4: Medido Piemonte INCC | AP4: Medido Terceiros INCC | AQ4: Medido Terceiros | AR4: Medido Piemonte | AS4: Medido Piemonte INCC | AT4: Medido Terceiros INCC | AU4: Medido Terceiros | AV4: Medido Piemonte | AW4: Medido Piemonte INCC | AX4: Medido Terceiros INCC | AY4: Medido Terceiros | AZ4: Medido Piemonte | BA4: Medido Piemonte INCC | BB4: Medido Terceiros INCC | BC4: Medido Terceiros | BD4: Medido Piemonte | BE4: Medido Piemonte INCC | BF4: Medido Terceiros INCC | BG4: Medido Terceiros | BH4: Medido Piemonte | BI4: Medido Piemonte INCC | BJ4: Medido Terceiros INCC | BK4: Medido Terceiros | BL4: Medido Piemonte | BM4: Medido Piemonte INCC | BN4: Medido Terceiros INCC | BO4: Medido Terceiros | BP4: Medido Piemonte | BQ4: Medido Piemonte INCC | BR4: Medido Terceiros INCC | BS4: Medido Terceiros | BT4: Medido Piemonte | BU4: Medido Piemonte INCC | BV4: Medido Terceiros INCC | BW4: Medido Terceiros | BX4: Medido Piemonte | BY4: Medido Piemonte INCC | BZ4: Medido Terceiros INCC | CA4: Medido Terceiros | CB4: Medido Piemonte | CC4: Medido Piemonte INCC | CD4: Medido Terceiros INCC | CE4: Medido Terceiros | CF4: Medido Piemonte | CG4: Medido Piemonte INCC | CH4: Medido Terceiros INCC | CI4: Medido Terceiros | CJ4: Medido Piemonte | CK4: Medido Piemonte INCC | CL4: Medido Terceiros INCC | CM4: Medido Terceiros | CN4: Medido Piemonte | CO4: Medido Piemonte INCC | CP4: Medido Terceiros INCC | CQ4: Medido Terceiros | CR4: Medido Piemonte | CS4: Medido Piemonte INCC | CT4: Medido Terceiros INCC | CU4: Medido Terceiros | CV4: Medido Piemonte | CW4: Medido Piemonte INCC | CX4: Medido Terceiros INCC | CY4: Medido Terceiros | CZ4: Medido Piemonte | DA4: Medido Piemonte INCC | DB4: Medido Terceiros INCC | DC4: Medido Terceiros | DD4: Medido Piemonte | DE4: Medido Piemonte INCC | DF4: Medido Terceiros INCC | DG4: Medido Terceiros | DH4: Medido Piemonte | DI4: Medido Piemonte INCC | DJ4: Medido Terceiros INCC | DK4: Medido Terceiros | DL4: Medido Piemonte | DM4: Medido Piemonte INCC | DN4: Medido Terceiros INCC | DO4: Medido Terceiros | DP4: Medido Piemonte | DQ4: Medido Piemonte INCC | DR4: Medido Terceiros INCC | DS4: Medido Terceiros | DT4: Medido Piemonte | DU4: Medido Piemonte INCC | DV4: Medido Terceiros INCC | DW4: Medido Terceiros | DX4: Medido Piemonte | DY4: Medido Piemonte INCC | DZ4: Medido Terceiros INCC | EA4: Medido Terceiros | EB4: Medido Piemonte | EC4: Medido Piemonte INCC | ED4: Medido Terceiros INCC | EE4: Medido Terceiros | EF4: Medido Piemonte | EG4: Medido Piemonte INCC | EH4: Medido Terceiros INCC | EI4: Medido Terceiros | EJ4: Medido Piemonte | EK4: Medido Piemonte INCC | EL4: Medido Terceiros INCC | EM4: Medido Terceiros | EN4: Medido Piemonte | EO4: Medido Piemonte INCC | EP4: Medido Terceiros INCC | EQ4: Medido Terceiros | ER4: Medido Piemonte | ES4: Medido Piemonte INCC | ET4: Medido Terceiros INCC | EU4: Medido Terceiros | EV4: Medido Piemonte | EW4: Medido Piemonte INCC | EX4: Medido Terceiros INCC | EY4: Medido Terceiros
A5: 01.01.04.01.001 | B5: COORDENADOR DE OBRAS | C5: 34 | D5: =E5*C5 -> 393747.2 | E5: 11580.8 | F5: =K5*$C$1 -> -2.1744057e-10 | G5: =D5/$C$2 -> 376.62255 | H5: =E5/$C$2 -> 11.077134 | I5: =SUMIFS($L5:$EQ5,$L$4:$EQ$4,$M$4) -> 376.62255 | J5: =SUMIFS($L5:$EQ5,$L$4:$EQ$4,$N$4) -> 0 | K5: =G5-I5-J5 -> -1.7053026e-13 | L5: =IF($E5*L$2/$C$2-O5>0,$E5*L$2/$C$2-O5,0) -> 11753.625 | M5: =IFERROR(L5/L$2,0) -> 11.077134 | N5: =IFERROR(O5/L$2,0) -> 0 | P5: =IF($E5*P$2/$C$2-S5>0,$E5*P$2/$C$2-S5,0) -> 11800.349 | Q5: =IFERROR(P5/P$2,0) -> 11.077134 | R5: =IFERROR(S5/P$2,0) -> 0 | T5: =IF($E5*T$2/$C$2-W5>0,$E5*T$2/$C$2-W5,0) -> 11900.076 | U5: =IFERROR(T5/T$2,0) -> 11.077134 | V5: =IFERROR(W5/T$2,0) -> 0 | X5: =IF($E5*X$2/$C$2-AA5>0,$E5*X$2/$C$2-AA5,0) -> 11906.756 | Y5: =IFERROR(X5/X$2,0) -> 11.077134 | Z5: =IFERROR(AA5/X$2,0) -> 0 | AB5: =IF($E5*AB$2/$C$2-AE5>0,$E5*AB$2/$C$2-AE5,0) -> 11935.578 | AC5: =IFERROR(AB5/AB$2,0) -> 11.077134 | AD5: =IFERROR(AE5/AB$2,0) -> 0 | AF5: =IF($E5*AF$2/$C$2-AI5>0,$E5*AF$2/$C$2-AI5,0) -> 11964.091 | AG5: =IFERROR(AF5/AF$2,0) -> 11.077134 | AH5: =IFERROR(AI5/AF$2,0) -> 0 | AJ5: =IF($E5*AJ$2/$C$2-AM5>0,$E5*AJ$2/$C$2-AM5,0) -> 11988.239 | AK5: =IFERROR(AJ5/AJ$2,0) -> 11.077134 | AL5: =IFERROR(AM5/AJ$2,0) -> 0 | AN5: =IF($E5*AN$2/$C$2-AQ5>0,$E5*AN$2/$C$2-AQ5,0) -> 12000.247 | AO5: =IFERROR(AN5/AN$2,0) -> 11.077134 | AP5: =IFERROR(AQ5/AN$2,0) -> 0 | AR5: =IF($E5*AR$2/$C$2-AU5>0,$E5*AR$2/$C$2-AU5,0) -> 12031.429 | AS5: =IFERROR(AR5/AR$2,0) -> 11.077134 | AT5: =IFERROR(AU5/AR$2,0) -> 0 | AV5: =IF($E5*AV$2/$C$2-AY5>0,$E5*AV$2/$C$2-AY5,0) -> 12059.266 | AW5: =IFERROR(AV5/AV$2,0) -> 11.077134 | AX5: =IFERROR(AY5/AV$2,0) -> 0 | AZ5: =IF($E5*AZ$2/$C$2-BC5>0,$E5*AZ$2/$C$2-BC5,0) -> 12083.724 | BA5: =IFERROR(AZ5/AZ$2,0) -> 11.077134 | BB5: =IFERROR(BC5/AZ$2,0) -> 0 | BD5: =IF($E5*BD$2/$C$2-BG5>0,$E5*BD$2/$C$2-BG5,0) -> 12112.879 | BE5: =IFERROR(BD5/BD$2,0) -> 11.077134 | BF5: =IFERROR(BG5/BD$2,0) -> 0 | BH5: =IF($E5*BH$2/$C$2-BK5>0,$E5*BH$2/$C$2-BK5,0) -> 12162.593 | BI5: =IFERROR(BH5/BH$2,0) -> 11.077134 | BJ5: =IFERROR(BK5/BH$2,0) -> 0 | BL5: =IF($E5*BL$2/$C$2-BO5>0,$E5*BL$2/$C$2-BO5,0) -> 12234.218 | BM5: =IFERROR(BL5/BL$2,0) -> 11.077134 | BN5: =IFERROR(BO5/BL$2,0) -> 0 | BP5: =IF($E5*BP$2/$C$2-BS5>0,$E5*BP$2/$C$2-BS5,0) -> 12348.213 | BQ5: =IFERROR(BP5/BP$2,0) -> 11.077134 | BR5: =IFERROR(BS5/BP$2,0) -> 0 | BT5: =IF($E5*BT$2/$C$2-BW5>0,$E5*BT$2/$C$2-BW5,0) -> 12433.551 | BU5: =IFERROR(BT5/BT$2,0) -> 11.077134 | BV5: =IFERROR(BW5/BT$2,0) -> 0 | BX5: =IF($E5*BX$2/$C$2-CA5>0,$E5*BX$2/$C$2-CA5,0) -> 12513.162 | BY5: =IFERROR(BX5/BX$2,0) -> 11.077134 | BZ5: =IFERROR(CA5/BX$2,0) -> 0 | CB5: =IF($E5*CB$2/$C$2-CE5>0,$E5*CB$2/$C$2-CE5,0) -> 12589.395 | CC5: =IFERROR(CB5/CB$2,0) -> 11.077134 | CD5: =IFERROR(CE5/CB$2,0) -> 0 | CF5: =IF($E5*CF$2/$C$2-CI5>0,$E5*CF$2/$C$2-CI5,0) -> 12673.748 | CG5: =IFERROR(CF5/CF$2,0) -> 11.077134 | CH5: =IFERROR(CI5/CF$2,0) -> 0 | CJ5: =IF($E5*CJ$2/$C$2-CM5>0,$E5*CJ$2/$C$2-CM5,0) -> 12729.377 | CK5: =IFERROR(CJ5/CJ$2,0) -> 11.077134 | CL5: =IFERROR(CM5/CJ$2,0) -> 0 | CN5: =IF($E5*CN$2/$C$2-CQ5>0,$E5*CN$2/$C$2-CQ5,0) -> 12793.979 | CO5: =IFERROR(CN5/CN$2,0) -> 11.077134 | CP5: =IFERROR(CQ5/CN$2,0) -> 0 | CR5: =IF($E5*CR$2/$C$2-CU5>0,$E5*CR$2/$C$2-CU5,0) -> 12885.155 | CS5: =IFERROR(CR5/CR$2,0) -> 11.077134 | CT5: =IFERROR(CU5/CR$2,0) -> 0 | CV5: =IF($E5*CV$2/$C$2-CY5>0,$E5*CV$2/$C$2-CY5,0) -> 12950.897 | CW5: =IFERROR(CV5/CV$2,0) -> 11.077134 | CX5: =IFERROR(CY5/CV$2,0) -> 0 | CZ5: =IF($E5*CZ$2/$C$2-DC5>0,$E5*CZ$2/$C$2-DC5,0) -> 12999.969 | DA5: =IFERROR(CZ5/CZ$2,0) -> 11.077134 | DB5: =IFERROR(DC5/CZ$2,0) -> 0 | DD5: =IF($E5*DD$2/$C$2-DG5>0,$E5*DD$2/$C$2-DG5,0) -> 13077.265 | DE5: =IFERROR(DD5/DD$2,0) -> 11.077134 | DF5: =IFERROR(DG5/DD$2,0) -> 0 | DH5: =IF($E5*DH$2/$C$2-DK5>0,$E5*DH$2/$C$2-DK5,0) -> 13110.962 | DI5: =IFERROR(DH5/DH$2,0) -> 11.077134 | DJ5: =IFERROR(DK5/DH$2,0) -> 0 | DL5: =IF($E5*DL$2/$C$2-DO5>0,$E5*DL$2/$C$2-DO5,0) -> 13236.2 | DM5: =IFERROR(DL5/DL$2,0) -> 11.077134 | DN5: =IFERROR(DO5/DL$2,0) -> 0 | DP5: =IF($E5*DP$2/$C$2-DS5>0,$E5*DP$2/$C$2-DS5,0) -> 13357.229 | DQ5: =IFERROR(DP5/DP$2,0) -> 11.077134 | DR5: =IFERROR(DS5/DP$2,0) -> 0 | DT5: =IF($E5*DT$2/$C$2-DW5>0,$E5*DT$2/$C$2-DW5,0) -> 13450.288 | DU5: =IFERROR(DT5/DT$2,0) -> 11.077134 | DV5: =IFERROR(DW5/DT$2,0) -> 0 | DX5: =IF($E5*DX$2/$C$2-EA5>0,$E5*DX$2/$C$2-EA5,0) -> 13478.933 | DY5: =IFERROR(DX5/DX$2,0) -> 11.077134 | DZ5: =IFERROR(EA5/DX$2,0) -> 0 | EB5: =IF($E5*EB$2/$C$2-EE5>0,$E5*EB$2/$C$2-EE5,0) -> 13507.534 | EC5: =IFERROR(EB5/EB$2,0) -> 11.077134 | ED5: =IFERROR(EE5/EB$2,0) -> 0 | EF5: =IF($E5*EF$2/$C$2-EI5>0,$E5*EF$2/$C$2-EI5,0) -> 13545.839 | EG5: =IFERROR(EF5/EF$2,0) -> 11.077134 | EH5: =IFERROR(EI5/EF$2,0) -> 0 | EJ5: =IF($E5*EJ$2/$C$2-EM5>0,$E5*EJ$2/$C$2-EM5,0) -> 13573.898 | EK5: =IFERROR(EJ5/EJ$2,0) -> 11.077134 | EL5: =IFERROR(EM5/EJ$2,0) -> 0 | EN5: =IF($E5*EN$2/$C$2-EQ5>0,$E5*EN$2/$C$2-EQ5,0) -> 13659.169 | EO5: =IFERROR(EN5/EN$2,0) -> 11.077134 | EP5: =IFERROR(EQ5/EN$2,0) -> 0 | ER5: =IF($E5*ER$2/$C$2-EU5>0,$E5*ER$2/$C$2-EU5,0) -> 13705.871 | ES5: =IFERROR(ER5/ER$2,0) -> 11.077134 | ET5: =IFERROR(EU5/ER$2,0) -> 0 | EV5: =IF($E5*EV$2/$C$2-EY5>0,$E5*EV$2/$C$2-EY5,0)*0.19 -> 2613.3948 | EW5: =IFERROR(EV5/EV$2,0) -> 2.1046554 | EX5: =IFERROR(EY5/EV$2,0) -> 0
A6: 01.01.04.01.002 | B6: ENGENHEIRO RESIDENTE | C6: 34 | D6: =E6*C6 -> 619611.58 | E6: 18223.87 | F6: =K6*$C$1 -> 1.4496038e-10 | G6: =D6/$C$2 -> 592.66375 | H6: =E6/$C$2 -> 17.431287 | I6: =SUMIFS($L6:$EQ6,$L$4:$EQ$4,$M$4) -> 592.66375 | J6: =SUMIFS($L6:$EQ6,$L$4:$EQ$4,$N$4) -> 0 | K6: =G6-I6-J6 -> 1.1368684e-13 | L6: =IF($E6*L$2/$C$2-O6>0,$E6*L$2/$C$2-O6,0) -> 18495.833 | M6: =IFERROR(L6/L$2,0) -> 17.431287 | N6: =IFERROR(O6/L$2,0) -> 0 | P6: =IF($E6*P$2/$C$2-S6>0,$E6*P$2/$C$2-S6,0) -> 18569.358 | Q6: =IFERROR(P6/P$2,0) -> 17.431287 | R6: =IFERROR(S6/P$2,0) -> 0 | T6: =IF($E6*T$2/$C$2-W6>0,$E6*T$2/$C$2-W6,0) -> 18726.292 | U6: =IFERROR(T6/T$2,0) -> 17.431287 | V6: =IFERROR(W6/T$2,0) -> 0 | X6: =IF($E6*X$2/$C$2-AA6>0,$E6*X$2/$C$2-AA6,0) -> 18736.803 | Y6: =IFERROR(X6/X$2,0) -> 17.431287 | Z6: =IFERROR(AA6/X$2,0) -> 0 | AB6: =IF($E6*AB$2/$C$2-AE6>0,$E6*AB$2/$C$2-AE6,0) -> 18782.159 | AC6: =IFERROR(AB6/AB$2,0) -> 17.431287 | AD6: =IFERROR(AE6/AB$2,0) -> 0 | AF6: =IF($E6*AF$2/$C$2-AI6>0,$E6*AF$2/$C$2-AI6,0) -> 18827.027 | AG6: =IFERROR(AF6/AF$2,0) -> 17.431287 | AH6: =IFERROR(AI6/AF$2,0) -> 0 | AJ6: =IF($E6*AJ$2/$C$2-AM6>0,$E6*AJ$2/$C$2-AM6,0) -> 18865.028 | AK6: =IFERROR(AJ6/AJ$2,0) -> 17.431287 | AL6: =IFERROR(AM6/AJ$2,0) -> 0 | AN6: =IF($E6*AN$2/$C$2-AQ6>0,$E6*AN$2/$C$2-AQ6,0) -> 18883.923 | AO6: =IFERROR(AN6/AN$2,0) -> 17.431287 | AP6: =IFERROR(AQ6/AN$2,0) -> 0 | AR6: =IF($E6*AR$2/$C$2-AU6>0,$E6*AR$2/$C$2-AU6,0) -> 18932.992 | AS6: =IFERROR(AR6/AR$2,0) -> 17.431287 | AT6: =IFERROR(AU6/AR$2,0) -> 0 | AV6: =IF($E6*AV$2/$C$2-AY6>0,$E6*AV$2/$C$2-AY6,0) -> 18976.797 | AW6: =IFERROR(AV6/AV$2,0) -> 17.431287 | AX6: =IFERROR(AY6/AV$2,0) -> 0 | AZ6: =IF($E6*AZ$2/$C$2-BC6>0,$E6*AZ$2/$C$2-BC6,0) -> 19015.285 | BA6: =IFERROR(AZ6/AZ$2,0) -> 17.431287 | BB6: =IFERROR(BC6/AZ$2,0) -> 0 | BD6: =IF($E6*BD$2/$C$2-BG6>0,$E6*BD$2/$C$2-BG6,0) -> 19061.164 | BE6: =IFERROR(BD6/BD$2,0) -> 17.431287 | BF6: =IFERROR(BG6/BD$2,0) -> 0 | BH6: =IF($E6*BH$2/$C$2-BK6>0,$E6*BH$2/$C$2-BK6,0) -> 19139.396 | BI6: =IFERROR(BH6/BH$2,0) -> 17.431287 | BJ6: =IFERROR(BK6/BH$2,0) -> 0 | BL6: =IF($E6*BL$2/$C$2-BO6>0,$E6*BL$2/$C$2-BO6,0) -> 19252.107 | BM6: =IFERROR(BL6/BL$2,0) -> 17.431287 | BN6: =IFERROR(BO6/BL$2,0) -> 0 | BP6: =IF($E6*BP$2/$C$2-BS6>0,$E6*BP$2/$C$2-BS6,0) -> 19431.492 | BQ6: =IFERROR(BP6/BP$2,0) -> 17.431287 | BR6: =IFERROR(BS6/BP$2,0) -> 0 | BT6: =IF($E6*BT$2/$C$2-BW6>0,$E6*BT$2/$C$2-BW6,0) -> 19565.783 | BU6: =IFERROR(BT6/BT$2,0) -> 17.431287 | BV6: =IFERROR(BW6/BT$2,0) -> 0 | BX6: =IF($E6*BX$2/$C$2-CA6>0,$E6*BX$2/$C$2-CA6,0) -> 19691.061 | BY6: =IFERROR(BX6/BX$2,0) -> 17.431287 | BZ6: =IFERROR(CA6/BX$2,0) -> 0 | CB6: =IF($E6*CB$2/$C$2-CE6>0,$E6*CB$2/$C$2-CE6,0) -> 19811.024 | CC6: =IFERROR(CB6/CB$2,0) -> 17.431287 | CD6: =IFERROR(CE6/CB$2,0) -> 0 | CF6: =IF($E6*CF$2/$C$2-CI6>0,$E6*CF$2/$C$2-CI6,0) -> 19943.763 | CG6: =IFERROR(CF6/CF$2,0) -> 17.431287 | CH6: =IFERROR(CI6/CF$2,0) -> 0 | CJ6: =IF($E6*CJ$2/$C$2-CM6>0,$E6*CJ$2/$C$2-CM6,0) -> 20031.303 | CK6: =IFERROR(CJ6/CJ$2,0) -> 17.431287 | CL6: =IFERROR(CM6/CJ$2,0) -> 0 | CN6: =IF($E6*CN$2/$C$2-CQ6>0,$E6*CN$2/$C$2-CQ6,0) -> 20132.962 | CO6: =IFERROR(CN6/CN$2,0) -> 17.431287 | CP6: =IFERROR(CQ6/CN$2,0) -> 0 | CR6: =IF($E6*CR$2/$C$2-CU6>0,$E6*CR$2/$C$2-CU6,0) -> 20276.439 | CS6: =IFERROR(CR6/CR$2,0) -> 17.431287 | CT6: =IFERROR(CU6/CR$2,0) -> 0 | CV6: =IF($E6*CV$2/$C$2-CY6>0,$E6*CV$2/$C$2-CY6,0) -> 20379.894 | CW6: =IFERROR(CV6/CV$2,0) -> 17.431287 | CX6: =IFERROR(CY6/CV$2,0) -> 0 | CZ6: =IF($E6*CZ$2/$C$2-DC6>0,$E6*CZ$2/$C$2-DC6,0) -> 20457.114 | DA6: =IFERROR(CZ6/CZ$2,0) -> 17.431287 | DB6: =IFERROR(DC6/CZ$2,0) -> 0 | DD6: =IF($E6*DD$2/$C$2-DG6>0,$E6*DD$2/$C$2-DG6,0) -> 20578.75 | DE6: =IFERROR(DD6/DD$2,0) -> 17.431287 | DF6: =IFERROR(DG6/DD$2,0) -> 0 | DH6: =IF($E6*DH$2/$C$2-DK6>0,$E6*DH$2/$C$2-DK6,0) -> 20631.776 | DI6: =IFERROR(DH6/DH$2,0) -> 17.431287 | DJ6: =IFERROR(DK6/DH$2,0) -> 0 | DL6: =IF($E6*DL$2/$C$2-DO6>0,$E6*DL$2/$C$2-DO6,0) -> 20828.854 | DM6: =IFERROR(DL6/DL$2,0) -> 17.431287 | DN6: =IFERROR(DO6/DL$2,0) -> 0 | DP6: =IF($E6*DP$2/$C$2-DS6>0,$E6*DP$2/$C$2-DS6,0) -> 21019.308 | DQ6: =IFERROR(DP6/DP$2,0) -> 17.431287 | DR6: =IFERROR(DS6/DP$2,0) -> 0 | DT6: =IF($E6*DT$2/$C$2-DW6>0,$E6*DT$2/$C$2-DW6,0) -> 21165.748 | DU6: =IFERROR(DT6/DT$2,0) -> 17.431287 | DV6: =IFERROR(DW6/DT$2,0) -> 0 | DX6: =IF($E6*DX$2/$C$2-EA6>0,$E6*DX$2/$C$2-EA6,0) -> 21210.826 | DY6: =IFERROR(DX6/DX$2,0) -> 17.431287 | DZ6: =IFERROR(EA6/DX$2,0) -> 0 | EB6: =IF($E6*EB$2/$C$2-EE6>0,$E6*EB$2/$C$2-EE6,0) -> 21255.833 | EC6: =IFERROR(EB6/EB$2,0) -> 17.431287 | ED6: =IFERROR(EE6/EB$2,0) -> 0 | EF6: =IF($E6*EF$2/$C$2-EI6>0,$E6*EF$2/$C$2-EI6,0) -> 21316.111 | EG6: =IFERROR(EF6/EF$2,0) -> 17.431287 | EH6: =IFERROR(EI6/EF$2,0) -> 0 | EJ6: =IF($E6*EJ$2/$C$2-EM6>0,$E6*EJ$2/$C$2-EM6,0) -> 21360.264 | EK6: =IFERROR(EJ6/EJ$2,0) -> 17.431287 | EL6: =IFERROR(EM6/EJ$2,0) -> 0 | EN6: =IF($E6*EN$2/$C$2-EQ6>0,$E6*EN$2/$C$2-EQ6,0) -> 21494.45 | EO6: =IFERROR(EN6/EN$2,0) -> 17.431287 | EP6: =IFERROR(EQ6/EN$2,0) -> 0 | ER6: =IF($E6*ER$2/$C$2-EU6>0,$E6*ER$2/$C$2-EU6,0) -> 21567.94 | ES6: =IFERROR(ER6/ER$2,0) -> 17.431287 | ET6: =IFERROR(EU6/ER$2,0) -> 0 | EV6: =IF($E6*EV$2/$C$2-EY6>0,$E6*EV$2/$C$2-EY6,0)*0.19 -> 4112.511 | EW6: =IFERROR(EV6/EV$2,0) -> 3.3119445 | EX6: =IFERROR(EY6/EV$2,0) -> 0
A7: 01.01.04.01.003 | B7: ESTAGIARIO | C7: 34 | D7: =E7*C7 -> 148620.12 | E7: 4371.18 | F7: =K7*$C$1 -> -3.6240095e-11 | G7: =D7/$C$2 -> 142.15641 | H7: =E7/$C$2 -> 4.1810709 | I7: =SUMIFS($L7:$EQ7,$L$4:$EQ$4,$M$4) -> 142.15641 | J7: =SUMIFS($L7:$EQ7,$L$4:$EQ$4,$N$4) -> 0 | K7: =G7-I7-J7 -> -2.8421709e-14 | L7: =IF($E7*L$2/$C$2-O7>0,$E7*L$2/$C$2-O7,0) -> 4436.4131 | M7: =IFERROR(L7/L$2,0) -> 4.1810709 | N7: =IFERROR(O7/L$2,0) -> 0 | P7: =IF($E7*P$2/$C$2-S7>0,$E7*P$2/$C$2-S7,0) -> 4454.0488 | Q7: =IFERROR(P7/P$2,0) -> 4.1810709 | R7: =IFERROR(S7/P$2,0) -> 0 | T7: =IF($E7*T$2/$C$2-W7>0,$E7*T$2/$C$2-W7,0) -> 4491.691 | U7: =IFERROR(T7/T$2,0) -> 4.1810709 | V7: =IFERROR(W7/T$2,0) -> 0 | X7: =IF($E7*X$2/$C$2-AA7>0,$E7*X$2/$C$2-AA7,0) -> 4494.2122 | Y7: =IFERROR(X7/X$2,0) -> 4.1810709 | Z7: =IFERROR(AA7/X$2,0) -> 0 | AB7: =IF($E7*AB$2/$C$2-AE7>0,$E7*AB$2/$C$2-AE7,0) -> 4505.0913 | AC7: =IFERROR(AB7/AB$2,0) -> 4.1810709 | AD7: =IFERROR(AE7/AB$2,0) -> 0 | AF7: =IF($E7*AF$2/$C$2-AI7>0,$E7*AF$2/$C$2-AI7,0) -> 4515.8534 | AG7: =IFERROR(AF7/AF$2,0) -> 4.1810709 | AH7: =IFERROR(AI7/AF$2,0) -> 0 | AJ7: =IF($E7*AJ$2/$C$2-AM7>0,$E7*AJ$2/$C$2-AM7,0) -> 4524.9681 | AK7: =IFERROR(AJ7/AJ$2,0) -> 4.1810709 | AL7: =IFERROR(AM7/AJ$2,0) -> 0 | AN7: =IF($E7*AN$2/$C$2-AQ7>0,$E7*AN$2/$C$2-AQ7,0) -> 4529.5004 | AO7: =IFERROR(AN7/AN$2,0) -> 4.1810709 | AP7: =IFERROR(AQ7/AN$2,0) -> 0 | AR7: =IF($E7*AR$2/$C$2-AU7>0,$E7*AR$2/$C$2-AU7,0) -> 4541.2701 | AS7: =IFERROR(AR7/AR$2,0) -> 4.1810709 | AT7: =IFERROR(AU7/AR$2,0) -> 0 | AV7: =IF($E7*AV$2/$C$2-AY7>0,$E7*AV$2/$C$2-AY7,0) -> 4551.7772 | AW7: =IFERROR(AV7/AV$2,0) -> 4.1810709 | AX7: =IFERROR(AY7/AV$2,0) -> 0 | AZ7: =IF($E7*AZ$2/$C$2-BC7>0,$E7*AZ$2/$C$2-BC7,0) -> 4561.009 | BA7: =IFERROR(AZ7/AZ$2,0) -> 4.1810709 | BB7: =IFERROR(BC7/AZ$2,0) -> 0 | BD7: =IF($E7*BD$2/$C$2-BG7>0,$E7*BD$2/$C$2-BG7,0) -> 4572.0136 | BE7: =IFERROR(BD7/BD$2,0) -> 4.1810709 | BF7: =IFERROR(BG7/BD$2,0) -> 0 | BH7: =IF($E7*BH$2/$C$2-BK7>0,$E7*BH$2/$C$2-BK7,0) -> 4590.7782 | BI7: =IFERROR(BH7/BH$2,0) -> 4.1810709 | BJ7: =IFERROR(BK7/BH$2,0) -> 0 | BL7: =IF($E7*BL$2/$C$2-BO7>0,$E7*BL$2/$C$2-BO7,0) -> 4617.813 | BM7: =IFERROR(BL7/BL$2,0) -> 4.1810709 | BN7: =IFERROR(BO7/BL$2,0) -> 0 | BP7: =IF($E7*BP$2/$C$2-BS7>0,$E7*BP$2/$C$2-BS7,0) -> 4660.8404 | BQ7: =IFERROR(BP7/BP$2,0) -> 4.1810709 | BR7: =IFERROR(BS7/BP$2,0) -> 0 | BT7: =IF($E7*BT$2/$C$2-BW7>0,$E7*BT$2/$C$2-BW7,0) -> 4693.0514 | BU7: =IFERROR(BT7/BT$2,0) -> 4.1810709 | BV7: =IFERROR(BW7/BT$2,0) -> 0 | BX7: =IF($E7*BX$2/$C$2-CA7>0,$E7*BX$2/$C$2-CA7,0) -> 4723.1007 | BY7: =IFERROR(BX7/BX$2,0) -> 4.1810709 | BZ7: =IFERROR(CA7/BX$2,0) -> 0 | CB7: =IF($E7*CB$2/$C$2-CE7>0,$E7*CB$2/$C$2-CE7,0) -> 4751.8749 | CC7: =IFERROR(CB7/CB$2,0) -> 4.1810709 | CD7: =IFERROR(CE7/CB$2,0) -> 0 | CF7: =IF($E7*CF$2/$C$2-CI7>0,$E7*CF$2/$C$2-CI7,0) -> 4783.7137 | CG7: =IFERROR(CF7/CF$2,0) -> 4.1810709 | CH7: =IFERROR(CI7/CF$2,0) -> 0 | CJ7: =IF($E7*CJ$2/$C$2-CM7>0,$E7*CJ$2/$C$2-CM7,0) -> 4804.7111 | CK7: =IFERROR(CJ7/CJ$2,0) -> 4.1810709 | CL7: =IFERROR(CM7/CJ$2,0) -> 0 | CN7: =IF($E7*CN$2/$C$2-CQ7>0,$E7*CN$2/$C$2-CQ7,0) -> 4829.0951 | CO7: =IFERROR(CN7/CN$2,0) -> 4.1810709 | CP7: =IFERROR(CQ7/CN$2,0) -> 0 | CR7: =IF($E7*CR$2/$C$2-CU7>0,$E7*CR$2/$C$2-CU7,0) -> 4863.5095 | CS7: =IFERROR(CR7/CR$2,0) -> 4.1810709 | CT7: =IFERROR(CU7/CR$2,0) -> 0 | CV7: =IF($E7*CV$2/$C$2-CY7>0,$E7*CV$2/$C$2-CY7,0) -> 4888.3241 | CW7: =IFERROR(CV7/CV$2,0) -> 4.1810709 | CX7: =IFERROR(CY7/CV$2,0) -> 0 | CZ7: =IF($E7*CZ$2/$C$2-DC7>0,$E7*CZ$2/$C$2-DC7,0) -> 4906.8463 | DA7: =IFERROR(CZ7/CZ$2,0) -> 4.1810709 | DB7: =IFERROR(DC7/CZ$2,0) -> 0 | DD7: =IF($E7*DD$2/$C$2-DG7>0,$E7*DD$2/$C$2-DG7,0) -> 4936.0218 | DE7: =IFERROR(DD7/DD$2,0) -> 4.1810709 | DF7: =IFERROR(DG7/DD$2,0) -> 0 | DH7: =IF($E7*DH$2/$C$2-DK7>0,$E7*DH$2/$C$2-DK7,0) -> 4948.7406 | DI7: =IFERROR(DH7/DH$2,0) -> 4.1810709 | DJ7: =IFERROR(DK7/DH$2,0) -> 0 | DL7: =IF($E7*DL$2/$C$2-DO7>0,$E7*DL$2/$C$2-DO7,0) -> 4996.0118 | DM7: =IFERROR(DL7/DL$2,0) -> 4.1810709 | DN7: =IFERROR(DO7/DL$2,0) -> 0 | DP7: =IF($E7*DP$2/$C$2-DS7>0,$E7*DP$2/$C$2-DS7,0) -> 5041.6942 | DQ7: =IFERROR(DP7/DP$2,0) -> 4.1810709 | DR7: =IFERROR(DS7/DP$2,0) -> 0 | DT7: =IF($E7*DT$2/$C$2-DW7>0,$E7*DT$2/$C$2-DW7,0) -> 5076.8193 | DU7: =IFERROR(DT7/DT$2,0) -> 4.1810709 | DV7: =IFERROR(DW7/DT$2,0) -> 0 | DX7: =IF($E7*DX$2/$C$2-EA7>0,$E7*DX$2/$C$2-EA7,0) -> 5087.6316 | DY7: =IFERROR(DX7/DX$2,0) -> 4.1810709 | DZ7: =IFERROR(EA7/DX$2,0) -> 0 | EB7: =IF($E7*EB$2/$C$2-EE7>0,$E7*EB$2/$C$2-EE7,0) -> 5098.4271 | EC7: =IFERROR(EB7/EB$2,0) -> 4.1810709 | ED7: =IFERROR(EE7/EB$2,0) -> 0 | EF7: =IF($E7*EF$2/$C$2-EI7>0,$E7*EF$2/$C$2-EI7,0) -> 5112.8853 | EG7: =IFERROR(EF7/EF$2,0) -> 4.1810709 | EH7: =IFERROR(EI7/EF$2,0) -> 0 | EJ7: =IF($E7*EJ$2/$C$2-EM7>0,$E7*EJ$2/$C$2-EM7,0) -> 5123.4759 | EK7: =IFERROR(EJ7/EJ$2,0) -> 4.1810709 | EL7: =IFERROR(EM7/EJ$2,0) -> 0 | EN7: =IF($E7*EN$2/$C$2-EQ7>0,$E7*EN$2/$C$2-EQ7,0) -> 5155.6618 | EO7: =IFERROR(EN7/EN$2,0) -> 4.1810709 | EP7: =IFERROR(EQ7/EN$2,0) -> 0 | ER7: =IF($E7*ER$2/$C$2-EU7>0,$E7*ER$2/$C$2-EU7,0) -> 5173.2892 | ES7: =IFERROR(ER7/ER$2,0) -> 4.1810709 | ET7: =IFERROR(EU7/ER$2,0) -> 0 | EV7: =IF($E7*EV$2/$C$2-EY7>0,$E7*EV$2/$C$2-EY7,0)*0.19 -> 986.42747 | EW7: =IFERROR(EV7/EV$2,0) -> 0.79440347 | EX7: =IFERROR(EY7/EV$2,0) -> 0
A8: 01.01.04.01.004 | B8: MESTRE DE OBRAS | C8: 34 | D8: =E8*C8 -> 506600 | E8: 14900 | F8: =K8*$C$1 -> -2.1744057e-10 | G8: =D8/$C$2 -> 484.56721 | H8: =E8/$C$2 -> 14.251977 | I8: =SUMIFS($L8:$EQ8,$L$4:$EQ$4,$M$4) -> 484.56721 | J8: =SUMIFS($L8:$EQ8,$L$4:$EQ$4,$N$4) -> 0 | K8: =G8-I8-J8 -> -1.7053026e-13 | L8: =IF($E8*L$2/$C$2-O8>0,$E8*L$2/$C$2-O8,0) -> 15122.359 | M8: =IFERROR(L8/L$2,0) -> 14.251977 | N8: =IFERROR(O8/L$2,0) -> 0 | P8: =IF($E8*P$2/$C$2-S8>0,$E8*P$2/$C$2-S8,0) -> 15182.474 | Q8: =IFERROR(P8/P$2,0) -> 14.251977 | R8: =IFERROR(S8/P$2,0) -> 0 | T8: =IF($E8*T$2/$C$2-W8>0,$E8*T$2/$C$2-W8,0) -> 15310.785 | U8: =IFERROR(T8/T$2,0) -> 14.251977 | V8: =IFERROR(W8/T$2,0) -> 0 | X8: =IF($E8*X$2/$C$2-AA8>0,$E8*X$2/$C$2-AA8,0) -> 15319.379 | Y8: =IFERROR(X8/X$2,0) -> 14.251977 | Z8: =IFERROR(AA8/X$2,0) -> 0 | AB8: =IF($E8*AB$2/$C$2-AE8>0,$E8*AB$2/$C$2-AE8,0) -> 15356.462 | AC8: =IFERROR(AB8/AB$2,0) -> 14.251977 | AD8: =IFERROR(AE8/AB$2,0) -> 0 | AF8: =IF($E8*AF$2/$C$2-AI8>0,$E8*AF$2/$C$2-AI8,0) -> 15393.147 | AG8: =IFERROR(AF8/AF$2,0) -> 14.251977 | AH8: =IFERROR(AI8/AF$2,0) -> 0 | AJ8: =IF($E8*AJ$2/$C$2-AM8>0,$E8*AJ$2/$C$2-AM8,0) -> 15424.216 | AK8: =IFERROR(AJ8/AJ$2,0) -> 14.251977 | AL8: =IFERROR(AM8/AJ$2,0) -> 0 | AN8: =IF($E8*AN$2/$C$2-AQ8>0,$E8*AN$2/$C$2-AQ8,0) -> 15439.665 | AO8: =IFERROR(AN8/AN$2,0) -> 14.251977 | AP8: =IFERROR(AQ8/AN$2,0) -> 0 | AR8: =IF($E8*AR$2/$C$2-AU8>0,$E8*AR$2/$C$2-AU8,0) -> 15479.785 | AS8: =IFERROR(AR8/AR$2,0) -> 14.251977 | AT8: =IFERROR(AU8/AR$2,0) -> 0 | AV8: =IF($E8*AV$2/$C$2-AY8>0,$E8*AV$2/$C$2-AY8,0) -> 15515.6 | AW8: =IFERROR(AV8/AV$2,0) -> 14.251977 | AX8: =IFERROR(AY8/AV$2,0) -> 0 | AZ8: =IF($E8*AZ$2/$C$2-BC8>0,$E8*AZ$2/$C$2-BC8,0) -> 15547.068 | BA8: =IFERROR(AZ8/AZ$2,0) -> 14.251977 | BB8: =IFERROR(BC8/AZ$2,0) -> 0 | BD8: =IF($E8*BD$2/$C$2-BG8>0,$E8*BD$2/$C$2-BG8,0) -> 15584.579 | BE8: =IFERROR(BD8/BD$2,0) -> 14.251977 | BF8: =IFERROR(BG8/BD$2,0) -> 0 | BH8: =IF($E8*BH$2/$C$2-BK8>0,$E8*BH$2/$C$2-BK8,0) -> 15648.542 | BI8: =IFERROR(BH8/BH$2,0) -> 14.251977 | BJ8: =IFERROR(BK8/BH$2,0) -> 0 | BL8: =IF($E8*BL$2/$C$2-BO8>0,$E8*BL$2/$C$2-BO8,0) -> 15740.696 | BM8: =IFERROR(BL8/BL$2,0) -> 14.251977 | BN8: =IFERROR(BO8/BL$2,0) -> 0 | BP8: =IF($E8*BP$2/$C$2-BS8>0,$E8*BP$2/$C$2-BS8,0) -> 15887.363 | BQ8: =IFERROR(BP8/BP$2,0) -> 14.251977 | BR8: =IFERROR(BS8/BP$2,0) -> 0 | BT8: =IF($E8*BT$2/$C$2-BW8>0,$E8*BT$2/$C$2-BW8,0) -> 15997.16 | BU8: =IFERROR(BT8/BT$2,0) -> 14.251977 | BV8: =IFERROR(BW8/BT$2,0) -> 0 | BX8: =IF($E8*BX$2/$C$2-CA8>0,$E8*BX$2/$C$2-CA8,0) -> 16099.589 | BY8: =IFERROR(BX8/BX$2,0) -> 14.251977 | BZ8: =IFERROR(CA8/BX$2,0) -> 0 | CB8: =IF($E8*CB$2/$C$2-CE8>0,$E8*CB$2/$C$2-CE8,0) -> 16197.671 | CC8: =IFERROR(CB8/CB$2,0) -> 14.251977 | CD8: =IFERROR(CE8/CB$2,0) -> 0 | CF8: =IF($E8*CF$2/$C$2-CI8>0,$E8*CF$2/$C$2-CI8,0) -> 16306.2 | CG8: =IFERROR(CF8/CF$2,0) -> 14.251977 | CH8: =IFERROR(CI8/CF$2,0) -> 0 | CJ8: =IF($E8*CJ$2/$C$2-CM8>0,$E8*CJ$2/$C$2-CM8,0) -> 16377.773 | CK8: =IFERROR(CJ8/CJ$2,0) -> 14.251977 | CL8: =IFERROR(CM8/CJ$2,0) -> 0 | CN8: =IF($E8*CN$2/$C$2-CQ8>0,$E8*CN$2/$C$2-CQ8,0) -> 16460.891 | CO8: =IFERROR(CN8/CN$2,0) -> 14.251977 | CP8: =IFERROR(CQ8/CN$2,0) -> 0 | CR8: =IF($E8*CR$2/$C$2-CU8>0,$E8*CR$2/$C$2-CU8,0) -> 16578.199 | CS8: =IFERROR(CR8/CR$2,0) -> 14.251977 | CT8: =IFERROR(CU8/CR$2,0) -> 0 | CV8: =IF($E8*CV$2/$C$2-CY8>0,$E8*CV$2/$C$2-CY8,0) -> 16662.784 | CW8: =IFERROR(CV8/CV$2,0) -> 14.251977 | CX8: =IFERROR(CY8/CV$2,0) -> 0 | CZ8: =IF($E8*CZ$2/$C$2-DC8>0,$E8*CZ$2/$C$2-DC8,0) -> 16725.921 | DA8: =IFERROR(CZ8/CZ$2,0) -> 14.251977 | DB8: =IFERROR(DC8/CZ$2,0) -> 0 | DD8: =IF($E8*DD$2/$C$2-DG8>0,$E8*DD$2/$C$2-DG8,0) -> 16825.371 | DE8: =IFERROR(DD8/DD$2,0) -> 14.251977 | DF8: =IFERROR(DG8/DD$2,0) -> 0 | DH8: =IF($E8*DH$2/$C$2-DK8>0,$E8*DH$2/$C$2-DK8,0) -> 16868.725 | DI8: =IFERROR(DH8/DH$2,0) -> 14.251977 | DJ8: =IFERROR(DK8/DH$2,0) -> 0 | DL8: =IF($E8*DL$2/$C$2-DO8>0,$E8*DL$2/$C$2-DO8,0) -> 17029.858 | DM8: =IFERROR(DL8/DL$2,0) -> 14.251977 | DN8: =IFERROR(DO8/DL$2,0) -> 0 | DP8: =IF($E8*DP$2/$C$2-DS8>0,$E8*DP$2/$C$2-DS8,0) -> 17185.575 | DQ8: =IFERROR(DP8/DP$2,0) -> 14.251977 | DR8: =IFERROR(DS8/DP$2,0) -> 0 | DT8: =IF($E8*DT$2/$C$2-DW8>0,$E8*DT$2/$C$2-DW8,0) -> 17305.306 | DU8: =IFERROR(DT8/DT$2,0) -> 14.251977 | DV8: =IFERROR(DW8/DT$2,0) -> 0 | DX8: =IF($E8*DX$2/$C$2-EA8>0,$E8*DX$2/$C$2-EA8,0) -> 17342.162 | DY8: =IFERROR(DX8/DX$2,0) -> 14.251977 | DZ8: =IFERROR(EA8/DX$2,0) -> 0 | EB8: =IF($E8*EB$2/$C$2-EE8>0,$E8*EB$2/$C$2-EE8,0) -> 17378.96 | EC8: =IFERROR(EB8/EB$2,0) -> 14.251977 | ED8: =IFERROR(EE8/EB$2,0) -> 0 | EF8: =IF($E8*EF$2/$C$2-EI8>0,$E8*EF$2/$C$2-EI8,0) -> 17428.244 | EG8: =IFERROR(EF8/EF$2,0) -> 14.251977 | EH8: =IFERROR(EI8/EF$2,0) -> 0 | EJ8: =IF($E8*EJ$2/$C$2-EM8>0,$E8*EJ$2/$C$2-EM8,0) -> 17464.344 | EK8: =IFERROR(EJ8/EJ$2,0) -> 14.251977 | EL8: =IFERROR(EM8/EJ$2,0) -> 0 | EN8: =IF($E8*EN$2/$C$2-EQ8>0,$E8*EN$2/$C$2-EQ8,0) -> 17574.056 | EO8: =IFERROR(EN8/EN$2,0) -> 14.251977 | EP8: =IFERROR(EQ8/EN$2,0) -> 0 | ER8: =IF($E8*ER$2/$C$2-EU8>0,$E8*ER$2/$C$2-EU8,0) -> 17634.142 | ES8: =IFERROR(ER8/ER$2,0) -> 14.251977 | ET8: =IFERROR(EU8/ER$2,0) -> 0 | EV8: =IF($E8*EV$2/$C$2-EY8>0,$E8*EV$2/$C$2-EY8,0)*0.19 -> 3362.426 | EW8: =IFERROR(EV8/EV$2,0) -> 2.7078756 | EX8: =IFERROR(EY8/EV$2,0) -> 0
A9: 01.01.04.01.006 | B9: ADMINISTRATIVO DE OBRAS | C9: 34 | D9: =E9*C9 -> 193948.24 | E9: 5704.36 | F9: =K9*$C$1 -> -1.4496038e-10 | G9: =D9/$C$2 -> 185.51314 | H9: =E9/$C$2 -> 5.4562689 | I9: =SUMIFS($L9:$EQ9,$L$4:$EQ$4,$M$4) -> 185.51314 | J9: =SUMIFS($L9:$EQ9,$L$4:$EQ$4,$N$4) -> 0 | K9: =G9-I9-J9 -> -1.1368684e-13 | L9: =IF($E9*L$2/$C$2-O9>0,$E9*L$2/$C$2-O9,0) -> 5789.4887 | M9: =IFERROR(L9/L$2,0) -> 5.4562689 | N9: =IFERROR(O9/L$2,0) -> 0 | P9: =IF($E9*P$2/$C$2-S9>0,$E9*P$2/$C$2-S9,0) -> 5812.5032 | Q9: =IFERROR(P9/P$2,0) -> 5.4562689 | R9: =IFERROR(S9/P$2,0) -> 0 | T9: =IF($E9*T$2/$C$2-W9>0,$E9*T$2/$C$2-W9,0) -> 5861.626 | U9: =IFERROR(T9/T$2,0) -> 5.4562689 | V9: =IFERROR(W9/T$2,0) -> 0 | X9: =IF($E9*X$2/$C$2-AA9>0,$E9*X$2/$C$2-AA9,0) -> 5864.9162 | Y9: =IFERROR(X9/X$2,0) -> 5.4562689 | Z9: =IFERROR(AA9/X$2,0) -> 0 | AB9: =IF($E9*AB$2/$C$2-AE9>0,$E9*AB$2/$C$2-AE9,0) -> 5879.1134 | AC9: =IFERROR(AB9/AB$2,0) -> 5.4562689 | AD9: =IFERROR(AE9/AB$2,0) -> 0 | AF9: =IF($E9*AF$2/$C$2-AI9>0,$E9*AF$2/$C$2-AI9,0) -> 5893.1578 | AG9: =IFERROR(AF9/AF$2,0) -> 5.4562689 | AH9: =IFERROR(AI9/AF$2,0) -> 0 | AJ9: =IF($E9*AJ$2/$C$2-AM9>0,$E9*AJ$2/$C$2-AM9,0) -> 5905.0525 | AK9: =IFERROR(AJ9/AJ$2,0) -> 5.4562689 | AL9: =IFERROR(AM9/AJ$2,0) -> 0 | AN9: =IF($E9*AN$2/$C$2-AQ9>0,$E9*AN$2/$C$2-AQ9,0) -> 5910.9671 | AO9: =IFERROR(AN9/AN$2,0) -> 5.4562689 | AP9: =IFERROR(AQ9/AN$2,0) -> 0 | AR9: =IF($E9*AR$2/$C$2-AU9>0,$E9*AR$2/$C$2-AU9,0) -> 5926.3265 | AS9: =IFERROR(AR9/AR$2,0) -> 5.4562689 | AT9: =IFERROR(AU9/AR$2,0) -> 0 | AV9: =IF($E9*AV$2/$C$2-AY9>0,$E9*AV$2/$C$2-AY9,0) -> 5940.0381 | AW9: =IFERROR(AV9/AV$2,0) -> 5.4562689 | AX9: =IFERROR(AY9/AV$2,0) -> 0 | AZ9: =IF($E9*AZ$2/$C$2-BC9>0,$E9*AZ$2/$C$2-BC9,0) -> 5952.0855 | BA9: =IFERROR(AZ9/AZ$2,0) -> 5.4562689 | BB9: =IFERROR(BC9/AZ$2,0) -> 0 | BD9: =IF($E9*BD$2/$C$2-BG9>0,$E9*BD$2/$C$2-BG9,0) -> 5966.4464 | BE9: =IFERROR(BD9/BD$2,0) -> 5.4562689 | BF9: =IFERROR(BG9/BD$2,0) -> 0 | BH9: =IF($E9*BH$2/$C$2-BK9>0,$E9*BH$2/$C$2-BK9,0) -> 5990.9342 | BI9: =IFERROR(BH9/BH$2,0) -> 5.4562689 | BJ9: =IFERROR(BK9/BH$2,0) -> 0 | BL9: =IF($E9*BL$2/$C$2-BO9>0,$E9*BL$2/$C$2-BO9,0) -> 6026.2144 | BM9: =IFERROR(BL9/BL$2,0) -> 5.4562689 | BN9: =IFERROR(BO9/BL$2,0) -> 0 | BP9: =IF($E9*BP$2/$C$2-BS9>0,$E9*BP$2/$C$2-BS9,0) -> 6082.3649 | BQ9: =IFERROR(BP9/BP$2,0) -> 5.4562689 | BR9: =IFERROR(BS9/BP$2,0) -> 0 | BT9: =IF($E9*BT$2/$C$2-BW9>0,$E9*BT$2/$C$2-BW9,0) -> 6124.3999 | BU9: =IFERROR(BT9/BT$2,0) -> 5.4562689 | BV9: =IFERROR(BW9/BT$2,0) -> 0 | BX9: =IF($E9*BX$2/$C$2-CA9>0,$E9*BX$2/$C$2-CA9,0) -> 6163.6142 | BY9: =IFERROR(BX9/BX$2,0) -> 5.4562689 | BZ9: =IFERROR(CA9/BX$2,0) -> 0 | CB9: =IF($E9*CB$2/$C$2-CE9>0,$E9*CB$2/$C$2-CE9,0) -> 6201.1642 | CC9: =IFERROR(CB9/CB$2,0) -> 5.4562689 | CD9: =IFERROR(CE9/CB$2,0) -> 0 | CF9: =IF($E9*CF$2/$C$2-CI9>0,$E9*CF$2/$C$2-CI9,0) -> 6242.7137 | CG9: =IFERROR(CF9/CF$2,0) -> 5.4562689 | CH9: =IFERROR(CI9/CF$2,0) -> 0 | CJ9: =IF($E9*CJ$2/$C$2-CM9>0,$E9*CJ$2/$C$2-CM9,0) -> 6270.1151 | CK9: =IFERROR(CJ9/CJ$2,0) -> 5.4562689 | CL9: =IFERROR(CM9/CJ$2,0) -> 0 | CN9: =IF($E9*CN$2/$C$2-CQ9>0,$E9*CN$2/$C$2-CQ9,0) -> 6301.936 | CO9: =IFERROR(CN9/CN$2,0) -> 5.4562689 | CP9: =IFERROR(CQ9/CN$2,0) -> 0 | CR9: =IF($E9*CR$2/$C$2-CU9>0,$E9*CR$2/$C$2-CU9,0) -> 6346.8466 | CS9: =IFERROR(CR9/CR$2,0) -> 5.4562689 | CT9: =IFERROR(CU9/CR$2,0) -> 0 | CV9: =IF($E9*CV$2/$C$2-CY9>0,$E9*CV$2/$C$2-CY9,0) -> 6379.2295 | CW9: =IFERROR(CV9/CV$2,0) -> 5.4562689 | CX9: =IFERROR(CY9/CV$2,0) -> 0 | CZ9: =IF($E9*CZ$2/$C$2-DC9>0,$E9*CZ$2/$C$2-DC9,0) -> 6403.4008 | DA9: =IFERROR(CZ9/CZ$2,0) -> 5.4562689 | DB9: =IFERROR(DC9/CZ$2,0) -> 0 | DD9: =IF($E9*DD$2/$C$2-DG9>0,$E9*DD$2/$C$2-DG9,0) -> 6441.4746 | DE9: =IFERROR(DD9/DD$2,0) -> 5.4562689 | DF9: =IFERROR(DG9/DD$2,0) -> 0 | DH9: =IF($E9*DH$2/$C$2-DK9>0,$E9*DH$2/$C$2-DK9,0) -> 6458.0726 | DI9: =IFERROR(DH9/DH$2,0) -> 5.4562689 | DJ9: =IFERROR(DK9/DH$2,0) -> 0 | DL9: =IF($E9*DL$2/$C$2-DO9>0,$E9*DL$2/$C$2-DO9,0) -> 6519.7612 | DM9: =IFERROR(DL9/DL$2,0) -> 5.4562689 | DN9: =IFERROR(DO9/DL$2,0) -> 0 | DP9: =IF($E9*DP$2/$C$2-DS9>0,$E9*DP$2/$C$2-DS9,0) -> 6579.3764 | DQ9: =IFERROR(DP9/DP$2,0) -> 5.4562689 | DR9: =IFERROR(DS9/DP$2,0) -> 0 | DT9: =IF($E9*DT$2/$C$2-DW9>0,$E9*DT$2/$C$2-DW9,0) -> 6625.2145 | DU9: =IFERROR(DT9/DT$2,0) -> 5.4562689 | DV9: =IFERROR(DW9/DT$2,0) -> 0 | DX9: =IF($E9*DX$2/$C$2-EA9>0,$E9*DX$2/$C$2-EA9,0) -> 6639.3244 | DY9: =IFERROR(DX9/DX$2,0) -> 5.4562689 | DZ9: =IFERROR(EA9/DX$2,0) -> 0 | EB9: =IF($E9*EB$2/$C$2-EE9>0,$E9*EB$2/$C$2-EE9,0) -> 6653.4125 | EC9: =IFERROR(EB9/EB$2,0) -> 5.4562689 | ED9: =IFERROR(EE9/EB$2,0) -> 0 | EF9: =IF($E9*EF$2/$C$2-EI9>0,$E9*EF$2/$C$2-EI9,0) -> 6672.2803 | EG9: =IFERROR(EF9/EF$2,0) -> 5.4562689 | EH9: =IFERROR(EI9/EF$2,0) -> 0 | EJ9: =IF($E9*EJ$2/$C$2-EM9>0,$E9*EJ$2/$C$2-EM9,0) -> 6686.101 | EK9: =IFERROR(EJ9/EJ$2,0) -> 5.4562689 | EL9: =IFERROR(EM9/EJ$2,0) -> 0 | EN9: =IF($E9*EN$2/$C$2-EQ9>0,$E9*EN$2/$C$2-EQ9,0) -> 6728.1034 | EO9: =IFERROR(EN9/EN$2,0) -> 5.4562689 | EP9: =IFERROR(EQ9/EN$2,0) -> 0 | ER9: =IF($E9*ER$2/$C$2-EU9>0,$E9*ER$2/$C$2-EU9,0) -> 6751.107 | ES9: =IFERROR(ER9/ER$2,0) -> 5.4562689 | ET9: =IFERROR(EU9/ER$2,0) -> 0 | EV9: =IF($E9*EV$2/$C$2-EY9>0,$E9*EV$2/$C$2-EY9,0)*0.19 -> 1287.2811 | EW9: =IFERROR(EV9/EV$2,0) -> 1.0366911 | EX9: =IFERROR(EY9/EV$2,0) -> 0
A10: 01.01.04.01.008 | B10: ALMOXARIFE | C10: 34 | D10: =E10*C10 -> 329713.64 | E10: 9697.46 | F10: =K10*$C$1 -> 1.4496038e-10 | G10: =D10/$C$2 -> 315.3739 | H10: =E10/$C$2 -> 9.2757031 | I10: =SUMIFS($L10:$EQ10,$L$4:$EQ$4,$M$4) -> 315.3739 | J10: =SUMIFS($L10:$EQ10,$L$4:$EQ$4,$N$4) -> 0 | K10: =G10-I10-J10 -> 1.1368684e-13 | L10: =IF($E10*L$2/$C$2-O10>0,$E10*L$2/$C$2-O10,0) -> 9842.1795 | M10: =IFERROR(L10/L$2,0) -> 9.2757031 | N10: =IFERROR(O10/L$2,0) -> 0 | P10: =IF($E10*P$2/$C$2-S10>0,$E10*P$2/$C$2-S10,0) -> 9881.3044 | Q10: =IFERROR(P10/P$2,0) -> 9.2757031 | R10: =IFERROR(S10/P$2,0) -> 0 | T10: =IF($E10*T$2/$C$2-W10>0,$E10*T$2/$C$2-W10,0) -> 9964.8136 | U10: =IFERROR(T10/T$2,0) -> 9.2757031 | V10: =IFERROR(W10/T$2,0) -> 0 | X10: =IF($E10*X$2/$C$2-AA10>0,$E10*X$2/$C$2-AA10,0) -> 9970.4068 | Y10: =IFERROR(X10/X$2,0) -> 9.2757031 | Z10: =IFERROR(AA10/X$2,0) -> 0 | AB10: =IF($E10*AB$2/$C$2-AE10>0,$E10*AB$2/$C$2-AE10,0) -> 9994.5422 | AC10: =IFERROR(AB10/AB$2,0) -> 9.2757031 | AD10: =IFERROR(AE10/AB$2,0) -> 0 | AF10: =IF($E10*AF$2/$C$2-AI10>0,$E10*AF$2/$C$2-AI10,0) -> 10018.418 | AG10: =IFERROR(AF10/AF$2,0) -> 9.2757031 | AH10: =IFERROR(AI10/AF$2,0) -> 0 | AJ10: =IF($E10*AJ$2/$C$2-AM10>0,$E10*AJ$2/$C$2-AM10,0) -> 10038.639 | AK10: =IFERROR(AJ10/AJ$2,0) -> 9.2757031 | AL10: =IFERROR(AM10/AJ$2,0) -> 0 | AN10: =IF($E10*AN$2/$C$2-AQ10>0,$E10*AN$2/$C$2-AQ10,0) -> 10048.694 | AO10: =IFERROR(AN10/AN$2,0) -> 9.2757031 | AP10: =IFERROR(AQ10/AN$2,0) -> 0 | AR10: =IF($E10*AR$2/$C$2-AU10>0,$E10*AR$2/$C$2-AU10,0) -> 10074.805 | AS10: =IFERROR(AR10/AR$2,0) -> 9.2757031 | AT10: =IFERROR(AU10/AR$2,0) -> 0 | AV10: =IF($E10*AV$2/$C$2-AY10>0,$E10*AV$2/$C$2-AY10,0) -> 10098.115 | AW10: =IFERROR(AV10/AV$2,0) -> 9.2757031 | AX10: =IFERROR(AY10/AV$2,0) -> 0 | AZ10: =IF($E10*AZ$2/$C$2-BC10>0,$E10*AZ$2/$C$2-BC10,0) -> 10118.595 | BA10: =IFERROR(AZ10/AZ$2,0) -> 9.2757031 | BB10: =IFERROR(BC10/AZ$2,0) -> 0 | BD10: =IF($E10*BD$2/$C$2-BG10>0,$E10*BD$2/$C$2-BG10,0) -> 10143.009 | BE10: =IFERROR(BD10/BD$2,0) -> 9.2757031 | BF10: =IFERROR(BG10/BD$2,0) -> 0 | BH10: =IF($E10*BH$2/$C$2-BK10>0,$E10*BH$2/$C$2-BK10,0) -> 10184.638 | BI10: =IFERROR(BH10/BH$2,0) -> 9.2757031 | BJ10: =IFERROR(BK10/BH$2,0) -> 0 | BL10: =IF($E10*BL$2/$C$2-BO10>0,$E10*BL$2/$C$2-BO10,0) -> 10244.615 | BM10: =IFERROR(BL10/BL$2,0) -> 9.2757031 | BN10: =IFERROR(BO10/BL$2,0) -> 0 | BP10: =IF($E10*BP$2/$C$2-BS10>0,$E10*BP$2/$C$2-BS10,0) -> 10340.071 | BQ10: =IFERROR(BP10/BP$2,0) -> 9.2757031 | BR10: =IFERROR(BS10/BP$2,0) -> 0 | BT10: =IF($E10*BT$2/$C$2-BW10>0,$E10*BT$2/$C$2-BW10,0) -> 10411.531 | BU10: =IFERROR(BT10/BT$2,0) -> 9.2757031 | BV10: =IFERROR(BW10/BT$2,0) -> 0 | BX10: =IF($E10*BX$2/$C$2-CA10>0,$E10*BX$2/$C$2-CA10,0) -> 10478.196 | BY10: =IFERROR(BX10/BX$2,0) -> 9.2757031 | BZ10: =IFERROR(CA10/BX$2,0) -> 0 | CB10: =IF($E10*CB$2/$C$2-CE10>0,$E10*CB$2/$C$2-CE10,0) -> 10542.031 | CC10: =IFERROR(CB10/CB$2,0) -> 9.2757031 | CD10: =IFERROR(CE10/CB$2,0) -> 0 | CF10: =IF($E10*CF$2/$C$2-CI10>0,$E10*CF$2/$C$2-CI10,0) -> 10612.666 | CG10: =IFERROR(CF10/CF$2,0) -> 9.2757031 | CH10: =IFERROR(CI10/CF$2,0) -> 0 | CJ10: =IF($E10*CJ$2/$C$2-CM10>0,$E10*CJ$2/$C$2-CM10,0) -> 10659.248 | CK10: =IFERROR(CJ10/CJ$2,0) -> 9.2757031 | CL10: =IFERROR(CM10/CJ$2,0) -> 0 | CN10: =IF($E10*CN$2/$C$2-CQ10>0,$E10*CN$2/$C$2-CQ10,0) -> 10713.344 | CO10: =IFERROR(CN10/CN$2,0) -> 9.2757031 | CP10: =IFERROR(CQ10/CN$2,0) -> 0 | CR10: =IF($E10*CR$2/$C$2-CU10>0,$E10*CR$2/$C$2-CU10,0) -> 10789.693 | CS10: =IFERROR(CR10/CR$2,0) -> 9.2757031 | CT10: =IFERROR(CU10/CR$2,0) -> 0 | CV10: =IF($E10*CV$2/$C$2-CY10>0,$E10*CV$2/$C$2-CY10,0) -> 10844.744 | CW10: =IFERROR(CV10/CV$2,0) -> 9.2757031 | CX10: =IFERROR(CY10/CV$2,0) -> 0 | CZ10: =IF($E10*CZ$2/$C$2-DC10>0,$E10*CZ$2/$C$2-DC10,0) -> 10885.835 | DA10: =IFERROR(CZ10/CZ$2,0) -> 9.2757031 | DB10: =IFERROR(DC10/CZ$2,0) -> 0 | DD10: =IF($E10*DD$2/$C$2-DG10>0,$E10*DD$2/$C$2-DG10,0) -> 10950.561 | DE10: =IFERROR(DD10/DD$2,0) -> 9.2757031 | DF10: =IFERROR(DG10/DD$2,0) -> 0 | DH10: =IF($E10*DH$2/$C$2-DK10>0,$E10*DH$2/$C$2-DK10,0) -> 10978.778 | DI10: =IFERROR(DH10/DH$2,0) -> 9.2757031 | DJ10: =IFERROR(DK10/DH$2,0) -> 0 | DL10: =IF($E10*DL$2/$C$2-DO10>0,$E10*DL$2/$C$2-DO10,0) -> 11083.649 | DM10: =IFERROR(DL10/DL$2,0) -> 9.2757031 | DN10: =IFERROR(DO10/DL$2,0) -> 0 | DP10: =IF($E10*DP$2/$C$2-DS10>0,$E10*DP$2/$C$2-DS10,0) -> 11184.995 | DQ10: =IFERROR(DP10/DP$2,0) -> 9.2757031 | DR10: =IFERROR(DS10/DP$2,0) -> 0 | DT10: =IF($E10*DT$2/$C$2-DW10>0,$E10*DT$2/$C$2-DW10,0) -> 11262.92 | DU10: =IFERROR(DT10/DT$2,0) -> 9.2757031 | DV10: =IFERROR(DW10/DT$2,0) -> 0 | DX10: =IF($E10*DX$2/$C$2-EA10>0,$E10*DX$2/$C$2-EA10,0) -> 11286.907 | DY10: =IFERROR(DX10/DX$2,0) -> 9.2757031 | DZ10: =IFERROR(EA10/DX$2,0) -> 0 | EB10: =IF($E10*EB$2/$C$2-EE10>0,$E10*EB$2/$C$2-EE10,0) -> 11310.857 | EC10: =IFERROR(EB10/EB$2,0) -> 9.2757031 | ED10: =IFERROR(EE10/EB$2,0) -> 0 | EF10: =IF($E10*EF$2/$C$2-EI10>0,$E10*EF$2/$C$2-EI10,0) -> 11342.933 | EG10: =IFERROR(EF10/EF$2,0) -> 9.2757031 | EH10: =IFERROR(EI10/EF$2,0) -> 0 | EJ10: =IF($E10*EJ$2/$C$2-EM10>0,$E10*EJ$2/$C$2-EM10,0) -> 11366.428 | EK10: =IFERROR(EJ10/EJ$2,0) -> 9.2757031 | EL10: =IFERROR(EM10/EJ$2,0) -> 0 | EN10: =IF($E10*EN$2/$C$2-EQ10>0,$E10*EN$2/$C$2-EQ10,0) -> 11437.832 | EO10: =IFERROR(EN10/EN$2,0) -> 9.2757031 | EP10: =IFERROR(EQ10/EN$2,0) -> 0 | ER10: =IF($E10*ER$2/$C$2-EU10>0,$E10*ER$2/$C$2-EU10,0) -> 11476.939 | ES10: =IFERROR(ER10/ER$2,0) -> 9.2757031 | ET10: =IFERROR(EU10/ER$2,0) -> 0 | EV10: =IF($E10*EV$2/$C$2-EY10>0,$E10*EV$2/$C$2-EY10,0)*0.19 -> 2188.3887 | EW10: =IFERROR(EV10/EV$2,0) -> 1.7623836 | EX10: =IFERROR(EY10/EV$2,0) -> 0
A11: 01.01.04.01.010 | B11: ENGENHEIRO DE SEGURANÇA | C11: 34 | D11: =E11*C11 -> 128184.08 | E11: 3770.12 | F11: =K11*$C$1 -> -7.2480191e-11 | G11: =D11/$C$2 -> 122.60916 | H11: =E11/$C$2 -> 3.6061519 | I11: =SUMIFS($L11:$EQ11,$L$4:$EQ$4,$M$4) -> 122.60916 | J11: =SUMIFS($L11:$EQ11,$L$4:$EQ$4,$N$4) -> 0 | K11: =G11-I11-J11 -> -5.6843419e-14 | L11: =IF($E11*L$2/$C$2-O11>0,$E11*L$2/$C$2-O11,0) -> 3826.3832 | M11: =IFERROR(L11/L$2,0) -> 3.6061519 | N11: =IFERROR(O11/L$2,0) -> 0 | P11: =IF($E11*P$2/$C$2-S11>0,$E11*P$2/$C$2-S11,0) -> 3841.5939 | Q11: =IFERROR(P11/P$2,0) -> 3.6061519 | R11: =IFERROR(S11/P$2,0) -> 0 | T11: =IF($E11*T$2/$C$2-W11>0,$E11*T$2/$C$2-W11,0) -> 3874.0601 | U11: =IFERROR(T11/T$2,0) -> 3.6061519 | V11: =IFERROR(W11/T$2,0) -> 0 | X11: =IF($E11*X$2/$C$2-AA11>0,$E11*X$2/$C$2-AA11,0) -> 3876.2346 | Y11: =IFERROR(X11/X$2,0) -> 3.6061519 | Z11: =IFERROR(AA11/X$2,0) -> 0 | AB11: =IF($E11*AB$2/$C$2-AE11>0,$E11*AB$2/$C$2-AE11,0) -> 3885.6178 | AC11: =IFERROR(AB11/AB$2,0) -> 3.6061519 | AD11: =IFERROR(AE11/AB$2,0) -> 0 | AF11: =IF($E11*AF$2/$C$2-AI11>0,$E11*AF$2/$C$2-AI11,0) -> 3894.9001 | AG11: =IFERROR(AF11/AF$2,0) -> 3.6061519 | AH11: =IFERROR(AI11/AF$2,0) -> 0 | AJ11: =IF($E11*AJ$2/$C$2-AM11>0,$E11*AJ$2/$C$2-AM11,0) -> 3902.7615 | AK11: =IFERROR(AJ11/AJ$2,0) -> 3.6061519 | AL11: =IFERROR(AM11/AJ$2,0) -> 0 | AN11: =IF($E11*AN$2/$C$2-AQ11>0,$E11*AN$2/$C$2-AQ11,0) -> 3906.6705 | AO11: =IFERROR(AN11/AN$2,0) -> 3.6061519 | AP11: =IFERROR(AQ11/AN$2,0) -> 0 | AR11: =IF($E11*AR$2/$C$2-AU11>0,$E11*AR$2/$C$2-AU11,0) -> 3916.8219 | AS11: =IFERROR(AR11/AR$2,0) -> 3.6061519 | AT11: =IFERROR(AU11/AR$2,0) -> 0 | AV11: =IF($E11*AV$2/$C$2-AY11>0,$E11*AV$2/$C$2-AY11,0) -> 3925.8841 | AW11: =IFERROR(AV11/AV$2,0) -> 3.6061519 | AX11: =IFERROR(AY11/AV$2,0) -> 0 | AZ11: =IF($E11*AZ$2/$C$2-BC11>0,$E11*AZ$2/$C$2-BC11,0) -> 3933.8465 | BA11: =IFERROR(AZ11/AZ$2,0) -> 3.6061519 | BB11: =IFERROR(BC11/AZ$2,0) -> 0 | BD11: =IF($E11*BD$2/$C$2-BG11>0,$E11*BD$2/$C$2-BG11,0) -> 3943.3379 | BE11: =IFERROR(BD11/BD$2,0) -> 3.6061519 | BF11: =IFERROR(BG11/BD$2,0) -> 0 | BH11: =IF($E11*BH$2/$C$2-BK11>0,$E11*BH$2/$C$2-BK11,0) -> 3959.5223 | BI11: =IFERROR(BH11/BH$2,0) -> 3.6061519 | BJ11: =IFERROR(BK11/BH$2,0) -> 0 | BL11: =IF($E11*BL$2/$C$2-BO11>0,$E11*BL$2/$C$2-BO11,0) -> 3982.8397 | BM11: =IFERROR(BL11/BL$2,0) -> 3.6061519 | BN11: =IFERROR(BO11/BL$2,0) -> 0 | BP11: =IF($E11*BP$2/$C$2-BS11>0,$E11*BP$2/$C$2-BS11,0) -> 4019.9506 | BQ11: =IFERROR(BP11/BP$2,0) -> 3.6061519 | BR11: =IFERROR(BS11/BP$2,0) -> 0 | BT11: =IF($E11*BT$2/$C$2-BW11>0,$E11*BT$2/$C$2-BW11,0) -> 4047.7324 | BU11: =IFERROR(BT11/BT$2,0) -> 3.6061519 | BV11: =IFERROR(BW11/BT$2,0) -> 0 | BX11: =IF($E11*BX$2/$C$2-CA11>0,$E11*BX$2/$C$2-CA11,0) -> 4073.6498 | BY11: =IFERROR(BX11/BX$2,0) -> 3.6061519 | BZ11: =IFERROR(CA11/BX$2,0) -> 0 | CB11: =IF($E11*CB$2/$C$2-CE11>0,$E11*CB$2/$C$2-CE11,0) -> 4098.4673 | CC11: =IFERROR(CB11/CB$2,0) -> 3.6061519 | CD11: =IFERROR(CE11/CB$2,0) -> 0 | CF11: =IF($E11*CF$2/$C$2-CI11>0,$E11*CF$2/$C$2-CI11,0) -> 4125.9282 | CG11: =IFERROR(CF11/CF$2,0) -> 3.6061519 | CH11: =IFERROR(CI11/CF$2,0) -> 0 | CJ11: =IF($E11*CJ$2/$C$2-CM11>0,$E11*CJ$2/$C$2-CM11,0) -> 4144.0383 | CK11: =IFERROR(CJ11/CJ$2,0) -> 3.6061519 | CL11: =IFERROR(CM11/CJ$2,0) -> 0 | CN11: =IF($E11*CN$2/$C$2-CQ11>0,$E11*CN$2/$C$2-CQ11,0) -> 4165.0694 | CO11: =IFERROR(CN11/CN$2,0) -> 3.6061519 | CP11: =IFERROR(CQ11/CN$2,0) -> 0 | CR11: =IF($E11*CR$2/$C$2-CU11>0,$E11*CR$2/$C$2-CU11,0) -> 4194.7516 | CS11: =IFERROR(CR11/CR$2,0) -> 3.6061519 | CT11: =IFERROR(CU11/CR$2,0) -> 0 | CV11: =IF($E11*CV$2/$C$2-CY11>0,$E11*CV$2/$C$2-CY11,0) -> 4216.1541 | CW11: =IFERROR(CV11/CV$2,0) -> 3.6061519 | CX11: =IFERROR(CY11/CV$2,0) -> 0 | CZ11: =IF($E11*CZ$2/$C$2-DC11>0,$E11*CZ$2/$C$2-DC11,0) -> 4232.1294 | DA11: =IFERROR(CZ11/CZ$2,0) -> 3.6061519 | DB11: =IFERROR(DC11/CZ$2,0) -> 0 | DD11: =IF($E11*DD$2/$C$2-DG11>0,$E11*DD$2/$C$2-DG11,0) -> 4257.2931 | DE11: =IFERROR(DD11/DD$2,0) -> 3.6061519 | DF11: =IFERROR(DG11/DD$2,0) -> 0 | DH11: =IF($E11*DH$2/$C$2-DK11>0,$E11*DH$2/$C$2-DK11,0) -> 4268.263 | DI11: =IFERROR(DH11/DH$2,0) -> 3.6061519 | DJ11: =IFERROR(DK11/DH$2,0) -> 0 | DL11: =IF($E11*DL$2/$C$2-DO11>0,$E11*DL$2/$C$2-DO11,0) -> 4309.0342 | DM11: =IFERROR(DL11/DL$2,0) -> 3.6061519 | DN11: =IFERROR(DO11/DL$2,0) -> 0 | DP11: =IF($E11*DP$2/$C$2-DS11>0,$E11*DP$2/$C$2-DS11,0) -> 4348.435 | DQ11: =IFERROR(DP11/DP$2,0) -> 3.6061519 | DR11: =IFERROR(DS11/DP$2,0) -> 0 | DT11: =IF($E11*DT$2/$C$2-DW11>0,$E11*DT$2/$C$2-DW11,0) -> 4378.7303 | DU11: =IFERROR(DT11/DT$2,0) -> 3.6061519 | DV11: =IFERROR(DW11/DT$2,0) -> 0 | DX11: =IF($E11*DX$2/$C$2-EA11>0,$E11*DX$2/$C$2-EA11,0) -> 4388.0558 | DY11: =IFERROR(DX11/DX$2,0) -> 3.6061519 | DZ11: =IFERROR(EA11/DX$2,0) -> 0 | EB11: =IF($E11*EB$2/$C$2-EE11>0,$E11*EB$2/$C$2-EE11,0) -> 4397.3668 | EC11: =IFERROR(EB11/EB$2,0) -> 3.6061519 | ED11: =IFERROR(EE11/EB$2,0) -> 0 | EF11: =IF($E11*EF$2/$C$2-EI11>0,$E11*EF$2/$C$2-EI11,0) -> 4409.8369 | EG11: =IFERROR(EF11/EF$2,0) -> 3.6061519 | EH11: =IFERROR(EI11/EF$2,0) -> 0 | EJ11: =IF($E11*EJ$2/$C$2-EM11>0,$E11*EJ$2/$C$2-EM11,0) -> 4418.9713 | EK11: =IFERROR(EJ11/EJ$2,0) -> 3.6061519 | EL11: =IFERROR(EM11/EJ$2,0) -> 0 | EN11: =IF($E11*EN$2/$C$2-EQ11>0,$E11*EN$2/$C$2-EQ11,0) -> 4446.7315 | EO11: =IFERROR(EN11/EN$2,0) -> 3.6061519 | EP11: =IFERROR(EQ11/EN$2,0) -> 0 | ER11: =IF($E11*ER$2/$C$2-EU11>0,$E11*ER$2/$C$2-EU11,0) -> 4461.935 | ES11: =IFERROR(ER11/ER$2,0) -> 3.6061519 | ET11: =IFERROR(EU11/ER$2,0) -> 0 | EV11: =IF($E11*EV$2/$C$2-EY11>0,$E11*EV$2/$C$2-EY11,0)*0.19 -> 850.78856 | EW11: =IFERROR(EV11/EV$2,0) -> 0.68516886 | EX11: =IFERROR(EY11/EV$2,0) -> 0
A12: 01.01.04.01.011 | B12: TECNICO SEGURANCA | C12: 34 | D12: =E12*C12 -> 142181.54 | E12: 4181.81 | F12: =K12*$C$1 -> 3.6240095e-11 | G12: =D12/$C$2 -> 135.99785 | H12: =E12/$C$2 -> 3.9999369 | I12: =SUMIFS($L12:$EQ12,$L$4:$EQ$4,$M$4) -> 135.99785 | J12: =SUMIFS($L12:$EQ12,$L$4:$EQ$4,$N$4) -> 0 | K12: =G12-I12-J12 -> 2.8421709e-14 | L12: =IF($E12*L$2/$C$2-O12>0,$E12*L$2/$C$2-O12,0) -> 4244.217 | M12: =IFERROR(L12/L$2,0) -> 3.9999369 | N12: =IFERROR(O12/L$2,0) -> 0 | P12: =IF($E12*P$2/$C$2-S12>0,$E12*P$2/$C$2-S12,0) -> 4261.0887 | Q12: =IFERROR(P12/P$2,0) -> 3.9999369 | R12: =IFERROR(S12/P$2,0) -> 0 | T12: =IF($E12*T$2/$C$2-W12>0,$E12*T$2/$C$2-W12,0) -> 4297.1002 | U12: =IFERROR(T12/T$2,0) -> 3.9999369 | V12: =IFERROR(W12/T$2,0) -> 0 | X12: =IF($E12*X$2/$C$2-AA12>0,$E12*X$2/$C$2-AA12,0) -> 4299.5121 | Y12: =IFERROR(X12/X$2,0) -> 3.9999369 | Z12: =IFERROR(AA12/X$2,0) -> 0 | AB12: =IF($E12*AB$2/$C$2-AE12>0,$E12*AB$2/$C$2-AE12,0) -> 4309.92 | AC12: =IFERROR(AB12/AB$2,0) -> 3.9999369 | AD12: =IFERROR(AE12/AB$2,0) -> 0 | AF12: =IF($E12*AF$2/$C$2-AI12>0,$E12*AF$2/$C$2-AI12,0) -> 4320.2158 | AG12: =IFERROR(AF12/AF$2,0) -> 3.9999369 | AH12: =IFERROR(AI12/AF$2,0) -> 0 | AJ12: =IF($E12*AJ$2/$C$2-AM12>0,$E12*AJ$2/$C$2-AM12,0) -> 4328.9357 | AK12: =IFERROR(AJ12/AJ$2,0) -> 3.9999369 | AL12: =IFERROR(AM12/AJ$2,0) -> 0 | AN12: =IF($E12*AN$2/$C$2-AQ12>0,$E12*AN$2/$C$2-AQ12,0) -> 4333.2716 | AO12: =IFERROR(AN12/AN$2,0) -> 3.9999369 | AP12: =IFERROR(AQ12/AN$2,0) -> 0 | AR12: =IF($E12*AR$2/$C$2-AU12>0,$E12*AR$2/$C$2-AU12,0) -> 4344.5314 | AS12: =IFERROR(AR12/AR$2,0) -> 3.9999369 | AT12: =IFERROR(AU12/AR$2,0) -> 0 | AV12: =IF($E12*AV$2/$C$2-AY12>0,$E12*AV$2/$C$2-AY12,0) -> 4354.5833 | AW12: =IFERROR(AV12/AV$2,0) -> 3.9999369 | AX12: =IFERROR(AY12/AV$2,0) -> 0 | AZ12: =IF($E12*AZ$2/$C$2-BC12>0,$E12*AZ$2/$C$2-BC12,0) -> 4363.4151 | BA12: =IFERROR(AZ12/AZ$2,0) -> 3.9999369 | BB12: =IFERROR(BC12/AZ$2,0) -> 0 | BD12: =IF($E12*BD$2/$C$2-BG12>0,$E12*BD$2/$C$2-BG12,0) -> 4373.943 | BE12: =IFERROR(BD12/BD$2,0) -> 3.9999369 | BF12: =IFERROR(BG12/BD$2,0) -> 0 | BH12: =IF($E12*BH$2/$C$2-BK12>0,$E12*BH$2/$C$2-BK12,0) -> 4391.8947 | BI12: =IFERROR(BH12/BH$2,0) -> 3.9999369 | BJ12: =IFERROR(BK12/BH$2,0) -> 0 | BL12: =IF($E12*BL$2/$C$2-BO12>0,$E12*BL$2/$C$2-BO12,0) -> 4417.7583 | BM12: =IFERROR(BL12/BL$2,0) -> 3.9999369 | BN12: =IFERROR(BO12/BL$2,0) -> 0 | BP12: =IF($E12*BP$2/$C$2-BS12>0,$E12*BP$2/$C$2-BS12,0) -> 4458.9216 | BQ12: =IFERROR(BP12/BP$2,0) -> 3.9999369 | BR12: =IFERROR(BS12/BP$2,0) -> 0 | BT12: =IF($E12*BT$2/$C$2-BW12>0,$E12*BT$2/$C$2-BW12,0) -> 4489.7371 | BU12: =IFERROR(BT12/BT$2,0) -> 3.9999369 | BV12: =IFERROR(BW12/BT$2,0) -> 0 | BX12: =IF($E12*BX$2/$C$2-CA12>0,$E12*BX$2/$C$2-CA12,0) -> 4518.4847 | BY12: =IFERROR(BX12/BX$2,0) -> 3.9999369 | BZ12: =IFERROR(CA12/BX$2,0) -> 0 | CB12: =IF($E12*CB$2/$C$2-CE12>0,$E12*CB$2/$C$2-CE12,0) -> 4546.0123 | CC12: =IFERROR(CB12/CB$2,0) -> 3.9999369 | CD12: =IFERROR(CE12/CB$2,0) -> 0 | CF12: =IF($E12*CF$2/$C$2-CI12>0,$E12*CF$2/$C$2-CI12,0) -> 4576.4718 | CG12: =IFERROR(CF12/CF$2,0) -> 3.9999369 | CH12: =IFERROR(CI12/CF$2,0) -> 0 | CJ12: =IF($E12*CJ$2/$C$2-CM12>0,$E12*CJ$2/$C$2-CM12,0) -> 4596.5595 | CK12: =IFERROR(CJ12/CJ$2,0) -> 3.9999369 | CL12: =IFERROR(CM12/CJ$2,0) -> 0 | CN12: =IF($E12*CN$2/$C$2-CQ12>0,$E12*CN$2/$C$2-CQ12,0) -> 4619.8871 | CO12: =IFERROR(CN12/CN$2,0) -> 3.9999369 | CP12: =IFERROR(CQ12/CN$2,0) -> 0 | CR12: =IF($E12*CR$2/$C$2-CU12>0,$E12*CR$2/$C$2-CU12,0) -> 4652.8106 | CS12: =IFERROR(CR12/CR$2,0) -> 3.9999369 | CT12: =IFERROR(CU12/CR$2,0) -> 0 | CV12: =IF($E12*CV$2/$C$2-CY12>0,$E12*CV$2/$C$2-CY12,0) -> 4676.5502 | CW12: =IFERROR(CV12/CV$2,0) -> 3.9999369 | CX12: =IFERROR(CY12/CV$2,0) -> 0 | CZ12: =IF($E12*CZ$2/$C$2-DC12>0,$E12*CZ$2/$C$2-DC12,0) -> 4694.2699 | DA12: =IFERROR(CZ12/CZ$2,0) -> 3.9999369 | DB12: =IFERROR(DC12/CZ$2,0) -> 0 | DD12: =IF($E12*DD$2/$C$2-DG12>0,$E12*DD$2/$C$2-DG12,0) -> 4722.1815 | DE12: =IFERROR(DD12/DD$2,0) -> 3.9999369 | DF12: =IFERROR(DG12/DD$2,0) -> 0 | DH12: =IF($E12*DH$2/$C$2-DK12>0,$E12*DH$2/$C$2-DK12,0) -> 4734.3493 | DI12: =IFERROR(DH12/DH$2,0) -> 3.9999369 | DJ12: =IFERROR(DK12/DH$2,0) -> 0 | DL12: =IF($E12*DL$2/$C$2-DO12>0,$E12*DL$2/$C$2-DO12,0) -> 4779.5726 | DM12: =IFERROR(DL12/DL$2,0) -> 3.9999369 | DN12: =IFERROR(DO12/DL$2,0) -> 0 | DP12: =IF($E12*DP$2/$C$2-DS12>0,$E12*DP$2/$C$2-DS12,0) -> 4823.2759 | DQ12: =IFERROR(DP12/DP$2,0) -> 3.9999369 | DR12: =IFERROR(DS12/DP$2,0) -> 0 | DT12: =IF($E12*DT$2/$C$2-DW12>0,$E12*DT$2/$C$2-DW12,0) -> 4856.8793 | DU12: =IFERROR(DT12/DT$2,0) -> 3.9999369 | DV12: =IFERROR(DW12/DT$2,0) -> 0 | DX12: =IF($E12*DX$2/$C$2-EA12>0,$E12*DX$2/$C$2-EA12,0) -> 4867.2232 | DY12: =IFERROR(DX12/DX$2,0) -> 3.9999369 | DZ12: =IFERROR(EA12/DX$2,0) -> 0 | EB12: =IF($E12*EB$2/$C$2-EE12>0,$E12*EB$2/$C$2-EE12,0) -> 4877.551 | EC12: =IFERROR(EB12/EB$2,0) -> 3.9999369 | ED12: =IFERROR(EE12/EB$2,0) -> 0 | EF12: =IF($E12*EF$2/$C$2-EI12>0,$E12*EF$2/$C$2-EI12,0) -> 4891.3828 | EG12: =IFERROR(EF12/EF$2,0) -> 3.9999369 | EH12: =IFERROR(EI12/EF$2,0) -> 0 | EJ12: =IF($E12*EJ$2/$C$2-EM12>0,$E12*EJ$2/$C$2-EM12,0) -> 4901.5146 | EK12: =IFERROR(EJ12/EJ$2,0) -> 3.9999369 | EL12: =IFERROR(EM12/EJ$2,0) -> 0 | EN12: =IF($E12*EN$2/$C$2-EQ12>0,$E12*EN$2/$C$2-EQ12,0) -> 4932.3062 | EO12: =IFERROR(EN12/EN$2,0) -> 3.9999369 | EP12: =IFERROR(EQ12/EN$2,0) -> 0 | ER12: =IF($E12*ER$2/$C$2-EU12>0,$E12*ER$2/$C$2-EU12,0) -> 4949.1699 | ES12: =IFERROR(ER12/ER$2,0) -> 3.9999369 | ET12: =IFERROR(EU12/ER$2,0) -> 0 | EV12: =IF($E12*EV$2/$C$2-EY12>0,$E12*EV$2/$C$2-EY12,0)*0.19 -> 943.69307 | EW12: =IFERROR(EV12/EV$2,0) -> 0.75998801 | EX12: =IFERROR(EY12/EV$2,0) -> 0
D13: =SUM(D5:D12) -> 2462606.4 | E13: =SUM(E5:E12) -> 72429.6 | F13: =SUM(F5:F12) -> -3.6240095e-10 | G13: =SUM(G5:G12) -> 2355.504 | H13: =SUM(H5:H12) -> 69.279529 | I13: =SUM(I5:I12) -> 2355.504 | J13: =SUM(J5:J12) -> 0 | K13: =SUM(K5:K12) -> -2.8421709e-13 | ... EY13: =SUM(EY5:EY12) -> 0
EN29: =EN14*3 -> 0

Sheet Qoya
A1: INCC DI - Vigente | B1: ='IND. FIN.'!V1 -> 46204 | C1: =VLOOKUP(B1,'IND. FIN.'!$C$4:$D$1000,2,0) -> 1280.641 | D1: Contrato Piemonte | L1: Contratos Terceiro
A2: INCC - Base | B2: 45170 | C2: ='IND. FIN.'!D35 -> 1078.412 | D2: R$ | G2: INCC | L2: Thal | O2: Thal | Q2: INCC - Base | R2: ='IND. FIN.'!D48 -> 1141.398 | S2: =IF(S3>$B$1,0,VLOOKUP(S$3,'IND. FIN.'!$C$4:$D$1000,2,0)) -> 1101.389 | W2: =IF(W3>$B$1,0,VLOOKUP(W$3,'IND. FIN.'!$C$4:$D$1000,2,0)) -> 1110.887 | AA2: =IF(AA3>$B$1,0,VLOOKUP(AA$3,'IND. FIN.'!$C$4:$D$1000,2,0)) -> 1118.827 | AE2: =IF(AE3>$B$1,0,VLOOKUP(AE$3,'IND. FIN.'!$C$4:$D$1000,2,0)) -> 1126.916 | AI2: =IF(AI3>$B$1,0,VLOOKUP(AI$3,'IND. FIN.'!$C$4:$D$1000,2,0)) -> 1134.775 | AM2: =IF(AM3>$B$1,0,VLOOKUP(AM$3,'IND. FIN.'!$C$4:$D$1000,2,0)) -> 1141.398 | AQ2: =IF(AQ3>$B$1,0,VLOOKUP(AQ$3,'IND. FIN.'!$C$4:$D$1000,2,0)) -> 1149.17 | AU2: =IF(AU3>$B$1,0,VLOOKUP(AU$3,'IND. FIN.'!$C$4:$D$1000,2,0)) -> 1153.725 | AY2: =IF(AY3>$B$1,0,VLOOKUP(AY$3,'IND. FIN.'!$C$4:$D$1000,2,0)) -> 1159.536 | BC2: =IF(BC3>$B$1,0,VLOOKUP(BC$3,'IND. FIN.'!$C$4:$D$1000,2,0)) -> 1169.116 | BG2: =IF(BG3>$B$1,0,VLOOKUP(BG$3,'IND. FIN.'!$C$4:$D$1000,2,0)) -> 1173.775 | BK2: =IF(BK3>$B$1,0,VLOOKUP(BK$3,'IND. FIN.'!$C$4:$D$1000,2,0)) -> 1178.386 | BO2: =IF(BO3>$B$1,0,VLOOKUP(BO$3,'IND. FIN.'!$C$4:$D$1000,2,0)) -> 1184.462 | BS2: =IF(BS3>$B$1,0,VLOOKUP(BS$3,'IND. FIN.'!$C$4:$D$1000,2,0)) -> 1191.327 | BW2: =IF(BW3>$B$1,0,VLOOKUP(BW$3,'IND. FIN.'!$C$4:$D$1000,2,0)) -> 1199.509 | CA2: =IF(CA3>$B$1,0,VLOOKUP(CA$3,'IND. FIN.'!$C$4:$D$1000,2,0)) -> 1210.471 | CE2: =IF(CE3>$B$1,0,VLOOKUP(CE$3,'IND. FIN.'!$C$4:$D$1000,2,0)) -> 1216.706 | CI2: =IF(CI3>$B$1,0,VLOOKUP(CI$3,'IND. FIN.'!$C$4:$D$1000,2,0)) -> 1218.747 | CM2: =IF(CM3>$B$1,0,VLOOKUP(CM$3,'IND. FIN.'!$C$4:$D$1000,2,0)) -> 1222.356 | CQ2: =IF(CQ3>$B$1,0,VLOOKUP(CQ$3,'IND. FIN.'!$C$4:$D$1000,2,0)) -> 1225.633 | CU2: =IF(CU3>$B$1,0,VLOOKUP(CU$3,'IND. FIN.'!$C$4:$D$1000,2,0)) -> 1228.161 | CY2: =IF(CY3>$B$1,0,VLOOKUP(CY$3,'IND. FIN.'!$C$4:$D$1000,2,0)) -> 1237.036 | DC2: =IF(DC3>$B$1,0,VLOOKUP(DC$3,'IND. FIN.'!$C$4:$D$1000,2,0)) -> 1240.481 | DG2: =IF(DG3>$B$1,0,VLOOKUP(DG$3,'IND. FIN.'!$C$4:$D$1000,2,0)) -> 1247.181 | DK2: =IF(DK3>$B$1,0,VLOOKUP(DK$3,'IND. FIN.'!$C$4:$D$1000,2,0)) -> 1259.652 | DO2: =IF(DO3>$B$1,0,VLOOKUP(DO$3,'IND. FIN.'!$C$4:$D$1000,2,0)) -> 1270.695 | DS2: =IF(DS3>$B$1,0,VLOOKUP(DS$3,'IND. FIN.'!$C$4:$D$1000,2,0)) -> 1280.641 | DW2: =IF(DW3>$B$1,0,VLOOKUP(DW$3,'IND. FIN.'!$C$4:$D$1000,2,0)) -> 0 | EA2: =IF(EA3>$B$1,0,VLOOKUP(EA$3,'IND. FIN.'!$C$4:$D$1000,2,0)) -> 0 | EE2: =IF(EE3>$B$1,0,VLOOKUP(EE$3,'IND. FIN.'!$C$4:$D$1000,2,0)) -> 0 | EI2: =IF(EI3>$B$1,0,VLOOKUP(EI$3,'IND. FIN.'!$C$4:$D$1000,2,0)) -> 0 | EM2: =IF(EM3>$B$1,0,VLOOKUP(EM$3,'IND. FIN.'!$C$4:$D$1000,2,0)) -> 0 | EQ2: =IF(EQ3>$B$1,0,VLOOKUP(EQ$3,'IND. FIN.'!$C$4:$D$1000,2,0)) -> 0 | EU2: =IF(EU3>$B$1,0,VLOOKUP(EU$3,'IND. FIN.'!$C$4:$D$1000,2,0)) -> 0 | EY2: =IF(EY3>$B$1,0,VLOOKUP(EY$3,'IND. FIN.'!$C$4:$D$1000,2,0)) -> 0 | FC2: =IF(FC3>$B$1,0,VLOOKUP(FC$3,'IND. FIN.'!$C$4:$D$1000,2,0)) -> 0
A3: Orçamento base | D3: Valor total | E3: Valor unitário | F3: Saldo | G3: Valor total | H3: Valor unitário | I3: Total medido Piemonte | J3: Total medido Terceiros | K3: Saldo | L3: Prazo | M3: Valor total | N3: Valor unitário | O3: Prazo | P3: Valor total | Q3: Valor unitário | R3: Saldo | S3: 45413 | W3: =EDATE(S3,1) -> 45444 | AA3: =EDATE(W3,1) -> 45474 | AE3: =EDATE(AA3,1) -> 45505 | AI3: =EDATE(AE3,1) -> 45536 | AM3: =EDATE(AI3,1) -> 45566 | AQ3: =EDATE(AM3,1) -> 45597 | AU3: =EDATE(AQ3,1) -> 45627 | AY3: =EDATE(AU3,1) -> 45658 | BC3: =EDATE(AY3,1) -> 45689 | BG3: =EDATE(BC3,1) -> 45717 | BK3: =EDATE(BG3,1) -> 45748 | BO3: =EDATE(BK3,1) -> 45778 | BS3: =EDATE(BO3,1) -> 45809 | BW3: =EDATE(BS3,1) -> 45839 | CA3: =EDATE(BW3,1) -> 45870 | CE3: =EDATE(CA3,1) -> 45901 | CI3: =EDATE(CE3,1) -> 45931 | CM3: =EDATE(CI3,1) -> 45962 | CQ3: =EDATE(CM3,1) -> 45992 | CU3: =EDATE(CQ3,1) -> 46023 | CY3: =EDATE(CU3,1) -> 46054 | DC3: =EDATE(CY3,1) -> 46082 | DG3: =EDATE(DC3,1) -> 46113 | DK3: =EDATE(DG3,1) -> 46143 | DO3: =EDATE(DK3,1) -> 46174 | DS3: =EDATE(DO3,1) -> 46204 | DW3: =EDATE(DS3,1) -> 46235 | EA3: =EDATE(DW3,1) -> 46266 | EE3: =EDATE(EA3,1) -> 46296 | EI3: =EDATE(EE3,1) -> 46327 | EM3: =EDATE(EI3,1) -> 46357 | EQ3: =EDATE(EM3,1) -> 46388 | EU3: =EDATE(EQ3,1) -> 46419 | EY3: =EDATE(EU3,1) -> 46447 | FC3: =EDATE(EY3,1) -> 46478
A4: 01.01.04.01 | B4: PESSOAL | C4: Prazo | S4: Medido Piemonte | T4: Medido Piemonte INCC | U4: Medido Terceiros INCC | V4: Medido Terceiros | W4: Medido Piemonte | X4: Medido Piemonte INCC | Y4: Medido Terceiros INCC | Z4: Medido Terceiros | AA4: Medido Piemonte | AB4: Medido Piemonte INCC | AC4: Medido Terceiros INCC | AD4: Medido Terceiros | AE4: Medido Piemonte | AF4: Medido Piemonte INCC | AG4: Medido Terceiros INCC | AH4: Medido Terceiros | AI4: Medido Piemonte | AJ4: Medido Piemonte INCC | AK4: Medido Terceiros INCC | AL4: Medido Terceiros | AM4: Medido Piemonte | AN4: Medido Piemonte INCC | AO4: Medido Terceiros INCC | AP4: Medido Terceiros | AQ4: Medido Piemonte | AR4: Medido Piemonte INCC | AS4: Medido Terceiros INCC | AT4: Medido Terceiros | AU4: Medido Piemonte | AV4: Medido Piemonte INCC | AW4: Medido Terceiros INCC | AX4: Medido Terceiros | AY4: Medido Piemonte | AZ4: Medido Piemonte INCC | BA4: Medido Terceiros INCC | BB4: Medido Terceiros | BC4: Medido Piemonte | BD4: Medido Piemonte INCC | BE4: Medido Terceiros INCC | BF4: Medido Terceiros | BG4: Medido Piemonte | BH4: Medido Piemonte INCC | BI4: Medido Terceiros INCC | BJ4: Medido Terceiros | BK4: Medido Piemonte | BL4: Medido Piemonte INCC | BM4: Medido Terceiros INCC | BN4: Medido Terceiros | BO4: Medido Piemonte | BP4: Medido Piemonte INCC | BQ4: Medido Terceiros INCC | BR4: Medido Terceiros | BS4: Medido Piemonte | BT4: Medido Piemonte INCC | BU4: Medido Terceiros INCC | BV4: Medido Terceiros | BW4: Medido Piemonte | BX4: Medido Piemonte INCC | BY4: Medido Terceiros INCC | BZ4: Medido Terceiros | CA4: Medido Piemonte | CB4: Medido Piemonte INCC | CC4: Medido Terceiros INCC | CD4: Medido Terceiros | CE4: Medido Piemonte | CF4: Medido Piemonte INCC | CG4: Medido Terceiros INCC | CH4: Medido Terceiros | CI4: Medido Piemonte | CJ4: Medido Piemonte INCC | CK4: Medido Terceiros INCC | CL4: Medido Terceiros | CM4: Medido Piemonte | CN4: Medido Piemonte INCC | CO4: Medido Terceiros INCC | CP4: Medido Terceiros | CQ4: Medido Piemonte | CR4: Medido Piemonte INCC | CS4: Medido Terceiros INCC | CT4: Medido Terceiros | CU4: Medido Piemonte | CV4: Medido Piemonte INCC | CW4: Medido Terceiros INCC | CX4: Medido Terceiros | CY4: Medido Piemonte | CZ4: Medido Piemonte INCC | DA4: Medido Terceiros INCC | DB4: Medido Terceiros | DC4: Medido Piemonte | DD4: Medido Piemonte INCC | DE4: Medido Terceiros INCC | DF4: Medido Terceiros | DG4: Medido Piemonte | DH4: Medido Piemonte INCC | DI4: Medido Terceiros INCC | DJ4: Medido Terceiros | DK4: Medido Piemonte | DL4: Medido Piemonte INCC | DM4: Medido Terceiros INCC | DN4: Medido Terceiros | DO4: Medido Piemonte | DP4: Medido Piemonte INCC | DQ4: Medido Terceiros INCC | DR4: Medido Terceiros | DS4: Medido Piemonte | DT4: Medido Piemonte INCC | DU4: Medido Terceiros INCC | DV4: Medido Terceiros | DW4: Medido Piemonte | DX4: Medido Piemonte INCC | DY4: Medido Terceiros INCC | DZ4: Medido Terceiros | EA4: Medido Piemonte | EB4: Medido Piemonte INCC | EC4: Medido Terceiros INCC | ED4: Medido Terceiros | EE4: Medido Piemonte | EF4: Medido Piemonte INCC | EG4: Medido Terceiros INCC | EH4: Medido Terceiros | EI4: Medido Piemonte | EJ4: Medido Piemonte INCC | EK4: Medido Terceiros INCC | EL4: Medido Terceiros | EM4: Medido Piemonte | EN4: Medido Piemonte INCC | EO4: Medido Terceiros INCC | EP4: Medido Terceiros | EQ4: Medido Piemonte | ER4: Medido Piemonte INCC | ES4: Medido Terceiros INCC | ET4: Medido Terceiros | EU4: Medido Piemonte | EV4: Medido Piemonte INCC | EW4: Medido Terceiros INCC | EX4: Medido Terceiros | EY4: Medido Piemonte | EZ4: Medido Piemonte INCC | FA4: Medido Terceiros INCC | FB4: Medido Terceiros | FC4: Medido Piemonte | FD4: Medido Piemonte INCC | FE4: Medido Terceiros INCC | FF4: Medido Terceiros
A5: 01.01.04.01.001 | B5: COORDENADOR DE OBRAS | C5: 36 | D5: =E5*C5 -> 936910.8 | E5: 26025.3 | F5: =K5*$C$1 -> 278151.2 | G5: =D5/$C$2 -> 868.78744 | H5: =E5/$C$2 -> 24.132984 | I5: =SUMIFS($S5:$FF5,$S$4:$FF$4,$T$4) -> 651.59058 | J5: =SUMIFS($S5:$FF5,$S$4:$FF$4,$U$4) -> 0 | K5: =G5-I5-J5 -> 217.19686 | R5: =M5-SUMIFS(S5:ET5,$S$4:$ET$4,$V$4) -> 0 | S5: =IF($E5*S$2/$C$2-V5>0,$E5*S$2/$C$2-V5,0) -> 26579.804 | T5: =IFERROR(S5/S$2,0) -> 24.132984 | U5: =IFERROR(V5/S$2,0) -> 0 | W5: =IF($E5*W$2/$C$2-Z5>0,$E5*W$2/$C$2-Z5,0) -> 26809.019 | X5: =IFERROR(W5/W$2,0) -> 24.132984 | Y5: =IFERROR(Z5/W$2,0) -> 0 | AA5: =IF($E5*AA$2/$C$2-AD5>0,$E5*AA$2/$C$2-AD5,0) -> 27000.635 | AB5: =IFERROR(AA5/AA$2,0) -> 24.132984 | AC5: =IFERROR(AD5/AA$2,0) -> 0 | AE5: =IF($E5*AE$2/$C$2-AH5>0,$E5*AE$2/$C$2-AH5,0) -> 27195.846 | AF5: =IFERROR(AE5/AE$2,0) -> 24.132984 | AG5: =IFERROR(AH5/AE$2,0) -> 0 | AI5: =IF($E5*AI$2/$C$2-AL5>0,$E5*AI$2/$C$2-AL5,0) -> 27385.507 | AJ5: =IFERROR(AI5/AI$2,0) -> 24.132984 | AK5: =IFERROR(AL5/AI$2,0) -> 0 | AM5: 27545.34 | AN5: =IFERROR(AM5/AM$2,0) -> 24.132984 | AO5: =IFERROR(AP5/AM$2,0) -> 0 | AQ5: 27732.902 | AR5: =IFERROR(AQ5/AQ$2,0) -> 24.132984 | AS5: =IFERROR(AT5/AQ$2,0) -> 0 | AU5: 27842.827 | AV5: =IFERROR(AU5/AU$2,0) -> 24.132984 | AW5: =IFERROR(AX5/AU$2,0) -> 0 | AY5: 27983.064 | AZ5: =IFERROR(AY5/AY$2,0) -> 24.132984 | BA5: =IFERROR(BB5/AY$2,0) -> 0 | BC5: =IF($E5*BC$2/$C$2-BF5>0,$E5*BC$2/$C$2-BF5,0) -> 28214.258 | BD5: =IFERROR(BC5/BC$2,0) -> 24.132984 | BE5: =IFERROR(BF5/BC$2,0) -> 0 | BG5: =IF($E5*BG$2/$C$2-BJ5>0,$E5*BG$2/$C$2-BJ5,0) -> 28326.694 | BH5: =IFERROR(BG5/BG$2,0) -> 24.132984 | BI5: =IFERROR(BJ5/BG$2,0) -> 0 | BK5: =IF($E5*BK$2/$C$2-BN5>0,$E5*BK$2/$C$2-BN5,0) -> 28437.971 | BL5: =IFERROR(BK5/BK$2,0) -> 24.132984 | BM5: =IFERROR(BN5/BK$2,0) -> 0 | BO5: =IF($E5*BO$2/$C$2-BR5>0,$E5*BO$2/$C$2-BR5,0) -> 28584.603 | BP5: =IFERROR(BO5/BO$2,0) -> 24.132984 | BQ5: =IFERROR(BR5/BO$2,0) -> 0 | BS5: =IF($E5*BS$2/$C$2-BV5>0,$E5*BS$2/$C$2-BV5,0) -> 28750.276 | BT5: =IFERROR(BS5/BS$2,0) -> 24.132984 | BU5: =IFERROR(BV5/BS$2,0) -> 0 | BW5: =IF($E5*BW$2/$C$2-BZ5>0,$E5*BW$2/$C$2-BZ5,0) -> 28947.732 | BX5: =IFERROR(BW5/BW$2,0) -> 24.132984 | BY5: =IFERROR(BZ5/BW$2,0) -> 0 | CA5: =IF($E5*CA$2/$C$2-CD5>0,$E5*CA$2/$C$2-CD5,0) -> 29212.278 | CB5: =IFERROR(CA5/CA$2,0) -> 24.132984 | CC5: =IFERROR(CD5/CA$2,0) -> 0 | CE5: =IF($E5*CE$2/$C$2-CH5>0,$E5*CE$2/$C$2-CH5,0) -> 29362.747 | CF5: =IFERROR(CE5/CE$2,0) -> 24.132984 | CG5: =IFERROR(CH5/CE$2,0) -> 0 | CI5: =IF($E5*CI$2/$C$2-CL5>0,$E5*CI$2/$C$2-CL5,0) -> 29412.002 | CJ5: =IFERROR(CI5/CI$2,0) -> 24.132984 | CK5: =IFERROR(CL5/CI$2,0) -> 0 | CM5: =IF($E5*CM$2/$C$2-CP5>0,$E5*CM$2/$C$2-CP5,0) -> 29499.098 | CN5: =IFERROR(CM5/CM$2,0) -> 24.132984 | CO5: =IFERROR(CP5/CM$2,0) -> 0 | CQ5: =IF($E5*CQ$2/$C$2-CT5>0,$E5*CQ$2/$C$2-CT5,0) -> 29578.182 | CR5: =IFERROR(CQ5/CQ$2,0) -> 24.132984 | CS5: =IFERROR(CT5/CQ$2,0) -> 0 | CU5: =IF($E5*CU$2/$C$2-CX5>0,$E5*CU$2/$C$2-CX5,0) -> 29639.19 | CV5: =IFERROR(CU5/CU$2,0) -> 24.132984 | CW5: =IFERROR(CX5/CU$2,0) -> 0 | CY5: =IF($E5*CY$2/$C$2-DB5>0,$E5*CY$2/$C$2-DB5,0) -> 29853.371 | CZ5: =IFERROR(CY5/CY$2,0) -> 24.132984 | DA5: =IFERROR(DB5/CY$2,0) -> 0 | DC5: =IF($E5*DC$2/$C$2-DF5>0,$E5*DC$2/$C$2-DF5,0) -> 29936.509 | DD5: =IFERROR(DC5/DC$2,0) -> 24.132984 | DE5: =IFERROR(DF5/DC$2,0) -> 0 | DG5: =IF($E5*DG$2/$C$2-DJ5>0,$E5*DG$2/$C$2-DJ5,0) -> 30098.2 | DH5: =IFERROR(DG5/DG$2,0) -> 24.132984 | DI5: =IFERROR(DJ5/DG$2,0) -> 0 | DK5: =IF($E5*DK$2/$C$2-DN5>0,$E5*DK$2/$C$2-DN5,0) -> 30399.162 | DL5: =IFERROR(DK5/DK$2,0) -> 24.132984 | DM5: =IFERROR(DN5/DK$2,0) -> 0 | DO5: =IF($E5*DO$2/$C$2-DR5>0,$E5*DO$2/$C$2-DR5,0) -> 30665.663 | DP5: =IFERROR(DO5/DO$2,0) -> 24.132984 | DQ5: =IFERROR(DR5/DO$2,0) -> 0 | DS5: =IF($E5*DS$2/$C$2-DV5>0,$E5*DS$2/$C$2-DV5,0) -> 30905.689 | DT5: =IFERROR(DS5/DS$2,0) -> 24.132984 | DU5: =IFERROR(DV5/DS$2,0) -> 0 | DW5: =IF($E5*DW$2/$C$2-DZ5>0,$E5*DW$2/$C$2-DZ5,0) -> 0 | DX5: =IFERROR(DW5/DW$2,0) -> 0 | DY5: =IFERROR(DZ5/DW$2,0) -> 0 | EA5: =IF($E5*EA$2/$C$2-ED5>0,$E5*EA$2/$C$2-ED5,0) -> 0 | EB5: =IFERROR(EA5/EA$2,0) -> 0 | EC5: =IFERROR(ED5/EA$2,0) -> 0 | EE5: =IF($E5*EE$2/$C$2-EH5>0,$E5*EE$2/$C$2-EH5,0) -> 0 | EF5: =IFERROR(EE5/EE$2,0) -> 0 | EG5: =IFERROR(EH5/EE$2,0) -> 0 | EI5: =IF($E5*EI$2/$C$2-EL5>0,$E5*EI$2/$C$2-EL5,0) -> 0 | EJ5: =IFERROR(EI5/EI$2,0) -> 0 | EK5: =IFERROR(EL5/EI$2,0) -> 0 | EM5: =IF($E5*EM$2/$C$2-EP5>0,$E5*EM$2/$C$2-EP5,0) -> 0 | EN5: =IFERROR(EM5/EM$2,0) -> 0 | EO5: =IFERROR(EP5/EM$2,0) -> 0 | EQ5: =IF($E5*EQ$2/$C$2-ET5>0,$E5*EQ$2/$C$2-ET5,0) -> 0 | ER5: =IFERROR(EQ5/EQ$2,0) -> 0 | ES5: =IFERROR(ET5/EQ$2,0) -> 0 | EU5: =IF($E5*EU$2/$C$2-EX5>0,$E5*EU$2/$C$2-EX5,0) -> 0 | EV5: =IFERROR(EU5/EU$2,0) -> 0 | EW5: =IFERROR(EX5/EU$2,0) -> 0 | EY5: =IF($E5*EY$2/$C$2-FB5>0,$E5*EY$2/$C$2-FB5,0) -> 0 | EZ5: =IFERROR(EY5/EY$2,0) -> 0 | FA5: =IFERROR(FB5/EY$2,0) -> 0 | FC5: =IF($E5*FC$2/$C$2-FF5>0,$E5*FC$2/$C$2-FF5,0) -> 0 | FD5: =IFERROR(FC5/FC$2,0) -> 0 | FE5: =IFERROR(FF5/FC$2,0) -> 0
A6: 01.01.04.01.002 | B6: ENGENHEIRO RESIDENTE | C6: 36 | D6: =E6*C6 -> 713349 | E6: 19815.25 | F6: =K6*$C$1 -> 211779.91 | G6: =D6/$C$2 -> 661.48096 | H6: =E6/$C$2 -> 18.374471 | I6: =SUMIFS($S6:$FF6,$S$4:$FF$4,$T$4) -> 496.11072 | J6: =SUMIFS($S6:$FF6,$S$4:$FF$4,$U$4) -> 0 | K6: =G6-I6-J6 -> 165.37024 | R6: =M6-SUMIFS(S6:ET6,$S$4:$ET$4,$V$4) -> 0 | S6: =IF($E6*S$2/$C$2-V6>0,$E6*S$2/$C$2-V6,0) -> 20237.44 | T6: =IFERROR(S6/S$2,0) -> 18.374471 | U6: =IFERROR(V6/S$2,0) -> 0 | W6: =IF($E6*W$2/$C$2-Z6>0,$E6*W$2/$C$2-Z6,0) -> 20411.961 | X6: =IFERROR(W6/W$2,0) -> 18.374471 | Y6: =IFERROR(Z6/W$2,0) -> 0 | AA6: =IF($E6*AA$2/$C$2-AD6>0,$E6*AA$2/$C$2-AD6,0) -> 20557.854 | AB6: =IFERROR(AA6/AA$2,0) -> 18.374471 | AC6: =IFERROR(AD6/AA$2,0) -> 0 | AE6: =IF($E6*AE$2/$C$2-AH6>0,$E6*AE$2/$C$2-AH6,0) -> 20706.485 | AF6: =IFERROR(AE6/AE$2,0) -> 18.374471 | AG6: =IFERROR(AH6/AE$2,0) -> 0 | AI6: =IF($E6*AI$2/$C$2-AL6>0,$E6*AI$2/$C$2-AL6,0) -> 20850.89 | AJ6: =IFERROR(AI6/AI$2,0) -> 18.374471 | AK6: =IFERROR(AL6/AI$2,0) -> 0 | AM6: 20972.584 | AN6: =IFERROR(AM6/AM$2,0) -> 18.374471 | AO6: =IFERROR(AP6/AM$2,0) -> 0 | AQ6: 21115.391 | AR6: =IFERROR(AQ6/AQ$2,0) -> 18.374471 | AS6: =IFERROR(AT6/AQ$2,0) -> 0 | AU6: 21199.087 | AV6: =IFERROR(AU6/AU$2,0) -> 18.374471 | AW6: =IFERROR(AX6/AU$2,0) -> 0 | AY6: 21305.861 | AZ6: =IFERROR(AY6/AY$2,0) -> 18.374471 | BA6: =IFERROR(BB6/AY$2,0) -> 0 | BC6: =IF($E6*BC$2/$C$2-BF6>0,$E6*BC$2/$C$2-BF6,0) -> 21481.888 | BD6: =IFERROR(BC6/BC$2,0) -> 18.374471 | BE6: =IFERROR(BF6/BC$2,0) -> 0 | BG6: =IF($E6*BG$2/$C$2-BJ6>0,$E6*BG$2/$C$2-BJ6,0) -> 21567.495 | BH6: =IFERROR(BG6/BG$2,0) -> 18.374471 | BI6: =IFERROR(BJ6/BG$2,0) -> 0 | BK6: =IF($E6*BK$2/$C$2-BN6>0,$E6*BK$2/$C$2-BN6,0) -> 21652.219 | BL6: =IFERROR(BK6/BK$2,0) -> 18.374471 | BM6: =IFERROR(BN6/BK$2,0) -> 0 | BO6: =IF($E6*BO$2/$C$2-BR6>0,$E6*BO$2/$C$2-BR6,0) -> 21763.863 | BP6: =IFERROR(BO6/BO$2,0) -> 18.374471 | BQ6: =IFERROR(BR6/BO$2,0) -> 0 | BS6: =IF($E6*BS$2/$C$2-BV6>0,$E6*BS$2/$C$2-BV6,0) -> 21890.003 | BT6: =IFERROR(BS6/BS$2,0) -> 18.374471 | BU6: =IFERROR(BV6/BS$2,0) -> 0 | BW6: =IF($E6*BW$2/$C$2-BZ6>0,$E6*BW$2/$C$2-BZ6,0) -> 22040.343 | BX6: =IFERROR(BW6/BW$2,0) -> 18.374471 | BY6: =IFERROR(BZ6/BW$2,0) -> 0 | CA6: =IF($E6*CA$2/$C$2-CD6>0,$E6*CA$2/$C$2-CD6,0) -> 22241.764 | CB6: =IFERROR(CA6/CA$2,0) -> 18.374471 | CC6: =IFERROR(CD6/CA$2,0) -> 0 | CE6: =IF($E6*CE$2/$C$2-CH6>0,$E6*CE$2/$C$2-CH6,0) -> 22356.329 | CF6: =IFERROR(CE6/CE$2,0) -> 18.374471 | CG6: =IFERROR(CH6/CE$2,0) -> 0 | CI6: =IF($E6*CI$2/$C$2-CL6>0,$E6*CI$2/$C$2-CL6,0) -> 22393.831 | CJ6: =IFERROR(CI6/CI$2,0) -> 18.374471 | CK6: =IFERROR(CL6/CI$2,0) -> 0 | CM6: =IF($E6*CM$2/$C$2-CP6>0,$E6*CM$2/$C$2-CP6,0) -> 22460.145 | CN6: =IFERROR(CM6/CM$2,0) -> 18.374471 | CO6: =IFERROR(CP6/CM$2,0) -> 0 | CQ6: =IF($E6*CQ$2/$C$2-CT6>0,$E6*CQ$2/$C$2-CT6,0) -> 22520.358 | CR6: =IFERROR(CQ6/CQ$2,0) -> 18.374471 | CS6: =IFERROR(CT6/CQ$2,0) -> 0 | CU6: =IF($E6*CU$2/$C$2-CX6>0,$E6*CU$2/$C$2-CX6,0) -> 22566.809 | CV6: =IFERROR(CU6/CU$2,0) -> 18.374471 | CW6: =IFERROR(CX6/CU$2,0) -> 0 | CY6: =IF($E6*CY$2/$C$2-DB6>0,$E6*CY$2/$C$2-DB6,0) -> 22729.882 | CZ6: =IFERROR(CY6/CY$2,0) -> 18.374471 | DA6: =IFERROR(DB6/CY$2,0) -> 0 | DC6: =IF($E6*DC$2/$C$2-DF6>0,$E6*DC$2/$C$2-DF6,0) -> 22793.182 | DD6: =IFERROR(DC6/DC$2,0) -> 18.374471 | DE6: =IFERROR(DF6/DC$2,0) -> 0 | DG6: =IF($E6*DG$2/$C$2-DJ6>0,$E6*DG$2/$C$2-DJ6,0) -> 22916.291 | DH6: =IFERROR(DG6/DG$2,0) -> 18.374471 | DI6: =IFERROR(DJ6/DG$2,0) -> 0 | DK6: =IF($E6*DK$2/$C$2-DN6>0,$E6*DK$2/$C$2-DN6,0) -> 23145.439 | DL6: =IFERROR(DK6/DK$2,0) -> 18.374471 | DM6: =IFERROR(DN6/DK$2,0) -> 0 | DO6: =IF($E6*DO$2/$C$2-DR6>0,$E6*DO$2/$C$2-DR6,0) -> 23348.348 | DP6: =IFERROR(DO6/DO$2,0) -> 18.374471 | DQ6: =IFERROR(DR6/DO$2,0) -> 0 | DS6: =IF($E6*DS$2/$C$2-DV6>0,$E6*DS$2/$C$2-DV6,0) -> 23531.101 | DT6: =IFERROR(DS6/DS$2,0) -> 18.374471 | DU6: =IFERROR(DV6/DS$2,0) -> 0 | DW6: =IF($E6*DW$2/$C$2-DZ6>0,$E6*DW$2/$C$2-DZ6,0) -> 0 | DX6: =IFERROR(DW6/DW$2,0) -> 0 | DY6: =IFERROR(DZ6/DW$2,0) -> 0 | EA6: =IF($E6*EA$2/$C$2-ED6>0,$E6*EA$2/$C$2-ED6,0) -> 0 | EB6: =IFERROR(EA6/EA$2,0) -> 0 | EC6: =IFERROR(ED6/EA$2,0) -> 0 | EE6: =IF($E6*EE$2/$C$2-EH6>0,$E6*EE$2/$C$2-EH6,0) -> 0 | EF6: =IFERROR(EE6/EE$2,0) -> 0 | EG6: =IFERROR(EH6/EE$2,0) -> 0 | EI6: =IF($E6*EI$2/$C$2-EL6>0,$E6*EI$2/$C$2-EL6,0) -> 0 | EJ6: =IFERROR(EI6/EI$2,0) -> 0 | EK6: =IFERROR(EL6/EI$2,0) -> 0 | EM6: =IF($E6*EM$2/$C$2-EP6>0,$E6*EM$2/$C$2-EP6,0) -> 0 | EN6: =IFERROR(EM6/EM$2,0) -> 0 | EO6: =IFERROR(EP6/EM$2,0) -> 0 | EQ6: =IF($E6*EQ$2/$C$2-ET6>0,$E6*EQ$2/$C$2-ET6,0) -> 0 | ER6: =IFERROR(EQ6/EQ$2,0) -> 0 | ES6: =IFERROR(ET6/EQ$2,0) -> 0 | EU6: =IF($E6*EU$2/$C$2-EX6>0,$E6*EU$2/$C$2-EX6,0) -> 0 | EV6: =IFERROR(EU6/EU$2,0) -> 0 | EW6: =IFERROR(EX6/EU$2,0) -> 0 | EY6: =IF($E6*EY$2/$C$2-FB6>0,$E6*EY$2/$C$2-FB6,0) -> 0 | EZ6: =IFERROR(EY6/EY$2,0) -> 0 | FA6: =IFERROR(FB6/EY$2,0) -> 0 | FC6: =IF($E6*FC$2/$C$2-FF6>0,$E6*FC$2/$C$2-FF6,0) -> 0 | FD6: =IFERROR(FC6/FC$2,0) -> 0 | FE6: =IFERROR(FF6/FC$2,0) -> 0
A7: 01.01.04.01.003 | B7: ESTAGIÁRIO | C7: 36 | D7: =E7*C7 -> 394115.04 | E7: 10947.64 | F7: =K7*$C$1 -> 117005.35 | G7: =D7/$C$2 -> 365.45869 | H7: =E7/$C$2 -> 10.15163 | I7: =SUMIFS($S7:$FF7,$S$4:$FF$4,$T$4) -> 274.09402 | J7: =SUMIFS($S7:$FF7,$S$4:$FF$4,$U$4) -> 0 | K7: =G7-I7-J7 -> 91.364673 | R7: =M7-SUMIFS(S7:ET7,$S$4:$ET$4,$V$4) -> 0 | S7: =IF($E7*S$2/$C$2-V7>0,$E7*S$2/$C$2-V7,0) -> 11180.894 | T7: =IFERROR(S7/S$2,0) -> 10.15163 | U7: =IFERROR(V7/S$2,0) -> 0 | W7: =IF($E7*W$2/$C$2-Z7>0,$E7*W$2/$C$2-Z7,0) -> 11277.314 | X7: =IFERROR(W7/W$2,0) -> 10.15163 | Y7: =IFERROR(Z7/W$2,0) -> 0 | AA7: =IF($E7*AA$2/$C$2-AD7>0,$E7*AA$2/$C$2-AD7,0) -> 11357.918 | AB7: =IFERROR(AA7/AA$2,0) -> 10.15163 | AC7: =IFERROR(AD7/AA$2,0) -> 0 | AE7: =IF($E7*AE$2/$C$2-AH7>0,$E7*AE$2/$C$2-AH7,0) -> 11440.035 | AF7: =IFERROR(AE7/AE$2,0) -> 10.15163 | AG7: =IFERROR(AH7/AE$2,0) -> 0 | AI7: =IF($E7*AI$2/$C$2-AL7>0,$E7*AI$2/$C$2-AL7,0) -> 11519.816 | AJ7: =IFERROR(AI7/AI$2,0) -> 10.15163 | AK7: =IFERROR(AL7/AI$2,0) -> 0 | AM7: 11587.051 | AN7: =IFERROR(AM7/AM$2,0) -> 10.15163 | AO7: =IFERROR(AP7/AM$2,0) -> 0 | AQ7: 11665.949 | AR7: =IFERROR(AQ7/AQ$2,0) -> 10.15163 | AS7: =IFERROR(AT7/AQ$2,0) -> 0 | AU7: 11712.19 | AV7: =IFERROR(AU7/AU$2,0) -> 10.15163 | AW7: =IFERROR(AX7/AU$2,0) -> 0 | AY7: 11771.181 | AZ7: =IFERROR(AY7/AY$2,0) -> 10.15163 | BA7: =IFERROR(BB7/AY$2,0) -> 0 | BC7: =IF($E7*BC$2/$C$2-BF7>0,$E7*BC$2/$C$2-BF7,0) -> 11868.433 | BD7: =IFERROR(BC7/BC$2,0) -> 10.15163 | BE7: =IFERROR(BF7/BC$2,0) -> 0 | BG7: =IF($E7*BG$2/$C$2-BJ7>0,$E7*BG$2/$C$2-BJ7,0) -> 11915.73 | BH7: =IFERROR(BG7/BG$2,0) -> 10.15163 | BI7: =IFERROR(BJ7/BG$2,0) -> 0 | BK7: =IF($E7*BK$2/$C$2-BN7>0,$E7*BK$2/$C$2-BN7,0) -> 11962.539 | BL7: =IFERROR(BK7/BK$2,0) -> 10.15163 | BM7: =IFERROR(BN7/BK$2,0) -> 0 | BO7: =IF($E7*BO$2/$C$2-BR7>0,$E7*BO$2/$C$2-BR7,0) -> 12024.22 | BP7: =IFERROR(BO7/BO$2,0) -> 10.15163 | BQ7: =IFERROR(BR7/BO$2,0) -> 0 | BS7: =IF($E7*BS$2/$C$2-BV7>0,$E7*BS$2/$C$2-BV7,0) -> 12093.911 | BT7: =IFERROR(BS7/BS$2,0) -> 10.15163 | BU7: =IFERROR(BV7/BS$2,0) -> 0 | BW7: =IF($E7*BW$2/$C$2-BZ7>0,$E7*BW$2/$C$2-BZ7,0) -> 12176.972 | BX7: =IFERROR(BW7/BW$2,0) -> 10.15163 | BY7: =IFERROR(BZ7/BW$2,0) -> 0 | CA7: =IF($E7*CA$2/$C$2-CD7>0,$E7*CA$2/$C$2-CD7,0) -> 12288.254 | CB7: =IFERROR(CA7/CA$2,0) -> 10.15163 | CC7: =IFERROR(CD7/CA$2,0) -> 0 | CE7: =IF($E7*CE$2/$C$2-CH7>0,$E7*CE$2/$C$2-CH7,0) -> 12351.55 | CF7: =IFERROR(CE7/CE$2,0) -> 10.15163 | CG7: =IFERROR(CH7/CE$2,0) -> 0 | CI7: =IF($E7*CI$2/$C$2-CL7>0,$E7*CI$2/$C$2-CL7,0) -> 12372.269 | CJ7: =IFERROR(CI7/CI$2,0) -> 10.15163 | CK7: =IFERROR(CL7/CI$2,0) -> 0 | CM7: =IF($E7*CM$2/$C$2-CP7>0,$E7*CM$2/$C$2-CP7,0) -> 12408.906 | CN7: =IFERROR(CM7/CM$2,0) -> 10.15163 | CO7: =IFERROR(CP7/CM$2,0) -> 0 | CQ7: =IF($E7*CQ$2/$C$2-CT7>0,$E7*CQ$2/$C$2-CT7,0) -> 12442.173 | CR7: =IFERROR(CQ7/CQ$2,0) -> 10.15163 | CS7: =IFERROR(CT7/CQ$2,0) -> 0 | CU7: =IF($E7*CU$2/$C$2-CX7>0,$E7*CU$2/$C$2-CX7,0) -> 12467.836 | CV7: =IFERROR(CU7/CU$2,0) -> 10.15163 | CW7: =IFERROR(CX7/CU$2,0) -> 0 | CY7: =IF($E7*CY$2/$C$2-DB7>0,$E7*CY$2/$C$2-DB7,0) -> 12557.932 | CZ7: =IFERROR(CY7/CY$2,0) -> 10.15163 | DA7: =IFERROR(DB7/CY$2,0) -> 0 | DC7: =IF($E7*DC$2/$C$2-DF7>0,$E7*DC$2/$C$2-DF7,0) -> 12592.905 | DD7: =IFERROR(DC7/DC$2,0) -> 10.15163 | DE7: =IFERROR(DF7/DC$2,0) -> 0 | DG7: =IF($E7*DG$2/$C$2-DJ7>0,$E7*DG$2/$C$2-DJ7,0) -> 12660.921 | DH7: =IFERROR(DG7/DG$2,0) -> 10.15163 | DI7: =IFERROR(DJ7/DG$2,0) -> 0 | DK7: =IF($E7*DK$2/$C$2-DN7>0,$E7*DK$2/$C$2-DN7,0) -> 12787.521 | DL7: =IFERROR(DK7/DK$2,0) -> 10.15163 | DM7: =IFERROR(DN7/DK$2,0) -> 0 | DO7: =IF($E7*DO$2/$C$2-DR7>0,$E7*DO$2/$C$2-DR7,0) -> 12899.626 | DP7: =IFERROR(DO7/DO$2,0) -> 10.15163 | DQ7: =IFERROR(DR7/DO$2,0) -> 0 | DS7: =IF($E7*DS$2/$C$2-DV7>0,$E7*DS$2/$C$2-DV7,0) -> 13000.594 | DT7: =IFERROR(DS7/DS$2,0) -> 10.15163 | DU7: =IFERROR(DV7/DS$2,0) -> 0 | DW7: =IF($E7*DW$2/$C$2-DZ7>0,$E7*DW$2/$C$2-DZ7,0) -> 0 | DX7: =IFERROR(DW7/DW$2,0) -> 0 | DY7: =IFERROR(DZ7/DW$2,0) -> 0 | EA7: =IF($E7*EA$2/$C$2-ED7>0,$E7*EA$2/$C$2-ED7,0) -> 0 | EB7: =IFERROR(EA7/EA$2,0) -> 0 | EC7: =IFERROR(ED7/EA$2,0) -> 0 | EE7: =IF($E7*EE$2/$C$2-EH7>0,$E7*EE$2/$C$2-EH7,0) -> 0 | EF7: =IFERROR(EE7/EE$2,0) -> 0 | EG7: =IFERROR(EH7/EE$2,0) -> 0 | EI7: =IF($E7*EI$2/$C$2-EL7>0,$E7*EI$2/$C$2-EL7,0) -> 0 | EJ7: =IFERROR(EI7/EI$2,0) -> 0 | EK7: =IFERROR(EL7/EI$2,0) -> 0 | EM7: =IF($E7*EM$2/$C$2-EP7>0,$E7*EM$2/$C$2-EP7,0) -> 0 | EN7: =IFERROR(EM7/EM$2,0) -> 0 | EO7: =IFERROR(EP7/EM$2,0) -> 0 | EQ7: =IF($E7*EQ$2/$C$2-ET7>0,$E7*EQ$2/$C$2-ET7,0) -> 0 | ER7: =IFERROR(EQ7/EQ$2,0) -> 0 | ES7: =IFERROR(ET7/EQ$2,0) -> 0 | EU7: =IF($E7*EU$2/$C$2-EX7>0,$E7*EU$2/$C$2-EX7,0) -> 0 | EV7: =IFERROR(EU7/EU$2,0) -> 0 | EW7: =IFERROR(EX7/EU$2,0) -> 0 | EY7: =IF($E7*EY$2/$C$2-FB7>0,$E7*EY$2/$C$2-FB7,0) -> 0 | EZ7: =IFERROR(EY7/EY$2,0) -> 0 | FA7: =IFERROR(FB7/EY$2,0) -> 0 | FC7: =IF($E7*FC$2/$C$2-FF7>0,$E7*FC$2/$C$2-FF7,0) -> 0 | FD7: =IFERROR(FC7/FC$2,0) -> 0 | FE7: =IFERROR(FF7/FC$2,0) -> 0
A8: 01.01.04.01.004 | B8: MESTRE DE OBRAS | C8: 36 | D8: =E8*C8 -> 508482.36 | E8: 14124.51 | F8: =K8*$C$1 -> 112467.47 | G8: =D8/$C$2 -> 471.51029 | H8: =E8/$C$2 -> 13.097508 | I8: =SUMIFS($S8:$FF8,$S$4:$FF$4,$T$4) -> 117.87757 | J8: =SUMIFS($S8:$FF8,$S$4:$FF$4,$U$4) -> 265.81149 | K8: =G8-I8-J8 -> 87.821231 | L8: 6 | M8: =N8*L8 -> 100949.58 | N8: 16824.93 | O8: 30 | P8: =Q8*O8 -> 463200 | Q8: 15440 | R8: =(M8+P8)-SUMIFS(S8:ET8,$S$4:$ET$4,$V$4) -> 254510.92 | S8: =IF($E8*S$2/$C$2-V8>0,$E8*S$2/$C$2-V8,0) -> 0 | T8: =IFERROR(S8/S$2,0) -> 0 | U8: =IFERROR(V8/S$2,0) -> 15.276101 | V8: 16824.93 | W8: =IF($E8*W$2/$C$2-Z8>0,$E8*W$2/$C$2-Z8,0) -> 0 | X8: =IFERROR(W8/W$2,0) -> 0 | Y8: =IFERROR(Z8/W$2,0) -> 15.145492 | Z8: 16824.93 | AA8: =IF($E8*AA$2/$C$2-AD8>0,$E8*AA$2/$C$2-AD8,0) -> 0 | AB8: =IFERROR(AA8/AA$2,0) -> 0 | AC8: =IFERROR(AD8/AA$2,0) -> 15.038009 | AD8: 16824.93 | AE8: =IF($E8*AE$2/$C$2-AH8>0,$E8*AE$2/$C$2-AH8,0) -> 0 | AF8: =IFERROR(AE8/AE$2,0) -> 0 | AG8: =IFERROR(AH8/AE$2,0) -> 14.930066 | AH8: 16824.93 | AI8: =IF($E8*AI$2/$C$2-AL8>0,$E8*AI$2/$C$2-AL8,0) -> 0 | AJ8: =IFERROR(AI8/AI$2,0) -> 0 | AK8: =IFERROR(AL8/AI$2,0) -> 14.826666 | AL8: 16824.93 | AN8: =IFERROR(AM8/AM$2,0) -> 0 | AO8: =IFERROR(AP8/AM$2,0) -> 14.740634 | AP8: 16824.93 | AR8: =IFERROR(AQ8/AQ$2,0) -> 0 | AS8: =IFERROR(AT8/AQ$2,0) -> 13.527271 | AT8: =IF($Q8*AQ$2/$R$2>0,$Q8*AQ$2/$R$2,0) -> 15545.134 | AV8: =IFERROR(AU8/AU$2,0) -> 0 | AW8: =IFERROR(AX8/AU$2,0) -> 13.527271 | AX8: =IF($Q8*AU$2/$R$2>0,$Q8*AU$2/$R$2,0) -> 15606.751 | AZ8: =IFERROR(AY8/AY$2,0) -> 0 | BA8: =IFERROR(BB8/AY$2,0) -> 13.527271 | BB8: =IF($Q8*AY$2/$R$2>0,$Q8*AY$2/$R$2,0) -> 15685.358 | BC8: =IF($E8*BC$2/$C$2-BF8>0,$E8*BC$2/$C$2-BF8,0) -> 0 | BD8: =IFERROR(BC8/BC$2,0) -> 0 | BE8: =IFERROR(BF8/BC$2,0) -> 13.527271 | BF8: =IF($Q8*BC$2/$R$2>0,$Q8*BC$2/$R$2,0) -> 15814.949 | BG8: =IF($E8*BG$2/$C$2-BJ8>0,$E8*BG$2/$C$2-BJ8,0) -> 0 | BH8: =IFERROR(BG8/BG$2,0) -> 0 | BI8: =IFERROR(BJ8/BG$2,0) -> 13.527271 | BJ8: =IF($Q8*BG$2/$R$2>0,$Q8*BG$2/$R$2,0) -> 15877.972 | BK8: =IF($E8*BK$2/$C$2-BN8>0,$E8*BK$2/$C$2-BN8,0) -> 0 | BL8: =IFERROR(BK8/BK$2,0) -> 0 | BM8: =IFERROR(BN8/BK$2,0) -> 13.527271 | BN8: =IF($Q8*BK$2/$R$2>0,$Q8*BK$2/$R$2,0) -> 15940.347 | BO8: =IF($E8*BO$2/$C$2-BR8>0,$E8*BO$2/$C$2-BR8,0) -> 0 | BP8: =IFERROR(BO8/BO$2,0) -> 0 | BQ8: =IFERROR(BR8/BO$2,0) -> 13.527271 | BR8: =IF($Q8*BO$2/$R$2>0,$Q8*BO$2/$R$2,0) -> 16022.538 | BS8: =IF($E8*BS$2/$C$2-BV8>0,$E8*BS$2/$C$2-BV8,0) -> 0 | BT8: =IFERROR(BS8/BS$2,0) -> 0 | BU8: =IFERROR(BV8/BS$2,0) -> 13.527271 | BV8: =IF($Q8*BS$2/$R$2>0,$Q8*BS$2/$R$2,0) -> 16115.403 | BW8: =IF($E8*BW$2/$C$2-BZ8>0,$E8*BW$2/$C$2-BZ8,0) -> 0 | BX8: =IFERROR(BW8/BW$2,0) -> 0 | BY8: =IFERROR(BZ8/BW$2,0) -> 13.527271 | BZ8: =IF($Q8*BW$2/$R$2>0,$Q8*BW$2/$R$2,0) -> 16226.083 | CA8: =IF($E8*CA$2/$C$2-CD8>0,$E8*CA$2/$C$2-CD8,0) -> 0 | CB8: =IFERROR(CA8/CA$2,0) -> 0 | CC8: =IFERROR(CD8/CA$2,0) -> 13.527271 | CD8: =IF($Q8*CA$2/$R$2>0,$Q8*CA$2/$R$2,0) -> 16374.369 | CE8: =IF($E8*CE$2/$C$2-CH8>0,$E8*CE$2/$C$2-CH8,0) -> 0 | CF8: =IFERROR(CE8/CE$2,0) -> 0 | CG8: =IFERROR(CH8/CE$2,0) -> 13.527271 | CH8: =IF($Q8*CE$2/$R$2>0,$Q8*CE$2/$R$2,0) -> 16458.712 | CI8: =IF($E8*CI$2/$C$2-CL8>0,$E8*CI$2/$C$2-CL8,0) -> 0 | CJ8: =IFERROR(CI8/CI$2,0) -> 0 | CK8: =IFERROR(CL8/CI$2,0) -> 13.527271 | CL8: =IF($Q8*CI$2/$R$2>0,$Q8*CI$2/$R$2,0) -> 16486.321 | CM8: 16009.818 | CN8: =IFERROR(CM8/CM$2,0) -> 13.097508 | CO8: =IFERROR(CP8/CM$2,0) -> 13.527271 | CP8: 16535.141 | CQ8: =IF($E8*CQ$2/$C$2-CT8>0,$E8*CQ$2/$C$2-CT8,0) -> 16052.738 | CR8: =IFERROR(CQ8/CQ$2,0) -> 13.097508 | CS8: =IFERROR(CT8/CQ$2,0) -> 0 | CU8: =IF($E8*CU$2/$C$2-CX8>0,$E8*CU$2/$C$2-CX8,0) -> 16085.849 | CV8: =IFERROR(CU8/CU$2,0) -> 13.097508 | CW8: =IFERROR(CX8/CU$2,0) -> 0 | CY8: =IF($E8*CY$2/$C$2-DB8>0,$E8*CY$2/$C$2-DB8,0) -> 16202.089 | CZ8: =IFERROR(CY8/CY$2,0) -> 13.097508 | DA8: =IFERROR(DB8/CY$2,0) -> 0 | DC8: =IF($E8*DC$2/$C$2-DF8>0,$E8*DC$2/$C$2-DF8,0) -> 16247.21 | DD8: =IFERROR(DC8/DC$2,0) -> 13.097508 | DE8: =IFERROR(DF8/DC$2,0) -> 0 | DG8: =IF($E8*DG$2/$C$2-DJ8>0,$E8*DG$2/$C$2-DJ8,0) -> 16334.963 | DH8: =IFERROR(DG8/DG$2,0) -> 13.097508 | DI8: =IFERROR(DJ8/DG$2,0) -> 0 | DK8: =IF($E8*DK$2/$C$2-DN8>0,$E8*DK$2/$C$2-DN8,0) -> 16498.302 | DL8: =IFERROR(DK8/DK$2,0) -> 13.097508 | DM8: =IFERROR(DN8/DK$2,0) -> 0 | DO8: =IF($E8*DO$2/$C$2-DR8>0,$E8*DO$2/$C$2-DR8,0) -> 16642.938 | DP8: =IFERROR(DO8/DO$2,0) -> 13.097508 | DQ8: =IFERROR(DR8/DO$2,0) -> 0 | DS8: =IF($E8*DS$2/$C$2-DV8>0,$E8*DS$2/$C$2-DV8,0) -> 16773.206 | DT8: =IFERROR(DS8/DS$2,0) -> 13.097508 | DU8: =IFERROR(DV8/DS$2,0) -> 0 | DW8: =IF($E8*DW$2/$C$2-DZ8>0,$E8*DW$2/$C$2-DZ8,0) -> 0 | DX8: =IFERROR(DW8/DW$2,0) -> 0 | DY8: =IFERROR(DZ8/DW$2,0) -> 0 | EA8: =IF($E8*EA$2/$C$2-ED8>0,$E8*EA$2/$C$2-ED8,0) -> 0 | EB8: =IFERROR(EA8/EA$2,0) -> 0 | EC8: =IFERROR(ED8/EA$2,0) -> 0 | EE8: =IF($E8*EE$2/$C$2-EH8>0,$E8*EE$2/$C$2-EH8,0) -> 0 | EF8: =IFERROR(EE8/EE$2,0) -> 0 | EG8: =IFERROR(EH8/EE$2,0) -> 0 | EI8: =IF($E8*EI$2/$C$2-EL8>0,$E8*EI$2/$C$2-EL8,0) -> 0 | EJ8: =IFERROR(EI8/EI$2,0) -> 0 | EK8: =IFERROR(EL8/EI$2,0) -> 0 | EM8: =IF($E8*EM$2/$C$2-EP8>0,$E8*EM$2/$C$2-EP8,0) -> 0 | EN8: =IFERROR(EM8/EM$2,0) -> 0 | EO8: =IFERROR(EP8/EM$2,0) -> 0 | EQ8: =IF($E8*EQ$2/$C$2-ET8>0,$E8*EQ$2/$C$2-ET8,0) -> 0 | ER8: =IFERROR(EQ8/EQ$2,0) -> 0 | ES8: =IFERROR(ET8/EQ$2,0) -> 0 | EU8: =IF($E8*EU$2/$C$2-EX8>0,$E8*EU$2/$C$2-EX8,0) -> 0 | EV8: =IFERROR(EU8/EU$2,0) -> 0 | EW8: =IFERROR(EX8/EU$2,0) -> 0 | EY8: =IF($E8*EY$2/$C$2-FB8>0,$E8*EY$2/$C$2-FB8,0) -> 0 | EZ8: =IFERROR(EY8/EY$2,0) -> 0 | FA8: =IFERROR(FB8/EY$2,0) -> 0 | FC8: =IF($E8*FC$2/$C$2-FF8>0,$E8*FC$2/$C$2-FF8,0) -> 0 | FD8: =IFERROR(FC8/FC$2,0) -> 0 | FE8: =IFERROR(FF8/FC$2,0) -> 0
A9: 01.01.04.01.005 | B9: CONTRA-MESTRE DE OBRAS | C9: 36 | D9: =E9*C9 -> 304128 | E9: 8448 | F9: =K9*$C$1 -> 101429.31 | G9: =D9/$C$2 -> 282.01467 | H9: =E9/$C$2 -> 7.8337407 | I9: =SUMIFS($S9:$FF9,$S$4:$FF$4,$T$4) -> 47.382231 | J9: =SUMIFS($S9:$FF9,$S$4:$FF$4,$U$4) -> 155.43045 | K9: =G9-I9-J9 -> 79.201989 | O9: 30 | P9: =Q9*O9 -> 253440 | Q9: 8448 | R9: =P9-SUMIFS(S9:ET9,$S$4:$ET$4,$V$4) -> 65319.082 | S9: =IF($E9*S$2/$C$2-V9>0,$E9*S$2/$C$2-V9,0) -> 8627.9959 | T9: =IFERROR(S9/S$2,0) -> 7.8337407 | U9: =IFERROR(V9/S$2,0) -> 0 | W9: =IF($E9*W$2/$C$2-Z9>0,$E9*W$2/$C$2-Z9,0) -> 8702.4007 | X9: =IFERROR(W9/W$2,0) -> 7.8337407 | Y9: =IFERROR(Z9/W$2,0) -> 0 | AA9: =IF($E9*AA$2/$C$2-AD9>0,$E9*AA$2/$C$2-AD9,0) -> 8764.6006 | AB9: =IFERROR(AA9/AA$2,0) -> 7.8337407 | AC9: =IFERROR(AD9/AA$2,0) -> 0 | AE9: =IF($E9*AE$2/$C$2-AH9>0,$E9*AE$2/$C$2-AH9,0) -> 8827.9678 | AF9: =IFERROR(AE9/AE$2,0) -> 7.8337407 | AG9: =IFERROR(AH9/AE$2,0) -> 0 | AI9: =IF($E9*AI$2/$C$2-AL9>0,$E9*AI$2/$C$2-AL9,0) -> 8889.5331 | AJ9: =IFERROR(AI9/AI$2,0) -> 7.8337407 | AK9: =IFERROR(AL9/AI$2,0) -> 0 | AM9: 493.41599 | AN9: =IFERROR(AM9/AM$2,0) -> 0.43229092 | AO9: =IFERROR(AP9/AM$2,0) -> 0 | AR9: =IFERROR(AQ9/AQ$2,0) -> 0 | AS9: =IFERROR(AT9/AQ$2,0) -> 7.4014498 | AT9: =IF($Q9*AQ$2/$R$2>0,$Q9*AQ$2/$R$2,0) -> 8505.5241 | AV9: =IFERROR(AU9/AU$2,0) -> 0 | AW9: =IFERROR(AX9/AU$2,0) -> 7.4014498 | AX9: =IF($Q9*AU$2/$R$2>0,$Q9*AU$2/$R$2,0) -> 8539.2377 | AZ9: =IFERROR(AY9/AY$2,0) -> 0 | BA9: =IFERROR(BB9/AY$2,0) -> 7.4014498 | BB9: =IF($Q9*AY$2/$R$2>0,$Q9*AY$2/$R$2,0) -> 8582.2475 | BC9: =IF($E9*BC$2/$C$2-BF9>0,$E9*BC$2/$C$2-BF9,0) -> 505.39823 | BD9: =IFERROR(BC9/BC$2,0) -> 0.43229092 | BE9: =IFERROR(BF9/BC$2,0) -> 7.4014498 | BF9: =IF($Q9*BC$2/$R$2>0,$Q9*BC$2/$R$2,0) -> 8653.1534 | BG9: =IF($E9*BG$2/$C$2-BJ9>0,$E9*BG$2/$C$2-BJ9,0) -> 507.41228 | BH9: =IFERROR(BG9/BG$2,0) -> 0.43229092 | BI9: =IFERROR(BJ9/BG$2,0) -> 7.4014498 | BJ9: =IF($Q9*BG$2/$R$2>0,$Q9*BG$2/$R$2,0) -> 8687.6367 | BK9: =IF($E9*BK$2/$C$2-BN9>0,$E9*BK$2/$C$2-BN9,0) -> 509.40557 | BL9: =IFERROR(BK9/BK$2,0) -> 0.43229092 | BM9: =IFERROR(BN9/BK$2,0) -> 7.4014498 | BN9: =IF($Q9*BK$2/$R$2>0,$Q9*BK$2/$R$2,0) -> 8721.7648 | BO9: =IF($E9*BO$2/$C$2-BR9>0,$E9*BO$2/$C$2-BR9,0) -> 512.03217 | BP9: =IFERROR(BO9/BO$2,0) -> 0.43229092 | BQ9: =IFERROR(BR9/BO$2,0) -> 7.4014498 | BR9: =IF($Q9*BO$2/$R$2>0,$Q9*BO$2/$R$2,0) -> 8766.736 | BS9: =IF($E9*BS$2/$C$2-BV9>0,$E9*BS$2/$C$2-BV9,0) -> 514.99985 | BT9: =IFERROR(BS9/BS$2,0) -> 0.43229092 | BU9: =IFERROR(BV9/BS$2,0) -> 7.4014498 | BV9: =IF($Q9*BS$2/$R$2>0,$Q9*BS$2/$R$2,0) -> 8817.547 | BW9: =IF($E9*BW$2/$C$2-BZ9>0,$E9*BW$2/$C$2-BZ9,0) -> 518.53685 | BX9: =IFERROR(BW9/BW$2,0) -> 0.43229092 | BY9: =IFERROR(BZ9/BW$2,0) -> 7.4014498 | BZ9: =IF($Q9*BW$2/$R$2>0,$Q9*BW$2/$R$2,0) -> 8878.1056 | CA9: =IF($E9*CA$2/$C$2-CD9>0,$E9*CA$2/$C$2-CD9,0) -> 523.27562 | CB9: =IFERROR(CA9/CA$2,0) -> 0.43229092 | CC9: =IFERROR(CD9/CA$2,0) -> 7.4014498 | CD9: =IF($Q9*CA$2/$R$2>0,$Q9*CA$2/$R$2,0) -> 8959.2403 | CE9: =IF($E9*CE$2/$C$2-CH9>0,$E9*CE$2/$C$2-CH9,0) -> 525.97096 | CF9: =IFERROR(CE9/CE$2,0) -> 0.43229092 | CG9: =IFERROR(CH9/CE$2,0) -> 7.4014498 | CH9: =IF($Q9*CE$2/$R$2>0,$Q9*CE$2/$R$2,0) -> 9005.3884 | CI9: =IF($E9*CI$2/$C$2-CL9>0,$E9*CI$2/$C$2-CL9,0) -> 526.85326 | CJ9: =IFERROR(CI9/CI$2,0) -> 0.43229092 | CK9: =IFERROR(CL9/CI$2,0) -> 7.4014498 | CL9: =IF($Q9*CI$2/$R$2>0,$Q9*CI$2/$R$2,0) -> 9020.4947 | CM9: =IF($E9*CM$2/$C$2-CP9>0,$E9*CM$2/$C$2-CP9,0) -> 528.4134 | CN9: =IFERROR(CM9/CM$2,0) -> 0.43229092 | CO9: =IFERROR(CP9/CM$2,0) -> 7.4014498 | CP9: =IF($Q9*CM$2/$R$2>0,$Q9*CM$2/$R$2,0) -> 9047.2066 | CQ9: =IF($E9*CQ$2/$C$2-CT9>0,$E9*CQ$2/$C$2-CT9,0) -> 529.83002 | CR9: =IFERROR(CQ9/CQ$2,0) -> 0.43229092 | CS9: =IFERROR(CT9/CQ$2,0) -> 7.4014498 | CT9: =IF($Q9*CQ$2/$R$2>0,$Q9*CQ$2/$R$2,0) -> 9071.4611 | CU9: =IF($E9*CU$2/$C$2-CX9>0,$E9*CU$2/$C$2-CX9,0) -> 530.92285 | CV9: =IFERROR(CU9/CU$2,0) -> 0.43229092 | CW9: =IFERROR(CX9/CU$2,0) -> 7.4014498 | CX9: =IF($Q9*CU$2/$R$2>0,$Q9*CU$2/$R$2,0) -> 9090.172 | CY9: =IF($E9*CY$2/$C$2-DB9>0,$E9*CY$2/$C$2-DB9,0) -> 534.75943 | CZ9: =IFERROR(CY9/CY$2,0) -> 0.43229092 | DA9: =IFERROR(DB9/CY$2,0) -> 7.4014498 | DB9: =IF($Q9*CY$2/$R$2>0,$Q9*CY$2/$R$2,0) -> 9155.8599 | DC9: =IF($E9*DC$2/$C$2-DF9>0,$E9*DC$2/$C$2-DF9,0) -> 536.24867 | DD9: =IFERROR(DC9/DC$2,0) -> 0.43229092 | DE9: =IFERROR(DF9/DC$2,0) -> 7.4014498 | DF9: =IF($Q9*DC$2/$R$2>0,$Q9*DC$2/$R$2,0) -> 9181.3579 | DG9: =IF($E9*DG$2/$C$2-DJ9>0,$E9*DG$2/$C$2-DJ9,0) -> 539.14502 | DH9: =IFERROR(DG9/DG$2,0) -> 0.43229092 | DI9: =IFERROR(DJ9/DG$2,0) -> 7.4014498 | DJ9: =IF($Q9*DG$2/$R$2>0,$Q9*DG$2/$R$2,0) -> 9230.9476 | DK9: =IF($E9*DK$2/$C$2-DN9>0,$E9*DK$2/$C$2-DN9,0) -> 544.53612 | DL9: =IFERROR(DK9/DK$2,0) -> 0.43229092 | DM9: =IFERROR(DN9/DK$2,0) -> 7.4014498 | DN9: =IF($Q9*DK$2/$R$2>0,$Q9*DK$2/$R$2,0) -> 9323.251 | DO9: =IF($E9*DO$2/$C$2-DR9>0,$E9*DO$2/$C$2-DR9,0) -> 549.30991 | DP9: =IFERROR(DO9/DO$2,0) -> 0.43229092 | DQ9: =IFERROR(DR9/DO$2,0) -> 7.4014498 | DR9: =IF($Q9*DO$2/$R$2>0,$Q9*DO$2/$R$2,0) -> 9404.9853 | DS9: =IF($E9*DS$2/$C$2-DV9>0,$E9*DS$2/$C$2-DV9,0) -> 553.60948 | DT9: =IFERROR(DS9/DS$2,0) -> 0.43229092 | DU9: =IFERROR(DV9/DS$2,0) -> 7.4014498 | DV9: =IF($Q9*DS$2/$R$2>0,$Q9*DS$2/$R$2,0) -> 9478.6001 | DW9: =IF($E9*DW$2/$C$2-DZ9>0,$E9*DW$2/$C$2-DZ9,0) -> 0 | DX9: =IFERROR(DW9/DW$2,0) -> 0 | DY9: =IFERROR(DZ9/DW$2,0) -> 0 | DZ9: =IF($Q9*DW$2/$R$2>0,$Q9*DW$2/$R$2,0) -> 0 | EA9: =IF($E9*EA$2/$C$2-ED9>0,$E9*EA$2/$C$2-ED9,0) -> 0 | EB9: =IFERROR(EA9/EA$2,0) -> 0 | EC9: =IFERROR(ED9/EA$2,0) -> 0 | ED9: =IF($Q9*EA$2/$R$2>0,$Q9*EA$2/$R$2,0) -> 0 | EE9: =IF($E9*EE$2/$C$2-EH9>0,$E9*EE$2/$C$2-EH9,0) -> 0 | EF9: =IFERROR(EE9/EE$2,0) -> 0 | EG9: =IFERROR(EH9/EE$2,0) -> 0 | EH9: =IF($Q9*EE$2/$R$2>0,$Q9*EE$2/$R$2,0) -> 0 | EI9: =IF($E9*EI$2/$C$2-EL9>0,$E9*EI$2/$C$2-EL9,0) -> 0 | EJ9: =IFERROR(EI9/EI$2,0) -> 0 | EK9: =IFERROR(EL9/EI$2,0) -> 0 | EL9: =IF($Q9*EI$2/$R$2>0,$Q9*EI$2/$R$2,0) -> 0 | EM9: =IF($E9*EM$2/$C$2-EP9>0,$E9*EM$2/$C$2-EP9,0) -> 0 | EN9: =IFERROR(EM9/EM$2,0) -> 0 | EO9: =IFERROR(EP9/EM$2,0) -> 0 | EP9: =IF($Q9*EM$2/$R$2>0,$Q9*EM$2/$R$2,0) -> 0 | EQ9: =IF($E9*EQ$2/$C$2-ET9>0,$E9*EQ$2/$C$2-ET9,0) -> 0 | ER9: =IFERROR(EQ9/EQ$2,0) -> 0 | ES9: =IFERROR(ET9/EQ$2,0) -> 0 | ET9: =IF($Q9*EQ$2/$R$2>0,$Q9*EQ$2/$R$2,0) -> 0 | EU9: =IF($E9*EU$2/$C$2-EX9>0,$E9*EU$2/$C$2-EX9,0) -> 0 | EV9: =IFERROR(EU9/EU$2,0) -> 0 | EW9: =IFERROR(EX9/EU$2,0) -> 0 | EX9: =IF($Q9*EU$2/$R$2>0,$Q9*EU$2/$R$2,0) -> 0 | EY9: =IF($E9*EY$2/$C$2-FB9>0,$E9*EY$2/$C$2-FB9,0) -> 0 | EZ9: =IFERROR(EY9/EY$2,0) -> 0 | FA9: =IFERROR(FB9/EY$2,0) -> 0 | FB9: =IF($Q9*EY$2/$R$2>0,$Q9*EY$2/$R$2,0) -> 0 | FC9: =IF($E9*FC$2/$C$2-FF9>0,$E9*FC$2/$C$2-FF9,0) -> 0 | FD9: =IFERROR(FC9/FC$2,0) -> 0 | FE9: =IFERROR(FF9/FC$2,0) -> 0 | FF9: =IF($Q9*FC$2/$R$2>0,$Q9*FC$2/$R$2,0) -> 0
A10: 01.01.04.01.006 | B10: ANALISTA DE ENGENHARIA | C10: 36 | D10: =E10*C10 -> 287242.2 | E10: 7978.95 | F10: =K10*$C$1 -> 85276.809 | G10: =D10/$C$2 -> 266.35664 | H10: =E10/$C$2 -> 7.3987956 | I10: =SUMIFS($S10:$FF10,$S$4:$FF$4,$T$4) -> 199.76748 | J10: =SUMIFS($S10:$FF10,$S$4:$FF$4,$U$4) -> 0 | K10: =G10-I10-J10 -> 66.589161 | R10: =M10-SUMIFS(S10:ET10,$S$4:$ET$4,$V$4) -> 0 | S10: =IF($E10*S$2/$C$2-V10>0,$E10*S$2/$C$2-V10,0) -> 8148.9521 | T10: =IFERROR(S10/S$2,0) -> 7.3987956 | U10: =IFERROR(V10/S$2,0) -> 0 | W10: =IF($E10*W$2/$C$2-Z10>0,$E10*W$2/$C$2-Z10,0) -> 8219.2259 | X10: =IFERROR(W10/W$2,0) -> 7.3987956 | Y10: =IFERROR(Z10/W$2,0) -> 0 | AA10: =IF($E10*AA$2/$C$2-AD10>0,$E10*AA$2/$C$2-AD10,0) -> 8277.9723 | AB10: =IFERROR(AA10/AA$2,0) -> 7.3987956 | AC10: =IFERROR(AD10/AA$2,0) -> 0 | AE10: =IF($E10*AE$2/$C$2-AH10>0,$E10*AE$2/$C$2-AH10,0) -> 8337.8212 | AF10: =IFERROR(AE10/AE$2,0) -> 7.3987956 | AG10: =IFERROR(AH10/AE$2,0) -> 0 | AI10: =IF($E10*AI$2/$C$2-AL10>0,$E10*AI$2/$C$2-AL10,0) -> 8395.9683 | AJ10: =IFERROR(AI10/AI$2,0) -> 7.3987956 | AK10: =IFERROR(AL10/AI$2,0) -> 0 | AM10: 8444.9705 | AN10: =IFERROR(AM10/AM$2,0) -> 7.3987956 | AO10: =IFERROR(AP10/AM$2,0) -> 0 | AQ10: 8502.474 | AR10: =IFERROR(AQ10/AQ$2,0) -> 7.3987956 | AS10: =IFERROR(AT10/AQ$2,0) -> 0 | AU10: 8536.1755 | AV10: =IFERROR(AU10/AU$2,0) -> 7.3987956 | AW10: =IFERROR(AX10/AU$2,0) -> 0 | AY10: 8579.1699 | AZ10: =IFERROR(AY10/AY$2,0) -> 7.3987956 | BA10: =IFERROR(BB10/AY$2,0) -> 0 | BC10: =IF($E10*BC$2/$C$2-BF10>0,$E10*BC$2/$C$2-BF10,0) -> 8650.0504 | BD10: =IFERROR(BC10/BC$2,0) -> 7.3987956 | BE10: =IFERROR(BF10/BC$2,0) -> 0 | BG10: =IF($E10*BG$2/$C$2-BJ10>0,$E10*BG$2/$C$2-BJ10,0) -> 8684.5213 | BH10: =IFERROR(BG10/BG$2,0) -> 7.3987956 | BI10: =IFERROR(BJ10/BG$2,0) -> 0 | BK10: =IF($E10*BK$2/$C$2-BN10>0,$E10*BK$2/$C$2-BN10,0) -> 8718.6372 | BL10: =IFERROR(BK10/BK$2,0) -> 7.3987956 | BM10: =IFERROR(BN10/BK$2,0) -> 0 | BO10: =IF($E10*BO$2/$C$2-BR10>0,$E10*BO$2/$C$2-BR10,0) -> 8763.5923 | BP10: =IFERROR(BO10/BO$2,0) -> 7.3987956 | BQ10: =IFERROR(BR10/BO$2,0) -> 0 | BS10: =IF($E10*BS$2/$C$2-BV10>0,$E10*BS$2/$C$2-BV10,0) -> 8814.385 | BT10: =IFERROR(BS10/BS$2,0) -> 7.3987956 | BU10: =IFERROR(BV10/BS$2,0) -> 0 | BW10: =IF($E10*BW$2/$C$2-BZ10>0,$E10*BW$2/$C$2-BZ10,0) -> 8874.922 | BX10: =IFERROR(BW10/BW$2,0) -> 7.3987956 | BY10: =IFERROR(BZ10/BW$2,0) -> 0 | CA10: =IF($E10*CA$2/$C$2-CD10>0,$E10*CA$2/$C$2-CD10,0) -> 8956.0276 | CB10: =IFERROR(CA10/CA$2,0) -> 7.3987956 | CC10: =IFERROR(CD10/CA$2,0) -> 0 | CE10: =IF($E10*CE$2/$C$2-CH10>0,$E10*CE$2/$C$2-CH10,0) -> 9002.159 | CF10: =IFERROR(CE10/CE$2,0) -> 7.3987956 | CG10: =IFERROR(CH10/CE$2,0) -> 0 | CI10: =IF($E10*CI$2/$C$2-CL10>0,$E10*CI$2/$C$2-CL10,0) -> 9017.26 | CJ10: =IFERROR(CI10/CI$2,0) -> 7.3987956 | CK10: =IFERROR(CL10/CI$2,0) -> 0 | CM10: =IF($E10*CM$2/$C$2-CP10>0,$E10*CM$2/$C$2-CP10,0) -> 9043.9622 | CN10: =IFERROR(CM10/CM$2,0) -> 7.3987956 | CO10: =IFERROR(CP10/CM$2,0) -> 0 | CQ10: =IF($E10*CQ$2/$C$2-CT10>0,$E10*CQ$2/$C$2-CT10,0) -> 9068.2081 | CR10: =IFERROR(CQ10/CQ$2,0) -> 7.3987956 | CS10: =IFERROR(CT10/CQ$2,0) -> 0 | CU10: =IF($E10*CU$2/$C$2-CX10>0,$E10*CU$2/$C$2-CX10,0) -> 9086.9122 | CV10: =IFERROR(CU10/CU$2,0) -> 7.3987956 | CW10: =IFERROR(CX10/CU$2,0) -> 0 | CY10: =IF($E10*CY$2/$C$2-DB10>0,$E10*CY$2/$C$2-DB10,0) -> 9152.5766 | CZ10: =IFERROR(CY10/CY$2,0) -> 7.3987956 | DA10: =IFERROR(DB10/CY$2,0) -> 0 | DC10: =IF($E10*DC$2/$C$2-DF10>0,$E10*DC$2/$C$2-DF10,0) -> 9178.0654 | DD10: =IFERROR(DC10/DC$2,0) -> 7.3987956 | DE10: =IFERROR(DF10/DC$2,0) -> 0 | DG10: =IF($E10*DG$2/$C$2-DJ10>0,$E10*DG$2/$C$2-DJ10,0) -> 9227.6373 | DH10: =IFERROR(DG10/DG$2,0) -> 7.3987956 | DI10: =IFERROR(DJ10/DG$2,0) -> 0 | DK10: =IF($E10*DK$2/$C$2-DN10>0,$E10*DK$2/$C$2-DN10,0) -> 9319.9077 | DL10: =IFERROR(DK10/DK$2,0) -> 7.3987956 | DM10: =IFERROR(DN10/DK$2,0) -> 0 | DO10: =IF($E10*DO$2/$C$2-DR10>0,$E10*DO$2/$C$2-DR10,0) -> 9401.6126 | DP10: =IFERROR(DO10/DO$2,0) -> 7.3987956 | DQ10: =IFERROR(DR10/DO$2,0) -> 0 | DS10: =IF($E10*DS$2/$C$2-DV10>0,$E10*DS$2/$C$2-DV10,0) -> 9475.201 | DT10: =IFERROR(DS10/DS$2,0) -> 7.3987956 | DU10: =IFERROR(DV10/DS$2,0) -> 0 | DW10: =IF($E10*DW$2/$C$2-DZ10>0,$E10*DW$2/$C$2-DZ10,0) -> 0 | DX10: =IFERROR(DW10/DW$2,0) -> 0 | DY10: =IFERROR(DZ10/DW$2,0) -> 0 | EA10: =IF($E10*EA$2/$C$2-ED10>0,$E10*EA$2/$C$2-ED10,0) -> 0 | EB10: =IFERROR(EA10/EA$2,0) -> 0 | EC10: =IFERROR(ED10/EA$2,0) -> 0 | EE10: =IF($E10*EE$2/$C$2-EH10>0,$E10*EE$2/$C$2-EH10,0) -> 0 | EF10: =IFERROR(EE10/EE$2,0) -> 0 | EG10: =IFERROR(EH10/EE$2,0) -> 0 | EI10: =IF($E10*EI$2/$C$2-EL10>0,$E10*EI$2/$C$2-EL10,0) -> 0 | EJ10: =IFERROR(EI10/EI$2,0) -> 0 | EK10: =IFERROR(EL10/EI$2,0) -> 0 | EM10: =IF($E10*EM$2/$C$2-EP10>0,$E10*EM$2/$C$2-EP10,0) -> 0 | EN10: =IFERROR(EM10/EM$2,0) -> 0 | EO10: =IFERROR(EP10/EM$2,0) -> 0 | EQ10: =IF($E10*EQ$2/$C$2-ET10>0,$E10*EQ$2/$C$2-ET10,0) -> 0 | ER10: =IFERROR(EQ10/EQ$2,0) -> 0 | ES10: =IFERROR(ET10/EQ$2,0) -> 0 | EU10: =IF($E10*EU$2/$C$2-EX10>0,$E10*EU$2/$C$2-EX10,0) -> 0 | EV10: =IFERROR(EU10/EU$2,0) -> 0 | EW10: =IFERROR(EX10/EU$2,0) -> 0 | EY10: =IF($E10*EY$2/$C$2-FB10>0,$E10*EY$2/$C$2-FB10,0) -> 0 | EZ10: =IFERROR(EY10/EY$2,0) -> 0 | FA10: =IFERROR(FB10/EY$2,0) -> 0 | FC10: =IF($E10*FC$2/$C$2-FF10>0,$E10*FC$2/$C$2-FF10,0) -> 0 | FD10: =IFERROR(FC10/FC$2,0) -> 0 | FE10: =IFERROR(FF10/FC$2,0) -> 0
A11: 01.01.04.01.008 | B11: ALMOXARIFE | C11: 36 | D11: =E11*C11 -> 264448.08 | E11: 7345.78 | F11: =K11*$C$1 -> 81002.141 | G11: =D11/$C$2 -> 245.2199 | H11: =E11/$C$2 -> 6.8116638 | I11: =SUMIFS($S11:$FF11,$S$4:$FF$4,$T$4) -> 88.55163 | J11: =SUMIFS($S11:$FF11,$S$4:$FF$4,$U$4) -> 93.41702 | K11: =G11-I11-J11 -> 63.251248 | O11: 30 | P11: =Q11*O11 -> 246060 | Q11: 8202 | R11: =P11-SUMIFS(S11:ET11,$S$4:$ET$4,$V$4) -> 135200.69 | S11: =IF($E11*S$2/$C$2-V11>0,$E11*S$2/$C$2-V11,0) -> 7502.2916 | T11: =IFERROR(S11/S$2,0) -> 6.8116638 | U11: =IFERROR(V11/S$2,0) -> 0 | W11: =IF($E11*W$2/$C$2-Z11>0,$E11*W$2/$C$2-Z11,0) -> 7566.9888 | X11: =IFERROR(W11/W$2,0) -> 6.8116638 | Y11: =IFERROR(Z11/W$2,0) -> 0 | AA11: =IF($E11*AA$2/$C$2-AD11>0,$E11*AA$2/$C$2-AD11,0) -> 7621.0734 | AB11: =IFERROR(AA11/AA$2,0) -> 6.8116638 | AC11: =IFERROR(AD11/AA$2,0) -> 0 | AE11: =IF($E11*AE$2/$C$2-AH11>0,$E11*AE$2/$C$2-AH11,0) -> 7676.1729 | AF11: =IFERROR(AE11/AE$2,0) -> 6.8116638 | AG11: =IFERROR(AH11/AE$2,0) -> 0 | AI11: =IF($E11*AI$2/$C$2-AL11>0,$E11*AI$2/$C$2-AL11,0) -> 7729.7058 | AJ11: =IFERROR(AI11/AI$2,0) -> 6.8116638 | AK11: =IFERROR(AL11/AI$2,0) -> 0 | AN11: =IFERROR(AM11/AM$2,0) -> 0 | AO11: =IFERROR(AP11/AM$2,0) -> 0 | AR11: =IFERROR(AQ11/AQ$2,0) -> 0 | AS11: =IFERROR(AT11/AQ$2,0) -> 7.1859246 | AT11: =IF($Q11*AQ$2/$R$2>0,$Q11*AQ$2/$R$2,0) -> 8257.849 | AV11: =IFERROR(AU11/AU$2,0) -> 0 | AW11: =IFERROR(AX11/AU$2,0) -> 7.1859246 | AX11: =IF($Q11*AU$2/$R$2>0,$Q11*AU$2/$R$2,0) -> 8290.5809 | AZ11: =IFERROR(AY11/AY$2,0) -> 0 | BA11: =IFERROR(BB11/AY$2,0) -> 7.1859246 | BB11: =IF($Q11*AY$2/$R$2>0,$Q11*AY$2/$R$2,0) -> 8332.3383 | BC11: =IF($E11*BC$2/$C$2-BF11>0,$E11*BC$2/$C$2-BF11,0) -> 0 | BD11: =IFERROR(BC11/BC$2,0) -> 0 | BE11: =IFERROR(BF11/BC$2,0) -> 7.1859246 | BF11: =IF($Q11*BC$2/$R$2>0,$Q11*BC$2/$R$2,0) -> 8401.1795 | BG11: =IF($E11*BG$2/$C$2-BJ11>0,$E11*BG$2/$C$2-BJ11,0) -> 0 | BH11: =IFERROR(BG11/BG$2,0) -> 0 | BI11: =IFERROR(BJ11/BG$2,0) -> 7.1859246 | BJ11: =IF($Q11*BG$2/$R$2>0,$Q11*BG$2/$R$2,0) -> 8434.6587 | BK11: =IF($E11*BK$2/$C$2-BN11>0,$E11*BK$2/$C$2-BN11,0) -> 0 | BL11: =IFERROR(BK11/BK$2,0) -> 0 | BM11: =IFERROR(BN11/BK$2,0) -> 7.1859246 | BN11: =IF($Q11*BK$2/$R$2>0,$Q11*BK$2/$R$2,0) -> 8467.793 | BO11: =IF($E11*BO$2/$C$2-BR11>0,$E11*BO$2/$C$2-BR11,0) -> 0 | BP11: =IFERROR(BO11/BO$2,0) -> 0 | BQ11: =IFERROR(BR11/BO$2,0) -> 7.1859246 | BR11: =IF($Q11*BO$2/$R$2>0,$Q11*BO$2/$R$2,0) -> 8511.4547 | BS11: =IF($E11*BS$2/$C$2-BV11>0,$E11*BS$2/$C$2-BV11,0) -> 0 | BT11: =IFERROR(BS11/BS$2,0) -> 0 | BU11: =IFERROR(BV11/BS$2,0) -> 7.1859246 | BV11: =IF($Q11*BS$2/$R$2>0,$Q11*BS$2/$R$2,0) -> 8560.786 | BW11: =IF($E11*BW$2/$C$2-BZ11>0,$E11*BW$2/$C$2-BZ11,0) -> 0 | BX11: =IFERROR(BW11/BW$2,0) -> 0 | BY11: =IFERROR(BZ11/BW$2,0) -> 7.1859246 | BZ11: =IF($Q11*BW$2/$R$2>0,$Q11*BW$2/$R$2,0) -> 8619.5813 | CA11: =IF($E11*CA$2/$C$2-CD11>0,$E11*CA$2/$C$2-CD11,0) -> 0 | CB11: =IFERROR(CA11/CA$2,0) -> 0 | CC11: =IFERROR(CD11/CA$2,0) -> 7.1859246 | CD11: =IF($Q11*CA$2/$R$2>0,$Q11*CA$2/$R$2,0) -> 8698.3534 | CE11: =IF($E11*CE$2/$C$2-CH11>0,$E11*CE$2/$C$2-CH11,0) -> 0 | CF11: =IFERROR(CE11/CE$2,0) -> 0 | CG11: =IFERROR(CH11/CE$2,0) -> 7.1859246 | CH11: =IF($Q11*CE$2/$R$2>0,$Q11*CE$2/$R$2,0) -> 8743.1576 | CI11: =IF($E11*CI$2/$C$2-CL11>0,$E11*CI$2/$C$2-CL11,0) -> 0 | CJ11: =IFERROR(CI11/CI$2,0) -> 0 | CK11: =IFERROR(CL11/CI$2,0) -> 7.1859246 | CL11: =IF($Q11*CI$2/$R$2>0,$Q11*CI$2/$R$2,0) -> 8757.8241 | CM11: =IF($E11*CM$2/$C$2-CP11>0,$E11*CM$2/$C$2-CP11,0) -> 0 | CN11: =IFERROR(CM11/CM$2,0) -> 0 | CO11: =IFERROR(CP11/CM$2,0) -> 7.1859246 | CP11: =IF($Q11*CM$2/$R$2>0,$Q11*CM$2/$R$2,0) -> 8783.7581 | CQ11: =IF($E11*CQ$2/$C$2-CT11>0,$E11*CQ$2/$C$2-CT11,0) -> 8348.6 | CR11: =IFERROR(CQ11/CQ$2,0) -> 6.8116638 | CS11: =IFERROR(CT11/CQ$2,0) -> 0 | CU11: =IF($E11*CU$2/$C$2-CX11>0,$E11*CU$2/$C$2-CX11,0) -> 8365.8198 | CV11: =IFERROR(CU11/CU$2,0) -> 6.8116638 | CW11: =IFERROR(CX11/CU$2,0) -> 0 | CY11: =IF($E11*CY$2/$C$2-DB11>0,$E11*CY$2/$C$2-DB11,0) -> 8426.2734 | CZ11: =IFERROR(CY11/CY$2,0) -> 6.8116638 | DA11: =IFERROR(DB11/CY$2,0) -> 0 | DC11: =IF($E11*DC$2/$C$2-DF11>0,$E11*DC$2/$C$2-DF11,0) -> 8449.7395 | DD11: =IFERROR(DC11/DC$2,0) -> 6.8116638 | DE11: =IFERROR(DF11/DC$2,0) -> 0 | DG11: =IF($E11*DG$2/$C$2-DJ11>0,$E11*DG$2/$C$2-DJ11,0) -> 8495.3777 | DH11: =IFERROR(DG11/DG$2,0) -> 6.8116638 | DI11: =IFERROR(DJ11/DG$2,0) -> 0 | DK11: =IF($E11*DK$2/$C$2-DN11>0,$E11*DK$2/$C$2-DN11,0) -> 8580.326 | DL11: =IFERROR(DK11/DK$2,0) -> 6.8116638 | DM11: =IFERROR(DN11/DK$2,0) -> 0 | DO11: =IF($E11*DO$2/$C$2-DR11>0,$E11*DO$2/$C$2-DR11,0) -> 8655.5472 | DP11: =IFERROR(DO11/DO$2,0) -> 6.8116638 | DQ11: =IFERROR(DR11/DO$2,0) -> 0 | DS11: =IF($E11*DS$2/$C$2-DV11>0,$E11*DS$2/$C$2-DV11,0) -> 8723.296 | DT11: =IFERROR(DS11/DS$2,0) -> 6.8116638 | DU11: =IFERROR(DV11/DS$2,0) -> 0 | DW11: =IF($E11*DW$2/$C$2-DZ11>0,$E11*DW$2/$C$2-DZ11,0) -> 0 | DX11: =IFERROR(DW11/DW$2,0) -> 0 | DY11: =IFERROR(DZ11/DW$2,0) -> 0 | EA11: =IF($E11*EA$2/$C$2-ED11>0,$E11*EA$2/$C$2-ED11,0) -> 0 | EB11: =IFERROR(EA11/EA$2,0) -> 0 | EC11: =IFERROR(ED11/EA$2,0) -> 0 | EE11: =IF($E11*EE$2/$C$2-EH11>0,$E11*EE$2/$C$2-EH11,0) -> 0 | EF11: =IFERROR(EE11/EE$2,0) -> 0 | EG11: =IFERROR(EH11/EE$2,0) -> 0 | EI11: =IF($E11*EI$2/$C$2-EL11>0,$E11*EI$2/$C$2-EL11,0) -> 0 | EJ11: =IFERROR(EI11/EI$2,0) -> 0 | EK11: =IFERROR(EL11/EI$2,0) -> 0 | EM11: =IF($E11*EM$2/$C$2-EP11>0,$E11*EM$2/$C$2-EP11,0) -> 0 | EN11: =IFERROR(EM11/EM$2,0) -> 0 | EO11: =IFERROR(EP11/EM$2,0) -> 0 | EQ11: =IF($E11*EQ$2/$C$2-ET11>0,$E11*EQ$2/$C$2-ET11,0) -> 0 | ER11: =IFERROR(EQ11/EQ$2,0) -> 0 | ES11: =IFERROR(ET11/EQ$2,0) -> 0 | EU11: =IF($E11*EU$2/$C$2-EX11>0,$E11*EU$2/$C$2-EX11,0) -> 0 | EV11: =IFERROR(EU11/EU$2,0) -> 0 | EW11: =IFERROR(EX11/EU$2,0) -> 0 | EY11: =IF($E11*EY$2/$C$2-FB11>0,$E11*EY$2/$C$2-FB11,0) -> 0 | EZ11: =IFERROR(EY11/EY$2,0) -> 0 | FA11: =IFERROR(FB11/EY$2,0) -> 0 | FC11: =IF($E11*FC$2/$C$2-FF11>0,$E11*FC$2/$C$2-FF11,0) -> 0 | FD11: =IFERROR(FC11/FC$2,0) -> 0 | FE11: =IFERROR(FF11/FC$2,0) -> 0
A12: 01.01.04.01.010 | B12: ENGENHEIRO DE SEGURANÇA | C12: 36 | D12: =E12*C12 -> 167151.6 | E12: 4643.1 | F12: =K12*$C$1 -> 49624.168 | G12: =D12/$C$2 -> 154.9979 | H12: =E12/$C$2 -> 4.3054973 | I12: =SUMIFS($S12:$FF12,$S$4:$FF$4,$T$4) -> 116.24843 | J12: =SUMIFS($S12:$FF12,$S$4:$FF$4,$U$4) -> 0 | K12: =G12-I12-J12 -> 38.749476 | R12: =M12-SUMIFS(S12:ET12,$S$4:$ET$4,$V$4) -> 0 | S12: =IF($E12*S$2/$C$2-V12>0,$E12*S$2/$C$2-V12,0) -> 4742.0274 | T12: =IFERROR(S12/S$2,0) -> 4.3054973 | U12: =IFERROR(V12/S$2,0) -> 0 | W12: =IF($E12*W$2/$C$2-Z12>0,$E12*W$2/$C$2-Z12,0) -> 4782.921 | X12: =IFERROR(W12/W$2,0) -> 4.3054973 | Y12: =IFERROR(Z12/W$2,0) -> 0 | AA12: =IF($E12*AA$2/$C$2-AD12>0,$E12*AA$2/$C$2-AD12,0) -> 4817.1067 | AB12: =IFERROR(AA12/AA$2,0) -> 4.3054973 | AC12: =IFERROR(AD12/AA$2,0) -> 0 | AE12: =IF($E12*AE$2/$C$2-AH12>0,$E12*AE$2/$C$2-AH12,0) -> 4851.9338 | AF12: =IFERROR(AE12/AE$2,0) -> 4.3054973 | AG12: =IFERROR(AH12/AE$2,0) -> 0 | AI12: =IF($E12*AI$2/$C$2-AL12>0,$E12*AI$2/$C$2-AL12,0) -> 4885.7707 | AJ12: =IFERROR(AI12/AI$2,0) -> 4.3054973 | AK12: =IFERROR(AL12/AI$2,0) -> 0 | AM12: 4914.2861 | AN12: =IFERROR(AM12/AM$2,0) -> 4.3054973 | AO12: =IFERROR(AP12/AM$2,0) -> 0 | AQ12: 4947.7484 | AR12: =IFERROR(AQ12/AQ$2,0) -> 4.3054973 | AS12: =IFERROR(AT12/AQ$2,0) -> 0 | AT12: =IF($N12*AQ$2/$R$2>0,$N12*AQ$2/$R$2,0) -> 0 | AU12: 4967.3599 | AV12: =IFERROR(AU12/AU$2,0) -> 4.3054973 | AW12: =IFERROR(AX12/AU$2,0) -> 0 | AY12: 4992.3792 | AZ12: =IFERROR(AY12/AY$2,0) -> 4.3054973 | BA12: =IFERROR(BB12/AY$2,0) -> 0 | BC12: =IF($E12*BC$2/$C$2-BF12>0,$E12*BC$2/$C$2-BF12,0) -> 5033.6258 | BD12: =IFERROR(BC12/BC$2,0) -> 4.3054973 | BE12: =IFERROR(BF12/BC$2,0) -> 0 | BG12: =IF($E12*BG$2/$C$2-BJ12>0,$E12*BG$2/$C$2-BJ12,0) -> 5053.6851 | BH12: =IFERROR(BG12/BG$2,0) -> 4.3054973 | BI12: =IFERROR(BJ12/BG$2,0) -> 0 | BK12: =IF($E12*BK$2/$C$2-BN12>0,$E12*BK$2/$C$2-BN12,0) -> 5073.5378 | BL12: =IFERROR(BK12/BK$2,0) -> 4.3054973 | BM12: =IFERROR(BN12/BK$2,0) -> 0 | BO12: =IF($E12*BO$2/$C$2-BR12>0,$E12*BO$2/$C$2-BR12,0) -> 5099.698 | BP12: =IFERROR(BO12/BO$2,0) -> 4.3054973 | BQ12: =IFERROR(BR12/BO$2,0) -> 0 | BS12: =IF($E12*BS$2/$C$2-BV12>0,$E12*BS$2/$C$2-BV12,0) -> 5129.2552 | BT12: =IFERROR(BS12/BS$2,0) -> 4.3054973 | BU12: =IFERROR(BV12/BS$2,0) -> 0 | BW12: =IF($E12*BW$2/$C$2-BZ12>0,$E12*BW$2/$C$2-BZ12,0) -> 5164.4828 | BX12: =IFERROR(BW12/BW$2,0) -> 4.3054973 | BY12: =IFERROR(BZ12/BW$2,0) -> 0 | CA12: =IF($E12*CA$2/$C$2-CD12>0,$E12*CA$2/$C$2-CD12,0) -> 5211.6797 | CB12: =IFERROR(CA12/CA$2,0) -> 4.3054973 | CC12: =IFERROR(CD12/CA$2,0) -> 0 | CE12: =IF($E12*CE$2/$C$2-CH12>0,$E12*CE$2/$C$2-CH12,0) -> 5238.5244 | CF12: =IFERROR(CE12/CE$2,0) -> 4.3054973 | CG12: =IFERROR(CH12/CE$2,0) -> 0 | CI12: =IF($E12*CI$2/$C$2-CL12>0,$E12*CI$2/$C$2-CL12,0) -> 5247.312 | CJ12: =IFERROR(CI12/CI$2,0) -> 4.3054973 | CK12: =IFERROR(CL12/CI$2,0) -> 0 | CM12: =IF($E12*CM$2/$C$2-CP12>0,$E12*CM$2/$C$2-CP12,0) -> 5262.8505 | CN12: =IFERROR(CM12/CM$2,0) -> 4.3054973 | CO12: =IFERROR(CP12/CM$2,0) -> 0 | CQ12: =IF($E12*CQ$2/$C$2-CT12>0,$E12*CQ$2/$C$2-CT12,0) -> 5276.9596 | CR12: =IFERROR(CQ12/CQ$2,0) -> 4.3054973 | CS12: =IFERROR(CT12/CQ$2,0) -> 0 | CU12: =IF($E12*CU$2/$C$2-CX12>0,$E12*CU$2/$C$2-CX12,0) -> 5287.8439 | CV12: =IFERROR(CU12/CU$2,0) -> 4.3054973 | CW12: =IFERROR(CX12/CU$2,0) -> 0 | CY12: =IF($E12*CY$2/$C$2-DB12>0,$E12*CY$2/$C$2-DB12,0) -> 5326.0552 | CZ12: =IFERROR(CY12/CY$2,0) -> 4.3054973 | DA12: =IFERROR(DB12/CY$2,0) -> 0 | DC12: =IF($E12*DC$2/$C$2-DF12>0,$E12*DC$2/$C$2-DF12,0) -> 5340.8876 | DD12: =IFERROR(DC12/DC$2,0) -> 4.3054973 | DE12: =IFERROR(DF12/DC$2,0) -> 0 | DG12: =IF($E12*DG$2/$C$2-DJ12>0,$E12*DG$2/$C$2-DJ12,0) -> 5369.7345 | DH12: =IFERROR(DG12/DG$2,0) -> 4.3054973 | DI12: =IFERROR(DJ12/DG$2,0) -> 0 | DK12: =IF($E12*DK$2/$C$2-DN12>0,$E12*DK$2/$C$2-DN12,0) -> 5423.4283 | DL12: =IFERROR(DK12/DK$2,0) -> 4.3054973 | DM12: =IFERROR(DN12/DK$2,0) -> 0 | DO12: =IF($E12*DO$2/$C$2-DR12>0,$E12*DO$2/$C$2-DR12,0) -> 5470.9739 | DP12: =IFERROR(DO12/DO$2,0) -> 4.3054973 | DQ12: =IFERROR(DR12/DO$2,0) -> 0 | DS12: =IF($E12*DS$2/$C$2-DV12>0,$E12*DS$2/$C$2-DV12,0) -> 5513.7964 | DT12: =IFERROR(DS12/DS$2,0) -> 4.3054973 | DU12: =IFERROR(DV12/DS$2,0) -> 0 | DW12: =IF($E12*DW$2/$C$2-DZ12>0,$E12*DW$2/$C$2-DZ12,0) -> 0 | DX12: =IFERROR(DW12/DW$2,0) -> 0 | DY12: =IFERROR(DZ12/DW$2,0) -> 0 | EA12: =IF($E12*EA$2/$C$2-ED12>0,$E12*EA$2/$C$2-ED12,0) -> 0 | EB12: =IFERROR(EA12/EA$2,0) -> 0 | EC12: =IFERROR(ED12/EA$2,0) -> 0 | EE12: =IF($E12*EE$2/$C$2-EH12>0,$E12*EE$2/$C$2-EH12,0) -> 0 | EF12: =IFERROR(EE12/EE$2,0) -> 0 | EG12: =IFERROR(EH12/EE$2,0) -> 0 | EI12: =IF($E12*EI$2/$C$2-EL12>0,$E12*EI$2/$C$2-EL12,0) -> 0 | EJ12: =IFERROR(EI12/EI$2,0) -> 0 | EK12: =IFERROR(EL12/EI$2,0) -> 0 | EM12: =IF($E12*EM$2/$C$2-EP12>0,$E12*EM$2/$C$2-EP12,0) -> 0 | EN12: =IFERROR(EM12/EM$2,0) -> 0 | EO12: =IFERROR(EP12/EM$2,0) -> 0 | EQ12: =IF($E12*EQ$2/$C$2-ET12>0,$E12*EQ$2/$C$2-ET12,0) -> 0 | ER12: =IFERROR(EQ12/EQ$2,0) -> 0 | ES12: =IFERROR(ET12/EQ$2,0) -> 0 | EU12: =IF($E12*EU$2/$C$2-EX12>0,$E12*EU$2/$C$2-EX12,0) -> 0 | EV12: =IFERROR(EU12/EU$2,0) -> 0 | EW12: =IFERROR(EX12/EU$2,0) -> 0 | EY12: =IF($E12*EY$2/$C$2-FB12>0,$E12*EY$2/$C$2-FB12,0) -> 0 | EZ12: =IFERROR(EY12/EY$2,0) -> 0 | FA12: =IFERROR(FB12/EY$2,0) -> 0 | FC12: =IF($E12*FC$2/$C$2-FF12>0,$E12*FC$2/$C$2-FF12,0) -> 0 | FD12: =IFERROR(FC12/FC$2,0) -> 0 | FE12: =IFERROR(FF12/FC$2,0) -> 0
A13: 01.01.04.01.011 | B13: TÉCNICO SEGURANCA | C13: 36 | D13: =E13*C13 -> 264448.08 | E13: 7345.78 | F13: =K13*$C$1 -> 78509.664 | G13: =D13/$C$2 -> 245.2199 | H13: =E13/$C$2 -> 6.8116638 | I13: =SUMIFS($S13:$FF13,$S$4:$FF$4,$T$4) -> 183.91492 | J13: =SUMIFS($S13:$FF13,$S$4:$FF$4,$U$4) -> 0 | K13: =G13-I13-J13 -> 61.304974 | S13: =IF($E13*S$2/$C$2-V13>0,$E13*S$2/$C$2-V13,0) -> 7502.2916 | T13: =IFERROR(S13/S$2,0) -> 6.8116638 | U13: =IFERROR(V13/S$2,0) -> 0 | W13: =IF($E13*W$2/$C$2-Z13>0,$E13*W$2/$C$2-Z13,0) -> 7566.9888 | X13: =IFERROR(W13/W$2,0) -> 6.8116638 | Y13: =IFERROR(Z13/W$2,0) -> 0 | AA13: =IF($E13*AA$2/$C$2-AD13>0,$E13*AA$2/$C$2-AD13,0) -> 7621.0734 | AB13: =IFERROR(AA13/AA$2,0) -> 6.8116638 | AC13: =IFERROR(AD13/AA$2,0) -> 0 | AE13: =IF($E13*AE$2/$C$2-AH13>0,$E13*AE$2/$C$2-AH13,0) -> 7676.1729 | AF13: =IFERROR(AE13/AE$2,0) -> 6.8116638 | AG13: =IFERROR(AH13/AE$2,0) -> 0 | AI13: =IF($E13*AI$2/$C$2-AL13>0,$E13*AI$2/$C$2-AL13,0) -> 7729.7058 | AJ13: =IFERROR(AI13/AI$2,0) -> 6.8116638 | AK13: =IFERROR(AL13/AI$2,0) -> 0 | AM13: 7774.8195 | AN13: =IFERROR(AM13/AM$2,0) -> 6.8116638 | AO13: =IFERROR(AP13/AM$2,0) -> 0 | AQ13: 7827.7597 | AR13: =IFERROR(AQ13/AQ$2,0) -> 6.8116638 | AS13: =IFERROR(AT13/AQ$2,0) -> 0 | AU13: 7858.7868 | AV13: =IFERROR(AU13/AU$2,0) -> 6.8116638 | AW13: =IFERROR(AX13/AU$2,0) -> 0 | AY13: 7898.3694 | AZ13: =IFERROR(AY13/AY$2,0) -> 6.8116638 | BA13: =IFERROR(BB13/AY$2,0) -> 0 | BC13: =IF($E13*BC$2/$C$2-BF13>0,$E13*BC$2/$C$2-BF13,0) -> 7963.6252 | BD13: =IFERROR(BC13/BC$2,0) -> 6.8116638 | BE13: =IFERROR(BF13/BC$2,0) -> 0 | BG13: =IF($E13*BG$2/$C$2-BJ13>0,$E13*BG$2/$C$2-BJ13,0) -> 7995.3607 | BH13: =IFERROR(BG13/BG$2,0) -> 6.8116638 | BI13: =IFERROR(BJ13/BG$2,0) -> 0 | BK13: =IF($E13*BK$2/$C$2-BN13>0,$E13*BK$2/$C$2-BN13,0) -> 8026.7693 | BL13: =IFERROR(BK13/BK$2,0) -> 6.8116638 | BM13: =IFERROR(BN13/BK$2,0) -> 0 | BO13: =IF($E13*BO$2/$C$2-BR13>0,$E13*BO$2/$C$2-BR13,0) -> 8068.1569 | BP13: =IFERROR(BO13/BO$2,0) -> 6.8116638 | BQ13: =IFERROR(BR13/BO$2,0) -> 0 | BS13: =IF($E13*BS$2/$C$2-BV13>0,$E13*BS$2/$C$2-BV13,0) -> 8114.919 | BT13: =IFERROR(BS13/BS$2,0) -> 6.8116638 | BU13: =IFERROR(BV13/BS$2,0) -> 0 | BW13: =IF($E13*BW$2/$C$2-BZ13>0,$E13*BW$2/$C$2-BZ13,0) -> 8170.6521 | BX13: =IFERROR(BW13/BW$2,0) -> 6.8116638 | BY13: =IFERROR(BZ13/BW$2,0) -> 0 | CA13: =IF($E13*CA$2/$C$2-CD13>0,$E13*CA$2/$C$2-CD13,0) -> 8245.3215 | CB13: =IFERROR(CA13/CA$2,0) -> 6.8116638 | CC13: =IFERROR(CD13/CA$2,0) -> 0 | CE13: =IF($E13*CE$2/$C$2-CH13>0,$E13*CE$2/$C$2-CH13,0) -> 8287.7922 | CF13: =IFERROR(CE13/CE$2,0) -> 6.8116638 | CG13: =IFERROR(CH13/CE$2,0) -> 0 | CI13: =IF($E13*CI$2/$C$2-CL13>0,$E13*CI$2/$C$2-CL13,0) -> 8301.6948 | CJ13: =IFERROR(CI13/CI$2,0) -> 6.8116638 | CK13: =IFERROR(CL13/CI$2,0) -> 0 | CM13: =IF($E13*CM$2/$C$2-CP13>0,$E13*CM$2/$C$2-CP13,0) -> 8326.2781 | CN13: =IFERROR(CM13/CM$2,0) -> 6.8116638 | CO13: =IFERROR(CP13/CM$2,0) -> 0 | CQ13: =IF($E13*CQ$2/$C$2-CT13>0,$E13*CQ$2/$C$2-CT13,0) -> 8348.6 | CR13: =IFERROR(CQ13/CQ$2,0) -> 6.8116638 | CS13: =IFERROR(CT13/CQ$2,0) -> 0 | CU13: =IF($E13*CU$2/$C$2-CX13>0,$E13*CU$2/$C$2-CX13,0) -> 8365.8198 | CV13: =IFERROR(CU13/CU$2,0) -> 6.8116638 | CW13: =IFERROR(CX13/CU$2,0) -> 0 | CY13: =IF($E13*CY$2/$C$2-DB13>0,$E13*CY$2/$C$2-DB13,0) -> 8426.2734 | CZ13: =IFERROR(CY13/CY$2,0) -> 6.8116638 | DA13: =IFERROR(DB13/CY$2,0) -> 0 | DC13: =IF($E13*DC$2/$C$2-DF13>0,$E13*DC$2/$C$2-DF13,0) -> 8449.7395 | DD13: =IFERROR(DC13/DC$2,0) -> 6.8116638 | DE13: =IFERROR(DF13/DC$2,0) -> 0 | DG13: =IF($E13*DG$2/$C$2-DJ13>0,$E13*DG$2/$C$2-DJ13,0) -> 8495.3777 | DH13: =IFERROR(DG13/DG$2,0) -> 6.8116638 | DI13: =IFERROR(DJ13/DG$2,0) -> 0 | DK13: =IF($E13*DK$2/$C$2-DN13>0,$E13*DK$2/$C$2-DN13,0) -> 8580.326 | DL13: =IFERROR(DK13/DK$2,0) -> 6.8116638 | DM13: =IFERROR(DN13/DK$2,0) -> 0 | DO13: =IF($E13*DO$2/$C$2-DR13>0,$E13*DO$2/$C$2-DR13,0) -> 8655.5472 | DP13: =IFERROR(DO13/DO$2,0) -> 6.8116638 | DQ13: =IFERROR(DR13/DO$2,0) -> 0 | DS13: =IF($E13*DS$2/$C$2-DV13>0,$E13*DS$2/$C$2-DV13,0) -> 8723.296 | DT13: =IFERROR(DS13/DS$2,0) -> 6.8116638 | DU13: =IFERROR(DV13/DS$2,0) -> 0 | DW13: =IF($E13*DW$2/$C$2-DZ13>0,$E13*DW$2/$C$2-DZ13,0) -> 0 | DX13: =IFERROR(DW13/DW$2,0) -> 0 | DY13: =IFERROR(DZ13/DW$2,0) -> 0 | EA13: =IF($E13*EA$2/$C$2-ED13>0,$E13*EA$2/$C$2-ED13,0) -> 0 | EB13: =IFERROR(EA13/EA$2,0) -> 0 | EC13: =IFERROR(ED13/EA$2,0) -> 0 | EE13: =IF($E13*EE$2/$C$2-EH13>0,$E13*EE$2/$C$2-EH13,0) -> 0 | EF13: =IFERROR(EE13/EE$2,0) -> 0 | EG13: =IFERROR(EH13/EE$2,0) -> 0 | EI13: =IF($E13*EI$2/$C$2-EL13>0,$E13*EI$2/$C$2-EL13,0) -> 0 | EJ13: =IFERROR(EI13/EI$2,0) -> 0 | EK13: =IFERROR(EL13/EI$2,0) -> 0 | EM13: =IF($E13*EM$2/$C$2-EP13>0,$E13*EM$2/$C$2-EP13,0) -> 0 | EN13: =IFERROR(EM13/EM$2,0) -> 0 | EO13: =IFERROR(EP13/EM$2,0) -> 0 | EQ13: =IF($E13*EQ$2/$C$2-ET13>0,$E13*EQ$2/$C$2-ET13,0) -> 0 | ER13: =IFERROR(EQ13/EQ$2,0) -> 0 | ES13: =IFERROR(ET13/EQ$2,0) -> 0 | EU13: =IF($E13*EU$2/$C$2-EX13>0,$E13*EU$2/$C$2-EX13,0) -> 0 | EV13: =IFERROR(EU13/EU$2,0) -> 0 | EW13: =IFERROR(EX13/EU$2,0) -> 0 | EY13: =IF($E13*EY$2/$C$2-FB13>0,$E13*EY$2/$C$2-FB13,0) -> 0 | EZ13: =IFERROR(EY13/EY$2,0) -> 0 | FA13: =IFERROR(FB13/EY$2,0) -> 0 | FC13: =IF($E13*FC$2/$C$2-FF13>0,$E13*FC$2/$C$2-FF13,0) -> 0 | FD13: =IFERROR(FC13/FC$2,0) -> 0 | FE13: =IFERROR(FF13/FC$2,0) -> 0
A14: 01.01.04.02.003 | B14: OPERADOR DE ELEVADOR CREMALHEIRA | C14: 33 | D14: =E14*C14 -> 242410.74 | E14: 7345.78 | F14: =K14*$C$1 -> 252975.58 | G14: =D14/$C$2 -> 224.78491 | H14: =E14/$C$2 -> 6.8116638 | I14: =SUMIFS($S14:$FF14,$S$4:$FF$4,$T$4) -> 27.246655 | J14: =SUMIFS($S14:$FF14,$S$4:$FF$4,$U$4) -> 0 | K14: =G14-I14-J14 -> 197.53825 | DG14: =IF($E14*DG$2/$C$2-DJ14>0,$E14*DG$2/$C$2-DJ14,0) -> 8495.3777 | DH14: =IFERROR(DG14/DG$2,0) -> 6.8116638 | DI14: =IFERROR(DJ14/DG$2,0) -> 0 | DK14: =IF($E14*DK$2/$C$2-DN14>0,$E14*DK$2/$C$2-DN14,0) -> 8580.326 | DL14: =IFERROR(DK14/DK$2,0) -> 6.8116638 | DM14: =IFERROR(DN14/DK$2,0) -> 0 | DO14: =IF($E14*DO$2/$C$2-DR14>0,$E14*DO$2/$C$2-DR14,0) -> 8655.5472 | DP14: =IFERROR(DO14/DO$2,0) -> 6.8116638 | DQ14: =IFERROR(DR14/DO$2,0) -> 0 | DS14: =IF($E14*DS$2/$C$2-DV14>0,$E14*DS$2/$C$2-DV14,0) -> 8723.296 | DT14: =IFERROR(DS14/DS$2,0) -> 6.8116638 | DU14: =IFERROR(DV14/DS$2,0) -> 0 | DW14: =IF($E14*DW$2/$C$2-DZ14>0,$E14*DW$2/$C$2-DZ14,0) -> 0 | DX14: =IFERROR(DW14/DW$2,0) -> 0 | DY14: =IFERROR(DZ14/DW$2,0) -> 0 | EA14: =IF($E14*EA$2/$C$2-ED14>0,$E14*EA$2/$C$2-ED14,0) -> 0 | EB14: =IFERROR(EA14/EA$2,0) -> 0 | EC14: =IFERROR(ED14/EA$2,0) -> 0 | EE14: =IF($E14*EE$2/$C$2-EH14>0,$E14*EE$2/$C$2-EH14,0) -> 0 | EF14: =IFERROR(EE14/EE$2,0) -> 0 | EG14: =IFERROR(EH14/EE$2,0) -> 0 | EI14: =IF($E14*EI$2/$C$2-EL14>0,$E14*EI$2/$C$2-EL14,0) -> 0 | EJ14: =IFERROR(EI14/EI$2,0) -> 0 | EK14: =IFERROR(EL14/EI$2,0) -> 0 | EM14: =IF($E14*EM$2/$C$2-EP14>0,$E14*EM$2/$C$2-EP14,0) -> 0 | EN14: =IFERROR(EM14/EM$2,0) -> 0 | EO14: =IFERROR(EP14/EM$2,0) -> 0 | EQ14: =IF($E14*EQ$2/$C$2-ET14>0,$E14*EQ$2/$C$2-ET14,0) -> 0 | ER14: =IFERROR(EQ14/EQ$2,0) -> 0 | ES14: =IFERROR(ET14/EQ$2,0) -> 0 | EU14: =IF($E14*EU$2/$C$2-EX14>0,$E14*EU$2/$C$2-EX14,0) -> 0 | EV14: =IFERROR(EU14/EU$2,0) -> 0 | EW14: =IFERROR(EX14/EU$2,0) -> 0 | EY14: =IF($E14*EY$2/$C$2-FB14>0,$E14*EY$2/$C$2-FB14,0) -> 0 | EZ14: =IFERROR(EY14/EY$2,0) -> 0 | FA14: =IFERROR(FB14/EY$2,0) -> 0 | FC14: =IF($E14*FC$2/$C$2-FF14>0,$E14*FC$2/$C$2-FF14,0) -> 0 | FD14: =IFERROR(FC14/FC$2,0) -> 0 | FE14: =IFERROR(FF14/FC$2,0) -> 0
D15: =SUM(D5:D14) -> 4082685.9 | E15: =SUM(E5:E14) -> 114020.09 | F15: =SUM(F5:F14) -> 1368221.6 | G15: =SUM(G5:G14) -> 3785.8313 | H15: =SUM(H5:H14) -> 105.72962 | I15: =SUM(I5:I14) -> 2202.7842 | J15: =SUM(J5:J14) -> 514.65896 | K15: =SUM(K5:K14) -> 1068.3881 | ... FF15: =SUM(FF5:FF14) -> 0
CM16: cobrar mestre pie | CQ16: cobrar mestre pie

Sheet Lior
A1: INCC DI - Vigente | B1: ='IND. FIN.'!V1 -> 46204 | C1: =VLOOKUP(B1,'IND. FIN.'!$C$4:$D$97,2,0) -> 1280.641 | D1: Contrato Piemonte | L1: Contratos Terceiro
A2: INCC - Base | B2: 44682 | C2: ='IND. FIN.'!D37 -> 1084.242 | D2: R$ | G2: INCC | L2: Soares | P2: =IF(P3>$B$1,0,VLOOKUP(P$3,'IND. FIN.'!$C$4:$D$97,2,0)) -> 1110.887 | T2: =IF(T3>$B$1,0,VLOOKUP(T$3,'IND. FIN.'!$C$4:$D$97,2,0)) -> 1118.827 | X2: =IF(X3>$B$1,0,VLOOKUP(X$3,'IND. FIN.'!$C$4:$D$97,2,0)) -> 1126.916 | AB2: =IF(AB3>$B$1,0,VLOOKUP(AB$3,'IND. FIN.'!$C$4:$D$97,2,0)) -> 1134.775 | AF2: =IF(AF3>$B$1,0,VLOOKUP(AF$3,'IND. FIN.'!$C$4:$D$97,2,0)) -> 1141.398 | AJ2: =IF(AJ3>$B$1,0,VLOOKUP(AJ$3,'IND. FIN.'!$C$4:$D$97,2,0)) -> 1149.17 | AN2: =IF(AN3>$B$1,0,VLOOKUP(AN$3,'IND. FIN.'!$C$4:$D$97,2,0)) -> 1153.725 | AR2: =IF(AR3>$B$1,0,VLOOKUP(AR$3,'IND. FIN.'!$C$4:$D$97,2,0)) -> 1159.536 | AV2: =IF(AV3>$B$1,0,VLOOKUP(AV$3,'IND. FIN.'!$C$4:$D$97,2,0)) -> 1169.116 | AZ2: =IF(AZ3>$B$1,0,VLOOKUP(AZ$3,'IND. FIN.'!$C$4:$D$97,2,0)) -> 1173.775 | BD2: =IF(BD3>$B$1,0,VLOOKUP(BD$3,'IND. FIN.'!$C$4:$D$97,2,0)) -> 1178.386 | BH2: =IF(BH3>$B$1,0,VLOOKUP(BH$3,'IND. FIN.'!$C$4:$D$97,2,0)) -> 1184.462 | BL2: =IF(BL3>$B$1,0,VLOOKUP(BL$3,'IND. FIN.'!$C$4:$D$97,2,0)) -> 1191.327 | BP2: =IF(BP3>$B$1,0,VLOOKUP(BP$3,'IND. FIN.'!$C$4:$D$97,2,0)) -> 1199.509 | BT2: =IF(BT3>$B$1,0,VLOOKUP(BT$3,'IND. FIN.'!$C$4:$D$97,2,0)) -> 1210.471 | BX2: =IF(BX3>$B$1,0,VLOOKUP(BX$3,'IND. FIN.'!$C$4:$D$97,2,0)) -> 1216.706 | CB2: =IF(CB3>$B$1,0,VLOOKUP(CB$3,'IND. FIN.'!$C$4:$D$97,2,0)) -> 1218.747 | CF2: =IF(CF3>$B$1,0,VLOOKUP(CF$3,'IND. FIN.'!$C$4:$D$97,2,0)) -> 1222.356 | CJ2: =IF(CJ3>$B$1,0,VLOOKUP(CJ$3,'IND. FIN.'!$C$4:$D$97,2,0)) -> 1225.633 | CN2: =IF(CN3>$B$1,0,VLOOKUP(CN$3,'IND. FIN.'!$C$4:$D$97,2,0)) -> 1228.161 | CR2: =IF(CR3>$B$1,0,VLOOKUP(CR$3,'IND. FIN.'!$C$4:$D$97,2,0)) -> 1237.036 | CV2: =IF(CV3>$B$1,0,VLOOKUP(CV$3,'IND. FIN.'!$C$4:$D$97,2,0)) -> 1240.481 | CZ2: =IF(CZ3>$B$1,0,VLOOKUP(CZ$3,'IND. FIN.'!$C$4:$D$97,2,0)) -> 1247.181 | DD2: =IF(DD3>$B$1,0,VLOOKUP(DD$3,'IND. FIN.'!$C$4:$D$97,2,0)) -> 1259.652
A3: Orçamento base | D3: Valor total | E3: Valor unitário | F3: Saldo | G3: Valor total | H3: Valor unitário | I3: Total medido Piemonte | J3: Total medido Terceiros | K3: Saldo | L3: Prazo | M3: Valor total | N3: Valor unitário | O3: Saldo | P3: 45444 | T3: =EDATE(P3,1) -> 45474 | X3: =EDATE(T3,1) -> 45505 | AB3: =EDATE(X3,1) -> 45536 | AF3: =EDATE(AB3,1) -> 45566 | AJ3: =EDATE(AF3,1) -> 45597 | AN3: =EDATE(AJ3,1) -> 45627 | AR3: =EDATE(AN3,1) -> 45658 | AV3: =EDATE(AR3,1) -> 45689 | AZ3: =EDATE(AV3,1) -> 45717 | BD3: =EDATE(AZ3,1) -> 45748 | BH3: =EDATE(BD3,1) -> 45778 | BL3: =EDATE(BH3,1) -> 45809 | BP3: =EDATE(BL3,1) -> 45839 | BT3: =EDATE(BP3,1) -> 45870 | BX3: =EDATE(BT3,1) -> 45901 | CB3: =EDATE(BX3,1) -> 45931 | CF3: =EDATE(CB3,1) -> 45962 | CJ3: =EDATE(CF3,1) -> 45992 | CN3: =EDATE(CJ3,1) -> 46023 | CR3: =EDATE(CN3,1) -> 46054 | CV3: =EDATE(CR3,1) -> 46082 | CZ3: =EDATE(CV3,1) -> 46113 | DD3: =EDATE(CZ3,1) -> 46143
A4: 01.01.04.01 | B4: PESSOAL | C4: Prazo | P4: Medido Piemonte | Q4: Medido Piemonte INCC | R4: Medido Terceiros INCC | S4: Medido Terceiros | T4: Medido Piemonte | U4: Medido Piemonte INCC | V4: Medido Terceiros INCC | W4: Medido Terceiros | X4: Medido Piemonte | Y4: Medido Piemonte INCC | Z4: Medido Terceiros INCC | AA4: Medido Terceiros | AB4: Medido Piemonte | AC4: Medido Piemonte INCC | AD4: Medido Terceiros INCC | AE4: Medido Terceiros | AF4: Medido Piemonte | AG4: Medido Piemonte INCC | AH4: Medido Terceiros INCC | AI4: Medido Terceiros | AJ4: Medido Piemonte | AK4: Medido Piemonte INCC | AL4: Medido Terceiros INCC | AM4: Medido Terceiros | AN4: Medido Piemonte | AO4: Medido Piemonte INCC | AP4: Medido Terceiros INCC | AQ4: Medido Terceiros | AR4: Medido Piemonte | AS4: Medido Piemonte INCC | AT4: Medido Terceiros INCC | AU4: Medido Terceiros | AV4: Medido Piemonte | AW4: Medido Piemonte INCC | AX4: Medido Terceiros INCC | AY4: Medido Terceiros | AZ4: Medido Piemonte | BA4: Medido Piemonte INCC | BB4: Medido Terceiros INCC | BC4: Medido Terceiros | BD4: Medido Piemonte | BE4: Medido Piemonte INCC | BF4: Medido Terceiros INCC | BG4: Medido Terceiros | BH4: Medido Piemonte | BI4: Medido Piemonte INCC | BJ4: Medido Terceiros INCC | BK4: Medido Terceiros | BL4: Medido Piemonte | BM4: Medido Piemonte INCC | BN4: Medido Terceiros INCC | BO4: Medido Terceiros | BP4: Medido Piemonte | BQ4: Medido Piemonte INCC | BR4: Medido Terceiros INCC | BS4: Medido Terceiros | BT4: Medido Piemonte | BU4: Medido Piemonte INCC | BV4: Medido Terceiros INCC | BW4: Medido Terceiros | BX4: Medido Piemonte | BY4: Medido Piemonte INCC | BZ4: Medido Terceiros INCC | CA4: Medido Terceiros | CB4: Medido Piemonte | CC4: Medido Piemonte INCC | CD4: Medido Terceiros INCC | CE4: Medido Terceiros | CF4: Medido Piemonte | CG4: Medido Piemonte INCC | CH4: Medido Terceiros INCC | CI4: Medido Terceiros | CJ4: Medido Piemonte | CK4: Medido Piemonte INCC | CL4: Medido Terceiros INCC | CM4: Medido Terceiros | CN4: Medido Piemonte | CO4: Medido Piemonte INCC | CP4: Medido Terceiros INCC | CQ4: Medido Terceiros | CR4: Medido Piemonte | CS4: Medido Piemonte INCC | CT4: Medido Terceiros INCC | CU4: Medido Terceiros | CV4: Medido Piemonte | CW4: Medido Piemonte INCC | CX4: Medido Terceiros INCC | CY4: Medido Terceiros | CZ4: Medido Piemonte | DA4: Medido Piemonte INCC | DB4: Medido Terceiros INCC | DC4: Medido Terceiros | DD4: Medido Piemonte | DE4: Medido Piemonte INCC | DF4: Medido Terceiros INCC | DG4: Medido Terceiros
A5: 01.01.04.01.001 | B5: COORDENADOR DE OBRAS | C5: 24 | D5: =E5*C5 -> 212635.92 | E5: 8859.83 | F5: =K5*$C$1 -> -1.0919402e-10 | G5: =D5/$C$2 -> 196.11482 | H5: =E5/$C$2 -> 8.1714507 | I5: =SUMIFS($P5:$DG5,$P$4:$DG$4,$Q$4) -> 196.11482 | J5: =SUMIFS($P5:$DG5,$P$4:$DG$4,$R$4) -> 0 | K5: =G5-I5-J5 -> -8.5265128e-14 | O5: =M5-SUMIFS(P5:DG5,$P$4:$DG$4,$S$4) -> 0 | P5: =IF($E5*P$2/$C$2-S5>0,$E5*P$2/$C$2-S5,0) -> 9077.5583 | Q5: =IFERROR(P5/P$2,0) -> 8.1714507 | R5: =IFERROR(S5/P$2,0) -> 0 | T5: =IF($E5*T$2/$C$2-W5>0,$E5*T$2/$C$2-W5,0) -> 9142.4396 | U5: =IFERROR(T5/T$2,0) -> 8.1714507 | V5: =IFERROR(W5/T$2,0) -> 0 | X5: =IF($E5*X$2/$C$2-AA5>0,$E5*X$2/$C$2-AA5,0) -> 9208.5385 | Y5: =IFERROR(X5/X$2,0) -> 8.1714507 | Z5: =IFERROR(AA5/X$2,0) -> 0 | AB5: =IF($E5*AB$2/$C$2-AE5>0,$E5*AB$2/$C$2-AE5,0) -> 9272.7579 | AC5: =IFERROR(AB5/AB$2,0) -> 8.1714507 | AD5: =IFERROR(AE5/AB$2,0) -> 0 | AF5: =IF($E5*AF$2/$C$2-AI5>0,$E5*AF$2/$C$2-AI5,0) -> 9326.8774 | AG5: =IFERROR(AF5/AF$2,0) -> 8.1714507 | AH5: =IFERROR(AI5/AF$2,0) -> 0 | AJ5: =IF($E5*AJ$2/$C$2-AM5>0,$E5*AJ$2/$C$2-AM5,0) -> 9390.3859 | AK5: =IFERROR(AJ5/AJ$2,0) -> 8.1714507 | AL5: =IFERROR(AM5/AJ$2,0) -> 0 | AN5: =IF($E5*AN$2/$C$2-AQ5>0,$E5*AN$2/$C$2-AQ5,0) -> 9427.6069 | AO5: =IFERROR(AN5/AN$2,0) -> 8.1714507 | AP5: =IFERROR(AQ5/AN$2,0) -> 0 | AR5: =IF($E5*AR$2/$C$2-AU5>0,$E5*AR$2/$C$2-AU5,0) -> 9475.0912 | AS5: =IFERROR(AR5/AR$2,0) -> 8.1714507 | AT5: =IFERROR(AU5/AR$2,0) -> 0 | AV5: =IF($E5*AV$2/$C$2-AY5>0,$E5*AV$2/$C$2-AY5,0) -> 9553.3737 | AW5: =IFERROR(AV5/AV$2,0) -> 8.1714507 | AX5: =IFERROR(AY5/AV$2,0) -> 0 | AZ5: =IF($E5*AZ$2/$C$2-BC5>0,$E5*AZ$2/$C$2-BC5,0) -> 9591.4445 | BA5: =IFERROR(AZ5/AZ$2,0) -> 8.1714507 | BB5: =IFERROR(BC5/AZ$2,0) -> 0 | BD5: =IF($E5*BD$2/$C$2-BG5>0,$E5*BD$2/$C$2-BG5,0) -> 9629.1231 | BE5: =IFERROR(BD5/BD$2,0) -> 8.1714507 | BF5: =IFERROR(BG5/BD$2,0) -> 0 | BH5: =IF($E5*BH$2/$C$2-BK5>0,$E5*BH$2/$C$2-BK5,0) -> 9678.7728 | BI5: =IFERROR(BH5/BH$2,0) -> 8.1714507 | BJ5: =IFERROR(BK5/BH$2,0) -> 0 | BL5: =IF($E5*BL$2/$C$2-BO5>0,$E5*BL$2/$C$2-BO5,0) -> 9734.8698 | BM5: =IFERROR(BL5/BL$2,0) -> 8.1714507 | BN5: =IFERROR(BO5/BL$2,0) -> 0 | BP5: =IF($E5*BP$2/$C$2-BS5>0,$E5*BP$2/$C$2-BS5,0) -> 9801.7286 | BQ5: =IFERROR(BP5/BP$2,0) -> 8.1714507 | BR5: =IFERROR(BS5/BP$2,0) -> 0 | BT5: =IF($E5*BT$2/$C$2-BW5>0,$E5*BT$2/$C$2-BW5,0) -> 9891.304 | BU5: =IFERROR(BT5/BT$2,0) -> 8.1714507 | BV5: =IFERROR(BW5/BT$2,0) -> 0 | BX5: =IF($E5*BX$2/$C$2-CA5>0,$E5*BX$2/$C$2-CA5,0) -> 9942.253 | BY5: =IFERROR(BX5/BX$2,0) -> 8.1714507 | BZ5: =IFERROR(CA5/BX$2,0) -> 0 | CB5: =IF($E5*CB$2/$C$2-CE5>0,$E5*CB$2/$C$2-CE5,0) -> 9958.931 | CC5: =IFERROR(CB5/CB$2,0) -> 8.1714507 | CD5: =IFERROR(CE5/CB$2,0) -> 0 | CF5: =IF($E5*CF$2/$C$2-CI5>0,$E5*CF$2/$C$2-CI5,0) -> 9988.4217 | CG5: =IFERROR(CF5/CF$2,0) -> 8.1714507 | CH5: =IFERROR(CI5/CF$2,0) -> 0 | CJ5: =IF($E5*CJ$2/$C$2-CM5>0,$E5*CJ$2/$C$2-CM5,0) -> 10015.2 | CK5: =IFERROR(CJ5/CJ$2,0) -> 8.1714507 | CL5: =IFERROR(CM5/CJ$2,0) -> 0 | CN5: =IF($E5*CN$2/$C$2-CQ5>0,$E5*CN$2/$C$2-CQ5,0) -> 10035.857 | CO5: =IFERROR(CN5/CN$2,0) -> 8.1714507 | CP5: =IFERROR(CQ5/CN$2,0) -> 0 | CR5: =IF($E5*CR$2/$C$2-CU5>0,$E5*CR$2/$C$2-CU5,0) -> 10108.379 | CS5: =IFERROR(CR5/CR$2,0) -> 8.1714507 | CT5: =IFERROR(CU5/CR$2,0) -> 0 | CV5: =IF($E5*CV$2/$C$2-CY5>0,$E5*CV$2/$C$2-CY5,0) -> 10136.529 | CW5: =IFERROR(CV5/CV$2,0) -> 8.1714507 | CX5: =IFERROR(CY5/CV$2,0) -> 0 | CZ5: =IF($E5*CZ$2/$C$2-DC5>0,$E5*CZ$2/$C$2-DC5,0) -> 10191.278 | DA5: =IFERROR(CZ5/CZ$2,0) -> 8.1714507 | DB5: =IFERROR(DC5/CZ$2,0) -> 0 | DD5: =IF($E5*DD$2/$C$2-DG5>0,$E5*DD$2/$C$2-DG5,0) -> 10293.184 | DE5: =IFERROR(DD5/DD$2,0) -> 8.1714507 | DF5: =IFERROR(DG5/DD$2,0) -> 0
A6: 01.01.04.01.002 | B6: ENGENHEIRO RESIDENTE | C6: 24 | D6: =E6*C6 -> 485693.04 | E6: 20237.21 | F6: =K6*$C$1 -> 2.9118405e-10 | G6: =D6/$C$2 -> 447.9563 | H6: =E6/$C$2 -> 18.664846 | I6: =SUMIFS($P6:$DG6,$P$4:$DG$4,$Q$4) -> 447.9563 | J6: =SUMIFS($P6:$DG6,$P$4:$DG$4,$R$4) -> 0 | K6: =G6-I6-J6 -> 2.2737368e-13 | O6: =M6-SUMIFS(P6:DG6,$P$4:$DG$4,$S$4) -> 0 | P6: =IF($E6*P$2/$C$2-S6>0,$E6*P$2/$C$2-S6,0) -> 20734.535 | Q6: =IFERROR(P6/P$2,0) -> 18.664846 | R6: =IFERROR(S6/P$2,0) -> 0 | T6: =IF($E6*T$2/$C$2-W6>0,$E6*T$2/$C$2-W6,0) -> 20882.734 | U6: =IFERROR(T6/T$2,0) -> 18.664846 | V6: =IFERROR(W6/T$2,0) -> 0 | X6: =IF($E6*X$2/$C$2-AA6>0,$E6*X$2/$C$2-AA6,0) -> 21033.714 | Y6: =IFERROR(X6/X$2,0) -> 18.664846 | Z6: =IFERROR(AA6/X$2,0) -> 0 | AB6: =IF($E6*AB$2/$C$2-AE6>0,$E6*AB$2/$C$2-AE6,0) -> 21180.401 | AC6: =IFERROR(AB6/AB$2,0) -> 18.664846 | AD6: =IFERROR(AE6/AB$2,0) -> 0 | AF6: =IF($E6*AF$2/$C$2-AI6>0,$E6*AF$2/$C$2-AI6,0) -> 21304.018 | AG6: =IFERROR(AF6/AF$2,0) -> 18.664846 | AH6: =IFERROR(AI6/AF$2,0) -> 0 | AJ6: =IF($E6*AJ$2/$C$2-AM6>0,$E6*AJ$2/$C$2-AM6,0) -> 21449.081 | AK6: =IFERROR(AJ6/AJ$2,0) -> 18.664846 | AL6: =IFERROR(AM6/AJ$2,0) -> 0 | AN6: =IF($E6*AN$2/$C$2-AQ6>0,$E6*AN$2/$C$2-AQ6,0) -> 21534.099 | AO6: =IFERROR(AN6/AN$2,0) -> 18.664846 | AP6: =IFERROR(AQ6/AN$2,0) -> 0 | AR6: =IF($E6*AR$2/$C$2-AU6>0,$E6*AR$2/$C$2-AU6,0) -> 21642.561 | AS6: =IFERROR(AR6/AR$2,0) -> 18.664846 | AT6: =IFERROR(AU6/AR$2,0) -> 0 | AV6: =IF($E6*AV$2/$C$2-AY6>0,$E6*AV$2/$C$2-AY6,0) -> 21821.37 | AW6: =IFERROR(AV6/AV$2,0) -> 18.664846 | AX6: =IFERROR(AY6/AV$2,0) -> 0 | AZ6: =IF($E6*AZ$2/$C$2-BC6>0,$E6*AZ$2/$C$2-BC6,0) -> 21908.33 | BA6: =IFERROR(AZ6/AZ$2,0) -> 18.664846 | BB6: =IFERROR(BC6/AZ$2,0) -> 0 | BD6: =IF($E6*BD$2/$C$2-BG6>0,$E6*BD$2/$C$2-BG6,0) -> 21994.393 | BE6: =IFERROR(BD6/BD$2,0) -> 18.664846 | BF6: =IFERROR(BG6/BD$2,0) -> 0 | BH6: =IF($E6*BH$2/$C$2-BK6>0,$E6*BH$2/$C$2-BK6,0) -> 22107.801 | BI6: =IFERROR(BH6/BH$2,0) -> 18.664846 | BJ6: =IFERROR(BK6/BH$2,0) -> 0 | BL6: =IF($E6*BL$2/$C$2-BO6>0,$E6*BL$2/$C$2-BO6,0) -> 22235.935 | BM6: =IFERROR(BL6/BL$2,0) -> 18.664846 | BN6: =IFERROR(BO6/BL$2,0) -> 0 | BP6: =IF($E6*BP$2/$C$2-BS6>0,$E6*BP$2/$C$2-BS6,0) -> 22388.651 | BQ6: =IFERROR(BP6/BP$2,0) -> 18.664846 | BR6: =IFERROR(BS6/BP$2,0) -> 0 | BT6: =IF($E6*BT$2/$C$2-BW6>0,$E6*BT$2/$C$2-BW6,0) -> 22593.255 | BU6: =IFERROR(BT6/BT$2,0) -> 18.664846 | BV6: =IFERROR(BW6/BT$2,0) -> 0 | BX6: =IF($E6*BX$2/$C$2-CA6>0,$E6*BX$2/$C$2-CA6,0) -> 22709.63 | BY6: =IFERROR(BX6/BX$2,0) -> 18.664846 | BZ6: =IFERROR(CA6/BX$2,0) -> 0 | CB6: =IF($E6*CB$2/$C$2-CE6>0,$E6*CB$2/$C$2-CE6,0) -> 22747.725 | CC6: =IFERROR(CB6/CB$2,0) -> 18.664846 | CD6: =IFERROR(CE6/CB$2,0) -> 0 | CF6: =IF($E6*CF$2/$C$2-CI6>0,$E6*CF$2/$C$2-CI6,0) -> 22815.087 | CG6: =IFERROR(CF6/CF$2,0) -> 18.664846 | CH6: =IFERROR(CI6/CF$2,0) -> 0 | CJ6: =IF($E6*CJ$2/$C$2-CM6>0,$E6*CJ$2/$C$2-CM6,0) -> 22876.251 | CK6: =IFERROR(CJ6/CJ$2,0) -> 18.664846 | CL6: =IFERROR(CM6/CJ$2,0) -> 0 | CN6: =IF($E6*CN$2/$C$2-CQ6>0,$E6*CN$2/$C$2-CQ6,0) -> 22923.436 | CO6: =IFERROR(CN6/CN$2,0) -> 18.664846 | CP6: =IFERROR(CQ6/CN$2,0) -> 0 | CR6: =IF($E6*CR$2/$C$2-CU6>0,$E6*CR$2/$C$2-CU6,0) -> 23089.086 | CS6: =IFERROR(CR6/CR$2,0) -> 18.664846 | CT6: =IFERROR(CU6/CR$2,0) -> 0 | CV6: =IF($E6*CV$2/$C$2-CY6>0,$E6*CV$2/$C$2-CY6,0) -> 23153.387 | CW6: =IFERROR(CV6/CV$2,0) -> 18.664846 | CX6: =IFERROR(CY6/CV$2,0) -> 0 | CZ6: =IF($E6*CZ$2/$C$2-DC6>0,$E6*CZ$2/$C$2-DC6,0) -> 23278.441 | DA6: =IFERROR(CZ6/CZ$2,0) -> 18.664846 | DB6: =IFERROR(DC6/CZ$2,0) -> 0 | DD6: =IF($E6*DD$2/$C$2-DG6>0,$E6*DD$2/$C$2-DG6,0) -> 23511.211 | DE6: =IFERROR(DD6/DD$2,0) -> 18.664846 | DF6: =IFERROR(DG6/DD$2,0) -> 0
A7: 01.01.04.01.003 | B7: ESTAGIÁRIO | C7: 24 | D7: =E7*C7 -> 67101.84 | E7: 2795.91 | F7: =K7*$C$1 -> -9.0995016e-12 | G7: =D7/$C$2 -> 61.88825 | H7: =E7/$C$2 -> 2.5786771 | I7: =SUMIFS($P7:$DG7,$P$4:$DG$4,$Q$4) -> 61.88825 | J7: =SUMIFS($P7:$DG7,$P$4:$DG$4,$R$4) -> 0 | K7: =G7-I7-J7 -> -7.1054274e-15 | O7: =M7-SUMIFS(P7:DG7,$P$4:$DG$4,$S$4) -> 0 | P7: =IF($E7*P$2/$C$2-S7>0,$E7*P$2/$C$2-S7,0) -> 2864.6189 | Q7: =IFERROR(P7/P$2,0) -> 2.5786771 | R7: =IFERROR(S7/P$2,0) -> 0 | T7: =IF($E7*T$2/$C$2-W7>0,$E7*T$2/$C$2-W7,0) -> 2885.0935 | U7: =IFERROR(T7/T$2,0) -> 2.5786771 | V7: =IFERROR(W7/T$2,0) -> 0 | X7: =IF($E7*X$2/$C$2-AA7>0,$E7*X$2/$C$2-AA7,0) -> 2905.9525 | Y7: =IFERROR(X7/X$2,0) -> 2.5786771 | Z7: =IFERROR(AA7/X$2,0) -> 0 | AB7: =IF($E7*AB$2/$C$2-AE7>0,$E7*AB$2/$C$2-AE7,0) -> 2926.2183 | AC7: =IFERROR(AB7/AB$2,0) -> 2.5786771 | AD7: =IFERROR(AE7/AB$2,0) -> 0 | AF7: =IF($E7*AF$2/$C$2-AI7>0,$E7*AF$2/$C$2-AI7,0) -> 2943.2969 | AG7: =IFERROR(AF7/AF$2,0) -> 2.5786771 | AH7: =IFERROR(AI7/AF$2,0) -> 0 | AJ7: =IF($E7*AJ$2/$C$2-AM7>0,$E7*AJ$2/$C$2-AM7,0) -> 2963.3383 | AK7: =IFERROR(AJ7/AJ$2,0) -> 2.5786771 | AL7: =IFERROR(AM7/AJ$2,0) -> 0 | AN7: =IF($E7*AN$2/$C$2-AQ7>0,$E7*AN$2/$C$2-AQ7,0) -> 2975.0842 | AO7: =IFERROR(AN7/AN$2,0) -> 2.5786771 | AP7: =IFERROR(AQ7/AN$2,0) -> 0 | AR7: =IF($E7*AR$2/$C$2-AU7>0,$E7*AR$2/$C$2-AU7,0) -> 2990.0689 | AS7: =IFERROR(AR7/AR$2,0) -> 2.5786771 | AT7: =IFERROR(AU7/AR$2,0) -> 0 | AV7: =IF($E7*AV$2/$C$2-AY7>0,$E7*AV$2/$C$2-AY7,0) -> 3014.7726 | AW7: =IFERROR(AV7/AV$2,0) -> 2.5786771 | AX7: =IFERROR(AY7/AV$2,0) -> 0 | AZ7: =IF($E7*AZ$2/$C$2-BC7>0,$E7*AZ$2/$C$2-BC7,0) -> 3026.7867 | BA7: =IFERROR(AZ7/AZ$2,0) -> 2.5786771 | BB7: =IFERROR(BC7/AZ$2,0) -> 0 | BD7: =IF($E7*BD$2/$C$2-BG7>0,$E7*BD$2/$C$2-BG7,0) -> 3038.677 | BE7: =IFERROR(BD7/BD$2,0) -> 2.5786771 | BF7: =IFERROR(BG7/BD$2,0) -> 0 | BH7: =IF($E7*BH$2/$C$2-BK7>0,$E7*BH$2/$C$2-BK7,0) -> 3054.345 | BI7: =IFERROR(BH7/BH$2,0) -> 2.5786771 | BJ7: =IFERROR(BK7/BH$2,0) -> 0 | BL7: =IF($E7*BL$2/$C$2-BO7>0,$E7*BL$2/$C$2-BO7,0) -> 3072.0476 | BM7: =IFERROR(BL7/BL$2,0) -> 2.5786771 | BN7: =IFERROR(BO7/BL$2,0) -> 0 | BP7: =IF($E7*BP$2/$C$2-BS7>0,$E7*BP$2/$C$2-BS7,0) -> 3093.1464 | BQ7: =IFERROR(BP7/BP$2,0) -> 2.5786771 | BR7: =IFERROR(BS7/BP$2,0) -> 0 | BT7: =IF($E7*BT$2/$C$2-BW7>0,$E7*BT$2/$C$2-BW7,0) -> 3121.4138 | BU7: =IFERROR(BT7/BT$2,0) -> 2.5786771 | BV7: =IFERROR(BW7/BT$2,0) -> 0 | BX7: =IF($E7*BX$2/$C$2-CA7>0,$E7*BX$2/$C$2-CA7,0) -> 3137.4919 | BY7: =IFERROR(BX7/BX$2,0) -> 2.5786771 | BZ7: =IFERROR(CA7/BX$2,0) -> 0 | CB7: =IF($E7*CB$2/$C$2-CE7>0,$E7*CB$2/$C$2-CE7,0) -> 3142.755 | CC7: =IFERROR(CB7/CB$2,0) -> 2.5786771 | CD7: =IFERROR(CE7/CB$2,0) -> 0 | CF7: =IF($E7*CF$2/$C$2-CI7>0,$E7*CF$2/$C$2-CI7,0) -> 3152.0614 | CG7: =IFERROR(CF7/CF$2,0) -> 2.5786771 | CH7: =IFERROR(CI7/CF$2,0) -> 0 | CJ7: =IF($E7*CJ$2/$C$2-CM7>0,$E7*CJ$2/$C$2-CM7,0) -> 3160.5117 | CK7: =IFERROR(CJ7/CJ$2,0) -> 2.5786771 | CL7: =IFERROR(CM7/CJ$2,0) -> 0 | CN7: =IF($E7*CN$2/$C$2-CQ7>0,$E7*CN$2/$C$2-CQ7,0) -> 3167.0306 | CO7: =IFERROR(CN7/CN$2,0) -> 2.5786771 | CP7: =IFERROR(CQ7/CN$2,0) -> 0 | CR7: =IF($E7*CR$2/$C$2-CU7>0,$E7*CR$2/$C$2-CU7,0) -> 3189.9164 | CS7: =IFERROR(CR7/CR$2,0) -> 2.5786771 | CT7: =IFERROR(CU7/CR$2,0) -> 0 | CV7: =IF($E7*CV$2/$C$2-CY7>0,$E7*CV$2/$C$2-CY7,0) -> 3198.7999 | CW7: =IFERROR(CV7/CV$2,0) -> 2.5786771 | CX7: =IFERROR(CY7/CV$2,0) -> 0 | CZ7: =IF($E7*CZ$2/$C$2-DC7>0,$E7*CZ$2/$C$2-DC7,0) -> 3216.0771 | DA7: =IFERROR(CZ7/CZ$2,0) -> 2.5786771 | DB7: =IFERROR(DC7/CZ$2,0) -> 0 | DD7: =IF($E7*DD$2/$C$2-DG7>0,$E7*DD$2/$C$2-DG7,0) -> 3248.2357 | DE7: =IFERROR(DD7/DD$2,0) -> 2.5786771 | DF7: =IFERROR(DG7/DD$2,0) -> 0
A8: 01.01.04.01.004 | B8: MESTRE DE OBRAS | C8: 24 | D8: =E8*C8 -> 444000 | E8: 18500 | F8: =K8*$C$1 -> -1.4559203e-10 | G8: =D8/$C$2 -> 409.50268 | H8: =E8/$C$2 -> 17.062611 | I8: =SUMIFS($P8:$DG8,$P$4:$DG$4,$Q$4) -> 409.50268 | J8: =SUMIFS($P8:$DG8,$P$4:$DG$4,$R$4) -> 0 | K8: =G8-I8-J8 -> -1.1368684e-13 | O8: =M8-SUMIFS(P8:DG8,$P$4:$DG$4,$S$4) -> 0 | P8: =IF($E8*P$2/$C$2-S8>0,$E8*P$2/$C$2-S8,0) -> 18954.633 | Q8: =IFERROR(P8/P$2,0) -> 17.062611 | R8: =IFERROR(S8/P$2,0) -> 0 | T8: =IF($E8*T$2/$C$2-W8>0,$E8*T$2/$C$2-W8,0) -> 19090.11 | U8: =IFERROR(T8/T$2,0) -> 17.062611 | V8: =IFERROR(W8/T$2,0) -> 0 | X8: =IF($E8*X$2/$C$2-AA8>0,$E8*X$2/$C$2-AA8,0) -> 19228.13 | Y8: =IFERROR(X8/X$2,0) -> 17.062611 | Z8: =IFERROR(AA8/X$2,0) -> 0 | AB8: =IF($E8*AB$2/$C$2-AE8>0,$E8*AB$2/$C$2-AE8,0) -> 19362.225 | AC8: =IFERROR(AB8/AB$2,0) -> 17.062611 | AD8: =IFERROR(AE8/AB$2,0) -> 0 | AF8: =IF($E8*AF$2/$C$2-AI8>0,$E8*AF$2/$C$2-AI8,0) -> 19475.231 | AG8: =IFERROR(AF8/AF$2,0) -> 17.062611 | AH8: =IFERROR(AI8/AF$2,0) -> 0 | AJ8: =IF($E8*AJ$2/$C$2-AM8>0,$E8*AJ$2/$C$2-AM8,0) -> 19607.841 | AK8: =IFERROR(AJ8/AJ$2,0) -> 17.062611 | AL8: =IFERROR(AM8/AJ$2,0) -> 0 | AN8: =IF($E8*AN$2/$C$2-AQ8>0,$E8*AN$2/$C$2-AQ8,0) -> 19685.561 | AO8: =IFERROR(AN8/AN$2,0) -> 17.062611 | AP8: =IFERROR(AQ8/AN$2,0) -> 0 | AR8: =IF($E8*AR$2/$C$2-AU8>0,$E8*AR$2/$C$2-AU8,0) -> 19784.712 | AS8: =IFERROR(AR8/AR$2,0) -> 17.062611 | AT8: =IFERROR(AU8/AR$2,0) -> 0 | AV8: =IF($E8*AV$2/$C$2-AY8>0,$E8*AV$2/$C$2-AY8,0) -> 19948.172 | AW8: =IFERROR(AV8/AV$2,0) -> 17.062611 | AX8: =IFERROR(AY8/AV$2,0) -> 0 | AZ8: =IF($E8*AZ$2/$C$2-BC8>0,$E8*AZ$2/$C$2-BC8,0) -> 20027.667 | BA8: =IFERROR(AZ8/AZ$2,0) -> 17.062611 | BB8: =IFERROR(BC8/AZ$2,0) -> 0 | BD8: =IF($E8*BD$2/$C$2-BG8>0,$E8*BD$2/$C$2-BG8,0) -> 20106.342 | BE8: =IFERROR(BD8/BD$2,0) -> 17.062611 | BF8: =IFERROR(BG8/BD$2,0) -> 0 | BH8: =IF($E8*BH$2/$C$2-BK8>0,$E8*BH$2/$C$2-BK8,0) -> 20210.015 | BI8: =IFERROR(BH8/BH$2,0) -> 17.062611 | BJ8: =IFERROR(BK8/BH$2,0) -> 0 | BL8: =IF($E8*BL$2/$C$2-BO8>0,$E8*BL$2/$C$2-BO8,0) -> 20327.15 | BM8: =IFERROR(BL8/BL$2,0) -> 17.062611 | BN8: =IFERROR(BO8/BL$2,0) -> 0 | BP8: =IF($E8*BP$2/$C$2-BS8>0,$E8*BP$2/$C$2-BS8,0) -> 20466.756 | BQ8: =IFERROR(BP8/BP$2,0) -> 17.062611 | BR8: =IFERROR(BS8/BP$2,0) -> 0 | BT8: =IF($E8*BT$2/$C$2-BW8>0,$E8*BT$2/$C$2-BW8,0) -> 20653.796 | BU8: =IFERROR(BT8/BT$2,0) -> 17.062611 | BV8: =IFERROR(BW8/BT$2,0) -> 0 | BX8: =IF($E8*BX$2/$C$2-CA8>0,$E8*BX$2/$C$2-CA8,0) -> 20760.182 | BY8: =IFERROR(BX8/BX$2,0) -> 17.062611 | BZ8: =IFERROR(CA8/BX$2,0) -> 0 | CB8: =IF($E8*CB$2/$C$2-CE8>0,$E8*CB$2/$C$2-CE8,0) -> 20795.007 | CC8: =IFERROR(CB8/CB$2,0) -> 17.062611 | CD8: =IFERROR(CE8/CB$2,0) -> 0 | CF8: =IF($E8*CF$2/$C$2-CI8>0,$E8*CF$2/$C$2-CI8,0) -> 20856.586 | CG8: =IFERROR(CF8/CF$2,0) -> 17.062611 | CH8: =IFERROR(CI8/CF$2,0) -> 0 | CJ8: =IF($E8*CJ$2/$C$2-CM8>0,$E8*CJ$2/$C$2-CM8,0) -> 20912.5 | CK8: =IFERROR(CJ8/CJ$2,0) -> 17.062611 | CL8: =IFERROR(CM8/CJ$2,0) -> 0 | CN8: =IF($E8*CN$2/$C$2-CQ8>0,$E8*CN$2/$C$2-CQ8,0) -> 20955.634 | CO8: =IFERROR(CN8/CN$2,0) -> 17.062611 | CP8: =IFERROR(CQ8/CN$2,0) -> 0 | CR8: =IF($E8*CR$2/$C$2-CU8>0,$E8*CR$2/$C$2-CU8,0) -> 21107.065 | CS8: =IFERROR(CR8/CR$2,0) -> 17.062611 | CT8: =IFERROR(CU8/CR$2,0) -> 0 | CV8: =IF($E8*CV$2/$C$2-CY8>0,$E8*CV$2/$C$2-CY8,0) -> 21165.845 | CW8: =IFERROR(CV8/CV$2,0) -> 17.062611 | CX8: =IFERROR(CY8/CV$2,0) -> 0 | CZ8: =IF($E8*CZ$2/$C$2-DC8>0,$E8*CZ$2/$C$2-DC8,0) -> 21280.165 | DA8: =IFERROR(CZ8/CZ$2,0) -> 17.062611 | DB8: =IFERROR(DC8/CZ$2,0) -> 0 | DD8: =IF($E8*DD$2/$C$2-DG8>0,$E8*DD$2/$C$2-DG8,0) -> 21492.953 | DE8: =IFERROR(DD8/DD$2,0) -> 17.062611 | DF8: =IFERROR(DG8/DD$2,0) -> 0
A9: 01.01.04.01.006 | B9: ANALISTA DE ENGENHARIA | C9: 24 | D9: =E9*C9 -> 195572.64 | E9: 8148.86 | F9: =K9*$C$1 -> 1.0919402e-10 | G9: =D9/$C$2 -> 180.3773 | H9: =E9/$C$2 -> 7.5157207 | I9: =SUMIFS($P9:$DG9,$P$4:$DG$4,$Q$4) -> 180.3773 | J9: =SUMIFS($P9:$DG9,$P$4:$DG$4,$R$4) -> 0 | K9: =G9-I9-J9 -> 8.5265128e-14 | O9: =M9-SUMIFS(P9:DG9,$P$4:$DG$4,$S$4) -> 0 | P9: =IF($E9*P$2/$C$2-S9>0,$E9*P$2/$C$2-S9,0) -> 8349.1164 | Q9: =IFERROR(P9/P$2,0) -> 7.5157207 | R9: =IFERROR(S9/P$2,0) -> 0 | T9: =IF($E9*T$2/$C$2-W9>0,$E9*T$2/$C$2-W9,0) -> 8408.7912 | U9: =IFERROR(T9/T$2,0) -> 7.5157207 | V9: =IFERROR(W9/T$2,0) -> 0 | X9: =IF($E9*X$2/$C$2-AA9>0,$E9*X$2/$C$2-AA9,0) -> 8469.5859 | Y9: =IFERROR(X9/X$2,0) -> 7.5157207 | Z9: =IFERROR(AA9/X$2,0) -> 0 | AB9: =IF($E9*AB$2/$C$2-AE9>0,$E9*AB$2/$C$2-AE9,0) -> 8528.6519 | AC9: =IFERROR(AB9/AB$2,0) -> 7.5157207 | AD9: =IFERROR(AE9/AB$2,0) -> 0 | AF9: =IF($E9*AF$2/$C$2-AI9>0,$E9*AF$2/$C$2-AI9,0) -> 8578.4285 | AG9: =IFERROR(AF9/AF$2,0) -> 7.5157207 | AH9: =IFERROR(AI9/AF$2,0) -> 0 | AJ9: =IF($E9*AJ$2/$C$2-AM9>0,$E9*AJ$2/$C$2-AM9,0) -> 8636.8407 | AK9: =IFERROR(AJ9/AJ$2,0) -> 7.5157207 | AL9: =IFERROR(AM9/AJ$2,0) -> 0 | AN9: =IF($E9*AN$2/$C$2-AQ9>0,$E9*AN$2/$C$2-AQ9,0) -> 8671.0748 | AO9: =IFERROR(AN9/AN$2,0) -> 7.5157207 | AP9: =IFERROR(AQ9/AN$2,0) -> 0 | AR9: =IF($E9*AR$2/$C$2-AU9>0,$E9*AR$2/$C$2-AU9,0) -> 8714.7487 | AS9: =IFERROR(AR9/AR$2,0) -> 7.5157207 | AT9: =IFERROR(AU9/AR$2,0) -> 0 | AV9: =IF($E9*AV$2/$C$2-AY9>0,$E9*AV$2/$C$2-AY9,0) -> 8786.7493 | AW9: =IFERROR(AV9/AV$2,0) -> 7.5157207 | AX9: =IFERROR(AY9/AV$2,0) -> 0 | AZ9: =IF($E9*AZ$2/$C$2-BC9>0,$E9*AZ$2/$C$2-BC9,0) -> 8821.765 | BA9: =IFERROR(AZ9/AZ$2,0) -> 7.5157207 | BB9: =IFERROR(BC9/AZ$2,0) -> 0 | BD9: =IF($E9*BD$2/$C$2-BG9>0,$E9*BD$2/$C$2-BG9,0) -> 8856.42 | BE9: =IFERROR(BD9/BD$2,0) -> 7.5157207 | BF9: =IFERROR(BG9/BD$2,0) -> 0 | BH9: =IF($E9*BH$2/$C$2-BK9>0,$E9*BH$2/$C$2-BK9,0) -> 8902.0855 | BI9: =IFERROR(BH9/BH$2,0) -> 7.5157207 | BJ9: =IFERROR(BK9/BH$2,0) -> 0 | BL9: =IF($E9*BL$2/$C$2-BO9>0,$E9*BL$2/$C$2-BO9,0) -> 8953.6809 | BM9: =IFERROR(BL9/BL$2,0) -> 7.5157207 | BN9: =IFERROR(BO9/BL$2,0) -> 0 | BP9: =IF($E9*BP$2/$C$2-BS9>0,$E9*BP$2/$C$2-BS9,0) -> 9015.1746 | BQ9: =IFERROR(BP9/BP$2,0) -> 7.5157207 | BR9: =IFERROR(BS9/BP$2,0) -> 0 | BT9: =IF($E9*BT$2/$C$2-BW9>0,$E9*BT$2/$C$2-BW9,0) -> 9097.5619 | BU9: =IFERROR(BT9/BT$2,0) -> 7.5157207 | BV9: =IFERROR(BW9/BT$2,0) -> 0 | BX9: =IF($E9*BX$2/$C$2-CA9>0,$E9*BX$2/$C$2-CA9,0) -> 9144.4224 | BY9: =IFERROR(BX9/BX$2,0) -> 7.5157207 | BZ9: =IFERROR(CA9/BX$2,0) -> 0 | CB9: =IF($E9*CB$2/$C$2-CE9>0,$E9*CB$2/$C$2-CE9,0) -> 9159.762 | CC9: =IFERROR(CB9/CB$2,0) -> 7.5157207 | CD9: =IFERROR(CE9/CB$2,0) -> 0 | CF9: =IF($E9*CF$2/$C$2-CI9>0,$E9*CF$2/$C$2-CI9,0) -> 9186.8862 | CG9: =IFERROR(CF9/CF$2,0) -> 7.5157207 | CH9: =IFERROR(CI9/CF$2,0) -> 0 | CJ9: =IF($E9*CJ$2/$C$2-CM9>0,$E9*CJ$2/$C$2-CM9,0) -> 9211.5153 | CK9: =IFERROR(CJ9/CJ$2,0) -> 7.5157207 | CL9: =IFERROR(CM9/CJ$2,0) -> 0 | CN9: =IF($E9*CN$2/$C$2-CQ9>0,$E9*CN$2/$C$2-CQ9,0) -> 9230.515 | CO9: =IFERROR(CN9/CN$2,0) -> 7.5157207 | CP9: =IFERROR(CQ9/CN$2,0) -> 0 | CR9: =IF($E9*CR$2/$C$2-CU9>0,$E9*CR$2/$C$2-CU9,0) -> 9297.217 | CS9: =IFERROR(CR9/CR$2,0) -> 7.5157207 | CT9: =IFERROR(CU9/CR$2,0) -> 0 | CV9: =IF($E9*CV$2/$C$2-CY9>0,$E9*CV$2/$C$2-CY9,0) -> 9323.1087 | CW9: =IFERROR(CV9/CV$2,0) -> 7.5157207 | CX9: =IFERROR(CY9/CV$2,0) -> 0 | CZ9: =IF($E9*CZ$2/$C$2-DC9>0,$E9*CZ$2/$C$2-DC9,0) -> 9373.464 | DA9: =IFERROR(CZ9/CZ$2,0) -> 7.5157207 | DB9: =IFERROR(DC9/CZ$2,0) -> 0 | DD9: =IF($E9*DD$2/$C$2-DG9>0,$E9*DD$2/$C$2-DG9,0) -> 9467.1926 | DE9: =IFERROR(DD9/DD$2,0) -> 7.5157207 | DF9: =IFERROR(DG9/DD$2,0) -> 0
A10: 01.01.04.01.009 | B10: AUXILIAR DE ALMOXARIFE | C10: 24 | D10: =E10*C10 -> 151200 | E10: 6300 | F10: =K10*$C$1 -> -917.24001 | G10: =D10/$C$2 -> 139.45226 | H10: =E10/$C$2 -> 5.8105109 | I10: =SUMIFS($P10:$DG10,$P$4:$DG$4,$Q$4) -> 122.02073 | J10: =SUMIFS($P10:$DG10,$P$4:$DG$4,$R$4) -> 18.147768 | K10: =G10-I10-J10 -> -0.71623508 | L10: 4 | M10: =N10*L10 -> 27780 | N10: 6945 | O10: =M10-SUMIFS(P10:DG10,$P$4:$DG$4,$S$4) -> 6945 | P10: =IF($E10*P$2/$C$2-S10>0,$E10*P$2/$C$2-S10,0) -> 6454.8211 | Q10: =IFERROR(P10/P$2,0) -> 5.8105109 | R10: =IFERROR(S10/P$2,0) -> 0 | T10: =IF($E10*T$2/$C$2-W10>0,$E10*T$2/$C$2-W10,0) -> 6500.9565 | U10: =IFERROR(T10/T$2,0) -> 5.8105109 | V10: =IFERROR(W10/T$2,0) -> 0 | X10: =IF($E10*X$2/$C$2-AA10>0,$E10*X$2/$C$2-AA10,0) -> 6547.9577 | Y10: =IFERROR(X10/X$2,0) -> 5.8105109 | Z10: =IFERROR(AA10/X$2,0) -> 0 | AB10: =IF($E10*AB$2/$C$2-AE10>0,$E10*AB$2/$C$2-AE10,0) -> 6593.6225 | AC10: =IFERROR(AB10/AB$2,0) -> 5.8105109 | AD10: =IFERROR(AE10/AB$2,0) -> 0 | AF10: =IF($E10*AF$2/$C$2-AI10>0,$E10*AF$2/$C$2-AI10,0) -> 0 | AG10: =IFERROR(AF10/AF$2,0) -> 0 | AH10: =IFERROR(AI10/AF$2,0) -> 6.0846436 | AI10: 6945 | AJ10: =IF($E10*AJ$2/$C$2-AM10>0,$E10*AJ$2/$C$2-AM10,0) -> 0 | AK10: =IFERROR(AJ10/AJ$2,0) -> 0 | AL10: =IFERROR(AM10/AJ$2,0) -> 6.0434923 | AM10: 6945 | AN10: =IF($E10*AN$2/$C$2-AQ10>0,$E10*AN$2/$C$2-AQ10,0) -> 0 | AO10: =IFERROR(AN10/AN$2,0) -> 0 | AP10: =IFERROR(AQ10/AN$2,0) -> 6.0196321 | AQ10: 6945 | AS10: =IFERROR(AR10/AR$2,0) -> 0 | AT10: =IFERROR(AU10/AR$2,0) -> 0 | AV10: =IF($E10*AV$2/$C$2-AY10>0,$E10*AV$2/$C$2-AY10,0)*2 -> 13586.323 | AW10: =IFERROR(AV10/AV$2,0) -> 11.621022 | AX10: =IFERROR(AY10/AV$2,0) -> 0 | AZ10: =IF($E10*AZ$2/$C$2-BC10>0,$E10*AZ$2/$C$2-BC10,0) -> 6820.2325 | BA10: =IFERROR(AZ10/AZ$2,0) -> 5.8105109 | BB10: =IFERROR(BC10/AZ$2,0) -> 0 | BD10: =IF($E10*BD$2/$C$2-BG10>0,$E10*BD$2/$C$2-BG10,0) -> 6847.0247 | BE10: =IFERROR(BD10/BD$2,0) -> 5.8105109 | BF10: =IFERROR(BG10/BD$2,0) -> 0 | BH10: =IF($E10*BH$2/$C$2-BK10>0,$E10*BH$2/$C$2-BK10,0) -> 6882.3294 | BI10: =IFERROR(BH10/BH$2,0) -> 5.8105109 | BJ10: =IFERROR(BK10/BH$2,0) -> 0 | BL10: =IF($E10*BL$2/$C$2-BO10>0,$E10*BL$2/$C$2-BO10,0) -> 6922.2186 | BM10: =IFERROR(BL10/BL$2,0) -> 5.8105109 | BN10: =IFERROR(BO10/BL$2,0) -> 0 | BP10: =IF($E10*BP$2/$C$2-BS10>0,$E10*BP$2/$C$2-BS10,0) -> 6969.7602 | BQ10: =IFERROR(BP10/BP$2,0) -> 5.8105109 | BR10: =IFERROR(BS10/BP$2,0) -> 0 | BT10: =IF($E10*BT$2/$C$2-BW10>0,$E10*BT$2/$C$2-BW10,0) -> 7033.455 | BU10: =IFERROR(BT10/BT$2,0) -> 5.8105109 | BV10: =IFERROR(BW10/BT$2,0) -> 0 | BX10: =IF($E10*BX$2/$C$2-CA10>0,$E10*BX$2/$C$2-CA10,0) -> 7069.6835 | BY10: =IFERROR(BX10/BX$2,0) -> 5.8105109 | BZ10: =IFERROR(CA10/BX$2,0) -> 0 | CB10: =IF($E10*CB$2/$C$2-CE10>0,$E10*CB$2/$C$2-CE10,0) -> 7081.5428 | CC10: =IFERROR(CB10/CB$2,0) -> 5.8105109 | CD10: =IFERROR(CE10/CB$2,0) -> 0 | CF10: =IF($E10*CF$2/$C$2-CI10>0,$E10*CF$2/$C$2-CI10,0) -> 7102.5129 | CG10: =IFERROR(CF10/CF$2,0) -> 5.8105109 | CH10: =IFERROR(CI10/CF$2,0) -> 0 | CJ10: =IF($E10*CJ$2/$C$2-CM10>0,$E10*CJ$2/$C$2-CM10,0) -> 7121.554 | CK10: =IFERROR(CJ10/CJ$2,0) -> 5.8105109 | CL10: =IFERROR(CM10/CJ$2,0) -> 0 | CN10: =IF($E10*CN$2/$C$2-CQ10>0,$E10*CN$2/$C$2-CQ10,0) -> 7136.2429 | CO10: =IFERROR(CN10/CN$2,0) -> 5.8105109 | CP10: =IFERROR(CQ10/CN$2,0) -> 0 | CR10: =IF($E10*CR$2/$C$2-CU10>0,$E10*CR$2/$C$2-CU10,0) -> 7187.8112 | CS10: =IFERROR(CR10/CR$2,0) -> 5.8105109 | CT10: =IFERROR(CU10/CR$2,0) -> 0 | CV10: =IF($E10*CV$2/$C$2-CY10>0,$E10*CV$2/$C$2-CY10,0) -> 7207.8284 | CW10: =IFERROR(CV10/CV$2,0) -> 5.8105109 | CX10: =IFERROR(CY10/CV$2,0) -> 0 | CZ10: =IF($E10*CZ$2/$C$2-DC10>0,$E10*CZ$2/$C$2-DC10,0) -> 7246.7588 | DA10: =IFERROR(CZ10/CZ$2,0) -> 5.8105109 | DB10: =IFERROR(DC10/CZ$2,0) -> 0 | DD10: =IF($E10*DD$2/$C$2-DG10>0,$E10*DD$2/$C$2-DG10,0) -> 7319.2217 | DE10: =IFERROR(DD10/DD$2,0) -> 5.8105109 | DF10: =IFERROR(DG10/DD$2,0) -> 0
